Workbook

Sheet Дашборд
A1: ФИНАНСОВЫЙ ДАШБОРД 2025
A2: =TODAY() -> 46132
A5: КЛЮЧЕВЫЕ ПОКАЗАТЕЛИ
A7: Показатель | C7: Значение
A8: Годовая выручка (продажи) | C8: ='PL общ'!O14 -> 3706205 | E8: Выручка от реализации товаров
A9: Чистая прибыль | C9: ='PL общ'!O57 -> 841870.75 | E9: Прибыль после налогов
A10: Маржинальность | C10: ='PL общ'!O59 -> 0.2271517 | E10: Отношение прибыли к выручке
A11: Валовая прибыль | C11: ='PL общ'!O36 -> 1761272.4 | E11: Прибыль до расходов
A12: Рентабельность | C12: ='PL общ'!O58 -> 1.1451253 | E12: ROI вложений
A14: СРАВНЕНИЕ ПЛАТФОРМ
A16: Метрика | C16: Wildberries | F16: OZON
A17: Продажи (шт) | C17: ='PL WB'!O7 -> 4476 | D17: =C17/(C17+F17) -> 0.76748971 | F17: ='PL OZON'!O7 -> 1356 | G17: =100%-D17 -> 0.23251029
A18: Выручка (руб) | C18: ='PL WB'!O14 -> 2810873 | D18: =C18/(C18+F18) -> 0.75842351 | F18: ='PL OZON'!O14 -> 895332 | G18: =100%-D18 -> 0.24157649
A19: Чистая прибыль | C19: ='PL WB'!O57 -> 779514.99 | D19: =C19/(C19+F19) -> 0.92593191 | F19: ='PL OZON'!O57 -> 62355.76 | G19: =100%-D19 -> 0.074068092
A20: Средний чек | C20: =C18/C17 -> 627.98771 | F20: =F18/F17 -> 660.27434
A21: Маржа (%) | C21: ='PL WB'!O59 -> 0.27732131 | F21: ='PL OZON'!O59 -> 0.069645405
A23: СТРУКТУРА РАСХОДОВ
A25: Статья расходов | C25: Сумма (руб) | E25: Доля (%)
A26: Комиссии площадок | C26: ='PL общ'!O17 -> 1209754.8 | E26: =C26/'PL общ'!O14 -> 0.32641335
A27: Логистика | C27: ='PL общ'!O40 -> 519605 | E27: =C27/'PL общ'!O14 -> 0.14019867
A28: Продвижение | C28: ='PL общ'!O41 -> 23354 | E28: =C28/'PL общ'!O14 -> 0.0063013244
A29: Себестоимость | C29: ='PL общ'!O33 -> 735177.83 | E29: =C29/'PL общ'!O14 -> 0.19836405
A30: Хранение | C30: ='PL общ'!O43 -> 158529.89 | E30: =C30/'PL общ'!O14 -> 0.042774183
A31: Прочие расходы | C31: ='PL общ'!O38-'PL общ'!O40-'PL общ'!O41-'PL общ'!O43 -> 22959.81 | E31: =C31/'PL общ'!O14 -> 0.0061949649
A32: ИТОГО расходов | C32: ='PL общ'!O38+'PL общ'!O17+'PL общ'!O33 -> 2669381.3 | E32: =C32/'PL общ'!O14 -> 0.72024654
A34: ПОМЕСЯЧНАЯ ДИНАМИКА
A36: Месяц | B36: Янв | C36: Фев | D36: Мар | E36: Апр | F36: Май | G36: Июн | H36: Июл | I36: Авг | J36: Сен | K36: Окт | L36: Ноя | M36: Дек
A37: Выручка | B37: ='PL общ'!C15 -> 950524 | C37: ='PL общ'!D15 -> 834437 | D37: ='PL общ'!E15 -> 692756 | E37: ='PL общ'!F15 -> 313306 | F37: ='PL общ'!G15 -> 0 | G37: ='PL общ'!H15 -> 0 | H37: ='PL общ'!I15 -> 0 | I37: ='PL общ'!J15 -> 0 | ... M37: ='PL общ'!N15 -> 0
A38: Прибыль | B38: ='PL общ'!C57 -> 243054.14 | C38: ='PL общ'!D57 -> 288121.19 | D38: ='PL общ'!E57 -> 211258.46 | E38: ='PL общ'!F57 -> 99436.96 | F38: ='PL общ'!G57 -> 0 | G38: ='PL общ'!H57 -> 0 | H38: ='PL общ'!I57 -> 0 | I38: ='PL общ'!J57 -> 0 | ... M38: ='PL общ'!N57 -> 0

Sheet PL общ
A1: Заполняем PL и CF еженедельный!
A2: Прибыли и убытки | C2: 2025
C3: Январь | D3: Февраль | E3: Март | F3: Апрель | G3: Май | H3: Июнь | I3: Июль | J3: Август | K3: Сентябрь | L3: Октябрь | M3: Ноябрь | N3: Декабрь
A4: Товарооборот
A5: Остаток товара по цене закупки | C5: ='PL WB'!C5+'PL OZON'!C5 -> 1570857.7 | D5: ='PL WB'!D5+'PL OZON'!D5 -> 1522905.6 | E5: ='PL WB'!E5+'PL OZON'!E5 -> 1301418.9 | F5: ='PL WB'!F5+'PL OZON'!F5 -> 1109069.5 | G5: ='PL WB'!G5+'PL OZON'!G5 -> 1028078.6 | H5: ='PL WB'!H5+'PL OZON'!H5 -> 1028078.6 | I5: ='PL WB'!I5+'PL OZON'!I5 -> 1028078.6 | J5: ='PL WB'!J5+'PL OZON'!J5 -> 1028078.6 | ... N5: ='PL WB'!N5+'PL OZON'!N5 -> 1028078.6
B7: Продажи шт | C7: ='PL WB'!C7+'PL OZON'!C7 -> 1965 | D7: ='PL WB'!D7+'PL OZON'!D7 -> 1719 | E7: ='PL WB'!E7+'PL OZON'!E7 -> 1545 | F7: ='PL WB'!F7+'PL OZON'!F7 -> 603 | G7: ='PL WB'!G7+'PL OZON'!G7 -> 0 | H7: ='PL WB'!H7+'PL OZON'!H7 -> 0 | I7: ='PL WB'!I7+'PL OZON'!I7 -> 0 | J7: ='PL WB'!J7+'PL OZON'!J7 -> 0 | ... N7: ='PL WB'!N7+'PL OZON'!N7 -> 0 | O7: =SUM(C7:N7) -> 5832
B8: Отгрузки по себестоимости | C8: =C33 -> 240350.81 | D8: =D33 -> 221486.72 | E8: =E33 -> 192349.4 | F8: =F33 -> 80990.9 | G8: =G33 -> 0 | H8: =H33 -> 0 | I8: =I33 -> 0 | J8: =J33 -> 0 | ... N8: =N33 -> 0 | O8: =SUM(C8:N8) -> 735177.83
A10: Поступление товара, р | C10: ='PL WB'!C10+'PL OZON'!C10 -> 192398.77 | D10: ='PL WB'!D10+'PL OZON'!D10 -> 0 | E10: ='PL WB'!E10+'PL OZON'!E10 -> 0 | F10: ='PL WB'!F10+'PL OZON'!F10 -> 0 | G10: ='PL WB'!G10+'PL OZON'!G10 -> 0 | H10: ='PL WB'!H10+'PL OZON'!H10 -> 0 | I10: ='PL WB'!I10+'PL OZON'!I10 -> 0 | J10: ='PL WB'!J10+'PL OZON'!J10 -> 0 | ... N10: ='PL WB'!N10+'PL OZON'!N10 -> 0 | O10: =SUM(C10:N10) -> 192398.77
A11: Поступление товара, шт | C11: ='PL WB'!C11+'PL OZON'!C11 -> 1294 | D11: ='PL WB'!D11+'PL OZON'!D11 -> 0 | E11: ='PL WB'!E11+'PL OZON'!E11 -> 0 | F11: ='PL WB'!F11+'PL OZON'!F11 -> 0 | G11: ='PL WB'!G11+'PL OZON'!G11 -> 0 | H11: ='PL WB'!H11+'PL OZON'!H11 -> 0 | I11: ='PL WB'!I11+'PL OZON'!I11 -> 0 | J11: ='PL WB'!J11+'PL OZON'!J11 -> 0 | ... N11: ='PL WB'!N11+'PL OZON'!N11 -> 0 | O11: =SUM(C11:N11) -> 1294
A12: Доступно на складе по цене закупки | C12: ='PL WB'!C12+'PL OZON'!C12 -> 1522905.6 | D12: ='PL WB'!D12+'PL OZON'!D12 -> 1301418.9 | E12: ='PL WB'!E12+'PL OZON'!E12 -> 1109069.5 | F12: ='PL WB'!F12+'PL OZON'!F12 -> 1028078.6 | G12: ='PL WB'!G12+'PL OZON'!G12 -> 1028078.6 | H12: ='PL WB'!H12+'PL OZON'!H12 -> 1028078.6 | I12: ='PL WB'!I12+'PL OZON'!I12 -> 1028078.6 | J12: ='PL WB'!J12+'PL OZON'!J12 -> 1028078.6 | ... N12: ='PL WB'!N12+'PL OZON'!N12 -> 1028078.6
A13: Доступно на складе, шт | C13: ='PL WB'!C13+'PL OZON'!C13 -> 10153 | D13: ='PL WB'!D13+'PL OZON'!D13 -> 8438 | E13: ='PL WB'!E13+'PL OZON'!E13 -> 6908 | F13: ='PL WB'!F13+'PL OZON'!F13 -> 6309 | G13: ='PL WB'!G13+'PL OZON'!G13 -> 6309 | H13: ='PL WB'!H13+'PL OZON'!H13 -> 6306 | I13: ='PL WB'!I13+'PL OZON'!I13 -> 6306 | J13: ='PL WB'!J13+'PL OZON'!J13 -> 6306 | ... N13: ='PL WB'!N13+'PL OZON'!N13 -> 6306
A14: Продано товаров по цене в карточке | C14: ='PL WB'!C14+'PL OZON'!C14 -> 1213007 | D14: ='PL WB'!D14+'PL OZON'!D14 -> 1136792 | E14: ='PL WB'!E14+'PL OZON'!E14 -> 937183 | F14: ='PL WB'!F14+'PL OZON'!F14 -> 419223 | G14: ='PL WB'!G14+'PL OZON'!G14 -> 0 | H14: ='PL WB'!H14+'PL OZON'!H14 -> 0 | I14: ='PL WB'!I14+'PL OZON'!I14 -> 0 | J14: ='PL WB'!J14+'PL OZON'!J14 -> 0 | ... N14: ='PL WB'!N14+'PL OZON'!N14 -> 0 | O14: =SUM(C14:N14) -> 3706205
A15: Продано товаров -ПРОДАЖИ | C15: ='PL WB'!C15+'PL OZON'!C14 -> 950524 | D15: ='PL WB'!D15+'PL OZON'!D14 -> 834437 | E15: ='PL WB'!E15+'PL OZON'!E14 -> 692756 | F15: ='PL WB'!F15+'PL OZON'!F14 -> 313306 | G15: ='PL WB'!G15+'PL OZON'!G14 -> 0 | H15: ='PL WB'!H15+'PL OZON'!H14 -> 0 | I15: ='PL WB'!I15+'PL OZON'!I14 -> 0 | J15: ='PL WB'!J15+'PL OZON'!J14 -> 0 | ... N15: ='PL WB'!N15+'PL OZON'!N14 -> 0 | O15: =SUM(C15:N15) -> 2791023
O16: =SUM(C16:N16) -> 0
A17: Комиссия | C17: =C14-C20 -> 395838.84 | D17: =D14-D20 -> 369766.81 | E17: =E14-E20 -> 307275.59 | F17: =F14-F20 -> 136873.54 | G17: =G14-G20 -> 0 | H17: =H14-H20 -> 0 | I17: =I14-I20 -> 0 | J17: =J14-J20 -> 0 | ... M17: =M14-M20 -> 0 | N17: =N15-N20 -> 0 | O17: =SUM(C17:N17) -> 1209754.8
A18: % комиссии | C18: =C17/C14 -> 0.32632857 | D18: =D17/D15 -> 0.44313329 | E18: =E17/E15 -> 0.44355529 | F18: =F17/F15 -> 0.43686856 | G18: =G17/G15 -> #DIV/0! | H18: =H17/H15 -> #DIV/0! | I18: =I17/I15 -> #DIV/0! | J18: =J17/J15 -> #DIV/0! | K18: =K17/K15 -> #DIV/0! | ... O18: =O17/O15 -> 0.43344493
A20: Выручка от реализации (к перечислению за товар), руб | C20: ='PL WB'!C20+'PL OZON'!C20 -> 817168.16 | D20: ='PL WB'!D20+'PL OZON'!D20 -> 767025.19 | E20: ='PL WB'!E20+'PL OZON'!E20 -> 629907.41 | F20: ='PL WB'!F20+'PL OZON'!F20 -> 282349.46 | G20: ='PL WB'!G20+'PL OZON'!G20 -> 0 | H20: ='PL WB'!H20+'PL OZON'!H20 -> 0 | I20: ='PL WB'!I20+'PL OZON'!I20 -> 0 | J20: ='PL WB'!J20+'PL OZON'!J20 -> 0 | ... N20: ='PL WB'!N20+'PL OZON'!N20 -> 0 | O20: =SUM(C20:N20) -> 2496450.2
O21: =SUM(C21:N21) -> 0
A22: Возвраты, руб | C22: ='PL WB'!C22+'PL OZON'!C22 -> 6905 | D22: ='PL WB'!D22+'PL OZON'!D22 -> 3051 | E22: ='PL WB'!E22+'PL OZON'!E22 -> 11540 | F22: ='PL WB'!F22+'PL OZON'!F22 -> 2705 | G22: ='PL WB'!G22+'PL OZON'!G22 -> 0 | H22: ='PL WB'!H22+'PL OZON'!H22 -> 0 | I22: ='PL WB'!I22+'PL OZON'!I22 -> 0 | J22: ='PL WB'!J22+'PL OZON'!J22 -> 0 | ... N22: ='PL WB'!N22+'PL OZON'!N22 -> 0 | O22: =SUM(C22:N22) -> 24201
A23: Возвраты, шт | C23: ='PL WB'!C23+'PL OZON'!C23 -> 11 | D23: ='PL WB'!D23+'PL OZON'!D23 -> 4 | E23: ='PL WB'!E23+'PL OZON'!E23 -> 15 | F23: ='PL WB'!F23+'PL OZON'!F23 -> 5 | G23: ='PL WB'!G23+'PL OZON'!G23 -> 0 | H23: ='PL WB'!H23+'PL OZON'!H23 -> 0 | I23: ='PL WB'!I23+'PL OZON'!I23 -> 0 | J23: ='PL WB'!J23+'PL OZON'!J23 -> 0 | ... N23: ='PL WB'!N23+'PL OZON'!N23 -> 0 | O23: =SUM(C23:N23) -> 35
A24: % возвратов | C24: ='PL WB'!C24+'PL OZON'!C24 -> 0.017316571 | D24: =D22/D20 -> 0.0039777051 | E24: =E22/E20 -> 0.018320153 | F24: =F22/F20 -> 0.0095803265 | G24: =G22/G20 -> #DIV/0! | H24: =H22/H20 -> #DIV/0! | I24: =I22/I20 -> #DIV/0! | J24: =J22/J20 -> #DIV/0! | K24: =K22/K20 -> #DIV/0! | ... O24: =O22/O20 -> 0.0096941649
C25: ='PL WB'!C25+'PL OZON'!C25 -> 0
A26: Брак, руб | C26: ='PL WB'!C26+'PL OZON'!C26 -> 0
A27: Брак, шт | C27: ='PL WB'!C27+'PL OZON'!C27 -> 0 | D27: =SUM('PL WB (нед)'!H27:K27) -> 0 | E27: =SUM('PL WB (нед)'!L27:O27) -> 0 | F27: =SUM('PL WB (нед)'!P27:S27) -> 1 | G27: =SUM('PL WB (нед)'!T27:X27) -> 0 | H27: =SUM('PL WB (нед)'!Y27:AB27) -> 3 | I27: =SUM('PL WB (нед)'!AC27:AF27) -> 0 | J27: =SUM('PL WB (нед)'!AG27:AK27) -> 0 | K27: =SUM('PL WB (нед)'!AL27:AO27) -> 0 | L27: =SUM('PL WB (нед)'!AP27:AT27) -> 0 | M27: =SUM('PL WB (нед)'!AU27:AX27) -> 0 | N27: =SUM('PL WB (нед)'!AY27:BB27) -> 0
A28: % брака | C28: ='PL WB'!C28+'PL OZON'!C28 -> 0 | D28: =D27/D7 -> 0 | E28: =E27/E7 -> 0 | F28: =F27/F7 -> 0.0016583748 | G28: =G27/G7 -> #DIV/0! | H28: =H27/H7 -> #DIV/0! | I28: =I27/I7 -> #DIV/0! | J28: =J27/J7 -> #DIV/0! | K28: =K27/K7 -> #DIV/0! | ... N28: =N27/N7 -> #DIV/0!
A30: Поступление на счет | C30: ='PL WB'!C30+'PL OZON'!C30 -> 538094.63 | D30: ='PL WB'!D30+'PL OZON'!D30 -> 560103.5 | E30: ='PL WB'!E30+'PL OZON'!E30 -> 448883.78 | F30: ='PL WB'!F30+'PL OZON'!F30 -> 201984.28 | G30: ='PL WB'!G30+'PL OZON'!G30 -> 0 | H30: ='PL WB'!H30+'PL OZON'!H30 -> 0 | I30: ='PL WB'!I30+'PL OZON'!I30 -> 0 | J30: ='PL WB'!J30+'PL OZON'!J30 -> 0 | ... N30: ='PL WB'!N30+'PL OZON'!N30 -> 0 | O30: =SUM(C30:N30) -> 1749066.2
A31: в т.ч. Прочие доходы | C31: =SUM('PL WB (нед)'!C31:G31) -> 0 | D31: =SUM('PL WB (нед)'!H31:K31) -> 0 | E31: =SUM('PL WB (нед)'!L31:O31) -> 352.3 | F31: =SUM('PL WB (нед)'!P31:S31) -> 66.37 | G31: =SUM('PL WB (нед)'!T31:X31) -> 0 | H31: =SUM('PL WB (нед)'!Y31:AB31) -> 0 | I31: =SUM('PL WB (нед)'!AC31:AF31) -> 0 | J31: =SUM('PL WB (нед)'!AG31:AK31) -> 0 | K31: =SUM('PL WB (нед)'!AL31:AO31) -> 0 | L31: =SUM('PL WB (нед)'!AP31:AT31) -> 0 | M31: =SUM('PL WB (нед)'!AU31:AX31) -> 0 | N31: =SUM('PL WB (нед)'!AY31:BB31) -> 0 | O31: =SUM(C31:N31) -> 418.67
O32: =SUM(C32:N32) -> 0
A33: Себестоимость | C33: ='PL WB'!C33+'PL OZON'!C33 -> 240350.81 | D33: ='PL WB'!D33+'PL OZON'!D33 -> 221486.72 | E33: ='PL WB'!E33+'PL OZON'!E33 -> 192349.4 | F33: ='PL WB'!F33+'PL OZON'!F33 -> 80990.9 | G33: ='PL WB'!G33+'PL OZON'!G33 -> 0 | H33: ='PL WB'!H33+'PL OZON'!H33 -> 0 | I33: ='PL WB'!I33+'PL OZON'!I33 -> 0 | J33: ='PL WB'!J33+'PL OZON'!J33 -> 0 | ... N33: ='PL WB'!N33+'PL OZON'!N33 -> 0 | O33: =SUM(C33:N33) -> 735177.83
A34: % себестоимости | C34: =C33/C14 -> 0.19814462 | D34: =D33/D15 -> 0.26543253 | E34: =E33/E15 -> 0.27765822 | F34: =F33/F15 -> 0.25850415 | G34: =G33/G15 -> #DIV/0! | H34: =H33/H15 -> #DIV/0! | I34: =I33/I15 -> #DIV/0! | J34: =J33/J15 -> #DIV/0! | K34: =K33/K15 -> #DIV/0! | ... O34: =O33/O15 -> 0.26340802
A36: Валовая прибыль | C36: ='PL WB'!C36+'PL OZON'!C36 -> 576817.35 | D36: ='PL WB'!D36+'PL OZON'!D36 -> 545538.47 | E36: ='PL WB'!E36+'PL OZON'!E36 -> 437558.01 | F36: ='PL WB'!F36+'PL OZON'!F36 -> 201358.56 | G36: ='PL WB'!G36+'PL OZON'!G36 -> 0 | H36: ='PL WB'!H36+'PL OZON'!H36 -> 0 | I36: ='PL WB'!I36+'PL OZON'!I36 -> 0 | J36: ='PL WB'!J36+'PL OZON'!J36 -> 0 | K36: ='PL WB'!K36+'PL OZON'!K36 -> 0 | L36: =L20-L33 -> 0 | M36: =M20-M33 -> 0 | N36: =N20-N33 -> 0 | O36: =SUM(C36:N36) -> 1761272.4
O37: =SUM(C37:N37) -> 0
A38: Расходы | C38: ='PL WB'!C38+'PL OZON'!C38 -> 267226.53 | D38: ='PL WB'!D38+'PL OZON'!D38 -> 199006.69 | E38: ='PL WB'!E38+'PL OZON'!E38 -> 178158.93 | F38: ='PL WB'!F38+'PL OZON'!F38 -> 80056.55 | G38: ='PL WB'!G38+'PL OZON'!G38 -> 0 | H38: ='PL WB'!H38+'PL OZON'!H38 -> 0 | I38: ='PL WB'!I38+'PL OZON'!I38 -> 0 | J38: ='PL WB'!J38+'PL OZON'!J38 -> 0 | ... N38: ='PL WB'!N38+'PL OZON'!N38 -> 0 | O38: =SUM(C38:N38) -> 724448.7
A39: % расходы | C39: =C38/C14 -> 0.2203009 | D39: =D38/D14 -> 0.1750599 | E39: =E38/E14 -> 0.19010047 | F39: =F38/F14 -> 0.19096412 | G39: =G38/G14 -> #DIV/0! | H39: =H38/H14 -> #DIV/0! | I39: =I38/I14 -> #DIV/0! | J39: =J38/J14 -> #DIV/0! | ... N39: =N38/N14 -> #DIV/0!
A40: Логистика | C40: ='PL WB'!C40+'PL OZON'!C40 -> 183264 | D40: ='PL WB'!D40+'PL OZON'!D40 -> 153195 | E40: ='PL WB'!E40+'PL OZON'!E40 -> 134317 | F40: ='PL WB'!F40+'PL OZON'!F40 -> 48829 | G40: ='PL WB'!G40+'PL OZON'!G40 -> 0 | H40: ='PL WB'!H40+'PL OZON'!H40 -> 0 | I40: ='PL WB'!I40+'PL OZON'!I40 -> 0 | J40: ='PL WB'!J40+'PL OZON'!J40 -> 0 | ... N40: ='PL WB'!N40+'PL OZON'!N40 -> 0 | O40: =SUM(C40:N40) -> 519605
A41: Продвижение | C41: ='PL WB'!C41+'PL OZON'!C41 -> 11847 | D41: ='PL WB'!D41+'PL OZON'!D41 -> 7915 | E41: ='PL WB'!E41+'PL OZON'!E41 -> 3217 | F41: ='PL WB'!F41+'PL OZON'!F41 -> 375 | G41: ='PL WB'!G41+'PL OZON'!G41 -> 0 | H41: ='PL WB'!H41+'PL OZON'!H41 -> 0 | I41: ='PL WB'!I41+'PL OZON'!I41 -> 0 | J41: ='PL WB'!J41+'PL OZON'!J41 -> 0 | ... N41: ='PL WB'!N41+'PL OZON'!N41 -> 0 | O41: =SUM(C41:N41) -> 23354
A42: Эквайринг | C42: ='PL WB'!C42+'PL OZON'!C42 -> 3613 | D42: ='PL WB'!D42+'PL OZON'!D42 -> 2391 | E42: ='PL WB'!E42+'PL OZON'!E42 -> 1321 | F42: ='PL WB'!F42+'PL OZON'!F42 -> 773 | G42: ='PL WB'!G42+'PL OZON'!G42 -> 0 | H42: ='PL WB'!H42+'PL OZON'!H42 -> 0 | I42: ='PL WB'!I42+'PL OZON'!I42 -> 0 | J42: ='PL WB'!J42+'PL OZON'!J42 -> 0 | ... N42: ='PL WB'!N42+'PL OZON'!N42 -> 0 | O42: =SUM(C42:N42) -> 8098
A43: Хранение | C43: ='PL WB'!C43+'PL OZON'!C43 -> 53680.72 | D43: ='PL WB'!D43+'PL OZON'!D43 -> 35505.69 | E43: ='PL WB'!E43+'PL OZON'!E43 -> 39303.93 | F43: ='PL WB'!F43+'PL OZON'!F43 -> 30039.55 | G43: ='PL WB'!G43+'PL OZON'!G43 -> 0 | H43: ='PL WB'!H43+'PL OZON'!H43 -> 0 | I43: ='PL WB'!I43+'PL OZON'!I43 -> 0 | J43: ='PL WB'!J43+'PL OZON'!J43 -> 0 | ... N43: ='PL WB'!N43+'PL OZON'!N43 -> 0 | O43: =SUM(C43:N43) -> 158529.89
A44: Штрафы | C44: ='PL WB'!C44+'PL OZON'!C44 -> 741 | D44: ='PL WB'!D44+'PL OZON'!D44 -> 0 | E44: ='PL WB'!E44+'PL OZON'!E44 -> 0 | F44: ='PL WB'!F44+'PL OZON'!F44 -> 40 | G44: ='PL WB'!G44+'PL OZON'!G44 -> 0 | H44: ='PL WB'!H44+'PL OZON'!H44 -> 0 | I44: ='PL WB'!I44+'PL OZON'!I44 -> 0 | J44: ='PL WB'!J44+'PL OZON'!J44 -> 0 | ... N44: ='PL WB'!N44+'PL OZON'!N44 -> 0 | O44: =SUM(C44:N44) -> 781
A45: Платная приемка | C45: ='PL WB'!C45+'PL OZON'!C45 -> 14080.81 | D45: ='PL WB'!D45+'PL OZON'!D45 -> 0 | E45: ='PL WB'!E45+'PL OZON'!E45 -> 0 | F45: ='PL WB'!F45+'PL OZON'!F45 -> 0 | G45: ='PL WB'!G45+'PL OZON'!G45 -> 0 | H45: ='PL WB'!H45+'PL OZON'!H45 -> 0 | I45: ='PL WB'!I45+'PL OZON'!I45 -> 0 | J45: ='PL WB'!J45+'PL OZON'!J45 -> 0 | ... N45: ='PL WB'!N45+'PL OZON'!N45 -> 0 | O45: =SUM(C45:N45) -> 14080.81
A46: Прочее OZON | C46: ='PL WB'!C46+'PL OZON'!C46 -> 0 | D46: ='PL WB'!D46+'PL OZON'!D46 -> 0 | E46: ='PL WB'!E46+'PL OZON'!E46 -> 0 | F46: ='PL WB'!F46+'PL OZON'!F46 -> 0 | G46: ='PL WB'!G46+'PL OZON'!G46 -> 0 | H46: ='PL WB'!H46+'PL OZON'!H46 -> 0 | I46: ='PL WB'!I46+'PL OZON'!I46 -> 0 | J46: ='PL WB'!J46+'PL OZON'!J46 -> 0 | ... N46: ='PL WB'!N46+'PL OZON'!N46 -> 0 | O46: =SUM(C46:N46) -> 0
A47: Контент | C47: ='PL WB'!C47+'PL OZON'!C47 -> 0 | D47: ='PL WB'!D47+'PL OZON'!D47 -> 0 | E47: ='PL WB'!E47+'PL OZON'!E47 -> 0 | F47: ='PL WB'!F47+'PL OZON'!F47 -> 0 | G47: ='PL WB'!G47+'PL OZON'!G47 -> 0 | H47: ='PL WB'!H47+'PL OZON'!H47 -> 0 | I47: ='PL WB'!I47+'PL OZON'!I47 -> 0 | J47: ='PL WB'!J47+'PL OZON'!J47 -> 0 | ... N47: ='PL WB'!N47+'PL OZON'!N47 -> 0 | O47: =SUM(C47:N47) -> 0
A48: Аренда офиса | C48: ='PL WB'!C48+'PL OZON'!C48 -> 0 | D48: ='PL WB'!D48+'PL OZON'!D48 -> 0 | E48: ='PL WB'!E48+'PL OZON'!E48 -> 0 | F48: ='PL WB'!F48+'PL OZON'!F48 -> 0 | G48: ='PL WB'!G48+'PL OZON'!G48 -> 0 | H48: ='PL WB'!H48+'PL OZON'!H48 -> 0 | I48: ='PL WB'!I48+'PL OZON'!I48 -> 0 | J48: ='PL WB'!J48+'PL OZON'!J48 -> 0 | ... N48: ='PL WB'!N48+'PL OZON'!N48 -> 0 | O48: =SUM(C48:N48) -> 0
A49: Реклама внешняя | C49: ='PL WB'!C49+'PL OZON'!C49 -> 0 | D49: ='PL WB'!D49+'PL OZON'!D49 -> 0 | E49: ='PL WB'!E49+'PL OZON'!E49 -> 0 | F49: ='PL WB'!F49+'PL OZON'!F49 -> 0 | G49: ='PL WB'!G49+'PL OZON'!G49 -> 0 | H49: ='PL WB'!H49+'PL OZON'!H49 -> 0 | I49: ='PL WB'!I49+'PL OZON'!I49 -> 0 | J49: ='PL WB'!J49+'PL OZON'!J49 -> 0 | ... N49: ='PL WB'!N49+'PL OZON'!N49 -> 0 | O49: =SUM(C49:N49) -> 0
A50: Подписка Аналитика | C50: ='PL WB'!C50+'PL OZON'!C50 -> 0 | D50: ='PL WB'!D50+'PL OZON'!D50 -> 0 | E50: ='PL WB'!E50+'PL OZON'!E50 -> 0 | F50: ='PL WB'!F50+'PL OZON'!F50 -> 0 | G50: ='PL WB'!G50+'PL OZON'!G50 -> 0 | H50: ='PL WB'!H50+'PL OZON'!H50 -> 0 | I50: ='PL WB'!I50+'PL OZON'!I50 -> 0 | J50: ='PL WB'!J50+'PL OZON'!J50 -> 0 | ... N50: ='PL WB'!N50+'PL OZON'!N50 -> 0 | O50: =SUM(C50:N50) -> 0
A51: Прочие | C51: ='PL WB'!C51+'PL OZON'!C51 -> 0 | D51: ='PL WB'!D51+'PL OZON'!D51 -> 0 | E51: ='PL WB'!E51+'PL OZON'!E51 -> 0 | F51: ='PL WB'!F51+'PL OZON'!F51 -> 0 | G51: ='PL WB'!G51+'PL OZON'!G51 -> 0 | H51: ='PL WB'!H51+'PL OZON'!H51 -> 0 | I51: ='PL WB'!I51+'PL OZON'!I51 -> 0 | J51: ='PL WB'!J51+'PL OZON'!J51 -> 0 | ... N51: ='PL WB'!N51+'PL OZON'!N51 -> 0 | O51: =SUM(C51:N51) -> 0
C52: ='PL WB'!C52+'PL OZON'!C52 -> 0 | D52: ='PL WB'!D52+'PL OZON'!D52 -> 0 | E52: ='PL WB'!E52+'PL OZON'!E52 -> 0 | F52: ='PL WB'!F52+'PL OZON'!F52 -> 0 | G52: ='PL WB'!G52+'PL OZON'!G52 -> 0 | H52: ='PL WB'!H52+'PL OZON'!H52 -> 0 | I52: ='PL WB'!I52+'PL OZON'!I52 -> 0 | J52: ='PL WB'!J52+'PL OZON'!J52 -> 0 | ... N52: ='PL WB'!N52+'PL OZON'!N52 -> 0 | O52: =SUM(C52:N52) -> 0
A53: Прибыль до налогообложения | C53: ='PL WB'!C53+'PL OZON'!C53 -> 309590.82 | D53: ='PL WB'!D53+'PL OZON'!D53 -> 346531.78 | E53: ='PL WB'!E53+'PL OZON'!E53 -> 259751.38 | F53: ='PL WB'!F53+'PL OZON'!F53 -> 121368.38 | G53: ='PL WB'!G53+'PL OZON'!G53 -> 0 | H53: ='PL WB'!H53+'PL OZON'!H53 -> 0 | I53: ='PL WB'!I53+'PL OZON'!I53 -> 0 | J53: ='PL WB'!J53+'PL OZON'!J53 -> 0 | ... N53: ='PL WB'!N53+'PL OZON'!N53 -> 0 | O53: =SUM(C53:N53) -> 1037242.4
A55: Налоги начисленные | B55: УСН 6%+1% | C55: =C15*7% -> 66536.68 | D55: =D15*7% -> 58410.59 | E55: =E15*7% -> 48492.92 | F55: =F15*7% -> 21931.42 | G55: =G15*7% -> 0 | H55: =H15*7% -> 0 | I55: =I15*7% -> 0 | J55: =J15*7% -> 0 | ... N55: =N15*7% -> 0 | O55: =SUM(C55:N55) -> 195371.61
A57: Чистая прибыль | C57: ='PL WB'!C57+'PL OZON'!C57 -> 243054.14 | D57: ='PL WB'!D57+'PL OZON'!D57 -> 288121.19 | E57: ='PL WB'!E57+'PL OZON'!E57 -> 211258.46 | F57: ='PL WB'!F57+'PL OZON'!F57 -> 99436.96 | G57: ='PL WB'!G57+'PL OZON'!G57 -> 0 | H57: ='PL WB'!H57+'PL OZON'!H57 -> 0 | I57: ='PL WB'!I57+'PL OZON'!I57 -> 0 | J57: ='PL WB'!J57+'PL OZON'!J57 -> 0 | ... N57: ='PL WB'!N57+'PL OZON'!N57 -> 0 | O57: =SUM(C57:N57) -> 841870.75
A58: Рентабельность вложений | C58: =C57/C33 -> 1.0112474 | D58: =D57/D33 -> 1.3008509 | E58: =E57/E33 -> 1.0983058 | F58: =F57/F33 -> 1.2277547 | G58: =G57/G33 -> #DIV/0! | H58: =H57/H33 -> #DIV/0! | I58: =I57/I33 -> #DIV/0! | J58: =J57/J33 -> #DIV/0! | ... O58: =O57/O33 -> 1.1451253
A59: Маржинальность | C59: =C57/C14 -> 0.20037324 | D59: =D57/D14 -> 0.25345111 | E59: =E57/E14 -> 0.22541858 | F59: =F57/F14 -> 0.23719347 | G59: =G57/G14 -> #DIV/0! | H59: =H57/H14 -> #DIV/0! | I59: =I57/I14 -> #DIV/0! | J59: =J57/J14 -> #DIV/0! | ... O59: =O57/O14 -> 0.2271517
A60: Выплата диведентов: | C60: =CF!C38 -> 0 | D60: =CF!D38 -> 0 | E60: =CF!E38 -> 0 | F60: =CF!F38 -> 0 | G60: =CF!G38 -> 0 | H60: =CF!H38 -> 0 | I60: =CF!I38 -> 0 | J60: =CF!J38 -> 0 | ... N60: =CF!N38 -> 0
A62: Остаток денежных средств на конец периода | C62: =CF!C42 -> 2426951.9 | D62: =CF!D42 -> 2920729.8 | E62: =CF!E42 -> 3317903.7 | F62: =CF!F42 -> 3497581.5 | G62: =CF!G42 -> 3497581.5 | H62: =CF!H42 -> 3497581.5 | I62: =CF!I42 -> 3497581.5 | J62: =CF!J42 -> 3497581.5 | ... N62: =CF!N42 -> 3497581.5
A64: Накопленный финансовый результат | C64: ='PL WB'!C64+'PL OZON'!C64 -> 3564465 | D64: ='PL WB'!D64+'PL OZON'!D64 -> 3852586.2 | E64: ='PL WB'!E64+'PL OZON'!E64 -> 4063844.7 | F64: ='PL WB'!F64+'PL OZON'!F64 -> 4163281.6 | G64: ='PL WB'!G64+'PL OZON'!G64 -> 4163281.6 | H64: ='PL WB'!H64+'PL OZON'!H64 -> 4163281.6 | I64: ='PL WB'!I64+'PL OZON'!I64 -> 4163281.6 | J64: ='PL WB'!J64+'PL OZON'!J64 -> 4163281.6 | ... N64: ='PL WB'!N64+'PL OZON'!N64 -> 4163281.6
A66: Рекламные расходы на 1 единицу | C66: =IFERROR(C41/C7, ) -> 6.0290076 | D66: =IFERROR(D41/D7, ) -> 4.6044212 | E66: =IFERROR(E41/E7, ) -> 2.0822006 | F66: =IFERROR(F41/F7, ) -> 0.62189055 | G66: =IFERROR(G41/G7, ) -> 0 | H66: =IFERROR(H41/H7, ) -> 0 | I66: =IFERROR(I41/I7, ) -> 0 | J66: =IFERROR(J41/J7, ) -> 0 | ... O66: =IFERROR(O41/O7, ) -> 4.0044582
A67: Доля рекламных расходов | C67: =IFERROR(C41/C14, ) -> 0.0097666378 | D67: =IFERROR(D41/D14, ) -> 0.0069625754 | E67: =IFERROR(E41/E14, ) -> 0.0034326274 | F67: =IFERROR(F41/F14, ) -> 0.00089451199 | G67: =IFERROR(G41/G14, ) -> 0 | H67: =IFERROR(H41/H14, ) -> 0 | I67: =IFERROR(I41/I14, ) -> 0 | J67: =IFERROR(J41/J14, ) -> 0 | ... O67: =IFERROR(O41/O14, ) -> 0.0063013244
A68: Прибыль на 1 ед | C68: =IFERROR(C57/(C7-C23), ) -> 124.38799 | D68: =IFERROR(D57/(D7-D23), ) -> 168.00069 | E68: =IFERROR(E57/(E7-E23), ) -> 138.07742 | F68: =IFERROR(F57/(F7-F23), ) -> 166.28254 | G68: =IFERROR(G57/(G7-G23), ) -> 0 | H68: =IFERROR(H57/(H7-H23), ) -> 0 | I68: =IFERROR(I57/(I7-I23), ) -> 0 | J68: =IFERROR(J57/(J7-J23), ) -> 0 | ... O68: =IFERROR(O57/(O7-O23), ) -> 145.22525

Sheet PL WB (нед)
A1: Голубым выделены строки, которые заполняем! Заполняем эту вкладку, формулы не трогаем! Если добавляете строки - добавляете на всех листах PL и СF | C1: 1 | D1: 2 | E1: 3 | F1: 4 | G1: 5 | H1: 6 | I1: 7 | J1: 8 | K1: 9 | L1: 10 | M1: 11 | N1: 12 | O1: 13 | P1: 14 | Q1: 15 | R1: 16 | S1: 17 | T1: 18 | U1: 19 | V1: 20 | W1: 21 | X1: 22 | Y1: 23 | Z1: 24 | AA1: 25 | AB1: 26 | AC1: 27 | AD1: 28 | AE1: 29 | AF1: 30 | AG1: 31 | AH1: 32 | AI1: 33 | AJ1: 34 | AK1: 35 | AL1: 36 | AM1: 37 | AN1: 38 | AO1: 39 | AP1: 40 | AQ1: 41 | AR1: 42 | AS1: 43 | AT1: 44 | AU1: 45 | AV1: 46 | AW1: 47 | AX1: 48 | AY1: 49 | AZ1: 50 | BA1: 51 | BB1: 52 | BC1: Остаток года
A2: Прибыли и убытки, еженедельно | C2: Январь | H2: Февраль | L2: Март | P2: Апрель | T2: Май | Y2: Июнь | AC2: Июль | AG2: Август | AL2: Сентябрь | AP2: Октябрь | AU2: Ноябрь | AY2: Декабрь
C3: 01.01-04.01 | D3: 05.01-11.01 | E3: 12.01-18.01 | F3: 19.01-25.01 | G3: 26.01-01.02 | H3: 02.02-08.02 | I3: 09.02-15.02 | J3: 16.02-22.02 | K3: 23.02-01.03 | L3: 02.03-08.03 | M3: 09.03-15.03 | N3: 16.03-22.03 | O3: 23.03-29.03 | P3: 30.03-05.04 | Q3: 06.04-12.04 | R3: 13.04-19.04
A4: Товарооборот
A5: Остаток товара по цене закупки | C5: 1331789.1 | D5: =C12 -> 1514984.9 | E5: =D12 -> 1480919.9 | F5: =E12 -> 1434587.7 | G5: =F12 -> 1394134.5 | H5: =G12 -> 1355494.1 | I5: =H12 -> 1309516.1 | J5: =I12 -> 1263879 | K5: =J12 -> 1224679.8 | ... BB5: =BA12 -> 960491.03 | BC5: 1331789.1
A7: Продажи шт | C7: 0 | D7: 1202 | E7: 0 | F7: 0 | G7: 0 | H7: 0 | I7: 0 | J7: 0 | K7: 0 | L7: 0 | M7: 0 | N7: 0 | O7: 0 | P7: 0 | Q7: 0 | R7: 0 | S7: 0 | T7: 0 | U7: 0 | V7: 0 | W7: 0 | X7: 0 | Y7: 0 | Z7: 0 | AA7: 0 | AB7: 0 | AC7: 0 | AD7: 0 | AE7: 0 | AF7: 0 | AG7: 0 | AH7: 0 | AI7: 0 | AJ7: 0 | AK7: 0 | AL7: 0 | AM7: 0 | AN7: 0 | AO7: 0 | AP7: 0 | AQ7: 0 | AR7: 0 | AS7: 0 | AT7: 0 | AU7: 0 | AV7: 0 | AW7: 0 | AX7: 0 | AY7: 0 | AZ7: 0 | BA7: 0 | BB7: 0 | BC7: 484 | BD7: =SUM(C7:BC7) -> 4476
A8: Отгрузки по себестоимости | C8: =C33 -> 9203 | D8: =D33 -> 34065 | E8: =E33 -> 46332.16 | F8: =F33 -> 40453.2 | G8: =G33 -> 38640.45 | H8: =H33 -> 45978 | I8: =I33 -> 45637.06 | J8: =J33 -> 39199.24 | ... BC8: =BC33 -> 0 | BD8: =SUM(C8:BC8) -> 563696.83
BD9: =SUM(C9:BC9) -> 0
A10: Поступление товара, р | C10: 192398.77 | BD10: =SUM(C10:BC10) -> 192398.77
A11: Поступление товара, шт | C11: 1294 | BD11: =SUM(C11:BC11) -> 1294
A12: Доступно на складе по цене закупки | C12: =C10-C8+C5 -> 1514984.9 | D12: =D10-D8+D5 -> 1480919.9 | E12: =E10-E8+E5 -> 1434587.7 | F12: =F10-F8+F5 -> 1394134.5 | G12: =G10-G8+G5 -> 1355494.1 | H12: =H10-H8+H5 -> 1309516.1 | I12: =I10-I8+I5 -> 1263879 | J12: =J10-J8+J5 -> 1224679.8 | ... BC12: =BC10-BC8+BC5 -> 1331789.1 | BD12: =SUM(C12:BC12)/52.5 -> 1054175
A13: Доступно на складе, шт | C13: =9072-C7-C27+C11+C23 -> 10178 | D13: =C13-D7-D27+D11+D23 -> 9935 | E13: =D13-E7-E27+E11+E23 -> 9594 | F13: =E13-F7-F27+F11+F23 -> 9299 | G13: =F13-G7-G27+G11+G23 -> 9007 | H13: =G13-H7-H27+H11+H23 -> 8665 | I13: =H13-I7-I27+I11+I23 -> 8334 | J13: =I13-J7-J27+J11+J23 -> 8025 | K13: =J13-K7-K27+K11+K23 -> 7678 | ... BB13: =BA13-BB7-BB27+BB11+BB23 -> 5897 | BC13: 9072 | BD13: =SUM(C13:BC13)/53.5 -> 6497.4953
A14: Продано товаров WB по цене в карточке | C14: 48841 | D14: 164469 | E14: 219043 | F14: 192988 | G14: 188915 | H14: 218237 | I14: 231995 | J14: 209378 | K14: 219789 | L14: 210110 | M14: 193338 | N14: 193369 | O14: 175517 | P14: 132809 | Q14: 108682 | R14: 103393 | BD14: =SUM(C14:BC14) -> 2810873
A15: Продано товаров WB ВБ реализовал-ПРОДАЖИ | C15: 34445 | D15: 112779 | E15: 147256 | F15: 131182 | G15: 126111 | H15: 142988 | I15: 152014 | J15: 136874 | K15: 145168 | L15: 142232 | M15: 131792 | N15: 131955 | O15: 121928 | P15: 93126 | Q15: 75500 | R15: 70341 | BD15: =SUM(C15:BC15) -> 1895691
BD16: =SUM(C16:BC16) -> 0
A17: Комиссия ВБ | C17: =C14-C20 -> 14515 | D17: =D14-D20 -> 49977.42 | E17: =E14-E20 -> 66083.96 | F17: =F14-F20 -> 58319.03 | G17: =G14-G20 -> 56648.43 | H17: =H14-H20 -> 66021.4 | I17: =I14-I20 -> 71141.23 | J17: =J14-J20 -> 65610.81 | ... BC17: =BC14-BC20 -> 0 | BD17: =SUM(C17:BC17) -> 870568.78
A18: % комиссии | C18: =C17/C14 -> 0.29718884 | D18: =D17/D14 -> 0.30387137 | E18: =E17/E14 -> 0.30169401 | F18: =F17/F14 -> 0.30218993 | G18: =G17/G14 -> 0.299862 | H18: =H17/H14 -> 0.30252157 | I18: =I17/I14 -> 0.30664984 | J18: =J17/J14 -> 0.31336057 | ... BC18: =BC17/BC14 -> #DIV/0! | BD18: =SUM(C18:BC18) -> #DIV/0!
BD19: =SUM(C19:BC19) -> 0
A20: Выручка от реализации (к перечислению за товар), руб | C20: 34326 | D20: 114491.58 | E20: 152959.04 | F20: 134668.97 | G20: 132266.57 | H20: 152215.6 | I20: 160853.77 | J20: 143767.19 | K20: 150354.63 | L20: 142702.76 | M20: 131929.45 | N20: 132469.98 | O20: 120447.22 | P20: 91343.06 | Q20: 74011.04 | R20: 71497.36 | BD20: =SUM(C20:BC20) -> 1940304.2
BD21: =SUM(C21:BC21) -> 0
A22: Возвраты, руб | M22: 708 | N22: 1515 | O22: 2067 | P22: 1526 | Q22: 519 | BD22: =SUM(C22:BC22) -> 6335
A23: Возвраты, шт | M23: 1 | N23: 3 | O23: 3 | P23: 3 | Q23: 1 | BD23: =SUM(C23:BC23) -> 11
A24: % возвратов | C24: =C22/(C14-C22) -> 0 | D24: =D22/(D14-D22) -> 0 | E24: =E22/(E14-E22) -> 0 | F24: =F22/(F14-F22) -> 0 | G24: =G22/(G14-G22) -> 0 | H24: =H22/(H14-H22) -> 0 | I24: =I22/(I14-I22) -> 0 | J24: =J22/(J14-J22) -> 0 | ... BD24: =BD22/(BD14-BD22) -> 0.0022588391
A26: Брак, руб | BD26: =SUM(C26:BB26) -> 0
A27: Брак, шт | Q27: 1 | Z27: 2 | AA27: 1 | BD27: =SUM(C27:BC27) -> 4
A28: % брака | C28: =C27/C7 -> 0 | D28: =D27/D7 -> 0 | E28: =E27/E7 -> 0 | F28: =F27/F7 -> 0 | G28: =G27/G7 -> 0 | H28: =H27/H7 -> 0 | I28: =I27/I7 -> 0 | J28: =J27/J7 -> 0 | ... BC28: =BC27/BC7 -> #DIV/0!
BD29: =SUM(C29:BC29) -> 0
A30: Поступление на счет от ВБ | C30: =C20+C31-SUM(C40:C45)-C42 -> 26503.58 | D30: =D20+D31-SUM(D40:D45)-D42 -> 90050.43 | E30: =E20+E31-SUM(E40:E45)-E42 -> 122170.28 | F30: =F20+F31-SUM(F40:F45)-F41 -> 89431.22 | G30: =G20+G31-SUM(G40:G45)-G41 -> 95453.12 | H30: =H20+H31-SUM(H40:H45)-H41 -> 121464.16 | I30: =I20+I31-SUM(I40:I45)-I41 -> 131775.46 | J30: =J20+J31-SUM(J40:J45)-J41 -> 114834.31 | K30: =K20+K31-SUM(K40:K45)-K42 -> 119567.57 | L30: =L20+L31-SUM(L40:L45)-L42 -> 107669.87 | M30: =M20+M31-SUM(M40:M45)-M42 -> 99302.4 | N30: =N20+N31-SUM(N40:N45)-N42 -> 94859.58 | O30: =O20+O31-SUM(O40:O45)-O42 -> 88943.93 | P30: =P20+P31-SUM(P40:P45)-P42 -> 67847.65 | Q30: =Q20+Q31-SUM(Q40:Q45)-Q42 -> 53886.29 | R30: =R20+R31-SUM(R40:R45)-R42 -> 52150.34 | ... BC30: =BC20+BC31-SUM(BC40:BC45)-BC42 -> 0 | BD30: =SUM(C30:BC30) -> 1475910.2
A31: в т.ч. Прочие доходы | M31: 153.05 | N31: 128.25 | O31: 71 | P31: 11 | R31: 55.37 | BD31: =SUM(C31:BC31) -> 418.67
BD32: =SUM(C32:BC32) -> 0
A33: Себестоимость | C33: 9203 | D33: 34065 | E33: 46332.16 | F33: 40453.2 | G33: 38640.45 | H33: 45978 | I33: 45637.06 | J33: 39199.24 | K33: 40766.42 | L33: 39771 | M33: 38202.46 | N33: 45982.75 | O33: 36408.19 | P33: 24503.54 | Q33: 19559.56 | R33: 18994.8 | BD33: =SUM(C33:BC33) -> 563696.83
A34: % себестоимости в цене | C34: =C33/C14 -> 0.18842776 | D34: =D33/D14 -> 0.2071211 | E34: =E33/E14 -> 0.21152084 | F34: =F33/F14 -> 0.20961511 | G34: =G33/G14 -> 0.20453881 | H34: =H33/H14 -> 0.21067922 | I34: =I33/I14 -> 0.19671571 | J34: =J33/J14 -> 0.18721757 | ... BD34: =BD33/BD14 -> 0.20054155
BD35: =SUM(C35:BC35) -> 0
A36: Валовая прибыль | C36: =C20-C33 -> 25123 | D36: =D20-D33 -> 80426.58 | E36: =E20-E33 -> 106626.88 | F36: =F20-F33 -> 94215.77 | G36: =G20-G33 -> 93626.12 | H36: =H20-H33 -> 106237.6 | I36: =I20-I33 -> 115216.71 | J36: =J20-J33 -> 104567.95 | ... BC36: =BC20-BC33 -> 0 | BD36: =SUM(C36:BC36) -> 1376607.4
BD37: =SUM(C37:BC37) -> 0
A38: Расходы | C38: =SUM(C40:C51) -> 7822.42 | D38: =SUM(D40:D51) -> 24441.15 | E38: =SUM(E40:E51) -> 30788.76 | F38: =SUM(F40:F51) -> 45237.75 | G38: =SUM(G40:G51) -> 36813.45 | H38: =SUM(H40:H51) -> 30751.44 | I38: =SUM(I40:I51) -> 29078.31 | J38: =SUM(J40:J51) -> 28932.88 | ... BC38: =SUM(BC40:BC51) -> 0 | BD38: =SUM(C38:BC38) -> 464812.7
A39: % расходы | C39: =C38/C14 -> 0.16016093 | D39: =D38/D14 -> 0.14860642 | E39: =E38/E14 -> 0.14056035 | F39: =F38/F14 -> 0.23440706 | G39: =G38/G14 -> 0.1948678 | H39: =H38/H14 -> 0.14090846 | I39: =I38/I14 -> 0.12534024 | J39: =J38/J14 -> 0.13818491 | ... BC39: =BC38/BC14 -> #DIV/0!
A40: Логистика ВБ | C40: 4739 | D40: 19181 | E40: 25734 | F40: 26309 | G40: 31507 | H40: 24880 | I40: 23367 | J40: 23404 | K40: 24588 | L40: 25825 | M40: 23828 | N40: 29199 | O40: 23313 | P40: 15438 | Q40: 12164 | R40: 11631 | BD40: =SUM(C40:BC40) -> 345107
A41: Продвижение ВБ (взаимозачет) | BD41: =SUM(C41:BC41) -> 0
A42: Эквайринг ВБ | BD42: =SUM(C42:BC42) -> 0
A43: Хранение ВБ | C43: 3083.42 | D43: 5260.15 | E43: 5054.76 | F43: 4906.94 | G43: 5306.45 | H43: 5871.44 | I43: 5711.31 | J43: 5528.88 | K43: 6199.06 | L43: 9207.89 | M43: 8952.1 | N43: 8539.65 | O43: 8261.29 | P43: 8068.41 | Q43: 7920.75 | R43: 7771.39 | BD43: =SUM(C43:BC43) -> 105643.89
A44: Штрафы ВБ | F44: 741 | Q44: 40 | BD44: =SUM(C44:BC44) -> 781
A45: Платная приемка ВБ | F45: 13280.81 | BD45: =SUM(C45:BC45) -> 13280.81
BD46: =SUM(C46:BC46) -> 0
A47: Контент | BD47: =SUM(C47:BC47) -> 0
A48: Аренда офиса | BD48: =SUM(C48:BC48) -> 0
A49: Реклама внешняя | BD49: =SUM(C49:BC49) -> 0
A50: Подписка Аналитика | BD50: =SUM(C50:BC50) -> 0
A51: Прочие | BD51: =SUM(C51:BC51) -> 0
BD52: =SUM(C52:BC52) -> 0
A53: Прибыль до налогообложения | C53: =C36+C31-C38 -> 17300.58 | D53: =D36+D31-D38 -> 55985.43 | E53: =E36+E31-E38 -> 75838.12 | F53: =F36+F31-F38 -> 48978.02 | G53: =G36+G31-G38 -> 56812.67 | H53: =H36+H31-H38 -> 75486.16 | I53: =I36+I31-I38 -> 86138.4 | J53: =J36+J31-J38 -> 75635.07 | ... BC53: =BC36+BC31-BC38 -> 0 | BD53: =SUM(C53:BC53) -> 912213.36
BD54: =SUM(C54:BC54) -> 0
A55: Налоги начисленные | B55: УСН 6% | C55: =C15*6% -> 2066.7 | D55: =D15*6% -> 6766.74 | E55: =E15*6% -> 8835.36 | F55: =F15*6% -> 7870.92 | G55: =G15*6% -> 7566.66 | H55: =H15*6% -> 8579.28 | I55: =I15*6% -> 9120.84 | J55: =J15*6% -> 8212.44 | ... BC55: =BC15*6% -> 0 | BD55: =SUM(C55:BC55) -> 113741.46
BD56: =SUM(C56:BC56) -> 0
A57: Чистая прибыль | C57: =C53-C55 -> 15233.88 | D57: =D53-D55 -> 49218.69 | E57: =E53-E55 -> 67002.76 | F57: =F53-F55 -> 41107.1 | G57: =G53-G55 -> 49246.01 | H57: =H53-H55 -> 66906.88 | I57: =I53-I55 -> 77017.56 | J57: =J53-J55 -> 67422.63 | ... BC57: =BC53-BC55 -> 0 | BD57: =SUM(C57:BC57) -> 798471.9
A58: Рентабельность вложений | C58: =C57/C33 -> 1.6553167 | D58: =D57/D33 -> 1.4448463 | E58: =E57/E33 -> 1.4461394 | F58: =F57/F33 -> 1.0161644 | G58: =G57/G33 -> 1.2744678 | H58: =H57/H33 -> 1.4551934 | I58: =I57/I33 -> 1.68761 | J58: =J57/J33 -> 1.7199984 | ... BD58: =BD57/BD33 -> 1.4164917
A59: Маржинальность | C59: =C57/C14 -> 0.31190762 | D59: =D57/D14 -> 0.29925816 | E59: =E57/E14 -> 0.30588862 | F59: =F57/F14 -> 0.2130034 | G59: =G57/G14 -> 0.26067814 | H59: =H57/H14 -> 0.30657899 | I59: =I57/I14 -> 0.3319794 | J59: =J57/J14 -> 0.32201392 | ... BD59: =BD57/BD14 -> 0.28406545
A60: Выплата диведентов: | C60: ='CF (нед)'!C38 -> 0 | D60: ='CF (нед)'!D38 -> 0 | E60: ='CF (нед)'!E38 -> 0 | F60: ='CF (нед)'!F38 -> 0 | G60: ='CF (нед)'!G38 -> 0 | H60: ='CF (нед)'!H38 -> 0 | I60: ='CF (нед)'!I38 -> 0 | J60: ='CF (нед)'!J38 -> 0 | ... BC60: ='CF (нед)'!BC38 -> 0 | BD60: =SUM(C60:BB60) -> 0
A62: ='PL WB'!A62 -> Остаток денежных средств на конец периода | C62: ='CF (нед)'!C42 -> 1994177.9 | D62: ='CF (нед)'!D42 -> 2100356.8 | E62: ='CF (нед)'!E42 -> 2234359.4 | F62: ='CF (нед)'!F42 -> 2340085.2 | G62: ='CF (нед)'!G42 -> 2444316.6 | H62: ='CF (нед)'!H42 -> 2568251.9 | I62: ='CF (нед)'!I42 -> 2701831.8 | J62: ='CF (нед)'!J42 -> 2827470.9 | ... BC62: ='CF (нед)'!BC42 -> 3539892.4
G63: =G62-'PL WB'!C62 -> 17364.73 | K63: =K62-'PL WB'!D62 -> 31050.17 | O63: =O62-'PL WB'!E62 -> 39546.24 | S63: =S62-'PL WB'!F62 -> 42310.91 | X63: =X62-'PL WB'!G62 -> 42310.91 | AB63: =AB62-'PL WB'!H62 -> 42310.91 | AF63: =AF62-'PL WB'!I62 -> 42310.91 | AK63: =AK62-'PL WB'!J62 -> 42310.91 | AO63: =AO62-'PL WB'!K62 -> 42310.91 | AT63: =AT62-'PL WB'!L62 -> 42310.91 | AX63: =AX62-'PL WB'!M62 -> 42310.91 | BB63: 3023049.1 | BC63: =BC62-'PL WB'!O62 -> 3539892.4
A64: Накопленный финансовый результат | C64: =C57+3023049.0734-C60 -> 3038283 | D64: =D57+C64-D60 -> 3087501.6 | E64: =E57+D64-E60 -> 3154504.4 | F64: =F57+E64-F60 -> 3195611.5 | G64: =G57+F64-G60 -> 3244857.5 | H64: =H57+G64-H60 -> 3311764.4 | I64: =I57+H64-I60 -> 3388782 | J64: =J57+I64-J60 -> 3456204.6 | K64: =K57+J64-K60 -> 3526295.7 | ... BB64: =BB57+BA64-BB60 -> 3821521 | BC64: 3023049.1
G65: =G64-'PL WB'!C64 -> 0 | K65: =K64-'PL WB'!D64 -> 5770.44 | O65: =O64-'PL WB'!E64 -> 11049.51 | S65: =S64-'PL WB'!F64 -> 13439.18 | X65: =X64-'PL WB'!G64 -> 13439.18 | AB65: =AB64-'PL WB'!H64 -> 13439.18 | AF65: =AF64-'PL WB'!I64 -> 13439.18 | AK65: =AK64-'PL WB'!J64 -> 13439.18 | AO65: =AO64-'PL WB'!K64 -> 13439.18 | AT65: =AT64-'PL WB'!L64 -> 13439.18 | AX65: =AX64-'PL WB'!M64 -> 13439.18 | BB65: =BB64-'PL WB'!N64 -> 13439.18 | BC65: =BC64-'PL WB'!O64 -> 3023049.1
A66: Серые нули (стр 63, 65) - это проверки между листами! Если не ноль - ищем ошибку
B68: Сумма вложений с начала 2023 | C68: =SUM('CF (нед)'!$C$29:C29) -> 0 | D68: =SUM('CF (нед)'!$C$29:D29) -> 0 | E68: =SUM('CF (нед)'!$C$29:E29) -> 0 | F68: =SUM('CF (нед)'!$C$29:F29) -> 0 | G68: =SUM('CF (нед)'!$C$29:G29) -> 0 | H68: =SUM('CF (нед)'!$C$29:H29) -> 0 | I68: =SUM('CF (нед)'!$C$29:I29) -> 0 | J68: =SUM('CF (нед)'!$C$29:J29) -> 0 | ... BC68: =SUM('CF (нед)'!$C$29:BC29) -> 0
B69: Сумма себестоимости за 16 нед | C69: =SUM($C$33:C33) -> 9203 | D69: =SUM($C$33:D33) -> 43268 | E69: =SUM($C$33:E33) -> 89600.16 | F69: =SUM($C$33:F33) -> 130053.36 | G69: =SUM($C$33:G33) -> 168693.81 | H69: =SUM($C$33:H33) -> 214671.81 | I69: =SUM($C$33:I33) -> 260308.87 | J69: =SUM($C$33:J33) -> 299508.11 | ... Q69: =SUM($C$33:Q33) -> 544702.03 | R69: =SUM(C33:R33) -> 563696.83 | S69: =SUM(D33:S33) -> 554493.83 | T69: =SUM(E33:T33) -> 520428.83 | U69: =SUM(F33:U33) -> 474096.67 | V69: =SUM(G33:V33) -> 433643.47 | W69: =SUM(H33:W33) -> 395003.02 | X69: =SUM(I33:X33) -> 349025.02 | Y69: =SUM(J33:Y33) -> 303387.96 | ... BC69: =SUM(AN33:BC33) -> 0
B70: Прибыль за 16 нед | C70: =SUM($C$57:C57) -> 15233.88 | D70: =SUM($C$57:D57) -> 64452.57 | E70: =SUM($C$57:E57) -> 131455.33 | F70: =SUM($C$57:F57) -> 172562.43 | G70: =SUM($C$57:G57) -> 221808.44 | H70: =SUM($C$57:H57) -> 288715.32 | I70: =SUM($C$57:I57) -> 365732.88 | J70: =SUM($C$57:J57) -> 433155.51 | ... Q70: =SUM($C$57:Q57) -> 769536.82 | R70: =SUM(C57:R57) -> 798471.9 | S70: =SUM(D57:S57) -> 783238.02 | T70: =SUM(E57:T57) -> 734019.33 | U70: =SUM(F57:U57) -> 667016.57 | V70: =SUM(G57:V57) -> 625909.47 | W70: =SUM(H57:W57) -> 576663.46 | X70: =SUM(I57:X57) -> 509756.58 | Y70: =SUM(J57:Y57) -> 432739.02 | ... BC70: =SUM(AN57:BC57) -> 0
B71: Рентабельность за 16 нед | C71: =C70/C69 -> 1.6553167 | D71: =D70/D69 -> 1.4896129 | E71: =E70/E69 -> 1.4671328 | F71: =F70/F69 -> 1.3268587 | G71: =G70/G69 -> 1.3148582 | H71: =H70/H69 -> 1.3449149 | I71: =I70/I69 -> 1.4049958 | J71: =J70/J69 -> 1.446223 | ... BC71: =BC70/BC69 -> #DIV/0!
B72: Оборачиваемость за 16 нед | C72: =C69/C68 -> #DIV/0! | D72: =D69/D68 -> #DIV/0! | E72: =E69/E68 -> #DIV/0! | F72: =F69/F68 -> #DIV/0! | G72: =G69/G68 -> #DIV/0! | H72: =H69/H68 -> #DIV/0! | I72: =I69/I68 -> #DIV/0! | J72: =J69/J68 -> #DIV/0! | ... BC72: =BC69/BC68 -> #DIV/0!
B73: Оборачиваемость в днях | C73: =(C74*7)/C72 -> #DIV/0! | D73: =(D74*7)/D72 -> #DIV/0! | E73: =(E74*7)/E72 -> #DIV/0! | F73: =(F74*7)/F72 -> #DIV/0! | G73: =(G74*7)/G72 -> #DIV/0! | H73: =(H74*7)/H72 -> #DIV/0! | I73: =(I74*7)/I72 -> #DIV/0! | J73: =(J74*7)/J72 -> #DIV/0! | ... Q73: =(Q74*7)/Q72 -> #DIV/0! | R73: =(16*7)/R72 -> #DIV/0! | S73: =(16*7)/S72 -> #DIV/0! | T73: =(16*7)/T72 -> #DIV/0! | U73: =(16*7)/U72 -> #DIV/0! | V73: =(16*7)/V72 -> #DIV/0! | W73: =(16*7)/W72 -> #DIV/0! | X73: =(16*7)/X72 -> #DIV/0! | Y73: =(16*7)/Y72 -> #DIV/0! | ... BC73: =(16*7)/BC72 -> #DIV/0!
C74: 1 | D74: 2 | E74: 3 | F74: 4 | G74: 5 | H74: 6 | I74: 7 | J74: 8 | K74: 9 | L74: 10 | M74: 11 | N74: 12 | O74: 13 | P74: 14 | Q74: 15 | R74: 16 | S74: далее анализ последних 16 недель
B75: Остаток товара закончится через, дн | C75: =C12*C74*7/C69 -> 1152.3301 | D75: =D12*D74*7/D69 -> 479.17348 | E75: =E12*E74*7/E69 -> 336.23089 | F75: =F12*F74*7/F69 -> 300.15192 | G75: =G12*G74*7/G69 -> 281.23315 | H75: =H12*H74*7/H69 -> 256.20352 | I75: =I12*I74*7/I69 -> 237.90995 | J75: =J12*J74*7/J69 -> 228.98233 | ... R75: =R12*R74*7/R69 -> 190.83839 | S75: =S12*16*7/S69 -> 194.00576 | T75: =T12*16*7/T69 -> 206.70453 | U75: =U12*16*7/U69 -> 226.90519 | V75: =V12*16*7/V69 -> 248.07244 | W75: =W12*16*7/W69 -> 272.33968 | X75: =X12*16*7/X69 -> 308.21571 | Y75: =Y12*16*7/Y69 -> 354.57899 | Z75: =Z12*16*7/Z69 -> 407.18996 | ... BC75: =BC12*16*7/BC69 -> #DIV/0!
B76: Дата распродажи в 0 | C76: =TODAY( )+C75 -> 47284.33 | D76: =TODAY( )+D75 -> 46611.173 | E76: =TODAY( )+E75 -> 46468.231 | F76: =TODAY( )+F75 -> 46432.152 | G76: =TODAY( )+G75 -> 46413.233 | H76: =TODAY( )+H75 -> 46388.204 | I76: =TODAY( )+I75 -> 46369.91 | J76: =TODAY( )+J75 -> 46360.982 | ... BC76: =TODAY( )+BC75 -> NaN | BD76: 5

Sheet PL WB
A1: Заполняем PL и CF еженедельный!
A2: Прибыли и убытки | C2: 2025
C3: Январь | D3: Февраль | E3: Март | F3: Апрель | G3: Май | H3: Июнь | I3: Июль | J3: Август | K3: Сентябрь | L3: Октябрь | M3: Ноябрь | N3: Декабрь
A4: Товарооборот | O4: =SUM(C4:N4) -> 0
A5: Остаток товара по цене закупки | C5: ='PL WB (нед)'!C5 -> 1331789.1 | D5: =C12 -> 1355494.1 | E5: =D12 -> 1183913.3 | F5: =E12 -> 1023548.9 | G5: =F12 -> 960491.03 | H5: =G12 -> 960491.03 | I5: =H12 -> 960491.03 | J5: =I12 -> 960491.03 | K5: =J12 -> 960491.03 | ... N5: =M12 -> 960491.03 | O5: =SUM(C5:N5)/12 -> 1048222.8
O6: =SUM(C6:N6) -> 0
B7: Продажи шт | C7: =SUM('PL WB (нед)'!C7:G7) -> 1359 | D7: =SUM('PL WB (нед)'!H7:K7) -> 1329 | E7: =SUM('PL WB (нед)'!L7:O7) -> 1307 | F7: =SUM('PL WB (нед)'!P7:S7) -> 481 | G7: =SUM('PL WB (нед)'!T7:X7) -> 0 | H7: =SUM('PL WB (нед)'!Y7:AB7) -> 0 | I7: =SUM('PL WB (нед)'!AC7:AF7) -> 0 | J7: =SUM('PL WB (нед)'!AG7:AK7) -> 0 | K7: =SUM('PL WB (нед)'!AL7:AO7) -> 0 | L7: =SUM('PL WB (нед)'!AP7:AT7) -> 0 | M7: =SUM('PL WB (нед)'!AU7:AX7) -> 0 | N7: =SUM('PL WB (нед)'!AY7:BC7) -> 0 | O7: =SUM(C7:N7) -> 4476
B8: Отгрузки по себестоимости | C8: =C33 -> 168693.81 | D8: =D33 -> 171580.72 | E8: =E33 -> 160364.4 | F8: =F33 -> 63057.9 | G8: =G33 -> 0 | H8: =H33 -> 0 | I8: =I33 -> 0 | J8: =J33 -> 0 | ... N8: =N33 -> 0 | O8: =SUM(C8:N8) -> 563696.83
O9: =SUM(C9:N9) -> 0
A10: Поступление товара, р | C10: =SUM('PL WB (нед)'!C10:G10) -> 192398.77 | D10: =SUM('PL WB (нед)'!H10:K10) -> 0 | E10: =SUM('PL WB (нед)'!L10:O10) -> 0 | F10: =SUM('PL WB (нед)'!P10:S10) -> 0 | G10: =SUM('PL WB (нед)'!T10:X10) -> 0 | H10: =SUM('PL WB (нед)'!Y10:AB10) -> 0 | I10: =SUM('PL WB (нед)'!AC10:AF10) -> 0 | J10: =SUM('PL WB (нед)'!AG10:AK10) -> 0 | K10: =SUM('PL WB (нед)'!AL10:AO10) -> 0 | L10: =SUM('PL WB (нед)'!AP10:AT10) -> 0 | M10: =SUM('PL WB (нед)'!AU10:AX10) -> 0 | N10: =SUM('PL WB (нед)'!AY10:BC10) -> 0 | O10: =SUM(C10:N10) -> 192398.77
A11: Поступление товара, шт | C11: =SUM('PL WB (нед)'!C11:G11) -> 1294 | D11: =SUM('PL WB (нед)'!H11:K11) -> 0 | E11: =SUM('PL WB (нед)'!L11:O11) -> 0 | F11: =SUM('PL WB (нед)'!P11:S11) -> 0 | G11: =SUM('PL WB (нед)'!T11:X11) -> 0 | H11: =SUM('PL WB (нед)'!Y11:AB11) -> 0 | I11: =SUM('PL WB (нед)'!AC11:AF11) -> 0 | J11: =SUM('PL WB (нед)'!AG11:AK11) -> 0 | K11: =SUM('PL WB (нед)'!AL11:AO11) -> 0 | L11: =SUM('PL WB (нед)'!AP11:AT11) -> 0 | M11: =SUM('PL WB (нед)'!AU11:AX11) -> 0 | N11: =SUM('PL WB (нед)'!AY11:BC11) -> 0 | O11: =SUM(C11:N11) -> 1294
A12: Доступно на складе по цене закупки | C12: =C10-C8+C5 -> 1355494.1 | D12: =D10-D8+D5 -> 1183913.3 | E12: =E10-E8+E5 -> 1023548.9 | F12: =F10-F8+F5 -> 960491.03 | G12: =G10-G8+G5 -> 960491.03 | H12: =H10-H8+H5 -> 960491.03 | I12: =I10-I8+I5 -> 960491.03 | J12: =J10-J8+J5 -> 960491.03 | ... N12: =N10-N8+N5 -> 960491.03 | O12: =SUM(C12:N12) -> 12207376
A13: Доступно на складе, шт | C13: ='PL WB (нед)'!G13 -> 9007 | D13: =C13-D7-D27+D11+D23 -> 7678 | E13: =D13-E7-E27+E11+E23 -> 6378 | F13: =E13-F7-F27+F11+F23 -> 5900 | G13: =F13-G7-G27+G11+G23 -> 5900 | H13: =G13-H7-H27+H11+H23 -> 5897 | I13: =H13-I7-I27+I11+I23 -> 5897 | J13: =I13-J7-J27+J11+J23 -> 5897 | K13: =J13-K7-K27+K11+K23 -> 5897 | ... N13: =M13-N7-N27+N11+N23 -> 5897 | O13: =SUM(C13:N13) -> 76142
A14: Продано товаров WB по цене в карточке | C14: =SUM('PL WB (нед)'!C14:G14) -> 814256 | D14: =SUM('PL WB (нед)'!H14:K14) -> 879399 | E14: =SUM('PL WB (нед)'!L14:O14) -> 772334 | F14: =SUM('PL WB (нед)'!P14:S14) -> 344884 | G14: =SUM('PL WB (нед)'!T14:X14) -> 0 | H14: =SUM('PL WB (нед)'!Y14:AB14) -> 0 | I14: =SUM('PL WB (нед)'!AC14:AF14) -> 0 | J14: =SUM('PL WB (нед)'!AG14:AK14) -> 0 | K14: =SUM('PL WB (нед)'!AL14:AO14) -> 0 | L14: =SUM('PL WB (нед)'!AP14:AT14) -> 0 | M14: =SUM('PL WB (нед)'!AU14:AX14) -> 0 | N14: =SUM('PL WB (нед)'!AY14:BC14) -> 0 | O14: =SUM(C14:N14) -> 2810873
A15: Продано товаров WB ВБ реализовал-ПРОДАЖИ | C15: =SUM('PL WB (нед)'!C15:G15) -> 551773 | D15: =SUM('PL WB (нед)'!H15:K15) -> 577044 | E15: =SUM('PL WB (нед)'!L15:O15) -> 527907 | F15: =SUM('PL WB (нед)'!P15:S15) -> 238967 | G15: =SUM('PL WB (нед)'!T15:X15) -> 0 | H15: =SUM('PL WB (нед)'!Y15:AB15) -> 0 | I15: =SUM('PL WB (нед)'!AC15:AF15) -> 0 | J15: =SUM('PL WB (нед)'!AG15:AK15) -> 0 | K15: =SUM('PL WB (нед)'!AL15:AO15) -> 0 | L15: =SUM('PL WB (нед)'!AP15:AT15) -> 0 | M15: =SUM('PL WB (нед)'!AU15:AX15) -> 0 | N15: =SUM('PL WB (нед)'!AY15:BC15) -> 0 | O15: =SUM(C15:N15) -> 1895691
O16: =SUM(C16:N16) -> 0
A17: Комиссия ВБ | C17: =C14-C20 -> 245543.84 | D17: =D14-D20 -> 272207.81 | E17: =E14-E20 -> 244784.59 | F17: =F14-F20 -> 108032.54 | G17: =G14-G20 -> 0 | H17: =H14-H20 -> 0 | I17: =I14-I20 -> 0 | J17: =J14-J20 -> 0 | ... M17: =M14-M20 -> 0 | N17: =N15-N20 -> 0 | O17: =SUM(C17:N17) -> 870568.78
A18: % комиссии | C18: =C17/C14 -> 0.30155607 | D18: =D17/D15 -> 0.471728 | E18: =E17/E15 -> 0.46368885 | F18: =F17/F15 -> 0.45208142 | G18: =G17/G15 -> #DIV/0! | H18: =H17/H15 -> #DIV/0! | I18: =I17/I15 -> #DIV/0! | J18: =J17/J15 -> #DIV/0! | K18: =K17/K15 -> #DIV/0! | ... N18: =N17/N15 -> #DIV/0! | O18: =SUM(C18:N18) -> #DIV/0!
O19: =SUM(C19:N19) -> 0
A20: Выручка от реализации (к перечислению за товар), руб | C20: =SUM('PL WB (нед)'!C20:G20) -> 568712.16 | D20: =SUM('PL WB (нед)'!H20:K20) -> 607191.19 | E20: =SUM('PL WB (нед)'!L20:O20) -> 527549.41 | F20: =SUM('PL WB (нед)'!P20:S20) -> 236851.46 | G20: =SUM('PL WB (нед)'!T20:X20) -> 0 | H20: =SUM('PL WB (нед)'!Y20:AB20) -> 0 | I20: =SUM('PL WB (нед)'!AC20:AF20) -> 0 | J20: =SUM('PL WB (нед)'!AG20:AK20) -> 0 | K20: =SUM('PL WB (нед)'!AL20:AO20) -> 0 | L20: =SUM('PL WB (нед)'!AP20:AT20) -> 0 | M20: =SUM('PL WB (нед)'!AU20:AX20) -> 0 | N20: =SUM('PL WB (нед)'!AY20:BC20) -> 0 | O20: =SUM(C20:N20) -> 1940304.2
O21: =SUM(C21:N21) -> 0
A22: Возвраты, руб | C22: =SUM('PL WB (нед)'!C22:G22) -> 0 | D22: =SUM('PL WB (нед)'!H22:K22) -> 0 | E22: =SUM('PL WB (нед)'!L22:O22) -> 4290 | F22: =SUM('PL WB (нед)'!P22:S22) -> 2045 | G22: =SUM('PL WB (нед)'!T22:X22) -> 0 | H22: =SUM('PL WB (нед)'!Y22:AB22) -> 0 | I22: =SUM('PL WB (нед)'!AC22:AF22) -> 0 | J22: =SUM('PL WB (нед)'!AG22:AK22) -> 0 | K22: =SUM('PL WB (нед)'!AL22:AO22) -> 0 | L22: =SUM('PL WB (нед)'!AP22:AT22) -> 0 | M22: =SUM('PL WB (нед)'!AU22:AX22) -> 0 | N22: =SUM('PL WB (нед)'!AY22:BC22) -> 0 | O22: =SUM(C22:N22) -> 6335
A23: Возвраты, шт | C23: =SUM('PL WB (нед)'!C23:G23) -> 0 | D23: =SUM('PL WB (нед)'!H23:K23) -> 0 | E23: =SUM('PL WB (нед)'!L23:O23) -> 7 | F23: =SUM('PL WB (нед)'!P23:S23) -> 4 | G23: =SUM('PL WB (нед)'!T23:X23) -> 0 | H23: =SUM('PL WB (нед)'!Y23:AB23) -> 0 | I23: =SUM('PL WB (нед)'!AC23:AF23) -> 0 | J23: =SUM('PL WB (нед)'!AG23:AK23) -> 0 | K23: =SUM('PL WB (нед)'!AL23:AO23) -> 0 | L23: =SUM('PL WB (нед)'!AP23:AT23) -> 0 | M23: =SUM('PL WB (нед)'!AU23:AX23) -> 0 | N23: =SUM('PL WB (нед)'!AY23:BC23) -> 0 | O23: =SUM(C23:N23) -> 11
A24: % возвратов | C24: =C22/C14 -> 0 | D24: =D22/D20 -> 0 | E24: =E22/E20 -> 0.0081319397 | F24: =F22/F20 -> 0.0086341034 | G24: =G22/G20 -> #DIV/0! | H24: =H22/H20 -> #DIV/0! | I24: =I22/I20 -> #DIV/0! | J24: =J22/J20 -> #DIV/0! | K24: =K22/K20 -> #DIV/0! | ... O24: =O22/O20 -> 0.0032649519
A26: Брак, руб
A27: Брак, шт | C27: =SUM('PL WB (нед)'!C27:G27) -> 0 | D27: =SUM('PL WB (нед)'!H27:K27) -> 0 | E27: =SUM('PL WB (нед)'!L27:O27) -> 0 | F27: =SUM('PL WB (нед)'!P27:S27) -> 1 | G27: =SUM('PL WB (нед)'!T27:X27) -> 0 | H27: =SUM('PL WB (нед)'!Y27:AB27) -> 3 | I27: =SUM('PL WB (нед)'!AC27:AF27) -> 0 | J27: =SUM('PL WB (нед)'!AG27:AK27) -> 0 | K27: =SUM('PL WB (нед)'!AL27:AO27) -> 0 | L27: =SUM('PL WB (нед)'!AP27:AT27) -> 0 | M27: =SUM('PL WB (нед)'!AU27:AX27) -> 0 | N27: =SUM('PL WB (нед)'!AY27:BB27) -> 0
A28: % брака | C28: =C27/C7 -> 0 | D28: =D27/D7 -> 0 | E28: =E27/E7 -> 0 | F28: =F27/F7 -> 0.0020790021 | G28: =G27/G7 -> #DIV/0! | H28: =H27/H7 -> #DIV/0! | I28: =I27/I7 -> #DIV/0! | J28: =J27/J7 -> #DIV/0! | ... N28: =N27/N7 -> #DIV/0!
A30: Поступление на счет от ВБ | C30: =C20+C31-SUM(C40:C45)-C42 -> 423608.63 | D30: =D20+D31-SUM(D40:D45)-D42 -> 487641.5 | E30: =E20+E31-SUM(E40:E45)-E42 -> 390775.78 | F30: =F20+F31-SUM(F40:F45)-F42 -> 173884.28 | G30: =G20+G31-SUM(G40:G45)-G42 -> 0 | H30: =H20+H31-SUM(H40:H45)-H42 -> 0 | I30: =I20+I31-SUM(I40:I45)-I42 -> 0 | J30: =J20+J31-SUM(J40:J45)-J42 -> 0 | ... N30: =N20+N31-SUM(N40:N45)-N42 -> 0 | O30: =SUM(C30:N30) -> 1475910.2
A31: в т.ч. Прочие доходы | C31: =SUM('PL WB (нед)'!C31:G31) -> 0 | D31: =SUM('PL WB (нед)'!H31:K31) -> 0 | E31: =SUM('PL WB (нед)'!L31:O31) -> 352.3 | F31: =SUM('PL WB (нед)'!P31:S31) -> 66.37 | G31: =SUM('PL WB (нед)'!T31:X31) -> 0 | H31: =SUM('PL WB (нед)'!Y31:AB31) -> 0 | I31: =SUM('PL WB (нед)'!AC31:AF31) -> 0 | J31: =SUM('PL WB (нед)'!AG31:AK31) -> 0 | K31: =SUM('PL WB (нед)'!AL31:AO31) -> 0 | L31: =SUM('PL WB (нед)'!AP31:AT31) -> 0 | M31: =SUM('PL WB (нед)'!AU31:AX31) -> 0 | N31: =SUM('PL WB (нед)'!AY31:BB31) -> 0
A33: Себестоимость | C33: =SUM('PL WB (нед)'!C33:G33) -> 168693.81 | D33: =SUM('PL WB (нед)'!H33:K33) -> 171580.72 | E33: =SUM('PL WB (нед)'!L33:O33) -> 160364.4 | F33: =SUM('PL WB (нед)'!P33:S33) -> 63057.9 | G33: =SUM('PL WB (нед)'!T33:X33) -> 0 | H33: =SUM('PL WB (нед)'!Y33:AB33) -> 0 | I33: =SUM('PL WB (нед)'!AC33:AF33) -> 0 | J33: =SUM('PL WB (нед)'!AG33:AK33) -> 0 | K33: =SUM('PL WB (нед)'!AL33:AO33) -> 0 | L33: =SUM('PL WB (нед)'!AP33:AT33) -> 0 | M33: =SUM('PL WB (нед)'!AU33:AX33) -> 0 | N33: =SUM('PL WB (нед)'!AY33:BC33) -> 0 | O33: =SUM('PL WB (нед)'!AZ33:BD33) -> 563696.83
A34: % себестоимости | C34: =C33/C14 -> 0.2071754 | D34: =D33/D15 -> 0.29734426 | E34: =E33/E15 -> 0.30377396 | F34: =F33/F15 -> 0.26387702 | G34: =G33/G15 -> #DIV/0! | H34: =H33/H15 -> #DIV/0! | I34: =I33/I15 -> #DIV/0! | J34: =J33/J15 -> #DIV/0! | K34: =K33/K15 -> #DIV/0! | ... O34: =O33/O15 -> 0.29735692
A36: Валовая прибыль | C36: =C20-C33 -> 400018.35 | D36: =D20-D33 -> 435610.47 | E36: =E20-E33 -> 367185.01 | F36: =F20-F33 -> 173793.56 | G36: =G20-G33 -> 0 | H36: =H20-H33 -> 0 | I36: =I20-I33 -> 0 | J36: =J20-J33 -> 0 | ... O36: =O20-O33 -> 1376607.4
A38: Расходы | C38: =SUM(C40:C51) -> 145103.53 | D38: =SUM(D40:D51) -> 119549.69 | E38: =SUM(E40:E51) -> 137125.93 | F38: =SUM(F40:F51) -> 63033.55 | G38: =SUM(G40:G51) -> 0 | H38: =SUM(H40:H51) -> 0 | I38: =SUM(I40:I51) -> 0 | J38: =SUM(J40:J51) -> 0 | ... N38: =SUM(N40:N51) -> 0 | O38: =SUM(C38:N38) -> 464812.7
A39: % расходы | C39: =C38/C14 -> 0.17820382 | D39: =D38/D14 -> 0.13594476 | E39: =E38/E14 -> 0.17754745 | F39: =F38/F14 -> 0.18276739 | G39: =G38/G14 -> #DIV/0! | H39: =H38/H14 -> #DIV/0! | I39: =I38/I14 -> #DIV/0! | J39: =J38/J14 -> #DIV/0! | ... O39: =O38/O14 -> 0.1653624
A40: Логистика ВБ | C40: =SUM('PL WB (нед)'!C40:G40) -> 107470 | D40: =SUM('PL WB (нед)'!H40:K40) -> 96239 | E40: =SUM('PL WB (нед)'!L40:O40) -> 102165 | F40: =SUM('PL WB (нед)'!P40:S40) -> 39233 | G40: =SUM('PL WB (нед)'!T40:X40) -> 0 | H40: =SUM('PL WB (нед)'!Y40:AB40) -> 0 | I40: =SUM('PL WB (нед)'!AC40:AF40) -> 0 | J40: =SUM('PL WB (нед)'!AG40:AK40) -> 0 | K40: =SUM('PL WB (нед)'!AL40:AO40) -> 0 | L40: =SUM('PL WB (нед)'!AP40:AT40) -> 0 | M40: =SUM('PL WB (нед)'!AU40:AX40) -> 0 | N40: =SUM('PL WB (нед)'!AY40:BC40) -> 0 | O40: =SUM(C40:N40) -> 345107
A41: Продвижение ВБ (взаимозачет) | C41: =SUM('PL WB (нед)'!C41:G41) -> 0 | D41: =SUM('PL WB (нед)'!H41:K41) -> 0 | E41: =SUM('PL WB (нед)'!L41:O41) -> 0 | F41: =SUM('PL WB (нед)'!P41:S41) -> 0 | G41: =SUM('PL WB (нед)'!T41:X41) -> 0 | H41: =SUM('PL WB (нед)'!Y41:AB41) -> 0 | I41: =SUM('PL WB (нед)'!AC41:AF41) -> 0 | J41: =SUM('PL WB (нед)'!AG41:AK41) -> 0 | K41: =SUM('PL WB (нед)'!AL41:AO41) -> 0 | L41: =SUM('PL WB (нед)'!AP41:AT41) -> 0 | M41: =SUM('PL WB (нед)'!AU41:AX41) -> 0 | N41: =SUM('PL WB (нед)'!AY41:BC41) -> 0 | O41: =SUM(C41:N41) -> 0
A42: Эквайринг ВБ | C42: =SUM('PL WB (нед)'!C42:G42) -> 0 | D42: =SUM('PL WB (нед)'!H42:K42) -> 0 | E42: =SUM('PL WB (нед)'!L42:O42) -> 0 | F42: =SUM('PL WB (нед)'!P42:S42) -> 0 | G42: =SUM('PL WB (нед)'!T42:X42) -> 0 | H42: =SUM('PL WB (нед)'!Y42:AB42) -> 0 | I42: =SUM('PL WB (нед)'!AC42:AF42) -> 0 | J42: =SUM('PL WB (нед)'!AG42:AK42) -> 0 | K42: =SUM('PL WB (нед)'!AL42:AO42) -> 0 | L42: =SUM('PL WB (нед)'!AP42:AT42) -> 0 | M42: =SUM('PL WB (нед)'!AU42:AX42) -> 0 | N42: =SUM('PL WB (нед)'!AY42:BC42) -> 0 | O42: =SUM(C42:N42) -> 0
A43: Хранение ВБ | C43: =SUM('PL WB (нед)'!C43:G43) -> 23611.72 | D43: =SUM('PL WB (нед)'!H43:K43) -> 23310.69 | E43: =SUM('PL WB (нед)'!L43:O43) -> 34960.93 | F43: =SUM('PL WB (нед)'!P43:S43) -> 23760.55 | G43: =SUM('PL WB (нед)'!T43:X43) -> 0 | H43: =SUM('PL WB (нед)'!Y43:AB43) -> 0 | I43: =SUM('PL WB (нед)'!AC43:AF43) -> 0 | J43: =SUM('PL WB (нед)'!AG43:AK43) -> 0 | K43: =SUM('PL WB (нед)'!AL43:AO43) -> 0 | L43: =SUM('PL WB (нед)'!AP43:AT43) -> 0 | M43: =SUM('PL WB (нед)'!AU43:AX43) -> 0 | N43: =SUM('PL WB (нед)'!AY43:BC43) -> 0 | O43: =SUM(C43:N43) -> 105643.89
A44: Штрафы ВБ | C44: =SUM('PL WB (нед)'!C44:G44) -> 741 | D44: =SUM('PL WB (нед)'!H44:K44) -> 0 | E44: =SUM('PL WB (нед)'!L44:O44) -> 0 | F44: =SUM('PL WB (нед)'!P44:S44) -> 40 | G44: =SUM('PL WB (нед)'!T44:X44) -> 0 | H44: =SUM('PL WB (нед)'!Y44:AB44) -> 0 | I44: =SUM('PL WB (нед)'!AC44:AF44) -> 0 | J44: =SUM('PL WB (нед)'!AG44:AK44) -> 0 | K44: =SUM('PL WB (нед)'!AL44:AO44) -> 0 | L44: =SUM('PL WB (нед)'!AP44:AT44) -> 0 | M44: =SUM('PL WB (нед)'!AU44:AX44) -> 0 | N44: =SUM('PL WB (нед)'!AY44:BC44) -> 0 | O44: =SUM(C44:N44) -> 781
A45: Платная приемка ВБ | C45: =SUM('PL WB (нед)'!C45:G45) -> 13280.81 | D45: =SUM('PL WB (нед)'!H45:K45) -> 0 | E45: =SUM('PL WB (нед)'!L45:O45) -> 0 | F45: =SUM('PL WB (нед)'!P45:S45) -> 0 | G45: =SUM('PL WB (нед)'!T45:X45) -> 0 | H45: =SUM('PL WB (нед)'!Y45:AB45) -> 0 | I45: =SUM('PL WB (нед)'!AC45:AF45) -> 0 | J45: =SUM('PL WB (нед)'!AG45:AK45) -> 0 | K45: =SUM('PL WB (нед)'!AL45:AO45) -> 0 | L45: =SUM('PL WB (нед)'!AP45:AT45) -> 0 | M45: =SUM('PL WB (нед)'!AU45:AX45) -> 0 | N45: =SUM('PL WB (нед)'!AY45:BC45) -> 0 | O45: =SUM(C45:N45) -> 13280.81
C46: =SUM('PL WB (нед)'!C46:G46) -> 0 | D46: =SUM('PL WB (нед)'!H46:K46) -> 0 | E46: =SUM('PL WB (нед)'!L46:O46) -> 0 | F46: =SUM('PL WB (нед)'!P46:S46) -> 0 | G46: =SUM('PL WB (нед)'!T46:X46) -> 0 | H46: =SUM('PL WB (нед)'!Y46:AB46) -> 0 | I46: =SUM('PL WB (нед)'!AC46:AF46) -> 0 | J46: =SUM('PL WB (нед)'!AG46:AK46) -> 0 | K46: =SUM('PL WB (нед)'!AL46:AO46) -> 0 | L46: =SUM('PL WB (нед)'!AP46:AT46) -> 0 | M46: =SUM('PL WB (нед)'!AU46:AX46) -> 0 | N46: =SUM('PL WB (нед)'!AY46:BC46) -> 0
A47: Контент | C47: =SUM('PL WB (нед)'!C47:G47) -> 0 | D47: =SUM('PL WB (нед)'!H47:K47) -> 0 | E47: =SUM('PL WB (нед)'!L47:O47) -> 0 | F47: =SUM('PL WB (нед)'!P47:S47) -> 0 | G47: =SUM('PL WB (нед)'!T47:X47) -> 0 | H47: =SUM('PL WB (нед)'!Y47:AB47) -> 0 | I47: =SUM('PL WB (нед)'!AC47:AF47) -> 0 | J47: =SUM('PL WB (нед)'!AG47:AK47) -> 0 | K47: =SUM('PL WB (нед)'!AL47:AO47) -> 0 | L47: =SUM('PL WB (нед)'!AP47:AT47) -> 0 | M47: =SUM('PL WB (нед)'!AU47:AX47) -> 0 | N47: =SUM('PL WB (нед)'!AY47:BC47) -> 0
A48: Аренда офиса | C48: =SUM('PL WB (нед)'!C48:G48) -> 0 | D48: =SUM('PL WB (нед)'!H48:K48) -> 0 | E48: =SUM('PL WB (нед)'!L48:O48) -> 0 | F48: =SUM('PL WB (нед)'!P48:S48) -> 0 | G48: =SUM('PL WB (нед)'!T48:X48) -> 0 | H48: =SUM('PL WB (нед)'!Y48:AB48) -> 0 | I48: =SUM('PL WB (нед)'!AC48:AF48) -> 0 | J48: =SUM('PL WB (нед)'!AG48:AK48) -> 0 | K48: =SUM('PL WB (нед)'!AL48:AO48) -> 0 | L48: =SUM('PL WB (нед)'!AP48:AT48) -> 0 | M48: =SUM('PL WB (нед)'!AU48:AX48) -> 0 | N48: =SUM('PL WB (нед)'!AY48:BC48) -> 0
A49: Реклама внешняя | C49: =SUM('PL WB (нед)'!C49:G49) -> 0 | D49: =SUM('PL WB (нед)'!H49:K49) -> 0 | E49: =SUM('PL WB (нед)'!L49:O49) -> 0 | F49: =SUM('PL WB (нед)'!P49:S49) -> 0 | G49: =SUM('PL WB (нед)'!T49:X49) -> 0 | H49: =SUM('PL WB (нед)'!Y49:AB49) -> 0 | I49: =SUM('PL WB (нед)'!AC49:AF49) -> 0 | J49: =SUM('PL WB (нед)'!AG49:AK49) -> 0 | K49: =SUM('PL WB (нед)'!AL49:AO49) -> 0 | L49: =SUM('PL WB (нед)'!AP49:AT49) -> 0 | M49: =SUM('PL WB (нед)'!AU49:AX49) -> 0 | N49: =SUM('PL WB (нед)'!AY49:BC49) -> 0
A50: Подписка Аналитика | C50: =SUM('PL WB (нед)'!C50:G50) -> 0 | D50: =SUM('PL WB (нед)'!H50:K50) -> 0 | E50: =SUM('PL WB (нед)'!L50:O50) -> 0 | F50: =SUM('PL WB (нед)'!P50:S50) -> 0 | G50: =SUM('PL WB (нед)'!T50:X50) -> 0 | H50: =SUM('PL WB (нед)'!Y50:AB50) -> 0 | I50: =SUM('PL WB (нед)'!AC50:AF50) -> 0 | J50: =SUM('PL WB (нед)'!AG50:AK50) -> 0 | K50: =SUM('PL WB (нед)'!AL50:AO50) -> 0 | L50: =SUM('PL WB (нед)'!AP50:AT50) -> 0 | M50: =SUM('PL WB (нед)'!AU50:AX50) -> 0 | N50: =SUM('PL WB (нед)'!AY50:BC50) -> 0
A51: Прочие | C51: =SUM('PL WB (нед)'!C51:G51) -> 0 | D51: =SUM('PL WB (нед)'!H51:K51) -> 0 | E51: =SUM('PL WB (нед)'!L51:O51) -> 0 | F51: =SUM('PL WB (нед)'!P51:S51) -> 0 | G51: =SUM('PL WB (нед)'!T51:X51) -> 0 | H51: =SUM('PL WB (нед)'!Y51:AB51) -> 0 | I51: =SUM('PL WB (нед)'!AC51:AF51) -> 0 | J51: =SUM('PL WB (нед)'!AG51:AK51) -> 0 | K51: =SUM('PL WB (нед)'!AL51:AO51) -> 0 | L51: =SUM('PL WB (нед)'!AP51:AT51) -> 0 | M51: =SUM('PL WB (нед)'!AU51:AX51) -> 0 | N51: =SUM('PL WB (нед)'!AY51:BC51) -> 0
A53: Прибыль до налогообложения | C53: =C36+C31-C38 -> 254914.82 | D53: =D36+D31-D38 -> 316060.78 | E53: =E36+E31-E38 -> 230411.38 | F53: =F36+F31-F38 -> 110826.38 | G53: =G36+G31-G38 -> 0 | H53: =H36+H31-H38 -> 0 | I53: =I36+I31-I38 -> 0 | J53: =J36+J31-J38 -> 0 | ... N53: =N36+N31-N38 -> 0 | O53: =SUM(C53:N53) -> 912213.36
A55: Налоги начисленные | B55: УСН 6%+1% | C55: =C15*7% -> 38624.11 | D55: =D15*7% -> 40393.08 | E55: =E15*7% -> 36953.49 | F55: =F15*7% -> 16727.69 | G55: =G15*7% -> 0 | H55: =H15*7% -> 0 | I55: =I15*7% -> 0 | J55: =J15*7% -> 0 | ... N55: =N15*7% -> 0 | O55: =SUM(C55:N55) -> 132698.37
A57: Чистая прибыль | C57: =C53-C55 -> 216290.71 | D57: =D53-D55 -> 275667.7 | E57: =E53-E55 -> 193457.89 | F57: =F53-F55 -> 94098.69 | G57: =G53-G55 -> 0 | H57: =H53-H55 -> 0 | I57: =I53-I55 -> 0 | J57: =J53-J55 -> 0 | ... N57: =N53-N55 -> 0 | O57: =SUM(C57:N57) -> 779514.99
A58: Рентабельность вложений | C58: =C57/C33 -> 1.2821497 | D58: =D57/D33 -> 1.6066356 | E58: =E57/E33 -> 1.2063643 | F58: =F57/F33 -> 1.4922585 | G58: =G57/G33 -> #DIV/0! | H58: =H57/H33 -> #DIV/0! | I58: =I57/I33 -> #DIV/0! | J58: =J57/J33 -> #DIV/0! | ... O58: =O57/O33 -> 1.3828621
A59: Маржинальность | C59: =C57/C14 -> 0.26562986 | D59: =D57/D14 -> 0.31347284 | E59: =E57/E14 -> 0.25048475 | F59: =F57/F14 -> 0.27284156 | G59: =G57/G14 -> #DIV/0! | H59: =H57/H14 -> #DIV/0! | I59: =I57/I14 -> #DIV/0! | J59: =J57/J14 -> #DIV/0! | ... O59: =O57/O14 -> 0.27732131
A60: Выплата диведентов: | C60: =CF!C38 -> 0 | D60: =CF!D38 -> 0 | E60: =CF!E38 -> 0 | F60: =CF!F38 -> 0 | G60: =CF!G38 -> 0 | H60: =CF!H38 -> 0 | I60: =CF!I38 -> 0 | J60: =CF!J38 -> 0 | ... N60: =CF!N38 -> 0
A62: Остаток денежных средств на конец периода | C62: =CF!C42 -> 2426951.9 | D62: =CF!D42 -> 2920729.8 | E62: =CF!E42 -> 3317903.7 | F62: =CF!F42 -> 3497581.5 | G62: =CF!G42 -> 3497581.5 | H62: =CF!H42 -> 3497581.5 | I62: =CF!I42 -> 3497581.5 | J62: =CF!J42 -> 3497581.5 | ... N62: =CF!N42 -> 3497581.5
A64: Накопленный финансовый результат | C64: ='PL WB (нед)'!G64 -> 3244857.5 | D64: =D57+C64-D60 -> 3520525.2 | E64: =E57+D64-E60 -> 3713983.1 | F64: =F57+E64-F60 -> 3808081.8 | G64: =G57+F64-G60 -> 3808081.8 | H64: =H57+G64-H60 -> 3808081.8 | I64: =I57+H64-I60 -> 3808081.8 | J64: =J57+I64-J60 -> 3808081.8 | K64: =K57+J64-K60 -> 3808081.8 | ... N64: =N57+M64-N60 -> 3808081.8
A66: Рекламные расходы на 1 единицу | C66: =IFERROR(C41/C7, ) -> 0 | D66: =IFERROR(D41/D7, ) -> 0 | E66: =IFERROR(E41/E7, ) -> 0 | F66: =IFERROR(F41/F7, ) -> 0 | G66: =IFERROR(G41/G7, ) -> 0 | H66: =IFERROR(H41/H7, ) -> 0 | I66: =IFERROR(I41/I7, ) -> 0 | J66: =IFERROR(J41/J7, ) -> 0 | ... N66: =IFERROR(N41/N7, ) -> 0
A67: Доля рекламных расходов | C67: =IFERROR(C41/C15, ) -> 0 | D67: =IFERROR(D41/D15, ) -> 0 | E67: =IFERROR(E41/E15, ) -> 0 | F67: =IFERROR(F41/F15, ) -> 0 | G67: =IFERROR(G41/G15, ) -> 0 | H67: =IFERROR(H41/H15, ) -> 0 | I67: =IFERROR(I41/I15, ) -> 0 | J67: =IFERROR(J41/J15, ) -> 0 | ... N67: =IFERROR(N41/N15, ) -> 0
A68: Прибыль на 1 ед | C68: =IFERROR(C57/(C7-C23), ) -> 159.15431 | D68: =IFERROR(D57/(D7-D23), ) -> 207.42491 | E68: =IFERROR(E57/(E7-E23), ) -> 148.81376 | F68: =IFERROR(F57/(F7-F23), ) -> 197.27189 | G68: =IFERROR(G57/(G7-G23), ) -> 0 | H68: =IFERROR(H57/(H7-H23), ) -> 0 | I68: =IFERROR(I57/(I7-I23), ) -> 0 | J68: =IFERROR(J57/(J7-J23), ) -> 0 | ... N68: =IFERROR(N57/(N7-N23), ) -> 0

Sheet PL OZON (нед)
A1: Голубым выделены строки, которые заполняем! Заполняем эту вкладку, формулы не трогаем! Если добавляете строки - добавляете на всех листах PL и СF | C1: ='PL WB (нед)'!C1 -> 1 | D1: ='PL WB (нед)'!D1 -> 2 | E1: ='PL WB (нед)'!E1 -> 3 | F1: ='PL WB (нед)'!F1 -> 4 | G1: ='PL WB (нед)'!G1 -> 5 | H1: ='PL WB (нед)'!H1 -> 6 | I1: ='PL WB (нед)'!I1 -> 7 | J1: ='PL WB (нед)'!J1 -> 8 | ... BC1: ='PL WB (нед)'!BC1 -> Остаток года
A2: Прибыли и убытки, еженедельно | C2: Январь | H2: Февраль | L2: Март | P2: Апрель | T2: Май | Y2: Июнь | AC2: Июль | AG2: Август | AL2: Сентябрь | AP2: Октябрь | AU2: Ноябрь | AY2: Декабрь
C3: ='PL WB (нед)'!C3 -> NaN | D3: ='PL WB (нед)'!D3 -> NaN | E3: ='PL WB (нед)'!E3 -> NaN | F3: ='PL WB (нед)'!F3 -> NaN | G3: ='PL WB (нед)'!G3 -> NaN | H3: ='PL WB (нед)'!H3 -> NaN | I3: ='PL WB (нед)'!I3 -> NaN | J3: ='PL WB (нед)'!J3 -> NaN | ... BB3: ='PL WB (нед)'!BB3 -> 0 | BC3: 29.12-31.12
A4: Товарооборот
A5: Остаток товара по цене закупки | C5: 239068.58 | D5: =C12 -> 235066.58 | E5: =D12 -> 219001.58 | F5: =E12 -> 201900.58 | G5: =F12 -> 184577.58 | H5: =G12 -> 167411.58 | I5: =H12 -> 155448.58 | J5: =I12 -> 143723.58 | K5: =J12 -> 126685.58 | ... BC5: =BB12 -> 67587.58
BD6: =SUM(C6:BC6) -> 0
A7: Продажи шт | C7: 0 | D7: 0 | E7: 0 | F7: 0 | G7: 0 | H7: 0 | I7: 0 | J7: 0 | K7: 0 | L7: 0 | M7: 0 | N7: 0 | O7: 0 | P7: 0 | Q7: 0 | R7: 0 | S7: 0 | T7: 0 | U7: 0 | V7: 0 | W7: 0 | X7: 0 | Y7: 0 | Z7: 0 | AA7: 0 | AB7: 0 | AC7: 0 | AD7: 0 | AE7: 0 | AF7: 0 | AG7: 0 | AH7: 0 | AI7: 0 | AJ7: 0 | AK7: 0 | AL7: 0 | AM7: 0 | AN7: 0 | AO7: 0 | AP7: 0 | AQ7: 0 | AR7: 0 | AS7: 0 | AT7: 0 | AU7: 0 | AV7: 0 | AW7: 0 | AX7: 0 | AY7: 0 | AZ7: 0 | BA7: 0 | BB7: 0 | BC7: 0 | BD7: =SUM(C7:BC7) -> 1356
A8: Отгрузки по себестоимости | C8: =C33 -> 4002 | D8: =D33 -> 16065 | E8: =E33 -> 17101 | F8: =F33 -> 17323 | G8: =G33 -> 17166 | H8: =H33 -> 11963 | I8: =I33 -> 11725 | J8: =J33 -> 17038 | ... BC8: =BC33 -> 0 | BD8: =SUM(C8:BC8) -> 171481
BD9: =SUM(C9:BC9) -> 0
A10: Поступление товара, р | BD10: =SUM(C10:BC10) -> 0
A11: Поступление товара, шт | BD11: =SUM(C11:BC11) -> 0
A12: Доступно на складе по цене закупки | C12: =C10-C8+C5 -> 235066.58 | D12: =D10-D8+D5 -> 219001.58 | E12: =E10-E8+E5 -> 201900.58 | F12: =F10-F8+F5 -> 184577.58 | G12: =G10-G8+G5 -> 167411.58 | H12: =H10-H8+H5 -> 155448.58 | I12: =I10-I8+I5 -> 143723.58 | J12: =J10-J8+J5 -> 126685.58 | ... BC12: =BC10-BC8+BC5 -> 67587.58 | BD12: =SUM(C12:BC12) -> 4657878.7
A13: Доступно на складе, шт | C13: =1741-C7-C27+C11+C23 -> 1704 | D13: =C13-D7-D27+D11+D23 -> 1566 | E13: =D13-E7-E27+E11+E23 -> 1433 | F13: =E13-F7-F27+F11+F23 -> 1288 | G13: =F13-G7-G27+G11+G23 -> 1146 | H13: =G13-H7-H27+H11+H23 -> 1042 | I13: =H13-I7-I27+I11+I23 -> 942 | J13: =I13-J7-J27+J11+J23 -> 829 | K13: =J13-K7-K27+K11+K23 -> 760 | ... BC13: =BB13-BC7-BC27+BC11+BC23 -> 409
A14: Продано товаров OZON по цене в карточке-ВЫРУЧКА | C14: 23556 | D14: 92169 | E14: 91476 | F14: 98006 | G14: 93544 | H14: 65065 | I14: 64240 | J14: 80539 | K14: 47549 | L14: 54244 | M14: 46430 | N14: 34926 | O14: 29249 | P14: 21633 | Q14: 25109 | R14: 27597 | BD14: =SUM(C14:BC14) -> 895332
BD15: =SUM(C15:BC15) -> 0
BD16: =SUM(C16:BC16) -> 0
A17: Комиссия OZON | C17: 8844 | D17: 34710 | E17: 34473 | F17: 36913 | G17: 35355 | H17: 24418 | I17: 24277 | J17: 30783 | K17: 18081 | L17: 20446 | M17: 17665 | N17: 13238 | O17: 11142 | P17: 8115 | Q17: 9651 | R17: 11075 | BD17: 1741
A18: % комиссии | C18: =C17/C14 -> 0.37544575 | D18: =D17/D14 -> 0.37659083 | E18: =E17/E14 -> 0.37685295 | F18: =F17/F14 -> 0.37664021 | G18: =G17/G14 -> 0.37795048 | H18: =H17/H14 -> 0.37528625 | I18: =I17/I14 -> 0.37791096 | J18: =J17/J14 -> 0.38221234 | ... BC18: =BC17/BC14 -> #DIV/0!
BD19: =SUM(C19:BC19) -> 0
A20: Выручка от реализацииза вычетом комиссии, руб | C20: =C14-C17 -> 14712 | D20: =D14-D17 -> 57459 | E20: =E14-E17 -> 57003 | F20: =F14-F17 -> 61093 | G20: =G14-G17 -> 58189 | H20: =H14-H17 -> 40647 | I20: =I14-I17 -> 39963 | J20: =J14-J17 -> 49756 | ... T20: =T14-T17 -> 0 | BD20: =SUM(C20:BC20) -> 556146
BD21: =SUM(C21:BC21) -> 0
A22: Возвраты, руб | C22: 882 | D22: 3355 | E22: 471 | F22: 1771 | G22: 426 | H22: 1716 | I22: 635 | K22: 700 | L22: 2455 | M22: 2991 | N22: 1804 | R22: 660 | BD22: =SUM(C22:BC22) -> 17866
A23: Возвраты, шт | C23: 1 | D23: 6 | E23: 1 | F23: 2 | G23: 1 | H23: 2 | I23: 1 | K23: 1 | L23: 3 | M23: 3 | N23: 2 | R23: 1 | BD23: =SUM(C23:BC23) -> 24
A24: % возвратов | C24: =C22/(C14-C22) -> 0.03889918 | D24: =D22/(D14-D22) -> 0.037775576 | E24: =E22/(E14-E22) -> 0.0051755398 | F24: =F22/(F14-F22) -> 0.018402868 | G24: =G22/(G14-G22) -> 0.0045748405 | H24: =H22/(H14-H22) -> 0.027088036 | I24: =I22/(I14-I22) -> 0.0099834919 | J24: =J22/(J14-J22) -> 0 | ... BC24: =BC22/(BC14-BC22) -> #DIV/0! | BD24: =BD23/(BD7-BD23) -> 0.018018018
BD25: =SUM(C25:BC25) -> 0
A26: Брак, руб | BD26: =SUM(C26:BC26) -> 0
A27: Брак, шт | BD27: =SUM(C27:BC27) -> 0
A28: % брака | C28: =C27/C7 -> 0 | D28: =D27/D7 -> 0 | E28: =E27/E7 -> 0 | F28: =F27/F7 -> 0 | G28: =G27/G7 -> 0 | H28: =H27/H7 -> 0 | I28: =I27/I7 -> 0 | J28: =J27/J7 -> 0 | ... BD28: =BD27/BD7 -> 0
BD29: =SUM(C29:BC29) -> 0
A30: Поступление на счет от OZON | C30: =C20+C31-C38 -> 4783 | D30: =D20+D31-D38 -> 30486 | E30: =E20+E31-E38 -> 29296 | F30: =F20+F31-F38 -> 33501 | G30: =G20+G31-G38 -> 28267 | H30: =H20+H31-H38 -> 17859 | I30: =I20+I31-I38 -> 18826 | J30: =J20+J31-J38 -> 26376 | ... BC30: =BC20+BC31-BC38 -> 0 | BD30: =SUM(C30:BC30) -> 296510
A31: в т.ч. Прочие доходы | BD31: =SUM(C31:BC31) -> 0
BD32: =SUM(C32:BC32) -> 0
A33: Себестоимость | C33: 4002 | D33: 16065 | E33: 17101 | F33: 17323 | G33: 17166 | H33: 11963 | I33: 11725 | J33: 17038 | K33: 9180 | L33: 10041 | M33: 9258 | N33: 7105 | O33: 5581 | P33: 4485 | Q33: 6135 | R33: 7313 | BD33: =SUM(C33:BC33) -> 171481
A34: % себестоимости в цене | C34: =C33/C14 -> 0.16989302 | D34: =D33/D14 -> 0.17429938 | E34: =E33/E14 -> 0.18694521 | F34: =F33/F14 -> 0.17675448 | G34: =G33/G14 -> 0.18350723 | H34: =H33/H14 -> 0.18386229 | I34: =I33/I14 -> 0.18251868 | J34: =J33/J14 -> 0.21154968 | ... BD34: =BD33/BD14 -> 0.19152784
BD35: =SUM(C35:BC35) -> 0
A36: Валовая прибыль | C36: =C20-C33 -> 10710 | D36: =D20-D33 -> 41394 | E36: =E20-E33 -> 39902 | F36: =F20-F33 -> 43770 | G36: =G20-G33 -> 41023 | H36: =H20-H33 -> 28684 | I36: =I20-I33 -> 28238 | J36: =J20-J33 -> 32718 | ... BC36: =BC20-BC33 -> 0 | BD36: =SUM(C36:BC36) -> 384665
BD37: =SUM(C37:BC37) -> 0
A38: Расходы | C38: =SUM(C40:C51) -> 9929 | D38: =SUM(D40:D51) -> 26973 | E38: =SUM(E40:E51) -> 27707 | F38: =SUM(F40:F51) -> 27592 | G38: =SUM(G40:G51) -> 29922 | H38: =SUM(H40:H51) -> 22788 | I38: =SUM(I40:I51) -> 21137 | J38: =SUM(J40:J51) -> 23380 | ... BC38: =SUM(BC40:BC51) -> 0 | BD38: =SUM(C38:BC38) -> 259636
A39: % расходы | C39: =C38/C14 -> 0.4215062 | D39: =D38/D14 -> 0.2926472 | E39: =E38/E14 -> 0.30288819 | F39: =F38/F14 -> 0.28153378 | G39: =G38/G14 -> 0.31987086 | H39: =H38/H14 -> 0.35023438 | I39: =I38/I14 -> 0.32903176 | J39: =J38/J14 -> 0.29029414 | ... BD39: =BD38/BD14 -> 0.28998852
A40: Логистика OZON | C40: 4293 | D40: 16303 | E40: 18182 | F40: 18525 | G40: 18491 | H40: 15069 | I40: 13395 | J40: 18957 | K40: 9535 | L40: 10909 | M40: 11342 | N40: 6615 | O40: 3286 | P40: 2314 | Q40: 3054 | R40: 4228 | BD40: =SUM(C40:BC40) -> 174498
A41: Продвижение OZON | C41: 634 | D41: 1139 | E41: 2225 | F41: 2475 | G41: 5374 | H41: 2254 | I41: 3404 | J41: 1721 | K41: 536 | L41: 1608 | M41: 840 | N41: 330 | O41: 439 | P41: 108 | Q41: 126 | R41: 141 | BD41: =SUM(C41:BC41) -> 23354
A42: Эквайринг OZON | C42: 346 | D42: 848 | E42: 790 | F42: 884 | G42: 745 | H42: 524 | I42: 617 | J42: 749 | K42: 501 | L42: 383 | M42: 414 | N42: 241 | O42: 283 | P42: 252 | Q42: 223 | R42: 298 | BD42: =SUM(C42:BC42) -> 8098
A43: Хранение OZON | C43: 4656 | D43: 7883 | E43: 6510 | F43: 5708 | G43: 5312 | H43: 4941 | I43: 3721 | J43: 1953 | K43: 1580 | L43: 1367 | M43: 1598 | N43: 788 | O43: 590 | P43: 603 | Q43: 2613 | R43: 3063 | BD43: =SUM(C43:BC43) -> 52886
A44: Штрафы OZON | BD44: =SUM(C44:BC44) -> 0
A45: Платная приемка OZON | D45: 800 | BD45: =SUM(C45:BC45) -> 800
A46: Прочее OZON | BD46: =SUM(C46:BC46) -> 0
A47: Контент | BD47: =SUM(C47:BC47) -> 0
A48: Аренда офиса | BD48: =SUM(C48:BC48) -> 0
A49: Реклама внешняя | BD49: =SUM(C49:BC49) -> 0
A50: Подписка Аналитика | BD50: =SUM(C50:BC50) -> 0
A51: Прочие | BD51: =SUM(C51:BC51) -> 0
BD52: =SUM(C52:BC52) -> 0
A53: Прибыль до налогообложения | C53: =C36+C31-C38 -> 781 | D53: =D36+D31-D38 -> 14421 | E53: =E36+E31-E38 -> 12195 | F53: =F36+F31-F38 -> 16178 | G53: =G36+G31-G38 -> 11101 | H53: =H36+H31-H38 -> 5896 | I53: =I36+I31-I38 -> 7101 | J53: =J36+J31-J38 -> 9338 | ... BC53: =BC36+BC31-BC38 -> 0 | BD53: =SUM(C53:BC53) -> 125029
BD54: =SUM(C54:BC54) -> 0
A55: Налоги начисленные | B55: УСН 6% | C55: =C14*7% -> 1648.92 | D55: =D14*7% -> 6451.83 | E55: =E14*7% -> 6403.32 | F55: =F14*7% -> 6860.42 | G55: =G14*7% -> 6548.08 | H55: =H14*7% -> 4554.55 | I55: =I14*7% -> 4496.8 | J55: =J14*7% -> 5637.73 | ... BC55: =BC14*7% -> 0 | BD55: =SUM(C55:BC55) -> 62673.24
BD56: =SUM(C56:BC56) -> 0
A57: Чистая прибыль | C57: =C53-C55 -> -867.92 | D57: =D53-D55 -> 7969.17 | E57: =E53-E55 -> 5791.68 | F57: =F53-F55 -> 9317.58 | G57: =G53-G55 -> 4552.92 | H57: =H53-H55 -> 1341.45 | I57: =I53-I55 -> 2604.2 | J57: =J53-J55 -> 3700.27 | ... BC57: =BC53-BC55 -> 0 | BD57: =SUM(C57:BC57) -> 62355.76
A58: Рентабельность вложений | C58: =C57/C33 -> -0.21687156 | D58: =D57/D33 -> 0.49605789 | E58: =E57/E33 -> 0.33867493 | F58: =F57/F33 -> 0.53787335 | G58: =G57/G33 -> 0.26522894 | H58: =H57/H33 -> 0.11213324 | I58: =I57/I33 -> 0.22210661 | J58: =J57/J33 -> 0.21717749 | ... BD58: =BD57/BD33 -> 0.36363072
A59: Маржинальность | C59: =C57/C14 -> -0.036844965 | D59: =D57/D14 -> 0.086462585 | E59: =E57/E14 -> 0.063313656 | F59: =F57/F14 -> 0.095071526 | G59: =G57/G14 -> 0.048671427 | H59: =H57/H14 -> 0.020617075 | I59: =I57/I14 -> 0.040538605 | J59: =J57/J14 -> 0.045943828 | ... BD59: =BD57/BD14 -> 0.069645405
A60: Выплата диведентов: | C60: ='CF (нед)'!C38 -> 0 | D60: ='CF (нед)'!D38 -> 0 | E60: ='CF (нед)'!E38 -> 0 | F60: ='CF (нед)'!F38 -> 0 | G60: ='CF (нед)'!G38 -> 0 | H60: ='CF (нед)'!H38 -> 0 | I60: ='CF (нед)'!I38 -> 0 | J60: ='CF (нед)'!J38 -> 0 | ... BC60: ='CF (нед)'!BC38 -> 0 | BD60: =SUM(C60:BC60) -> 0
BD61: =SUM(C61:BC61) -> 0
A62: ='PL WB'!A62 -> Остаток денежных средств на конец периода | C62: ='CF (нед)'!C42 -> 1994177.9 | D62: ='CF (нед)'!D42 -> 2100356.8 | E62: ='CF (нед)'!E42 -> 2234359.4 | F62: ='CF (нед)'!F42 -> 2340085.2 | G62: ='CF (нед)'!G42 -> 2444316.6 | H62: ='CF (нед)'!H42 -> 2568251.9 | I62: ='CF (нед)'!I42 -> 2701831.8 | J62: ='CF (нед)'!J42 -> 2827470.9 | ... BC62: ='CF (нед)'!BC42 -> 3539892.4 | BD62: =SUM(C62:BC62) -> 1.7644632e+08
G63: =G62-'PL OZON'!C62 -> 17364.73 | K63: =K62-'PL OZON'!D62 -> 31050.17 | O63: =O62-'PL OZON'!E62 -> 39546.24 | S63: =S62-'PL OZON'!F62 -> 42310.91 | X63: =X62-'PL OZON'!G62 -> 42310.91 | AB63: =AB62-'PL OZON'!H62 -> 42310.91 | AF63: =AF62-'PL OZON'!I62 -> 42310.91 | AK63: =AK62-'PL OZON'!J62 -> 42310.91 | AO63: =AO62-'PL OZON'!K62 -> 42310.91 | AT63: =AT62-'PL OZON'!L62 -> 42310.91 | AX63: =AX62-'PL OZON'!M62 -> 42310.91
A64: Накопленный финансовый результат | C64: =C57+292844.08-C60 -> 291976.16 | D64: =D57+C64-D60 -> 299945.33 | E64: =E57+D64-E60 -> 305737.01 | F64: =F57+E64-F60 -> 315054.59 | G64: =G57+F64-G60 -> 319607.51 | H64: =H57+G64-H60 -> 320948.96 | I64: =I57+H64-I60 -> 323553.16 | J64: =J57+I64-J60 -> 327253.43 | K64: =K57+J64-K60 -> 332061 | ... BC64: =BC57+BB64-BC60 -> 355199.84 | BD64: =SUM(C64:BC64)/33 -> 558027.28
G65: =G64-'PL OZON'!C64 -> 0 | K65: =K64-'PL OZON'!D64 -> 0 | O65: =O64-'PL OZON'!E64 -> 0 | S65: =S64-'PL OZON'!F64 -> 0 | X65: =X64-'PL OZON'!G64 -> 0 | AB65: =AB64-'PL OZON'!H64 -> 0 | AF65: =AF64-'PL OZON'!I64 -> 0 | AK65: =AK64-'PL OZON'!J64 -> 0 | AO65: =AO64-'PL OZON'!K64 -> 0 | AT65: =AT64-'PL OZON'!L64 -> 0 | AX65: =AX64-'PL OZON'!M64 -> 0
A66: Серые нули (стр 63, 65) - это проверки между листами! Если не ноль - ищем ошибку | BD66: =SUM(C66:BC66) -> 0
BD67: =BD60+BC67-BD63 -> 0
B68: Сумма вложений с начала 2023 | C68: =SUM('CF (нед)'!$C$29:C29) -> 0 | D68: =SUM('CF (нед)'!$C$29:D29) -> 0 | E68: =SUM('CF (нед)'!$C$29:E29) -> 0 | F68: =SUM('CF (нед)'!$C$29:F29) -> 0 | G68: =SUM('CF (нед)'!$C$29:G29) -> 0 | H68: =SUM('CF (нед)'!$C$29:H29) -> 0 | I68: =SUM('CF (нед)'!$C$29:I29) -> 0 | J68: =SUM('CF (нед)'!$C$29:J29) -> 0 | ... BC68: =SUM('CF (нед)'!$C$29:BC29) -> 0 | BD68: =SUM(C68:BC68) -> 0
B69: Сумма себестоимости за 16 нед | C69: =SUM($C$33:C33) -> 4002 | D69: =SUM($C$33:D33) -> 20067 | E69: =SUM($C$33:E33) -> 37168 | F69: =SUM($C$33:F33) -> 54491 | G69: =SUM($C$33:G33) -> 71657 | H69: =SUM($C$33:H33) -> 83620 | I69: =SUM($C$33:I33) -> 95345 | J69: =SUM($C$33:J33) -> 112383 | ... Q69: =SUM($C$33:Q33) -> 164168 | R69: =SUM(C33:R33) -> 171481 | S69: =SUM(D33:S33) -> 167479 | T69: =SUM(E33:T33) -> 151414 | U69: =SUM(F33:U33) -> 134313 | V69: =SUM(G33:V33) -> 116990 | W69: =SUM(H33:W33) -> 99824 | X69: =SUM(I33:X33) -> 87861 | Y69: =SUM(J33:Y33) -> 76136 | ... BC69: =SUM(AN33:BC33) -> 0 | BD69: =SUM(C69:BC69) -> 2743696
B70: Прибыль за 16 нед | C70: =SUM($C$57:C57) -> -867.92 | D70: =SUM($C$57:D57) -> 7101.25 | E70: =SUM($C$57:E57) -> 12892.93 | F70: =SUM($C$57:F57) -> 22210.51 | G70: =SUM($C$57:G57) -> 26763.43 | H70: =SUM($C$57:H57) -> 28104.88 | I70: =SUM($C$57:I57) -> 30709.08 | J70: =SUM($C$57:J57) -> 34409.35 | ... Q70: =SUM($C$57:Q57) -> 62808.55 | R70: =SUM(C57:R57) -> 62355.76 | S70: =SUM(D57:S57) -> 63223.68 | T70: =SUM(E57:T57) -> 55254.51 | U70: =SUM(F57:U57) -> 49462.83 | V70: =SUM(G57:V57) -> 40145.25 | W70: =SUM(H57:W57) -> 35592.33 | X70: =SUM(I57:X57) -> 34250.88 | Y70: =SUM(J57:Y57) -> 31646.68 | ... BC70: =SUM(AN57:BC57) -> 0 | BD70: =SUM(C70:BC70) -> 997692.16
B71: Рентабельность за 16 нед | C71: =C70/C69 -> -0.21687156 | D71: =D70/D69 -> 0.35387701 | E71: =E70/E69 -> 0.34688253 | F71: =F70/F69 -> 0.4075996 | G71: =G70/G69 -> 0.37349359 | H71: =H70/H69 -> 0.33610237 | I71: =I70/I69 -> 0.3220838 | J71: =J70/J69 -> 0.30617932 | ... BC71: =BC70/BC69 -> #DIV/0! | BD71: =SUM(C71:BC71) -> #DIV/0!
B72: Оборачиваемость за 16 нед | C72: =C69/C68 -> #DIV/0! | D72: =D69/D68 -> #DIV/0! | E72: =E69/E68 -> #DIV/0! | F72: =F69/F68 -> #DIV/0! | G72: =G69/G68 -> #DIV/0! | H72: =H69/H68 -> #DIV/0! | I72: =I69/I68 -> #DIV/0! | J72: =J69/J68 -> #DIV/0! | ... BC72: =BC69/BC68 -> #DIV/0! | BD72: =SUM(C72:BC72) -> #DIV/0!
B73: Оборачиваемость в днях | C73: =(C74*7)/C72 -> #DIV/0! | D73: =(D74*7)/D72 -> #DIV/0! | E73: =(E74*7)/E72 -> #DIV/0! | F73: =(F74*7)/F72 -> #DIV/0! | G73: =(G74*7)/G72 -> #DIV/0! | H73: =(H74*7)/H72 -> #DIV/0! | I73: =(I74*7)/I72 -> #DIV/0! | J73: =(J74*7)/J72 -> #DIV/0! | ... Q73: =(Q74*7)/Q72 -> #DIV/0! | R73: =(16*7)/R72 -> #DIV/0! | S73: =(16*7)/S72 -> #DIV/0! | T73: =(16*7)/T72 -> #DIV/0! | U73: =(16*7)/U72 -> #DIV/0! | V73: =(16*7)/V72 -> #DIV/0! | W73: =(16*7)/W72 -> #DIV/0! | X73: =(16*7)/X72 -> #DIV/0! | Y73: =(16*7)/Y72 -> #DIV/0! | ... BC73: =(16*7)/BC72 -> #DIV/0! | BD73: =SUM(C73:BC73) -> #DIV/0!
C74: 1 | D74: 2 | E74: 3 | F74: 4 | G74: 5 | H74: 6 | I74: 7 | J74: 8 | K74: 9 | L74: 10 | M74: 11 | N74: 12 | O74: 13 | P74: 14 | Q74: 15 | R74: 16 | S74: далее анализ последних 16 недель | BD74: =SUM(C74:BC74) -> 136
B75: Остаток товара закончится через, дн | C75: =C12*C74*7/C69 -> 411.16093 | D75: =D12*D74*7/D69 -> 152.78926 | E75: =E12*E74*7/E69 -> 114.07426 | F75: =F12*F74*7/F69 -> 94.844511 | G75: =G12*G74*7/G69 -> 81.770173 | H75: =H12*H74*7/H69 -> 78.077498 | I75: =I12*I74*7/I69 -> 73.862871 | J75: =J12*J74*7/J69 -> 63.126918 | ... R75: =R12*R74*7/R69 -> 44.143718 | S75: =S12*16*7/S69 -> 45.198556 | T75: =T12*16*7/T69 -> 49.994115 | U75: =U12*16*7/U69 -> 56.359466 | V75: =V12*16*7/V69 -> 64.704752 | W75: =W12*16*7/W69 -> 75.831553 | X75: =X12*16*7/X69 -> 86.156645 | Y75: =Y12*16*7/Y69 -> 99.424831 | Z75: =Z12*16*7/Z69 -> 128.08909 | ... BC75: =BC12*16*7/BC69 -> #DIV/0! | BD75: =SUM(C75:BC75) -> #DIV/0!
B76: Дата распродажи в 0 | C76: =TODAY( )+C75 -> 46543.161 | D76: =TODAY( )+D75 -> 46284.789 | E76: =TODAY( )+E75 -> 46246.074 | F76: =TODAY( )+F75 -> 46226.845 | G76: =TODAY( )+G75 -> 46213.77 | H76: =TODAY( )+H75 -> 46210.077 | I76: =TODAY( )+I75 -> 46205.863 | J76: =TODAY( )+J75 -> 46195.127 | ... BC76: =TODAY( )+BC75 -> NaN | BD76: =SUM(C76:BC76) -> #DIV/0!

Sheet PL OZON
A1: Заполняем PL и CF еженедельный!
A2: Прибыли и убытки | C2: 2025
C3: Январь | D3: Февраль | E3: Март | F3: Апрель | G3: Май | H3: Июнь | I3: Июль | J3: Август | K3: Сентябрь | L3: Октябрь | M3: Ноябрь | N3: Декабрь
A4: Товарооборот
A5: Остаток товара по цене закупки | C5: ='PL OZON (нед)'!C5 -> 239068.58 | D5: =C12 -> 167411.58 | E5: =D12 -> 117505.58 | F5: =E12 -> 85520.58 | G5: =F12 -> 67587.58 | H5: =G12 -> 67587.58 | I5: =H12 -> 67587.58 | J5: =I12 -> 67587.58 | K5: =J12 -> 67587.58 | ... N5: =M12 -> 67587.58
B7: Продажи шт | C7: =SUM('PL OZON (нед)'!C7:G7) -> 606 | D7: =SUM('PL OZON (нед)'!H7:K7) -> 390 | E7: =SUM('PL OZON (нед)'!L7:O7) -> 238 | F7: =SUM('PL OZON (нед)'!P7:S7) -> 122 | G7: =SUM('PL OZON (нед)'!T7:X7) -> 0 | H7: =SUM('PL OZON (нед)'!Y7:AB7) -> 0 | I7: =SUM('PL OZON (нед)'!AC7:AF7) -> 0 | J7: =SUM('PL OZON (нед)'!AG7:AK7) -> 0 | K7: =SUM('PL OZON (нед)'!AL7:AO7) -> 0 | L7: =SUM('PL OZON (нед)'!AP7:AT7) -> 0 | M7: =SUM('PL OZON (нед)'!AU7:AX7) -> 0 | N7: =SUM('PL OZON (нед)'!AY7:BB7) -> 0 | O7: =SUM(C7:N7) -> 1356
B8: Отгрузки по себестоимости | C8: =C33 -> 71657 | D8: =D33 -> 49906 | E8: =E33 -> 31985 | F8: =F33 -> 17933 | G8: =G33 -> 0 | H8: =H33 -> 0 | I8: =I33 -> 0 | J8: =J33 -> 0 | ... N8: =N33 -> 0 | O8: =SUM(C8:N8) -> 171481
A10: Поступление товара, р | C10: =SUM('PL OZON (нед)'!C10:G10) -> 0 | D10: =SUM('PL OZON (нед)'!H10:K10) -> 0 | E10: =SUM('PL OZON (нед)'!L10:O10) -> 0 | F10: =SUM('PL OZON (нед)'!P10:S10) -> 0 | G10: =SUM('PL OZON (нед)'!T10:X10) -> 0 | H10: =SUM('PL OZON (нед)'!Y10:AB10) -> 0 | I10: =SUM('PL OZON (нед)'!AC10:AF10) -> 0 | J10: =SUM('PL OZON (нед)'!AG10:AK10) -> 0 | K10: =SUM('PL OZON (нед)'!AL10:AO10) -> 0 | L10: =SUM('PL OZON (нед)'!AP10:AT10) -> 0 | M10: =SUM('PL OZON (нед)'!AU10:AX10) -> 0 | N10: =SUM('PL OZON (нед)'!AY10:BB10) -> 0 | O10: =SUM(C10:N10) -> 0
A11: Поступление товара, шт | C11: =SUM('PL OZON (нед)'!C11:G11) -> 0 | D11: =SUM('PL OZON (нед)'!H11:K11) -> 0 | E11: =SUM('PL OZON (нед)'!L11:O11) -> 0 | F11: =SUM('PL OZON (нед)'!P11:S11) -> 0 | G11: =SUM('PL OZON (нед)'!T11:X11) -> 0 | H11: =SUM('PL OZON (нед)'!Y11:AB11) -> 0 | I11: =SUM('PL OZON (нед)'!AC11:AF11) -> 0 | J11: =SUM('PL OZON (нед)'!AG11:AK11) -> 0 | K11: =SUM('PL OZON (нед)'!AL11:AO11) -> 0 | L11: =SUM('PL OZON (нед)'!AP11:AT11) -> 0 | M11: =SUM('PL OZON (нед)'!AU11:AX11) -> 0 | N11: =SUM('PL OZON (нед)'!AY11:BB11) -> 0 | O11: =SUM(C11:N11) -> 0
A12: Доступно на складе по цене закупки | C12: =C10-C8+C5 -> 167411.58 | D12: =D10-D8+D5 -> 117505.58 | E12: =E10-E8+E5 -> 85520.58 | F12: =F10-F8+F5 -> 67587.58 | G12: =G10-G8+G5 -> 67587.58 | H12: =H10-H8+H5 -> 67587.58 | I12: =I10-I8+I5 -> 67587.58 | J12: =J10-J8+J5 -> 67587.58 | ... N12: =N10-N8+N5 -> 67587.58
A13: Доступно на складе, шт | C13: ='PL OZON (нед)'!G13 -> 1146 | D13: =C13-D7-D27+D11+D23 -> 760 | E13: =D13-E7-E27+E11+E23 -> 530 | F13: =E13-F7-F27+F11+F23 -> 409 | G13: =F13-G7-G27+G11+G23 -> 409 | H13: =G13-H7-H27+H11+H23 -> 409 | I13: =H13-I7-I27+I11+I23 -> 409 | J13: =I13-J7-J27+J11+J23 -> 409 | K13: =J13-K7-K27+K11+K23 -> 409 | ... N13: =M13-N7-N27+N11+N23 -> 409
A14: Продано товаров OZON по цене в карточке | C14: =SUM('PL OZON (нед)'!C14:G14) -> 398751 | D14: =SUM('PL OZON (нед)'!H14:K14) -> 257393 | E14: =SUM('PL OZON (нед)'!L14:O14) -> 164849 | F14: =SUM('PL OZON (нед)'!P14:S14) -> 74339 | G14: =SUM('PL OZON (нед)'!T14:X14) -> 0 | H14: =SUM('PL OZON (нед)'!Y14:AB14) -> 0 | I14: =SUM('PL OZON (нед)'!AC14:AF14) -> 0 | J14: =SUM('PL OZON (нед)'!AG14:AK14) -> 0 | K14: =SUM('PL OZON (нед)'!AL14:AO14) -> 0 | L14: =SUM('PL OZON (нед)'!AP14:AT14) -> 0 | M14: =SUM('PL OZON (нед)'!AU14:AX14) -> 0 | N14: =SUM('PL OZON (нед)'!AY14:BB14) -> 0 | O14: =SUM(C14:N14) -> 895332
O15: =SUM(C15:N15) -> 0
O16: =SUM(C16:N16) -> 0
A17: Комиссия OZON | C17: =C14-C20 -> 150295 | D17: =D14-D20 -> 97559 | E17: =E14-E20 -> 62491 | F17: =F14-F20 -> 28841 | G17: =G14-G20 -> 0 | H17: =H14-H20 -> 0 | I17: =I14-I20 -> 0 | J17: =J14-J20 -> 0 | ... N17: =N14-N20 -> 0 | O17: =SUM(C17:N17) -> 339186
A18: % комиссии | C18: =IFERROR(C17/C14,0) -> 0.37691442 | D18: =IFERROR(D17/D14,0) -> 0.3790274 | E18: =IFERROR(E17/E14,0) -> 0.37908025 | F18: =IFERROR(F17/F14,0) -> 0.38796594 | G18: =IFERROR(G17/G14,0) -> 0 | H18: =IFERROR(H17/H14,0) -> 0 | I18: =IFERROR(I17/I14,0) -> 0 | J18: =IFERROR(J17/J14,0) -> 0 | ... O18: =IFERROR(O17/O14,0) -> 0.37883824
A20: Выручка от реализации (к перечислению за товар), руб | C20: =SUM('PL OZON (нед)'!C20:G20) -> 248456 | D20: =SUM('PL OZON (нед)'!H20:K20) -> 159834 | E20: =SUM('PL OZON (нед)'!L20:O20) -> 102358 | F20: =SUM('PL OZON (нед)'!P20:S20) -> 45498 | G20: =SUM('PL OZON (нед)'!T20:X20) -> 0 | H20: =SUM('PL OZON (нед)'!Y20:AB20) -> 0 | I20: =SUM('PL OZON (нед)'!AC20:AF20) -> 0 | J20: =SUM('PL OZON (нед)'!AG20:AK20) -> 0 | K20: =SUM('PL OZON (нед)'!AL20:AO20) -> 0 | L20: =SUM('PL OZON (нед)'!AP20:AT20) -> 0 | M20: =SUM('PL OZON (нед)'!AU20:AX20) -> 0 | N20: =SUM('PL OZON (нед)'!AY20:BB20) -> 0 | O20: =SUM(C20:N20) -> 556146
O21: =SUM(C21:N21) -> 0
A22: Возвраты, руб | C22: =SUM('PL OZON (нед)'!C22:G22) -> 6905 | D22: =SUM('PL OZON (нед)'!H22:K22) -> 3051 | E22: =SUM('PL OZON (нед)'!L22:O22) -> 7250 | F22: =SUM('PL OZON (нед)'!P22:S22) -> 660 | G22: =SUM('PL OZON (нед)'!T22:X22) -> 0 | H22: =SUM('PL OZON (нед)'!Y22:AB22) -> 0 | I22: =SUM('PL OZON (нед)'!AC22:AF22) -> 0 | J22: =SUM('PL OZON (нед)'!AG22:AK22) -> 0 | K22: =SUM('PL WB (нед)'!AL22:AO22) -> 0 | L22: =SUM('PL WB (нед)'!AP22:AT22) -> 0 | M22: =SUM('PL WB (нед)'!AU22:AX22) -> 0 | N22: =SUM('PL WB (нед)'!AY22:BB22) -> 0 | O22: =SUM(C22:N22) -> 17866
A23: Возвраты, шт | C23: =SUM('PL OZON (нед)'!C23:G23) -> 11 | D23: =SUM('PL OZON (нед)'!H23:K23) -> 4 | E23: =SUM('PL OZON (нед)'!L23:O23) -> 8 | F23: =SUM('PL OZON (нед)'!P23:S23) -> 1 | G23: =SUM('PL OZON (нед)'!T23:X23) -> 0 | H23: =SUM('PL WB (нед)'!Y23:AB23) -> 0 | I23: =SUM('PL WB (нед)'!AC23:AF23) -> 0 | J23: =SUM('PL WB (нед)'!AG23:AK23) -> 0 | K23: =SUM('PL OZON (нед)'!AL23:AO23) -> 0 | L23: =SUM('PL OZON (нед)'!AP23:AT23) -> 0 | M23: =SUM('PL OZON (нед)'!AU23:AX23) -> 0 | N23: =SUM('PL OZON (нед)'!AY23:BB23) -> 0 | O23: =SUM(C23:N23) -> 24
A24: % возвратов | C24: =IFERROR(C22/C14,0) -> 0.017316571 | D24: =IFERROR(D22/D14,0) -> 0.011853469 | E24: =IFERROR(E22/E14,0) -> 0.043979642 | F24: =IFERROR(F22/F14,0) -> 0.0088782469 | G24: =IFERROR(G22/G14,0) -> 0 | H24: =IFERROR(H22/H14,0) -> 0 | I24: =IFERROR(I22/I14,0) -> 0 | J24: =IFERROR(J22/J14,0) -> 0 | ... O24: =IFERROR(O22/O14,0) -> 0.019954609
A26: Брак, руб
A27: Брак, шт | C27: =SUM('PL OZON (нед)'!C27:G27) -> 0 | D27: =SUM('PL OZON (нед)'!H27:K27) -> 0 | E27: =SUM('PL OZON (нед)'!L27:O27) -> 0 | F27: =SUM('PL OZON (нед)'!P27:S27) -> 0 | G27: =SUM('PL OZON (нед)'!T27:X27) -> 0 | H27: =SUM('PL OZON (нед)'!Y27:AB27) -> 0 | I27: =SUM('PL OZON (нед)'!AC27:AF27) -> 0 | J27: =SUM('PL OZON (нед)'!AG27:AK27) -> 0 | K27: =SUM('PL OZON (нед)'!AL27:AO27) -> 0 | L27: =SUM('PL OZON (нед)'!AP27:AT27) -> 0 | M27: =SUM('PL OZON (нед)'!AU27:AX27) -> 0 | N27: =SUM('PL OZON (нед)'!AY27:BB27) -> 0
A28: % брака | C28: =IFERROR(C27/C7,0) -> 0 | D28: =IFERROR(D27/D7,0) -> 0 | E28: =IFERROR(E27/E7,0) -> 0 | F28: =IFERROR(F27/F7,0) -> 0 | G28: =IFERROR(G27/G7,0) -> 0 | H28: =IFERROR(H27/H7,0) -> 0 | I28: =IFERROR(I27/I7,0) -> 0 | J28: =IFERROR(J27/J7,0) -> 0 | ... N28: =IFERROR(N27/N7,0) -> 0
A30: Поступление на счет от ВБ | C30: =C20+C31-SUM(C40:C45)-C41 -> 114486 | D30: =D20+D31-SUM(D40:D45)-D41 -> 72462 | E30: =E20+E31-SUM(E40:E45)-E41 -> 58108 | F30: =F20+F31-SUM(F40:F45)-F41 -> 28100 | G30: =G20+G31-SUM(G40:G45)-G41 -> 0 | H30: =H20+H31-SUM(H40:H45)-H41 -> 0 | I30: =I20+I31-SUM(I40:I45)-I41 -> 0 | J30: =J20+J31-SUM(J40:J45)-J41 -> 0 | ... N30: =N20+N31-SUM(N40:N45)-N41 -> 0 | O30: =SUM(C30:N30) -> 273156
A31: в т.ч. Прочие доходы | C31: =SUM('PL OZON (нед)'!C31:G31) -> 0 | D31: =SUM('PL OZON (нед)'!H31:K31) -> 0 | E31: =SUM('PL OZON (нед)'!L31:O31) -> 0 | F31: =SUM('PL OZON (нед)'!P31:S31) -> 0 | G31: =SUM('PL OZON (нед)'!T31:X31) -> 0 | H31: =SUM('PL OZON (нед)'!Y31:AB31) -> 0 | I31: =SUM('PL OZON (нед)'!AC31:AF31) -> 0 | J31: =SUM('PL OZON (нед)'!AG31:AK31) -> 0 | K31: =SUM('PL OZON (нед)'!AL31:AO31) -> 0 | L31: =SUM('PL OZON (нед)'!AP31:AT31) -> 0 | M31: =SUM('PL OZON (нед)'!AU31:AX31) -> 0 | N31: =SUM('PL OZON (нед)'!AY31:BB31) -> 0
A33: Себестоимость | C33: =SUM('PL OZON (нед)'!C33:G33) -> 71657 | D33: =SUM('PL OZON (нед)'!H33:K33) -> 49906 | E33: =SUM('PL OZON (нед)'!L33:O33) -> 31985 | F33: =SUM('PL OZON (нед)'!P33:S33) -> 17933 | G33: =SUM('PL OZON (нед)'!T33:X33) -> 0 | H33: =SUM('PL OZON (нед)'!Y33:AB33) -> 0 | I33: =SUM('PL OZON (нед)'!AC33:AF33) -> 0 | J33: =SUM('PL OZON (нед)'!AG33:AK33) -> 0 | K33: =SUM('PL OZON (нед)'!AL33:AO33) -> 0 | L33: =SUM('PL OZON (нед)'!AP33:AT33) -> 0 | M33: =SUM('PL OZON (нед)'!AU33:AX33) -> 0 | N33: =SUM('PL OZON (нед)'!AY33:BB33) -> 0 | O33: =SUM('PL OZON (нед)'!AZ33:BC33) -> 0
A34: % себестоимости | C34: =IFERROR(C33/C14,0) -> 0.17970362 | D34: =IFERROR(D33/D14,0) -> 0.19389028 | E34: =IFERROR(E33/E14,0) -> 0.19402605 | F34: =IFERROR(F33/F14,0) -> 0.24123273 | G34: =IFERROR(G33/G14,0) -> 0 | H34: =IFERROR(H33/H14,0) -> 0 | I34: =IFERROR(I33/I14,0) -> 0 | J34: =IFERROR(J33/J14,0) -> 0 | ... O34: =IFERROR(O33/O14,0) -> 0
A36: Валовая прибыль | C36: =C20-C33 -> 176799 | D36: =D20-D33 -> 109928 | E36: =E20-E33 -> 70373 | F36: =F20-F33 -> 27565 | G36: =G20-G33 -> 0 | H36: =H20-H33 -> 0 | I36: =I20-I33 -> 0 | J36: =J20-J33 -> 0 | ... O36: =O20-O33 -> 556146
A38: Расходы | C38: =SUM(C40:C51) -> 122123 | D38: =SUM(D40:D51) -> 79457 | E38: =SUM(E40:E51) -> 41033 | F38: =SUM(F40:F51) -> 17023 | G38: =SUM(G40:G51) -> 0 | H38: =SUM(H40:H51) -> 0 | I38: =SUM(I40:I51) -> 0 | J38: =SUM(J40:J51) -> 0 | ... N38: =SUM(N40:N51) -> 0 | O38: =SUM(C38:N38) -> 259636
A39: % расходы | C39: =IFERROR(C38/C14,0) -> 0.30626381 | D39: =IFERROR(D38/D14,0) -> 0.30869915 | E39: =IFERROR(E38/E14,0) -> 0.24891264 | F39: =IFERROR(F38/F14,0) -> 0.22899151 | G39: =IFERROR(G38/G14,0) -> 0 | H39: =IFERROR(H38/H14,0) -> 0 | I39: =IFERROR(I38/I14,0) -> 0 | J39: =IFERROR(J38/J14,0) -> 0 | ... N39: =IFERROR(N38/N14,0) -> 0
A40: Логистика OZON | C40: =SUM('PL OZON (нед)'!C40:G40) -> 75794 | D40: =SUM('PL OZON (нед)'!H40:K40) -> 56956 | E40: =SUM('PL OZON (нед)'!L40:O40) -> 32152 | F40: =SUM('PL OZON (нед)'!P40:S40) -> 9596 | G40: =SUM('PL OZON (нед)'!T40:X40) -> 0 | H40: =SUM('PL OZON (нед)'!Y40:AB40) -> 0 | I40: =SUM('PL OZON (нед)'!AC40:AF40) -> 0 | J40: =SUM('PL OZON (нед)'!AG40:AK40) -> 0 | K40: =SUM('PL OZON (нед)'!AL40:AO40) -> 0 | L40: =SUM('PL OZON (нед)'!AP40:AT40) -> 0 | M40: =SUM('PL OZON (нед)'!AU40:AX40) -> 0 | N40: =SUM('PL OZON (нед)'!AY40:BB40) -> 0 | O40: =SUM(C40:N40) -> 174498
A41: Продвижение OZON | C41: =SUM('PL OZON (нед)'!C41:G41) -> 11847 | D41: =SUM('PL OZON (нед)'!H41:K41) -> 7915 | E41: =SUM('PL OZON (нед)'!L41:O41) -> 3217 | F41: =SUM('PL OZON (нед)'!P41:S41) -> 375 | G41: =SUM('PL OZON (нед)'!T41:X41) -> 0 | H41: =SUM('PL OZON (нед)'!Y41:AB41) -> 0 | I41: =SUM('PL OZON (нед)'!AC41:AF41) -> 0 | J41: =SUM('PL OZON (нед)'!AG41:AK41) -> 0 | K41: =SUM('PL OZON (нед)'!AL41:AO41) -> 0 | L41: =SUM('PL OZON (нед)'!AP41:AT41) -> 0 | M41: =SUM('PL OZON (нед)'!AU41:AX41) -> 0 | N41: =SUM('PL OZON (нед)'!AY41:BB41) -> 0 | O41: =SUM(C41:N41) -> 23354
A42: Эквайринг OZON | C42: =SUM('PL OZON (нед)'!C42:G42) -> 3613 | D42: =SUM('PL OZON (нед)'!H42:K42) -> 2391 | E42: =SUM('PL OZON (нед)'!L42:O42) -> 1321 | F42: =SUM('PL OZON (нед)'!P42:S42) -> 773 | G42: =SUM('PL OZON (нед)'!T42:X42) -> 0 | H42: =SUM('PL OZON (нед)'!Y42:AB42) -> 0 | I42: =SUM('PL OZON (нед)'!AC42:AF42) -> 0 | J42: =SUM('PL OZON (нед)'!AG42:AK42) -> 0 | K42: =SUM('PL OZON (нед)'!AL42:AO42) -> 0 | L42: =SUM('PL OZON (нед)'!AP42:AT42) -> 0 | M42: =SUM('PL OZON (нед)'!AU42:AX42) -> 0 | N42: =SUM('PL OZON (нед)'!AY42:BB42) -> 0 | O42: =SUM(C42:N42) -> 8098
A43: Хранение OZON | C43: =SUM('PL OZON (нед)'!C43:G43) -> 30069 | D43: =SUM('PL OZON (нед)'!H43:K43) -> 12195 | E43: =SUM('PL OZON (нед)'!L43:O43) -> 4343 | F43: =SUM('PL OZON (нед)'!P43:S43) -> 6279 | G43: =SUM('PL OZON (нед)'!T43:X43) -> 0 | H43: =SUM('PL OZON (нед)'!Y43:AB43) -> 0 | I43: =SUM('PL OZON (нед)'!AC43:AF43) -> 0 | J43: =SUM('PL OZON (нед)'!AG43:AK43) -> 0 | K43: =SUM('PL OZON (нед)'!AL43:AO43) -> 0 | L43: =SUM('PL OZON (нед)'!AP43:AT43) -> 0 | M43: =SUM('PL OZON (нед)'!AU43:AX43) -> 0 | N43: =SUM('PL OZON (нед)'!AY43:BB43) -> 0 | O43: =SUM(C43:N43) -> 52886
A44: Штрафы OZON | C44: =SUM('PL OZON (нед)'!C44:G44) -> 0 | D44: =SUM('PL OZON (нед)'!H44:K44) -> 0 | E44: =SUM('PL OZON (нед)'!L44:O44) -> 0 | F44: =SUM('PL OZON (нед)'!P44:S44) -> 0 | G44: =SUM('PL OZON (нед)'!T44:X44) -> 0 | H44: =SUM('PL OZON (нед)'!Y44:AB44) -> 0 | I44: =SUM('PL OZON (нед)'!AC44:AF44) -> 0 | J44: =SUM('PL OZON (нед)'!AG44:AK44) -> 0 | K44: =SUM('PL OZON (нед)'!AL44:AO44) -> 0 | L44: =SUM('PL OZON (нед)'!AP44:AT44) -> 0 | M44: =SUM('PL OZON (нед)'!AU44:AX44) -> 0 | N44: =SUM('PL OZON (нед)'!AY44:BB44) -> 0 | O44: =SUM(C44:N44) -> 0
A45: Платная приемка OZON | C45: =SUM('PL OZON (нед)'!C45:G45) -> 800 | D45: =SUM('PL OZON (нед)'!H45:K45) -> 0 | E45: =SUM('PL OZON (нед)'!L45:O45) -> 0 | F45: =SUM('PL OZON (нед)'!P45:S45) -> 0 | G45: =SUM('PL OZON (нед)'!T45:X45) -> 0 | H45: =SUM('PL OZON (нед)'!Y45:AB45) -> 0 | I45: =SUM('PL OZON (нед)'!AC45:AF45) -> 0 | J45: =SUM('PL OZON (нед)'!AG45:AK45) -> 0 | K45: =SUM('PL OZON (нед)'!AL45:AO45) -> 0 | L45: =SUM('PL OZON (нед)'!AP45:AT45) -> 0 | M45: =SUM('PL OZON (нед)'!AU45:AX45) -> 0 | N45: =SUM('PL OZON (нед)'!AY45:BB45) -> 0 | O45: =SUM(C45:N45) -> 800
A46: Прочее OZON | C46: =SUM('PL OZON (нед)'!C46:G46) -> 0 | D46: =SUM('PL OZON (нед)'!H46:K46) -> 0 | E46: =SUM('PL OZON (нед)'!L46:O46) -> 0 | F46: =SUM('PL OZON (нед)'!P46:S46) -> 0 | G46: =SUM('PL OZON (нед)'!T46:X46) -> 0 | H46: =SUM('PL OZON (нед)'!Y46:AB46) -> 0 | I46: =SUM('PL OZON (нед)'!AC46:AF46) -> 0 | J46: =SUM('PL OZON (нед)'!AG46:AK46) -> 0 | K46: =SUM('PL OZON (нед)'!AL46:AO46) -> 0 | L46: =SUM('PL OZON (нед)'!AP46:AT46) -> 0 | M46: =SUM('PL OZON (нед)'!AU46:AX46) -> 0 | N46: =SUM('PL OZON (нед)'!AY46:BB46) -> 0 | O46: =SUM(C46:N46) -> 0
A47: Контент | C47: =SUM('PL OZON (нед)'!C47:G47) -> 0 | D47: =SUM('PL OZON (нед)'!H47:K47) -> 0 | E47: =SUM('PL OZON (нед)'!L47:O47) -> 0 | F47: =SUM('PL OZON (нед)'!P47:S47) -> 0 | G47: =SUM('PL OZON (нед)'!T47:X47) -> 0 | H47: =SUM('PL OZON (нед)'!Y47:AB47) -> 0 | I47: =SUM('PL OZON (нед)'!AC47:AF47) -> 0 | J47: =SUM('PL OZON (нед)'!AG47:AK47) -> 0 | K47: =SUM('PL OZON (нед)'!AL47:AO47) -> 0 | L47: =SUM('PL OZON (нед)'!AP47:AT47) -> 0 | M47: =SUM('PL OZON (нед)'!AU47:AX47) -> 0 | N47: =SUM('PL OZON (нед)'!AY47:BB47) -> 0 | O47: =SUM(C47:N47) -> 0
A48: Аренда офиса | C48: =SUM('PL OZON (нед)'!C48:G48) -> 0 | D48: =SUM('PL OZON (нед)'!H48:K48) -> 0 | E48: =SUM('PL OZON (нед)'!L48:O48) -> 0 | F48: =SUM('PL OZON (нед)'!P48:S48) -> 0 | G48: =SUM('PL OZON (нед)'!T48:X48) -> 0 | H48: =SUM('PL OZON (нед)'!Y48:AB48) -> 0 | I48: =SUM('PL OZON (нед)'!AC48:AF48) -> 0 | J48: =SUM('PL OZON (нед)'!AG48:AK48) -> 0 | K48: =SUM('PL OZON (нед)'!AL48:AO48) -> 0 | L48: =SUM('PL OZON (нед)'!AP48:AT48) -> 0 | M48: =SUM('PL OZON (нед)'!AU48:AX48) -> 0 | N48: =SUM('PL OZON (нед)'!AY48:BB48) -> 0 | O48: =SUM(C48:N48) -> 0
A49: Реклама внешняя | C49: =SUM('PL OZON (нед)'!C49:G49) -> 0 | D49: =SUM('PL OZON (нед)'!H49:K49) -> 0 | E49: =SUM('PL OZON (нед)'!L49:O49) -> 0 | F49: =SUM('PL OZON (нед)'!P49:S49) -> 0 | G49: =SUM('PL OZON (нед)'!T49:X49) -> 0 | H49: =SUM('PL OZON (нед)'!Y49:AB49) -> 0 | I49: =SUM('PL OZON (нед)'!AC49:AF49) -> 0 | J49: =SUM('PL OZON (нед)'!AG49:AK49) -> 0 | K49: =SUM('PL OZON (нед)'!AL49:AO49) -> 0 | L49: =SUM('PL OZON (нед)'!AP49:AT49) -> 0 | M49: =SUM('PL OZON (нед)'!AU49:AX49) -> 0 | N49: =SUM('PL OZON (нед)'!AY49:BB49) -> 0 | O49: =SUM(C49:N49) -> 0
A50: Подписка Аналитика | C50: =SUM('PL OZON (нед)'!C50:G50) -> 0 | D50: =SUM('PL OZON (нед)'!H50:K50) -> 0 | E50: =SUM('PL OZON (нед)'!L50:O50) -> 0 | F50: =SUM('PL OZON (нед)'!P50:S50) -> 0 | G50: =SUM('PL OZON (нед)'!T50:X50) -> 0 | H50: =SUM('PL OZON (нед)'!Y50:AB50) -> 0 | I50: =SUM('PL OZON (нед)'!AC50:AF50) -> 0 | J50: =SUM('PL OZON (нед)'!AG50:AK50) -> 0 | K50: =SUM('PL OZON (нед)'!AL50:AO50) -> 0 | L50: =SUM('PL OZON (нед)'!AP50:AT50) -> 0 | M50: =SUM('PL OZON (нед)'!AU50:AX50) -> 0 | N50: =SUM('PL OZON (нед)'!AY50:BB50) -> 0 | O50: =SUM(C50:N50) -> 0
A51: Прочие | C51: =SUM('PL OZON (нед)'!C51:G51) -> 0 | D51: =SUM('PL OZON (нед)'!H51:K51) -> 0 | E51: =SUM('PL OZON (нед)'!L51:O51) -> 0 | F51: =SUM('PL OZON (нед)'!P51:S51) -> 0 | G51: =SUM('PL OZON (нед)'!T51:X51) -> 0 | H51: =SUM('PL OZON (нед)'!Y51:AB51) -> 0 | I51: =SUM('PL OZON (нед)'!AC51:AF51) -> 0 | J51: =SUM('PL OZON (нед)'!AG51:AK51) -> 0 | K51: =SUM('PL OZON (нед)'!AL51:AO51) -> 0 | L51: =SUM('PL OZON (нед)'!AP51:AT51) -> 0 | M51: =SUM('PL OZON (нед)'!AU51:AX51) -> 0 | N51: =SUM('PL OZON (нед)'!AY51:BB51) -> 0 | O51: =SUM(C51:N51) -> 0
A53: Прибыль до налогообложения | C53: =C36+C31-C38 -> 54676 | D53: =D36+D31-D38 -> 30471 | E53: =E36+E31-E38 -> 29340 | F53: =F36+F31-F38 -> 10542 | G53: =G36+G31-G38 -> 0 | H53: =H36+H31-H38 -> 0 | I53: =I36+I31-I38 -> 0 | J53: =J36+J31-J38 -> 0 | ... N53: =N36+N31-N38 -> 0 | O53: =SUM(C53:N53) -> 125029
A55: Налоги начисленные | B55: УСН 6%+1% | C55: =C14*7% -> 27912.57 | D55: =D14*7% -> 18017.51 | E55: =E14*7% -> 11539.43 | F55: =F14*7% -> 5203.73 | G55: =G14*7% -> 0 | H55: =H14*7% -> 0 | I55: =I14*7% -> 0 | J55: =J14*7% -> 0 | ... N55: =N14*7% -> 0 | O55: =SUM(C55:N55) -> 62673.24
A57: Чистая прибыль | C57: =C53-C55 -> 26763.43 | D57: =D53-D55 -> 12453.49 | E57: =E53-E55 -> 17800.57 | F57: =F53-F55 -> 5338.27 | G57: =G53-G55 -> 0 | H57: =H53-H55 -> 0 | I57: =I53-I55 -> 0 | J57: =J53-J55 -> 0 | ... N57: =N53-N55 -> 0 | O57: =SUM(C57:N57) -> 62355.76
A58: Рентабельность вложений | C58: =IFERROR(C38/C14,0) -> 0.30626381 | D58: =IFERROR(D38/D14,0) -> 0.30869915 | E58: =IFERROR(E38/E14,0) -> 0.24891264 | F58: =IFERROR(F38/F14,0) -> 0.22899151 | G58: =IFERROR(G38/G14,0) -> 0 | H58: =IFERROR(H38/H14,0) -> 0 | I58: =IFERROR(I38/I14,0) -> 0 | J58: =IFERROR(J38/J14,0) -> 0 | ... O58: =IFERROR(O38/O14,0) -> 0.28998852
A59: Маржинальность | C59: =IFERROR(C57/C14,0) -> 0.067118151 | D59: =IFERROR(D57/D14,0) -> 0.048383173 | E59: =IFERROR(E57/E14,0) -> 0.10798106 | F59: =IFERROR(F57/F14,0) -> 0.071809817 | G59: =IFERROR(G57/G14,0) -> 0 | H59: =IFERROR(H57/H14,0) -> 0 | I59: =IFERROR(I57/I14,0) -> 0 | J59: =IFERROR(J57/J14,0) -> 0 | ... O59: =IFERROR(O57/O14,0) -> 0.069645405
A60: Выплата диведентов: | C60: =CF!C38 -> 0 | D60: =CF!D38 -> 0 | E60: =CF!E38 -> 0 | F60: =CF!F38 -> 0 | G60: =CF!G38 -> 0 | H60: =CF!H38 -> 0 | I60: =CF!I38 -> 0 | J60: =CF!J38 -> 0 | ... N60: =CF!N38 -> 0
A62: Остаток денежных средств на конец периода ВСЕГО | C62: =CF!C42 -> 2426951.9 | D62: =CF!D42 -> 2920729.8 | E62: =CF!E42 -> 3317903.7 | F62: =CF!F42 -> 3497581.5 | G62: =CF!G42 -> 3497581.5 | H62: =CF!H42 -> 3497581.5 | I62: =CF!I42 -> 3497581.5 | J62: =CF!J42 -> 3497581.5 | ... N62: =CF!N42 -> 3497581.5
A64: Накопленный финансовый результат | C64: ='PL OZON (нед)'!G64 -> 319607.51 | D64: =D57+C64-D60 -> 332061 | E64: =E57+D64-E60 -> 349861.57 | F64: =F57+E64-F60 -> 355199.84 | G64: =G57+F64-G60 -> 355199.84 | H64: =H57+G64-H60 -> 355199.84 | I64: =I57+H64-I60 -> 355199.84 | J64: =J57+I64-J60 -> 355199.84 | K64: =K57+J64-K60 -> 355199.84 | ... N64: =N57+M64-N60 -> 355199.84
A66: Рекламные расходы на 1 единицу | C66: =IFERROR(C41/C7, ) -> 19.549505 | D66: =IFERROR(D41/D7, ) -> 20.294872 | E66: =IFERROR(E41/E7, ) -> 13.516807 | F66: =IFERROR(F41/F7, ) -> 3.0737705 | G66: =IFERROR(G41/G7, ) -> 0 | H66: =IFERROR(H41/H7, ) -> 0 | I66: =IFERROR(I41/I7, ) -> 0 | J66: =IFERROR(J41/J7, ) -> 0 | ... N66: =IFERROR(N41/N7, ) -> 0
A67: Доля рекламных расходов | C67: =IFERROR(C41/C15, ) -> 0 | D67: =IFERROR(D41/D15, ) -> 0 | E67: =IFERROR(E41/E15, ) -> 0 | F67: =IFERROR(F41/F15, ) -> 0 | G67: =IFERROR(G41/G15, ) -> 0 | H67: =IFERROR(H41/H15, ) -> 0 | I67: =IFERROR(I41/I15, ) -> 0 | J67: =IFERROR(J41/J15, ) -> 0 | ... N67: =IFERROR(N41/N15, ) -> 0
A68: Чистая прибыль на 1 ед | C68: =IFERROR(C57/(C7-C23), ) -> 44.980555 | D68: =IFERROR(D57/(D7-D23), ) -> 32.262927 | E68: =IFERROR(E57/(E7-E23), ) -> 77.393783 | F68: =IFERROR(F57/(F7-F23), ) -> 44.117934 | G68: =IFERROR(G57/(G7-G23), ) -> 0 | H68: =IFERROR(H57/(H7-H23), ) -> 0 | I68: =IFERROR(I57/(I7-I23), ) -> 0 | J68: =IFERROR(J57/(J7-J23), ) -> 0 | ... N68: =IFERROR(N57/(N7-N23), ) -> 0

Sheet CF (нед)
A1: Заполняем Вложения инвестора, Закупки и выплаты дивидендов. Формулы не трогаем! | C1: ='PL WB (нед)'!C1 -> 1 | D1: ='PL WB (нед)'!D1 -> 2 | E1: ='PL WB (нед)'!E1 -> 3 | F1: ='PL WB (нед)'!F1 -> 4 | G1: ='PL WB (нед)'!G1 -> 5 | H1: ='PL WB (нед)'!H1 -> 6 | I1: ='PL WB (нед)'!I1 -> 7 | J1: ='PL WB (нед)'!J1 -> 8 | ... BC1: ='PL WB (нед)'!BC1 -> Остаток года
A2: Движение денежных средств, еженедельно | C2: Январь | H2: Февраль | L2: Март | P2: Апрель | T2: Май | Y2: Июнь | AC2: Июль | AG2: Август | AL2: Сентябрь | AP2: Октябрь | AU2: Ноябрь | AY2: Декабрь
C3: ='PL WB (нед)'!C3 -> NaN | D3: ='PL WB (нед)'!D3 -> NaN | E3: ='PL WB (нед)'!E3 -> NaN | F3: ='PL WB (нед)'!F3 -> NaN | G3: ='PL WB (нед)'!G3 -> NaN | H3: ='PL WB (нед)'!H3 -> NaN | I3: ='PL WB (нед)'!I3 -> NaN | J3: ='PL WB (нед)'!J3 -> NaN | ... BB3: ='PL WB (нед)'!BB3 -> 0 | BC3: 29.12-31.12
A4: Поступление товара по цене закупки | C4: ='PL WB (нед)'!C10+'PL OZON (нед)'!C10 -> 192398.77 | D4: ='PL WB (нед)'!D10+'PL OZON (нед)'!D10 -> 0 | E4: ='PL WB (нед)'!E10+'PL OZON (нед)'!E10 -> 0 | F4: ='PL WB (нед)'!F10+'PL OZON (нед)'!F10 -> 0 | G4: ='PL WB (нед)'!G10+'PL OZON (нед)'!G10 -> 0 | H4: ='PL WB (нед)'!H10+'PL OZON (нед)'!H10 -> 0 | I4: ='PL WB (нед)'!I10+'PL OZON (нед)'!I10 -> 0 | J4: ='PL WB (нед)'!J10+'PL OZON (нед)'!J10 -> 0 | ... BC4: ='PL WB (нед)'!BC10+'PL OZON (нед)'!BC10 -> 0
A5: Доступно на складе по цене закупки | C5: ='PL WB (нед)'!C12+'PL OZON (нед)'!C12 -> 1750051.4 | D5: ='PL WB (нед)'!D12+'PL OZON (нед)'!D12 -> 1699921.4 | E5: ='PL WB (нед)'!E12+'PL OZON (нед)'!E12 -> 1636488.3 | F5: ='PL WB (нед)'!F12+'PL OZON (нед)'!F12 -> 1578712.1 | G5: ='PL WB (нед)'!G12+'PL OZON (нед)'!G12 -> 1522905.6 | H5: ='PL WB (нед)'!H12+'PL OZON (нед)'!H12 -> 1464964.6 | I5: ='PL WB (нед)'!I12+'PL OZON (нед)'!I12 -> 1407602.6 | J5: ='PL WB (нед)'!J12+'PL OZON (нед)'!J12 -> 1351365.3 | ... BC5: ='PL WB (нед)'!BC12+'PL OZON (нед)'!BC12 -> 1399376.7
A7: Остаток денежных средств на начало периода | C7: 1967240.9 | D7: =C42 -> 1994177.9 | E7: =D42 -> 2100356.8 | F7: =E42 -> 2234359.4 | G7: =F42 -> 2340085.2 | H7: =G42 -> 2444316.6 | I7: =H42 -> 2568251.9 | J7: =I42 -> 2701831.8 | K7: =J42 -> 2827470.9 | ... BC7: =BB42 -> 3539892.4
A9: Поступление на счет от WB и OZON | C9: ='PL WB (нед)'!C30+'PL OZON (нед)'!C30 -> 31286.58 | D9: ='PL WB (нед)'!D30+'PL OZON (нед)'!D30 -> 120536.43 | E9: ='PL WB (нед)'!E30+'PL OZON (нед)'!E30 -> 151466.28 | F9: ='PL WB (нед)'!F30+'PL OZON (нед)'!F30 -> 122932.22 | G9: ='PL WB (нед)'!G30+'PL OZON (нед)'!G30 -> 123720.12 | H9: ='PL WB (нед)'!H30+'PL OZON (нед)'!H30 -> 139323.16 | I9: ='PL WB (нед)'!I30+'PL OZON (нед)'!I30 -> 150601.46 | J9: ='PL WB (нед)'!J30+'PL OZON (нед)'!J30 -> 141210.31 | ... BC9: ='PL WB (нед)'!BC30+'PL OZON (нед)'!BC30 -> 0
A11: Итого остаток + поступление | C11: =C7+C9 -> 1998527.5 | D11: =D7+D9 -> 2114714.3 | E11: =E7+E9 -> 2251823 | F11: =F7+F9 -> 2357291.6 | G11: =G7+G9 -> 2463805.4 | H11: =H7+H9 -> 2583639.8 | I11: =I7+I9 -> 2718853.4 | J11: =J7+J9 -> 2843042.1 | ... BC11: =BC7+BC9 -> 3539892.4
A13: Расходы - факт списания | C13: =SUM(C14:C19) -> 634 | D13: =SUM(D14:D19) -> 1139 | E13: =SUM(E14:E19) -> 2225 | F13: =SUM(F14:F19) -> 2475 | G13: =SUM(G14:G19) -> 5374 | H13: =SUM(H14:H19) -> 2254 | I13: =SUM(I14:I19) -> 3404 | J13: =SUM(J14:J19) -> 1721 | ... BC13: =SUM(BC14:BC19) -> 0
A14: Контент | C14: ='PL WB (нед)'!C47+'PL OZON (нед)'!C47 -> 0 | D14: ='PL WB (нед)'!D47+'PL OZON (нед)'!D47 -> 0 | E14: ='PL WB (нед)'!E47+'PL OZON (нед)'!E47 -> 0 | F14: ='PL WB (нед)'!F47+'PL OZON (нед)'!F47 -> 0 | G14: ='PL WB (нед)'!G47+'PL OZON (нед)'!G47 -> 0 | H14: ='PL WB (нед)'!H47+'PL OZON (нед)'!H47 -> 0 | I14: ='PL WB (нед)'!I47+'PL OZON (нед)'!I47 -> 0 | J14: ='PL WB (нед)'!J47+'PL OZON (нед)'!J47 -> 0 | ... BC14: ='PL WB (нед)'!BC47+'PL OZON (нед)'!BC47 -> 0
A15: Аренда офиса | C15: ='PL WB (нед)'!C48+'PL OZON (нед)'!C48 -> 0 | D15: ='PL WB (нед)'!D48+'PL OZON (нед)'!D48 -> 0 | E15: ='PL WB (нед)'!E48+'PL OZON (нед)'!E48 -> 0 | F15: ='PL WB (нед)'!F48+'PL OZON (нед)'!F48 -> 0 | G15: ='PL WB (нед)'!G48+'PL OZON (нед)'!G48 -> 0 | H15: ='PL WB (нед)'!H48+'PL OZON (нед)'!H48 -> 0 | I15: ='PL WB (нед)'!I48+'PL OZON (нед)'!I48 -> 0 | J15: ='PL WB (нед)'!J48+'PL OZON (нед)'!J48 -> 0 | ... BC15: ='PL WB (нед)'!BC48+'PL OZON (нед)'!BC48 -> 0
A16: Реклама внешняя | C16: ='PL WB (нед)'!C49+'PL OZON (нед)'!C49 -> 0 | D16: ='PL WB (нед)'!D49+'PL OZON (нед)'!D49 -> 0 | E16: ='PL WB (нед)'!E49+'PL OZON (нед)'!E49 -> 0 | F16: ='PL WB (нед)'!F49+'PL OZON (нед)'!F49 -> 0 | G16: ='PL WB (нед)'!G49+'PL OZON (нед)'!G49 -> 0 | H16: ='PL WB (нед)'!H49+'PL OZON (нед)'!H49 -> 0 | I16: ='PL WB (нед)'!I49+'PL OZON (нед)'!I49 -> 0 | J16: ='PL WB (нед)'!J49+'PL OZON (нед)'!J49 -> 0 | ... BC16: ='PL WB (нед)'!BC49+'PL OZON (нед)'!BC49 -> 0
A17: Продвижение | C17: ='PL WB (нед)'!C41+'PL OZON (нед)'!C41 -> 634 | D17: ='PL WB (нед)'!D41+'PL OZON (нед)'!D41 -> 1139 | E17: ='PL WB (нед)'!E41+'PL OZON (нед)'!E41 -> 2225 | F17: ='PL WB (нед)'!F41+'PL OZON (нед)'!F41 -> 2475 | G17: ='PL WB (нед)'!G41+'PL OZON (нед)'!G41 -> 5374 | H17: ='PL WB (нед)'!H41+'PL OZON (нед)'!H41 -> 2254 | I17: ='PL WB (нед)'!I41+'PL OZON (нед)'!I41 -> 3404 | J17: ='PL WB (нед)'!J41+'PL OZON (нед)'!J41 -> 1721 | ... BC17: ='PL WB (нед)'!BC41+'PL OZON (нед)'!BC41 -> 0
A18: Подписка Аналитика | C18: ='PL WB (нед)'!C51+'PL OZON (нед)'!C51 -> 0 | D18: ='PL WB (нед)'!D51+'PL OZON (нед)'!D51 -> 0 | E18: ='PL WB (нед)'!E51+'PL OZON (нед)'!E51 -> 0 | F18: ='PL WB (нед)'!F51+'PL OZON (нед)'!F51 -> 0 | G18: ='PL WB (нед)'!G51+'PL OZON (нед)'!G51 -> 0 | H18: ='PL WB (нед)'!H51+'PL OZON (нед)'!H51 -> 0 | I18: ='PL WB (нед)'!I50+'PL OZON (нед)'!I50 -> 0 | J18: ='PL WB (нед)'!J50+'PL OZON (нед)'!J50 -> 0 | K18: ='PL WB (нед)'!K50+'PL OZON (нед)'!K50 -> 0 | L18: ='PL WB (нед)'!L50+'PL OZON (нед)'!L50 -> 0 | M18: ='PL WB (нед)'!M50+'PL OZON (нед)'!M50 -> 0 | N18: ='PL WB (нед)'!N50+'PL OZON (нед)'!N50 -> 0 | O18: ='PL WB (нед)'!O50+'PL OZON (нед)'!O50 -> 0 | P18: ='PL WB (нед)'!P50+'PL OZON (нед)'!P50 -> 0 | ... BC18: ='PL WB (нед)'!BC50+'PL OZON (нед)'!BC50 -> 0
A19: Прочее | C19: ='PL WB (нед)'!C51+'PL OZON (нед)'!C51 -> 0 | D19: ='PL WB (нед)'!D51+'PL OZON (нед)'!D51 -> 0 | E19: ='PL WB (нед)'!E51+'PL OZON (нед)'!E51 -> 0 | F19: ='PL WB (нед)'!F51+'PL OZON (нед)'!F51 -> 0 | G19: ='PL WB (нед)'!G51+'PL OZON (нед)'!G51 -> 0 | H19: ='PL WB (нед)'!H51+'PL OZON (нед)'!H51 -> 0 | I19: ='PL WB (нед)'!I51+'PL OZON (нед)'!I51 -> 0 | J19: ='PL WB (нед)'!J51+'PL OZON (нед)'!J51 -> 0 | ... BC19: ='PL WB (нед)'!BC51+'PL OZON (нед)'!BC51 -> 0
A21: Налоги уплаченные | C21: ='PL WB (нед)'!C55+'PL OZON (нед)'!C55 -> 3715.62 | D21: ='PL WB (нед)'!D55+'PL OZON (нед)'!D55 -> 13218.57 | E21: ='PL WB (нед)'!E55+'PL OZON (нед)'!E55 -> 15238.68 | F21: ='PL WB (нед)'!F55+'PL OZON (нед)'!F55 -> 14731.34 | G21: ='PL WB (нед)'!G55+'PL OZON (нед)'!G55 -> 14114.74 | H21: ='PL WB (нед)'!H55+'PL OZON (нед)'!H55 -> 13133.83 | I21: ='PL WB (нед)'!I55+'PL OZON (нед)'!I55 -> 13617.64 | J21: ='PL WB (нед)'!J55+'PL OZON (нед)'!J55 -> 13850.17 | ... BC21: ='PL WB (нед)'!BC55+'PL OZON (нед)'!BC55 -> 0
A23: Закупка Китай
A24: Закупка нал
A25: Закупка р/с
A26: Доставка Китай
A27: Доставка РФ
A29: Вложения инвестора
A31: Самовыкупы (покупка товара)
A33: Остаток денежных средств на конец периода | C33: =C11-C13-C21-SUM(C23:C27)+C29-C31 -> 1994177.9 | D33: =D11-D13-D21-SUM(D23:D27)+D29-D31 -> 2100356.8 | E33: =E11-E13-E21-SUM(E23:E27)+E29-E31 -> 2234359.4 | F33: =F11-F13-F21-SUM(F23:F27)+F29-F31 -> 2340085.2 | G33: =G11-G13-G21-SUM(G23:G27)+G29-G31 -> 2444316.6 | H33: =H11-H13-H21-SUM(H23:H27)+H29-H31 -> 2568251.9 | I33: =I11-I13-I21-SUM(I23:I27)+I29-I31 -> 2701831.8 | J33: =J11-J13-J21-SUM(J23:J27)+J29-J31 -> 2827470.9 | ... BC33: =BC11-BC13-BC21-SUM(BC23:BC27)+BC29-BC31 -> 3539892.4
B35: Авансы уплаченные | C35: =283707+SUM(C23:C27)-C4 -> 91308.23 | D35: =C35+SUM(D23:D27)-D4 -> 91308.23 | E35: =D35+SUM(E23:E27)-E4 -> 91308.23 | F35: =E35+SUM(F23:F27)-F4 -> 91308.23 | G35: =F35+SUM(G23:G27)-G4 -> 91308.23 | H35: =G35+SUM(H23:H27)-H4 -> 91308.23 | I35: =H35+SUM(I23:I27)-I4 -> 91308.23 | J35: =I35+SUM(J23:J27)-J4 -> 91308.23 | K35: =J35+SUM(K23:K27)-K4 -> 91308.23 | ... BC35: =BB35+SUM(BC23:BC27)-BC4 -> 91308.23
B36: Денег в обороте | C36: =C5+C42+C35 -> 3835537.6 | D36: =D5+D42+D35 -> 3891586.4 | E36: =E5+E42+E35 -> 3962155.9 | F36: =F5+F42+F35 -> 4010105.5 | G36: =G5+G42+G35 -> 4058530.5 | H36: =H5+H42+H35 -> 4124524.8 | I36: =I5+I42+I35 -> 4200742.6 | J36: =J5+J42+J35 -> 4270144.5 | ... BC36: =BC5+BC42+BC35 -> 5030577.3
G37: =G36-CF!C36 -> 17364.73 | K37: =K36-CF!D36 -> 31050.17
A38: Выплата диведентов: | C38: =C39+C40 -> 0 | D38: =D39+D40 -> 0 | E38: =E39+E40 -> 0 | F38: =F39+F40 -> 0 | G38: =G39+G40 -> 0 | H38: =H39+H40 -> 0 | I38: =I39+I40 -> 0 | J38: =J39+J40 -> 0 | ... BC38: =BC39+BC40 -> 0
A39: Инвестор | B39: Остаток после вывода должен быть больше суммы закупки и доставки следующего месяца
A40: Управляющий
G41: =G42-CF!C42 -> 17364.73 | K41: =K42-CF!D42 -> 31050.17 | O41: =O42-CF!E42 -> 39546.24 | S41: =S42-CF!F42 -> 42310.91 | X41: =X42-CF!G42 -> 42310.91 | AB41: =AB42-CF!H42 -> 42310.91 | AF41: =AF42-CF!I42 -> 42310.91 | AK41: =AK42-CF!J42 -> 42310.91 | AO41: =AO42-CF!K42 -> 42310.91 | AT41: =AT42-CF!L42 -> 42310.91 | AX41: =AX42-CF!M42 -> 42310.91 | BB41: =BB42-CF!N42 -> 42310.91 | BC41: =BC42-CF!O42 -> 3539892.4
A42: Остаток денежных средств на конец периода | C42: =C33-C38 -> 1994177.9 | D42: =D33-D38 -> 2100356.8 | E42: =E33-E38 -> 2234359.4 | F42: =F33-F38 -> 2340085.2 | G42: =G33-G38 -> 2444316.6 | H42: =H33-H38 -> 2568251.9 | I42: =I33-I38 -> 2701831.8 | J42: =J33-J38 -> 2827470.9 | ... BC42: =BC33-BC38 -> 3539892.4
B43: Накопленный финансовый результат | C43: ='PL WB (нед)'!C64+'PL OZON (нед)'!C64 -> 3330259.1 | D43: ='PL WB (нед)'!D64+'PL OZON (нед)'!D64 -> 3387447 | E43: ='PL WB (нед)'!E64+'PL OZON (нед)'!E64 -> 3460241.4 | F43: ='PL WB (нед)'!F64+'PL OZON (нед)'!F64 -> 3510666.1 | G43: ='PL WB (нед)'!G64+'PL OZON (нед)'!G64 -> 3564465 | H43: ='PL WB (нед)'!H64+'PL OZON (нед)'!H64 -> 3632713.4 | I43: ='PL WB (нед)'!I64+'PL OZON (нед)'!I64 -> 3712335.1 | J43: ='PL WB (нед)'!J64+'PL OZON (нед)'!J64 -> 3783458 | ... BC43: ='PL WB (нед)'!BC64+'PL OZON (нед)'!BC64 -> 3378248.9
G44: =G43-'PL OZON'!C64 -> 3244857.5 | K44: =K43-CF!D43 -> 5770.44 | O44: =O43-CF!E43 -> 11049.51 | S44: =S43-CF!F43 -> 13439.18 | X44: =X43-CF!G43 -> 13439.18 | AB44: =AB43-CF!H43 -> 13439.18 | AF44: =AF43-CF!I43 -> 13439.18 | AK44: =AK43-CF!J43 -> 13439.18 | AO44: =AO43-CF!K43 -> 13439.18 | AT44: =AT43-CF!L43 -> 13439.18 | AX44: =AX43-CF!M43 -> 13439.18 | BB44: =BB43-CF!N43 -> 13439.18
A45: Серые нули (стр 34, 38, 41) - это проверки между листами! Если не ноль - ищем ошибку

Sheet CF
A1: Заполняем PL и CF еженедельный!
A2: Движение денежных средств | C2: 2023
C3: Январь | D3: Февраль | E3: Март | F3: Апрель | G3: Май | H3: Июнь | I3: Июль | J3: Август | K3: Сентябрь | L3: Октябрь | M3: Ноябрь | N3: Декабрь
A4: Поступление товара по цене закупки | C4: ='PL WB'!C10+'PL OZON'!C10 -> 192398.77 | D4: ='PL WB'!D10+'PL OZON'!D10 -> 0 | E4: ='PL WB'!E10+'PL OZON'!E10 -> 0 | F4: ='PL WB'!F10+'PL OZON'!F10 -> 0 | G4: ='PL WB'!G10+'PL OZON'!G10 -> 0 | H4: ='PL WB'!H10+'PL OZON'!H10 -> 0 | I4: ='PL WB'!I10+'PL OZON'!I10 -> 0 | J4: ='PL WB'!J10+'PL OZON'!J10 -> 0 | ... N4: ='PL WB'!N10+'PL OZON'!N10 -> 0 | O4: =SUM(C4:N4) -> 192398.77
A5: Доступно на складе по цене закупки | C5: ='PL WB'!C12+'PL OZON'!C12 -> 1522905.6 | D5: ='PL WB'!D12+'PL OZON'!D12 -> 1301418.9 | E5: ='PL WB'!E12+'PL OZON'!E12 -> 1109069.5 | F5: ='PL WB'!F12+'PL OZON'!F12 -> 1028078.6 | G5: ='PL WB'!G12+'PL OZON'!G12 -> 1028078.6 | H5: ='PL WB'!H12+'PL OZON'!H12 -> 1028078.6 | I5: ='PL WB'!I12+'PL OZON'!I12 -> 1028078.6 | J5: ='PL WB'!J12+'PL OZON'!J12 -> 1028078.6 | ... N5: ='PL WB'!N12+'PL OZON'!N12 -> 1028078.6
A7: Остаток денежных средств на начало периода | C7: ='CF (нед)'!C7 -> 1967240.9 | D7: =C42 -> 2426951.9 | E7: =D42 -> 2920729.8 | F7: =E42 -> 3317903.7 | G7: =F42 -> 3497581.5 | H7: =G42 -> 3497581.5 | I7: =H42 -> 3497581.5 | J7: =I42 -> 3497581.5 | K7: =J42 -> 3497581.5 | ... N7: =M42 -> 3497581.5
A9: Поступление на счет | C9: ='PL WB'!C30+'PL OZON'!C30 -> 538094.63 | D9: ='PL WB'!D30+'PL OZON'!D30 -> 560103.5 | E9: ='PL WB'!E30+'PL OZON'!E30 -> 448883.78 | F9: ='PL WB'!F30+'PL OZON'!F30 -> 201984.28 | G9: ='PL WB'!G30+'PL OZON'!G30 -> 0 | H9: ='PL WB'!H30+'PL OZON'!H30 -> 0 | I9: ='PL WB'!I30+'PL OZON'!I30 -> 0 | J9: ='PL WB'!J30+'PL OZON'!J30 -> 0 | ... N9: ='PL WB'!N30+'PL OZON'!N30 -> 0 | O9: =SUM(C9:N9) -> 1749066.2
A11: Итого остаток + поступление | C11: =C7+C9 -> 2505335.6 | D11: =D7+D9 -> 2987055.4 | E11: =E7+E9 -> 3369613.6 | F11: =F7+F9 -> 3519887.9 | G11: =G7+G9 -> 3497581.5 | H11: =H7+H9 -> 3497581.5 | I11: =I7+I9 -> 3497581.5 | J11: =J7+J9 -> 3497581.5 | ... N11: =N7+N9 -> 3497581.5
A13: Расходы - факт списания | C13: =SUM(C14:C19) -> 11847 | D13: =SUM(D14:D19) -> 7915 | E13: =SUM(E14:E19) -> 3217 | F13: =SUM(F14:F19) -> 375 | G13: =SUM(G14:G19) -> 0 | H13: =SUM(H14:H19) -> 0 | I13: =SUM(I14:I19) -> 0 | J13: =SUM(J14:J19) -> 0 | ... N13: =SUM(N14:N19) -> 0 | O13: =SUM(C13:N13) -> 23354
A14: Контент | C14: ='PL WB'!C47+'PL OZON'!C47 -> 0 | D14: ='PL WB'!D47+'PL OZON'!D47 -> 0 | E14: ='PL WB'!E47+'PL OZON'!E47 -> 0 | F14: ='PL WB'!F47+'PL OZON'!F47 -> 0 | G14: ='PL WB'!G47+'PL OZON'!G47 -> 0 | H14: ='PL WB'!H47+'PL OZON'!H47 -> 0 | I14: ='PL WB'!I47+'PL OZON'!I47 -> 0 | J14: ='PL WB'!J47+'PL OZON'!J47 -> 0 | ... N14: ='PL WB'!N47+'PL OZON'!N47 -> 0 | O14: =SUM(C14:N14) -> 0
A15: Аренда офиса | C15: ='PL WB'!C48+'PL OZON'!C48 -> 0 | D15: ='PL WB'!D48+'PL OZON'!D48 -> 0 | E15: ='PL WB'!E48+'PL OZON'!E48 -> 0 | F15: ='PL WB'!F48+'PL OZON'!F48 -> 0 | G15: ='PL WB'!G48+'PL OZON'!G48 -> 0 | H15: ='PL WB'!H48+'PL OZON'!H48 -> 0 | I15: ='PL WB'!I48+'PL OZON'!I48 -> 0 | J15: ='PL WB'!J48+'PL OZON'!J48 -> 0 | ... N15: ='PL WB'!N48+'PL OZON'!N48 -> 0 | O15: =SUM(C15:N15) -> 0
A16: Реклама внешняя | C16: ='PL WB'!C49+'PL OZON'!C49 -> 0 | D16: ='PL WB'!D49+'PL OZON'!D49 -> 0 | E16: ='PL WB'!E49+'PL OZON'!E49 -> 0 | F16: ='PL WB'!F49+'PL OZON'!F49 -> 0 | G16: ='PL WB'!G49+'PL OZON'!G49 -> 0 | H16: ='PL WB'!H49+'PL OZON'!H49 -> 0 | I16: ='PL WB'!I49+'PL OZON'!I49 -> 0 | J16: ='PL WB'!J49+'PL OZON'!J49 -> 0 | ... N16: ='PL WB'!N49+'PL OZON'!N49 -> 0 | O16: =SUM(C16:N16) -> 0
A17: Продвижение | C17: ='PL WB'!C41+'PL OZON'!C41 -> 11847 | D17: ='PL WB'!D41+'PL OZON'!D41 -> 7915 | E17: ='PL WB'!E41+'PL OZON'!E41 -> 3217 | F17: ='PL WB'!F41+'PL OZON'!F41 -> 375 | G17: ='PL WB'!G41+'PL OZON'!G41 -> 0 | H17: ='PL WB'!H41+'PL OZON'!H41 -> 0 | I17: ='PL WB'!I41+'PL OZON'!I41 -> 0 | J17: ='PL WB'!J41+'PL OZON'!J41 -> 0 | ... N17: ='PL WB'!N41+'PL OZON'!N41 -> 0 | O17: =SUM(C17:N17) -> 23354
A18: Подписка Аналитика | C18: ='PL WB'!C50+'PL OZON'!C50 -> 0 | D18: ='PL WB'!D50+'PL OZON'!D50 -> 0 | E18: ='PL WB'!E50+'PL OZON'!E50 -> 0 | F18: ='PL WB'!F50+'PL OZON'!F50 -> 0 | G18: ='PL WB'!G50+'PL OZON'!G50 -> 0 | H18: ='PL WB'!H50+'PL OZON'!H50 -> 0 | I18: ='PL WB'!I50+'PL OZON'!I50 -> 0 | J18: ='PL WB'!J50+'PL OZON'!J50 -> 0 | ... N18: ='PL WB'!N50+'PL OZON'!N50 -> 0 | O18: =SUM(C18:N18) -> 0
C19: ='PL WB'!C51+'PL OZON'!C51 -> 0 | D19: ='PL WB'!D51+'PL OZON'!D51 -> 0 | E19: ='PL WB'!E51+'PL OZON'!E51 -> 0 | F19: ='PL WB'!F51+'PL OZON'!F51 -> 0 | G19: ='PL WB'!G51+'PL OZON'!G51 -> 0 | H19: ='PL WB'!H51+'PL OZON'!H51 -> 0 | I19: ='PL WB'!I51+'PL OZON'!I51 -> 0 | J19: ='PL WB'!J51+'PL OZON'!J51 -> 0 | ... N19: ='PL WB'!N51+'PL OZON'!N51 -> 0 | O19: =SUM(C19:N19) -> 0
A21: Налоги уплаченные | C21: ='PL WB'!C55+'PL OZON'!C55 -> 66536.68 | D21: ='PL WB'!D55+'PL OZON'!D55 -> 58410.59 | E21: ='PL WB'!E55+'PL OZON'!E55 -> 48492.92 | F21: ='PL WB'!F55+'PL OZON'!F55 -> 21931.42 | G21: ='PL WB'!G55+'PL OZON'!G55 -> 0 | H21: ='PL WB'!H55+'PL OZON'!H55 -> 0 | I21: ='PL WB'!I55+'PL OZON'!I55 -> 0 | J21: ='PL WB'!J55+'PL OZON'!J55 -> 0 | ... N21: ='PL WB'!N55+'PL OZON'!N55 -> 0 | O21: =SUM(C21:N21) -> 195371.61
A23: Закупка Китай | C23: =SUM('CF (нед)'!C23:G23) -> 0 | D23: =SUM('CF (нед)'!H23:K23) -> 0 | E23: =SUM('CF (нед)'!L23:O23) -> 0 | F23: =SUM('CF (нед)'!P23:S23) -> 0 | G23: =SUM('CF (нед)'!T23:X23) -> 0 | H23: =SUM('CF (нед)'!Y23:AB23) -> 0 | I23: =SUM('CF (нед)'!AC23:AF23) -> 0 | J23: =SUM('CF (нед)'!AG23:AK23) -> 0 | K23: =SUM('CF (нед)'!AL23:AO23) -> 0 | L23: =SUM('CF (нед)'!AP23:AT23) -> 0 | M23: =SUM('CF (нед)'!AU23:AX23) -> 0 | N23: =SUM('CF (нед)'!AY23:BB23) -> 0 | O23: =SUM(C23:N23) -> 0
A24: Закупка нал | C24: =SUM('CF (нед)'!C24:G24) -> 0 | D24: =SUM('CF (нед)'!H24:K24) -> 0 | E24: =SUM('CF (нед)'!L24:O24) -> 0 | F24: =SUM('CF (нед)'!P24:S24) -> 0 | G24: =SUM('CF (нед)'!T24:X24) -> 0 | H24: =SUM('CF (нед)'!Y24:AB24) -> 0 | I24: =SUM('CF (нед)'!AC24:AF24) -> 0 | J24: =SUM('CF (нед)'!AG24:AK24) -> 0 | K24: =SUM('CF (нед)'!AL24:AO24) -> 0 | L24: =SUM('CF (нед)'!AP24:AT24) -> 0 | M24: =SUM('CF (нед)'!AU24:AX24) -> 0 | N24: =SUM('CF (нед)'!AY24:BB24) -> 0 | O24: =SUM(C24:N24) -> 0
A25: Закупка р/с | C25: =SUM('CF (нед)'!C25:G25) -> 0 | D25: =SUM('CF (нед)'!H25:K25) -> 0 | E25: =SUM('CF (нед)'!L25:O25) -> 0 | F25: =SUM('CF (нед)'!P25:S25) -> 0 | G25: =SUM('CF (нед)'!T25:X25) -> 0 | H25: =SUM('CF (нед)'!Y25:AB25) -> 0 | I25: =SUM('CF (нед)'!AC25:AF25) -> 0 | J25: =SUM('CF (нед)'!AG25:AK25) -> 0 | K25: =SUM('CF (нед)'!AL25:AO25) -> 0 | L25: =SUM('CF (нед)'!AP25:AT25) -> 0 | M25: =SUM('CF (нед)'!AU25:AX25) -> 0 | N25: =SUM('CF (нед)'!AY25:BB25) -> 0 | O25: =SUM(C25:N25) -> 0
A26: Доставка Китай | C26: =SUM('CF (нед)'!C26:G26) -> 0 | D26: =SUM('CF (нед)'!H26:K26) -> 0 | E26: =SUM('CF (нед)'!L26:O26) -> 0 | F26: =SUM('CF (нед)'!P26:S26) -> 0 | G26: =SUM('CF (нед)'!T26:X26) -> 0 | H26: =SUM('CF (нед)'!Y26:AB26) -> 0 | I26: =SUM('CF (нед)'!AC26:AF26) -> 0 | J26: =SUM('CF (нед)'!AG26:AK26) -> 0 | K26: =SUM('CF (нед)'!AM26:AO26) -> 0 | L26: =SUM('CF (нед)'!AP26:AT26) -> 0 | M26: =SUM('CF (нед)'!AU26:AX26) -> 0 | N26: =SUM('CF (нед)'!AY26:BB26) -> 0 | O26: =SUM(C26:N26) -> 0
A27: Доставка РФ | C27: =SUM('CF (нед)'!C27:G27) -> 0 | D27: =SUM('CF (нед)'!H27:K27) -> 0 | E27: =SUM('CF (нед)'!L27:O27) -> 0 | F27: =SUM('CF (нед)'!P27:S27) -> 0 | G27: =SUM('CF (нед)'!T27:X27) -> 0 | H27: =SUM('CF (нед)'!Y27:AB27) -> 0 | I27: =SUM('CF (нед)'!AC27:AF27) -> 0 | J27: =SUM('CF (нед)'!AG27:AK27) -> 0 | K27: =SUM('CF (нед)'!AL27:AO27) -> 0 | L27: =SUM('CF (нед)'!AP27:AT27) -> 0 | M27: =SUM('CF (нед)'!AU27:AX27) -> 0 | N27: =SUM('CF (нед)'!AY27:BB27) -> 0 | O27: =SUM(C27:N27) -> 0
A29: Вложения инвестора | C29: =SUM('CF (нед)'!C29:G29) -> 0 | D29: =SUM('CF (нед)'!H29:K29) -> 0 | E29: =SUM('CF (нед)'!L29:O29) -> 0 | F29: =SUM('CF (нед)'!P29:S29) -> 0 | G29: =SUM('CF (нед)'!T29:X29) -> 0 | H29: =SUM('CF (нед)'!Y29:AB29) -> 0 | I29: =SUM('CF (нед)'!AC29:AF29) -> 0 | J29: =SUM('CF (нед)'!AG29:AK29) -> 0 | K29: =SUM('CF (нед)'!AL29:AO29) -> 0 | L29: =SUM('CF (нед)'!AP29:AT29) -> 0 | M29: =SUM('CF (нед)'!AU29:AX29) -> 0 | N29: =SUM('CF (нед)'!AY29:BB29) -> 0 | O29: =SUM(C29:N29) -> 0
A31: Самовыкупы (покупка товара) | C31: =SUM('CF (нед)'!C31:G31) -> 0 | D31: =SUM('CF (нед)'!H31:K31) -> 0 | E31: =SUM('CF (нед)'!L31:O31) -> 0 | F31: =SUM('CF (нед)'!P31:S31) -> 0 | G31: =SUM('CF (нед)'!T31:X31) -> 0 | H31: =SUM('CF (нед)'!Y31:AB31) -> 0 | I31: =SUM('CF (нед)'!AC31:AF31) -> 0 | J31: =SUM('CF (нед)'!AG31:AK31) -> 0 | K31: =SUM('CF (нед)'!AL31:AO31) -> 0 | L31: =SUM('CF (нед)'!AP31:AT31) -> 0 | M31: =SUM('CF (нед)'!AU31:AX31) -> 0 | N31: =SUM('CF (нед)'!AY31:BB31) -> 0 | O31: =SUM(C31:N31) -> 0
A33: Остаток денежных средств на конец периода | C33: =C11-C13-C21-SUM(C23:C27)+C29-C31 -> 2426951.9 | D33: =D11-D13-D21-SUM(D23:D27)+D29-D31 -> 2920729.8 | E33: =E11-E13-E21-SUM(E23:E27)+E29-E31 -> 3317903.7 | F33: =F11-F13-F21-SUM(F23:F27)+F29-F31 -> 3497581.5 | G33: =G11-G13-G21-SUM(G23:G27)+G29-G31 -> 3497581.5 | H33: =H11-H13-H21-SUM(H23:H27)+H29-H31 -> 3497581.5 | I33: =I11-I13-I21-SUM(I23:I27)+I29-I31 -> 3497581.5 | J33: =J11-J13-J21-SUM(J23:J27)+J29-J31 -> 3497581.5 | ... N33: =N11-N13-N21-SUM(N23:N27)+N29-N31 -> 3497581.5
B35: Авансы уплаченные | C35: =283707+SUM(C23:C27)-C4 -> 91308.23 | D35: =C35+SUM(D23:D27)-D4 -> 91308.23 | E35: =D35+SUM(E23:E27)-E4 -> 91308.23 | F35: =E35+SUM(F23:F27)-F4 -> 91308.23 | G35: =F35+SUM(G23:G27)-G4 -> 91308.23 | H35: =G35+SUM(H23:H27)-H4 -> 91308.23 | I35: =H35+SUM(I23:I27)-I4 -> 91308.23 | J35: =I35+SUM(J23:J27)-J4 -> 91308.23 | K35: =J35+SUM(K23:K27)-K4 -> 91308.23 | ... N35: =M35+SUM(N23:N27)-N4 -> 91308.23
B36: Денег в обороте | C36: =C5+C35+C42 -> 4041165.7 | D36: =D5+D35+D42 -> 4313456.9 | E36: =E5+E35+E42 -> 4518281.4 | F36: =F5+F35+F42 -> 4616968.4 | G36: =G5+G35+G42 -> 4616968.4 | H36: =H5+H35+H42 -> 4616968.4 | I36: =I5+I35+I42 -> 4616968.4 | J36: =J5+J35+J42 -> 4616968.4 | ... N36: =N5+N35+N42 -> 4616968.4
A38: Выплата дивидентов: | C38: =SUM('CF (нед)'!C38:G38) -> 0 | D38: =SUM('CF (нед)'!H38:K38) -> 0 | E38: =SUM('CF (нед)'!L38:O38) -> 0 | F38: =SUM('CF (нед)'!P38:S38) -> 0 | G38: =SUM('CF (нед)'!T38:X38) -> 0 | H38: =SUM('CF (нед)'!Y38:AB38) -> 0 | I38: =SUM('CF (нед)'!AC38:AF38) -> 0 | J38: =SUM('CF (нед)'!AG38:AK38) -> 0 | K38: =SUM('CF (нед)'!AL38:AO38) -> 0 | L38: =SUM('CF (нед)'!AP38:AT38) -> 0 | M38: =SUM('CF (нед)'!AU38:AX38) -> 0 | N38: =SUM('CF (нед)'!AY38:BB38) -> 0 | O38: =SUM(C38:N38) -> 0
A39: Инвестор | B39: Остаток после вывода должен быть больше суммы закупки и доставки следующего месяца | C39: =SUM('CF (нед)'!C39:G39) -> 0 | D39: =SUM('CF (нед)'!H39:K39) -> 0 | E39: =SUM('CF (нед)'!L39:O39) -> 0 | F39: =SUM('CF (нед)'!P39:S39) -> 0 | G39: =SUM('CF (нед)'!T39:X39) -> 0 | H39: =SUM('CF (нед)'!Y39:AB39) -> 0 | I39: =SUM('CF (нед)'!AC39:AF39) -> 0 | J39: =SUM('CF (нед)'!AG39:AK39) -> 0 | K39: =SUM('CF (нед)'!AL39:AO39) -> 0 | L39: =SUM('CF (нед)'!AP39:AT39) -> 0 | M39: =SUM('CF (нед)'!AU39:AX39) -> 0 | N39: =SUM('CF (нед)'!AY39:BB39) -> 0 | O39: =SUM(C39:N39) -> 0
A40: Управляющий | C40: =SUM('CF (нед)'!C40:G40) -> 0 | D40: =SUM('CF (нед)'!H40:K40) -> 0 | E40: =SUM('CF (нед)'!L40:O40) -> 0 | F40: =SUM('CF (нед)'!P40:S40) -> 0 | G40: =SUM('CF (нед)'!T40:X40) -> 0 | H40: =SUM('CF (нед)'!Y40:AB40) -> 0 | I40: =SUM('CF (нед)'!AC40:AF40) -> 0 | J40: =SUM('CF (нед)'!AG40:AK40) -> 0 | K40: =SUM('CF (нед)'!AL40:AO40) -> 0 | L40: =SUM('CF (нед)'!AP40:AT40) -> 0 | M40: =SUM('CF (нед)'!AU40:AX40) -> 0 | N40: =SUM('CF (нед)'!AY40:BB40) -> 0 | O40: =SUM(C40:N40) -> 0
A42: Остаток денежных средств на конец периода | C42: =C33-C38 -> 2426951.9 | D42: =D33-D38 -> 2920729.8 | E42: =E33-E38 -> 3317903.7 | F42: =F33-F38 -> 3497581.5 | G42: =G33-G38 -> 3497581.5 | H42: =H33-H38 -> 3497581.5 | I42: =I33-I38 -> 3497581.5 | J42: =J33-J38 -> 3497581.5 | ... N42: =N33-N38 -> 3497581.5
B43: Накопленный финансовый результат | C43: ='PL WB'!C64+'PL OZON'!C64 -> 3564465 | D43: ='PL WB'!D64+'PL OZON'!D64 -> 3852586.2 | E43: ='PL WB'!E64+'PL OZON'!E64 -> 4063844.7 | F43: ='PL WB'!F64+'PL OZON'!F64 -> 4163281.6 | G43: ='PL WB'!G64+'PL OZON'!G64 -> 4163281.6 | H43: ='PL WB'!H64+'PL OZON'!H64 -> 4163281.6 | I43: ='PL WB'!I64+'PL OZON'!I64 -> 4163281.6 | J43: ='PL WB'!J64+'PL OZON'!J64 -> 4163281.6 | ... N43: ='PL WB'!N64+'PL OZON'!N64 -> 4163281.6
A45: Доступный остаток средств | C45: =C42-SUM(D23:D27) -> 2426951.9 | D45: =D42-SUM(E23:E27) -> 2920729.8 | E45: =E42-SUM(F23:F27) -> 3317903.7 | F45: =F42-SUM(G23:G27) -> 3497581.5 | G45: =G42-SUM(H23:H27) -> 3497581.5 | H45: =H42-SUM(I23:I27) -> 3497581.5 | I45: =I42-SUM(J23:J27) -> 3497581.5 | J45: =J42-SUM(K23:K27) -> 3497581.5 | ... N45: =N42-SUM(O23:O27) -> 3497581.5

Sheet проверка
A1: Серые нули это проверки между листами. Если серый не 0 - не идет проверка между листами PL с PL (нед) CF с CF (нед) Если не идет на PL (нед) - сверяем по строкам Сумма за 4 недели должна идти по этой же статье за месяц Аналогично с CF Возможные причины: 1. Если добавили статью - добавляем на всех 4 листах 2. Формула налога должна быль везде одинаковая на всех листах 3. Проверьте суммируются все расходы в общую сумму расходов

Sheet Оригинал
A1: http://postavka365.ru/?utm_source=unit
A2: Если у вас возникли вопросы по заполнению - напишите +79652083823 Андрей

Sheet Аудит
A1: АУДИТ ФИНАНСОВОЙ МОДЕЛИ
A2: Дата аудита: | B2: 31.03.2026
A3: Охват: | B3: PL общ, PL WB, PL OZON, CF, недельные варианты
A5: СВОДКА РЕЗУЛЬТАТОВ
A6: Статус | B6: Категория | C6: Кол-во | D6: Финансовый эффект
A7: 🔴 КРИТИЧНО | B7: Ошибки в формулах (неверные ссылки / пропуск данных) | C7: 4 | D7: Искажение данных до +153 548 руб. и более
A8: 🟡 ПРЕДУПРЕЖДЕНИЕ | B8: Непоследовательные формулы (разные знаменатели/строки) | C8: 3 | D8: Искажение % метрик (до ~12 п.п.)
A9: 🔵 ИНФОРМАЦИЯ | B9: Ошибки #ДЕЛ/0! в незаполненных месяцах | C9: Много | D9: Нет (данные пока не введены)
A10: ✅ ОК | B10: Кассовый баланс (CF) и переносы остатков | C10: — | D10: Корректны, расхождений нет
