Workbook
Name _12_18__15_3__утолщенный_шелк_7_100шт: #REF!
Name _14_20__17_3___утолщенный_шелк_7_100шт: #REF!
Name _169112569_2038161736993_ACRF1BN101PN_Маска_бандаж_для_лица_розовая: #REF!
Name _169153168_2038162681926_ACRF1BN101BC_Маска_бандаж_для_лица_черная: #REF!
Name _169395410_2038172050200_ACRF1BN201GR_Маска_бандаж_для_лица_серая: #REF!
Name _170899505_2038224716238_AHMA6BW101BG_Набор_мешков_для_стирки_6_шт.: #REF!
Name _172832355_2038337652454_AHMA7BW101BG_Набор_мешков_для_стирки_7_шт.: #REF!
Name _173605843_2038430289250_ACRH1MS101RJ_Массажер_для_пальцев_суставов: #REF!
Name _176170511_2038586639107_ACRF1SK101WH_Скребок_Гуаша_белый_короб: #REF!
Name _176500218_2038597850744_AHMA1BW101BG_Мешок_для_стирки_бюстгалтеров: #REF!
Name _176709293_2038605982115_ACRF2RS201NF_Комплект_Гуаша_роллер_и_скребок_бол_нефрит_прем: #REF!
Name _176721350_2038606201642_AHMA3BW201WH_Комплект_мешков_сетка_мелкая_на_шнурке_3_шт.: #REF!
Name _176723275_2038606256161_AHMA3BW202WH_Комплект_мешков_сетка_крупная_на_шнурке_3_шт.: #REF!
Name _177404837_2038627692689_AHMA3BW101BG_Комплект_мешков_для_стирки_3_шт.: #REF!
Name _177405495_2038627713902_AHMA3BW102BG_Комплект_мешков_для_деликатной_стирки_3_шт.: #REF!
Name _18_27__23_4___утолщенный_шелк_7_100шт: #REF!
Name _186800214_2038890789598_ACRA7TB101BC_Таблетница_круглая_7_2: #REF!
Name _186826338_2038891723249_ACRA7TB201BC_Таблетница_прямоугольная_7_2_черная: #REF!
Name _188194883_2038931439581_AHMA3BW211WH_Комплект_мешков_сетка_мелкая_на_шнурке_3_шт._с_шаром: #REF!
Name _199452263_2039291528267_AHMA3BW212WH_Комплект_мешков_сетка_крупная_на_шнурке_3_шт._с_шаром: #REF!
Name _20_30__26_4___утолщенный_шелк_7_100шт: #REF!
Name _20_34__30_4___утолщенный_шелк_7_100шт: #REF!
Name _200946531_2039323172727_AHMA3BW221WH_Комплект_мешков_сетка_крупная_на_шнурке_3_шт._с_цилиндром: #REF!
Name _200953158_2039323305576_ACRA7TB301BC_Таблетница_прямоугольная_7_3: #REF!
Name _204260887_2039399347548_AHMA3BW222WH_Комплект_мешков_мелкая_сетка_на_шнурке_3_шт._с_цилиндром: #REF!
Name _204615141_2039404446068_AHMA2BW201WH_Комплект_мешков_2_шт._серый: #REF!
Name _205841460_2039422231875_ACRF1SK202NF_Скребок_Гуаша_нефрит: #REF!
Name _22_34__30_4___утолщенный_шелк_7_100шт: #REF!
Name _220252787_2039735724354_ACRL1MS101RJ_Массажер_для_ног: #REF!
Name _223420736_2039813223373_ACRB1MS101RJ_Массажер_для_тела: #REF!
Name _223671295_2039818580389_ACRB1MS102RJ_Массажер_мяч_оранжевый: #REF!
Name _236072834_2040278804649_ACRB1MS102BL_Массажер_мяч_голубой: #REF!
Name _236072835_2040278804496_ACRB1MS102WH_Массажер_мяч_белый: #REF!
Name _236072836_2040278810534_ACRB1MS102PN_Массажер_мяч_розовый: #REF!
Name _236074677_2040278862540_AHMA2BW202WH_Комплект_мешков_2_шт._розовый: #REF!
Name _236929187_2040335626849_AHMA1BW112WH_Мешок_большой_крупная_сетка_60_80: #REF!
Name _236929188_2040335648124_AHMA1BW111WH_Мешок_большой_мелкая_сетка_60_80: #REF!
Name _239233529_2040478696884_AHMA1BW302WH_Мешок_для_стирки_обуви_XL___35_см: #REF!
Name _239235150_2040478720961_AHMA1BW301WH_Мешок_для_стирки_обуви_L___30_см: #REF!
Name _24_34__30_4___утолщенный_шелк_7_100шт: #REF!
Name _248267432_2040797652776_AAND1ST201BL_Палочка_для_жевания: #REF!
Name _251407392_2040900511679_AAND1BL102BL_Мяч_шина_синий: #REF!
Name _251516159_2040902555480_AAND1BL102RD_Мяч_шина_красный: #REF!
Name _251537223_2040903539366_AAND1BL101RD_Мяч_регби_красный: #REF!
Name _251537413_2040903547941_AAND1BL101BL_Мяч_регби_синий: #REF!
Name _253681275_2040957863936_ACRA7TB401CL_Таблетница_прямоугольная_7_2_цветная: #REF!
Name A1016__мелкое_отверстие_30_40: #REF!
Name A1016__толстое_отверстие_30_40: #REF!
Name A1016__толстое_отверстие_40_50: #REF!
Name A1016__толстое_отверстие_60_80: #REF!
Name A1016__тонкое_отверстие_40_50: #REF!
Name A1016__тонкое_отверстие_50_60: #REF!
Name A1016__тонкое_отверстие_60_80: #REF!
Name A1016_толстое_отверстие_50_60: #REF!
Name Бандаж_лайкра_розовый: #REF!
Name Бандаж_лайкра_черный: #REF!
Name Бандаж_силикон_серый: #REF!
Name Бежевые_трусики_20_20: #REF!
Name Бежевый_Бюстгальтер_Раковина_18_16: #REF!
Name Белый__скребок_Гуаша_в_коробке: #REF!

Sheet Акция 1
A1: Товар уже участвует в акции | B1: Бренд | C1: Предмет | D1: Наименование | E1: Артикул поставщика | F1: Артикул WB | G1: Последний баркод | H1: Количество дней на сайте | I1: Оборачиваемость | J1: Остаток товара на складах Wb (шт.) | K1: Остаток товара на складе продавца Wb (шт.) | L1: Плановая цена для акции | M1: Текущая розничная цена | N1: Валюта | O1: Текущая скидка на сайте, % | P1: Загружаемая скидка для участия в акции | Q1: Статус
A2: Да | B2: AROLS | C2: Бандажи косметические | D2: Маска-бандаж для лица подбородка косметический | E2: ACRF1BN101PN | F2: 169112569 | G2: 2038161736993 | H2: 1070.8294 | I2: 984 | J2: 128 | K2: 0 | L2: 746 | M2: 1258 | N2: RUB | O2: 41 | P2: 41 | Q2: Участвует: добавлен, цена равна или ниже плановой
A3: Да | B3: AROLS | C3: Бандажи косметические | D3: Бандаж для лица и подбородка многоразовый | E3: ACRF1BN101BC | F3: 169153168 | G3: 2038162681926 | H3: 1070.5835 | I3: 999 | J3: 216 | K3: 0 | L3: 746 | M3: 1258 | N3: RUB | O3: 41 | P3: 41 | Q3: Участвует: добавлен, цена равна или ниже плановой
A4: Да | B4: AROLS | C4: Бандажи косметические | D4: Бандаж для лица и подбородка многоразовый силиконовый | E4: ACRF1BN201GR | F4: 169395410 | G4: 2038172050200 | H4: 1067.6335 | I4: 999 | J4: 202 | K4: 0 | L4: 1045 | M4: 1656 | N4: RUB | O4: 37 | P4: 37 | Q4: Участвует: добавлен, цена равна или ниже плановой
A5: Да | B5: AROLS HOME | C5: Мешки для стирки | D5: Мешок для стирки белья -7 штук | E5: AHMA7BW101BG | F5: 172832355 | G5: 2038337652454 | H5: 1041.668 | I5: 269 | J5: 139 | K5: 0 | L5: 2097 | M5: 3027 | N5: RUB | O5: 31 | P5: 31 | Q5: Участвует: добавлен, цена равна или ниже плановой
A6: Да | B6: AROLS | C6: Массажеры механические | D6: Массажер для пальцев рук роликовый механический | E6: ACRH1MS101RJ | F6: 173605843 | G6: 2038430289250 | H6: 1035.8927 | I6: 999 | J6: 535 | K6: 0 | L6: 337 | M6: 585 | N6: RUB | O6: 43 | P6: 43 | Q6: Участвует: добавлен, цена равна или ниже плановой
A7: Да | B7: AROLS HOME | C7: Мешки для стирки | D7: Мешок для стирки бюстгальтера | E7: AHMA1BW101BG | F7: 176500218 | G7: 2038597850744 | H7: 1013.689 | I7: 726 | J7: 320 | K7: 0 | L7: 539 | M7: 792 | N7: RUB | O7: 40 | P7: 40 | Q7: Участвует: добавлен, цена равна или ниже плановой
A8: Да | B8: AROLS HOME | C8: Мешки для стирки | D8: Мешки для стирки одежды - сетка мелкая - 3 штуки | E8: AHMA3BW201WH | F8: 176721350 | G8: 2038606201642 | H8: 1011.7208 | I8: 334 | J8: 258 | K8: 0 | L8: 757 | M8: 1199 | N8: RUB | O8: 37 | P8: 37 | Q8: Участвует: добавлен, цена равна или ниже плановой
A9: Да | B9: AROLS HOME | C9: Мешки для стирки | D9: Мешок для стирки одежды - 3 штуки | E9: AHMA3BW101BG | F9: 177404837 | G9: 2038627692689 | H9: 1007.677 | I9: 502 | J9: 146 | K9: 0 | L9: 1246 | M9: 1799 | N9: RUB | O9: 31 | P9: 31 | Q9: Участвует: добавлен, цена равна или ниже плановой
A10: Да | B10: AROLS HOME | C10: Мешки для стирки | D10: Мешки для стирки белья - 3 штуки | E10: AHMA3BW102BG | F10: 177405495 | G10: 2038627713902 | H10: 1007.6705 | I10: 999 | J10: 264 | K10: 0 | L10: 1108 | M10: 1599 | N10: RUB | O10: 31 | P10: 31 | Q10: Участвует: добавлен, цена равна или ниже плановой
A11: Да | B11: AROLS | C11: Таблетницы | D11: Таблетница на неделю 2 приема круглая черная | E11: ACRA7TB101BC | F11: 186800214 | G11: 2038890789598 | H11: 960.62615 | I11: 168 | J11: 180 | K11: 0 | L11: 827 | M11: 1273 | N11: RUB | O11: 40 | P11: 40 | Q11: Участвует: добавлен, цена равна или ниже плановой
A12: Да | B12: AROLS HOME | C12: Мешки для стирки | D12: Мешки для стирки бюстгальтера - набор 2 штуки | E12: AHMA2BW201WH | F12: 204615141 | G12: 2039404446068 | H12: 876.64918 | I12: 602 | J12: 222 | K12: 0 | L12: 598 | M12: 941 | N12: RUB | O12: 37 | P12: 37 | Q12: Участвует: добавлен, цена равна или ниже плановой
A13: Да | B13: AROLS | C13: Массажеры механические | D13: Массажер для шеи спины тела ручной роликовый | E13: ACRB1MS101RJ | F13: 223420736 | G13: 2039813223373 | H13: 799.77998 | I13: 368 | J13: 56 | K13: 0 | L13: 901 | M13: 1313 | N13: RUB | O13: 32 | P13: 32 | Q13: Участвует: добавлен, цена равна или ниже плановой
... A55: Да | B55: AROLS | C55: Эспандеры | D55: Набор тканевых фитнес резинок 3 шт для ягодиц и ног | E55: ACRB3FR101CL | F55: 820643010 | G55: 2048933027488 | H55: 127.77703 | I55: 520 | J55: 89 | K55: 0 | L55: 1483 | M55: 2141 | N55: RUB | O55: 41 | P55: 41 | Q55: Участвует: добавлен, цена равна или ниже плановой

Sheet Акция 2
A1: Товар уже участвует в акции | B1: Бренд | C1: Предмет | D1: Наименование | E1: Артикул поставщика | F1: Артикул WB | G1: Последний баркод | H1: Количество дней на сайте | I1: Оборачиваемость | J1: Остаток товара на складах Wb (шт.) | K1: Остаток товара на складе продавца Wb (шт.) | L1: Плановая цена для акции | M1: Текущая розничная цена | N1: Валюта | O1: Текущая скидка на сайте, % | P1: Загружаемая скидка для участия в акции | Q1: Статус
A2: Да | B2: AROLS HOME | C2: Мешки для стирки | D2: Мешок для стирки белья - сетка крупная - 3 штуки | E2: AHMA3BW202WH | F2: 176723275 | G2: 2038606256161 | H2: 1011.7111 | I2: 87 | J2: 92 | K2: 0 | L2: 839 | M2: 1199 | N2: RUB | O2: 30 | P2: 30 | Q2: Участвует: добавлен, цена равна или ниже плановой
A3: Да | B3: AROLS | C3: Таблетницы | D3: Таблетница органайзер на неделю 7 дней 14 приемов | E3: ACRA7TB201BC | F3: 186826338 | G3: 2038891723249 | H3: 960.48538 | I3: 273 | J3: 457 | K3: 0 | L3: 868 | M3: 1241 | N3: RUB | O3: 30 | P3: 30 | Q3: Участвует: добавлен, цена равна или ниже плановой
A4: Да | B4: AROLS | C4: Массажеры механические | D4: Массажный мяч мфр 6 см для йоги фитнеса пилатеса | E4: ACRB1MS106WH | F4: 236072835 | G4: 2040278804496 | H4: 743.62222 | I4: 256 | J4: 427 | K4: 0 | L4: 597 | M4: 856 | N4: RUB | O4: 31 | P4: 31 | Q4: Участвует: добавлен, цена равна или ниже плановой
A5: Да | B5: AROLS HOME | C5: Мешки для стирки | D5: Большой мешок для стирки - 60*80 сетка крупная | E5: AHMA1BW112WH | F5: 236929187 | G5: 2040335626849 | H5: 739.71473 | I5: 72 | J5: 94 | K5: 0 | L5: 669 | M5: 956 | N5: RUB | O5: 30 | P5: 30 | Q5: Участвует: добавлен, цена равна или ниже плановой
A6: Да | B6: DOG JOY | C6: Игрушки для животных | D6: Прочная игрушка-мяч для собак средних-крупных пород | E6: AAND1BL102BL | F6: 251407392 | G6: 2040900511679 | H6: 678.51668 | I6: 643 | J6: 192 | K6: 0 | L6: 741 | M6: 913 | N6: RUB | O6: 30 | P6: 30 | Q6: Участвует: добавлен, цена равна или ниже плановой

Sheet Акция 3
A1: Товар уже участвует в акции | B1: Бренд | C1: Предмет | D1: Наименование | E1: Артикул поставщика | F1: Артикул WB | G1: Последний баркод | H1: Количество дней на сайте | I1: Оборачиваемость | J1: Остаток товара на складах Wb (шт.) | K1: Остаток товара на складе продавца Wb (шт.) | L1: Плановая цена для акции | M1: Текущая розничная цена | N1: Валюта | O1: Текущая скидка на сайте, % | P1: Загружаемая скидка для участия в акции | Q1: Статус
A2: Нет | B2: AROLS | C2: Бандажи косметические | D2: Маска-бандаж для лица подбородка косметический | E2: ACRF1BN101PN | F2: 169112569 | G2: 2038161736993 | H2: 1070.8311 | I2: 984 | J2: 128 | K2: 0 | L2: 594 | M2: 1258 | N2: RUB | O2: 41 | P2: 53 | Q2: Не участвует: не добавлен или цена выше плановой
A3: Нет | B3: AROLS | C3: Бандажи косметические | D3: Бандаж для лица и подбородка многоразовый | E3: ACRF1BN101BC | F3: 169153168 | G3: 2038162681926 | H3: 1070.5852 | I3: 999 | J3: 216 | K3: 0 | L3: 562 | M3: 1258 | N3: RUB | O3: 41 | P3: 56 | Q3: Не участвует: не добавлен или цена выше плановой
A4: Нет | B4: AROLS | C4: Бандажи косметические | D4: Бандаж для лица и подбородка многоразовый силиконовый | E4: ACRF1BN201GR | F4: 169395410 | G4: 2038172050200 | H4: 1067.6352 | I4: 999 | J4: 202 | K4: 0 | L4: 1011 | M4: 1656 | N4: RUB | O4: 37 | P4: 39 | Q4: Не участвует: не добавлен или цена выше плановой
A5: Нет | B5: AROLS HOME | C5: Мешки для стирки | D5: Мешок для стирки белья -7 штук | E5: AHMA7BW101BG | F5: 172832355 | G5: 2038337652454 | H5: 1041.6697 | I5: 269 | J5: 139 | K5: 0 | L5: 1101 | M5: 3027 | N5: RUB | O5: 31 | P5: 64 | Q5: Не участвует: не добавлен или цена выше плановой
A6: Да | B6: AROLS | C6: Массажеры механические | D6: Массажер для пальцев рук роликовый механический | E6: ACRH1MS101RJ | F6: 173605843 | G6: 2038430289250 | H6: 1035.8944 | I6: 999 | J6: 535 | K6: 0 | L6: 343 | M6: 585 | N6: RUB | O6: 43 | P6: 43 | Q6: Участвует: добавлен, цена равна или ниже плановой
A7: Да | B7: AROLS HOME | C7: Мешки для стирки | D7: Мешок для стирки бюстгальтера | E7: AHMA1BW101BG | F7: 176500218 | G7: 2038597850744 | H7: 1013.6907 | I7: 726 | J7: 320 | K7: 0 | L7: 475 | M7: 792 | N7: RUB | O7: 40 | P7: 40 | Q7: Участвует: добавлен, цена равна или ниже плановой
A8: Нет | B8: AROLS HOME | C8: Мешки для стирки | D8: Мешки для стирки одежды - сетка мелкая - 3 штуки | E8: AHMA3BW201WH | F8: 176721350 | G8: 2038606201642 | H8: 1011.7225 | I8: 334 | J8: 258 | K8: 0 | L8: 577 | M8: 1199 | N8: RUB | O8: 37 | P8: 52 | Q8: Не участвует: не добавлен или цена выше плановой
A9: Нет | B9: AROLS HOME | C9: Мешки для стирки | D9: Мешок для стирки белья - сетка крупная - 3 штуки | E9: AHMA3BW202WH | F9: 176723275 | G9: 2038606256161 | H9: 1011.712 | I9: 87 | J9: 92 | K9: 0 | L9: 752 | M9: 1199 | N9: RUB | O9: 30 | P9: 38 | Q9: Не участвует: не добавлен или цена выше плановой
A10: Нет | B10: AROLS HOME | C10: Мешки для стирки | D10: Мешок для стирки одежды - 3 штуки | E10: AHMA3BW101BG | F10: 177404837 | G10: 2038627692689 | H10: 1007.6787 | I10: 502 | J10: 146 | K10: 0 | L10: 696 | M10: 1799 | N10: RUB | O10: 31 | P10: 62 | Q10: Не участвует: не добавлен или цена выше плановой
A11: Нет | B11: AROLS HOME | C11: Мешки для стирки | D11: Мешки для стирки белья - 3 штуки | E11: AHMA3BW102BG | F11: 177405495 | G11: 2038627713902 | H11: 1007.6722 | I11: 999 | J11: 264 | K11: 0 | L11: 842 | M11: 1599 | N11: RUB | O11: 31 | P11: 48 | Q11: Не участвует: не добавлен или цена выше плановой
A12: Нет | B12: AROLS | C12: Таблетницы | D12: Таблетница на неделю 2 приема круглая черная | E12: ACRA7TB101BC | F12: 186800214 | G12: 2038890789598 | H12: 960.62784 | I12: 168 | J12: 180 | K12: 0 | L12: 696 | M12: 1273 | N12: RUB | O12: 40 | P12: 46 | Q12: Не участвует: не добавлен или цена выше плановой
A13: Нет | B13: AROLS | C13: Таблетницы | D13: Таблетница органайзер на неделю 7 дней 14 приемов | E13: ACRA7TB201BC | F13: 186826338 | G13: 2038891723249 | H13: 960.48628 | I13: 273 | J13: 457 | K13: 0 | L13: 638 | M13: 1241 | N13: RUB | O13: 30 | P13: 49 | Q13: Не участвует: не добавлен или цена выше плановой
... A60: Нет | B60: AROLS | C60: Эспандеры | D60: Набор тканевых фитнес резинок 3 шт для ягодиц и ног | E60: ACRB3FR101CL | F60: 820643010 | G60: 2048933027488 | H60: 127.77873 | I60: 520 | J60: 89 | K60: 0 | L60: 1043 | M60: 2141 | N60: RUB | O60: 41 | P60: 52 | Q60: Не участвует: не добавлен или цена выше плановой

Sheet Акция 4
A1: Товар уже участвует в акции | B1: Бренд | C1: Предмет | D1: Наименование | E1: Артикул поставщика | F1: Артикул WB | G1: Последний баркод | H1: Количество дней на сайте | I1: Оборачиваемость | J1: Остаток товара на складах Wb (шт.) | K1: Остаток товара на складе продавца Wb (шт.) | L1: Плановая цена для акции | M1: Текущая розничная цена | N1: Валюта | O1: Текущая скидка на сайте, % | P1: Загружаемая скидка для участия в акции | Q1: Статус
A2: Да | B2: AROLS | C2: Скакалки | D2: Скакалка спортивная взрослая скоростная | E2: ACRB1SK101BC | F2: 271440668 | G2: 2041473034138 | H2: 609.74101 | I2: 983 | J2: 130 | K2: 0 | L2: 1146 | M2: 1741 | N2: RUB | O2: 35 | P2: 35 | Q2: Участвует: добавлен, цена равна или ниже плановой
A3: Да | B3: AROLS | C3: Скакалки | D3: Скакалка спортивная скоростная | E3: ACRB1SK101RD | F3: 271440669 | G3: 2041473034145 | H3: 609.74101 | I3: 440 | J3: 128 | K3: 0 | L3: 813 | M3: 1575 | N3: RUB | O3: 49 | P3: 49 | Q3: Участвует: добавлен, цена равна или ниже плановой
A4: Да | B4: AROLS | C4: Скакалки | D4: Скакалка спортивная скоростная | E4: ACRB1SK101BL | F4: 271440670 | G4: 2041473034169 | H4: 609.74101 | I4: 999 | J4: 100 | K4: 0 | L4: 813 | M4: 1467 | N4: RUB | O4: 45 | P4: 45 | Q4: Участвует: добавлен, цена равна или ниже плановой
A5: Да | B5: AROLS | C5: Эспандеры | D5: Фитнес резинки тканевые 5 шт эспандер для ног ягодиц | E5: ACRB5FR200CL | F5: 550539998 | G5: 2046392546618 | H5: 260.69337 | I5: 999 | J5: 59 | K5: 0 | L5: 1387 | M5: 2542 | N5: RUB | O5: 46 | P5: 46 | Q5: Участвует: добавлен, цена равна или ниже плановой
A6: Да | B6: AROLS | C6: Эспандеры | D6: Набор фитнес резинок латексных 4 шт эспандер для йоги | E6: ACRB4FR300CL | F6: 550539999 | G6: 2046392546632 | H6: 260.69337 | I6: 999 | J6: 40 | K6: 0 | L6: 910 | M6: 1456 | N6: RUB | O6: 38 | P6: 38 | Q6: Участвует: добавлен, цена равна или ниже плановой
A7: Да | B7: AROLS | C7: Эспандеры | D7: Набор тканевых фитнес резинок 3 шт для ягодиц и ног | E7: ACRB3FR101CL | F7: 820643010 | G7: 2048933027488 | H7: 127.77951 | I7: 520 | J7: 89 | K7: 0 | L7: 1265 | M7: 2141 | N7: RUB | O7: 41 | P7: 41 | Q7: Участвует: добавлен, цена равна или ниже плановой

Sheet Акция 5

Sheet Акция 6

Sheet Акция 7

Sheet Акция 8
A1: Товар уже участвует в акции | B1: Бренд | C1: Предмет | D1: Наименование
A2: Да | B2: AROLS | C2: Массажеры механические | D2: Массажный мяч мфр для йоги - фитнеса пилатеса гимнастики
A3: Да | B3: AROLS | C3: Массажеры механические | D3: Массажный мяч мфр для йоги - фитнеса пилатеса гимнастики
A4: Да | B4: AROLS HOME | C4: Прессы для чеснока | D4: Чеснокодавка металлическая – пресс для чеснока измельчитель
A5: Да | B5: AROLS | C5: Массажеры механические | D5: Массажный мяч для мфр йоги пилатеса с шипами жесткий 7 см
A6: Да | B6: AROLS | C6: Массажеры механические | D6: Массажный мяч для мфр йоги пилатеса с шипами жесткий 7 см
A7: Нет | B7: AROLS | C7: Массажеры механические | D7: Массажный мяч для мфр йоги пилатеса с шипами жесткий 7 см
A8: Да | B8: AROLS | C8: Массажеры механические | D8: Массажный мяч с шипами для мфр йоги пилатеса жесткий 9 см

Sheet Акция 9

Sheet Акция 10

Sheet Акция 11

Sheet Рассчет акции
C1: Данные с листа Юнит ВБ (подтягиваются автоматически) | E1: Вставляем из | I1: ЖЕЛАЕМАЯ ЦЕНА | Q1: 1 | R1: АКЦИЯ | T1: 2 | U1: АКЦИЯ | W1: 3 | X1: АКЦИЯ | Z1: 4 | AA1: АКЦИЯ | AC1: 5 | AD1: АКЦИЯ | AF1: 6 | AG1: АКЦИЯ | AJ1: АКЦИЯ | AM1: АКЦИЯ | AP1: АКЦИЯ | AS1: АКЦИЯ | AV1: АКЦИЯ | AY1: АКЦИЯ | BF1: МАРЖА акции | BG1: МАРЖА текущая | BH1: БУДУТ УЧАСТВОВАТЬ (ПОСТАВИТЬ ЗНАК *) | BI1: ВНЕСТИ ИЗМЕНЕНИЯ В ШАБЛОН ЦЕН! | BJ1: ВНЕСТИ ИЗМЕНЕНИЯ В ШАБЛОН ЦЕН! | BM1: Остатки | BN1: Оборачиваемость
E2: "Цена текущая на ВБ" | N2: ЦЕНА ТЕКУЩАЯ НА ВБ | Q2: дата | R2: 17.06-19.07 | T2: дата | U2: 17.06-19.07 | W2: дата | X2: 10.06-.25.06 | Z2: дата | AA2: 16.06-29.06 | AC2: дата | AF2: дата | AI2: дата | AL2: дата | AO2: дата | AR2: дата | AU2: дата | AX2: дата | BA2: Выбор Акции | BD2: Для установки в акции
E3: перед сохранением листа | M3: подтягивается с листа текущая цена | Q3: Жаркие скидки (автоматические скидки) | T3: Жаркие скидки-2 (автоматические скидки) | W3: Повышаем заказы (автоматические скидки) | Z3: Спортивные скидки (автоматические скидки) | BD3: 0.4
A4: Арт. WB | B4: Арт. Поставщика | C4: Номенклатура | D4: Штрихкод | E4: Цена продажи | F4: Скидка | G4: Цена в карточке | H4: Маржа | I4: Цена продажи плановая | J4: 0.3 | K4: Цена в карточке | L4: Маржа | M4: Цена продажи плановая | N4: Скидка | O4: Цена в карточке | P4: Маржа | Q4: Цена плановая акции | R4: Скидка акции | S4: Цена в карточке | T4: Цена плановая акции | U4: Скидка акции | V4: Цена в карточке | W4: Цена плановая акции | X4: Скидка акции | Y4: Цена в карточке | Z4: Цена плановая акции | AA4: Скидка акции | AB4: Цена в карточке | AC4: Цена плановая акции | AD4: Скидка акции | AE4: Цена в карточке | AF4: Цена плановая акции | AG4: Скидка акции | AH4: Цена в карточке | AI4: Цена плановая акции | AJ4: Скидка акции | AK4: Цена в карточке | AL4: Цена плановая акции | AM4: Скидка акции | AN4: Цена в карточке | AO4: Цена плановая акции | AP4: Скидка акции | AQ4: Цена в карточке | AR4: Цена плановая акции | AS4: Скидка акции | AT4: Цена в карточке | AU4: Цена плановая акции | AV4: Скидка акции | AW4: Цена в карточке | AX4: Цена плановая акции | AY4: Скидка акции | AZ4: Цена в карточке | BA4: Цена продажи Акции МАКС | BB4: Номер акции | BC4: Цена продажи в Акции | BD4: Скидка Акции (вручную) | BE4: Цена в карточке в Акции | BI4: Цена новая | BJ4: Скидка Новая | BK4: Цена Видит покупатель
A5: 1 | B5: 2 | C5: 3 | D5: 4 | E5: 5 | F5: 6 | G5: 7 | H5: 8 | I5: 9 | J5: 10 | K5: 11 | L5: 12 | M5: 13 | N5: 14 | O5: 15 | Q5: 17 | R5: 18 | S5: 19 | T5: 20 | U5: 21 | V5: 22 | W5: 23 | X5: 24 | Y5: 25 | Z5: 26 | AA5: 27 | AB5: 28 | AC5: 29 | AD5: 30 | AE5: 31 | AI5: 15 | AJ5: 16 | AK5: 17 | BA5: 24 | BB5: 25 | BC5: 26 | BD5: 27 | BE5: 28 | BG5: 29 | BH5: 30
A6: =[1]Юнит!A5 -> 169112569 | B6: =[1]Юнит!C5 -> ACRF1BN101PN | C6: =[1]Юнит!D5 -> Бандаж для лица розовый | D6: =[1]Юнит!E5 -> 2038161736993 | E6: 746 | F6: 0.4 | G6: 1243 | H6: 0.21980974 | I6: =_xlfn.XLOOKUP(D6,[1]Юнит!$E:$E,[1]Юнит!$AN:$AN) -> 829 | J6: =$J$4 -> 0.3 | K6: =I6/(100%-$J$4) -> 1184.2857 | L6: =_xlfn.XLOOKUP(D6,[1]Юнит!$E:$E,[1]Юнит!$AR:$AR) -> 0.29258596 | M6: =MROUND(O6-O6*N6,1) -> 746 | N6: =_xlfn.XLOOKUP($A6,'Текущая цена на ВБ'!$C:$C,'Текущая цена на ВБ'!$K:$K,0,0)% -> 0.4 | O6: =_xlfn.XLOOKUP($A6,'Текущая цена на ВБ'!$C:$C,'Текущая цена на ВБ'!$I:$I,0) -> 1243 | P6: =_xlfn.XLOOKUP($A6,[1]Юнит!$A:$A,[1]Юнит!$AJ:$AJ,0) -> 0.22147729 | Q6: =_xlfn.XLOOKUP($A6,'Акция 1'!$F:$F,'Акция 1'!$L:$L,0,0) -> 746 | R6: =(_xlfn.XLOOKUP($A6,'Акция 1'!$F:$F,'Акция 1'!$P:$P,0,0))% -> 0.41 | S6: =Q6/(100%-R6) -> 1264.4068 | T6: =_xlfn.XLOOKUP($A6,'Акция 2'!$F:$F,'Акция 2'!$L:$L,0,0) -> 0 | U6: =(_xlfn.XLOOKUP($A6,'Акция 2'!$F:$F,'Акция 2'!$O:$O,0,0))% -> 0 | V6: =T6/(100%-U6) -> 0 | W6: =_xlfn.XLOOKUP($A6,'Акция 3'!$F:$F,'Акция 3'!$L:$L,0,0) -> 594 | X6: =(_xlfn.XLOOKUP($A6,'Акция 3'!$F:$F,'Акция 3'!$P:$P,0,0))% -> 0.53 | Y6: =W6/(100%-X6) -> 1263.8298 | Z6: =_xlfn.XLOOKUP($A6,'Акция 4'!$F:$F,'Акция 4'!$L:$L,0,0) -> 0 | AA6: =(_xlfn.XLOOKUP($A6,'Акция 4'!$F:$F,'Акция 4'!$P:$P,0,0))% -> 0 | AB6: =Z6/(100%-AA6) -> 0 | AC6: =_xlfn.XLOOKUP($A6,'Акция 5'!$F:$F,'Акция 5'!$L:$L,0,0) -> 0 | AD6: =(_xlfn.XLOOKUP($A6,'Акция 5'!$F:$F,'Акция 5'!O:O,0,0))% -> 0 | AE6: =AC6/(100%-AD6) -> 0 | AF6: =_xlfn.XLOOKUP($A6,'Акция 6'!$F:$F,'Акция 6'!$L:$L,0,0) -> 0 | AG6: =(_xlfn.XLOOKUP($A6,'Акция 6'!$F:$F,'Акция 6'!$O:$O,0,0))% -> 0 | AH6: =AF6/(100%-AG6) -> 0 | AI6: =_xlfn.XLOOKUP($A6,'Акция 7'!$F:$F,'Акция 7'!$L:$L,0,0) -> 0 | AJ6: =(_xlfn.XLOOKUP($A6,'Акция 7'!$F:$F,'Акция 7'!$O:$O,0,0))% -> 0 | AK6: =AI6/(100%-AJ6) -> 0 | AL6: =_xlfn.XLOOKUP($A6,'Акция 8'!$F:$F,'Акция 8'!$L:$L,0,0) -> 0 | AM6: =(_xlfn.XLOOKUP($A6,'Акция 8'!$F:$F,'Акция 8'!$S:$S,0,0))% -> 0 | AN6: =AL6/(100%-AM6) -> 0 | AO6: =_xlfn.XLOOKUP($A6,'Акция 9'!$F:$F,'Акция 9'!$L:$L,0,0) -> 0 | AP6: =(_xlfn.XLOOKUP($A6,'Акция 9'!$F:$F,'Акция 9'!$O:$O,0,0))% -> 0 | AQ6: =AO6/(100%-AP6) -> 0 | AR6: =_xlfn.XLOOKUP($A6,'Акция 10'!$F:$F,'Акция 10'!$L:$L,0,0) -> 0 | AS6: =(_xlfn.XLOOKUP($A6,'Акция 10'!$F:$F,'Акция 10'!$O:$O,0,0))% -> 0 | AT6: =AR6/(100%-AS6) -> 0 | AU6: =_xlfn.XLOOKUP($A6,'Акция 11'!$F:$F,'Акция 11'!$L:$L,0,0) -> 0 | AV6: =(_xlfn.XLOOKUP($A6,'Акция 11'!$F:$F,'Акция 11'!$O:$O,0,0))% -> 0 | AW6: =AU6/(100%-AV6) -> 0 | BA6: =MAX($Q6,$T6,W6,Z6,AC6,AF6,AL6,AO6,AR6,AU6,AX6,AI6) -> 746 | BB6: =IF(BA6=0,0,_xlfn.XLOOKUP($BA6,$Q6:$AZ6,$Q$1:$AZ$1,0,0)) -> 1 | BC6: =_xlfn.XLOOKUP($BB6,$Q$1:$AZ$1,$Q6:$AZ6,0,0) -> 746 | BD6: =IF(BA6=0,0,$BD$3) -> 0.4 | BE6: =BC6/(100%-BD6) -> 1243.3333 | BF6: =_xlfn.XLOOKUP(A6,[1]Юнит!$A:$A,[1]Юнит!$AU:$AU,0) -> 0.22166724 | BG6: =P6 -> 0.22147729 | BH6: * | BI6: =MROUND(IF($BH6="*",$BE6,K6),1) -> 1243 | BJ6: =IF($BH6="*",$BD6,J6) -> 0.4 | BK6: =MROUND(BI6-BI6*BJ6,1) -> 746 | BL6: =IF(BH6="*",1,0) -> 1 | BM6: =_xlfn.XLOOKUP(A6,'Текущая цена на ВБ'!C:C,'Текущая цена на ВБ'!F:F) -> 128 | BN6: =_xlfn.XLOOKUP(A6,'Текущая цена на ВБ'!C:C,'Текущая цена на ВБ'!H:H) -> 984
A7: =[1]Юнит!A6 -> 169153168 | B7: =[1]Юнит!C6 -> ACRF1BN101BC | C7: =[1]Юнит!D6 -> Бандаж для лица черный | D7: =[1]Юнит!E6 -> 2038162681926 | E7: 746 | F7: 0.4 | G7: 1243 | H7: 0.24774963 | I7: =_xlfn.XLOOKUP(D7,[1]Юнит!$E:$E,[1]Юнит!$AN:$AN) -> 829 | J7: =$J$4 -> 0.3 | K7: =I7/(100%-$J$4) -> 1184.2857 | L7: =_xlfn.XLOOKUP(D7,[1]Юнит!$E:$E,[1]Юнит!$AR:$AR) -> 0.3176011 | M7: =MROUND(O7-O7*N7,1) -> 746 | N7: =_xlfn.XLOOKUP($A7,'Текущая цена на ВБ'!$C:$C,'Текущая цена на ВБ'!$K:$K,0,0)% -> 0.4 | O7: =_xlfn.XLOOKUP($A7,'Текущая цена на ВБ'!$C:$C,'Текущая цена на ВБ'!$I:$I,0) -> 1243 | P7: =_xlfn.XLOOKUP($A7,[1]Юнит!$A:$A,[1]Юнит!$AJ:$AJ,0) -> 0.24928306 | Q7: =_xlfn.XLOOKUP($A7,'Акция 1'!$F:$F,'Акция 1'!$L:$L,0,0) -> 746 | R7: =(_xlfn.XLOOKUP($A7,'Акция 1'!$F:$F,'Акция 1'!$P:$P,0,0))% -> 0.41 | S7: =Q7/(100%-R7) -> 1264.4068 | T7: =_xlfn.XLOOKUP($A7,'Акция 2'!$F:$F,'Акция 2'!$L:$L,0,0) -> 0 | U7: =(_xlfn.XLOOKUP($A7,'Акция 2'!$F:$F,'Акция 2'!$O:$O,0,0))% -> 0 | V7: =T7/(100%-U7) -> 0 | W7: =_xlfn.XLOOKUP($A7,'Акция 3'!$F:$F,'Акция 3'!$L:$L,0,0) -> 562 | X7: =(_xlfn.XLOOKUP($A7,'Акция 3'!$F:$F,'Акция 3'!$P:$P,0,0))% -> 0.56 | Y7: =W7/(100%-X7) -> 1277.2727 | Z7: =_xlfn.XLOOKUP($A7,'Акция 4'!$F:$F,'Акция 4'!$L:$L,0,0) -> 0 | AA7: =(_xlfn.XLOOKUP($A7,'Акция 4'!$F:$F,'Акция 4'!$P:$P,0,0))% -> 0 | AB7: =Z7/(100%-AA7) -> 0 | AC7: =_xlfn.XLOOKUP($A7,'Акция 5'!$F:$F,'Акция 5'!$L:$L,0,0) -> 0 | AD7: =(_xlfn.XLOOKUP($A7,'Акция 5'!$F:$F,'Акция 5'!O:O,0,0))% -> 0 | AE7: =AC7/(100%-AD7) -> 0 | AF7: =_xlfn.XLOOKUP($A7,'Акция 6'!$F:$F,'Акция 6'!$L:$L,0,0) -> 0 | AG7: =(_xlfn.XLOOKUP($A7,'Акция 6'!$F:$F,'Акция 6'!$O:$O,0,0))% -> 0 | AH7: =AF7/(100%-AG7) -> 0 | AI7: =_xlfn.XLOOKUP($A7,'Акция 7'!$F:$F,'Акция 7'!$L:$L,0,0) -> 0 | AJ7: =(_xlfn.XLOOKUP($A7,'Акция 7'!$F:$F,'Акция 7'!$O:$O,0,0))% -> 0 | AK7: =AI7/(100%-AJ7) -> 0 | AL7: =_xlfn.XLOOKUP($A7,'Акция 8'!$F:$F,'Акция 8'!$L:$L,0,0) -> 0 | AM7: =(_xlfn.XLOOKUP($A7,'Акция 8'!$F:$F,'Акция 8'!$S:$S,0,0))% -> 0 | AN7: =AL7/(100%-AM7) -> 0 | AO7: =_xlfn.XLOOKUP($A7,'Акция 9'!$F:$F,'Акция 9'!$L:$L,0,0) -> 0 | AP7: =(_xlfn.XLOOKUP($A7,'Акция 9'!$F:$F,'Акция 9'!$O:$O,0,0))% -> 0 | AQ7: =AO7/(100%-AP7) -> 0 | AR7: =_xlfn.XLOOKUP($A7,'Акция 10'!$F:$F,'Акция 10'!$L:$L,0,0) -> 0 | AS7: =(_xlfn.XLOOKUP($A7,'Акция 10'!$F:$F,'Акция 10'!$O:$O,0,0))% -> 0 | AT7: =AR7/(100%-AS7) -> 0 | AU7: =_xlfn.XLOOKUP($A7,'Акция 11'!$F:$F,'Акция 11'!$L:$L,0,0) -> 0 | AV7: =(_xlfn.XLOOKUP($A7,'Акция 11'!$F:$F,'Акция 11'!$O:$O,0,0))% -> 0 | AW7: =AU7/(100%-AV7) -> 0 | BA7: =MAX($Q7,$T7,W7,Z7,AC7,AF7,AL7,AO7,AR7,AU7,AX7,AI7) -> 746 | BB7: =IF(BA7=0,0,_xlfn.XLOOKUP($BA7,$Q7:$AZ7,$Q$1:$AZ$1,0,0)) -> 1 | BC7: =_xlfn.XLOOKUP($BB7,$Q$1:$AZ$1,$Q7:$AZ7,0,0) -> 746 | BD7: =IF(BA7=0,0,$BD$3) -> 0.4 | BE7: =BC7/(100%-BD7) -> 1243.3333 | BF7: =_xlfn.XLOOKUP(A7,[1]Юнит!$A:$A,[1]Юнит!$AU:$AU,0) -> 0.24946556 | BG7: =P7 -> 0.24928306 | BH7: * | BI7: =MROUND(IF($BH7="*",$BE7,K7),1) -> 1243 | BJ7: =IF($BH7="*",$BD7,J7) -> 0.4 | BK7: =MROUND(BI7-BI7*BJ7,1) -> 746 | BL7: =IF(BH7="*",1,0) -> 1 | BM7: =_xlfn.XLOOKUP(A7,'Текущая цена на ВБ'!C:C,'Текущая цена на ВБ'!F:F) -> 216 | BN7: =_xlfn.XLOOKUP(A7,'Текущая цена на ВБ'!C:C,'Текущая цена на ВБ'!H:H) -> 999
A8: =[1]Юнит!A7 -> 169395410 | B8: =[1]Юнит!C7 -> ACRF1BN201GR | C8: =[1]Юнит!D7 -> Бандаж для лица серый | D8: =[1]Юнит!E7 -> 2038172050200 | E8: 1045 | F8: 0.4 | G8: 1742 | H8: 0.22712541 | I8: =_xlfn.XLOOKUP(D8,[1]Юнит!$E:$E,[1]Юнит!$AN:$AN) -> 1159 | J8: =$J$4 -> 0.3 | K8: =I8/(100%-$J$4) -> 1655.7143 | L8: =_xlfn.XLOOKUP(D8,[1]Юнит!$E:$E,[1]Юнит!$AR:$AR) -> 0.2967027 | M8: =MROUND(O8-O8*N8,1) -> 1045 | N8: =_xlfn.XLOOKUP($A8,'Текущая цена на ВБ'!$C:$C,'Текущая цена на ВБ'!$K:$K,0,0)% -> 0.4 | O8: =_xlfn.XLOOKUP($A8,'Текущая цена на ВБ'!$C:$C,'Текущая цена на ВБ'!$I:$I,0) -> 1742 | P8: =_xlfn.XLOOKUP($A8,[1]Юнит!$A:$A,[1]Юнит!$AJ:$AJ,0) -> 0.22775012 | Q8: =_xlfn.XLOOKUP($A8,'Акция 1'!$F:$F,'Акция 1'!$L:$L,0,0) -> 1045 | R8: =(_xlfn.XLOOKUP($A8,'Акция 1'!$F:$F,'Акция 1'!$P:$P,0,0))% -> 0.37 | S8: =Q8/(100%-R8) -> 1658.7302 | T8: =_xlfn.XLOOKUP($A8,'Акция 2'!$F:$F,'Акция 2'!$L:$L,0,0) -> 0 | U8: =(_xlfn.XLOOKUP($A8,'Акция 2'!$F:$F,'Акция 2'!$O:$O,0,0))% -> 0 | V8: =T8/(100%-U8) -> 0 | W8: =_xlfn.XLOOKUP($A8,'Акция 3'!$F:$F,'Акция 3'!$L:$L,0,0) -> 1011 | X8: =(_xlfn.XLOOKUP($A8,'Акция 3'!$F:$F,'Акция 3'!$P:$P,0,0))% -> 0.39 | Y8: =W8/(100%-X8) -> 1657.377 | Z8: =_xlfn.XLOOKUP($A8,'Акция 4'!$F:$F,'Акция 4'!$L:$L,0,0) -> 0 | AA8: =(_xlfn.XLOOKUP($A8,'Акция 4'!$F:$F,'Акция 4'!$P:$P,0,0))% -> 0 | AB8: =Z8/(100%-AA8) -> 0 | AC8: =_xlfn.XLOOKUP($A8,'Акция 5'!$F:$F,'Акция 5'!$L:$L,0,0) -> 0 | AD8: =(_xlfn.XLOOKUP($A8,'Акция 5'!$F:$F,'Акция 5'!O:O,0,0))% -> 0 | AE8: =AC8/(100%-AD8) -> 0 | AF8: =_xlfn.XLOOKUP($A8,'Акция 6'!$F:$F,'Акция 6'!$L:$L,0,0) -> 0 | AG8: =(_xlfn.XLOOKUP($A8,'Акция 6'!$F:$F,'Акция 6'!$O:$O,0,0))% -> 0 | AH8: =AF8/(100%-AG8) -> 0 | AI8: =_xlfn.XLOOKUP($A8,'Акция 7'!$F:$F,'Акция 7'!$L:$L,0,0) -> 0 | AJ8: =(_xlfn.XLOOKUP($A8,'Акция 7'!$F:$F,'Акция 7'!$O:$O,0,0))% -> 0 | AK8: =AI8/(100%-AJ8) -> 0 | AL8: =_xlfn.XLOOKUP($A8,'Акция 8'!$F:$F,'Акция 8'!$L:$L,0,0) -> 0 | AM8: =(_xlfn.XLOOKUP($A8,'Акция 8'!$F:$F,'Акция 8'!$S:$S,0,0))% -> 0 | AN8: =AL8/(100%-AM8) -> 0 | AO8: =_xlfn.XLOOKUP($A8,'Акция 9'!$F:$F,'Акция 9'!$L:$L,0,0) -> 0 | AP8: =(_xlfn.XLOOKUP($A8,'Акция 9'!$F:$F,'Акция 9'!$O:$O,0,0))% -> 0 | AQ8: =AO8/(100%-AP8) -> 0 | AR8: =_xlfn.XLOOKUP($A8,'Акция 10'!$F:$F,'Акция 10'!$L:$L,0,0) -> 0 | AS8: =(_xlfn.XLOOKUP($A8,'Акция 10'!$F:$F,'Акция 10'!$O:$O,0,0))% -> 0 | AT8: =AR8/(100%-AS8) -> 0 | AU8: =_xlfn.XLOOKUP($A8,'Акция 11'!$F:$F,'Акция 11'!$L:$L,0,0) -> 0 | AV8: =(_xlfn.XLOOKUP($A8,'Акция 11'!$F:$F,'Акция 11'!$O:$O,0,0))% -> 0 | AW8: =AU8/(100%-AV8) -> 0 | BA8: =MAX($Q8,$T8,W8,Z8,AC8,AF8,AL8,AO8,AR8,AU8,AX8,AI8) -> 1045 | BB8: =IF(BA8=0,0,_xlfn.XLOOKUP($BA8,$Q8:$AZ8,$Q$1:$AZ$1,0,0)) -> 1 | BC8: =_xlfn.XLOOKUP($BB8,$Q$1:$AZ$1,$Q8:$AZ8,0,0) -> 1045 | BD8: =IF(BA8=0,0,$BD$3) -> 0.4 | BE8: =BC8/(100%-BD8) -> 1741.6667 | BF8: =_xlfn.XLOOKUP(A8,[1]Юнит!$A:$A,[1]Юнит!$AU:$AU,0) -> 0.22761572 | BG8: =P8 -> 0.22775012 | BH8: * | BI8: =MROUND(IF($BH8="*",$BE8,K8),1) -> 1742 | BJ8: =IF($BH8="*",$BD8,J8) -> 0.4 | BK8: =MROUND(BI8-BI8*BJ8,1) -> 1045 | BL8: =IF(BH8="*",1,0) -> 1 | BM8: =_xlfn.XLOOKUP(A8,'Текущая цена на ВБ'!C:C,'Текущая цена на ВБ'!F:F) -> 202 | BN8: =_xlfn.XLOOKUP(A8,'Текущая цена на ВБ'!C:C,'Текущая цена на ВБ'!H:H) -> 999
A9: =[1]Юнит!A8 -> 172832355 | B9: =[1]Юнит!C8 -> AHMA7BW101BG | C9: =[1]Юнит!D8 -> Мешки 7 шт. | D9: =[1]Юнит!E8 -> 2038337652454 | E9: 2097 | F9: 0.4 | G9: 3495 | H9: 0.2678246 | I9: =_xlfn.XLOOKUP(D9,[1]Юнит!$E:$E,[1]Юнит!$AN:$AN) -> 2119 | J9: =$J$4 -> 0.3 | K9: =I9/(100%-$J$4) -> 3027.1429 | L9: =_xlfn.XLOOKUP(D9,[1]Юнит!$E:$E,[1]Юнит!$AR:$AR) -> 0.2760005 | M9: =MROUND(O9-O9*N9,1) -> 2097 | N9: =_xlfn.XLOOKUP($A9,'Текущая цена на ВБ'!$C:$C,'Текущая цена на ВБ'!$K:$K,0,0)% -> 0.4 | O9: =_xlfn.XLOOKUP($A9,'Текущая цена на ВБ'!$C:$C,'Текущая цена на ВБ'!$I:$I,0) -> 3495 | P9: =_xlfn.XLOOKUP($A9,[1]Юнит!$A:$A,[1]Юнит!$AJ:$AJ,0) -> 0.26913927 | Q9: =_xlfn.XLOOKUP($A9,'Акция 1'!$F:$F,'Акция 1'!$L:$L,0,0) -> 2097 | R9: =(_xlfn.XLOOKUP($A9,'Акция 1'!$F:$F,'Акция 1'!$P:$P,0,0))% -> 0.31 | S9: =Q9/(100%-R9) -> 3039.1304 | T9: =_xlfn.XLOOKUP($A9,'Акция 2'!$F:$F,'Акция 2'!$L:$L,0,0) -> 0 | U9: =(_xlfn.XLOOKUP($A9,'Акция 2'!$F:$F,'Акция 2'!$O:$O,0,0))% -> 0 | V9: =T9/(100%-U9) -> 0 | W9: =_xlfn.XLOOKUP($A9,'Акция 3'!$F:$F,'Акция 3'!$L:$L,0,0) -> 1101 | X9: =(_xlfn.XLOOKUP($A9,'Акция 3'!$F:$F,'Акция 3'!$P:$P,0,0))% -> 0.64 | Y9: =W9/(100%-X9) -> 3058.3333 | Z9: =_xlfn.XLOOKUP($A9,'Акция 4'!$F:$F,'Акция 4'!$L:$L,0,0) -> 0 | AA9: =(_xlfn.XLOOKUP($A9,'Акция 4'!$F:$F,'Акция 4'!$P:$P,0,0))% -> 0 | AB9: =Z9/(100%-AA9) -> 0 | AC9: =_xlfn.XLOOKUP($A9,'Акция 5'!$F:$F,'Акция 5'!$L:$L,0,0) -> 0 | AD9: =(_xlfn.XLOOKUP($A9,'Акция 5'!$F:$F,'Акция 5'!O:O,0,0))% -> 0 | AE9: =AC9/(100%-AD9) -> 0 | AF9: =_xlfn.XLOOKUP($A9,'Акция 6'!$F:$F,'Акция 6'!$L:$L,0,0) -> 0 | AG9: =(_xlfn.XLOOKUP($A9,'Акция 6'!$F:$F,'Акция 6'!$O:$O,0,0))% -> 0 | AH9: =AF9/(100%-AG9) -> 0 | AI9: =_xlfn.XLOOKUP($A9,'Акция 7'!$F:$F,'Акция 7'!$L:$L,0,0) -> 0 | AJ9: =(_xlfn.XLOOKUP($A9,'Акция 7'!$F:$F,'Акция 7'!$O:$O,0,0))% -> 0 | AK9: =AI9/(100%-AJ9) -> 0 | AL9: =_xlfn.XLOOKUP($A9,'Акция 8'!$F:$F,'Акция 8'!$L:$L,0,0) -> 0 | AM9: =(_xlfn.XLOOKUP($A9,'Акция 8'!$F:$F,'Акция 8'!$S:$S,0,0))% -> 0 | AN9: =AL9/(100%-AM9) -> 0 | AO9: =_xlfn.XLOOKUP($A9,'Акция 9'!$F:$F,'Акция 9'!$L:$L,0,0) -> 0 | AP9: =(_xlfn.XLOOKUP($A9,'Акция 9'!$F:$F,'Акция 9'!$O:$O,0,0))% -> 0 | AQ9: =AO9/(100%-AP9) -> 0 | AR9: =_xlfn.XLOOKUP($A9,'Акция 10'!$F:$F,'Акция 10'!$L:$L,0,0) -> 0 | AS9: =(_xlfn.XLOOKUP($A9,'Акция 10'!$F:$F,'Акция 10'!$O:$O,0,0))% -> 0 | AT9: =AR9/(100%-AS9) -> 0 | AU9: =_xlfn.XLOOKUP($A9,'Акция 11'!$F:$F,'Акция 11'!$L:$L,0,0) -> 0 | AV9: =(_xlfn.XLOOKUP($A9,'Акция 11'!$F:$F,'Акция 11'!$O:$O,0,0))% -> 0 | AW9: =AU9/(100%-AV9) -> 0 | BA9: =MAX($Q9,$T9,W9,Z9,AC9,AF9,AL9,AO9,AR9,AU9,AX9,AI9) -> 2097 | BB9: =IF(BA9=0,0,_xlfn.XLOOKUP($BA9,$Q9:$AZ9,$Q$1:$AZ$1,0,0)) -> 1 | BC9: =_xlfn.XLOOKUP($BB9,$Q$1:$AZ$1,$Q9:$AZ9,0,0) -> 2097 | BD9: =IF(BA9=0,0,$BD$3) -> 0.4 | BE9: =BC9/(100%-BD9) -> 3495 | BF9: =_xlfn.XLOOKUP(A9,[1]Юнит!$A:$A,[1]Юнит!$AU:$AU,0) -> 0.26913927 | BG9: =P9 -> 0.26913927 | BH9: * | BI9: =MROUND(IF($BH9="*",$BE9,K9),1) -> 3495 | BJ9: =IF($BH9="*",$BD9,J9) -> 0.4 | BK9: =MROUND(BI9-BI9*BJ9,1) -> 2097 | BL9: =IF(BH9="*",1,0) -> 1 | BM9: =_xlfn.XLOOKUP(A9,'Текущая цена на ВБ'!C:C,'Текущая цена на ВБ'!F:F) -> 139 | BN9: =_xlfn.XLOOKUP(A9,'Текущая цена на ВБ'!C:C,'Текущая цена на ВБ'!H:H) -> 269
A10: =[1]Юнит!A9 -> 176500218 | B10: =[1]Юнит!C9 -> AHMA1BW101BG | C10: =[1]Юнит!D9 -> Мешок для бюстгалтеров | D10: =[1]Юнит!E9 -> 2038597850744 | E10: 539 | F10: 0.4 | G10: 898 | H10: 0.1392272 | I10: =_xlfn.XLOOKUP(D10,[1]Юнит!$E:$E,[1]Юнит!$AN:$AN) -> 599 | J10: =$J$4 -> 0.3 | K10: =I10/(100%-$J$4) -> 855.71429 | L10: =_xlfn.XLOOKUP(D10,[1]Юнит!$E:$E,[1]Юнит!$AR:$AR) -> 0.26732668 | M10: =MROUND(O10-O10*N10,1) -> 539 | N10: =_xlfn.XLOOKUP($A10,'Текущая цена на ВБ'!$C:$C,'Текущая цена на ВБ'!$K:$K,0,0)% -> 0.4 | O10: =_xlfn.XLOOKUP($A10,'Текущая цена на ВБ'!$C:$C,'Текущая цена на ВБ'!$I:$I,0) -> 898 | P10: =_xlfn.XLOOKUP($A10,[1]Юнит!$A:$A,[1]Юнит!$AJ:$AJ,0) -> 0.19328635 | Q10: =_xlfn.XLOOKUP($A10,'Акция 1'!$F:$F,'Акция 1'!$L:$L,0,0) -> 539 | R10: =(_xlfn.XLOOKUP($A10,'Акция 1'!$F:$F,'Акция 1'!$P:$P,0,0))% -> 0.4 | S10: =Q10/(100%-R10) -> 898.33333 | T10: =_xlfn.XLOOKUP($A10,'Акция 2'!$F:$F,'Акция 2'!$L:$L,0,0) -> 0 | U10: =(_xlfn.XLOOKUP($A10,'Акция 2'!$F:$F,'Акция 2'!$O:$O,0,0))% -> 0 | V10: =T10/(100%-U10) -> 0 | W10: =_xlfn.XLOOKUP($A10,'Акция 3'!$F:$F,'Акция 3'!$L:$L,0,0) -> 475 | X10: =(_xlfn.XLOOKUP($A10,'Акция 3'!$F:$F,'Акция 3'!$P:$P,0,0))% -> 0.4 | Y10: =W10/(100%-X10) -> 791.66667 | Z10: =_xlfn.XLOOKUP($A10,'Акция 4'!$F:$F,'Акция 4'!$L:$L,0,0) -> 0 | AA10: =(_xlfn.XLOOKUP($A10,'Акция 4'!$F:$F,'Акция 4'!$P:$P,0,0))% -> 0 | AB10: =Z10/(100%-AA10) -> 0 | AC10: =_xlfn.XLOOKUP($A10,'Акция 5'!$F:$F,'Акция 5'!$L:$L,0,0) -> 0 | AD10: =(_xlfn.XLOOKUP($A10,'Акция 5'!$F:$F,'Акция 5'!O:O,0,0))% -> 0 | AE10: =AC10/(100%-AD10) -> 0 | AF10: =_xlfn.XLOOKUP($A10,'Акция 6'!$F:$F,'Акция 6'!$L:$L,0,0) -> 0 | AG10: =(_xlfn.XLOOKUP($A10,'Акция 6'!$F:$F,'Акция 6'!$O:$O,0,0))% -> 0 | AH10: =AF10/(100%-AG10) -> 0 | AI10: =_xlfn.XLOOKUP($A10,'Акция 7'!$F:$F,'Акция 7'!$L:$L,0,0) -> 0 | AJ10: =(_xlfn.XLOOKUP($A10,'Акция 7'!$F:$F,'Акция 7'!$O:$O,0,0))% -> 0 | AK10: =AI10/(100%-AJ10) -> 0 | AL10: =_xlfn.XLOOKUP($A10,'Акция 8'!$F:$F,'Акция 8'!$L:$L,0,0) -> 0 | AM10: =(_xlfn.XLOOKUP($A10,'Акция 8'!$F:$F,'Акция 8'!$S:$S,0,0))% -> 0 | AN10: =AL10/(100%-AM10) -> 0 | AO10: =_xlfn.XLOOKUP($A10,'Акция 9'!$F:$F,'Акция 9'!$L:$L,0,0) -> 0 | AP10: =(_xlfn.XLOOKUP($A10,'Акция 9'!$F:$F,'Акция 9'!$O:$O,0,0))% -> 0 | AQ10: =AO10/(100%-AP10) -> 0 | AR10: =_xlfn.XLOOKUP($A10,'Акция 10'!$F:$F,'Акция 10'!$L:$L,0,0) -> 0 | AS10: =(_xlfn.XLOOKUP($A10,'Акция 10'!$F:$F,'Акция 10'!$O:$O,0,0))% -> 0 | AT10: =AR10/(100%-AS10) -> 0 | AU10: =_xlfn.XLOOKUP($A10,'Акция 11'!$F:$F,'Акция 11'!$L:$L,0,0) -> 0 | AV10: =(_xlfn.XLOOKUP($A10,'Акция 11'!$F:$F,'Акция 11'!$O:$O,0,0))% -> 0 | AW10: =AU10/(100%-AV10) -> 0 | BA10: =MAX($Q10,$T10,W10,Z10,AC10,AF10,AL10,AO10,AR10,AU10,AX10,AI10) -> 539 | BB10: =IF(BA10=0,0,_xlfn.XLOOKUP($BA10,$Q10:$AZ10,$Q$1:$AZ$1,0,0)) -> 1 | BC10: =_xlfn.XLOOKUP($BB10,$Q$1:$AZ$1,$Q10:$AZ10,0,0) -> 539 | BD10: =IF(BA10=0,0,$BD$3) -> 0.4 | BE10: =BC10/(100%-BD10) -> 898.33333 | BF10: =_xlfn.XLOOKUP(A10,[1]Юнит!$A:$A,[1]Юнит!$AU:$AU,0) -> 0.19355971 | BG10: =P10 -> 0.19328635 | BH10: * | BI10: =MROUND(IF($BH10="*",$BE10,K10),1) -> 898 | BJ10: =IF($BH10="*",$BD10,J10) -> 0.4 | BK10: =MROUND(BI10-BI10*BJ10,1) -> 539 | BL10: =IF(BH10="*",1,0) -> 1 | BM10: =_xlfn.XLOOKUP(A10,'Текущая цена на ВБ'!C:C,'Текущая цена на ВБ'!F:F) -> 320 | BN10: =_xlfn.XLOOKUP(A10,'Текущая цена на ВБ'!C:C,'Текущая цена на ВБ'!H:H) -> 726
A11: =[1]Юнит!A10 -> 177404837 | B11: =[1]Юнит!C10 -> AHMA3BW101BG | C11: =[1]Юнит!D10 -> Мешки 3 шт. | D11: =[1]Юнит!E10 -> 2038627692689 | E11: 1246 | F11: 0.4 | G11: 2077 | H11: 0.23293966 | I11: =_xlfn.XLOOKUP(D11,[1]Юнит!$E:$E,[1]Юнит!$AN:$AN) -> 1259 | J11: =$J$4 -> 0.3 | K11: =I11/(100%-$J$4) -> 1798.5714 | L11: =_xlfn.XLOOKUP(D11,[1]Юнит!$E:$E,[1]Юнит!$AR:$AR) -> 0.24144133 | M11: =MROUND(O11-O11*N11,1) -> 1246 | N11: =_xlfn.XLOOKUP($A11,'Текущая цена на ВБ'!$C:$C,'Текущая цена на ВБ'!$K:$K,0,0)% -> 0.4 | O11: =_xlfn.XLOOKUP($A11,'Текущая цена на ВБ'!$C:$C,'Текущая цена на ВБ'!$I:$I,0) -> 2077 | P11: =_xlfn.XLOOKUP($A11,[1]Юнит!$A:$A,[1]Юнит!$AJ:$AJ,0) -> 0.23436899 | Q11: =_xlfn.XLOOKUP($A11,'Акция 1'!$F:$F,'Акция 1'!$L:$L,0,0) -> 1246 | R11: =(_xlfn.XLOOKUP($A11,'Акция 1'!$F:$F,'Акция 1'!$P:$P,0,0))% -> 0.31 | S11: =Q11/(100%-R11) -> 1805.7971 | T11: =_xlfn.XLOOKUP($A11,'Акция 2'!$F:$F,'Акция 2'!$L:$L,0,0) -> 0 | U11: =(_xlfn.XLOOKUP($A11,'Акция 2'!$F:$F,'Акция 2'!$O:$O,0,0))% -> 0 | V11: =T11/(100%-U11) -> 0 | W11: =_xlfn.XLOOKUP($A11,'Акция 3'!$F:$F,'Акция 3'!$L:$L,0,0) -> 696 | X11: =(_xlfn.XLOOKUP($A11,'Акция 3'!$F:$F,'Акция 3'!$P:$P,0,0))% -> 0.62 | Y11: =W11/(100%-X11) -> 1831.5789 | Z11: =_xlfn.XLOOKUP($A11,'Акция 4'!$F:$F,'Акция 4'!$L:$L,0,0) -> 0 | AA11: =(_xlfn.XLOOKUP($A11,'Акция 4'!$F:$F,'Акция 4'!$P:$P,0,0))% -> 0 | AB11: =Z11/(100%-AA11) -> 0 | AC11: =_xlfn.XLOOKUP($A11,'Акция 5'!$F:$F,'Акция 5'!$L:$L,0,0) -> 0 | AD11: =(_xlfn.XLOOKUP($A11,'Акция 5'!$F:$F,'Акция 5'!O:O,0,0))% -> 0 | AE11: =AC11/(100%-AD11) -> 0 | AF11: =_xlfn.XLOOKUP($A11,'Акция 6'!$F:$F,'Акция 6'!$L:$L,0,0) -> 0 | AG11: =(_xlfn.XLOOKUP($A11,'Акция 6'!$F:$F,'Акция 6'!$O:$O,0,0))% -> 0 | AH11: =AF11/(100%-AG11) -> 0 | AI11: =_xlfn.XLOOKUP($A11,'Акция 7'!$F:$F,'Акция 7'!$L:$L,0,0) -> 0 | AJ11: =(_xlfn.XLOOKUP($A11,'Акция 7'!$F:$F,'Акция 7'!$O:$O,0,0))% -> 0 | AK11: =AI11/(100%-AJ11) -> 0 | AL11: =_xlfn.XLOOKUP($A11,'Акция 8'!$F:$F,'Акция 8'!$L:$L,0,0) -> 0 | AM11: =(_xlfn.XLOOKUP($A11,'Акция 8'!$F:$F,'Акция 8'!$S:$S,0,0))% -> 0 | AN11: =AL11/(100%-AM11) -> 0 | AO11: =_xlfn.XLOOKUP($A11,'Акция 9'!$F:$F,'Акция 9'!$L:$L,0,0) -> 0 | AP11: =(_xlfn.XLOOKUP($A11,'Акция 9'!$F:$F,'Акция 9'!$O:$O,0,0))% -> 0 | AQ11: =AO11/(100%-AP11) -> 0 | AR11: =_xlfn.XLOOKUP($A11,'Акция 10'!$F:$F,'Акция 10'!$L:$L,0,0) -> 0 | AS11: =(_xlfn.XLOOKUP($A11,'Акция 10'!$F:$F,'Акция 10'!$O:$O,0,0))% -> 0 | AT11: =AR11/(100%-AS11) -> 0 | AU11: =_xlfn.XLOOKUP($A11,'Акция 11'!$F:$F,'Акция 11'!$L:$L,0,0) -> 0 | AV11: =(_xlfn.XLOOKUP($A11,'Акция 11'!$F:$F,'Акция 11'!$O:$O,0,0))% -> 0 | AW11: =AU11/(100%-AV11) -> 0 | BA11: =MAX($Q11,$T11,W11,Z11,AC11,AF11,AL11,AO11,AR11,AU11,AX11,AI11) -> 1246 | BB11: =IF(BA11=0,0,_xlfn.XLOOKUP($BA11,$Q11:$AZ11,$Q$1:$AZ$1,0,0)) -> 1 | BC11: =_xlfn.XLOOKUP($BB11,$Q$1:$AZ$1,$Q11:$AZ11,0,0) -> 1246 | BD11: =IF(BA11=0,0,$BD$3) -> 0.4 | BE11: =BC11/(100%-BD11) -> 2076.6667 | BF11: =_xlfn.XLOOKUP(A11,[1]Юнит!$A:$A,[1]Юнит!$AU:$AU,0) -> 0.23425734 | BG11: =P11 -> 0.23436899 | BH11: * | BI11: =MROUND(IF($BH11="*",$BE11,K11),1) -> 2077 | BJ11: =IF($BH11="*",$BD11,J11) -> 0.4 | BK11: =MROUND(BI11-BI11*BJ11,1) -> 1246 | BL11: =IF(BH11="*",1,0) -> 1 | BM11: =_xlfn.XLOOKUP(A11,'Текущая цена на ВБ'!C:C,'Текущая цена на ВБ'!F:F) -> 146 | BN11: =_xlfn.XLOOKUP(A11,'Текущая цена на ВБ'!C:C,'Текущая цена на ВБ'!H:H) -> 502
A12: =[1]Юнит!A11 -> 177405495 | B12: =[1]Юнит!C11 -> AHMA3BW102BG | C12: =[1]Юнит!D11 -> Мешки/деликат 3 шт. | D12: =[1]Юнит!E11 -> 2038627713902 | E12: 1108 | F12: 0.4 | G12: 1847 | H12: 0.23328655 | I12: =_xlfn.XLOOKUP(D12,[1]Юнит!$E:$E,[1]Юнит!$AN:$AN) -> 1119 | J12: =$J$4 -> 0.3 | K12: =I12/(100%-$J$4) -> 1598.5714 | L12: =_xlfn.XLOOKUP(D12,[1]Юнит!$E:$E,[1]Юнит!$AR:$AR) -> 0.24160115 | M12: =MROUND(O12-O12*N12,1) -> 1108 | N12: =_xlfn.XLOOKUP($A12,'Текущая цена на ВБ'!$C:$C,'Текущая цена на ВБ'!$K:$K,0,0)% -> 0.4 | O12: =_xlfn.XLOOKUP($A12,'Текущая цена на ВБ'!$C:$C,'Текущая цена на ВБ'!$I:$I,0) -> 1847 | P12: =_xlfn.XLOOKUP($A12,[1]Юнит!$A:$A,[1]Юнит!$AJ:$AJ,0) -> 0.23489234 | Q12: =_xlfn.XLOOKUP($A12,'Акция 1'!$F:$F,'Акция 1'!$L:$L,0,0) -> 1108 | R12: =(_xlfn.XLOOKUP($A12,'Акция 1'!$F:$F,'Акция 1'!$P:$P,0,0))% -> 0.31 | S12: =Q12/(100%-R12) -> 1605.7971 | T12: =_xlfn.XLOOKUP($A12,'Акция 2'!$F:$F,'Акция 2'!$L:$L,0,0) -> 0 | U12: =(_xlfn.XLOOKUP($A12,'Акция 2'!$F:$F,'Акция 2'!$O:$O,0,0))% -> 0 | V12: =T12/(100%-U12) -> 0 | W12: =_xlfn.XLOOKUP($A12,'Акция 3'!$F:$F,'Акция 3'!$L:$L,0,0) -> 842 | X12: =(_xlfn.XLOOKUP($A12,'Акция 3'!$F:$F,'Акция 3'!$P:$P,0,0))% -> 0.48 | Y12: =W12/(100%-X12) -> 1619.2308 | Z12: =_xlfn.XLOOKUP($A12,'Акция 4'!$F:$F,'Акция 4'!$L:$L,0,0) -> 0 | AA12: =(_xlfn.XLOOKUP($A12,'Акция 4'!$F:$F,'Акция 4'!$P:$P,0,0))% -> 0 | AB12: =Z12/(100%-AA12) -> 0 | AC12: =_xlfn.XLOOKUP($A12,'Акция 5'!$F:$F,'Акция 5'!$L:$L,0,0) -> 0 | AD12: =(_xlfn.XLOOKUP($A12,'Акция 5'!$F:$F,'Акция 5'!O:O,0,0))% -> 0 | AE12: =AC12/(100%-AD12) -> 0 | AF12: =_xlfn.XLOOKUP($A12,'Акция 6'!$F:$F,'Акция 6'!$L:$L,0,0) -> 0 | AG12: =(_xlfn.XLOOKUP($A12,'Акция 6'!$F:$F,'Акция 6'!$O:$O,0,0))% -> 0 | AH12: =AF12/(100%-AG12) -> 0 | AI12: =_xlfn.XLOOKUP($A12,'Акция 7'!$F:$F,'Акция 7'!$L:$L,0,0) -> 0 | AJ12: =(_xlfn.XLOOKUP($A12,'Акция 7'!$F:$F,'Акция 7'!$O:$O,0,0))% -> 0 | AK12: =AI12/(100%-AJ12) -> 0 | AL12: =_xlfn.XLOOKUP($A12,'Акция 8'!$F:$F,'Акция 8'!$L:$L,0,0) -> 0 | AM12: =(_xlfn.XLOOKUP($A12,'Акция 8'!$F:$F,'Акция 8'!$S:$S,0,0))% -> 0 | AN12: =AL12/(100%-AM12) -> 0 | AO12: =_xlfn.XLOOKUP($A12,'Акция 9'!$F:$F,'Акция 9'!$L:$L,0,0) -> 0 | AP12: =(_xlfn.XLOOKUP($A12,'Акция 9'!$F:$F,'Акция 9'!$O:$O,0,0))% -> 0 | AQ12: =AO12/(100%-AP12) -> 0 | AR12: =_xlfn.XLOOKUP($A12,'Акция 10'!$F:$F,'Акция 10'!$L:$L,0,0) -> 0 | AS12: =(_xlfn.XLOOKUP($A12,'Акция 10'!$F:$F,'Акция 10'!$O:$O,0,0))% -> 0 | AT12: =AR12/(100%-AS12) -> 0 | AU12: =_xlfn.XLOOKUP($A12,'Акция 11'!$F:$F,'Акция 11'!$L:$L,0,0) -> 0 | AV12: =(_xlfn.XLOOKUP($A12,'Акция 11'!$F:$F,'Акция 11'!$O:$O,0,0))% -> 0 | AW12: =AU12/(100%-AV12) -> 0 | BA12: =MAX($Q12,$T12,W12,Z12,AC12,AF12,AL12,AO12,AR12,AU12,AX12,AI12) -> 1108 | BB12: =IF(BA12=0,0,_xlfn.XLOOKUP($BA12,$Q12:$AZ12,$Q$1:$AZ$1,0,0)) -> 1 | BC12: =_xlfn.XLOOKUP($BB12,$Q$1:$AZ$1,$Q12:$AZ12,0,0) -> 1108 | BD12: =IF(BA12=0,0,$BD$3) -> 0.4 | BE12: =BC12/(100%-BD12) -> 1846.6667 | BF12: =_xlfn.XLOOKUP(A12,[1]Юнит!$A:$A,[1]Юнит!$AU:$AU,0) -> 0.23476687 | BG12: =P12 -> 0.23489234 | BH12: * | BI12: =MROUND(IF($BH12="*",$BE12,K12),1) -> 1847 | BJ12: =IF($BH12="*",$BD12,J12) -> 0.4 | BK12: =MROUND(BI12-BI12*BJ12,1) -> 1108 | BL12: =IF(BH12="*",1,0) -> 1 | BM12: =_xlfn.XLOOKUP(A12,'Текущая цена на ВБ'!C:C,'Текущая цена на ВБ'!F:F) -> 264 | BN12: =_xlfn.XLOOKUP(A12,'Текущая цена на ВБ'!C:C,'Текущая цена на ВБ'!H:H) -> 999
A13: =[1]Юнит!A12 -> 176721350 | B13: =[1]Юнит!C12 -> AHMA3BW201WH | C13: =[1]Юнит!D12 -> Мешки/шнурок мелк 3 шт. | D13: =[1]Юнит!E12 -> 2038606201642 | E13: 757 | F13: 0.4 | G13: 1262 | H13: 0.17981188 | I13: =_xlfn.XLOOKUP(D13,[1]Юнит!$E:$E,[1]Юнит!$AN:$AN) -> 839 | J13: =$J$4 -> 0.3 | K13: =I13/(100%-$J$4) -> 1198.5714 | L13: =_xlfn.XLOOKUP(D13,[1]Юнит!$E:$E,[1]Юнит!$AR:$AR) -> 0.25386338 | M13: =MROUND(O13-O13*N13,1) -> 757 | N13: =_xlfn.XLOOKUP($A13,'Текущая цена на ВБ'!$C:$C,'Текущая цена на ВБ'!$K:$K,0,0)% -> 0.4 | O13: =_xlfn.XLOOKUP($A13,'Текущая цена на ВБ'!$C:$C,'Текущая цена на ВБ'!$I:$I,0) -> 1262 | P13: =_xlfn.XLOOKUP($A13,[1]Юнит!$A:$A,[1]Юнит!$AJ:$AJ,0) -> 0.18082062 | Q13: =_xlfn.XLOOKUP($A13,'Акция 1'!$F:$F,'Акция 1'!$L:$L,0,0) -> 757 | R13: =(_xlfn.XLOOKUP($A13,'Акция 1'!$F:$F,'Акция 1'!$P:$P,0,0))% -> 0.37 | S13: =Q13/(100%-R13) -> 1201.5873 | T13: =_xlfn.XLOOKUP($A13,'Акция 2'!$F:$F,'Акция 2'!$L:$L,0,0) -> 0 | U13: =(_xlfn.XLOOKUP($A13,'Акция 2'!$F:$F,'Акция 2'!$O:$O,0,0))% -> 0 | V13: =T13/(100%-U13) -> 0 | W13: =_xlfn.XLOOKUP($A13,'Акция 3'!$F:$F,'Акция 3'!$L:$L,0,0) -> 577 | X13: =(_xlfn.XLOOKUP($A13,'Акция 3'!$F:$F,'Акция 3'!$P:$P,0,0))% -> 0.52 | Y13: =W13/(100%-X13) -> 1202.0833 | Z13: =_xlfn.XLOOKUP($A13,'Акция 4'!$F:$F,'Акция 4'!$L:$L,0,0) -> 0 | AA13: =(_xlfn.XLOOKUP($A13,'Акция 4'!$F:$F,'Акция 4'!$P:$P,0,0))% -> 0 | AB13: =Z13/(100%-AA13) -> 0 | AC13: =_xlfn.XLOOKUP($A13,'Акция 5'!$F:$F,'Акция 5'!$L:$L,0,0) -> 0 | AD13: =(_xlfn.XLOOKUP($A13,'Акция 5'!$F:$F,'Акция 5'!O:O,0,0))% -> 0 | AE13: =AC13/(100%-AD13) -> 0 | AF13: =_xlfn.XLOOKUP($A13,'Акция 6'!$F:$F,'Акция 6'!$L:$L,0,0) -> 0 | AG13: =(_xlfn.XLOOKUP($A13,'Акция 6'!$F:$F,'Акция 6'!$O:$O,0,0))% -> 0 | AH13: =AF13/(100%-AG13) -> 0 | AI13: =_xlfn.XLOOKUP($A13,'Акция 7'!$F:$F,'Акция 7'!$L:$L,0,0) -> 0 | AJ13: =(_xlfn.XLOOKUP($A13,'Акция 7'!$F:$F,'Акция 7'!$O:$O,0,0))% -> 0 | AK13: =AI13/(100%-AJ13) -> 0 | AL13: =_xlfn.XLOOKUP($A13,'Акция 8'!$F:$F,'Акция 8'!$L:$L,0,0) -> 0 | AM13: =(_xlfn.XLOOKUP($A13,'Акция 8'!$F:$F,'Акция 8'!$S:$S,0,0))% -> 0 | AN13: =AL13/(100%-AM13) -> 0 | AO13: =_xlfn.XLOOKUP($A13,'Акция 9'!$F:$F,'Акция 9'!$L:$L,0,0) -> 0 | AP13: =(_xlfn.XLOOKUP($A13,'Акция 9'!$F:$F,'Акция 9'!$O:$O,0,0))% -> 0 | AQ13: =AO13/(100%-AP13) -> 0 | AR13: =_xlfn.XLOOKUP($A13,'Акция 10'!$F:$F,'Акция 10'!$L:$L,0,0) -> 0 | AS13: =(_xlfn.XLOOKUP($A13,'Акция 10'!$F:$F,'Акция 10'!$O:$O,0,0))% -> 0 | AT13: =AR13/(100%-AS13) -> 0 | AU13: =_xlfn.XLOOKUP($A13,'Акция 11'!$F:$F,'Акция 11'!$L:$L,0,0) -> 0 | AV13: =(_xlfn.XLOOKUP($A13,'Акция 11'!$F:$F,'Акция 11'!$O:$O,0,0))% -> 0 | AW13: =AU13/(100%-AV13) -> 0 | BA13: =MAX($Q13,$T13,W13,Z13,AC13,AF13,AL13,AO13,AR13,AU13,AX13,AI13) -> 757 | BB13: =IF(BA13=0,0,_xlfn.XLOOKUP($BA13,$Q13:$AZ13,$Q$1:$AZ$1,0,0)) -> 1 | BC13: =_xlfn.XLOOKUP($BB13,$Q$1:$AZ$1,$Q13:$AZ13,0,0) -> 757 | BD13: =IF(BA13=0,0,$BD$3) -> 0.4 | BE13: =BC13/(100%-BD13) -> 1261.6667 | BF13: =_xlfn.XLOOKUP(A13,[1]Юнит!$A:$A,[1]Юнит!$AU:$AU,0) -> 0.18062269 | BG13: =P13 -> 0.18082062 | BH13: * | BI13: =MROUND(IF($BH13="*",$BE13,K13),1) -> 1262 | BJ13: =IF($BH13="*",$BD13,J13) -> 0.4 | BK13: =MROUND(BI13-BI13*BJ13,1) -> 757 | BL13: =IF(BH13="*",1,0) -> 1 | BM13: =_xlfn.XLOOKUP(A13,'Текущая цена на ВБ'!C:C,'Текущая цена на ВБ'!F:F) -> 258 | BN13: =_xlfn.XLOOKUP(A13,'Текущая цена на ВБ'!C:C,'Текущая цена на ВБ'!H:H) -> 334
A14: =[1]Юнит!A13 -> 176723275 | B14: =[1]Юнит!C13 -> AHMA3BW202WH | C14: =[1]Юнит!D13 -> Мешки/шнурок крупн 3 шт. | D14: =[1]Юнит!E13 -> 2038606256161 | E14: 839 | F14: 0.4 | G14: 1398 | H14: 0.22155069 | I14: =_xlfn.XLOOKUP(D14,[1]Юнит!$E:$E,[1]Юнит!$AN:$AN) -> 839 | J14: =$J$4 -> 0.3 | K14: =I14/(100%-J12) -> 1198.5714 | L14: =_xlfn.XLOOKUP(D14,[1]Юнит!$E:$E,[1]Юнит!$AR:$AR) -> 0.2214957 | M14: =MROUND(O14-O14*N14,1) -> 839 | N14: =_xlfn.XLOOKUP($A14,'Текущая цена на ВБ'!$C:$C,'Текущая цена на ВБ'!$K:$K,0,0)% -> 0.4 | O14: =_xlfn.XLOOKUP($A14,'Текущая цена на ВБ'!$C:$C,'Текущая цена на ВБ'!$I:$I,0) -> 1398 | P14: =_xlfn.XLOOKUP($A14,[1]Юнит!$A:$A,[1]Юнит!$AJ:$AJ,0) -> 0.22132677 | Q14: =_xlfn.XLOOKUP($A14,'Акция 1'!$F:$F,'Акция 1'!$L:$L,0,0) -> 0 | R14: =(_xlfn.XLOOKUP($A14,'Акция 1'!$F:$F,'Акция 1'!$P:$P,0,0))% -> 0 | S14: =Q14/(100%-R14) -> 0 | T14: =_xlfn.XLOOKUP($A14,'Акция 2'!$F:$F,'Акция 2'!$L:$L,0,0) -> 839 | U14: =(_xlfn.XLOOKUP($A14,'Акция 2'!$F:$F,'Акция 2'!$O:$O,0,0))% -> 0.3 | V14: =T14/(100%-U14) -> 1198.5714 | W14: =_xlfn.XLOOKUP($A14,'Акция 3'!$F:$F,'Акция 3'!$L:$L,0,0) -> 752 | X14: =(_xlfn.XLOOKUP($A14,'Акция 3'!$F:$F,'Акция 3'!$P:$P,0,0))% -> 0.38 | Y14: =W14/(100%-X14) -> 1212.9032 | Z14: =_xlfn.XLOOKUP($A14,'Акция 4'!$F:$F,'Акция 4'!$L:$L,0,0) -> 0 | AA14: =(_xlfn.XLOOKUP($A14,'Акция 4'!$F:$F,'Акция 4'!$P:$P,0,0))% -> 0 | AB14: =Z14/(100%-AA14) -> 0 | AC14: =_xlfn.XLOOKUP($A14,'Акция 5'!$F:$F,'Акция 5'!$L:$L,0,0) -> 0 | AD14: =(_xlfn.XLOOKUP($A14,'Акция 5'!$F:$F,'Акция 5'!O:O,0,0))% -> 0 | AE14: =AC14/(100%-AD14) -> 0 | AF14: =_xlfn.XLOOKUP($A14,'Акция 6'!$F:$F,'Акция 6'!$L:$L,0,0) -> 0 | AG14: =(_xlfn.XLOOKUP($A14,'Акция 6'!$F:$F,'Акция 6'!$O:$O,0,0))% -> 0 | AH14: =AF14/(100%-AG14) -> 0 | AI14: =_xlfn.XLOOKUP($A14,'Акция 7'!$F:$F,'Акция 7'!$L:$L,0,0) -> 0 | AJ14: =(_xlfn.XLOOKUP($A14,'Акция 7'!$F:$F,'Акция 7'!$O:$O,0,0))% -> 0 | AK14: =AI14/(100%-AJ14) -> 0 | AL14: =_xlfn.XLOOKUP($A14,'Акция 8'!$F:$F,'Акция 8'!$L:$L,0,0) -> 0 | AM14: =(_xlfn.XLOOKUP($A14,'Акция 8'!$F:$F,'Акция 8'!$S:$S,0,0))% -> 0 | AN14: =AL14/(100%-AM14) -> 0 | AO14: =_xlfn.XLOOKUP($A14,'Акция 9'!$F:$F,'Акция 9'!$L:$L,0,0) -> 0 | AP14: =(_xlfn.XLOOKUP($A14,'Акция 9'!$F:$F,'Акция 9'!$O:$O,0,0))% -> 0 | AQ14: =AO14/(100%-AP14) -> 0 | AR14: =_xlfn.XLOOKUP($A14,'Акция 10'!$F:$F,'Акция 10'!$L:$L,0,0) -> 0 | AS14: =(_xlfn.XLOOKUP($A14,'Акция 10'!$F:$F,'Акция 10'!$O:$O,0,0))% -> 0 | AT14: =AR14/(100%-AS14) -> 0 | AU14: =_xlfn.XLOOKUP($A14,'Акция 11'!$F:$F,'Акция 11'!$L:$L,0,0) -> 0 | AV14: =(_xlfn.XLOOKUP($A14,'Акция 11'!$F:$F,'Акция 11'!$O:$O,0,0))% -> 0 | AW14: =AU14/(100%-AV14) -> 0 | BA14: =MAX($Q14,$T14,W14,Z14,AC14,AF14,AL14,AO14,AR14,AU14,AX14,AI14) -> 839 | BB14: =IF(BA14=0,0,_xlfn.XLOOKUP($BA14,$Q14:$AZ14,$Q$1:$AZ$1,0,0)) -> 2 | BC14: =_xlfn.XLOOKUP($BB14,$Q$1:$AZ$1,$Q14:$AZ14,0,0) -> 839 | BD14: =IF(BA14=0,0,$BD$3) -> 0.4 | BE14: =BC14/(100%-BD14) -> 1398.3333 | BF14: =_xlfn.XLOOKUP(A14,[1]Юнит!$A:$A,[1]Юнит!$AU:$AU,0) -> 0.2214957 | BG14: =P14 -> 0.22132677 | BI14: =MROUND(IF($BH14="*",$BE14,K14),1) -> 1199 | BJ14: =IF($BH14="*",$BD14,J14) -> 0.3 | BK14: =MROUND(BI14-BI14*BJ14,1) -> 839 | BL14: =IF(BH14="*",1,0) -> 0 | BM14: =_xlfn.XLOOKUP(A14,'Текущая цена на ВБ'!C:C,'Текущая цена на ВБ'!F:F) -> 92 | BN14: =_xlfn.XLOOKUP(A14,'Текущая цена на ВБ'!C:C,'Текущая цена на ВБ'!H:H) -> 87
A15: =[1]Юнит!A14 -> 204615141 | B15: =[1]Юнит!C14 -> AHMA2BW201WH | C15: =[1]Юнит!D14 -> Мешки 2 шт. серый | D15: =[1]Юнит!E14 -> 2039404446068 | E15: 598 | F15: 0.4 | G15: 997 | H15: 0.15895687 | I15: =_xlfn.XLOOKUP(D15,[1]Юнит!$E:$E,[1]Юнит!$AN:$AN) -> 659 | J15: =$J$4 -> 0.3 | K15: =I15/(100%-J13) -> 941.42857 | L15: =_xlfn.XLOOKUP(D15,[1]Юнит!$E:$E,[1]Юнит!$AR:$AR) -> 0.2336652 | M15: =MROUND(O15-O15*N15,1) -> 598 | N15: =_xlfn.XLOOKUP($A15,'Текущая цена на ВБ'!$C:$C,'Текущая цена на ВБ'!$K:$K,0,0)% -> 0.4 | O15: =_xlfn.XLOOKUP($A15,'Текущая цена на ВБ'!$C:$C,'Текущая цена на ВБ'!$I:$I,0) -> 997 | P15: =_xlfn.XLOOKUP($A15,[1]Юнит!$A:$A,[1]Юнит!$AJ:$AJ,0) -> 0.16289095 | Q15: =_xlfn.XLOOKUP($A15,'Акция 1'!$F:$F,'Акция 1'!$L:$L,0,0) -> 598 | R15: =(_xlfn.XLOOKUP($A15,'Акция 1'!$F:$F,'Акция 1'!$P:$P,0,0))% -> 0.37 | S15: =Q15/(100%-R15) -> 949.20635 | T15: =_xlfn.XLOOKUP($A15,'Акция 2'!$F:$F,'Акция 2'!$L:$L,0,0) -> 0 | U15: =(_xlfn.XLOOKUP($A15,'Акция 2'!$F:$F,'Акция 2'!$O:$O,0,0))% -> 0 | V15: =T15/(100%-U15) -> 0 | W15: =_xlfn.XLOOKUP($A15,'Акция 3'!$F:$F,'Акция 3'!$L:$L,0,0) -> 446 | X15: =(_xlfn.XLOOKUP($A15,'Акция 3'!$F:$F,'Акция 3'!$P:$P,0,0))% -> 0.53 | Y15: =W15/(100%-X15) -> 948.93617 | Z15: =_xlfn.XLOOKUP($A15,'Акция 4'!$F:$F,'Акция 4'!$L:$L,0,0) -> 0 | AA15: =(_xlfn.XLOOKUP($A15,'Акция 4'!$F:$F,'Акция 4'!$P:$P,0,0))% -> 0 | AB15: =Z15/(100%-AA15) -> 0 | AC15: =_xlfn.XLOOKUP($A15,'Акция 5'!$F:$F,'Акция 5'!$L:$L,0,0) -> 0 | AD15: =(_xlfn.XLOOKUP($A15,'Акция 5'!$F:$F,'Акция 5'!O:O,0,0))% -> 0 | AE15: =AC15/(100%-AD15) -> 0 | AF15: =_xlfn.XLOOKUP($A15,'Акция 6'!$F:$F,'Акция 6'!$L:$L,0,0) -> 0 | AG15: =(_xlfn.XLOOKUP($A15,'Акция 6'!$F:$F,'Акция 6'!$O:$O,0,0))% -> 0 | AH15: =AF15/(100%-AG15) -> 0 | AI15: =_xlfn.XLOOKUP($A15,'Акция 7'!$F:$F,'Акция 7'!$L:$L,0,0) -> 0 | AJ15: =(_xlfn.XLOOKUP($A15,'Акция 7'!$F:$F,'Акция 7'!$O:$O,0,0))% -> 0 | AK15: =AI15/(100%-AJ15) -> 0 | AL15: =_xlfn.XLOOKUP($A15,'Акция 8'!$F:$F,'Акция 8'!$L:$L,0,0) -> 0 | AM15: =(_xlfn.XLOOKUP($A15,'Акция 8'!$F:$F,'Акция 8'!$S:$S,0,0))% -> 0 | AN15: =AL15/(100%-AM15) -> 0 | AO15: =_xlfn.XLOOKUP($A15,'Акция 9'!$F:$F,'Акция 9'!$L:$L,0,0) -> 0 | AP15: =(_xlfn.XLOOKUP($A15,'Акция 9'!$F:$F,'Акция 9'!$O:$O,0,0))% -> 0 | AQ15: =AO15/(100%-AP15) -> 0 | AR15: =_xlfn.XLOOKUP($A15,'Акция 10'!$F:$F,'Акция 10'!$L:$L,0,0) -> 0 | AS15: =(_xlfn.XLOOKUP($A15,'Акция 10'!$F:$F,'Акция 10'!$O:$O,0,0))% -> 0 | AT15: =AR15/(100%-AS15) -> 0 | AU15: =_xlfn.XLOOKUP($A15,'Акция 11'!$F:$F,'Акция 11'!$L:$L,0,0) -> 0 | AV15: =(_xlfn.XLOOKUP($A15,'Акция 11'!$F:$F,'Акция 11'!$O:$O,0,0))% -> 0 | AW15: =AU15/(100%-AV15) -> 0 | BA15: =MAX($Q15,$T15,W15,Z15,AC15,AF15,AL15,AO15,AR15,AU15,AX15,AI15) -> 598 | BB15: =IF(BA15=0,0,_xlfn.XLOOKUP($BA15,$Q15:$AZ15,$Q$1:$AZ$1,0,0)) -> 1 | BC15: =_xlfn.XLOOKUP($BB15,$Q$1:$AZ$1,$Q15:$AZ15,0,0) -> 598 | BD15: =IF(BA15=0,0,$BD$3) -> 0.4 | BE15: =BC15/(100%-BD15) -> 996.66667 | BF15: =_xlfn.XLOOKUP(A15,[1]Юнит!$A:$A,[1]Юнит!$AU:$AU,0) -> 0.16263439 | BG15: =P15 -> 0.16289095 | BH15: * | BI15: =MROUND(IF($BH15="*",$BE15,K15),1) -> 997 | BJ15: =IF($BH15="*",$BD15,J15) -> 0.4 | BK15: =MROUND(BI15-BI15*BJ15,1) -> 598 | BL15: =IF(BH15="*",1,0) -> 1 | BM15: =_xlfn.XLOOKUP(A15,'Текущая цена на ВБ'!C:C,'Текущая цена на ВБ'!F:F) -> 222 | BN15: =_xlfn.XLOOKUP(A15,'Текущая цена на ВБ'!C:C,'Текущая цена на ВБ'!H:H) -> 602
A16: =[1]Юнит!A15 -> 236074677 | B16: =[1]Юнит!C15 -> AHMA2BW202WH | C16: =[1]Юнит!D15 -> Мешки 2 шт. розовый | D16: =[1]Юнит!E15 -> 2040278862540 | E16: 750 | F16: 0.4 | G16: 1250 | H16: 0.17359446 | I16: =_xlfn.XLOOKUP(D16,[1]Юнит!$E:$E,[1]Юнит!$AN:$AN) -> 759 | J16: =$J$4 -> 0.3 | K16: =I16/(100%-J14) -> 1084.2857 | L16: =_xlfn.XLOOKUP(D16,[1]Юнит!$E:$E,[1]Юнит!$AR:$AR) -> 0.18370224 | M16: =MROUND(O16-O16*N16,1) -> 750 | N16: =_xlfn.XLOOKUP($A16,'Текущая цена на ВБ'!$C:$C,'Текущая цена на ВБ'!$K:$K,0,0)% -> 0.4 | O16: =_xlfn.XLOOKUP($A16,'Текущая цена на ВБ'!$C:$C,'Текущая цена на ВБ'!$I:$I,0) -> 1250 | P16: =_xlfn.XLOOKUP($A16,[1]Юнит!$A:$A,[1]Юнит!$AJ:$AJ,0) -> 0.17474667 | Q16: =_xlfn.XLOOKUP($A16,'Акция 1'!$F:$F,'Акция 1'!$L:$L,0,0) -> 750 | R16: =(_xlfn.XLOOKUP($A16,'Акция 1'!$F:$F,'Акция 1'!$P:$P,0,0))% -> 0.31 | S16: =Q16/(100%-R16) -> 1086.9565 | T16: =_xlfn.XLOOKUP($A16,'Акция 2'!$F:$F,'Акция 2'!$L:$L,0,0) -> 0 | U16: =(_xlfn.XLOOKUP($A16,'Акция 2'!$F:$F,'Акция 2'!$O:$O,0,0))% -> 0 | V16: =T16/(100%-U16) -> 0 | W16: =_xlfn.XLOOKUP($A16,'Акция 3'!$F:$F,'Акция 3'!$L:$L,0,0) -> 582 | X16: =(_xlfn.XLOOKUP($A16,'Акция 3'!$F:$F,'Акция 3'!$P:$P,0,0))% -> 0.47 | Y16: =W16/(100%-X16) -> 1098.1132 | Z16: =_xlfn.XLOOKUP($A16,'Акция 4'!$F:$F,'Акция 4'!$L:$L,0,0) -> 0 | AA16: =(_xlfn.XLOOKUP($A16,'Акция 4'!$F:$F,'Акция 4'!$P:$P,0,0))% -> 0 | AB16: =Z16/(100%-AA16) -> 0 | AC16: =_xlfn.XLOOKUP($A16,'Акция 5'!$F:$F,'Акция 5'!$L:$L,0,0) -> 0 | AD16: =(_xlfn.XLOOKUP($A16,'Акция 5'!$F:$F,'Акция 5'!O:O,0,0))% -> 0 | AE16: =AC16/(100%-AD16) -> 0 | AF16: =_xlfn.XLOOKUP($A16,'Акция 6'!$F:$F,'Акция 6'!$L:$L,0,0) -> 0 | AG16: =(_xlfn.XLOOKUP($A16,'Акция 6'!$F:$F,'Акция 6'!$O:$O,0,0))% -> 0 | AH16: =AF16/(100%-AG16) -> 0 | AI16: =_xlfn.XLOOKUP($A16,'Акция 7'!$F:$F,'Акция 7'!$L:$L,0,0) -> 0 | AJ16: =(_xlfn.XLOOKUP($A16,'Акция 7'!$F:$F,'Акция 7'!$O:$O,0,0))% -> 0 | AK16: =AI16/(100%-AJ16) -> 0 | AL16: =_xlfn.XLOOKUP($A16,'Акция 8'!$F:$F,'Акция 8'!$L:$L,0,0) -> 0 | AM16: =(_xlfn.XLOOKUP($A16,'Акция 8'!$F:$F,'Акция 8'!$S:$S,0,0))% -> 0 | AN16: =AL16/(100%-AM16) -> 0 | AO16: =_xlfn.XLOOKUP($A16,'Акция 9'!$F:$F,'Акция 9'!$L:$L,0,0) -> 0 | AP16: =(_xlfn.XLOOKUP($A16,'Акция 9'!$F:$F,'Акция 9'!$O:$O,0,0))% -> 0 | AQ16: =AO16/(100%-AP16) -> 0 | AR16: =_xlfn.XLOOKUP($A16,'Акция 10'!$F:$F,'Акция 10'!$L:$L,0,0) -> 0 | AS16: =(_xlfn.XLOOKUP($A16,'Акция 10'!$F:$F,'Акция 10'!$O:$O,0,0))% -> 0 | AT16: =AR16/(100%-AS16) -> 0 | AU16: =_xlfn.XLOOKUP($A16,'Акция 11'!$F:$F,'Акция 11'!$L:$L,0,0) -> 0 | AV16: =(_xlfn.XLOOKUP($A16,'Акция 11'!$F:$F,'Акция 11'!$O:$O,0,0))% -> 0 | AW16: =AU16/(100%-AV16) -> 0 | BA16: =MAX($Q16,$T16,W16,Z16,AC16,AF16,AL16,AO16,AR16,AU16,AX16,AI16) -> 750 | BB16: =IF(BA16=0,0,_xlfn.XLOOKUP($BA16,$Q16:$AZ16,$Q$1:$AZ$1,0,0)) -> 1 | BC16: =_xlfn.XLOOKUP($BB16,$Q$1:$AZ$1,$Q16:$AZ16,0,0) -> 750 | BD16: =IF(BA16=0,0,$BD$3) -> 0.4 | BE16: =BC16/(100%-BD16) -> 1250 | BF16: =_xlfn.XLOOKUP(A16,[1]Юнит!$A:$A,[1]Юнит!$AU:$AU,0) -> 0.17474667 | BG16: =P16 -> 0.17474667 | BH16: * | BI16: =MROUND(IF($BH16="*",$BE16,K16),1) -> 1250 | BJ16: =IF($BH16="*",$BD16,J16) -> 0.4 | BK16: =MROUND(BI16-BI16*BJ16,1) -> 750 | BL16: =IF(BH16="*",1,0) -> 1 | BM16: =_xlfn.XLOOKUP(A16,'Текущая цена на ВБ'!C:C,'Текущая цена на ВБ'!F:F) -> 18 | BN16: =_xlfn.XLOOKUP(A16,'Текущая цена на ВБ'!C:C,'Текущая цена на ВБ'!H:H) -> 152
A17: =[1]Юнит!A16 -> 236929187 | B17: =[1]Юнит!C16 -> AHMA1BW112WH | C17: =[1]Юнит!D16 -> Мешок 60*80 крупн | D17: =[1]Юнит!E16 -> 2040335626849 | E17: 669 | F17: 0.4 | G17: 1115 | H17: 0.23978648 | I17: =_xlfn.XLOOKUP(D17,[1]Юнит!$E:$E,[1]Юнит!$AN:$AN) -> 669 | J17: =$J$4 -> 0.3 | K17: =I17/(100%-J15) -> 955.71429 | L17: =_xlfn.XLOOKUP(D17,[1]Юнит!$E:$E,[1]Юнит!$AR:$AR) -> 0.23967963 | M17: =MROUND(O17-O17*N17,1) -> 669 | N17: =_xlfn.XLOOKUP($A17,'Текущая цена на ВБ'!$C:$C,'Текущая цена на ВБ'!$K:$K,0,0)% -> 0.4 | O17: =_xlfn.XLOOKUP($A17,'Текущая цена на ВБ'!$C:$C,'Текущая цена на ВБ'!$I:$I,0) -> 1115 | P17: =_xlfn.XLOOKUP($A17,[1]Юнит!$A:$A,[1]Юнит!$AJ:$AJ,0) -> 0.23967963 | Q17: =_xlfn.XLOOKUP($A17,'Акция 1'!$F:$F,'Акция 1'!$L:$L,0,0) -> 0 | R17: =(_xlfn.XLOOKUP($A17,'Акция 1'!$F:$F,'Акция 1'!$P:$P,0,0))% -> 0 | S17: =Q17/(100%-R17) -> 0 | T17: =_xlfn.XLOOKUP($A17,'Акция 2'!$F:$F,'Акция 2'!$L:$L,0,0) -> 669 | U17: =(_xlfn.XLOOKUP($A17,'Акция 2'!$F:$F,'Акция 2'!$O:$O,0,0))% -> 0.3 | V17: =T17/(100%-U17) -> 955.71429 | W17: =_xlfn.XLOOKUP($A17,'Акция 3'!$F:$F,'Акция 3'!$L:$L,0,0) -> 595 | X17: =(_xlfn.XLOOKUP($A17,'Акция 3'!$F:$F,'Акция 3'!$P:$P,0,0))% -> 0.38 | Y17: =W17/(100%-X17) -> 959.67742 | Z17: =_xlfn.XLOOKUP($A17,'Акция 4'!$F:$F,'Акция 4'!$L:$L,0,0) -> 0 | AA17: =(_xlfn.XLOOKUP($A17,'Акция 4'!$F:$F,'Акция 4'!$P:$P,0,0))% -> 0 | AB17: =Z17/(100%-AA17) -> 0 | AC17: =_xlfn.XLOOKUP($A17,'Акция 5'!$F:$F,'Акция 5'!$L:$L,0,0) -> 0 | AD17: =(_xlfn.XLOOKUP($A17,'Акция 5'!$F:$F,'Акция 5'!O:O,0,0))% -> 0 | AE17: =AC17/(100%-AD17) -> 0 | AF17: =_xlfn.XLOOKUP($A17,'Акция 6'!$F:$F,'Акция 6'!$L:$L,0,0) -> 0 | AG17: =(_xlfn.XLOOKUP($A17,'Акция 6'!$F:$F,'Акция 6'!$O:$O,0,0))% -> 0 | AH17: =AF17/(100%-AG17) -> 0 | AI17: =_xlfn.XLOOKUP($A17,'Акция 7'!$F:$F,'Акция 7'!$L:$L,0,0) -> 0 | AJ17: =(_xlfn.XLOOKUP($A17,'Акция 7'!$F:$F,'Акция 7'!$O:$O,0,0))% -> 0 | AK17: =AI17/(100%-AJ17) -> 0 | AL17: =_xlfn.XLOOKUP($A17,'Акция 8'!$F:$F,'Акция 8'!$L:$L,0,0) -> 0 | AM17: =(_xlfn.XLOOKUP($A17,'Акция 8'!$F:$F,'Акция 8'!$S:$S,0,0))% -> 0 | AN17: =AL17/(100%-AM17) -> 0 | AO17: =_xlfn.XLOOKUP($A17,'Акция 9'!$F:$F,'Акция 9'!$L:$L,0,0) -> 0 | AP17: =(_xlfn.XLOOKUP($A17,'Акция 9'!$F:$F,'Акция 9'!$O:$O,0,0))% -> 0 | AQ17: =AO17/(100%-AP17) -> 0 | AR17: =_xlfn.XLOOKUP($A17,'Акция 10'!$F:$F,'Акция 10'!$L:$L,0,0) -> 0 | AS17: =(_xlfn.XLOOKUP($A17,'Акция 10'!$F:$F,'Акция 10'!$O:$O,0,0))% -> 0 | AT17: =AR17/(100%-AS17) -> 0 | AU17: =_xlfn.XLOOKUP($A17,'Акция 11'!$F:$F,'Акция 11'!$L:$L,0,0) -> 0 | AV17: =(_xlfn.XLOOKUP($A17,'Акция 11'!$F:$F,'Акция 11'!$O:$O,0,0))% -> 0 | AW17: =AU17/(100%-AV17) -> 0 | BA17: =MAX($Q17,$T17,W17,Z17,AC17,AF17,AL17,AO17,AR17,AU17,AX17,AI17) -> 669 | BB17: =IF(BA17=0,0,_xlfn.XLOOKUP($BA17,$Q17:$AZ17,$Q$1:$AZ$1,0,0)) -> 2 | BC17: =_xlfn.XLOOKUP($BB17,$Q$1:$AZ$1,$Q17:$AZ17,0,0) -> 669 | BD17: =IF(BA17=0,0,$BD$3) -> 0.4 | BE17: =BC17/(100%-BD17) -> 1115 | BF17: =_xlfn.XLOOKUP(A17,[1]Юнит!$A:$A,[1]Юнит!$AU:$AU,0) -> 0.23967963 | BG17: =P17 -> 0.23967963 | BI17: =MROUND(IF($BH17="*",$BE17,K17),1) -> 956 | BJ17: =IF($BH17="*",$BD17,J17) -> 0.3 | BK17: =MROUND(BI17-BI17*BJ17,1) -> 669 | BL17: =IF(BH17="*",1,0) -> 0 | BM17: =_xlfn.XLOOKUP(A17,'Текущая цена на ВБ'!C:C,'Текущая цена на ВБ'!F:F) -> 94 | BN17: =_xlfn.XLOOKUP(A17,'Текущая цена на ВБ'!C:C,'Текущая цена на ВБ'!H:H) -> 72
A18: =[1]Юнит!A17 -> 236929188 | B18: =[1]Юнит!C17 -> AHMA1BW111WH | C18: =[1]Юнит!D17 -> Мешок 60*80 мелк | D18: =[1]Юнит!E17 -> 2040335648124 | E18: 669 | F18: 0.3 | G18: 956 | H18: 0.23978648 | I18: =_xlfn.XLOOKUP(D18,[1]Юнит!$E:$E,[1]Юнит!$AN:$AN) -> 669 | J18: =$J$4 -> 0.3 | K18: =I18/(100%-J16) -> 955.71429 | L18: =_xlfn.XLOOKUP(D18,[1]Юнит!$E:$E,[1]Юнит!$AR:$AR) -> 0.23958014 | M18: =MROUND(O18-O18*N18,1) -> 669 | N18: =_xlfn.XLOOKUP($A18,'Текущая цена на ВБ'!$C:$C,'Текущая цена на ВБ'!$K:$K,0,0)% -> 0.3 | O18: =_xlfn.XLOOKUP($A18,'Текущая цена на ВБ'!$C:$C,'Текущая цена на ВБ'!$I:$I,0) -> 956 | P18: =_xlfn.XLOOKUP($A18,[1]Юнит!$A:$A,[1]Юнит!$AJ:$AJ,0) -> 0.23978648 | Q18: =_xlfn.XLOOKUP($A18,'Акция 1'!$F:$F,'Акция 1'!$L:$L,0,0) -> 0 | R18: =(_xlfn.XLOOKUP($A18,'Акция 1'!$F:$F,'Акция 1'!$P:$P,0,0))% -> 0 | S18: =Q18/(100%-R18) -> 0 | T18: =_xlfn.XLOOKUP($A18,'Акция 2'!$F:$F,'Акция 2'!$L:$L,0,0) -> 0 | U18: =(_xlfn.XLOOKUP($A18,'Акция 2'!$F:$F,'Акция 2'!$O:$O,0,0))% -> 0 | V18: =T18/(100%-U18) -> 0 | W18: =_xlfn.XLOOKUP($A18,'Акция 3'!$F:$F,'Акция 3'!$L:$L,0,0) -> 0 | X18: =(_xlfn.XLOOKUP($A18,'Акция 3'!$F:$F,'Акция 3'!$P:$P,0,0))% -> 0 | Y18: =W18/(100%-X18) -> 0 | Z18: =_xlfn.XLOOKUP($A18,'Акция 4'!$F:$F,'Акция 4'!$L:$L,0,0) -> 0 | AA18: =(_xlfn.XLOOKUP($A18,'Акция 4'!$F:$F,'Акция 4'!$P:$P,0,0))% -> 0 | AB18: =Z18/(100%-AA18) -> 0 | AC18: =_xlfn.XLOOKUP($A18,'Акция 5'!$F:$F,'Акция 5'!$L:$L,0,0) -> 0 | AD18: =(_xlfn.XLOOKUP($A18,'Акция 5'!$F:$F,'Акция 5'!O:O,0,0))% -> 0 | AE18: =AC18/(100%-AD18) -> 0 | AF18: =_xlfn.XLOOKUP($A18,'Акция 6'!$F:$F,'Акция 6'!$L:$L,0,0) -> 0 | AG18: =(_xlfn.XLOOKUP($A18,'Акция 6'!$F:$F,'Акция 6'!$O:$O,0,0))% -> 0 | AH18: =AF18/(100%-AG18) -> 0 | AI18: =_xlfn.XLOOKUP($A18,'Акция 7'!$F:$F,'Акция 7'!$L:$L,0,0) -> 0 | AJ18: =(_xlfn.XLOOKUP($A18,'Акция 7'!$F:$F,'Акция 7'!$O:$O,0,0))% -> 0 | AK18: =AI18/(100%-AJ18) -> 0 | AL18: =_xlfn.XLOOKUP($A18,'Акция 8'!$F:$F,'Акция 8'!$L:$L,0,0) -> 0 | AM18: =(_xlfn.XLOOKUP($A18,'Акция 8'!$F:$F,'Акция 8'!$S:$S,0,0))% -> 0 | AN18: =AL18/(100%-AM18) -> 0 | AO18: =_xlfn.XLOOKUP($A18,'Акция 9'!$F:$F,'Акция 9'!$L:$L,0,0) -> 0 | AP18: =(_xlfn.XLOOKUP($A18,'Акция 9'!$F:$F,'Акция 9'!$O:$O,0,0))% -> 0 | AQ18: =AO18/(100%-AP18) -> 0 | AR18: =_xlfn.XLOOKUP($A18,'Акция 10'!$F:$F,'Акция 10'!$L:$L,0,0) -> 0 | AS18: =(_xlfn.XLOOKUP($A18,'Акция 10'!$F:$F,'Акция 10'!$O:$O,0,0))% -> 0 | AT18: =AR18/(100%-AS18) -> 0 | AU18: =_xlfn.XLOOKUP($A18,'Акция 11'!$F:$F,'Акция 11'!$L:$L,0,0) -> 0 | AV18: =(_xlfn.XLOOKUP($A18,'Акция 11'!$F:$F,'Акция 11'!$O:$O,0,0))% -> 0 | AW18: =AU18/(100%-AV18) -> 0 | BA18: =MAX($Q18,$T18,W18,Z18,AC18,AF18,AL18,AO18,AR18,AU18,AX18,AI18) -> 0 | BB18: =IF(BA18=0,0,_xlfn.XLOOKUP($BA18,$Q18:$AZ18,$Q$1:$AZ$1,0,0)) -> 0 | BC18: =_xlfn.XLOOKUP($BB18,$Q$1:$AZ$1,$Q18:$AZ18,0,0) -> 0 | BD18: =IF(BA18=0,0,$BD$3) -> 0 | BE18: =BC18/(100%-BD18) -> 0 | BF18: =_xlfn.XLOOKUP(A18,[1]Юнит!$A:$A,[1]Юнит!$AU:$AU,0) -> 0 | BG18: =P18 -> 0.23978648 | BH18: * | BI18: =MROUND(IF($BH18="*",$BE18,K18),1) -> 0 | BJ18: =IF($BH18="*",$BD18,J18) -> 0 | BK18: =MROUND(BI18-BI18*BJ18,1) -> 0 | BL18: =IF(BH18="*",1,0) -> 1 | BM18: =_xlfn.XLOOKUP(A18,'Текущая цена на ВБ'!C:C,'Текущая цена на ВБ'!F:F) -> 130 | BN18: =_xlfn.XLOOKUP(A18,'Текущая цена на ВБ'!C:C,'Текущая цена на ВБ'!H:H) -> 999
A19: =[1]Юнит!A18 -> 239235150 | B19: =[1]Юнит!C18 -> AHMA1BW301WH | C19: =[1]Юнит!D18 -> Мешок для обуви L - 30 см | D19: =[1]Юнит!E18 -> 2040478720961 | E19: 494 | F19: 0.4 | G19: 823 | H19: 0.095462089 | I19: =_xlfn.XLOOKUP(D19,[1]Юнит!$E:$E,[1]Юнит!$AN:$AN) -> 499 | J19: =$J$4 -> 0.3 | K19: =I19/(100%-J17) -> 712.85714 | L19: =_xlfn.XLOOKUP(D19,[1]Юнит!$E:$E,[1]Юнит!$AR:$AR) -> 0.10599872 | M19: =MROUND(O19-O19*N19,1) -> 494 | N19: =_xlfn.XLOOKUP($A19,'Текущая цена на ВБ'!$C:$C,'Текущая цена на ВБ'!$K:$K,0,0)% -> 0.4 | O19: =_xlfn.XLOOKUP($A19,'Текущая цена на ВБ'!$C:$C,'Текущая цена на ВБ'!$I:$I,0) -> 823 | P19: =_xlfn.XLOOKUP($A19,[1]Юнит!$A:$A,[1]Юнит!$AJ:$AJ,0) -> 0.097321507 | Q19: =_xlfn.XLOOKUP($A19,'Акция 1'!$F:$F,'Акция 1'!$L:$L,0,0) -> 494 | R19: =(_xlfn.XLOOKUP($A19,'Акция 1'!$F:$F,'Акция 1'!$P:$P,0,0))% -> 0.31 | S19: =Q19/(100%-R19) -> 715.94203 | T19: =_xlfn.XLOOKUP($A19,'Акция 2'!$F:$F,'Акция 2'!$L:$L,0,0) -> 0 | U19: =(_xlfn.XLOOKUP($A19,'Акция 2'!$F:$F,'Акция 2'!$O:$O,0,0))% -> 0 | V19: =T19/(100%-U19) -> 0 | W19: =_xlfn.XLOOKUP($A19,'Акция 3'!$F:$F,'Акция 3'!$L:$L,0,0) -> 346 | X19: =(_xlfn.XLOOKUP($A19,'Акция 3'!$F:$F,'Акция 3'!$P:$P,0,0))% -> 0.52 | Y19: =W19/(100%-X19) -> 720.83333 | Z19: =_xlfn.XLOOKUP($A19,'Акция 4'!$F:$F,'Акция 4'!$L:$L,0,0) -> 0 | AA19: =(_xlfn.XLOOKUP($A19,'Акция 4'!$F:$F,'Акция 4'!$P:$P,0,0))% -> 0 | AB19: =Z19/(100%-AA19) -> 0 | AC19: =_xlfn.XLOOKUP($A19,'Акция 5'!$F:$F,'Акция 5'!$L:$L,0,0) -> 0 | AD19: =(_xlfn.XLOOKUP($A19,'Акция 5'!$F:$F,'Акция 5'!O:O,0,0))% -> 0 | AE19: =AC19/(100%-AD19) -> 0 | AF19: =_xlfn.XLOOKUP($A19,'Акция 6'!$F:$F,'Акция 6'!$L:$L,0,0) -> 0 | AG19: =(_xlfn.XLOOKUP($A19,'Акция 6'!$F:$F,'Акция 6'!$O:$O,0,0))% -> 0 | AH19: =AF19/(100%-AG19) -> 0 | AI19: =_xlfn.XLOOKUP($A19,'Акция 7'!$F:$F,'Акция 7'!$L:$L,0,0) -> 0 | AJ19: =(_xlfn.XLOOKUP($A19,'Акция 7'!$F:$F,'Акция 7'!$O:$O,0,0))% -> 0 | AK19: =AI19/(100%-AJ19) -> 0 | AL19: =_xlfn.XLOOKUP($A19,'Акция 8'!$F:$F,'Акция 8'!$L:$L,0,0) -> 0 | AM19: =(_xlfn.XLOOKUP($A19,'Акция 8'!$F:$F,'Акция 8'!$S:$S,0,0))% -> 0 | AN19: =AL19/(100%-AM19) -> 0 | AO19: =_xlfn.XLOOKUP($A19,'Акция 9'!$F:$F,'Акция 9'!$L:$L,0,0) -> 0 | AP19: =(_xlfn.XLOOKUP($A19,'Акция 9'!$F:$F,'Акция 9'!$O:$O,0,0))% -> 0 | AQ19: =AO19/(100%-AP19) -> 0 | AR19: =_xlfn.XLOOKUP($A19,'Акция 10'!$F:$F,'Акция 10'!$L:$L,0,0) -> 0 | AS19: =(_xlfn.XLOOKUP($A19,'Акция 10'!$F:$F,'Акция 10'!$O:$O,0,0))% -> 0 | AT19: =AR19/(100%-AS19) -> 0 | AU19: =_xlfn.XLOOKUP($A19,'Акция 11'!$F:$F,'Акция 11'!$L:$L,0,0) -> 0 | AV19: =(_xlfn.XLOOKUP($A19,'Акция 11'!$F:$F,'Акция 11'!$O:$O,0,0))% -> 0 | AW19: =AU19/(100%-AV19) -> 0 | BA19: =MAX($Q19,$T19,W19,Z19,AC19,AF19,AL19,AO19,AR19,AU19,AX19,AI19) -> 494 | BB19: =IF(BA19=0,0,_xlfn.XLOOKUP($BA19,$Q19:$AZ19,$Q$1:$AZ$1,0,0)) -> 1 | BC19: =_xlfn.XLOOKUP($BB19,$Q$1:$AZ$1,$Q19:$AZ19,0,0) -> 494 | BD19: =IF(BA19=0,0,$BD$3) -> 0.4 | BE19: =BC19/(100%-BD19) -> 823.33333 | BF19: =_xlfn.XLOOKUP(A19,[1]Юнит!$A:$A,[1]Юнит!$AU:$AU,0) -> 0.097658623 | BG19: =P19 -> 0.097321507 | BI19: =MROUND(IF($BH19="*",$BE19,K19),1) -> 713 | BJ19: =IF($BH19="*",$BD19,J19) -> 0.3 | BK19: =MROUND(BI19-BI19*BJ19,1) -> 499 | BL19: =IF(BH19="*",1,0) -> 0 | BM19: =_xlfn.XLOOKUP(A19,'Текущая цена на ВБ'!C:C,'Текущая цена на ВБ'!F:F) -> 1 | BN19: =_xlfn.XLOOKUP(A19,'Текущая цена на ВБ'!C:C,'Текущая цена на ВБ'!H:H) -> 18
A20: =[1]Юнит!A19 -> 239233529 | B20: =[1]Юнит!C19 -> AHMA1BW302WH | C20: =[1]Юнит!D19 -> Мешок для обуви XL - 35 см | D20: =[1]Юнит!E19 -> 2040478696884 | E20: 702 | F20: 0.4 | G20: 1170 | H20: 0.081470627 | I20: =_xlfn.XLOOKUP(D20,[1]Юнит!$E:$E,[1]Юнит!$AN:$AN) -> 709 | J20: =$J$4 -> 0.3 | K20: =I20/(100%-J18) -> 1012.8571 | L20: =_xlfn.XLOOKUP(D20,[1]Юнит!$E:$E,[1]Юнит!$AR:$AR) -> 0.092052243 | M20: =MROUND(O20-O20*N20,1) -> 702 | N20: =_xlfn.XLOOKUP($A20,'Текущая цена на ВБ'!$C:$C,'Текущая цена на ВБ'!$K:$K,0,0)% -> 0.4 | O20: =_xlfn.XLOOKUP($A20,'Текущая цена на ВБ'!$C:$C,'Текущая цена на ВБ'!$I:$I,0,0) -> 1170 | P20: =_xlfn.XLOOKUP($A20,[1]Юнит!$A:$A,[1]Юнит!$AJ:$AJ,0) -> 0.083696638 | Q20: =_xlfn.XLOOKUP($A20,'Акция 1'!$F:$F,'Акция 1'!$L:$L,0,0) -> 702 | R20: =(_xlfn.XLOOKUP($A20,'Акция 1'!$F:$F,'Акция 1'!$P:$P,0,0))% -> 0.31 | S20: =Q20/(100%-R20) -> 1017.3913 | T20: =_xlfn.XLOOKUP($A20,'Акция 2'!$F:$F,'Акция 2'!$L:$L,0,0) -> 0 | U20: =(_xlfn.XLOOKUP($A20,'Акция 2'!$F:$F,'Акция 2'!$O:$O,0,0))% -> 0 | V20: =T20/(100%-U20) -> 0 | W20: =_xlfn.XLOOKUP($A20,'Акция 3'!$F:$F,'Акция 3'!$L:$L,0,0) -> 501 | X20: =(_xlfn.XLOOKUP($A20,'Акция 3'!$F:$F,'Акция 3'!$P:$P,0,0))% -> 0.51 | Y20: =W20/(100%-X20) -> 1022.449 | Z20: =_xlfn.XLOOKUP($A20,'Акция 4'!$F:$F,'Акция 4'!$L:$L,0,0) -> 0 | AA20: =(_xlfn.XLOOKUP($A20,'Акция 4'!$F:$F,'Акция 4'!$P:$P,0,0))% -> 0 | AB20: =Z20/(100%-AA20) -> 0 | AC20: =_xlfn.XLOOKUP($A20,'Акция 5'!$F:$F,'Акция 5'!$L:$L,0,0) -> 0 | AD20: =(_xlfn.XLOOKUP($A20,'Акция 5'!$F:$F,'Акция 5'!O:O,0,0))% -> 0 | AE20: =AC20/(100%-AD20) -> 0 | AF20: =_xlfn.XLOOKUP($A20,'Акция 6'!$F:$F,'Акция 6'!$L:$L,0,0) -> 0 | AG20: =(_xlfn.XLOOKUP($A20,'Акция 6'!$F:$F,'Акция 6'!$O:$O,0,0))% -> 0 | AH20: =AF20/(100%-AG20) -> 0 | AI20: =_xlfn.XLOOKUP($A20,'Акция 7'!$F:$F,'Акция 7'!$L:$L,0,0) -> 0 | AJ20: =(_xlfn.XLOOKUP($A20,'Акция 7'!$F:$F,'Акция 7'!$O:$O,0,0))% -> 0 | AK20: =AI20/(100%-AJ20) -> 0 | AL20: =_xlfn.XLOOKUP($A20,'Акция 8'!$F:$F,'Акция 8'!$L:$L,0,0) -> 0 | AM20: =(_xlfn.XLOOKUP($A20,'Акция 8'!$F:$F,'Акция 8'!$S:$S,0,0))% -> 0 | AN20: =AL20/(100%-AM20) -> 0 | AO20: =_xlfn.XLOOKUP($A20,'Акция 9'!$F:$F,'Акция 9'!$L:$L,0,0) -> 0 | AP20: =(_xlfn.XLOOKUP($A20,'Акция 9'!$F:$F,'Акция 9'!$O:$O,0,0))% -> 0 | AQ20: =AO20/(100%-AP20) -> 0 | AR20: =_xlfn.XLOOKUP($A20,'Акция 10'!$F:$F,'Акция 10'!$L:$L,0,0) -> 0 | AS20: =(_xlfn.XLOOKUP($A20,'Акция 10'!$F:$F,'Акция 10'!$O:$O,0,0))% -> 0 | AT20: =AR20/(100%-AS20) -> 0 | AU20: =_xlfn.XLOOKUP($A20,'Акция 11'!$F:$F,'Акция 11'!$L:$L,0,0) -> 0 | AV20: =(_xlfn.XLOOKUP($A20,'Акция 11'!$F:$F,'Акция 11'!$O:$O,0,0))% -> 0 | AW20: =AU20/(100%-AV20) -> 0 | BA20: =MAX($Q20,$T20,W20,Z20,AC20,AF20,AL20,AO20,AR20,AU20,AX20,AI20) -> 702 | BB20: =IF(BA20=0,0,_xlfn.XLOOKUP($BA20,$Q20:$AZ20,$Q$1:$AZ$1,0,0)) -> 1 | BC20: =_xlfn.XLOOKUP($BB20,$Q$1:$AZ$1,$Q20:$AZ20,0,0) -> 702 | BD20: =IF(BA20=0,0,$BD$3) -> 0.4 | BE20: =BC20/(100%-BD20) -> 1170 | BF20: =_xlfn.XLOOKUP(A20,[1]Юнит!$A:$A,[1]Юнит!$AU:$AU,0) -> 0.083696638 | BG20: =P20 -> 0.083696638 | BH20: * | BI20: =MROUND(IF($BH20="*",$BE20,K20),1) -> 1170 | BJ20: =IF($BH20="*",$BD20,J20) -> 0.4 | BK20: =MROUND(BI20-BI20*BJ20,1) -> 702 | BL20: =IF(BH20="*",1,0) -> 1 | BM20: =_xlfn.XLOOKUP(A20,'Текущая цена на ВБ'!C:C,'Текущая цена на ВБ'!F:F) -> 55 | BN20: =_xlfn.XLOOKUP(A20,'Текущая цена на ВБ'!C:C,'Текущая цена на ВБ'!H:H) -> 290
A21: =[1]Юнит!A20 -> 173605843 | B21: =[1]Юнит!C20 -> ACRH1MS101RJ | C21: =[1]Юнит!D20 -> Массажер для пальцев | D21: =[1]Юнит!E20 -> 2038430289250 | E21: 343 | F21: 0.4 | G21: 572 | H21: -0.061096596 | I21: =_xlfn.XLOOKUP(D21,[1]Юнит!$E:$E,[1]Юнит!$AN:$AN) -> 409 | J21: =$J$4 -> 0.3 | K21: =I21/(100%-J19) -> 584.28571 | L21: =_xlfn.XLOOKUP(D21,[1]Юнит!$E:$E,[1]Юнит!$AR:$AR) -> 0.11356733 | M21: =MROUND(O21-O21*N21,1) -> 343 | N21: =_xlfn.XLOOKUP($A21,'Текущая цена на ВБ'!$C:$C,'Текущая цена на ВБ'!$K:$K,0,0)% -> 0.4 | O21: =_xlfn.XLOOKUP($A21,'Текущая цена на ВБ'!$C:$C,'Текущая цена на ВБ'!$I:$I,0,0) -> 572 | P21: =_xlfn.XLOOKUP($A21,[1]Юнит!$A:$A,[1]Юнит!$AJ:$AJ,0) -> -0.04296317 | Q21: =_xlfn.XLOOKUP($A21,'Акция 1'!$F:$F,'Акция 1'!$L:$L,0,0) -> 337 | R21: =(_xlfn.XLOOKUP($A21,'Акция 1'!$F:$F,'Акция 1'!$P:$P,0,0))% -> 0.43 | S21: =Q21/(100%-R21) -> 591.22807 | T21: =_xlfn.XLOOKUP($A21,'Акция 2'!$F:$F,'Акция 2'!$L:$L,0,0) -> 0 | U21: =(_xlfn.XLOOKUP($A21,'Акция 2'!$F:$F,'Акция 2'!$O:$O,0,0))% -> 0 | V21: =T21/(100%-U21) -> 0 | W21: =_xlfn.XLOOKUP($A21,'Акция 3'!$F:$F,'Акция 3'!$L:$L,0,0) -> 343 | X21: =(_xlfn.XLOOKUP($A21,'Акция 3'!$F:$F,'Акция 3'!$P:$P,0,0))% -> 0.43 | Y21: =W21/(100%-X21) -> 601.75439 | Z21: =_xlfn.XLOOKUP($A21,'Акция 4'!$F:$F,'Акция 4'!$L:$L,0,0) -> 0 | AA21: =(_xlfn.XLOOKUP($A21,'Акция 4'!$F:$F,'Акция 4'!$P:$P,0,0))% -> 0 | AB21: =Z21/(100%-AA21) -> 0 | AC21: =_xlfn.XLOOKUP($A21,'Акция 5'!$F:$F,'Акция 5'!$L:$L,0,0) -> 0 | AD21: =(_xlfn.XLOOKUP($A21,'Акция 5'!$F:$F,'Акция 5'!O:O,0,0))% -> 0 | AE21: =AC21/(100%-AD21) -> 0 | AF21: =_xlfn.XLOOKUP($A21,'Акция 6'!$F:$F,'Акция 6'!$L:$L,0,0) -> 0 | AG21: =(_xlfn.XLOOKUP($A21,'Акция 6'!$F:$F,'Акция 6'!$O:$O,0,0))% -> 0 | AH21: =AF21/(100%-AG21) -> 0 | AI21: =_xlfn.XLOOKUP($A21,'Акция 7'!$F:$F,'Акция 7'!$L:$L,0,0) -> 0 | AJ21: =(_xlfn.XLOOKUP($A21,'Акция 7'!$F:$F,'Акция 7'!$O:$O,0,0))% -> 0 | AK21: =AI21/(100%-AJ21) -> 0 | AL21: =_xlfn.XLOOKUP($A21,'Акция 8'!$F:$F,'Акция 8'!$L:$L,0,0) -> 0 | AM21: =(_xlfn.XLOOKUP($A21,'Акция 8'!$F:$F,'Акция 8'!$S:$S,0,0))% -> 0 | AN21: =AL21/(100%-AM21) -> 0 | AO21: =_xlfn.XLOOKUP($A21,'Акция 9'!$F:$F,'Акция 9'!$L:$L,0,0) -> 0 | AP21: =(_xlfn.XLOOKUP($A21,'Акция 9'!$F:$F,'Акция 9'!$O:$O,0,0))% -> 0 | AQ21: =AO21/(100%-AP21) -> 0 | AR21: =_xlfn.XLOOKUP($A21,'Акция 10'!$F:$F,'Акция 10'!$L:$L,0,0) -> 0 | AS21: =(_xlfn.XLOOKUP($A21,'Акция 10'!$F:$F,'Акция 10'!$O:$O,0,0))% -> 0 | AT21: =AR21/(100%-AS21) -> 0 | AU21: =_xlfn.XLOOKUP($A21,'Акция 11'!$F:$F,'Акция 11'!$L:$L,0,0) -> 0 | AV21: =(_xlfn.XLOOKUP($A21,'Акция 11'!$F:$F,'Акция 11'!$O:$O,0,0))% -> 0 | AW21: =AU21/(100%-AV21) -> 0 | BA21: =MAX($Q21,$T21,W21,Z21,AC21,AF21,AL21,AO21,AR21,AU21,AX21,AI21) -> 343 | BB21: =IF(BA21=0,0,_xlfn.XLOOKUP($BA21,$Q21:$AZ21,$Q$1:$AZ$1,0,0)) -> 3 | BC21: =_xlfn.XLOOKUP($BB21,$Q$1:$AZ$1,$Q21:$AZ21,0,0) -> 343 | BD21: =IF(BA21=0,0,$BD$3) -> 0.4 | BE21: =BC21/(100%-BD21) -> 571.66667 | BF21: =_xlfn.XLOOKUP(A21,[1]Юнит!$A:$A,[1]Юнит!$AU:$AU,0) -> -0.043530496 | BG21: =P21 -> -0.04296317 | BH21: * | BI21: =MROUND(IF($BH21="*",$BE21,K21),1) -> 572 | BJ21: =IF($BH21="*",$BD21,J21) -> 0.4 | BK21: =MROUND(BI21-BI21*BJ21,1) -> 343 | BL21: =IF(BH21="*",1,0) -> 1 | BM21: =_xlfn.XLOOKUP(A21,'Текущая цена на ВБ'!C:C,'Текущая цена на ВБ'!F:F) -> 535 | BN21: =_xlfn.XLOOKUP(A21,'Текущая цена на ВБ'!C:C,'Текущая цена на ВБ'!H:H) -> 999
A22: =[1]Юнит!A21 -> 223420736 | B22: =[1]Юнит!C21 -> ACRB1MS101RJ | C22: =[1]Юнит!D21 -> Массажер для тела оранжевый | D22: =[1]Юнит!E21 -> 2039813223373 | E22: 901 | F22: 0.4 | G22: 1502 | H22: 0.24464344 | I22: =_xlfn.XLOOKUP(D22,[1]Юнит!$E:$E,[1]Юнит!$AN:$AN) -> 919 | J22: =$J$4 -> 0.3 | K22: =I22/(100%-J20) -> 1312.8571 | L22: =_xlfn.XLOOKUP(D22,[1]Юнит!$E:$E,[1]Юнит!$AR:$AR) -> 0.26094324 | M22: =MROUND(O22-O22*N22,1) -> 901 | N22: =_xlfn.XLOOKUP($A22,'Текущая цена на ВБ'!$C:$C,'Текущая цена на ВБ'!$K:$K,0,0)% -> 0.4 | O22: =_xlfn.XLOOKUP($A22,'Текущая цена на ВБ'!$C:$C,'Текущая цена на ВБ'!$I:$I,0,0) -> 1502 | P22: =_xlfn.XLOOKUP($A22,[1]Юнит!$A:$A,[1]Юнит!$AJ:$AJ,0) -> 0.2477284 | Q22: =_xlfn.XLOOKUP($A22,'Акция 1'!$F:$F,'Акция 1'!$L:$L,0,0) -> 901 | R22: =(_xlfn.XLOOKUP($A22,'Акция 1'!$F:$F,'Акция 1'!$P:$P,0,0))% -> 0.32 | S22: =Q22/(100%-R22) -> 1325 | T22: =_xlfn.XLOOKUP($A22,'Акция 2'!$F:$F,'Акция 2'!$L:$L,0,0) -> 0 | U22: =(_xlfn.XLOOKUP($A22,'Акция 2'!$F:$F,'Акция 2'!$O:$O,0,0))% -> 0 | V22: =T22/(100%-U22) -> 0 | W22: =_xlfn.XLOOKUP($A22,'Акция 3'!$F:$F,'Акция 3'!$L:$L,0,0) -> 771 | X22: =(_xlfn.XLOOKUP($A22,'Акция 3'!$F:$F,'Акция 3'!$P:$P,0,0))% -> 0.42 | Y22: =W22/(100%-X22) -> 1329.3103 | Z22: =_xlfn.XLOOKUP($A22,'Акция 4'!$F:$F,'Акция 4'!$L:$L,0,0) -> 0 | AA22: =(_xlfn.XLOOKUP($A22,'Акция 4'!$F:$F,'Акция 4'!$P:$P,0,0))% -> 0 | AB22: =Z22/(100%-AA22) -> 0 | AC22: =_xlfn.XLOOKUP($A22,'Акция 5'!$F:$F,'Акция 5'!$L:$L,0,0) -> 0 | AD22: =(_xlfn.XLOOKUP($A22,'Акция 5'!$F:$F,'Акция 5'!O:O,0,0))% -> 0 | AE22: =AC22/(100%-AD22) -> 0 | AF22: =_xlfn.XLOOKUP($A22,'Акция 6'!$F:$F,'Акция 6'!$L:$L,0,0) -> 0 | AG22: =(_xlfn.XLOOKUP($A22,'Акция 6'!$F:$F,'Акция 6'!$O:$O,0,0))% -> 0 | AH22: =AF22/(100%-AG22) -> 0 | AI22: =_xlfn.XLOOKUP($A22,'Акция 7'!$F:$F,'Акция 7'!$L:$L,0,0) -> 0 | AJ22: =(_xlfn.XLOOKUP($A22,'Акция 7'!$F:$F,'Акция 7'!$O:$O,0,0))% -> 0 | AK22: =AI22/(100%-AJ22) -> 0 | AL22: =_xlfn.XLOOKUP($A22,'Акция 8'!$F:$F,'Акция 8'!$L:$L,0,0) -> 0 | AM22: =(_xlfn.XLOOKUP($A22,'Акция 8'!$F:$F,'Акция 8'!$S:$S,0,0))% -> 0 | AN22: =AL22/(100%-AM22) -> 0 | AO22: =_xlfn.XLOOKUP($A22,'Акция 9'!$F:$F,'Акция 9'!$L:$L,0,0) -> 0 | AP22: =(_xlfn.XLOOKUP($A22,'Акция 9'!$F:$F,'Акция 9'!$O:$O,0,0))% -> 0 | AQ22: =AO22/(100%-AP22) -> 0 | AR22: =_xlfn.XLOOKUP($A22,'Акция 10'!$F:$F,'Акция 10'!$L:$L,0,0) -> 0 | AS22: =(_xlfn.XLOOKUP($A22,'Акция 10'!$F:$F,'Акция 10'!$O:$O,0,0))% -> 0 | AT22: =AR22/(100%-AS22) -> 0 | AU22: =_xlfn.XLOOKUP($A22,'Акция 11'!$F:$F,'Акция 11'!$L:$L,0,0) -> 0 | AV22: =(_xlfn.XLOOKUP($A22,'Акция 11'!$F:$F,'Акция 11'!$O:$O,0,0))% -> 0 | AW22: =AU22/(100%-AV22) -> 0 | BA22: =MAX($Q22,$T22,W22,Z22,AC22,AF22,AL22,AO22,AR22,AU22,AX22,AI22) -> 901 | BB22: =IF(BA22=0,0,_xlfn.XLOOKUP($BA22,$Q22:$AZ22,$Q$1:$AZ$1,0,0)) -> 1 | BC22: =_xlfn.XLOOKUP($BB22,$Q$1:$AZ$1,$Q22:$AZ22,0,0) -> 901 | BD22: =IF(BA22=0,0,$BD$3) -> 0.4 | BE22: =BC22/(100%-BD22) -> 1501.6667 | BF22: =_xlfn.XLOOKUP(A22,[1]Юнит!$A:$A,[1]Юнит!$AU:$AU,0) -> 0.24757696 | BG22: =P22 -> 0.2477284 | BH22: * | BI22: =MROUND(IF($BH22="*",$BE22,K22),1) -> 1502 | BJ22: =IF($BH22="*",$BD22,J22) -> 0.4 | BK22: =MROUND(BI22-BI22*BJ22,1) -> 901 | BL22: =IF(BH22="*",1,0) -> 1 | BM22: =_xlfn.XLOOKUP(A22,'Текущая цена на ВБ'!C:C,'Текущая цена на ВБ'!F:F) -> 56 | BN22: =_xlfn.XLOOKUP(A22,'Текущая цена на ВБ'!C:C,'Текущая цена на ВБ'!H:H) -> 368
A23: =[1]Юнит!A22 -> 275208801 | B23: =[1]Юнит!C22 -> ACRB1MS101PN | C23: =[1]Юнит!D22 -> Массажер для тела розовый | D23: =[1]Юнит!E22 -> 2041591042329 | E23: 725 | F23: 0.4 | G23: 1208 | H23: 0.16603916 | I23: =_xlfn.XLOOKUP(D23,[1]Юнит!$E:$E,[1]Юнит!$AN:$AN) -> 919 | J23: =$J$4 -> 0.3 | K23: =I23/(100%-J21) -> 1312.8571 | L23: =_xlfn.XLOOKUP(D23,[1]Юнит!$E:$E,[1]Юнит!$AR:$AR) -> 0.32866241 | M23: =MROUND(O23-O23*N23,1) -> 725 | N23: =_xlfn.XLOOKUP($A23,'Текущая цена на ВБ'!$C:$C,'Текущая цена на ВБ'!$K:$K,0,0)% -> 0.4 | O23: =_xlfn.XLOOKUP($A23,'Текущая цена на ВБ'!$C:$C,'Текущая цена на ВБ'!$I:$I,0,0) -> 1208 | P23: =_xlfn.XLOOKUP($A23,[1]Юнит!$A:$A,[1]Юнит!$AJ:$AJ,0) -> 0.16754244 | Q23: =_xlfn.XLOOKUP($A23,'Акция 1'!$F:$F,'Акция 1'!$L:$L,0,0) -> 725 | R23: =(_xlfn.XLOOKUP($A23,'Акция 1'!$F:$F,'Акция 1'!$P:$P,0,0))% -> 0.45 | S23: =Q23/(100%-R23) -> 1318.1818 | T23: =_xlfn.XLOOKUP($A23,'Акция 2'!$F:$F,'Акция 2'!$L:$L,0,0) -> 0 | U23: =(_xlfn.XLOOKUP($A23,'Акция 2'!$F:$F,'Акция 2'!$O:$O,0,0))% -> 0 | V23: =T23/(100%-U23) -> 0 | W23: =_xlfn.XLOOKUP($A23,'Акция 3'!$F:$F,'Акция 3'!$L:$L,0,0) -> 545 | X23: =(_xlfn.XLOOKUP($A23,'Акция 3'!$F:$F,'Акция 3'!$P:$P,0,0))% -> 0.59 | Y23: =W23/(100%-X23) -> 1329.2683 | Z23: =_xlfn.XLOOKUP($A23,'Акция 4'!$F:$F,'Акция 4'!$L:$L,0,0) -> 0 | AA23: =(_xlfn.XLOOKUP($A23,'Акция 4'!$F:$F,'Акция 4'!$P:$P,0,0))% -> 0 | AB23: =Z23/(100%-AA23) -> 0 | AC23: =_xlfn.XLOOKUP($A23,'Акция 5'!$F:$F,'Акция 5'!$L:$L,0,0) -> 0 | AD23: =(_xlfn.XLOOKUP($A23,'Акция 5'!$F:$F,'Акция 5'!O:O,0,0))% -> 0 | AE23: =AC23/(100%-AD23) -> 0 | AF23: =_xlfn.XLOOKUP($A23,'Акция 6'!$F:$F,'Акция 6'!$L:$L,0,0) -> 0 | AG23: =(_xlfn.XLOOKUP($A23,'Акция 6'!$F:$F,'Акция 6'!$O:$O,0,0))% -> 0 | AH23: =AF23/(100%-AG23) -> 0 | AI23: =_xlfn.XLOOKUP($A23,'Акция 7'!$F:$F,'Акция 7'!$L:$L,0,0) -> 0 | AJ23: =(_xlfn.XLOOKUP($A23,'Акция 7'!$F:$F,'Акция 7'!$O:$O,0,0))% -> 0 | AK23: =AI23/(100%-AJ23) -> 0 | AL23: =_xlfn.XLOOKUP($A23,'Акция 8'!$F:$F,'Акция 8'!$L:$L,0,0) -> 0 | AM23: =(_xlfn.XLOOKUP($A23,'Акция 8'!$F:$F,'Акция 8'!$S:$S,0,0))% -> 0 | AN23: =AL23/(100%-AM23) -> 0 | AO23: =_xlfn.XLOOKUP($A23,'Акция 9'!$F:$F,'Акция 9'!$L:$L,0,0) -> 0 | AP23: =(_xlfn.XLOOKUP($A23,'Акция 9'!$F:$F,'Акция 9'!$O:$O,0,0))% -> 0 | AQ23: =AO23/(100%-AP23) -> 0 | AR23: =_xlfn.XLOOKUP($A23,'Акция 10'!$F:$F,'Акция 10'!$L:$L,0,0) -> 0 | AS23: =(_xlfn.XLOOKUP($A23,'Акция 10'!$F:$F,'Акция 10'!$O:$O,0,0))% -> 0 | AT23: =AR23/(100%-AS23) -> 0 | AU23: =_xlfn.XLOOKUP($A23,'Акция 11'!$F:$F,'Акция 11'!$L:$L,0,0) -> 0 | AV23: =(_xlfn.XLOOKUP($A23,'Акция 11'!$F:$F,'Акция 11'!$O:$O,0,0))% -> 0 | AW23: =AU23/(100%-AV23) -> 0 | BA23: =MAX($Q23,$T23,W23,Z23,AC23,AF23,AL23,AO23,AR23,AU23,AX23,AI23) -> 725 | BB23: =IF(BA23=0,0,_xlfn.XLOOKUP($BA23,$Q23:$AZ23,$Q$1:$AZ$1,0,0)) -> 1 | BC23: =_xlfn.XLOOKUP($BB23,$Q$1:$AZ$1,$Q23:$AZ23,0,0) -> 725 | BD23: =IF(BA23=0,0,$BD$3) -> 0.4 | BE23: =BC23/(100%-BD23) -> 1208.3333 | BF23: =_xlfn.XLOOKUP(A23,[1]Юнит!$A:$A,[1]Юнит!$AU:$AU,0) -> 0.16775277 | BG23: =P23 -> 0.16754244 | BH23: * | BI23: =MROUND(IF($BH23="*",$BE23,K23),1) -> 1208 | BJ23: =IF($BH23="*",$BD23,J23) -> 0.4 | BK23: =MROUND(BI23-BI23*BJ23,1) -> 725 | BL23: =IF(BH23="*",1,0) -> 1 | BM23: =_xlfn.XLOOKUP(A23,'Текущая цена на ВБ'!C:C,'Текущая цена на ВБ'!F:F) -> 58 | BN23: =_xlfn.XLOOKUP(A23,'Текущая цена на ВБ'!C:C,'Текущая цена на ВБ'!H:H) -> 215
A24: =[1]Юнит!A23 -> 275208802 | B24: =[1]Юнит!C23 -> ACRB1MS101BL | C24: =[1]Юнит!D23 -> Массажер для тела голубой | D24: =[1]Юнит!E23 -> 2041591055954 | E24: 919 | F24: 0.3 | G24: 1313 | H24: 0.25414505 | I24: =_xlfn.XLOOKUP(D24,[1]Юнит!$E:$E,[1]Юнит!$AN:$AN) -> 919 | J24: =$J$4 -> 0.3 | K24: =I24/(100%-J22) -> 1312.8571 | L24: =_xlfn.XLOOKUP(D24,[1]Юнит!$E:$E,[1]Юнит!$AR:$AR) -> 0.25407151 | M24: =MROUND(O24-O24*N24,1) -> 919 | N24: =_xlfn.XLOOKUP($A24,'Текущая цена на ВБ'!$C:$C,'Текущая цена на ВБ'!$K:$K,0,0)% -> 0.3 | O24: =_xlfn.XLOOKUP($A24,'Текущая цена на ВБ'!$C:$C,'Текущая цена на ВБ'!$I:$I,0,0) -> 1313 | P24: =_xlfn.XLOOKUP($A24,[1]Юнит!$A:$A,[1]Юнит!$AJ:$AJ,0) -> 0.25414505 | Q24: =_xlfn.XLOOKUP($A24,'Акция 1'!$F:$F,'Акция 1'!$L:$L,0,0) -> 0 | R24: =(_xlfn.XLOOKUP($A24,'Акция 1'!$F:$F,'Акция 1'!$P:$P,0,0))% -> 0 | S24: =Q24/(100%-R24) -> 0 | T24: =_xlfn.XLOOKUP($A24,'Акция 2'!$F:$F,'Акция 2'!$L:$L,0,0) -> 0 | U24: =(_xlfn.XLOOKUP($A24,'Акция 2'!$F:$F,'Акция 2'!$O:$O,0,0))% -> 0 | V24: =T24/(100%-U24) -> 0 | W24: =_xlfn.XLOOKUP($A24,'Акция 3'!$F:$F,'Акция 3'!$L:$L,0,0) -> 0 | X24: =(_xlfn.XLOOKUP($A24,'Акция 3'!$F:$F,'Акция 3'!$P:$P,0,0))% -> 0 | Y24: =W24/(100%-X24) -> 0 | Z24: =_xlfn.XLOOKUP($A24,'Акция 4'!$F:$F,'Акция 4'!$L:$L,0,0) -> 0 | AA24: =(_xlfn.XLOOKUP($A24,'Акция 4'!$F:$F,'Акция 4'!$P:$P,0,0))% -> 0 | AB24: =Z24/(100%-AA24) -> 0 | AC24: =_xlfn.XLOOKUP($A24,'Акция 5'!$F:$F,'Акция 5'!$L:$L,0,0) -> 0 | AD24: =(_xlfn.XLOOKUP($A24,'Акция 5'!$F:$F,'Акция 5'!O:O,0,0))% -> 0 | AE24: =AC24/(100%-AD24) -> 0 | AF24: =_xlfn.XLOOKUP($A24,'Акция 6'!$F:$F,'Акция 6'!$L:$L,0,0) -> 0 | AG24: =(_xlfn.XLOOKUP($A24,'Акция 6'!$F:$F,'Акция 6'!$O:$O,0,0))% -> 0 | AH24: =AF24/(100%-AG24) -> 0 | AI24: =_xlfn.XLOOKUP($A24,'Акция 7'!$F:$F,'Акция 7'!$L:$L,0,0) -> 0 | AJ24: =(_xlfn.XLOOKUP($A24,'Акция 7'!$F:$F,'Акция 7'!$O:$O,0,0))% -> 0 | AK24: =AI24/(100%-AJ24) -> 0 | AL24: =_xlfn.XLOOKUP($A24,'Акция 8'!$F:$F,'Акция 8'!$L:$L,0,0) -> 0 | AM24: =(_xlfn.XLOOKUP($A24,'Акция 8'!$F:$F,'Акция 8'!$S:$S,0,0))% -> 0 | AN24: =AL24/(100%-AM24) -> 0 | AO24: =_xlfn.XLOOKUP($A24,'Акция 9'!$F:$F,'Акция 9'!$L:$L,0,0) -> 0 | AP24: =(_xlfn.XLOOKUP($A24,'Акция 9'!$F:$F,'Акция 9'!$O:$O,0,0))% -> 0 | AQ24: =AO24/(100%-AP24) -> 0 | AR24: =_xlfn.XLOOKUP($A24,'Акция 10'!$F:$F,'Акция 10'!$L:$L,0,0) -> 0 | AS24: =(_xlfn.XLOOKUP($A24,'Акция 10'!$F:$F,'Акция 10'!$O:$O,0,0))% -> 0 | AT24: =AR24/(100%-AS24) -> 0 | AU24: =_xlfn.XLOOKUP($A24,'Акция 11'!$F:$F,'Акция 11'!$L:$L,0,0) -> 0 | AV24: =(_xlfn.XLOOKUP($A24,'Акция 11'!$F:$F,'Акция 11'!$O:$O,0,0))% -> 0 | AW24: =AU24/(100%-AV24) -> 0 | BA24: =MAX($Q24,$T24,W24,Z24,AC24,AF24,AL24,AO24,AR24,AU24,AX24,AI24) -> 0 | BB24: =IF(BA24=0,0,_xlfn.XLOOKUP($BA24,$Q24:$AZ24,$Q$1:$AZ$1,0,0)) -> 0 | BC24: =_xlfn.XLOOKUP($BB24,$Q$1:$AZ$1,$Q24:$AZ24,0,0) -> 0 | BD24: =IF(BA24=0,0,$BD$3) -> 0 | BE24: =BC24/(100%-BD24) -> 0 | BF24: =_xlfn.XLOOKUP(A24,[1]Юнит!$A:$A,[1]Юнит!$AU:$AU,0) -> 0 | BG24: =P24 -> 0.25414505 | BI24: =MROUND(IF($BH24="*",$BE24,K24),1) -> 1313 | BJ24: =IF($BH24="*",$BD24,J24) -> 0.3 | BK24: =MROUND(BI24-BI24*BJ24,1) -> 919 | BL24: =IF(BH24="*",1,0) -> 0 | BM24: =_xlfn.XLOOKUP(A24,'Текущая цена на ВБ'!C:C,'Текущая цена на ВБ'!F:F) -> 60 | BN24: =_xlfn.XLOOKUP(A24,'Текущая цена на ВБ'!C:C,'Текущая цена на ВБ'!H:H) -> 999
A25: =[1]Юнит!A24 -> 236072835 | B25: =[1]Юнит!C24 -> ACRB1MS106WH | C25: =[1]Юнит!D24 -> Мяч с шипами белый 6 см | D25: =[1]Юнит!E24 -> 2040278804496 | E25: 597 | F25: 0.4 | G25: 995 | H25: 0.22903115 | I25: =_xlfn.XLOOKUP(D25,[1]Юнит!$E:$E,[1]Юнит!$AN:$AN) -> 599 | J25: =$J$4 -> 0.3 | K25: =I25/(100%-J23) -> 855.71429 | L25: =_xlfn.XLOOKUP(D25,[1]Юнит!$E:$E,[1]Юнит!$AR:$AR) -> 0.23506836 | M25: =MROUND(O25-O25*N25,1) -> 597 | N25: =_xlfn.XLOOKUP($A25,'Текущая цена на ВБ'!$C:$C,'Текущая цена на ВБ'!$K:$K,0,0)% -> 0.4 | O25: =_xlfn.XLOOKUP($A25,'Текущая цена на ВБ'!$C:$C,'Текущая цена на ВБ'!$I:$I,0,0) -> 995 | P25: =_xlfn.XLOOKUP($A25,[1]Юнит!$A:$A,[1]Юнит!$AJ:$AJ,0) -> 0.23274028 | Q25: =_xlfn.XLOOKUP($A25,'Акция 1'!$F:$F,'Акция 1'!$L:$L,0,0) -> 0 | R25: =(_xlfn.XLOOKUP($A25,'Акция 1'!$F:$F,'Акция 1'!$P:$P,0,0))% -> 0 | S25: =Q25/(100%-R25) -> 0 | T25: =_xlfn.XLOOKUP($A25,'Акция 2'!$F:$F,'Акция 2'!$L:$L,0,0) -> 597 | U25: =(_xlfn.XLOOKUP($A25,'Акция 2'!$F:$F,'Акция 2'!$O:$O,0,0))% -> 0.31 | V25: =T25/(100%-U25) -> 865.21739 | W25: =_xlfn.XLOOKUP($A25,'Акция 3'!$F:$F,'Акция 3'!$L:$L,0,0) -> 488 | X25: =(_xlfn.XLOOKUP($A25,'Акция 3'!$F:$F,'Акция 3'!$P:$P,0,0))% -> 0.43 | Y25: =W25/(100%-X25) -> 856.14035 | Z25: =_xlfn.XLOOKUP($A25,'Акция 4'!$F:$F,'Акция 4'!$L:$L,0,0) -> 0 | AA25: =(_xlfn.XLOOKUP($A25,'Акция 4'!$F:$F,'Акция 4'!$P:$P,0,0))% -> 0 | AB25: =Z25/(100%-AA25) -> 0 | AC25: =_xlfn.XLOOKUP($A25,'Акция 5'!$F:$F,'Акция 5'!$L:$L,0,0) -> 0 | AD25: =(_xlfn.XLOOKUP($A25,'Акция 5'!$F:$F,'Акция 5'!O:O,0,0))% -> 0 | AE25: =AC25/(100%-AD25) -> 0 | AF25: =_xlfn.XLOOKUP($A25,'Акция 6'!$F:$F,'Акция 6'!$L:$L,0,0) -> 0 | AG25: =(_xlfn.XLOOKUP($A25,'Акция 6'!$F:$F,'Акция 6'!$O:$O,0,0))% -> 0 | AH25: =AF25/(100%-AG25) -> 0 | AI25: =_xlfn.XLOOKUP($A25,'Акция 7'!$F:$F,'Акция 7'!$L:$L,0,0) -> 0 | AJ25: =(_xlfn.XLOOKUP($A25,'Акция 7'!$F:$F,'Акция 7'!$O:$O,0,0))% -> 0 | AK25: =AI25/(100%-AJ25) -> 0 | AL25: =_xlfn.XLOOKUP($A25,'Акция 8'!$F:$F,'Акция 8'!$L:$L,0,0) -> 0 | AM25: =(_xlfn.XLOOKUP($A25,'Акция 8'!$F:$F,'Акция 8'!$S:$S,0,0))% -> 0 | AN25: =AL25/(100%-AM25) -> 0 | AO25: =_xlfn.XLOOKUP($A25,'Акция 9'!$F:$F,'Акция 9'!$L:$L,0,0) -> 0 | AP25: =(_xlfn.XLOOKUP($A25,'Акция 9'!$F:$F,'Акция 9'!$O:$O,0,0))% -> 0 | AQ25: =AO25/(100%-AP25) -> 0 | AR25: =_xlfn.XLOOKUP($A25,'Акция 10'!$F:$F,'Акция 10'!$L:$L,0,0) -> 0 | AS25: =(_xlfn.XLOOKUP($A25,'Акция 10'!$F:$F,'Акция 10'!$O:$O,0,0))% -> 0 | AT25: =AR25/(100%-AS25) -> 0 | AU25: =_xlfn.XLOOKUP($A25,'Акция 11'!$F:$F,'Акция 11'!$L:$L,0,0) -> 0 | AV25: =(_xlfn.XLOOKUP($A25,'Акция 11'!$F:$F,'Акция 11'!$O:$O,0,0))% -> 0 | AW25: =AU25/(100%-AV25) -> 0 | BA25: =MAX($Q25,$T25,W25,Z25,AC25,AF25,AL25,AO25,AR25,AU25,AX25,AI25) -> 597 | BB25: =IF(BA25=0,0,_xlfn.XLOOKUP($BA25,$Q25:$AZ25,$Q$1:$AZ$1,0,0)) -> 2 | BC25: =_xlfn.XLOOKUP($BB25,$Q$1:$AZ$1,$Q25:$AZ25,0,0) -> 597 | BD25: =IF(BA25=0,0,$BD$3) -> 0.4 | BE25: =BC25/(100%-BD25) -> 995 | BF25: =_xlfn.XLOOKUP(A25,[1]Юнит!$A:$A,[1]Юнит!$AU:$AU,0) -> 0.23274028 | BG25: =P25 -> 0.23274028 | BH25: * | BI25: =MROUND(IF($BH25="*",$BE25,K25),1) -> 995 | BJ25: =IF($BH25="*",$BD25,J25) -> 0.4 | BK25: =MROUND(BI25-BI25*BJ25,1) -> 597 | BL25: =IF(BH25="*",1,0) -> 1 | BM25: =_xlfn.XLOOKUP(A25,'Текущая цена на ВБ'!C:C,'Текущая цена на ВБ'!F:F) -> 427 | BN25: =_xlfn.XLOOKUP(A25,'Текущая цена на ВБ'!C:C,'Текущая цена на ВБ'!H:H) -> 256
A26: =[1]Юнит!A25 -> 236072836 | B26: =[1]Юнит!C25 -> ACRB1MS106PN | C26: =[1]Юнит!D25 -> Мяч с шипами розовый 6 см | D26: =[1]Юнит!E25 -> 2040278810534 | E26: 593 | F26: 0.4 | G26: 988 | H26: 0.22903115 | I26: =_xlfn.XLOOKUP(D26,[1]Юнит!$E:$E,[1]Юнит!$AN:$AN) -> 599 | J26: =$J$4 -> 0.3 | K26: =I26/(100%-J24) -> 855.71429 | L26: =_xlfn.XLOOKUP(D26,[1]Юнит!$E:$E,[1]Юнит!$AR:$AR) -> 0.23754209 | M26: =MROUND(O26-O26*N26,1) -> 593 | N26: =_xlfn.XLOOKUP($A26,'Текущая цена на ВБ'!$C:$C,'Текущая цена на ВБ'!$K:$K,0,0)% -> 0.4 | O26: =_xlfn.XLOOKUP($A26,'Текущая цена на ВБ'!$C:$C,'Текущая цена на ВБ'!$I:$I,0,0) -> 988 | P26: =_xlfn.XLOOKUP($A26,[1]Юнит!$A:$A,[1]Юнит!$AJ:$AJ,0) -> 0.23029978 | Q26: =_xlfn.XLOOKUP($A26,'Акция 1'!$F:$F,'Акция 1'!$L:$L,0,0) -> 593 | R26: =(_xlfn.XLOOKUP($A26,'Акция 1'!$F:$F,'Акция 1'!$P:$P,0,0))% -> 0.31 | S26: =Q26/(100%-R26) -> 859.42029 | T26: =_xlfn.XLOOKUP($A26,'Акция 2'!$F:$F,'Акция 2'!$L:$L,0,0) -> 0 | U26: =(_xlfn.XLOOKUP($A26,'Акция 2'!$F:$F,'Акция 2'!$O:$O,0,0))% -> 0 | V26: =T26/(100%-U26) -> 0 | W26: =_xlfn.XLOOKUP($A26,'Акция 3'!$F:$F,'Акция 3'!$L:$L,0,0) -> 485 | X26: =(_xlfn.XLOOKUP($A26,'Акция 3'!$F:$F,'Акция 3'!$P:$P,0,0))% -> 0.44 | Y26: =W26/(100%-X26) -> 866.07143 | Z26: =_xlfn.XLOOKUP($A26,'Акция 4'!$F:$F,'Акция 4'!$L:$L,0,0) -> 0 | AA26: =(_xlfn.XLOOKUP($A26,'Акция 4'!$F:$F,'Акция 4'!$P:$P,0,0))% -> 0 | AB26: =Z26/(100%-AA26) -> 0 | AC26: =_xlfn.XLOOKUP($A26,'Акция 5'!$F:$F,'Акция 5'!$L:$L,0,0) -> 0 | AD26: =(_xlfn.XLOOKUP($A26,'Акция 5'!$F:$F,'Акция 5'!O:O,0,0))% -> 0 | AE26: =AC26/(100%-AD26) -> 0 | AF26: =_xlfn.XLOOKUP($A26,'Акция 6'!$F:$F,'Акция 6'!$L:$L,0,0) -> 0 | AG26: =(_xlfn.XLOOKUP($A26,'Акция 6'!$F:$F,'Акция 6'!$O:$O,0,0))% -> 0 | AH26: =AF26/(100%-AG26) -> 0 | AI26: =_xlfn.XLOOKUP($A26,'Акция 7'!$F:$F,'Акция 7'!$L:$L,0,0) -> 0 | AJ26: =(_xlfn.XLOOKUP($A26,'Акция 7'!$F:$F,'Акция 7'!$O:$O,0,0))% -> 0 | AK26: =AI26/(100%-AJ26) -> 0 | AL26: =_xlfn.XLOOKUP($A26,'Акция 8'!$F:$F,'Акция 8'!$L:$L,0,0) -> 0 | AM26: =(_xlfn.XLOOKUP($A26,'Акция 8'!$F:$F,'Акция 8'!$S:$S,0,0))% -> 0 | AN26: =AL26/(100%-AM26) -> 0 | AO26: =_xlfn.XLOOKUP($A26,'Акция 9'!$F:$F,'Акция 9'!$L:$L,0,0) -> 0 | AP26: =(_xlfn.XLOOKUP($A26,'Акция 9'!$F:$F,'Акция 9'!$O:$O,0,0))% -> 0 | AQ26: =AO26/(100%-AP26) -> 0 | AR26: =_xlfn.XLOOKUP($A26,'Акция 10'!$F:$F,'Акция 10'!$L:$L,0,0) -> 0 | AS26: =(_xlfn.XLOOKUP($A26,'Акция 10'!$F:$F,'Акция 10'!$O:$O,0,0))% -> 0 | AT26: =AR26/(100%-AS26) -> 0 | AU26: =_xlfn.XLOOKUP($A26,'Акция 11'!$F:$F,'Акция 11'!$L:$L,0,0) -> 0 | AV26: =(_xlfn.XLOOKUP($A26,'Акция 11'!$F:$F,'Акция 11'!$O:$O,0,0))% -> 0 | AW26: =AU26/(100%-AV26) -> 0 | BA26: =MAX($Q26,$T26,W26,Z26,AC26,AF26,AL26,AO26,AR26,AU26,AX26,AI26) -> 593 | BB26: =IF(BA26=0,0,_xlfn.XLOOKUP($BA26,$Q26:$AZ26,$Q$1:$AZ$1,0,0)) -> 1 | BC26: =_xlfn.XLOOKUP($BB26,$Q$1:$AZ$1,$Q26:$AZ26,0,0) -> 593 | BD26: =IF(BA26=0,0,$BD$3) -> 0.4 | BE26: =BC26/(100%-BD26) -> 988.33333 | BF26: =_xlfn.XLOOKUP(A26,[1]Юнит!$A:$A,[1]Юнит!$AU:$AU,0) -> 0.23053577 | BG26: =P26 -> 0.23029978 | BH26: * | BI26: =MROUND(IF($BH26="*",$BE26,K26),1) -> 988 | BJ26: =IF($BH26="*",$BD26,J26) -> 0.4 | BK26: =MROUND(BI26-BI26*BJ26,1) -> 593 | BL26: =IF(BH26="*",1,0) -> 1 | BM26: =_xlfn.XLOOKUP(A26,'Текущая цена на ВБ'!C:C,'Текущая цена на ВБ'!F:F) -> 300 | BN26: =_xlfn.XLOOKUP(A26,'Текущая цена на ВБ'!C:C,'Текущая цена на ВБ'!H:H) -> 638
A27: =[1]Юнит!A26 -> 236072834 | B27: =[1]Юнит!C26 -> ACRB1MS106BL | C27: =[1]Юнит!D26 -> Мяч с шипами голубой 6 см | D27: =[1]Юнит!E26 -> 2040278804649 | E27: 545 | F27: 0.4 | G27: 908 | H27: 0.19587221 | I27: =_xlfn.XLOOKUP(D27,[1]Юнит!$E:$E,[1]Юнит!$AN:$AN) -> 599 | J27: =$J$4 -> 0.3 | K27: =I27/(100%-J25) -> 855.71429 | L27: =_xlfn.XLOOKUP(D27,[1]Юнит!$E:$E,[1]Юнит!$AR:$AR) -> 0.2658132 | M27: =MROUND(O27-O27*N27,1) -> 545 | N27: =_xlfn.XLOOKUP($A27,'Текущая цена на ВБ'!$C:$C,'Текущая цена на ВБ'!$K:$K,0,0)% -> 0.4 | O27: =_xlfn.XLOOKUP($A27,'Текущая цена на ВБ'!$C:$C,'Текущая цена на ВБ'!$I:$I,0,0) -> 908 | P27: =_xlfn.XLOOKUP($A27,[1]Юнит!$A:$A,[1]Юнит!$AJ:$AJ,0) -> 0.19973588 | Q27: =_xlfn.XLOOKUP($A27,'Акция 1'!$F:$F,'Акция 1'!$L:$L,0,0) -> 545 | R27: =(_xlfn.XLOOKUP($A27,'Акция 1'!$F:$F,'Акция 1'!$P:$P,0,0))% -> 0.37 | S27: =Q27/(100%-R27) -> 865.07937 | T27: =_xlfn.XLOOKUP($A27,'Акция 2'!$F:$F,'Акция 2'!$L:$L,0,0) -> 0 | U27: =(_xlfn.XLOOKUP($A27,'Акция 2'!$F:$F,'Акция 2'!$O:$O,0,0))% -> 0 | V27: =T27/(100%-U27) -> 0 | W27: =_xlfn.XLOOKUP($A27,'Акция 3'!$F:$F,'Акция 3'!$L:$L,0,0) -> 410 | X27: =(_xlfn.XLOOKUP($A27,'Акция 3'!$F:$F,'Акция 3'!$P:$P,0,0))% -> 0.52 | Y27: =W27/(100%-X27) -> 854.16667 | Z27: =_xlfn.XLOOKUP($A27,'Акция 4'!$F:$F,'Акция 4'!$L:$L,0,0) -> 0 | AA27: =(_xlfn.XLOOKUP($A27,'Акция 4'!$F:$F,'Акция 4'!$P:$P,0,0))% -> 0 | AB27: =Z27/(100%-AA27) -> 0 | AC27: =_xlfn.XLOOKUP($A27,'Акция 5'!$F:$F,'Акция 5'!$L:$L,0,0) -> 0 | AD27: =(_xlfn.XLOOKUP($A27,'Акция 5'!$F:$F,'Акция 5'!O:O,0,0))% -> 0 | AE27: =AC27/(100%-AD27) -> 0 | AF27: =_xlfn.XLOOKUP($A27,'Акция 6'!$F:$F,'Акция 6'!$L:$L,0,0) -> 0 | AG27: =(_xlfn.XLOOKUP($A27,'Акция 6'!$F:$F,'Акция 6'!$O:$O,0,0))% -> 0 | AH27: =AF27/(100%-AG27) -> 0 | AI27: =_xlfn.XLOOKUP($A27,'Акция 7'!$F:$F,'Акция 7'!$L:$L,0,0) -> 0 | AJ27: =(_xlfn.XLOOKUP($A27,'Акция 7'!$F:$F,'Акция 7'!$O:$O,0,0))% -> 0 | AK27: =AI27/(100%-AJ27) -> 0 | AL27: =_xlfn.XLOOKUP($A27,'Акция 8'!$F:$F,'Акция 8'!$L:$L,0,0) -> 0 | AM27: =(_xlfn.XLOOKUP($A27,'Акция 8'!$F:$F,'Акция 8'!$S:$S,0,0))% -> 0 | AN27: =AL27/(100%-AM27) -> 0 | AO27: =_xlfn.XLOOKUP($A27,'Акция 9'!$F:$F,'Акция 9'!$L:$L,0,0) -> 0 | AP27: =(_xlfn.XLOOKUP($A27,'Акция 9'!$F:$F,'Акция 9'!$O:$O,0,0))% -> 0 | AQ27: =AO27/(100%-AP27) -> 0 | AR27: =_xlfn.XLOOKUP($A27,'Акция 10'!$F:$F,'Акция 10'!$L:$L,0,0) -> 0 | AS27: =(_xlfn.XLOOKUP($A27,'Акция 10'!$F:$F,'Акция 10'!$O:$O,0,0))% -> 0 | AT27: =AR27/(100%-AS27) -> 0 | AU27: =_xlfn.XLOOKUP($A27,'Акция 11'!$F:$F,'Акция 11'!$L:$L,0,0) -> 0 | AV27: =(_xlfn.XLOOKUP($A27,'Акция 11'!$F:$F,'Акция 11'!$O:$O,0,0))% -> 0 | AW27: =AU27/(100%-AV27) -> 0 | BA27: =MAX($Q27,$T27,W27,Z27,AC27,AF27,AL27,AO27,AR27,AU27,AX27,AI27) -> 545 | BB27: =IF(BA27=0,0,_xlfn.XLOOKUP($BA27,$Q27:$AZ27,$Q$1:$AZ$1,0,0)) -> 1 | BC27: =_xlfn.XLOOKUP($BB27,$Q$1:$AZ$1,$Q27:$AZ27,0,0) -> 545 | BD27: =IF(BA27=0,0,$BD$3) -> 0.4 | BE27: =BC27/(100%-BD27) -> 908.33333 | BF27: =_xlfn.XLOOKUP(A27,[1]Юнит!$A:$A,[1]Юнит!$AU:$AU,0) -> 0.20000387 | BG27: =P27 -> 0.19973588 | BH27: * | BI27: =MROUND(IF($BH27="*",$BE27,K27),1) -> 908 | BJ27: =IF($BH27="*",$BD27,J27) -> 0.4 | BK27: =MROUND(BI27-BI27*BJ27,1) -> 545 | BL27: =IF(BH27="*",1,0) -> 1 | BM27: =_xlfn.XLOOKUP(A27,'Текущая цена на ВБ'!C:C,'Текущая цена на ВБ'!F:F) -> 254 | BN27: =_xlfn.XLOOKUP(A27,'Текущая цена на ВБ'!C:C,'Текущая цена на ВБ'!H:H) -> 443
A28: =[1]Юнит!A27 -> 223671295 | B28: =[1]Юнит!C27 -> ACRB1MS106RJ | C28: =[1]Юнит!D27 -> Мяч с шипами оранжевый 6 см | D28: =[1]Юнит!E27 -> 2039818580389 | E28: 431 | F28: 0.4 | G28: 718 | H28: 0.096726984 | I28: =_xlfn.XLOOKUP(D28,[1]Юнит!$E:$E,[1]Юнит!$AN:$AN) -> 599 | J28: =$J$4 -> 0.3 | K28: =I28/(100%-J26) -> 855.71429 | L28: =_xlfn.XLOOKUP(D28,[1]Юнит!$E:$E,[1]Юнит!$AR:$AR) -> 0.33295711 | M28: =MROUND(O28-O28*N28,1) -> 431 | N28: =_xlfn.XLOOKUP($A28,'Текущая цена на ВБ'!$C:$C,'Текущая цена на ВБ'!$K:$K,0,0)% -> 0.4 | O28: =_xlfn.XLOOKUP($A28,'Текущая цена на ВБ'!$C:$C,'Текущая цена на ВБ'!$I:$I,0,0) -> 718 | P28: =_xlfn.XLOOKUP($A28,[1]Юнит!$A:$A,[1]Юнит!$AJ:$AJ,0) -> 0.099849836 | Q28: =_xlfn.XLOOKUP($A28,'Акция 1'!$F:$F,'Акция 1'!$L:$L,0,0) -> 431 | R28: =(_xlfn.XLOOKUP($A28,'Акция 1'!$F:$F,'Акция 1'!$P:$P,0,0))% -> 0.5 | S28: =Q28/(100%-R28) -> 862 | T28: =_xlfn.XLOOKUP($A28,'Акция 2'!$F:$F,'Акция 2'!$L:$L,0,0) -> 0 | U28: =(_xlfn.XLOOKUP($A28,'Акция 2'!$F:$F,'Акция 2'!$O:$O,0,0))% -> 0 | V28: =T28/(100%-U28) -> 0 | W28: =_xlfn.XLOOKUP($A28,'Акция 3'!$F:$F,'Акция 3'!$L:$L,0,0) -> 324 | X28: =(_xlfn.XLOOKUP($A28,'Акция 3'!$F:$F,'Акция 3'!$P:$P,0,0))% -> 0.63 | Y28: =W28/(100%-X28) -> 875.67568 | Z28: =_xlfn.XLOOKUP($A28,'Акция 4'!$F:$F,'Акция 4'!$L:$L,0,0) -> 0 | AA28: =(_xlfn.XLOOKUP($A28,'Акция 4'!$F:$F,'Акция 4'!$P:$P,0,0))% -> 0 | AB28: =Z28/(100%-AA28) -> 0 | AC28: =_xlfn.XLOOKUP($A28,'Акция 5'!$F:$F,'Акция 5'!$L:$L,0,0) -> 0 | AD28: =(_xlfn.XLOOKUP($A28,'Акция 5'!$F:$F,'Акция 5'!O:O,0,0))% -> 0 | AE28: =AC28/(100%-AD28) -> 0 | AF28: =_xlfn.XLOOKUP($A28,'Акция 6'!$F:$F,'Акция 6'!$L:$L,0,0) -> 0 | AG28: =(_xlfn.XLOOKUP($A28,'Акция 6'!$F:$F,'Акция 6'!$O:$O,0,0))% -> 0 | AH28: =AF28/(100%-AG28) -> 0 | AI28: =_xlfn.XLOOKUP($A28,'Акция 7'!$F:$F,'Акция 7'!$L:$L,0,0) -> 0 | AJ28: =(_xlfn.XLOOKUP($A28,'Акция 7'!$F:$F,'Акция 7'!$O:$O,0,0))% -> 0 | AK28: =AI28/(100%-AJ28) -> 0 | AL28: =_xlfn.XLOOKUP($A28,'Акция 8'!$F:$F,'Акция 8'!$L:$L,0,0) -> 0 | AM28: =(_xlfn.XLOOKUP($A28,'Акция 8'!$F:$F,'Акция 8'!$S:$S,0,0))% -> 0 | AN28: =AL28/(100%-AM28) -> 0 | AO28: =_xlfn.XLOOKUP($A28,'Акция 9'!$F:$F,'Акция 9'!$L:$L,0,0) -> 0 | AP28: =(_xlfn.XLOOKUP($A28,'Акция 9'!$F:$F,'Акция 9'!$O:$O,0,0))% -> 0 | AQ28: =AO28/(100%-AP28) -> 0 | AR28: =_xlfn.XLOOKUP($A28,'Акция 10'!$F:$F,'Акция 10'!$L:$L,0,0) -> 0 | AS28: =(_xlfn.XLOOKUP($A28,'Акция 10'!$F:$F,'Акция 10'!$O:$O,0,0))% -> 0 | AT28: =AR28/(100%-AS28) -> 0 | AU28: =_xlfn.XLOOKUP($A28,'Акция 11'!$F:$F,'Акция 11'!$L:$L,0,0) -> 0 | AV28: =(_xlfn.XLOOKUP($A28,'Акция 11'!$F:$F,'Акция 11'!$O:$O,0,0))% -> 0 | AW28: =AU28/(100%-AV28) -> 0 | BA28: =MAX($Q28,$T28,W28,Z28,AC28,AF28,AL28,AO28,AR28,AU28,AX28,AI28) -> 431 | BB28: =IF(BA28=0,0,_xlfn.XLOOKUP($BA28,$Q28:$AZ28,$Q$1:$AZ$1,0,0)) -> 1 | BC28: =_xlfn.XLOOKUP($BB28,$Q$1:$AZ$1,$Q28:$AZ28,0,0) -> 431 | BD28: =IF(BA28=0,0,$BD$3) -> 0.4 | BE28: =BC28/(100%-BD28) -> 718.33333 | BF28: =_xlfn.XLOOKUP(A28,[1]Юнит!$A:$A,[1]Юнит!$AU:$AU,0) -> 0.10023506 | BG28: =P28 -> 0.099849836 | BH28: * | BI28: =MROUND(IF($BH28="*",$BE28,K28),1) -> 718 | BJ28: =IF($BH28="*",$BD28,J28) -> 0.4 | BK28: =MROUND(BI28-BI28*BJ28,1) -> 431 | BL28: =IF(BH28="*",1,0) -> 1 | BM28: =_xlfn.XLOOKUP(A28,'Текущая цена на ВБ'!C:C,'Текущая цена на ВБ'!F:F) -> 447 | BN28: =_xlfn.XLOOKUP(A28,'Текущая цена на ВБ'!C:C,'Текущая цена на ВБ'!H:H) -> 823
A29: =[1]Юнит!A28 -> 370591238 | B29: =[1]Юнит!C28 -> ACRB1MS106BС | C29: =[1]Юнит!D28 -> Мяч с шипами черный 6 см | D29: =[1]Юнит!E28 -> 2043369663040 | E29: 599 | F29: 0.3 | G29: 856 | H29: 0.25419858 | I29: =_xlfn.XLOOKUP(D29,[1]Юнит!$E:$E,[1]Юнит!$AN:$AN) -> 599 | J29: =$J$4 -> 0.3 | K29: =I29/(100%-J27) -> 855.71429 | L29: =_xlfn.XLOOKUP(D29,[1]Юнит!$E:$E,[1]Юнит!$AR:$AR) -> 0.25397294 | M29: =MROUND(O29-O29*N29,1) -> 599 | N29: =_xlfn.XLOOKUP($A29,'Текущая цена на ВБ'!$C:$C,'Текущая цена на ВБ'!$K:$K,0,0)% -> 0.3 | O29: =_xlfn.XLOOKUP($A29,'Текущая цена на ВБ'!$C:$C,'Текущая цена на ВБ'!$I:$I,0,0) -> 856 | P29: =_xlfn.XLOOKUP($A29,[1]Юнит!$A:$A,[1]Юнит!$AJ:$AJ,0) -> 0.25419858 | Q29: =_xlfn.XLOOKUP($A29,'Акция 1'!$F:$F,'Акция 1'!$L:$L,0,0) -> 0 | R29: =(_xlfn.XLOOKUP($A29,'Акция 1'!$F:$F,'Акция 1'!$P:$P,0,0))% -> 0 | S29: =Q29/(100%-R29) -> 0 | T29: =_xlfn.XLOOKUP($A29,'Акция 2'!$F:$F,'Акция 2'!$L:$L,0,0) -> 0 | U29: =(_xlfn.XLOOKUP($A29,'Акция 2'!$F:$F,'Акция 2'!$O:$O,0,0))% -> 0 | V29: =T29/(100%-U29) -> 0 | W29: =_xlfn.XLOOKUP($A29,'Акция 3'!$F:$F,'Акция 3'!$L:$L,0,0) -> 0 | X29: =(_xlfn.XLOOKUP($A29,'Акция 3'!$F:$F,'Акция 3'!$P:$P,0,0))% -> 0 | Y29: =W29/(100%-X29) -> 0 | Z29: =_xlfn.XLOOKUP($A29,'Акция 4'!$F:$F,'Акция 4'!$L:$L,0,0) -> 0 | AA29: =(_xlfn.XLOOKUP($A29,'Акция 4'!$F:$F,'Акция 4'!$P:$P,0,0))% -> 0 | AB29: =Z29/(100%-AA29) -> 0 | AC29: =_xlfn.XLOOKUP($A29,'Акция 5'!$F:$F,'Акция 5'!$L:$L,0,0) -> 0 | AD29: =(_xlfn.XLOOKUP($A29,'Акция 5'!$F:$F,'Акция 5'!O:O,0,0))% -> 0 | AE29: =AC29/(100%-AD29) -> 0 | AF29: =_xlfn.XLOOKUP($A29,'Акция 6'!$F:$F,'Акция 6'!$L:$L,0,0) -> 0 | AG29: =(_xlfn.XLOOKUP($A29,'Акция 6'!$F:$F,'Акция 6'!$O:$O,0,0))% -> 0 | AH29: =AF29/(100%-AG29) -> 0 | AI29: =_xlfn.XLOOKUP($A29,'Акция 7'!$F:$F,'Акция 7'!$L:$L,0,0) -> 0 | AJ29: =(_xlfn.XLOOKUP($A29,'Акция 7'!$F:$F,'Акция 7'!$O:$O,0,0))% -> 0 | AK29: =AI29/(100%-AJ29) -> 0 | AL29: =_xlfn.XLOOKUP($A29,'Акция 8'!$F:$F,'Акция 8'!$L:$L,0,0) -> 0 | AM29: =(_xlfn.XLOOKUP($A29,'Акция 8'!$F:$F,'Акция 8'!$S:$S,0,0))% -> 0 | AN29: =AL29/(100%-AM29) -> 0 | AO29: =_xlfn.XLOOKUP($A29,'Акция 9'!$F:$F,'Акция 9'!$L:$L,0,0) -> 0 | AP29: =(_xlfn.XLOOKUP($A29,'Акция 9'!$F:$F,'Акция 9'!$O:$O,0,0))% -> 0 | AQ29: =AO29/(100%-AP29) -> 0 | AR29: =_xlfn.XLOOKUP($A29,'Акция 10'!$F:$F,'Акция 10'!$L:$L,0,0) -> 0 | AS29: =(_xlfn.XLOOKUP($A29,'Акция 10'!$F:$F,'Акция 10'!$O:$O,0,0))% -> 0 | AT29: =AR29/(100%-AS29) -> 0 | AU29: =_xlfn.XLOOKUP($A29,'Акция 11'!$F:$F,'Акция 11'!$L:$L,0,0) -> 0 | AV29: =(_xlfn.XLOOKUP($A29,'Акция 11'!$F:$F,'Акция 11'!$O:$O,0,0))% -> 0 | AW29: =AU29/(100%-AV29) -> 0 | BA29: =MAX($Q29,$T29,W29,Z29,AC29,AF29,AL29,AO29,AR29,AU29,AX29,AI29) -> 0 | BB29: =IF(BA29=0,0,_xlfn.XLOOKUP($BA29,$Q29:$AZ29,$Q$1:$AZ$1,0,0)) -> 0 | BC29: =_xlfn.XLOOKUP($BB29,$Q$1:$AZ$1,$Q29:$AZ29,0,0) -> 0 | BD29: =IF(BA29=0,0,$BD$3) -> 0 | BE29: =BC29/(100%-BD29) -> 0 | BF29: =_xlfn.XLOOKUP(A29,[1]Юнит!$A:$A,[1]Юнит!$AU:$AU,0) -> 0 | BG29: =P29 -> 0.25419858 | BI29: =MROUND(IF($BH29="*",$BE29,K29),1) -> 856 | BJ29: =IF($BH29="*",$BD29,J29) -> 0.3 | BK29: =MROUND(BI29-BI29*BJ29,1) -> 599 | BL29: =IF(BH29="*",1,0) -> 0 | BM29: =_xlfn.XLOOKUP(A29,'Текущая цена на ВБ'!C:C,'Текущая цена на ВБ'!F:F) -> 252 | BN29: =_xlfn.XLOOKUP(A29,'Текущая цена на ВБ'!C:C,'Текущая цена на ВБ'!H:H) -> 999
A30: =[1]Юнит!A29 -> 419145391 | B30: =[1]Юнит!C29 -> ACRB1MS107WH | C30: =[1]Юнит!D29 -> Мяч с шипами белый 7 см | D30: =[1]Юнит!E29 -> 2044025326637 | E30: 619 | F30: 0.3 | G30: 884 | H30: 0.24701468 | I30: =_xlfn.XLOOKUP(D30,[1]Юнит!$E:$E,[1]Юнит!$AN:$AN) -> 619 | J30: =$J$4 -> 0.3 | K30: =I30/(100%-J28) -> 884.28571 | L30: =_xlfn.XLOOKUP(D30,[1]Юнит!$E:$E,[1]Юнит!$AR:$AR) -> 0.24723535 | M30: =MROUND(O30-O30*N30,1) -> 619 | N30: =_xlfn.XLOOKUP($A30,'Текущая цена на ВБ'!$C:$C,'Текущая цена на ВБ'!$K:$K,0,0)% -> 0.3 | O30: =_xlfn.XLOOKUP($A30,'Текущая цена на ВБ'!$C:$C,'Текущая цена на ВБ'!$I:$I,0,0) -> 884 | P30: =_xlfn.XLOOKUP($A30,[1]Юнит!$A:$A,[1]Юнит!$AJ:$AJ,0) -> 0.24701468 | Q30: =_xlfn.XLOOKUP($A30,'Акция 1'!$F:$F,'Акция 1'!$L:$L,0,0) -> 0 | R30: =(_xlfn.XLOOKUP($A30,'Акция 1'!$F:$F,'Акция 1'!$P:$P,0,0))% -> 0 | S30: =Q30/(100%-R30) -> 0 | T30: =_xlfn.XLOOKUP($A30,'Акция 2'!$F:$F,'Акция 2'!$L:$L,0,0) -> 0 | U30: =(_xlfn.XLOOKUP($A30,'Акция 2'!$F:$F,'Акция 2'!$O:$O,0,0))% -> 0 | V30: =T30/(100%-U30) -> 0 | W30: =_xlfn.XLOOKUP($A30,'Акция 3'!$F:$F,'Акция 3'!$L:$L,0,0) -> 0 | X30: =(_xlfn.XLOOKUP($A30,'Акция 3'!$F:$F,'Акция 3'!$P:$P,0,0))% -> 0 | Y30: =W30/(100%-X30) -> 0 | Z30: =_xlfn.XLOOKUP($A30,'Акция 4'!$F:$F,'Акция 4'!$L:$L,0,0) -> 0 | AA30: =(_xlfn.XLOOKUP($A30,'Акция 4'!$F:$F,'Акция 4'!$P:$P,0,0))% -> 0 | AB30: =Z30/(100%-AA30) -> 0 | AC30: =_xlfn.XLOOKUP($A30,'Акция 5'!$F:$F,'Акция 5'!$L:$L,0,0) -> 0 | AD30: =(_xlfn.XLOOKUP($A30,'Акция 5'!$F:$F,'Акция 5'!O:O,0,0))% -> 0 | AE30: =AC30/(100%-AD30) -> 0 | AF30: =_xlfn.XLOOKUP($A30,'Акция 6'!$F:$F,'Акция 6'!$L:$L,0,0) -> 0 | AG30: =(_xlfn.XLOOKUP($A30,'Акция 6'!$F:$F,'Акция 6'!$O:$O,0,0))% -> 0 | AH30: =AF30/(100%-AG30) -> 0 | AI30: =_xlfn.XLOOKUP($A30,'Акция 7'!$F:$F,'Акция 7'!$L:$L,0,0) -> 0 | AJ30: =(_xlfn.XLOOKUP($A30,'Акция 7'!$F:$F,'Акция 7'!$O:$O,0,0))% -> 0 | AK30: =AI30/(100%-AJ30) -> 0 | AL30: =_xlfn.XLOOKUP($A30,'Акция 8'!$F:$F,'Акция 8'!$L:$L,0,0) -> 0 | AM30: =(_xlfn.XLOOKUP($A30,'Акция 8'!$F:$F,'Акция 8'!$S:$S,0,0))% -> 0 | AN30: =AL30/(100%-AM30) -> 0 | AO30: =_xlfn.XLOOKUP($A30,'Акция 9'!$F:$F,'Акция 9'!$L:$L,0,0) -> 0 | AP30: =(_xlfn.XLOOKUP($A30,'Акция 9'!$F:$F,'Акция 9'!$O:$O,0,0))% -> 0 | AQ30: =AO30/(100%-AP30) -> 0 | AR30: =_xlfn.XLOOKUP($A30,'Акция 10'!$F:$F,'Акция 10'!$L:$L,0,0) -> 0 | AS30: =(_xlfn.XLOOKUP($A30,'Акция 10'!$F:$F,'Акция 10'!$O:$O,0,0))% -> 0 | AT30: =AR30/(100%-AS30) -> 0 | AU30: =_xlfn.XLOOKUP($A30,'Акция 11'!$F:$F,'Акция 11'!$L:$L,0,0) -> 0 | AV30: =(_xlfn.XLOOKUP($A30,'Акция 11'!$F:$F,'Акция 11'!$O:$O,0,0))% -> 0 | AW30: =AU30/(100%-AV30) -> 0 | BA30: =MAX($Q30,$T30,W30,Z30,AC30,AF30,AL30,AO30,AR30,AU30,AX30,AI30) -> 0 | BB30: =IF(BA30=0,0,_xlfn.XLOOKUP($BA30,$Q30:$AZ30,$Q$1:$AZ$1,0,0)) -> 0 | BC30: =_xlfn.XLOOKUP($BB30,$Q$1:$AZ$1,$Q30:$AZ30,0,0) -> 0 | BD30: =IF(BA30=0,0,$BD$3) -> 0 | BE30: =BC30/(100%-BD30) -> 0 | BF30: =_xlfn.XLOOKUP(A30,[1]Юнит!$A:$A,[1]Юнит!$AU:$AU,0) -> 0 | BG30: =P30 -> 0.24701468 | BI30: =MROUND(IF($BH30="*",$BE30,K30),1) -> 884 | BJ30: =IF($BH30="*",$BD30,J30) -> 0.3 | BK30: =MROUND(BI30-BI30*BJ30,1) -> 619 | BL30: =IF(BH30="*",1,0) -> 0 | BM30: =_xlfn.XLOOKUP(A30,'Текущая цена на ВБ'!C:C,'Текущая цена на ВБ'!F:F) -> 298 | BN30: =_xlfn.XLOOKUP(A30,'Текущая цена на ВБ'!C:C,'Текущая цена на ВБ'!H:H) -> 999
A31: =[1]Юнит!A30 -> 419145389 | B31: =[1]Юнит!C30 -> ACRB1MS107PN | C31: =[1]Юнит!D30 -> Мяч с шипами розовый 7 см | D31: =[1]Юнит!E30 -> 2044025316447 | E31: 612 | F31: 0.4 | G31: 1020 | H31: 0.24222939 | I31: =_xlfn.XLOOKUP(D31,[1]Юнит!$E:$E,[1]Юнит!$AN:$AN) -> 619 | J31: =$J$4 -> 0.3 | K31: =I31/(100%-J29) -> 884.28571 | L31: =_xlfn.XLOOKUP(D31,[1]Юнит!$E:$E,[1]Юнит!$AR:$AR) -> 0.25111102 | M31: =MROUND(O31-O31*N31,1) -> 612 | N31: =_xlfn.XLOOKUP($A31,'Текущая цена на ВБ'!$C:$C,'Текущая цена на ВБ'!$K:$K,0,0)% -> 0.4 | O31: =_xlfn.XLOOKUP($A31,'Текущая цена на ВБ'!$C:$C,'Текущая цена на ВБ'!$I:$I,0,0) -> 1020 | P31: =_xlfn.XLOOKUP($A31,[1]Юнит!$A:$A,[1]Юнит!$AJ:$AJ,0) -> 0.24334595 | Q31: =_xlfn.XLOOKUP($A31,'Акция 1'!$F:$F,'Акция 1'!$L:$L,0,0) -> 612 | R31: =(_xlfn.XLOOKUP($A31,'Акция 1'!$F:$F,'Акция 1'!$P:$P,0,0))% -> 0.31 | S31: =Q31/(100%-R31) -> 886.95652 | T31: =_xlfn.XLOOKUP($A31,'Акция 2'!$F:$F,'Акция 2'!$L:$L,0,0) -> 0 | U31: =(_xlfn.XLOOKUP($A31,'Акция 2'!$F:$F,'Акция 2'!$O:$O,0,0))% -> 0 | V31: =T31/(100%-U31) -> 0 | W31: =_xlfn.XLOOKUP($A31,'Акция 3'!$F:$F,'Акция 3'!$L:$L,0,0) -> 433 | X31: =(_xlfn.XLOOKUP($A31,'Акция 3'!$F:$F,'Акция 3'!$P:$P,0,0))% -> 0.51 | Y31: =W31/(100%-X31) -> 883.67347 | Z31: =_xlfn.XLOOKUP($A31,'Акция 4'!$F:$F,'Акция 4'!$L:$L,0,0) -> 0 | AA31: =(_xlfn.XLOOKUP($A31,'Акция 4'!$F:$F,'Акция 4'!$P:$P,0,0))% -> 0 | AB31: =Z31/(100%-AA31) -> 0 | AC31: =_xlfn.XLOOKUP($A31,'Акция 5'!$F:$F,'Акция 5'!$L:$L,0,0) -> 0 | AD31: =(_xlfn.XLOOKUP($A31,'Акция 5'!$F:$F,'Акция 5'!O:O,0,0))% -> 0 | AE31: =AC31/(100%-AD31) -> 0 | AF31: =_xlfn.XLOOKUP($A31,'Акция 6'!$F:$F,'Акция 6'!$L:$L,0,0) -> 0 | AG31: =(_xlfn.XLOOKUP($A31,'Акция 6'!$F:$F,'Акция 6'!$O:$O,0,0))% -> 0 | AH31: =AF31/(100%-AG31) -> 0 | AI31: =_xlfn.XLOOKUP($A31,'Акция 7'!$F:$F,'Акция 7'!$L:$L,0,0) -> 0 | AJ31: =(_xlfn.XLOOKUP($A31,'Акция 7'!$F:$F,'Акция 7'!$O:$O,0,0))% -> 0 | AK31: =AI31/(100%-AJ31) -> 0 | AL31: =_xlfn.XLOOKUP($A31,'Акция 8'!$F:$F,'Акция 8'!$L:$L,0,0) -> 0 | AM31: =(_xlfn.XLOOKUP($A31,'Акция 8'!$F:$F,'Акция 8'!$S:$S,0,0))% -> 0 | AN31: =AL31/(100%-AM31) -> 0 | AO31: =_xlfn.XLOOKUP($A31,'Акция 9'!$F:$F,'Акция 9'!$L:$L,0,0) -> 0 | AP31: =(_xlfn.XLOOKUP($A31,'Акция 9'!$F:$F,'Акция 9'!$O:$O,0,0))% -> 0 | AQ31: =AO31/(100%-AP31) -> 0 | AR31: =_xlfn.XLOOKUP($A31,'Акция 10'!$F:$F,'Акция 10'!$L:$L,0,0) -> 0 | AS31: =(_xlfn.XLOOKUP($A31,'Акция 10'!$F:$F,'Акция 10'!$O:$O,0,0))% -> 0 | AT31: =AR31/(100%-AS31) -> 0 | AU31: =_xlfn.XLOOKUP($A31,'Акция 11'!$F:$F,'Акция 11'!$L:$L,0,0) -> 0 | AV31: =(_xlfn.XLOOKUP($A31,'Акция 11'!$F:$F,'Акция 11'!$O:$O,0,0))% -> 0 | AW31: =AU31/(100%-AV31) -> 0 | BA31: =MAX($Q31,$T31,W31,Z31,AC31,AF31,AL31,AO31,AR31,AU31,AX31,AI31) -> 612 | BB31: =IF(BA31=0,0,_xlfn.XLOOKUP($BA31,$Q31:$AZ31,$Q$1:$AZ$1,0,0)) -> 1 | BC31: =_xlfn.XLOOKUP($BB31,$Q$1:$AZ$1,$Q31:$AZ31,0,0) -> 612 | BD31: =IF(BA31=0,0,$BD$3) -> 0.4 | BE31: =BC31/(100%-BD31) -> 1020 | BF31: =_xlfn.XLOOKUP(A31,[1]Юнит!$A:$A,[1]Юнит!$AU:$AU,0) -> 0.24334595 | BG31: =P31 -> 0.24334595 | BH31: * | BI31: =MROUND(IF($BH31="*",$BE31,K31),1) -> 1020 | BJ31: =IF($BH31="*",$BD31,J31) -> 0.4 | BK31: =MROUND(BI31-BI31*BJ31,1) -> 612 | BL31: =IF(BH31="*",1,0) -> 1 | BM31: =_xlfn.XLOOKUP(A31,'Текущая цена на ВБ'!C:C,'Текущая цена на ВБ'!F:F) -> 118 | BN31: =_xlfn.XLOOKUP(A31,'Текущая цена на ВБ'!C:C,'Текущая цена на ВБ'!H:H) -> 717
A32: =[1]Юнит!A31 -> 419145748 | B32: =[1]Юнит!C31 -> ACRB1MS107BL | C32: =[1]Юнит!D31 -> Мяч с шипами голубой 7 см | D32: =[1]Юнит!E31 -> 2044025338661 | E32: 553 | F32: 0.4 | G32: 922 | H32: 0.20483135 | I32: =_xlfn.XLOOKUP(D32,[1]Юнит!$E:$E,[1]Юнит!$AN:$AN) -> 619 | J32: =$J$4 -> 0.3 | K32: =I32/(100%-J30) -> 884.28571 | L32: =_xlfn.XLOOKUP(D32,[1]Юнит!$E:$E,[1]Юнит!$AR:$AR) -> 0.28462417 | M32: =MROUND(O32-O32*N32,1) -> 553 | N32: =_xlfn.XLOOKUP($A32,'Текущая цена на ВБ'!$C:$C,'Текущая цена на ВБ'!$K:$K,0,0)% -> 0.4 | O32: =_xlfn.XLOOKUP($A32,'Текущая цена на ВБ'!$C:$C,'Текущая цена на ВБ'!$I:$I,0,0) -> 922 | P32: =_xlfn.XLOOKUP($A32,[1]Юнит!$A:$A,[1]Юнит!$AJ:$AJ,0) -> 0.20786038 | Q32: =_xlfn.XLOOKUP($A32,'Акция 1'!$F:$F,'Акция 1'!$L:$L,0,0) -> 553 | R32: =(_xlfn.XLOOKUP($A32,'Акция 1'!$F:$F,'Акция 1'!$P:$P,0,0))% -> 0.41 | S32: =Q32/(100%-R32) -> 937.28814 | T32: =_xlfn.XLOOKUP($A32,'Акция 2'!$F:$F,'Акция 2'!$L:$L,0,0) -> 0 | U32: =(_xlfn.XLOOKUP($A32,'Акция 2'!$F:$F,'Акция 2'!$O:$O,0,0))% -> 0 | V32: =T32/(100%-U32) -> 0 | W32: =_xlfn.XLOOKUP($A32,'Акция 3'!$F:$F,'Акция 3'!$L:$L,0,0) -> 504 | X32: =(_xlfn.XLOOKUP($A32,'Акция 3'!$F:$F,'Акция 3'!$P:$P,0,0))% -> 0.46 | Y32: =W32/(100%-X32) -> 933.33333 | Z32: =_xlfn.XLOOKUP($A32,'Акция 4'!$F:$F,'Акция 4'!$L:$L,0,0) -> 0 | AA32: =(_xlfn.XLOOKUP($A32,'Акция 4'!$F:$F,'Акция 4'!$P:$P,0,0))% -> 0 | AB32: =Z32/(100%-AA32) -> 0 | AC32: =_xlfn.XLOOKUP($A32,'Акция 5'!$F:$F,'Акция 5'!$L:$L,0,0) -> 0 | AD32: =(_xlfn.XLOOKUP($A32,'Акция 5'!$F:$F,'Акция 5'!O:O,0,0))% -> 0 | AE32: =AC32/(100%-AD32) -> 0 | AF32: =_xlfn.XLOOKUP($A32,'Акция 6'!$F:$F,'Акция 6'!$L:$L,0,0) -> 0 | AG32: =(_xlfn.XLOOKUP($A32,'Акция 6'!$F:$F,'Акция 6'!$O:$O,0,0))% -> 0 | AH32: =AF32/(100%-AG32) -> 0 | AI32: =_xlfn.XLOOKUP($A32,'Акция 7'!$F:$F,'Акция 7'!$L:$L,0,0) -> 0 | AJ32: =(_xlfn.XLOOKUP($A32,'Акция 7'!$F:$F,'Акция 7'!$O:$O,0,0))% -> 0 | AK32: =AI32/(100%-AJ32) -> 0 | AL32: =_xlfn.XLOOKUP($A32,'Акция 8'!$F:$F,'Акция 8'!$L:$L,0,0) -> 0 | AM32: =(_xlfn.XLOOKUP($A32,'Акция 8'!$F:$F,'Акция 8'!$S:$S,0,0))% -> 0 | AN32: =AL32/(100%-AM32) -> 0 | AO32: =_xlfn.XLOOKUP($A32,'Акция 9'!$F:$F,'Акция 9'!$L:$L,0,0) -> 0 | AP32: =(_xlfn.XLOOKUP($A32,'Акция 9'!$F:$F,'Акция 9'!$O:$O,0,0))% -> 0 | AQ32: =AO32/(100%-AP32) -> 0 | AR32: =_xlfn.XLOOKUP($A32,'Акция 10'!$F:$F,'Акция 10'!$L:$L,0,0) -> 0 | AS32: =(_xlfn.XLOOKUP($A32,'Акция 10'!$F:$F,'Акция 10'!$O:$O,0,0))% -> 0 | AT32: =AR32/(100%-AS32) -> 0 | AU32: =_xlfn.XLOOKUP($A32,'Акция 11'!$F:$F,'Акция 11'!$L:$L,0,0) -> 0 | AV32: =(_xlfn.XLOOKUP($A32,'Акция 11'!$F:$F,'Акция 11'!$O:$O,0,0))% -> 0 | AW32: =AU32/(100%-AV32) -> 0 | BA32: =MAX($Q32,$T32,W32,Z32,AC32,AF32,AL32,AO32,AR32,AU32,AX32,AI32) -> 553 | BB32: =IF(BA32=0,0,_xlfn.XLOOKUP($BA32,$Q32:$AZ32,$Q$1:$AZ$1,0,0)) -> 1 | BC32: =_xlfn.XLOOKUP($BB32,$Q$1:$AZ$1,$Q32:$AZ32,0,0) -> 553 | BD32: =IF(BA32=0,0,$BD$3) -> 0.4 | BE32: =BC32/(100%-BD32) -> 921.66667 | BF32: =_xlfn.XLOOKUP(A32,[1]Юнит!$A:$A,[1]Юнит!$AU:$AU,0) -> 0.20759921 | BG32: =P32 -> 0.20786038 | BH32: * | BI32: =MROUND(IF($BH32="*",$BE32,K32),1) -> 922 | BJ32: =IF($BH32="*",$BD32,J32) -> 0.4 | BK32: =MROUND(BI32-BI32*BJ32,1) -> 553 | BL32: =IF(BH32="*",1,0) -> 1 | BM32: =_xlfn.XLOOKUP(A32,'Текущая цена на ВБ'!C:C,'Текущая цена на ВБ'!F:F) -> 109 | BN32: =_xlfn.XLOOKUP(A32,'Текущая цена на ВБ'!C:C,'Текущая цена на ВБ'!H:H) -> 999
A33: =[1]Юнит!A32 -> 419141548 | B33: =[1]Юнит!C32 -> ACRB1MS107RJ | C33: =[1]Юнит!D32 -> Мяч с шипами оранжевый 7 см | D33: =[1]Юнит!E32 -> 2044025288003 | E33: 593 | F33: 0.4 | G33: 988 | H33: 0.23223026 | I33: =_xlfn.XLOOKUP(D33,[1]Юнит!$E:$E,[1]Юнит!$AN:$AN) -> 619 | J33: =$J$4 -> 0.3 | K33: =I33/(100%-J31) -> 884.28571 | L33: =_xlfn.XLOOKUP(D33,[1]Юнит!$E:$E,[1]Юнит!$AR:$AR) -> 0.26205409 | M33: =MROUND(O33-O33*N33,1) -> 593 | N33: =_xlfn.XLOOKUP($A33,'Текущая цена на ВБ'!$C:$C,'Текущая цена на ВБ'!$K:$K,0,0)% -> 0.4 | O33: =_xlfn.XLOOKUP($A33,'Текущая цена на ВБ'!$C:$C,'Текущая цена на ВБ'!$I:$I,0,0) -> 988 | P33: =_xlfn.XLOOKUP($A33,[1]Юнит!$A:$A,[1]Юнит!$AJ:$AJ,0) -> 0.23253287 | Q33: =_xlfn.XLOOKUP($A33,'Акция 1'!$F:$F,'Акция 1'!$L:$L,0,0) -> 593 | R33: =(_xlfn.XLOOKUP($A33,'Акция 1'!$F:$F,'Акция 1'!$P:$P,0,0))% -> 0.33 | S33: =Q33/(100%-R33) -> 885.07463 | T33: =_xlfn.XLOOKUP($A33,'Акция 2'!$F:$F,'Акция 2'!$L:$L,0,0) -> 0 | U33: =(_xlfn.XLOOKUP($A33,'Акция 2'!$F:$F,'Акция 2'!$O:$O,0,0))% -> 0 | V33: =T33/(100%-U33) -> 0 | W33: =_xlfn.XLOOKUP($A33,'Акция 3'!$F:$F,'Акция 3'!$L:$L,0,0) -> 420 | X33: =(_xlfn.XLOOKUP($A33,'Акция 3'!$F:$F,'Акция 3'!$P:$P,0,0))% -> 0.53 | Y33: =W33/(100%-X33) -> 893.61702 | Z33: =_xlfn.XLOOKUP($A33,'Акция 4'!$F:$F,'Акция 4'!$L:$L,0,0) -> 0 | AA33: =(_xlfn.XLOOKUP($A33,'Акция 4'!$F:$F,'Акция 4'!$P:$P,0,0))% -> 0 | AB33: =Z33/(100%-AA33) -> 0 | AC33: =_xlfn.XLOOKUP($A33,'Акция 5'!$F:$F,'Акция 5'!$L:$L,0,0) -> 0 | AD33: =(_xlfn.XLOOKUP($A33,'Акция 5'!$F:$F,'Акция 5'!O:O,0,0))% -> 0 | AE33: =AC33/(100%-AD33) -> 0 | AF33: =_xlfn.XLOOKUP($A33,'Акция 6'!$F:$F,'Акция 6'!$L:$L,0,0) -> 0 | AG33: =(_xlfn.XLOOKUP($A33,'Акция 6'!$F:$F,'Акция 6'!$O:$O,0,0))% -> 0 | AH33: =AF33/(100%-AG33) -> 0 | AI33: =_xlfn.XLOOKUP($A33,'Акция 7'!$F:$F,'Акция 7'!$L:$L,0,0) -> 0 | AJ33: =(_xlfn.XLOOKUP($A33,'Акция 7'!$F:$F,'Акция 7'!$O:$O,0,0))% -> 0 | AK33: =AI33/(100%-AJ33) -> 0 | AL33: =_xlfn.XLOOKUP($A33,'Акция 8'!$F:$F,'Акция 8'!$L:$L,0,0) -> 0 | AM33: =(_xlfn.XLOOKUP($A33,'Акция 8'!$F:$F,'Акция 8'!$S:$S,0,0))% -> 0 | AN33: =AL33/(100%-AM33) -> 0 | AO33: =_xlfn.XLOOKUP($A33,'Акция 9'!$F:$F,'Акция 9'!$L:$L,0,0) -> 0 | AP33: =(_xlfn.XLOOKUP($A33,'Акция 9'!$F:$F,'Акция 9'!$O:$O,0,0))% -> 0 | AQ33: =AO33/(100%-AP33) -> 0 | AR33: =_xlfn.XLOOKUP($A33,'Акция 10'!$F:$F,'Акция 10'!$L:$L,0,0) -> 0 | AS33: =(_xlfn.XLOOKUP($A33,'Акция 10'!$F:$F,'Акция 10'!$O:$O,0,0))% -> 0 | AT33: =AR33/(100%-AS33) -> 0 | AU33: =_xlfn.XLOOKUP($A33,'Акция 11'!$F:$F,'Акция 11'!$L:$L,0,0) -> 0 | AV33: =(_xlfn.XLOOKUP($A33,'Акция 11'!$F:$F,'Акция 11'!$O:$O,0,0))% -> 0 | AW33: =AU33/(100%-AV33) -> 0 | BA33: =MAX($Q33,$T33,W33,Z33,AC33,AF33,AL33,AO33,AR33,AU33,AX33,AI33) -> 593 | BB33: =IF(BA33=0,0,_xlfn.XLOOKUP($BA33,$Q33:$AZ33,$Q$1:$AZ$1,0,0)) -> 1 | BC33: =_xlfn.XLOOKUP($BB33,$Q$1:$AZ$1,$Q33:$AZ33,0,0) -> 593 | BD33: =IF(BA33=0,0,$BD$3) -> 0.4 | BE33: =BC33/(100%-BD33) -> 988.33333 | BF33: =_xlfn.XLOOKUP(A33,[1]Юнит!$A:$A,[1]Юнит!$AU:$AU,0) -> 0.2327681 | BG33: =P33 -> 0.23253287 | BH33: * | BI33: =MROUND(IF($BH33="*",$BE33,K33),1) -> 988 | BJ33: =IF($BH33="*",$BD33,J33) -> 0.4 | BK33: =MROUND(BI33-BI33*BJ33,1) -> 593 | BL33: =IF(BH33="*",1,0) -> 1 | BM33: =_xlfn.XLOOKUP(A33,'Текущая цена на ВБ'!C:C,'Текущая цена на ВБ'!F:F) -> 76 | BN33: =_xlfn.XLOOKUP(A33,'Текущая цена на ВБ'!C:C,'Текущая цена на ВБ'!H:H) -> 258
A34: =[1]Юнит!A33 -> 419145985 | B34: =[1]Юнит!C33 -> ACRB1MS107BС | C34: =[1]Юнит!D33 -> Мяч с шипами черный 7 см | D34: =[1]Юнит!E33 -> 2044025344532 | E34: 552 | F34: 0.4 | G34: 920 | H34: 0.1567912 | I34: =_xlfn.XLOOKUP(D34,[1]Юнит!$E:$E,[1]Юнит!$AN:$AN) -> 619 | J34: =$J$4 -> 0.3 | K34: =I34/(100%-J32) -> 884.28571 | L34: =_xlfn.XLOOKUP(D34,[1]Юнит!$E:$E,[1]Юнит!$AR:$AR) -> 0.28530812 | M34: =MROUND(O34-O34*N34,1) -> 552 | N34: =_xlfn.XLOOKUP($A34,'Текущая цена на ВБ'!$C:$C,'Текущая цена на ВБ'!$K:$K,0,0)% -> 0.4 | O34: =_xlfn.XLOOKUP($A34,'Текущая цена на ВБ'!$C:$C,'Текущая цена на ВБ'!$I:$I,0,0) -> 920 | P34: =_xlfn.XLOOKUP($A34,[1]Юнит!$A:$A,[1]Юнит!$AJ:$AJ,0) -> 0.20705747 | Q34: =_xlfn.XLOOKUP($A34,'Акция 1'!$F:$F,'Акция 1'!$L:$L,0,0) -> 552 | R34: =(_xlfn.XLOOKUP($A34,'Акция 1'!$F:$F,'Акция 1'!$P:$P,0,0))% -> 0.4 | S34: =Q34/(100%-R34) -> 920 | T34: =_xlfn.XLOOKUP($A34,'Акция 2'!$F:$F,'Акция 2'!$L:$L,0,0) -> 0 | U34: =(_xlfn.XLOOKUP($A34,'Акция 2'!$F:$F,'Акция 2'!$O:$O,0,0))% -> 0 | V34: =T34/(100%-U34) -> 0 | W34: =_xlfn.XLOOKUP($A34,'Акция 3'!$F:$F,'Акция 3'!$L:$L,0,0) -> 420 | X34: =(_xlfn.XLOOKUP($A34,'Акция 3'!$F:$F,'Акция 3'!$P:$P,0,0))% -> 0.49 | Y34: =W34/(100%-X34) -> 823.52941 | Z34: =_xlfn.XLOOKUP($A34,'Акция 4'!$F:$F,'Акция 4'!$L:$L,0,0) -> 0 | AA34: =(_xlfn.XLOOKUP($A34,'Акция 4'!$F:$F,'Акция 4'!$P:$P,0,0))% -> 0 | AB34: =Z34/(100%-AA34) -> 0 | AC34: =_xlfn.XLOOKUP($A34,'Акция 5'!$F:$F,'Акция 5'!$L:$L,0,0) -> 0 | AD34: =(_xlfn.XLOOKUP($A34,'Акция 5'!$F:$F,'Акция 5'!O:O,0,0))% -> 0 | AE34: =AC34/(100%-AD34) -> 0 | AF34: =_xlfn.XLOOKUP($A34,'Акция 6'!$F:$F,'Акция 6'!$L:$L,0,0) -> 0 | AG34: =(_xlfn.XLOOKUP($A34,'Акция 6'!$F:$F,'Акция 6'!$O:$O,0,0))% -> 0 | AH34: =AF34/(100%-AG34) -> 0 | AI34: =_xlfn.XLOOKUP($A34,'Акция 7'!$F:$F,'Акция 7'!$L:$L,0,0) -> 0 | AJ34: =(_xlfn.XLOOKUP($A34,'Акция 7'!$F:$F,'Акция 7'!$O:$O,0,0))% -> 0 | AK34: =AI34/(100%-AJ34) -> 0 | AL34: =_xlfn.XLOOKUP($A34,'Акция 8'!$F:$F,'Акция 8'!$L:$L,0,0) -> 0 | AM34: =(_xlfn.XLOOKUP($A34,'Акция 8'!$F:$F,'Акция 8'!$S:$S,0,0))% -> 0 | AN34: =AL34/(100%-AM34) -> 0 | AO34: =_xlfn.XLOOKUP($A34,'Акция 9'!$F:$F,'Акция 9'!$L:$L,0,0) -> 0 | AP34: =(_xlfn.XLOOKUP($A34,'Акция 9'!$F:$F,'Акция 9'!$O:$O,0,0))% -> 0 | AQ34: =AO34/(100%-AP34) -> 0 | AR34: =_xlfn.XLOOKUP($A34,'Акция 10'!$F:$F,'Акция 10'!$L:$L,0,0) -> 0 | AS34: =(_xlfn.XLOOKUP($A34,'Акция 10'!$F:$F,'Акция 10'!$O:$O,0,0))% -> 0 | AT34: =AR34/(100%-AS34) -> 0 | AU34: =_xlfn.XLOOKUP($A34,'Акция 11'!$F:$F,'Акция 11'!$L:$L,0,0) -> 0 | AV34: =(_xlfn.XLOOKUP($A34,'Акция 11'!$F:$F,'Акция 11'!$O:$O,0,0))% -> 0 | AW34: =AU34/(100%-AV34) -> 0 | BA34: =MAX($Q34,$T34,W34,Z34,AC34,AF34,AL34,AO34,AR34,AU34,AX34,AI34) -> 552 | BB34: =IF(BA34=0,0,_xlfn.XLOOKUP($BA34,$Q34:$AZ34,$Q$1:$AZ$1,0,0)) -> 1 | BC34: =_xlfn.XLOOKUP($BB34,$Q$1:$AZ$1,$Q34:$AZ34,0,0) -> 552 | BD34: =IF(BA34=0,0,$BD$3) -> 0.4 | BE34: =BC34/(100%-BD34) -> 920 | BF34: =_xlfn.XLOOKUP(A34,[1]Юнит!$A:$A,[1]Юнит!$AU:$AU,0) -> 0.20705747 | BG34: =P34 -> 0.20705747 | BH34: * | BI34: =MROUND(IF($BH34="*",$BE34,K34),1) -> 920 | BJ34: =IF($BH34="*",$BD34,J34) -> 0.4 | BK34: =MROUND(BI34-BI34*BJ34,1) -> 552 | BL34: =IF(BH34="*",1,0) -> 1 | BM34: =_xlfn.XLOOKUP(A34,'Текущая цена на ВБ'!C:C,'Текущая цена на ВБ'!F:F) -> 90 | BN34: =_xlfn.XLOOKUP(A34,'Текущая цена на ВБ'!C:C,'Текущая цена на ВБ'!H:H) -> 999
A35: =[1]Юнит!A34 -> 419145390 | B35: =[1]Юнит!C34 -> ACRB1MS109PN | C35: =[1]Юнит!D34 -> Мяч с шипами розовый 9 см | D35: =[1]Юнит!E34 -> 2044025321588 | E35: 709 | F35: 0.3 | G35: 1013 | H35: 0.24842955 | I35: =_xlfn.XLOOKUP(D35,[1]Юнит!$E:$E,[1]Юнит!$AN:$AN) -> 709 | J35: =$J$4 -> 0.3 | K35: =I35/(100%-J33) -> 1012.8571 | L35: =_xlfn.XLOOKUP(D35,[1]Юнит!$E:$E,[1]Юнит!$AR:$AR) -> 0.24833342 | M35: =MROUND(O35-O35*N35,1) -> 709 | N35: =_xlfn.XLOOKUP($A35,'Текущая цена на ВБ'!$C:$C,'Текущая цена на ВБ'!$K:$K,0,0)% -> 0.3 | O35: =_xlfn.XLOOKUP($A35,'Текущая цена на ВБ'!$C:$C,'Текущая цена на ВБ'!$I:$I,0,0) -> 1013 | P35: =_xlfn.XLOOKUP($A35,[1]Юнит!$A:$A,[1]Юнит!$AJ:$AJ,0) -> 0.24842955 | Q35: =_xlfn.XLOOKUP($A35,'Акция 1'!$F:$F,'Акция 1'!$L:$L,0,0) -> 0 | R35: =(_xlfn.XLOOKUP($A35,'Акция 1'!$F:$F,'Акция 1'!$P:$P,0,0))% -> 0 | S35: =Q35/(100%-R35) -> 0 | T35: =_xlfn.XLOOKUP($A35,'Акция 2'!$F:$F,'Акция 2'!$L:$L,0,0) -> 0 | U35: =(_xlfn.XLOOKUP($A35,'Акция 2'!$F:$F,'Акция 2'!$O:$O,0,0))% -> 0 | V35: =T35/(100%-U35) -> 0 | W35: =_xlfn.XLOOKUP($A35,'Акция 3'!$F:$F,'Акция 3'!$L:$L,0,0) -> 0 | X35: =(_xlfn.XLOOKUP($A35,'Акция 3'!$F:$F,'Акция 3'!$P:$P,0,0))% -> 0 | Y35: =W35/(100%-X35) -> 0 | Z35: =_xlfn.XLOOKUP($A35,'Акция 4'!$F:$F,'Акция 4'!$L:$L,0,0) -> 0 | AA35: =(_xlfn.XLOOKUP($A35,'Акция 4'!$F:$F,'Акция 4'!$P:$P,0,0))% -> 0 | AB35: =Z35/(100%-AA35) -> 0 | AC35: =_xlfn.XLOOKUP($A35,'Акция 5'!$F:$F,'Акция 5'!$L:$L,0,0) -> 0 | AD35: =(_xlfn.XLOOKUP($A35,'Акция 5'!$F:$F,'Акция 5'!O:O,0,0))% -> 0 | AE35: =AC35/(100%-AD35) -> 0 | AF35: =_xlfn.XLOOKUP($A35,'Акция 6'!$F:$F,'Акция 6'!$L:$L,0,0) -> 0 | AG35: =(_xlfn.XLOOKUP($A35,'Акция 6'!$F:$F,'Акция 6'!$O:$O,0,0))% -> 0 | AH35: =AF35/(100%-AG35) -> 0 | AI35: =_xlfn.XLOOKUP($A35,'Акция 7'!$F:$F,'Акция 7'!$L:$L,0,0) -> 0 | AJ35: =(_xlfn.XLOOKUP($A35,'Акция 7'!$F:$F,'Акция 7'!$O:$O,0,0))% -> 0 | AK35: =AI35/(100%-AJ35) -> 0 | AL35: =_xlfn.XLOOKUP($A35,'Акция 8'!$F:$F,'Акция 8'!$L:$L,0,0) -> 0 | AM35: =(_xlfn.XLOOKUP($A35,'Акция 8'!$F:$F,'Акция 8'!$S:$S,0,0))% -> 0 | AN35: =AL35/(100%-AM35) -> 0 | AO35: =_xlfn.XLOOKUP($A35,'Акция 9'!$F:$F,'Акция 9'!$L:$L,0,0) -> 0 | AP35: =(_xlfn.XLOOKUP($A35,'Акция 9'!$F:$F,'Акция 9'!$O:$O,0,0))% -> 0 | AQ35: =AO35/(100%-AP35) -> 0 | AR35: =_xlfn.XLOOKUP($A35,'Акция 10'!$F:$F,'Акция 10'!$L:$L,0,0) -> 0 | AS35: =(_xlfn.XLOOKUP($A35,'Акция 10'!$F:$F,'Акция 10'!$O:$O,0,0))% -> 0 | AT35: =AR35/(100%-AS35) -> 0 | AU35: =_xlfn.XLOOKUP($A35,'Акция 11'!$F:$F,'Акция 11'!$L:$L,0,0) -> 0 | AV35: =(_xlfn.XLOOKUP($A35,'Акция 11'!$F:$F,'Акция 11'!$O:$O,0,0))% -> 0 | AW35: =AU35/(100%-AV35) -> 0 | BA35: =MAX($Q35,$T35,W35,Z35,AC35,AF35,AL35,AO35,AR35,AU35,AX35,AI35) -> 0 | BB35: =IF(BA35=0,0,_xlfn.XLOOKUP($BA35,$Q35:$AZ35,$Q$1:$AZ$1,0,0)) -> 0 | BC35: =_xlfn.XLOOKUP($BB35,$Q$1:$AZ$1,$Q35:$AZ35,0,0) -> 0 | BD35: =IF(BA35=0,0,$BD$3) -> 0 | BE35: =BC35/(100%-BD35) -> 0 | BF35: =_xlfn.XLOOKUP(A35,[1]Юнит!$A:$A,[1]Юнит!$AU:$AU,0) -> 0 | BG35: =P35 -> 0.24842955 | BI35: =MROUND(IF($BH35="*",$BE35,K35),1) -> 1013 | BJ35: =IF($BH35="*",$BD35,J35) -> 0.3 | BK35: =MROUND(BI35-BI35*BJ35,1) -> 709 | BL35: =IF(BH35="*",1,0) -> 0 | BM35: =_xlfn.XLOOKUP(A35,'Текущая цена на ВБ'!C:C,'Текущая цена на ВБ'!F:F) -> 152 | BN35: =_xlfn.XLOOKUP(A35,'Текущая цена на ВБ'!C:C,'Текущая цена на ВБ'!H:H) -> 999
A36: =[1]Юнит!A35 -> 419145749 | B36: =[1]Юнит!C35 -> ACRB1MS109BL | C36: =[1]Юнит!D35 -> Мяч с шипами голубой 9 см | D36: =[1]Юнит!E35 -> 2044025342057 | E36: 502 | F36: 0.4 | G36: 837 | H36: 0.10752793 | I36: =_xlfn.XLOOKUP(D36,[1]Юнит!$E:$E,[1]Юнит!$AN:$AN) -> 709 | J36: =$J$4 -> 0.3 | K36: =I36/(100%-J34) -> 1012.8571 | L36: =_xlfn.XLOOKUP(D36,[1]Юнит!$E:$E,[1]Юнит!$AR:$AR) -> 0.35128732 | M36: =MROUND(O36-O36*N36,1) -> 502 | N36: =_xlfn.XLOOKUP($A36,'Текущая цена на ВБ'!$C:$C,'Текущая цена на ВБ'!$K:$K,0,0)% -> 0.4 | O36: =_xlfn.XLOOKUP($A36,'Текущая цена на ВБ'!$C:$C,'Текущая цена на ВБ'!$I:$I,0,0) -> 837 | P36: =_xlfn.XLOOKUP($A36,[1]Юнит!$A:$A,[1]Юнит!$AJ:$AJ,0) -> 0.11298031 | Q36: =_xlfn.XLOOKUP($A36,'Акция 1'!$F:$F,'Акция 1'!$L:$L,0,0) -> 502 | R36: =(_xlfn.XLOOKUP($A36,'Акция 1'!$F:$F,'Акция 1'!$P:$P,0,0))% -> 0.51 | S36: =Q36/(100%-R36) -> 1024.4898 | T36: =_xlfn.XLOOKUP($A36,'Акция 2'!$F:$F,'Акция 2'!$L:$L,0,0) -> 0 | U36: =(_xlfn.XLOOKUP($A36,'Акция 2'!$F:$F,'Акция 2'!$O:$O,0,0))% -> 0 | V36: =T36/(100%-U36) -> 0 | W36: =_xlfn.XLOOKUP($A36,'Акция 3'!$F:$F,'Акция 3'!$L:$L,0,0) -> 475 | X36: =(_xlfn.XLOOKUP($A36,'Акция 3'!$F:$F,'Акция 3'!$P:$P,0,0))% -> 0.54 | Y36: =W36/(100%-X36) -> 1032.6087 | Z36: =_xlfn.XLOOKUP($A36,'Акция 4'!$F:$F,'Акция 4'!$L:$L,0,0) -> 0 | AA36: =(_xlfn.XLOOKUP($A36,'Акция 4'!$F:$F,'Акция 4'!$P:$P,0,0))% -> 0 | AB36: =Z36/(100%-AA36) -> 0 | AC36: =_xlfn.XLOOKUP($A36,'Акция 5'!$F:$F,'Акция 5'!$L:$L,0,0) -> 0 | AD36: =(_xlfn.XLOOKUP($A36,'Акция 5'!$F:$F,'Акция 5'!O:O,0,0))% -> 0 | AE36: =AC36/(100%-AD36) -> 0 | AF36: =_xlfn.XLOOKUP($A36,'Акция 6'!$F:$F,'Акция 6'!$L:$L,0,0) -> 0 | AG36: =(_xlfn.XLOOKUP($A36,'Акция 6'!$F:$F,'Акция 6'!$O:$O,0,0))% -> 0 | AH36: =AF36/(100%-AG36) -> 0 | AI36: =_xlfn.XLOOKUP($A36,'Акция 7'!$F:$F,'Акция 7'!$L:$L,0,0) -> 0 | AJ36: =(_xlfn.XLOOKUP($A36,'Акция 7'!$F:$F,'Акция 7'!$O:$O,0,0))% -> 0 | AK36: =AI36/(100%-AJ36) -> 0 | AL36: =_xlfn.XLOOKUP($A36,'Акция 8'!$F:$F,'Акция 8'!$L:$L,0,0) -> 0 | AM36: =(_xlfn.XLOOKUP($A36,'Акция 8'!$F:$F,'Акция 8'!$S:$S,0,0))% -> 0 | AN36: =AL36/(100%-AM36) -> 0 | AO36: =_xlfn.XLOOKUP($A36,'Акция 9'!$F:$F,'Акция 9'!$L:$L,0,0) -> 0 | AP36: =(_xlfn.XLOOKUP($A36,'Акция 9'!$F:$F,'Акция 9'!$O:$O,0,0))% -> 0 | AQ36: =AO36/(100%-AP36) -> 0 | AR36: =_xlfn.XLOOKUP($A36,'Акция 10'!$F:$F,'Акция 10'!$L:$L,0,0) -> 0 | AS36: =(_xlfn.XLOOKUP($A36,'Акция 10'!$F:$F,'Акция 10'!$O:$O,0,0))% -> 0 | AT36: =AR36/(100%-AS36) -> 0 | AU36: =_xlfn.XLOOKUP($A36,'Акция 11'!$F:$F,'Акция 11'!$L:$L,0,0) -> 0 | AV36: =(_xlfn.XLOOKUP($A36,'Акция 11'!$F:$F,'Акция 11'!$O:$O,0,0))% -> 0 | AW36: =AU36/(100%-AV36) -> 0 | BA36: =MAX($Q36,$T36,W36,Z36,AC36,AF36,AL36,AO36,AR36,AU36,AX36,AI36) -> 502 | BB36: =IF(BA36=0,0,_xlfn.XLOOKUP($BA36,$Q36:$AZ36,$Q$1:$AZ$1,0,0)) -> 1 | BC36: =_xlfn.XLOOKUP($BB36,$Q$1:$AZ$1,$Q36:$AZ36,0,0) -> 502 | BD36: =IF(BA36=0,0,$BD$3) -> 0.4 | BE36: =BC36/(100%-BD36) -> 836.66667 | BF36: =_xlfn.XLOOKUP(A36,[1]Юнит!$A:$A,[1]Юнит!$AU:$AU,0) -> 0.11265481 | BG36: =P36 -> 0.11298031 | BH36: * | BI36: =MROUND(IF($BH36="*",$BE36,K36),1) -> 837 | BJ36: =IF($BH36="*",$BD36,J36) -> 0.4 | BK36: =MROUND(BI36-BI36*BJ36,1) -> 502 | BL36: =IF(BH36="*",1,0) -> 1 | BM36: =_xlfn.XLOOKUP(A36,'Текущая цена на ВБ'!C:C,'Текущая цена на ВБ'!F:F) -> 106 | BN36: =_xlfn.XLOOKUP(A36,'Текущая цена на ВБ'!C:C,'Текущая цена на ВБ'!H:H) -> 816
A37: =[1]Юнит!A36 -> 419141549 | B37: =[1]Юнит!C36 -> ACRB1MS109RJ | C37: =[1]Юнит!D36 -> Мяч с шипами оранжевый 9 см | D37: =[1]Юнит!E36 -> 2044025291485 | E37: 709 | F37: 0.3 | G37: 1013 | H37: 0.24842955 | I37: =_xlfn.XLOOKUP(D37,[1]Юнит!$E:$E,[1]Юнит!$AN:$AN) -> 709 | J37: =$J$4 -> 0.3 | K37: =I37/(100%-J35) -> 1012.8571 | L37: =_xlfn.XLOOKUP(D37,[1]Юнит!$E:$E,[1]Юнит!$AR:$AR) -> 0.24833342 | M37: =MROUND(O37-O37*N37,1) -> 709 | N37: =_xlfn.XLOOKUP($A37,'Текущая цена на ВБ'!$C:$C,'Текущая цена на ВБ'!$K:$K,0,0)% -> 0.3 | O37: =_xlfn.XLOOKUP($A37,'Текущая цена на ВБ'!$C:$C,'Текущая цена на ВБ'!$I:$I,0,0) -> 1013 | P37: =_xlfn.XLOOKUP($A37,[1]Юнит!$A:$A,[1]Юнит!$AJ:$AJ,0) -> 0.24842955 | Q37: =_xlfn.XLOOKUP($A37,'Акция 1'!$F:$F,'Акция 1'!$L:$L,0,0) -> 0 | R37: =(_xlfn.XLOOKUP($A37,'Акция 1'!$F:$F,'Акция 1'!$P:$P,0,0))% -> 0 | S37: =Q37/(100%-R37) -> 0 | T37: =_xlfn.XLOOKUP($A37,'Акция 2'!$F:$F,'Акция 2'!$L:$L,0,0) -> 0 | U37: =(_xlfn.XLOOKUP($A37,'Акция 2'!$F:$F,'Акция 2'!$O:$O,0,0))% -> 0 | V37: =T37/(100%-U37) -> 0 | W37: =_xlfn.XLOOKUP($A37,'Акция 3'!$F:$F,'Акция 3'!$L:$L,0,0) -> 0 | X37: =(_xlfn.XLOOKUP($A37,'Акция 3'!$F:$F,'Акция 3'!$P:$P,0,0))% -> 0 | Y37: =W37/(100%-X37) -> 0 | Z37: =_xlfn.XLOOKUP($A37,'Акция 4'!$F:$F,'Акция 4'!$L:$L,0,0) -> 0 | AA37: =(_xlfn.XLOOKUP($A37,'Акция 4'!$F:$F,'Акция 4'!$P:$P,0,0))% -> 0 | AB37: =Z37/(100%-AA37) -> 0 | AC37: =_xlfn.XLOOKUP($A37,'Акция 5'!$F:$F,'Акция 5'!$L:$L,0,0) -> 0 | AD37: =(_xlfn.XLOOKUP($A37,'Акция 5'!$F:$F,'Акция 5'!O:O,0,0))% -> 0 | AE37: =AC37/(100%-AD37) -> 0 | AF37: =_xlfn.XLOOKUP($A37,'Акция 6'!$F:$F,'Акция 6'!$L:$L,0,0) -> 0 | AG37: =(_xlfn.XLOOKUP($A37,'Акция 6'!$F:$F,'Акция 6'!$O:$O,0,0))% -> 0 | AH37: =AF37/(100%-AG37) -> 0 | AI37: =_xlfn.XLOOKUP($A37,'Акция 7'!$F:$F,'Акция 7'!$L:$L,0,0) -> 0 | AJ37: =(_xlfn.XLOOKUP($A37,'Акция 7'!$F:$F,'Акция 7'!$O:$O,0,0))% -> 0 | AK37: =AI37/(100%-AJ37) -> 0 | AL37: =_xlfn.XLOOKUP($A37,'Акция 8'!$F:$F,'Акция 8'!$L:$L,0,0) -> 0 | AM37: =(_xlfn.XLOOKUP($A37,'Акция 8'!$F:$F,'Акция 8'!$S:$S,0,0))% -> 0 | AN37: =AL37/(100%-AM37) -> 0 | AO37: =_xlfn.XLOOKUP($A37,'Акция 9'!$F:$F,'Акция 9'!$L:$L,0,0) -> 0 | AP37: =(_xlfn.XLOOKUP($A37,'Акция 9'!$F:$F,'Акция 9'!$O:$O,0,0))% -> 0 | AQ37: =AO37/(100%-AP37) -> 0 | AR37: =_xlfn.XLOOKUP($A37,'Акция 10'!$F:$F,'Акция 10'!$L:$L,0,0) -> 0 | AS37: =(_xlfn.XLOOKUP($A37,'Акция 10'!$F:$F,'Акция 10'!$O:$O,0,0))% -> 0 | AT37: =AR37/(100%-AS37) -> 0 | AU37: =_xlfn.XLOOKUP($A37,'Акция 11'!$F:$F,'Акция 11'!$L:$L,0,0) -> 0 | AV37: =(_xlfn.XLOOKUP($A37,'Акция 11'!$F:$F,'Акция 11'!$O:$O,0,0))% -> 0 | AW37: =AU37/(100%-AV37) -> 0 | BA37: =MAX($Q37,$T37,W37,Z37,AC37,AF37,AL37,AO37,AR37,AU37,AX37,AI37) -> 0 | BB37: =IF(BA37=0,0,_xlfn.XLOOKUP($BA37,$Q37:$AZ37,$Q$1:$AZ$1,0,0)) -> 0 | BC37: =_xlfn.XLOOKUP($BB37,$Q$1:$AZ$1,$Q37:$AZ37,0,0) -> 0 | BD37: =IF(BA37=0,0,$BD$3) -> 0 | BE37: =BC37/(100%-BD37) -> 0 | BF37: =_xlfn.XLOOKUP(A37,[1]Юнит!$A:$A,[1]Юнит!$AU:$AU,0) -> 0 | BG37: =P37 -> 0.24842955 | BI37: =MROUND(IF($BH37="*",$BE37,K37),1) -> 1013 | BJ37: =IF($BH37="*",$BD37,J37) -> 0.3 | BK37: =MROUND(BI37-BI37*BJ37,1) -> 709 | BL37: =IF(BH37="*",1,0) -> 0 | BM37: =_xlfn.XLOOKUP(A37,'Текущая цена на ВБ'!C:C,'Текущая цена на ВБ'!F:F) -> 98 | BN37: =_xlfn.XLOOKUP(A37,'Текущая цена на ВБ'!C:C,'Текущая цена на ВБ'!H:H) -> 339
A38: =[1]Юнит!A37 -> 419145986 | B38: =[1]Юнит!C37 -> ACRB1MS109BС | C38: =[1]Юнит!D37 -> Мяч с шипами черный 9 см | D38: =[1]Юнит!E37 -> 2044025347953 | E38: 681 | F38: 0.4 | G38: 1135 | H38: 0.23370848 | I38: =_xlfn.XLOOKUP(D38,[1]Юнит!$E:$E,[1]Юнит!$AN:$AN) -> 709 | J38: =$J$4 -> 0.3 | K38: =I38/(100%-J36) -> 1012.8571 | L38: =_xlfn.XLOOKUP(D38,[1]Юнит!$E:$E,[1]Юнит!$AR:$AR) -> 0.26231604 | M38: =MROUND(O38-O38*N38,1) -> 681 | N38: =_xlfn.XLOOKUP($A38,'Текущая цена на ВБ'!$C:$C,'Текущая цена на ВБ'!$K:$K,0,0)% -> 0.4 | O38: =_xlfn.XLOOKUP($A38,'Текущая цена на ВБ'!$C:$C,'Текущая цена на ВБ'!$I:$I,0,0) -> 1135 | P38: =_xlfn.XLOOKUP($A38,[1]Юнит!$A:$A,[1]Юнит!$AJ:$AJ,0) -> 0.23486354 | Q38: =_xlfn.XLOOKUP($A38,'Акция 1'!$F:$F,'Акция 1'!$L:$L,0,0) -> 681 | R38: =(_xlfn.XLOOKUP($A38,'Акция 1'!$F:$F,'Акция 1'!$P:$P,0,0))% -> 0.33 | S38: =Q38/(100%-R38) -> 1016.4179 | T38: =_xlfn.XLOOKUP($A38,'Акция 2'!$F:$F,'Акция 2'!$L:$L,0,0) -> 0 | U38: =(_xlfn.XLOOKUP($A38,'Акция 2'!$F:$F,'Акция 2'!$O:$O,0,0))% -> 0 | V38: =T38/(100%-U38) -> 0 | W38: =_xlfn.XLOOKUP($A38,'Акция 3'!$F:$F,'Акция 3'!$L:$L,0,0) -> 481 | X38: =(_xlfn.XLOOKUP($A38,'Акция 3'!$F:$F,'Акция 3'!$P:$P,0,0))% -> 0.53 | Y38: =W38/(100%-X38) -> 1023.4043 | Z38: =_xlfn.XLOOKUP($A38,'Акция 4'!$F:$F,'Акция 4'!$L:$L,0,0) -> 0 | AA38: =(_xlfn.XLOOKUP($A38,'Акция 4'!$F:$F,'Акция 4'!$P:$P,0,0))% -> 0 | AB38: =Z38/(100%-AA38) -> 0 | AC38: =_xlfn.XLOOKUP($A38,'Акция 5'!$F:$F,'Акция 5'!$L:$L,0,0) -> 0 | AD38: =(_xlfn.XLOOKUP($A38,'Акция 5'!$F:$F,'Акция 5'!O:O,0,0))% -> 0 | AE38: =AC38/(100%-AD38) -> 0 | AF38: =_xlfn.XLOOKUP($A38,'Акция 6'!$F:$F,'Акция 6'!$L:$L,0,0) -> 0 | AG38: =(_xlfn.XLOOKUP($A38,'Акция 6'!$F:$F,'Акция 6'!$O:$O,0,0))% -> 0 | AH38: =AF38/(100%-AG38) -> 0 | AI38: =_xlfn.XLOOKUP($A38,'Акция 7'!$F:$F,'Акция 7'!$L:$L,0,0) -> 0 | AJ38: =(_xlfn.XLOOKUP($A38,'Акция 7'!$F:$F,'Акция 7'!$O:$O,0,0))% -> 0 | AK38: =AI38/(100%-AJ38) -> 0 | AL38: =_xlfn.XLOOKUP($A38,'Акция 8'!$F:$F,'Акция 8'!$L:$L,0,0) -> 0 | AM38: =(_xlfn.XLOOKUP($A38,'Акция 8'!$F:$F,'Акция 8'!$S:$S,0,0))% -> 0 | AN38: =AL38/(100%-AM38) -> 0 | AO38: =_xlfn.XLOOKUP($A38,'Акция 9'!$F:$F,'Акция 9'!$L:$L,0,0) -> 0 | AP38: =(_xlfn.XLOOKUP($A38,'Акция 9'!$F:$F,'Акция 9'!$O:$O,0,0))% -> 0 | AQ38: =AO38/(100%-AP38) -> 0 | AR38: =_xlfn.XLOOKUP($A38,'Акция 10'!$F:$F,'Акция 10'!$L:$L,0,0) -> 0 | AS38: =(_xlfn.XLOOKUP($A38,'Акция 10'!$F:$F,'Акция 10'!$O:$O,0,0))% -> 0 | AT38: =AR38/(100%-AS38) -> 0 | AU38: =_xlfn.XLOOKUP($A38,'Акция 11'!$F:$F,'Акция 11'!$L:$L,0,0) -> 0 | AV38: =(_xlfn.XLOOKUP($A38,'Акция 11'!$F:$F,'Акция 11'!$O:$O,0,0))% -> 0 | AW38: =AU38/(100%-AV38) -> 0 | BA38: =MAX($Q38,$T38,W38,Z38,AC38,AF38,AL38,AO38,AR38,AU38,AX38,AI38) -> 681 | BB38: =IF(BA38=0,0,_xlfn.XLOOKUP($BA38,$Q38:$AZ38,$Q$1:$AZ$1,0,0)) -> 1 | BC38: =_xlfn.XLOOKUP($BB38,$Q$1:$AZ$1,$Q38:$AZ38,0,0) -> 681 | BD38: =IF(BA38=0,0,$BD$3) -> 0.4 | BE38: =BC38/(100%-BD38) -> 1135 | BF38: =_xlfn.XLOOKUP(A38,[1]Юнит!$A:$A,[1]Юнит!$AU:$AU,0) -> 0.23486354 | BG38: =P38 -> 0.23486354 | BH38: * | BI38: =MROUND(IF($BH38="*",$BE38,K38),1) -> 1135 | BJ38: =IF($BH38="*",$BD38,J38) -> 0.4 | BK38: =MROUND(BI38-BI38*BJ38,1) -> 681 | BL38: =IF(BH38="*",1,0) -> 1 | BM38: =_xlfn.XLOOKUP(A38,'Текущая цена на ВБ'!C:C,'Текущая цена на ВБ'!F:F) -> 119 | BN38: =_xlfn.XLOOKUP(A38,'Текущая цена на ВБ'!C:C,'Текущая цена на ВБ'!H:H) -> 999
A39: =[1]Юнит!A38 -> 419146579 | B39: =[1]Юнит!C38 -> ACRB1MS109LI | C39: =[1]Юнит!D38 -> Мяч с шипами фиолетовый 9 см | D39: =[1]Юнит!E38 -> 2044025354937 | E39: 702 | F39: 0.4 | G39: 1170 | H39: 0.24366476 | I39: =_xlfn.XLOOKUP(D39,[1]Юнит!$E:$E,[1]Юнит!$AN:$AN) -> 709 | J39: =$J$4 -> 0.3 | K39: =I39/(100%-J37) -> 1012.8571 | L39: =_xlfn.XLOOKUP(D39,[1]Юнит!$E:$E,[1]Юнит!$AR:$AR) -> 0.25186639 | M39: =MROUND(O39-O39*N39,1) -> 702 | N39: =_xlfn.XLOOKUP($A39,'Текущая цена на ВБ'!$C:$C,'Текущая цена на ВБ'!$K:$K,0,0)% -> 0.4 | O39: =_xlfn.XLOOKUP($A39,'Текущая цена на ВБ'!$C:$C,'Текущая цена на ВБ'!$I:$I,0,0) -> 1170 | P39: =_xlfn.XLOOKUP($A39,[1]Юнит!$A:$A,[1]Юнит!$AJ:$AJ,0) -> 0.24510438 | Q39: =_xlfn.XLOOKUP($A39,'Акция 1'!$F:$F,'Акция 1'!$L:$L,0,0) -> 702 | R39: =(_xlfn.XLOOKUP($A39,'Акция 1'!$F:$F,'Акция 1'!$P:$P,0,0))% -> 0.31 | S39: =Q39/(100%-R39) -> 1017.3913 | T39: =_xlfn.XLOOKUP($A39,'Акция 2'!$F:$F,'Акция 2'!$L:$L,0,0) -> 0 | U39: =(_xlfn.XLOOKUP($A39,'Акция 2'!$F:$F,'Акция 2'!$O:$O,0,0))% -> 0 | V39: =T39/(100%-U39) -> 0 | W39: =_xlfn.XLOOKUP($A39,'Акция 3'!$F:$F,'Акция 3'!$L:$L,0,0) -> 481 | X39: =(_xlfn.XLOOKUP($A39,'Акция 3'!$F:$F,'Акция 3'!$P:$P,0,0))% -> 0.53 | Y39: =W39/(100%-X39) -> 1023.4043 | Z39: =_xlfn.XLOOKUP($A39,'Акция 4'!$F:$F,'Акция 4'!$L:$L,0,0) -> 0 | AA39: =(_xlfn.XLOOKUP($A39,'Акция 4'!$F:$F,'Акция 4'!$P:$P,0,0))% -> 0 | AB39: =Z39/(100%-AA39) -> 0 | AC39: =_xlfn.XLOOKUP($A39,'Акция 5'!$F:$F,'Акция 5'!$L:$L,0,0) -> 0 | AD39: =(_xlfn.XLOOKUP($A39,'Акция 5'!$F:$F,'Акция 5'!O:O,0,0))% -> 0 | AE39: =AC39/(100%-AD39) -> 0 | AF39: =_xlfn.XLOOKUP($A39,'Акция 6'!$F:$F,'Акция 6'!$L:$L,0,0) -> 0 | AG39: =(_xlfn.XLOOKUP($A39,'Акция 6'!$F:$F,'Акция 6'!$O:$O,0,0))% -> 0 | AH39: =AF39/(100%-AG39) -> 0 | AI39: =_xlfn.XLOOKUP($A39,'Акция 7'!$F:$F,'Акция 7'!$L:$L,0,0) -> 0 | AJ39: =(_xlfn.XLOOKUP($A39,'Акция 7'!$F:$F,'Акция 7'!$O:$O,0,0))% -> 0 | AK39: =AI39/(100%-AJ39) -> 0 | AL39: =_xlfn.XLOOKUP($A39,'Акция 8'!$F:$F,'Акция 8'!$L:$L,0,0) -> 0 | AM39: =(_xlfn.XLOOKUP($A39,'Акция 8'!$F:$F,'Акция 8'!$S:$S,0,0))% -> 0 | AN39: =AL39/(100%-AM39) -> 0 | AO39: =_xlfn.XLOOKUP($A39,'Акция 9'!$F:$F,'Акция 9'!$L:$L,0,0) -> 0 | AP39: =(_xlfn.XLOOKUP($A39,'Акция 9'!$F:$F,'Акция 9'!$O:$O,0,0))% -> 0 | AQ39: =AO39/(100%-AP39) -> 0 | AR39: =_xlfn.XLOOKUP($A39,'Акция 10'!$F:$F,'Акция 10'!$L:$L,0,0) -> 0 | AS39: =(_xlfn.XLOOKUP($A39,'Акция 10'!$F:$F,'Акция 10'!$O:$O,0,0))% -> 0 | AT39: =AR39/(100%-AS39) -> 0 | AU39: =_xlfn.XLOOKUP($A39,'Акция 11'!$F:$F,'Акция 11'!$L:$L,0,0) -> 0 | AV39: =(_xlfn.XLOOKUP($A39,'Акция 11'!$F:$F,'Акция 11'!$O:$O,0,0))% -> 0 | AW39: =AU39/(100%-AV39) -> 0 | BA39: =MAX($Q39,$T39,W39,Z39,AC39,AF39,AL39,AO39,AR39,AU39,AX39,AI39) -> 702 | BB39: =IF(BA39=0,0,_xlfn.XLOOKUP($BA39,$Q39:$AZ39,$Q$1:$AZ$1,0,0)) -> 1 | BC39: =_xlfn.XLOOKUP($BB39,$Q$1:$AZ$1,$Q39:$AZ39,0,0) -> 702 | BD39: =IF(BA39=0,0,$BD$3) -> 0.4 | BE39: =BC39/(100%-BD39) -> 1170 | BF39: =_xlfn.XLOOKUP(A39,[1]Юнит!$A:$A,[1]Юнит!$AU:$AU,0) -> 0.24510438 | BG39: =P39 -> 0.24510438 | BH39: * | BI39: =MROUND(IF($BH39="*",$BE39,K39),1) -> 1170 | BJ39: =IF($BH39="*",$BD39,J39) -> 0.4 | BK39: =MROUND(BI39-BI39*BJ39,1) -> 702 | BL39: =IF(BH39="*",1,0) -> 1 | BM39: =_xlfn.XLOOKUP(A39,'Текущая цена на ВБ'!C:C,'Текущая цена на ВБ'!F:F) -> 120 | BN39: =_xlfn.XLOOKUP(A39,'Текущая цена на ВБ'!C:C,'Текущая цена на ВБ'!H:H) -> 999
A40: =[1]Юнит!A39 -> 340734340 | B40: =[1]Юнит!C39 -> ACRB1MS103PN | C40: =[1]Юнит!D39 -> Мяч гладкий розовый | D40: =[1]Юнит!E39 -> 2042985583893 | E40: 513 | F40: 0.4 | G40: 855 | H40: 0.13158205 | I40: =_xlfn.XLOOKUP(D40,[1]Юнит!$E:$E,[1]Юнит!$AN:$AN) -> 519 | J40: =$J$4 -> 0.3 | K40: =I40/(100%-J38) -> 741.42857 | L40: =_xlfn.XLOOKUP(D40,[1]Юнит!$E:$E,[1]Юнит!$AR:$AR) -> 0.14228054 | M40: =MROUND(O40-O40*N40,1) -> 513 | N40: =_xlfn.XLOOKUP($A40,'Текущая цена на ВБ'!$C:$C,'Текущая цена на ВБ'!$K:$K,0,0)% -> 0.4 | O40: =_xlfn.XLOOKUP($A40,'Текущая цена на ВБ'!$C:$C,'Текущая цена на ВБ'!$I:$I,0,0) -> 855 | P40: =_xlfn.XLOOKUP($A40,[1]Юнит!$A:$A,[1]Юнит!$AJ:$AJ,0) -> 0.13306745 | Q40: =_xlfn.XLOOKUP($A40,'Акция 1'!$F:$F,'Акция 1'!$L:$L,0,0) -> 513 | R40: =(_xlfn.XLOOKUP($A40,'Акция 1'!$F:$F,'Акция 1'!$P:$P,0,0))% -> 0.31 | S40: =Q40/(100%-R40) -> 743.47826 | T40: =_xlfn.XLOOKUP($A40,'Акция 2'!$F:$F,'Акция 2'!$L:$L,0,0) -> 0 | U40: =(_xlfn.XLOOKUP($A40,'Акция 2'!$F:$F,'Акция 2'!$O:$O,0,0))% -> 0 | V40: =T40/(100%-U40) -> 0 | W40: =_xlfn.XLOOKUP($A40,'Акция 3'!$F:$F,'Акция 3'!$L:$L,0,0) -> 351 | X40: =(_xlfn.XLOOKUP($A40,'Акция 3'!$F:$F,'Акция 3'!$P:$P,0,0))% -> 0.53 | Y40: =W40/(100%-X40) -> 746.80851 | Z40: =_xlfn.XLOOKUP($A40,'Акция 4'!$F:$F,'Акция 4'!$L:$L,0,0) -> 0 | AA40: =(_xlfn.XLOOKUP($A40,'Акция 4'!$F:$F,'Акция 4'!$P:$P,0,0))% -> 0 | AB40: =Z40/(100%-AA40) -> 0 | AC40: =_xlfn.XLOOKUP($A40,'Акция 5'!$F:$F,'Акция 5'!$L:$L,0,0) -> 0 | AD40: =(_xlfn.XLOOKUP($A40,'Акция 5'!$F:$F,'Акция 5'!O:O,0,0))% -> 0 | AE40: =AC40/(100%-AD40) -> 0 | AF40: =_xlfn.XLOOKUP($A40,'Акция 6'!$F:$F,'Акция 6'!$L:$L,0,0) -> 0 | AG40: =(_xlfn.XLOOKUP($A40,'Акция 6'!$F:$F,'Акция 6'!$O:$O,0,0))% -> 0 | AH40: =AF40/(100%-AG40) -> 0 | AI40: =_xlfn.XLOOKUP($A40,'Акция 7'!$F:$F,'Акция 7'!$L:$L,0,0) -> 0 | AJ40: =(_xlfn.XLOOKUP($A40,'Акция 7'!$F:$F,'Акция 7'!$O:$O,0,0))% -> 0 | AK40: =AI40/(100%-AJ40) -> 0 | AL40: =_xlfn.XLOOKUP($A40,'Акция 8'!$F:$F,'Акция 8'!$L:$L,0,0) -> 0 | AM40: =(_xlfn.XLOOKUP($A40,'Акция 8'!$F:$F,'Акция 8'!$S:$S,0,0))% -> 0 | AN40: =AL40/(100%-AM40) -> 0 | AO40: =_xlfn.XLOOKUP($A40,'Акция 9'!$F:$F,'Акция 9'!$L:$L,0,0) -> 0 | AP40: =(_xlfn.XLOOKUP($A40,'Акция 9'!$F:$F,'Акция 9'!$O:$O,0,0))% -> 0 | AQ40: =AO40/(100%-AP40) -> 0 | AR40: =_xlfn.XLOOKUP($A40,'Акция 10'!$F:$F,'Акция 10'!$L:$L,0,0) -> 0 | AS40: =(_xlfn.XLOOKUP($A40,'Акция 10'!$F:$F,'Акция 10'!$O:$O,0,0))% -> 0 | AT40: =AR40/(100%-AS40) -> 0 | AU40: =_xlfn.XLOOKUP($A40,'Акция 11'!$F:$F,'Акция 11'!$L:$L,0,0) -> 0 | AV40: =(_xlfn.XLOOKUP($A40,'Акция 11'!$F:$F,'Акция 11'!$O:$O,0,0))% -> 0 | AW40: =AU40/(100%-AV40) -> 0 | BA40: =MAX($Q40,$T40,W40,Z40,AC40,AF40,AL40,AO40,AR40,AU40,AX40,AI40) -> 513 | BB40: =IF(BA40=0,0,_xlfn.XLOOKUP($BA40,$Q40:$AZ40,$Q$1:$AZ$1,0,0)) -> 1 | BC40: =_xlfn.XLOOKUP($BB40,$Q$1:$AZ$1,$Q40:$AZ40,0,0) -> 513 | BD40: =IF(BA40=0,0,$BD$3) -> 0.4 | BE40: =BC40/(100%-BD40) -> 855 | BF40: =_xlfn.XLOOKUP(A40,[1]Юнит!$A:$A,[1]Юнит!$AU:$AU,0) -> 0.13306745 | BG40: =P40 -> 0.13306745 | BH40: * | BI40: =MROUND(IF($BH40="*",$BE40,K40),1) -> 855 | BJ40: =IF($BH40="*",$BD40,J40) -> 0.4 | BK40: =MROUND(BI40-BI40*BJ40,1) -> 513 | BL40: =IF(BH40="*",1,0) -> 1 | BM40: =_xlfn.XLOOKUP(A40,'Текущая цена на ВБ'!C:C,'Текущая цена на ВБ'!F:F) -> 4 | BN40: =_xlfn.XLOOKUP(A40,'Текущая цена на ВБ'!C:C,'Текущая цена на ВБ'!H:H) -> 999
A41: =[1]Юнит!A40 -> 340741532 | B41: =[1]Юнит!C40 -> ACRB1MS103BL | C41: =[1]Юнит!D40 -> Мяч гладкий голубой | D41: =[1]Юнит!E40 -> 2042986356632 | E41: 513 | F41: 0.4 | G41: 855 | H41: 0.13158205 | I41: =_xlfn.XLOOKUP(D41,[1]Юнит!$E:$E,[1]Юнит!$AN:$AN) -> 519 | J41: =$J$4 -> 0.3 | K41: =I41/(100%-J39) -> 741.42857 | L41: =_xlfn.XLOOKUP(D41,[1]Юнит!$E:$E,[1]Юнит!$AR:$AR) -> 0.14228054 | M41: =MROUND(O41-O41*N41,1) -> 513 | N41: =_xlfn.XLOOKUP($A41,'Текущая цена на ВБ'!$C:$C,'Текущая цена на ВБ'!$K:$K,0,0)% -> 0.4 | O41: =_xlfn.XLOOKUP($A41,'Текущая цена на ВБ'!$C:$C,'Текущая цена на ВБ'!$I:$I,0,0) -> 855 | P41: =_xlfn.XLOOKUP($A41,[1]Юнит!$A:$A,[1]Юнит!$AJ:$AJ,0) -> 0.13306745 | Q41: =_xlfn.XLOOKUP($A41,'Акция 1'!$F:$F,'Акция 1'!$L:$L,0,0) -> 513 | R41: =(_xlfn.XLOOKUP($A41,'Акция 1'!$F:$F,'Акция 1'!$P:$P,0,0))% -> 0.31 | S41: =Q41/(100%-R41) -> 743.47826 | T41: =_xlfn.XLOOKUP($A41,'Акция 2'!$F:$F,'Акция 2'!$L:$L,0,0) -> 0 | U41: =(_xlfn.XLOOKUP($A41,'Акция 2'!$F:$F,'Акция 2'!$O:$O,0,0))% -> 0 | V41: =T41/(100%-U41) -> 0 | W41: =_xlfn.XLOOKUP($A41,'Акция 3'!$F:$F,'Акция 3'!$L:$L,0,0) -> 351 | X41: =(_xlfn.XLOOKUP($A41,'Акция 3'!$F:$F,'Акция 3'!$P:$P,0,0))% -> 0.53 | Y41: =W41/(100%-X41) -> 746.80851 | Z41: =_xlfn.XLOOKUP($A41,'Акция 4'!$F:$F,'Акция 4'!$L:$L,0,0) -> 0 | AA41: =(_xlfn.XLOOKUP($A41,'Акция 4'!$F:$F,'Акция 4'!$P:$P,0,0))% -> 0 | AB41: =Z41/(100%-AA41) -> 0 | AC41: =_xlfn.XLOOKUP($A41,'Акция 5'!$F:$F,'Акция 5'!$L:$L,0,0) -> 0 | AD41: =(_xlfn.XLOOKUP($A41,'Акция 5'!$F:$F,'Акция 5'!O:O,0,0))% -> 0 | AE41: =AC41/(100%-AD41) -> 0 | AF41: =_xlfn.XLOOKUP($A41,'Акция 6'!$F:$F,'Акция 6'!$L:$L,0,0) -> 0 | AG41: =(_xlfn.XLOOKUP($A41,'Акция 6'!$F:$F,'Акция 6'!$O:$O,0,0))% -> 0 | AH41: =AF41/(100%-AG41) -> 0 | AI41: =_xlfn.XLOOKUP($A41,'Акция 7'!$F:$F,'Акция 7'!$L:$L,0,0) -> 0 | AJ41: =(_xlfn.XLOOKUP($A41,'Акция 7'!$F:$F,'Акция 7'!$O:$O,0,0))% -> 0 | AK41: =AI41/(100%-AJ41) -> 0 | AL41: =_xlfn.XLOOKUP($A41,'Акция 8'!$F:$F,'Акция 8'!$L:$L,0,0) -> 0 | AM41: =(_xlfn.XLOOKUP($A41,'Акция 8'!$F:$F,'Акция 8'!$S:$S,0,0))% -> 0 | AN41: =AL41/(100%-AM41) -> 0 | AO41: =_xlfn.XLOOKUP($A41,'Акция 9'!$F:$F,'Акция 9'!$L:$L,0,0) -> 0 | AP41: =(_xlfn.XLOOKUP($A41,'Акция 9'!$F:$F,'Акция 9'!$O:$O,0,0))% -> 0 | AQ41: =AO41/(100%-AP41) -> 0 | AR41: =_xlfn.XLOOKUP($A41,'Акция 10'!$F:$F,'Акция 10'!$L:$L,0,0) -> 0 | AS41: =(_xlfn.XLOOKUP($A41,'Акция 10'!$F:$F,'Акция 10'!$O:$O,0,0))% -> 0 | AT41: =AR41/(100%-AS41) -> 0 | AU41: =_xlfn.XLOOKUP($A41,'Акция 11'!$F:$F,'Акция 11'!$L:$L,0,0) -> 0 | AV41: =(_xlfn.XLOOKUP($A41,'Акция 11'!$F:$F,'Акция 11'!$O:$O,0,0))% -> 0 | AW41: =AU41/(100%-AV41) -> 0 | BA41: =MAX($Q41,$T41,W41,Z41,AC41,AF41,AL41,AO41,AR41,AU41,AX41,AI41) -> 513 | BB41: =IF(BA41=0,0,_xlfn.XLOOKUP($BA41,$Q41:$AZ41,$Q$1:$AZ$1,0,0)) -> 1 | BC41: =_xlfn.XLOOKUP($BB41,$Q$1:$AZ$1,$Q41:$AZ41,0,0) -> 513 | BD41: =IF(BA41=0,0,$BD$3) -> 0.4 | BE41: =BC41/(100%-BD41) -> 855 | BF41: =_xlfn.XLOOKUP(A41,[1]Юнит!$A:$A,[1]Юнит!$AU:$AU,0) -> 0.13306745 | BG41: =P41 -> 0.13306745 | BH41: * | BI41: =MROUND(IF($BH41="*",$BE41,K41),1) -> 855 | BJ41: =IF($BH41="*",$BD41,J41) -> 0.4 | BK41: =MROUND(BI41-BI41*BJ41,1) -> 513 | BL41: =IF(BH41="*",1,0) -> 1 | BM41: =_xlfn.XLOOKUP(A41,'Текущая цена на ВБ'!C:C,'Текущая цена на ВБ'!F:F) -> 60 | BN41: =_xlfn.XLOOKUP(A41,'Текущая цена на ВБ'!C:C,'Текущая цена на ВБ'!H:H) -> 999
A42: =[1]Юнит!A41 -> 340743352 | B42: =[1]Юнит!C41 -> ACRB1MS103LI | C42: =[1]Юнит!D41 -> Мяч гладкий сиреневый | D42: =[1]Юнит!E41 -> 2042986372359 | E42: 513 | F42: 0.4 | G42: 855 | H42: 0.13158205 | I42: =_xlfn.XLOOKUP(D42,[1]Юнит!$E:$E,[1]Юнит!$AN:$AN) -> 519 | J42: =$J$4 -> 0.3 | K42: =I42/(100%-J40) -> 741.42857 | L42: =_xlfn.XLOOKUP(D42,[1]Юнит!$E:$E,[1]Юнит!$AR:$AR) -> 0.14228054 | M42: =MROUND(O42-O42*N42,1) -> 513 | N42: =_xlfn.XLOOKUP($A42,'Текущая цена на ВБ'!$C:$C,'Текущая цена на ВБ'!$K:$K,0,0)% -> 0.4 | O42: =_xlfn.XLOOKUP($A42,'Текущая цена на ВБ'!$C:$C,'Текущая цена на ВБ'!$I:$I,0,0) -> 855 | P42: =_xlfn.XLOOKUP($A42,[1]Юнит!$A:$A,[1]Юнит!$AJ:$AJ,0) -> 0.13306745 | Q42: =_xlfn.XLOOKUP($A42,'Акция 1'!$F:$F,'Акция 1'!$L:$L,0,0) -> 513 | R42: =(_xlfn.XLOOKUP($A42,'Акция 1'!$F:$F,'Акция 1'!$P:$P,0,0))% -> 0.31 | S42: =Q42/(100%-R42) -> 743.47826 | T42: =_xlfn.XLOOKUP($A42,'Акция 2'!$F:$F,'Акция 2'!$L:$L,0,0) -> 0 | U42: =(_xlfn.XLOOKUP($A42,'Акция 2'!$F:$F,'Акция 2'!$O:$O,0,0))% -> 0 | V42: =T42/(100%-U42) -> 0 | W42: =_xlfn.XLOOKUP($A42,'Акция 3'!$F:$F,'Акция 3'!$L:$L,0,0) -> 351 | X42: =(_xlfn.XLOOKUP($A42,'Акция 3'!$F:$F,'Акция 3'!$P:$P,0,0))% -> 0.53 | Y42: =W42/(100%-X42) -> 746.80851 | Z42: =_xlfn.XLOOKUP($A42,'Акция 4'!$F:$F,'Акция 4'!$L:$L,0,0) -> 0 | AA42: =(_xlfn.XLOOKUP($A42,'Акция 4'!$F:$F,'Акция 4'!$P:$P,0,0))% -> 0 | AB42: =Z42/(100%-AA42) -> 0 | AC42: =_xlfn.XLOOKUP($A42,'Акция 5'!$F:$F,'Акция 5'!$L:$L,0,0) -> 0 | AD42: =(_xlfn.XLOOKUP($A42,'Акция 5'!$F:$F,'Акция 5'!O:O,0,0))% -> 0 | AE42: =AC42/(100%-AD42) -> 0 | AF42: =_xlfn.XLOOKUP($A42,'Акция 6'!$F:$F,'Акция 6'!$L:$L,0,0) -> 0 | AG42: =(_xlfn.XLOOKUP($A42,'Акция 6'!$F:$F,'Акция 6'!$O:$O,0,0))% -> 0 | AH42: =AF42/(100%-AG42) -> 0 | AI42: =_xlfn.XLOOKUP($A42,'Акция 7'!$F:$F,'Акция 7'!$L:$L,0,0) -> 0 | AJ42: =(_xlfn.XLOOKUP($A42,'Акция 7'!$F:$F,'Акция 7'!$O:$O,0,0))% -> 0 | AK42: =AI42/(100%-AJ42) -> 0 | AL42: =_xlfn.XLOOKUP($A42,'Акция 8'!$F:$F,'Акция 8'!$L:$L,0,0) -> 0 | AM42: =(_xlfn.XLOOKUP($A42,'Акция 8'!$F:$F,'Акция 8'!$S:$S,0,0))% -> 0 | AN42: =AL42/(100%-AM42) -> 0 | AO42: =_xlfn.XLOOKUP($A42,'Акция 9'!$F:$F,'Акция 9'!$L:$L,0,0) -> 0 | AP42: =(_xlfn.XLOOKUP($A42,'Акция 9'!$F:$F,'Акция 9'!$O:$O,0,0))% -> 0 | AQ42: =AO42/(100%-AP42) -> 0 | AR42: =_xlfn.XLOOKUP($A42,'Акция 10'!$F:$F,'Акция 10'!$L:$L,0,0) -> 0 | AS42: =(_xlfn.XLOOKUP($A42,'Акция 10'!$F:$F,'Акция 10'!$O:$O,0,0))% -> 0 | AT42: =AR42/(100%-AS42) -> 0 | AU42: =_xlfn.XLOOKUP($A42,'Акция 11'!$F:$F,'Акция 11'!$L:$L,0,0) -> 0 | AV42: =(_xlfn.XLOOKUP($A42,'Акция 11'!$F:$F,'Акция 11'!$O:$O,0,0))% -> 0 | AW42: =AU42/(100%-AV42) -> 0 | BA42: =MAX($Q42,$T42,W42,Z42,AC42,AF42,AL42,AO42,AR42,AU42,AX42,AI42) -> 513 | BB42: =IF(BA42=0,0,_xlfn.XLOOKUP($BA42,$Q42:$AZ42,$Q$1:$AZ$1,0,0)) -> 1 | BC42: =_xlfn.XLOOKUP($BB42,$Q$1:$AZ$1,$Q42:$AZ42,0,0) -> 513 | BD42: =IF(BA42=0,0,$BD$3) -> 0.4 | BE42: =BC42/(100%-BD42) -> 855 | BF42: =_xlfn.XLOOKUP(A42,[1]Юнит!$A:$A,[1]Юнит!$AU:$AU,0) -> 0.13306745 | BG42: =P42 -> 0.13306745 | BH42: * | BI42: =MROUND(IF($BH42="*",$BE42,K42),1) -> 855 | BJ42: =IF($BH42="*",$BD42,J42) -> 0.4 | BK42: =MROUND(BI42-BI42*BJ42,1) -> 513 | BL42: =IF(BH42="*",1,0) -> 1 | BM42: =_xlfn.XLOOKUP(A42,'Текущая цена на ВБ'!C:C,'Текущая цена на ВБ'!F:F) -> 27 | BN42: =_xlfn.XLOOKUP(A42,'Текущая цена на ВБ'!C:C,'Текущая цена на ВБ'!H:H) -> 216
A43: =[1]Юнит!A42 -> 340743911 | B43: =[1]Юнит!C42 -> ACRB1MS103RJ | C43: =[1]Юнит!D42 -> Мяч гладкий оранжевый | D43: =[1]Юнит!E42 -> 2042986377583 | E43: 508 | F43: 0.4 | G43: 847 | H43: 0.12304425 | I43: =_xlfn.XLOOKUP(D43,[1]Юнит!$E:$E,[1]Юнит!$AN:$AN) -> 519 | J43: =$J$4 -> 0.3 | K43: =I43/(100%-J41) -> 741.42857 | L43: =_xlfn.XLOOKUP(D43,[1]Юнит!$E:$E,[1]Юнит!$AR:$AR) -> 0.14361665 | M43: =MROUND(O43-O43*N43,1) -> 508 | N43: =_xlfn.XLOOKUP($A43,'Текущая цена на ВБ'!$C:$C,'Текущая цена на ВБ'!$K:$K,0,0)% -> 0.4 | O43: =_xlfn.XLOOKUP($A43,'Текущая цена на ВБ'!$C:$C,'Текущая цена на ВБ'!$I:$I,0,0) -> 847 | P43: =_xlfn.XLOOKUP($A43,[1]Юнит!$A:$A,[1]Юнит!$AJ:$AJ,0) -> 0.12690484 | Q43: =_xlfn.XLOOKUP($A43,'Акция 1'!$F:$F,'Акция 1'!$L:$L,0,0) -> 508 | R43: =(_xlfn.XLOOKUP($A43,'Акция 1'!$F:$F,'Акция 1'!$P:$P,0,0))% -> 0.32 | S43: =Q43/(100%-R43) -> 747.05882 | T43: =_xlfn.XLOOKUP($A43,'Акция 2'!$F:$F,'Акция 2'!$L:$L,0,0) -> 0 | U43: =(_xlfn.XLOOKUP($A43,'Акция 2'!$F:$F,'Акция 2'!$O:$O,0,0))% -> 0 | V43: =T43/(100%-U43) -> 0 | W43: =_xlfn.XLOOKUP($A43,'Акция 3'!$F:$F,'Акция 3'!$L:$L,0,0) -> 363 | X43: =(_xlfn.XLOOKUP($A43,'Акция 3'!$F:$F,'Акция 3'!$P:$P,0,0))% -> 0.51 | Y43: =W43/(100%-X43) -> 740.81633 | Z43: =_xlfn.XLOOKUP($A43,'Акция 4'!$F:$F,'Акция 4'!$L:$L,0,0) -> 0 | AA43: =(_xlfn.XLOOKUP($A43,'Акция 4'!$F:$F,'Акция 4'!$P:$P,0,0))% -> 0 | AB43: =Z43/(100%-AA43) -> 0 | AC43: =_xlfn.XLOOKUP($A43,'Акция 5'!$F:$F,'Акция 5'!$L:$L,0,0) -> 0 | AD43: =(_xlfn.XLOOKUP($A43,'Акция 5'!$F:$F,'Акция 5'!O:O,0,0))% -> 0 | AE43: =AC43/(100%-AD43) -> 0 | AF43: =_xlfn.XLOOKUP($A43,'Акция 6'!$F:$F,'Акция 6'!$L:$L,0,0) -> 0 | AG43: =(_xlfn.XLOOKUP($A43,'Акция 6'!$F:$F,'Акция 6'!$O:$O,0,0))% -> 0 | AH43: =AF43/(100%-AG43) -> 0 | AI43: =_xlfn.XLOOKUP($A43,'Акция 7'!$F:$F,'Акция 7'!$L:$L,0,0) -> 0 | AJ43: =(_xlfn.XLOOKUP($A43,'Акция 7'!$F:$F,'Акция 7'!$O:$O,0,0))% -> 0 | AK43: =AI43/(100%-AJ43) -> 0 | AL43: =_xlfn.XLOOKUP($A43,'Акция 8'!$F:$F,'Акция 8'!$L:$L,0,0) -> 0 | AM43: =(_xlfn.XLOOKUP($A43,'Акция 8'!$F:$F,'Акция 8'!$S:$S,0,0))% -> 0 | AN43: =AL43/(100%-AM43) -> 0 | AO43: =_xlfn.XLOOKUP($A43,'Акция 9'!$F:$F,'Акция 9'!$L:$L,0,0) -> 0 | AP43: =(_xlfn.XLOOKUP($A43,'Акция 9'!$F:$F,'Акция 9'!$O:$O,0,0))% -> 0 | AQ43: =AO43/(100%-AP43) -> 0 | AR43: =_xlfn.XLOOKUP($A43,'Акция 10'!$F:$F,'Акция 10'!$L:$L,0,0) -> 0 | AS43: =(_xlfn.XLOOKUP($A43,'Акция 10'!$F:$F,'Акция 10'!$O:$O,0,0))% -> 0 | AT43: =AR43/(100%-AS43) -> 0 | AU43: =_xlfn.XLOOKUP($A43,'Акция 11'!$F:$F,'Акция 11'!$L:$L,0,0) -> 0 | AV43: =(_xlfn.XLOOKUP($A43,'Акция 11'!$F:$F,'Акция 11'!$O:$O,0,0))% -> 0 | AW43: =AU43/(100%-AV43) -> 0 | BA43: =MAX($Q43,$T43,W43,Z43,AC43,AF43,AL43,AO43,AR43,AU43,AX43,AI43) -> 508 | BB43: =IF(BA43=0,0,_xlfn.XLOOKUP($BA43,$Q43:$AZ43,$Q$1:$AZ$1,0,0)) -> 1 | BC43: =_xlfn.XLOOKUP($BB43,$Q$1:$AZ$1,$Q43:$AZ43,0,0) -> 508 | BD43: =IF(BA43=0,0,$BD$3) -> 0.4 | BE43: =BC43/(100%-BD43) -> 846.66667 | BF43: =_xlfn.XLOOKUP(A43,[1]Юнит!$A:$A,[1]Юнит!$AU:$AU,0) -> 0.12658866 | BG43: =P43 -> 0.12690484 | BH43: * | BI43: =MROUND(IF($BH43="*",$BE43,K43),1) -> 847 | BJ43: =IF($BH43="*",$BD43,J43) -> 0.4 | BK43: =MROUND(BI43-BI43*BJ43,1) -> 508 | BL43: =IF(BH43="*",1,0) -> 1 | BM43: =_xlfn.XLOOKUP(A43,'Текущая цена на ВБ'!C:C,'Текущая цена на ВБ'!F:F) -> 13 | BN43: =_xlfn.XLOOKUP(A43,'Текущая цена на ВБ'!C:C,'Текущая цена на ВБ'!H:H) -> 416
A44: =[1]Юнит!A43 -> 820643010 | B44: =[1]Юнит!C43 -> ACRB3FR101CL | C44: =[1]Юнит!D43 -> Набор эластичных лент 3 шт. в мешке | D44: =[1]Юнит!E43 -> 2048933027488 | E44: 1483 | F44: 0.4 | G44: 2472 | H44: 0.093054805 | I44: =_xlfn.XLOOKUP(D44,[1]Юнит!$E:$E,[1]Юнит!$AN:$AN) -> 1499 | J44: =$J$4 -> 0.3 | K44: =I44/(100%-J42) -> 2141.4286 | L44: =_xlfn.XLOOKUP(D44,[1]Юнит!$E:$E,[1]Юнит!$AR:$AR) -> 0.17880592 | M44: =MROUND(O44-O44*N44,1) -> 1483 | N44: =_xlfn.XLOOKUP($A44,'Текущая цена на ВБ'!$C:$C,'Текущая цена на ВБ'!$K:$K,0,0)% -> 0.4 | O44: =_xlfn.XLOOKUP($A44,'Текущая цена на ВБ'!$C:$C,'Текущая цена на ВБ'!$I:$I,0,0) -> 2472 | P44: =_xlfn.XLOOKUP($A44,[1]Юнит!$A:$A,[1]Юнит!$AJ:$AJ,0) -> 0.17080372 | Q44: =_xlfn.XLOOKUP($A44,'Акция 1'!$F:$F,'Акция 1'!$L:$L,0,0) -> 1483 | R44: =(_xlfn.XLOOKUP($A44,'Акция 1'!$F:$F,'Акция 1'!$P:$P,0,0))% -> 0.41 | S44: =Q44/(100%-R44) -> 2513.5593 | T44: =_xlfn.XLOOKUP($A44,'Акция 2'!$F:$F,'Акция 2'!$L:$L,0,0) -> 0 | U44: =(_xlfn.XLOOKUP($A44,'Акция 2'!$F:$F,'Акция 2'!$O:$O,0,0))% -> 0 | V44: =T44/(100%-U44) -> 0 | W44: =_xlfn.XLOOKUP($A44,'Акция 3'!$F:$F,'Акция 3'!$L:$L,0,0) -> 1043 | X44: =(_xlfn.XLOOKUP($A44,'Акция 3'!$F:$F,'Акция 3'!$P:$P,0,0))% -> 0.52 | Y44: =W44/(100%-X44) -> 2172.9167 | Z44: =_xlfn.XLOOKUP($A44,'Акция 4'!$F:$F,'Акция 4'!$L:$L,0,0) -> 1265 | AA44: =(_xlfn.XLOOKUP($A44,'Акция 4'!$F:$F,'Акция 4'!$P:$P,0,0))% -> 0.41 | AB44: =Z44/(100%-AA44) -> 2144.0678 | AC44: =_xlfn.XLOOKUP($A44,'Акция 5'!$F:$F,'Акция 5'!$L:$L,0,0) -> 0 | AD44: =(_xlfn.XLOOKUP($A44,'Акция 5'!$F:$F,'Акция 5'!O:O,0,0))% -> 0 | AE44: =AC44/(100%-AD44) -> 0 | AF44: =_xlfn.XLOOKUP($A44,'Акция 6'!$F:$F,'Акция 6'!$L:$L,0,0) -> 0 | AG44: =(_xlfn.XLOOKUP($A44,'Акция 6'!$F:$F,'Акция 6'!$O:$O,0,0))% -> 0 | AH44: =AF44/(100%-AG44) -> 0 | AI44: =_xlfn.XLOOKUP($A44,'Акция 7'!$F:$F,'Акция 7'!$L:$L,0,0) -> 0 | AJ44: =(_xlfn.XLOOKUP($A44,'Акция 7'!$F:$F,'Акция 7'!$O:$O,0,0))% -> 0 | AK44: =AI44/(100%-AJ44) -> 0 | AL44: =_xlfn.XLOOKUP($A44,'Акция 8'!$F:$F,'Акция 8'!$L:$L,0,0) -> 0 | AM44: =(_xlfn.XLOOKUP($A44,'Акция 8'!$F:$F,'Акция 8'!$S:$S,0,0))% -> 0 | AN44: =AL44/(100%-AM44) -> 0 | AO44: =_xlfn.XLOOKUP($A44,'Акция 9'!$F:$F,'Акция 9'!$L:$L,0,0) -> 0 | AP44: =(_xlfn.XLOOKUP($A44,'Акция 9'!$F:$F,'Акция 9'!$O:$O,0,0))% -> 0 | AQ44: =AO44/(100%-AP44) -> 0 | AR44: =_xlfn.XLOOKUP($A44,'Акция 10'!$F:$F,'Акция 10'!$L:$L,0,0) -> 0 | AS44: =(_xlfn.XLOOKUP($A44,'Акция 10'!$F:$F,'Акция 10'!$O:$O,0,0))% -> 0 | AT44: =AR44/(100%-AS44) -> 0 | AU44: =_xlfn.XLOOKUP($A44,'Акция 11'!$F:$F,'Акция 11'!$L:$L,0,0) -> 0 | AV44: =(_xlfn.XLOOKUP($A44,'Акция 11'!$F:$F,'Акция 11'!$O:$O,0,0))% -> 0 | AW44: =AU44/(100%-AV44) -> 0 | BA44: =MAX($Q44,$T44,W44,Z44,AC44,AF44,AL44,AO44,AR44,AU44,AX44,AI44) -> 1483 | BB44: =IF(BA44=0,0,_xlfn.XLOOKUP($BA44,$Q44:$AZ44,$Q$1:$AZ$1,0,0)) -> 1 | BC44: =_xlfn.XLOOKUP($BB44,$Q$1:$AZ$1,$Q44:$AZ44,0,0) -> 1483 | BD44: =IF(BA44=0,0,$BD$3) -> 0.4 | BE44: =BC44/(100%-BD44) -> 2471.6667 | BF44: =_xlfn.XLOOKUP(A44,[1]Юнит!$A:$A,[1]Юнит!$AU:$AU,0) -> 0.17070133 | BG44: =P44 -> 0.17080372 | BH44: * | BI44: =MROUND(IF($BH44="*",$BE44,K44),1) -> 2472 | BJ44: =IF($BH44="*",$BD44,J44) -> 0.4 | BK44: =MROUND(BI44-BI44*BJ44,1) -> 1483 | BL44: =IF(BH44="*",1,0) -> 1 | BM44: =_xlfn.XLOOKUP(A44,'Текущая цена на ВБ'!C:C,'Текущая цена на ВБ'!F:F) -> 89 | BN44: =_xlfn.XLOOKUP(A44,'Текущая цена на ВБ'!C:C,'Текущая цена на ВБ'!H:H) -> 520
A45: =[1]Юнит!A44 -> 550539998 | B45: =[1]Юнит!C44 -> ACRB5FR200CL | C45: =[1]Юнит!D44 -> Набор эластичных лент 5 шт. в мешке | D45: =[1]Юнит!E44 -> 2046392546618 | E45: 1624 | F45: 0.4 | G45: 2707 | H45: 0.16697511 | I45: =_xlfn.XLOOKUP(D45,[1]Юнит!$E:$E,[1]Юнит!$AN:$AN) -> 1379 | J45: =$J$4 -> 0.3 | K45: =I45/(100%-J43) -> 1970 | L45: =_xlfn.XLOOKUP(D45,[1]Юнит!$E:$E,[1]Юнит!$AR:$AR) -> 0.11341953 | M45: =MROUND(O45-O45*N45,1) -> 1624 | N45: =_xlfn.XLOOKUP($A45,'Текущая цена на ВБ'!$C:$C,'Текущая цена на ВБ'!$K:$K,0,0)% -> 0.4 | O45: =_xlfn.XLOOKUP($A45,'Текущая цена на ВБ'!$C:$C,'Текущая цена на ВБ'!$I:$I,0,0) -> 2707 | P45: =_xlfn.XLOOKUP($A45,[1]Юнит!$A:$A,[1]Юнит!$AJ:$AJ,0) -> 0.23669593 | Q45: =_xlfn.XLOOKUP($A45,'Акция 1'!$F:$F,'Акция 1'!$L:$L,0,0) -> 1624 | R45: =(_xlfn.XLOOKUP($A45,'Акция 1'!$F:$F,'Акция 1'!$P:$P,0,0))% -> 0.46 | S45: =Q45/(100%-R45) -> 3007.4074 | T45: =_xlfn.XLOOKUP($A45,'Акция 2'!$F:$F,'Акция 2'!$L:$L,0,0) -> 0 | U45: =(_xlfn.XLOOKUP($A45,'Акция 2'!$F:$F,'Акция 2'!$O:$O,0,0))% -> 0 | V45: =T45/(100%-U45) -> 0 | W45: =_xlfn.XLOOKUP($A45,'Акция 3'!$F:$F,'Акция 3'!$L:$L,0,0) -> 1440 | X45: =(_xlfn.XLOOKUP($A45,'Акция 3'!$F:$F,'Акция 3'!$P:$P,0,0))% -> 0.46 | Y45: =W45/(100%-X45) -> 2666.6667 | Z45: =_xlfn.XLOOKUP($A45,'Акция 4'!$F:$F,'Акция 4'!$L:$L,0,0) -> 1387 | AA45: =(_xlfn.XLOOKUP($A45,'Акция 4'!$F:$F,'Акция 4'!$P:$P,0,0))% -> 0.46 | AB45: =Z45/(100%-AA45) -> 2568.5185 | AC45: =_xlfn.XLOOKUP($A45,'Акция 5'!$F:$F,'Акция 5'!$L:$L,0,0) -> 0 | AD45: =(_xlfn.XLOOKUP($A45,'Акция 5'!$F:$F,'Акция 5'!O:O,0,0))% -> 0 | AE45: =AC45/(100%-AD45) -> 0 | AF45: =_xlfn.XLOOKUP($A45,'Акция 6'!$F:$F,'Акция 6'!$L:$L,0,0) -> 0 | AG45: =(_xlfn.XLOOKUP($A45,'Акция 6'!$F:$F,'Акция 6'!$O:$O,0,0))% -> 0 | AH45: =AF45/(100%-AG45) -> 0 | AI45: =_xlfn.XLOOKUP($A45,'Акция 7'!$F:$F,'Акция 7'!$L:$L,0,0) -> 0 | AJ45: =(_xlfn.XLOOKUP($A45,'Акция 7'!$F:$F,'Акция 7'!$O:$O,0,0))% -> 0 | AK45: =AI45/(100%-AJ45) -> 0 | AL45: =_xlfn.XLOOKUP($A45,'Акция 8'!$F:$F,'Акция 8'!$L:$L,0,0) -> 0 | AM45: =(_xlfn.XLOOKUP($A45,'Акция 8'!$F:$F,'Акция 8'!$S:$S,0,0))% -> 0 | AN45: =AL45/(100%-AM45) -> 0 | AO45: =_xlfn.XLOOKUP($A45,'Акция 9'!$F:$F,'Акция 9'!$L:$L,0,0) -> 0 | AP45: =(_xlfn.XLOOKUP($A45,'Акция 9'!$F:$F,'Акция 9'!$O:$O,0,0))% -> 0 | AQ45: =AO45/(100%-AP45) -> 0 | AR45: =_xlfn.XLOOKUP($A45,'Акция 10'!$F:$F,'Акция 10'!$L:$L,0,0) -> 0 | AS45: =(_xlfn.XLOOKUP($A45,'Акция 10'!$F:$F,'Акция 10'!$O:$O,0,0))% -> 0 | AT45: =AR45/(100%-AS45) -> 0 | AU45: =_xlfn.XLOOKUP($A45,'Акция 11'!$F:$F,'Акция 11'!$L:$L,0,0) -> 0 | AV45: =(_xlfn.XLOOKUP($A45,'Акция 11'!$F:$F,'Акция 11'!$O:$O,0,0))% -> 0 | AW45: =AU45/(100%-AV45) -> 0 | BA45: =MAX($Q45,$T45,W45,Z45,AC45,AF45,AL45,AO45,AR45,AU45,AX45,AI45) -> 1624 | BB45: =IF(BA45=0,0,_xlfn.XLOOKUP($BA45,$Q45:$AZ45,$Q$1:$AZ$1,0,0)) -> 1 | BC45: =_xlfn.XLOOKUP($BB45,$Q$1:$AZ$1,$Q45:$AZ45,0,0) -> 1624 | BD45: =IF(BA45=0,0,$BD$3) -> 0.4 | BE45: =BC45/(100%-BD45) -> 2706.6667 | BF45: =_xlfn.XLOOKUP(A45,[1]Юнит!$A:$A,[1]Юнит!$AU:$AU,0) -> 0.23661055 | BG45: =P45 -> 0.23669593 | BH45: * | BI45: =MROUND(IF($BH45="*",$BE45,K45),1) -> 2707 | BJ45: =IF($BH45="*",$BD45,J45) -> 0.4 | BK45: =MROUND(BI45-BI45*BJ45,1) -> 1624 | BL45: =IF(BH45="*",1,0) -> 1 | BM45: =_xlfn.XLOOKUP(A45,'Текущая цена на ВБ'!C:C,'Текущая цена на ВБ'!F:F) -> 59 | BN45: =_xlfn.XLOOKUP(A45,'Текущая цена на ВБ'!C:C,'Текущая цена на ВБ'!H:H) -> 999
A46: =[1]Юнит!A45 -> 550539999 | B46: =[1]Юнит!C45 -> ACRB4FR300CL | C46: =[1]Юнит!D45 -> Набор эластичных лент 4 шт. | D46: =[1]Юнит!E45 -> 2046392546632 | E46: 999 | F46: 0.4 | G46: 1665 | H46: 0.069034456 | I46: =_xlfn.XLOOKUP(D46,[1]Юнит!$E:$E,[1]Юнит!$AN:$AN) -> 1019 | J46: =$J$4 -> 0.3 | K46: =I46/(100%-J44) -> 1455.7143 | L46: =_xlfn.XLOOKUP(D46,[1]Юнит!$E:$E,[1]Юнит!$AR:$AR) -> 0.13772601 | M46: =MROUND(O46-O46*N46,1) -> 999 | N46: =_xlfn.XLOOKUP($A46,'Текущая цена на ВБ'!$C:$C,'Текущая цена на ВБ'!$K:$K,0,0)% -> 0.4 | O46: =_xlfn.XLOOKUP($A46,'Текущая цена на ВБ'!$C:$C,'Текущая цена на ВБ'!$I:$I,0,0) -> 1665 | P46: =_xlfn.XLOOKUP($A46,[1]Юнит!$A:$A,[1]Юнит!$AJ:$AJ,0) -> 0.12186466 | Q46: =_xlfn.XLOOKUP($A46,'Акция 1'!$F:$F,'Акция 1'!$L:$L,0,0) -> 999 | R46: =(_xlfn.XLOOKUP($A46,'Акция 1'!$F:$F,'Акция 1'!$P:$P,0,0))% -> 0.38 | S46: =Q46/(100%-R46) -> 1611.2903 | T46: =_xlfn.XLOOKUP($A46,'Акция 2'!$F:$F,'Акция 2'!$L:$L,0,0) -> 0 | U46: =(_xlfn.XLOOKUP($A46,'Акция 2'!$F:$F,'Акция 2'!$O:$O,0,0))% -> 0 | V46: =T46/(100%-U46) -> 0 | W46: =_xlfn.XLOOKUP($A46,'Акция 3'!$F:$F,'Акция 3'!$L:$L,0,0) -> 750 | X46: =(_xlfn.XLOOKUP($A46,'Акция 3'!$F:$F,'Акция 3'!$P:$P,0,0))% -> 0.49 | Y46: =W46/(100%-X46) -> 1470.5882 | Z46: =_xlfn.XLOOKUP($A46,'Акция 4'!$F:$F,'Акция 4'!$L:$L,0,0) -> 910 | AA46: =(_xlfn.XLOOKUP($A46,'Акция 4'!$F:$F,'Акция 4'!$P:$P,0,0))% -> 0.38 | AB46: =Z46/(100%-AA46) -> 1467.7419 | AC46: =_xlfn.XLOOKUP($A46,'Акция 5'!$F:$F,'Акция 5'!$L:$L,0,0) -> 0 | AD46: =(_xlfn.XLOOKUP($A46,'Акция 5'!$F:$F,'Акция 5'!O:O,0,0))% -> 0 | AE46: =AC46/(100%-AD46) -> 0 | AF46: =_xlfn.XLOOKUP($A46,'Акция 6'!$F:$F,'Акция 6'!$L:$L,0,0) -> 0 | AG46: =(_xlfn.XLOOKUP($A46,'Акция 6'!$F:$F,'Акция 6'!$O:$O,0,0))% -> 0 | AH46: =AF46/(100%-AG46) -> 0 | AI46: =_xlfn.XLOOKUP($A46,'Акция 7'!$F:$F,'Акция 7'!$L:$L,0,0) -> 0 | AJ46: =(_xlfn.XLOOKUP($A46,'Акция 7'!$F:$F,'Акция 7'!$O:$O,0,0))% -> 0 | AK46: =AI46/(100%-AJ46) -> 0 | AL46: =_xlfn.XLOOKUP($A46,'Акция 8'!$F:$F,'Акция 8'!$L:$L,0,0) -> 0 | AM46: =(_xlfn.XLOOKUP($A46,'Акция 8'!$F:$F,'Акция 8'!$S:$S,0,0))% -> 0 | AN46: =AL46/(100%-AM46) -> 0 | AO46: =_xlfn.XLOOKUP($A46,'Акция 9'!$F:$F,'Акция 9'!$L:$L,0,0) -> 0 | AP46: =(_xlfn.XLOOKUP($A46,'Акция 9'!$F:$F,'Акция 9'!$O:$O,0,0))% -> 0 | AQ46: =AO46/(100%-AP46) -> 0 | AR46: =_xlfn.XLOOKUP($A46,'Акция 10'!$F:$F,'Акция 10'!$L:$L,0,0) -> 0 | AS46: =(_xlfn.XLOOKUP($A46,'Акция 10'!$F:$F,'Акция 10'!$O:$O,0,0))% -> 0 | AT46: =AR46/(100%-AS46) -> 0 | AU46: =_xlfn.XLOOKUP($A46,'Акция 11'!$F:$F,'Акция 11'!$L:$L,0,0) -> 0 | AV46: =(_xlfn.XLOOKUP($A46,'Акция 11'!$F:$F,'Акция 11'!$O:$O,0,0))% -> 0 | AW46: =AU46/(100%-AV46) -> 0 | BA46: =MAX($Q46,$T46,W46,Z46,AC46,AF46,AL46,AO46,AR46,AU46,AX46,AI46) -> 999 | BB46: =IF(BA46=0,0,_xlfn.XLOOKUP($BA46,$Q46:$AZ46,$Q$1:$AZ$1,0,0)) -> 1 | BC46: =_xlfn.XLOOKUP($BB46,$Q$1:$AZ$1,$Q46:$AZ46,0,0) -> 999 | BD46: =IF(BA46=0,0,$BD$3) -> 0.4 | BE46: =BC46/(100%-BD46) -> 1665 | BF46: =_xlfn.XLOOKUP(A46,[1]Юнит!$A:$A,[1]Юнит!$AU:$AU,0) -> 0.12186466 | BG46: =P46 -> 0.12186466 | BH46: * | BI46: =MROUND(IF($BH46="*",$BE46,K46),1) -> 1665 | BJ46: =IF($BH46="*",$BD46,J46) -> 0.4 | BK46: =MROUND(BI46-BI46*BJ46,1) -> 999 | BL46: =IF(BH46="*",1,0) -> 1 | BM46: =_xlfn.XLOOKUP(A46,'Текущая цена на ВБ'!C:C,'Текущая цена на ВБ'!F:F) -> 40 | BN46: =_xlfn.XLOOKUP(A46,'Текущая цена на ВБ'!C:C,'Текущая цена на ВБ'!H:H) -> 999
A47: =[1]Юнит!A46 -> 550540000 | B47: =[1]Юнит!C46 -> ACRB5FR400CL | C47: =[1]Юнит!D46 -> Набор эластичных лент 5 шт. | D47: =[1]Юнит!E46 -> 2046392546656 | E47: 749 | F47: 0.3 | G47: 1070 | H47: 0.38109853 | I47: =_xlfn.XLOOKUP(D47,[1]Юнит!$E:$E,[1]Юнит!$AN:$AN) -> 0 | J47: =$J$4 -> 0.3 | K47: =I47/(100%-J45) -> 0 | L47: =_xlfn.XLOOKUP(D47,[1]Юнит!$E:$E,[1]Юнит!$AR:$AR) -> #DIV/0! | M47: =MROUND(O47-O47*N47,1) -> 749 | N47: =_xlfn.XLOOKUP($A47,'Текущая цена на ВБ'!$C:$C,'Текущая цена на ВБ'!$K:$K,0,0)% -> 0.3 | O47: =_xlfn.XLOOKUP($A47,'Текущая цена на ВБ'!$C:$C,'Текущая цена на ВБ'!$I:$I,0,0) -> 1070 | P47: =_xlfn.XLOOKUP($A47,[1]Юнит!$A:$A,[1]Юнит!$AJ:$AJ,0) -> 0.38109853 | Q47: =_xlfn.XLOOKUP($A47,'Акция 1'!$F:$F,'Акция 1'!$L:$L,0,0) -> 0 | R47: =(_xlfn.XLOOKUP($A47,'Акция 1'!$F:$F,'Акция 1'!$P:$P,0,0))% -> 0 | S47: =Q47/(100%-R47) -> 0 | T47: =_xlfn.XLOOKUP($A47,'Акция 2'!$F:$F,'Акция 2'!$L:$L,0,0) -> 0 | U47: =(_xlfn.XLOOKUP($A47,'Акция 2'!$F:$F,'Акция 2'!$O:$O,0,0))% -> 0 | V47: =T47/(100%-U47) -> 0 | W47: =_xlfn.XLOOKUP($A47,'Акция 3'!$F:$F,'Акция 3'!$L:$L,0,0) -> 0 | X47: =(_xlfn.XLOOKUP($A47,'Акция 3'!$F:$F,'Акция 3'!$P:$P,0,0))% -> 0 | Y47: =W47/(100%-X47) -> 0 | Z47: =_xlfn.XLOOKUP($A47,'Акция 4'!$F:$F,'Акция 4'!$L:$L,0,0) -> 0 | AA47: =(_xlfn.XLOOKUP($A47,'Акция 4'!$F:$F,'Акция 4'!$P:$P,0,0))% -> 0 | AB47: =Z47/(100%-AA47) -> 0 | AC47: =_xlfn.XLOOKUP($A47,'Акция 5'!$F:$F,'Акция 5'!$L:$L,0,0) -> 0 | AD47: =(_xlfn.XLOOKUP($A47,'Акция 5'!$F:$F,'Акция 5'!O:O,0,0))% -> 0 | AE47: =AC47/(100%-AD47) -> 0 | AF47: =_xlfn.XLOOKUP($A47,'Акция 6'!$F:$F,'Акция 6'!$L:$L,0,0) -> 0 | AG47: =(_xlfn.XLOOKUP($A47,'Акция 6'!$F:$F,'Акция 6'!$O:$O,0,0))% -> 0 | AH47: =AF47/(100%-AG47) -> 0 | AI47: =_xlfn.XLOOKUP($A47,'Акция 7'!$F:$F,'Акция 7'!$L:$L,0,0) -> 0 | AJ47: =(_xlfn.XLOOKUP($A47,'Акция 7'!$F:$F,'Акция 7'!$O:$O,0,0))% -> 0 | AK47: =AI47/(100%-AJ47) -> 0 | AL47: =_xlfn.XLOOKUP($A47,'Акция 8'!$F:$F,'Акция 8'!$L:$L,0,0) -> 0 | AM47: =(_xlfn.XLOOKUP($A47,'Акция 8'!$F:$F,'Акция 8'!$S:$S,0,0))% -> 0 | AN47: =AL47/(100%-AM47) -> 0 | AO47: =_xlfn.XLOOKUP($A47,'Акция 9'!$F:$F,'Акция 9'!$L:$L,0,0) -> 0 | AP47: =(_xlfn.XLOOKUP($A47,'Акция 9'!$F:$F,'Акция 9'!$O:$O,0,0))% -> 0 | AQ47: =AO47/(100%-AP47) -> 0 | AR47: =_xlfn.XLOOKUP($A47,'Акция 10'!$F:$F,'Акция 10'!$L:$L,0,0) -> 0 | AS47: =(_xlfn.XLOOKUP($A47,'Акция 10'!$F:$F,'Акция 10'!$O:$O,0,0))% -> 0 | AT47: =AR47/(100%-AS47) -> 0 | AU47: =_xlfn.XLOOKUP($A47,'Акция 11'!$F:$F,'Акция 11'!$L:$L,0,0) -> 0 | AV47: =(_xlfn.XLOOKUP($A47,'Акция 11'!$F:$F,'Акция 11'!$O:$O,0,0))% -> 0 | AW47: =AU47/(100%-AV47) -> 0 | BA47: =MAX($Q47,$T47,W47,Z47,AC47,AF47,AL47,AO47,AR47,AU47,AX47,AI47) -> 0 | BB47: =IF(BA47=0,0,_xlfn.XLOOKUP($BA47,$Q47:$AZ47,$Q$1:$AZ$1,0,0)) -> 0 | BC47: =_xlfn.XLOOKUP($BB47,$Q$1:$AZ$1,$Q47:$AZ47,0,0) -> 0 | BD47: =IF(BA47=0,0,$BD$3) -> 0 | BE47: =BC47/(100%-BD47) -> 0 | BF47: =_xlfn.XLOOKUP(A47,[1]Юнит!$A:$A,[1]Юнит!$AU:$AU,0) -> 0 | BG47: =P47 -> 0.38109853 | BI47: =MROUND(IF($BH47="*",$BE47,K47),1) -> 0 | BJ47: =IF($BH47="*",$BD47,J47) -> 0.3 | BK47: =MROUND(BI47-BI47*BJ47,1) -> 0 | BL47: =IF(BH47="*",1,0) -> 0 | BM47: =_xlfn.XLOOKUP(A47,'Текущая цена на ВБ'!C:C,'Текущая цена на ВБ'!F:F) | BN47: =_xlfn.XLOOKUP(A47,'Текущая цена на ВБ'!C:C,'Текущая цена на ВБ'!H:H)
A48: =[1]Юнит!A47 -> 271440668 | B48: =[1]Юнит!C47 -> ACRB1SK101BC | C48: =[1]Юнит!D47 -> Скакалка черная | D48: =[1]Юнит!E47 -> 2041473034138 | E48: 1206 | F48: 0.4 | G48: 2010 | H48: 0.21969194 | I48: =_xlfn.XLOOKUP(D48,[1]Юнит!$E:$E,[1]Юнит!$AN:$AN) -> 1219 | J48: =$J$4 -> 0.3 | K48: =I48/(100%-J46) -> 1741.4286 | L48: =_xlfn.XLOOKUP(D48,[1]Юнит!$E:$E,[1]Юнит!$AR:$AR) -> 0.25151206 | M48: =MROUND(O48-O48*N48,1) -> 1206 | N48: =_xlfn.XLOOKUP($A48,'Текущая цена на ВБ'!$C:$C,'Текущая цена на ВБ'!$K:$K,0,0)% -> 0.4 | O48: =_xlfn.XLOOKUP($A48,'Текущая цена на ВБ'!$C:$C,'Текущая цена на ВБ'!$I:$I,0,0) -> 2010 | P48: =_xlfn.XLOOKUP($A48,[1]Юнит!$A:$A,[1]Юнит!$AJ:$AJ,0) -> 0.24419834 | Q48: =_xlfn.XLOOKUP($A48,'Акция 1'!$F:$F,'Акция 1'!$L:$L,0,0) -> 1206 | R48: =(_xlfn.XLOOKUP($A48,'Акция 1'!$F:$F,'Акция 1'!$P:$P,0,0))% -> 0.35 | S48: =Q48/(100%-R48) -> 1855.3846 | T48: =_xlfn.XLOOKUP($A48,'Акция 2'!$F:$F,'Акция 2'!$L:$L,0,0) -> 0 | U48: =(_xlfn.XLOOKUP($A48,'Акция 2'!$F:$F,'Акция 2'!$O:$O,0,0))% -> 0 | V48: =T48/(100%-U48) -> 0 | W48: =_xlfn.XLOOKUP($A48,'Акция 3'!$F:$F,'Акция 3'!$L:$L,0,0) -> 916 | X48: =(_xlfn.XLOOKUP($A48,'Акция 3'!$F:$F,'Акция 3'!$P:$P,0,0))% -> 0.48 | Y48: =W48/(100%-X48) -> 1761.5385 | Z48: =_xlfn.XLOOKUP($A48,'Акция 4'!$F:$F,'Акция 4'!$L:$L,0,0) -> 1146 | AA48: =(_xlfn.XLOOKUP($A48,'Акция 4'!$F:$F,'Акция 4'!$P:$P,0,0))% -> 0.35 | AB48: =Z48/(100%-AA48) -> 1763.0769 | AC48: =_xlfn.XLOOKUP($A48,'Акция 5'!$F:$F,'Акция 5'!$L:$L,0,0) -> 0 | AD48: =(_xlfn.XLOOKUP($A48,'Акция 5'!$F:$F,'Акция 5'!O:O,0,0))% -> 0 | AE48: =AC48/(100%-AD48) -> 0 | AF48: =_xlfn.XLOOKUP($A48,'Акция 6'!$F:$F,'Акция 6'!$L:$L,0,0) -> 0 | AG48: =(_xlfn.XLOOKUP($A48,'Акция 6'!$F:$F,'Акция 6'!$O:$O,0,0))% -> 0 | AH48: =AF48/(100%-AG48) -> 0 | AI48: =_xlfn.XLOOKUP($A48,'Акция 7'!$F:$F,'Акция 7'!$L:$L,0,0) -> 0 | AJ48: =(_xlfn.XLOOKUP($A48,'Акция 7'!$F:$F,'Акция 7'!$O:$O,0,0))% -> 0 | AK48: =AI48/(100%-AJ48) -> 0 | AL48: =_xlfn.XLOOKUP($A48,'Акция 8'!$F:$F,'Акция 8'!$L:$L,0,0) -> 0 | AM48: =(_xlfn.XLOOKUP($A48,'Акция 8'!$F:$F,'Акция 8'!$S:$S,0,0))% -> 0 | AN48: =AL48/(100%-AM48) -> 0 | AO48: =_xlfn.XLOOKUP($A48,'Акция 9'!$F:$F,'Акция 9'!$L:$L,0,0) -> 0 | AP48: =(_xlfn.XLOOKUP($A48,'Акция 9'!$F:$F,'Акция 9'!$O:$O,0,0))% -> 0 | AQ48: =AO48/(100%-AP48) -> 0 | AR48: =_xlfn.XLOOKUP($A48,'Акция 10'!$F:$F,'Акция 10'!$L:$L,0,0) -> 0 | AS48: =(_xlfn.XLOOKUP($A48,'Акция 10'!$F:$F,'Акция 10'!$O:$O,0,0))% -> 0 | AT48: =AR48/(100%-AS48) -> 0 | AU48: =_xlfn.XLOOKUP($A48,'Акция 11'!$F:$F,'Акция 11'!$L:$L,0,0) -> 0 | AV48: =(_xlfn.XLOOKUP($A48,'Акция 11'!$F:$F,'Акция 11'!$O:$O,0,0))% -> 0 | AW48: =AU48/(100%-AV48) -> 0 | BA48: =MAX($Q48,$T48,W48,Z48,AC48,AF48,AL48,AO48,AR48,AU48,AX48,AI48) -> 1206 | BB48: =IF(BA48=0,0,_xlfn.XLOOKUP($BA48,$Q48:$AZ48,$Q$1:$AZ$1,0,0)) -> 1 | BC48: =_xlfn.XLOOKUP($BB48,$Q$1:$AZ$1,$Q48:$AZ48,0,0) -> 1206 | BD48: =IF(BA48=0,0,$BD$3) -> 0.4 | BE48: =BC48/(100%-BD48) -> 2010 | BF48: =_xlfn.XLOOKUP(A48,[1]Юнит!$A:$A,[1]Юнит!$AU:$AU,0) -> 0.24419834 | BG48: =P48 -> 0.24419834 | BH48: * | BI48: =MROUND(IF($BH48="*",$BE48,K48),1) -> 2010 | BJ48: =IF($BH48="*",$BD48,J48) -> 0.4 | BK48: =MROUND(BI48-BI48*BJ48,1) -> 1206 | BL48: =IF(BH48="*",1,0) -> 1 | BM48: =_xlfn.XLOOKUP(A48,'Текущая цена на ВБ'!C:C,'Текущая цена на ВБ'!F:F) -> 130 | BN48: =_xlfn.XLOOKUP(A48,'Текущая цена на ВБ'!C:C,'Текущая цена на ВБ'!H:H) -> 983
A49: =[1]Юнит!A48 -> 271440669 | B49: =[1]Юнит!C48 -> ACRB1SK101RD | C49: =[1]Юнит!D48 -> Скакалка красная | D49: =[1]Юнит!E48 -> 2041473034145 | E49: 1088 | F49: 0.4 | G49: 1813 | H49: 0.057175101 | I49: =_xlfn.XLOOKUP(D49,[1]Юнит!$E:$E,[1]Юнит!$AN:$AN) -> 1219 | J49: =$J$4 -> 0.3 | K49: =I49/(100%-J47) -> 1741.4286 | L49: =_xlfn.XLOOKUP(D49,[1]Юнит!$E:$E,[1]Юнит!$AR:$AR) -> 0.28184263 | M49: =MROUND(O49-O49*N49,1) -> 1088 | N49: =_xlfn.XLOOKUP($A49,'Текущая цена на ВБ'!$C:$C,'Текущая цена на ВБ'!$K:$K,0,0)% -> 0.4 | O49: =_xlfn.XLOOKUP($A49,'Текущая цена на ВБ'!$C:$C,'Текущая цена на ВБ'!$I:$I,0,0) -> 1813 | P49: =_xlfn.XLOOKUP($A49,[1]Юнит!$A:$A,[1]Юнит!$AJ:$AJ,0) -> 0.2036681 | Q49: =_xlfn.XLOOKUP($A49,'Акция 1'!$F:$F,'Акция 1'!$L:$L,0,0) -> 1088 | R49: =(_xlfn.XLOOKUP($A49,'Акция 1'!$F:$F,'Акция 1'!$P:$P,0,0))% -> 0.49 | S49: =Q49/(100%-R49) -> 2133.3333 | T49: =_xlfn.XLOOKUP($A49,'Акция 2'!$F:$F,'Акция 2'!$L:$L,0,0) -> 0 | U49: =(_xlfn.XLOOKUP($A49,'Акция 2'!$F:$F,'Акция 2'!$O:$O,0,0))% -> 0 | V49: =T49/(100%-U49) -> 0 | W49: =_xlfn.XLOOKUP($A49,'Акция 3'!$F:$F,'Акция 3'!$L:$L,0,0) -> 819 | X49: =(_xlfn.XLOOKUP($A49,'Акция 3'!$F:$F,'Акция 3'!$P:$P,0,0))% -> 0.49 | Y49: =W49/(100%-X49) -> 1605.8824 | Z49: =_xlfn.XLOOKUP($A49,'Акция 4'!$F:$F,'Акция 4'!$L:$L,0,0) -> 813 | AA49: =(_xlfn.XLOOKUP($A49,'Акция 4'!$F:$F,'Акция 4'!$P:$P,0,0))% -> 0.49 | AB49: =Z49/(100%-AA49) -> 1594.1176 | AC49: =_xlfn.XLOOKUP($A49,'Акция 5'!$F:$F,'Акция 5'!$L:$L,0,0) -> 0 | AD49: =(_xlfn.XLOOKUP($A49,'Акция 5'!$F:$F,'Акция 5'!O:O,0,0))% -> 0 | AE49: =AC49/(100%-AD49) -> 0 | AF49: =_xlfn.XLOOKUP($A49,'Акция 6'!$F:$F,'Акция 6'!$L:$L,0,0) -> 0 | AG49: =(_xlfn.XLOOKUP($A49,'Акция 6'!$F:$F,'Акция 6'!$O:$O,0,0))% -> 0 | AH49: =AF49/(100%-AG49) -> 0 | AI49: =_xlfn.XLOOKUP($A49,'Акция 7'!$F:$F,'Акция 7'!$L:$L,0,0) -> 0 | AJ49: =(_xlfn.XLOOKUP($A49,'Акция 7'!$F:$F,'Акция 7'!$O:$O,0,0))% -> 0 | AK49: =AI49/(100%-AJ49) -> 0 | AL49: =_xlfn.XLOOKUP($A49,'Акция 8'!$F:$F,'Акция 8'!$L:$L,0,0) -> 0 | AM49: =(_xlfn.XLOOKUP($A49,'Акция 8'!$F:$F,'Акция 8'!$S:$S,0,0))% -> 0 | AN49: =AL49/(100%-AM49) -> 0 | AO49: =_xlfn.XLOOKUP($A49,'Акция 9'!$F:$F,'Акция 9'!$L:$L,0,0) -> 0 | AP49: =(_xlfn.XLOOKUP($A49,'Акция 9'!$F:$F,'Акция 9'!$O:$O,0,0))% -> 0 | AQ49: =AO49/(100%-AP49) -> 0 | AR49: =_xlfn.XLOOKUP($A49,'Акция 10'!$F:$F,'Акция 10'!$L:$L,0,0) -> 0 | AS49: =(_xlfn.XLOOKUP($A49,'Акция 10'!$F:$F,'Акция 10'!$O:$O,0,0))% -> 0 | AT49: =AR49/(100%-AS49) -> 0 | AU49: =_xlfn.XLOOKUP($A49,'Акция 11'!$F:$F,'Акция 11'!$L:$L,0,0) -> 0 | AV49: =(_xlfn.XLOOKUP($A49,'Акция 11'!$F:$F,'Акция 11'!$O:$O,0,0))% -> 0 | AW49: =AU49/(100%-AV49) -> 0 | BA49: =MAX($Q49,$T49,W49,Z49,AC49,AF49,AL49,AO49,AR49,AU49,AX49,AI49) -> 1088 | BB49: =IF(BA49=0,0,_xlfn.XLOOKUP($BA49,$Q49:$AZ49,$Q$1:$AZ$1,0,0)) -> 1 | BC49: =_xlfn.XLOOKUP($BB49,$Q$1:$AZ$1,$Q49:$AZ49,0,0) -> 1088 | BD49: =IF(BA49=0,0,$BD$3) -> 0.4 | BE49: =BC49/(100%-BD49) -> 1813.3333 | BF49: =_xlfn.XLOOKUP(A49,[1]Юнит!$A:$A,[1]Юнит!$AU:$AU,0) -> 0.20380162 | BG49: =P49 -> 0.2036681 | BH49: * | BI49: =MROUND(IF($BH49="*",$BE49,K49),1) -> 1813 | BJ49: =IF($BH49="*",$BD49,J49) -> 0.4 | BK49: =MROUND(BI49-BI49*BJ49,1) -> 1088 | BL49: =IF(BH49="*",1,0) -> 1 | BM49: =_xlfn.XLOOKUP(A49,'Текущая цена на ВБ'!C:C,'Текущая цена на ВБ'!F:F) -> 128 | BN49: =_xlfn.XLOOKUP(A49,'Текущая цена на ВБ'!C:C,'Текущая цена на ВБ'!H:H) -> 440
A50: =[1]Юнит!A49 -> 271440670 | B50: =[1]Юнит!C49 -> ACRB1SK101BL | C50: =[1]Юнит!D49 -> Скакалка синяя | D50: =[1]Юнит!E49 -> 2041473034169 | E50: 1088 | F50: 0.4 | G50: 1813 | H50: 0.059673818 | I50: =_xlfn.XLOOKUP(D50,[1]Юнит!$E:$E,[1]Юнит!$AN:$AN) -> 1219 | J50: =$J$4 -> 0.3 | K50: =I50/(100%-J48) -> 1741.4286 | L50: =_xlfn.XLOOKUP(D50,[1]Юнит!$E:$E,[1]Юнит!$AR:$AR) -> 0.28184263 | M50: =MROUND(O50-O50*N50,1) -> 1088 | N50: =_xlfn.XLOOKUP($A50,'Текущая цена на ВБ'!$C:$C,'Текущая цена на ВБ'!$K:$K,0,0)% -> 0.4 | O50: =_xlfn.XLOOKUP($A50,'Текущая цена на ВБ'!$C:$C,'Текущая цена на ВБ'!$I:$I,0,0) -> 1813 | P50: =_xlfn.XLOOKUP($A50,[1]Юнит!$A:$A,[1]Юнит!$AJ:$AJ,0) -> 0.2036681 | Q50: =_xlfn.XLOOKUP($A50,'Акция 1'!$F:$F,'Акция 1'!$L:$L,0,0) -> 1088 | R50: =(_xlfn.XLOOKUP($A50,'Акция 1'!$F:$F,'Акция 1'!$P:$P,0,0))% -> 0.45 | S50: =Q50/(100%-R50) -> 1978.1818 | T50: =_xlfn.XLOOKUP($A50,'Акция 2'!$F:$F,'Акция 2'!$L:$L,0,0) -> 0 | U50: =(_xlfn.XLOOKUP($A50,'Акция 2'!$F:$F,'Акция 2'!$O:$O,0,0))% -> 0 | V50: =T50/(100%-U50) -> 0 | W50: =_xlfn.XLOOKUP($A50,'Акция 3'!$F:$F,'Акция 3'!$L:$L,0,0) -> 819 | X50: =(_xlfn.XLOOKUP($A50,'Акция 3'!$F:$F,'Акция 3'!$P:$P,0,0))% -> 0.45 | Y50: =W50/(100%-X50) -> 1489.0909 | Z50: =_xlfn.XLOOKUP($A50,'Акция 4'!$F:$F,'Акция 4'!$L:$L,0,0) -> 813 | AA50: =(_xlfn.XLOOKUP($A50,'Акция 4'!$F:$F,'Акция 4'!$P:$P,0,0))% -> 0.45 | AB50: =Z50/(100%-AA50) -> 1478.1818 | AC50: =_xlfn.XLOOKUP($A50,'Акция 5'!$F:$F,'Акция 5'!$L:$L,0,0) -> 0 | AD50: =(_xlfn.XLOOKUP($A50,'Акция 5'!$F:$F,'Акция 5'!O:O,0,0))% -> 0 | AE50: =AC50/(100%-AD50) -> 0 | AF50: =_xlfn.XLOOKUP($A50,'Акция 6'!$F:$F,'Акция 6'!$L:$L,0,0) -> 0 | AG50: =(_xlfn.XLOOKUP($A50,'Акция 6'!$F:$F,'Акция 6'!$O:$O,0,0))% -> 0 | AH50: =AF50/(100%-AG50) -> 0 | AI50: =_xlfn.XLOOKUP($A50,'Акция 7'!$F:$F,'Акция 7'!$L:$L,0,0) -> 0 | AJ50: =(_xlfn.XLOOKUP($A50,'Акция 7'!$F:$F,'Акция 7'!$O:$O,0,0))% -> 0 | AK50: =AI50/(100%-AJ50) -> 0 | AL50: =_xlfn.XLOOKUP($A50,'Акция 8'!$F:$F,'Акция 8'!$L:$L,0,0) -> 0 | AM50: =(_xlfn.XLOOKUP($A50,'Акция 8'!$F:$F,'Акция 8'!$S:$S,0,0))% -> 0 | AN50: =AL50/(100%-AM50) -> 0 | AO50: =_xlfn.XLOOKUP($A50,'Акция 9'!$F:$F,'Акция 9'!$L:$L,0,0) -> 0 | AP50: =(_xlfn.XLOOKUP($A50,'Акция 9'!$F:$F,'Акция 9'!$O:$O,0,0))% -> 0 | AQ50: =AO50/(100%-AP50) -> 0 | AR50: =_xlfn.XLOOKUP($A50,'Акция 10'!$F:$F,'Акция 10'!$L:$L,0,0) -> 0 | AS50: =(_xlfn.XLOOKUP($A50,'Акция 10'!$F:$F,'Акция 10'!$O:$O,0,0))% -> 0 | AT50: =AR50/(100%-AS50) -> 0 | AU50: =_xlfn.XLOOKUP($A50,'Акция 11'!$F:$F,'Акция 11'!$L:$L,0,0) -> 0 | AV50: =(_xlfn.XLOOKUP($A50,'Акция 11'!$F:$F,'Акция 11'!$O:$O,0,0))% -> 0 | AW50: =AU50/(100%-AV50) -> 0 | BA50: =MAX($Q50,$T50,W50,Z50,AC50,AF50,AL50,AO50,AR50,AU50,AX50,AI50) -> 1088 | BB50: =IF(BA50=0,0,_xlfn.XLOOKUP($BA50,$Q50:$AZ50,$Q$1:$AZ$1,0,0)) -> 1 | BC50: =_xlfn.XLOOKUP($BB50,$Q$1:$AZ$1,$Q50:$AZ50,0,0) -> 1088 | BD50: =IF(BA50=0,0,$BD$3) -> 0.4 | BE50: =BC50/(100%-BD50) -> 1813.3333 | BF50: =_xlfn.XLOOKUP(A50,[1]Юнит!$A:$A,[1]Юнит!$AU:$AU,0) -> 0.20380162 | BG50: =P50 -> 0.2036681 | BH50: * | BI50: =MROUND(IF($BH50="*",$BE50,K50),1) -> 1813 | BJ50: =IF($BH50="*",$BD50,J50) -> 0.4 | BK50: =MROUND(BI50-BI50*BJ50,1) -> 1088 | BL50: =IF(BH50="*",1,0) -> 1 | BM50: =_xlfn.XLOOKUP(A50,'Текущая цена на ВБ'!C:C,'Текущая цена на ВБ'!F:F) -> 100 | BN50: =_xlfn.XLOOKUP(A50,'Текущая цена на ВБ'!C:C,'Текущая цена на ВБ'!H:H) -> 999
A51: =[1]Юнит!A50 -> 550445272 | B51: =[1]Юнит!C50 -> ACRF1KP101BC | C51: =[1]Юнит!D50 -> Капа черный/красный - черная коробка | D51: =[1]Юнит!E50 -> 2046391283330 | E51: 602 | F51: 0.3 | G51: 860 | H51: 0 | I51: =_xlfn.XLOOKUP(D51,[1]Юнит!$E:$E,[1]Юнит!$AN:$AN) -> 0 | J51: =$J$4 -> 0.3 | K51: =I51/(100%-J49) -> 0 | L51: =_xlfn.XLOOKUP(D51,[1]Юнит!$E:$E,[1]Юнит!$AR:$AR) -> #DIV/0! | M51: =MROUND(O51-O51*N51,1) -> 602 | N51: =_xlfn.XLOOKUP($A51,'Текущая цена на ВБ'!$C:$C,'Текущая цена на ВБ'!$K:$K,0,0)% -> 0.3 | O51: =_xlfn.XLOOKUP($A51,'Текущая цена на ВБ'!$C:$C,'Текущая цена на ВБ'!$I:$I,0,0) -> 860 | P51: =_xlfn.XLOOKUP($A51,[1]Юнит!$A:$A,[1]Юнит!$AJ:$AJ,0) -> 0 | Q51: =_xlfn.XLOOKUP($A51,'Акция 1'!$F:$F,'Акция 1'!$L:$L,0,0) -> 0 | R51: =(_xlfn.XLOOKUP($A51,'Акция 1'!$F:$F,'Акция 1'!$P:$P,0,0))% -> 0 | S51: =Q51/(100%-R51) -> 0 | T51: =_xlfn.XLOOKUP($A51,'Акция 2'!$F:$F,'Акция 2'!$L:$L,0,0) -> 0 | U51: =(_xlfn.XLOOKUP($A51,'Акция 2'!$F:$F,'Акция 2'!$O:$O,0,0))% -> 0 | V51: =T51/(100%-U51) -> 0 | W51: =_xlfn.XLOOKUP($A51,'Акция 3'!$F:$F,'Акция 3'!$L:$L,0,0) -> 0 | X51: =(_xlfn.XLOOKUP($A51,'Акция 3'!$F:$F,'Акция 3'!$P:$P,0,0))% -> 0 | Y51: =W51/(100%-X51) -> 0 | Z51: =_xlfn.XLOOKUP($A51,'Акция 4'!$F:$F,'Акция 4'!$L:$L,0,0) -> 0 | AA51: =(_xlfn.XLOOKUP($A51,'Акция 4'!$F:$F,'Акция 4'!$P:$P,0,0))% -> 0 | AB51: =Z51/(100%-AA51) -> 0 | AC51: =_xlfn.XLOOKUP($A51,'Акция 5'!$F:$F,'Акция 5'!$L:$L,0,0) -> 0 | AD51: =(_xlfn.XLOOKUP($A51,'Акция 5'!$F:$F,'Акция 5'!O:O,0,0))% -> 0 | AE51: =AC51/(100%-AD51) -> 0 | AF51: =_xlfn.XLOOKUP($A51,'Акция 6'!$F:$F,'Акция 6'!$L:$L,0,0) -> 0 | AG51: =(_xlfn.XLOOKUP($A51,'Акция 6'!$F:$F,'Акция 6'!$O:$O,0,0))% -> 0 | AH51: =AF51/(100%-AG51) -> 0 | AI51: =_xlfn.XLOOKUP($A51,'Акция 7'!$F:$F,'Акция 7'!$L:$L,0,0) -> 0 | AJ51: =(_xlfn.XLOOKUP($A51,'Акция 7'!$F:$F,'Акция 7'!$O:$O,0,0))% -> 0 | AK51: =AI51/(100%-AJ51) -> 0 | AL51: =_xlfn.XLOOKUP($A51,'Акция 8'!$F:$F,'Акция 8'!$L:$L,0,0) -> 0 | AM51: =(_xlfn.XLOOKUP($A51,'Акция 8'!$F:$F,'Акция 8'!$S:$S,0,0))% -> 0 | AN51: =AL51/(100%-AM51) -> 0 | AO51: =_xlfn.XLOOKUP($A51,'Акция 9'!$F:$F,'Акция 9'!$L:$L,0,0) -> 0 | AP51: =(_xlfn.XLOOKUP($A51,'Акция 9'!$F:$F,'Акция 9'!$O:$O,0,0))% -> 0 | AQ51: =AO51/(100%-AP51) -> 0 | AR51: =_xlfn.XLOOKUP($A51,'Акция 10'!$F:$F,'Акция 10'!$L:$L,0,0) -> 0 | AS51: =(_xlfn.XLOOKUP($A51,'Акция 10'!$F:$F,'Акция 10'!$O:$O,0,0))% -> 0 | AT51: =AR51/(100%-AS51) -> 0 | AU51: =_xlfn.XLOOKUP($A51,'Акция 11'!$F:$F,'Акция 11'!$L:$L,0,0) -> 0 | AV51: =(_xlfn.XLOOKUP($A51,'Акция 11'!$F:$F,'Акция 11'!$O:$O,0,0))% -> 0 | AW51: =AU51/(100%-AV51) -> 0 | BA51: =MAX($Q51,$T51,W51,Z51,AC51,AF51,AL51,AO51,AR51,AU51,AX51,AI51) -> 0 | BB51: =IF(BA51=0,0,_xlfn.XLOOKUP($BA51,$Q51:$AZ51,$Q$1:$AZ$1,0,0)) -> 0 | BC51: =_xlfn.XLOOKUP($BB51,$Q$1:$AZ$1,$Q51:$AZ51,0,0) -> 0 | BD51: =IF(BA51=0,0,$BD$3) -> 0 | BE51: =BC51/(100%-BD51) -> 0 | BF51: =_xlfn.XLOOKUP(A51,[1]Юнит!$A:$A,[1]Юнит!$AU:$AU,0) -> 0 | BG51: =P51 -> 0 | BI51: =MROUND(IF($BH51="*",$BE51,K51),1) -> 0 | BJ51: =IF($BH51="*",$BD51,J51) -> 0.3 | BK51: =MROUND(BI51-BI51*BJ51,1) -> 0 | BL51: =IF(BH51="*",1,0) -> 0 | BM51: =_xlfn.XLOOKUP(A51,'Текущая цена на ВБ'!C:C,'Текущая цена на ВБ'!F:F) | BN51: =_xlfn.XLOOKUP(A51,'Текущая цена на ВБ'!C:C,'Текущая цена на ВБ'!H:H)
A52: =[1]Юнит!A51 -> 550445274 | B52: =[1]Юнит!C51 -> ACRF1KP102BC | C52: =[1]Юнит!D51 -> Капа черный/белый-черная коробка | D52: =[1]Юнит!E51 -> 2046391283385 | E52: 602 | F52: 0.3 | G52: 860 | H52: 0 | I52: =_xlfn.XLOOKUP(D52,[1]Юнит!$E:$E,[1]Юнит!$AN:$AN) -> 0 | J52: =$J$4 -> 0.3 | K52: =I52/(100%-J50) -> 0 | L52: =_xlfn.XLOOKUP(D52,[1]Юнит!$E:$E,[1]Юнит!$AR:$AR) -> #DIV/0! | M52: =MROUND(O52-O52*N52,1) -> 602 | N52: =_xlfn.XLOOKUP($A52,'Текущая цена на ВБ'!$C:$C,'Текущая цена на ВБ'!$K:$K,0,0)% -> 0.3 | O52: =_xlfn.XLOOKUP($A52,'Текущая цена на ВБ'!$C:$C,'Текущая цена на ВБ'!$I:$I,0,0) -> 860 | P52: =_xlfn.XLOOKUP($A52,[1]Юнит!$A:$A,[1]Юнит!$AJ:$AJ,0) -> 0 | Q52: =_xlfn.XLOOKUP($A52,'Акция 1'!$F:$F,'Акция 1'!$L:$L,0,0) -> 0 | R52: =(_xlfn.XLOOKUP($A52,'Акция 1'!$F:$F,'Акция 1'!$P:$P,0,0))% -> 0 | S52: =Q52/(100%-R52) -> 0 | T52: =_xlfn.XLOOKUP($A52,'Акция 2'!$F:$F,'Акция 2'!$L:$L,0,0) -> 0 | U52: =(_xlfn.XLOOKUP($A52,'Акция 2'!$F:$F,'Акция 2'!$O:$O,0,0))% -> 0 | V52: =T52/(100%-U52) -> 0 | W52: =_xlfn.XLOOKUP($A52,'Акция 3'!$F:$F,'Акция 3'!$L:$L,0,0) -> 0 | X52: =(_xlfn.XLOOKUP($A52,'Акция 3'!$F:$F,'Акция 3'!$P:$P,0,0))% -> 0 | Y52: =W52/(100%-X52) -> 0 | Z52: =_xlfn.XLOOKUP($A52,'Акция 4'!$F:$F,'Акция 4'!$L:$L,0,0) -> 0 | AA52: =(_xlfn.XLOOKUP($A52,'Акция 4'!$F:$F,'Акция 4'!$P:$P,0,0))% -> 0 | AB52: =Z52/(100%-AA52) -> 0 | AC52: =_xlfn.XLOOKUP($A52,'Акция 5'!$F:$F,'Акция 5'!$L:$L,0,0) -> 0 | AD52: =(_xlfn.XLOOKUP($A52,'Акция 5'!$F:$F,'Акция 5'!O:O,0,0))% -> 0 | AE52: =AC52/(100%-AD52) -> 0 | AF52: =_xlfn.XLOOKUP($A52,'Акция 6'!$F:$F,'Акция 6'!$L:$L,0,0) -> 0 | AG52: =(_xlfn.XLOOKUP($A52,'Акция 6'!$F:$F,'Акция 6'!$O:$O,0,0))% -> 0 | AH52: =AF52/(100%-AG52) -> 0 | AI52: =_xlfn.XLOOKUP($A52,'Акция 7'!$F:$F,'Акция 7'!$L:$L,0,0) -> 0 | AJ52: =(_xlfn.XLOOKUP($A52,'Акция 7'!$F:$F,'Акция 7'!$O:$O,0,0))% -> 0 | AK52: =AI52/(100%-AJ52) -> 0 | AL52: =_xlfn.XLOOKUP($A52,'Акция 8'!$F:$F,'Акция 8'!$L:$L,0,0) -> 0 | AM52: =(_xlfn.XLOOKUP($A52,'Акция 8'!$F:$F,'Акция 8'!$S:$S,0,0))% -> 0 | AN52: =AL52/(100%-AM52) -> 0 | AO52: =_xlfn.XLOOKUP($A52,'Акция 9'!$F:$F,'Акция 9'!$L:$L,0,0) -> 0 | AP52: =(_xlfn.XLOOKUP($A52,'Акция 9'!$F:$F,'Акция 9'!$O:$O,0,0))% -> 0 | AQ52: =AO52/(100%-AP52) -> 0 | AR52: =_xlfn.XLOOKUP($A52,'Акция 10'!$F:$F,'Акция 10'!$L:$L,0,0) -> 0 | AS52: =(_xlfn.XLOOKUP($A52,'Акция 10'!$F:$F,'Акция 10'!$O:$O,0,0))% -> 0 | AT52: =AR52/(100%-AS52) -> 0 | AU52: =_xlfn.XLOOKUP($A52,'Акция 11'!$F:$F,'Акция 11'!$L:$L,0,0) -> 0 | AV52: =(_xlfn.XLOOKUP($A52,'Акция 11'!$F:$F,'Акция 11'!$O:$O,0,0))% -> 0 | AW52: =AU52/(100%-AV52) -> 0 | BA52: =MAX($Q52,$T52,W52,Z52,AC52,AF52,AL52,AO52,AR52,AU52,AX52,AI52) -> 0 | BB52: =IF(BA52=0,0,_xlfn.XLOOKUP($BA52,$Q52:$AZ52,$Q$1:$AZ$1,0,0)) -> 0 | BC52: =_xlfn.XLOOKUP($BB52,$Q$1:$AZ$1,$Q52:$AZ52,0,0) -> 0 | BD52: =IF(BA52=0,0,$BD$3) -> 0 | BE52: =BC52/(100%-BD52) -> 0 | BF52: =_xlfn.XLOOKUP(A52,[1]Юнит!$A:$A,[1]Юнит!$AU:$AU,0) -> 0 | BG52: =P52 -> 0 | BI52: =MROUND(IF($BH52="*",$BE52,K52),1) -> 0 | BJ52: =IF($BH52="*",$BD52,J52) -> 0.3 | BK52: =MROUND(BI52-BI52*BJ52,1) -> 0 | BL52: =IF(BH52="*",1,0) -> 0 | BM52: =_xlfn.XLOOKUP(A52,'Текущая цена на ВБ'!C:C,'Текущая цена на ВБ'!F:F) | BN52: =_xlfn.XLOOKUP(A52,'Текущая цена на ВБ'!C:C,'Текущая цена на ВБ'!H:H)
A53: =[1]Юнит!A52 -> 550445275 | B53: =[1]Юнит!C52 -> ACRF1KP103BC | C53: =[1]Юнит!D52 -> Капа белый/черный | D53: =[1]Юнит!E52 -> 2046391283415 | E53: 602 | F53: 0.3 | G53: 860 | H53: 0 | I53: =_xlfn.XLOOKUP(D53,[1]Юнит!$E:$E,[1]Юнит!$AN:$AN) -> 0 | J53: =$J$4 -> 0.3 | K53: =I53/(100%-J51) -> 0 | L53: =_xlfn.XLOOKUP(D53,[1]Юнит!$E:$E,[1]Юнит!$AR:$AR) -> #DIV/0! | M53: =MROUND(O53-O53*N53,1) -> 602 | N53: =_xlfn.XLOOKUP($A53,'Текущая цена на ВБ'!$C:$C,'Текущая цена на ВБ'!$K:$K,0,0)% -> 0.3 | O53: =_xlfn.XLOOKUP($A53,'Текущая цена на ВБ'!$C:$C,'Текущая цена на ВБ'!$I:$I,0,0) -> 860 | P53: =_xlfn.XLOOKUP($A53,[1]Юнит!$A:$A,[1]Юнит!$AJ:$AJ,0) -> 0 | Q53: =_xlfn.XLOOKUP($A53,'Акция 1'!$F:$F,'Акция 1'!$L:$L,0,0) -> 0 | R53: =(_xlfn.XLOOKUP($A53,'Акция 1'!$F:$F,'Акция 1'!$P:$P,0,0))% -> 0 | S53: =Q53/(100%-R53) -> 0 | T53: =_xlfn.XLOOKUP($A53,'Акция 2'!$F:$F,'Акция 2'!$L:$L,0,0) -> 0 | U53: =(_xlfn.XLOOKUP($A53,'Акция 2'!$F:$F,'Акция 2'!$O:$O,0,0))% -> 0 | V53: =T53/(100%-U53) -> 0 | W53: =_xlfn.XLOOKUP($A53,'Акция 3'!$F:$F,'Акция 3'!$L:$L,0,0) -> 0 | X53: =(_xlfn.XLOOKUP($A53,'Акция 3'!$F:$F,'Акция 3'!$P:$P,0,0))% -> 0 | Y53: =W53/(100%-X53) -> 0 | Z53: =_xlfn.XLOOKUP($A53,'Акция 4'!$F:$F,'Акция 4'!$L:$L,0,0) -> 0 | AA53: =(_xlfn.XLOOKUP($A53,'Акция 4'!$F:$F,'Акция 4'!$P:$P,0,0))% -> 0 | AB53: =Z53/(100%-AA53) -> 0 | AC53: =_xlfn.XLOOKUP($A53,'Акция 5'!$F:$F,'Акция 5'!$L:$L,0,0) -> 0 | AD53: =(_xlfn.XLOOKUP($A53,'Акция 5'!$F:$F,'Акция 5'!O:O,0,0))% -> 0 | AE53: =AC53/(100%-AD53) -> 0 | AF53: =_xlfn.XLOOKUP($A53,'Акция 6'!$F:$F,'Акция 6'!$L:$L,0,0) -> 0 | AG53: =(_xlfn.XLOOKUP($A53,'Акция 6'!$F:$F,'Акция 6'!$O:$O,0,0))% -> 0 | AH53: =AF53/(100%-AG53) -> 0 | AI53: =_xlfn.XLOOKUP($A53,'Акция 7'!$F:$F,'Акция 7'!$L:$L,0,0) -> 0 | AJ53: =(_xlfn.XLOOKUP($A53,'Акция 7'!$F:$F,'Акция 7'!$O:$O,0,0))% -> 0 | AK53: =AI53/(100%-AJ53) -> 0 | AL53: =_xlfn.XLOOKUP($A53,'Акция 8'!$F:$F,'Акция 8'!$L:$L,0,0) -> 0 | AM53: =(_xlfn.XLOOKUP($A53,'Акция 8'!$F:$F,'Акция 8'!$S:$S,0,0))% -> 0 | AN53: =AL53/(100%-AM53) -> 0 | AO53: =_xlfn.XLOOKUP($A53,'Акция 9'!$F:$F,'Акция 9'!$L:$L,0,0) -> 0 | AP53: =(_xlfn.XLOOKUP($A53,'Акция 9'!$F:$F,'Акция 9'!$O:$O,0,0))% -> 0 | AQ53: =AO53/(100%-AP53) -> 0 | AR53: =_xlfn.XLOOKUP($A53,'Акция 10'!$F:$F,'Акция 10'!$L:$L,0,0) -> 0 | AS53: =(_xlfn.XLOOKUP($A53,'Акция 10'!$F:$F,'Акция 10'!$O:$O,0,0))% -> 0 | AT53: =AR53/(100%-AS53) -> 0 | AU53: =_xlfn.XLOOKUP($A53,'Акция 11'!$F:$F,'Акция 11'!$L:$L,0,0) -> 0 | AV53: =(_xlfn.XLOOKUP($A53,'Акция 11'!$F:$F,'Акция 11'!$O:$O,0,0))% -> 0 | AW53: =AU53/(100%-AV53) -> 0 | BA53: =MAX($Q53,$T53,W53,Z53,AC53,AF53,AL53,AO53,AR53,AU53,AX53,AI53) -> 0 | BB53: =IF(BA53=0,0,_xlfn.XLOOKUP($BA53,$Q53:$AZ53,$Q$1:$AZ$1,0,0)) -> 0 | BC53: =_xlfn.XLOOKUP($BB53,$Q$1:$AZ$1,$Q53:$AZ53,0,0) -> 0 | BD53: =IF(BA53=0,0,$BD$3) -> 0 | BE53: =BC53/(100%-BD53) -> 0 | BF53: =_xlfn.XLOOKUP(A53,[1]Юнит!$A:$A,[1]Юнит!$AU:$AU,0) -> 0 | BG53: =P53 -> 0 | BI53: =MROUND(IF($BH53="*",$BE53,K53),1) -> 0 | BJ53: =IF($BH53="*",$BD53,J53) -> 0.3 | BK53: =MROUND(BI53-BI53*BJ53,1) -> 0 | BL53: =IF(BH53="*",1,0) -> 0 | BM53: =_xlfn.XLOOKUP(A53,'Текущая цена на ВБ'!C:C,'Текущая цена на ВБ'!F:F) | BN53: =_xlfn.XLOOKUP(A53,'Текущая цена на ВБ'!C:C,'Текущая цена на ВБ'!H:H)
A54: =[1]Юнит!A53 -> 550445277 | B54: =[1]Юнит!C53 -> ACRF1KP101RD | C54: =[1]Юнит!D53 -> Капа белый/красный | D54: =[1]Юнит!E53 -> 2046391283446 | E54: 602 | F54: 0.3 | G54: 860 | H54: 0 | I54: =_xlfn.XLOOKUP(D54,[1]Юнит!$E:$E,[1]Юнит!$AN:$AN) -> 0 | J54: =$J$4 -> 0.3 | K54: =I54/(100%-J52) -> 0 | L54: =_xlfn.XLOOKUP(D54,[1]Юнит!$E:$E,[1]Юнит!$AR:$AR) -> #DIV/0! | M54: =MROUND(O54-O54*N54,1) -> 602 | N54: =_xlfn.XLOOKUP($A54,'Текущая цена на ВБ'!$C:$C,'Текущая цена на ВБ'!$K:$K,0,0)% -> 0.3 | O54: =_xlfn.XLOOKUP($A54,'Текущая цена на ВБ'!$C:$C,'Текущая цена на ВБ'!$I:$I,0,0) -> 860 | P54: =_xlfn.XLOOKUP($A54,[1]Юнит!$A:$A,[1]Юнит!$AJ:$AJ,0) -> 0 | Q54: =_xlfn.XLOOKUP($A54,'Акция 1'!$F:$F,'Акция 1'!$L:$L,0,0) -> 0 | R54: =(_xlfn.XLOOKUP($A54,'Акция 1'!$F:$F,'Акция 1'!$P:$P,0,0))% -> 0 | S54: =Q54/(100%-R54) -> 0 | T54: =_xlfn.XLOOKUP($A54,'Акция 2'!$F:$F,'Акция 2'!$L:$L,0,0) -> 0 | U54: =(_xlfn.XLOOKUP($A54,'Акция 2'!$F:$F,'Акция 2'!$O:$O,0,0))% -> 0 | V54: =T54/(100%-U54) -> 0 | W54: =_xlfn.XLOOKUP($A54,'Акция 3'!$F:$F,'Акция 3'!$L:$L,0,0) -> 0 | X54: =(_xlfn.XLOOKUP($A54,'Акция 3'!$F:$F,'Акция 3'!$P:$P,0,0))% -> 0 | Y54: =W54/(100%-X54) -> 0 | Z54: =_xlfn.XLOOKUP($A54,'Акция 4'!$F:$F,'Акция 4'!$L:$L,0,0) -> 0 | AA54: =(_xlfn.XLOOKUP($A54,'Акция 4'!$F:$F,'Акция 4'!$P:$P,0,0))% -> 0 | AB54: =Z54/(100%-AA54) -> 0 | AC54: =_xlfn.XLOOKUP($A54,'Акция 5'!$F:$F,'Акция 5'!$L:$L,0,0) -> 0 | AD54: =(_xlfn.XLOOKUP($A54,'Акция 5'!$F:$F,'Акция 5'!O:O,0,0))% -> 0 | AE54: =AC54/(100%-AD54) -> 0 | AF54: =_xlfn.XLOOKUP($A54,'Акция 6'!$F:$F,'Акция 6'!$L:$L,0,0) -> 0 | AG54: =(_xlfn.XLOOKUP($A54,'Акция 6'!$F:$F,'Акция 6'!$O:$O,0,0))% -> 0 | AH54: =AF54/(100%-AG54) -> 0 | AI54: =_xlfn.XLOOKUP($A54,'Акция 7'!$F:$F,'Акция 7'!$L:$L,0,0) -> 0 | AJ54: =(_xlfn.XLOOKUP($A54,'Акция 7'!$F:$F,'Акция 7'!$O:$O,0,0))% -> 0 | AK54: =AI54/(100%-AJ54) -> 0 | AL54: =_xlfn.XLOOKUP($A54,'Акция 8'!$F:$F,'Акция 8'!$L:$L,0,0) -> 0 | AM54: =(_xlfn.XLOOKUP($A54,'Акция 8'!$F:$F,'Акция 8'!$S:$S,0,0))% -> 0 | AN54: =AL54/(100%-AM54) -> 0 | AO54: =_xlfn.XLOOKUP($A54,'Акция 9'!$F:$F,'Акция 9'!$L:$L,0,0) -> 0 | AP54: =(_xlfn.XLOOKUP($A54,'Акция 9'!$F:$F,'Акция 9'!$O:$O,0,0))% -> 0 | AQ54: =AO54/(100%-AP54) -> 0 | AR54: =_xlfn.XLOOKUP($A54,'Акция 10'!$F:$F,'Акция 10'!$L:$L,0,0) -> 0 | AS54: =(_xlfn.XLOOKUP($A54,'Акция 10'!$F:$F,'Акция 10'!$O:$O,0,0))% -> 0 | AT54: =AR54/(100%-AS54) -> 0 | AU54: =_xlfn.XLOOKUP($A54,'Акция 11'!$F:$F,'Акция 11'!$L:$L,0,0) -> 0 | AV54: =(_xlfn.XLOOKUP($A54,'Акция 11'!$F:$F,'Акция 11'!$O:$O,0,0))% -> 0 | AW54: =AU54/(100%-AV54) -> 0 | BA54: =MAX($Q54,$T54,W54,Z54,AC54,AF54,AL54,AO54,AR54,AU54,AX54,AI54) -> 0 | BB54: =IF(BA54=0,0,_xlfn.XLOOKUP($BA54,$Q54:$AZ54,$Q$1:$AZ$1,0,0)) -> 0 | BC54: =_xlfn.XLOOKUP($BB54,$Q$1:$AZ$1,$Q54:$AZ54,0,0) -> 0 | BD54: =IF(BA54=0,0,$BD$3) -> 0 | BE54: =BC54/(100%-BD54) -> 0 | BF54: =_xlfn.XLOOKUP(A54,[1]Юнит!$A:$A,[1]Юнит!$AU:$AU,0) -> 0 | BG54: =P54 -> 0 | BI54: =MROUND(IF($BH54="*",$BE54,K54),1) -> 0 | BJ54: =IF($BH54="*",$BD54,J54) -> 0.3 | BK54: =MROUND(BI54-BI54*BJ54,1) -> 0 | BL54: =IF(BH54="*",1,0) -> 0 | BM54: =_xlfn.XLOOKUP(A54,'Текущая цена на ВБ'!C:C,'Текущая цена на ВБ'!F:F) | BN54: =_xlfn.XLOOKUP(A54,'Текущая цена на ВБ'!C:C,'Текущая цена на ВБ'!H:H)
A55: =[1]Юнит!A54 -> 550445279 | B55: =[1]Юнит!C54 -> ACRF1KP102RD | C55: =[1]Юнит!D54 -> Капа красный/белый | D55: =[1]Юнит!E54 -> 2046391283507 | E55: 602 | F55: 0.3 | G55: 860 | H55: 0 | I55: =_xlfn.XLOOKUP(D55,[1]Юнит!$E:$E,[1]Юнит!$AN:$AN) -> 0 | J55: =$J$4 -> 0.3 | K55: =I55/(100%-J53) -> 0 | L55: =_xlfn.XLOOKUP(D55,[1]Юнит!$E:$E,[1]Юнит!$AR:$AR) -> #DIV/0! | M55: =MROUND(O55-O55*N55,1) -> 602 | N55: =_xlfn.XLOOKUP($A55,'Текущая цена на ВБ'!$C:$C,'Текущая цена на ВБ'!$K:$K,0,0)% -> 0.3 | O55: =_xlfn.XLOOKUP($A55,'Текущая цена на ВБ'!$C:$C,'Текущая цена на ВБ'!$I:$I,0,0) -> 860 | P55: =_xlfn.XLOOKUP($A55,[1]Юнит!$A:$A,[1]Юнит!$AJ:$AJ,0) -> 0 | Q55: =_xlfn.XLOOKUP($A55,'Акция 1'!$F:$F,'Акция 1'!$L:$L,0,0) -> 0 | R55: =(_xlfn.XLOOKUP($A55,'Акция 1'!$F:$F,'Акция 1'!$P:$P,0,0))% -> 0 | S55: =Q55/(100%-R55) -> 0 | T55: =_xlfn.XLOOKUP($A55,'Акция 2'!$F:$F,'Акция 2'!$L:$L,0,0) -> 0 | U55: =(_xlfn.XLOOKUP($A55,'Акция 2'!$F:$F,'Акция 2'!$O:$O,0,0))% -> 0 | V55: =T55/(100%-U55) -> 0 | W55: =_xlfn.XLOOKUP($A55,'Акция 3'!$F:$F,'Акция 3'!$L:$L,0,0) -> 0 | X55: =(_xlfn.XLOOKUP($A55,'Акция 3'!$F:$F,'Акция 3'!$P:$P,0,0))% -> 0 | Y55: =W55/(100%-X55) -> 0 | Z55: =_xlfn.XLOOKUP($A55,'Акция 4'!$F:$F,'Акция 4'!$L:$L,0,0) -> 0 | AA55: =(_xlfn.XLOOKUP($A55,'Акция 4'!$F:$F,'Акция 4'!$P:$P,0,0))% -> 0 | AB55: =Z55/(100%-AA55) -> 0 | AC55: =_xlfn.XLOOKUP($A55,'Акция 5'!$F:$F,'Акция 5'!$L:$L,0,0) -> 0 | AD55: =(_xlfn.XLOOKUP($A55,'Акция 5'!$F:$F,'Акция 5'!O:O,0,0))% -> 0 | AE55: =AC55/(100%-AD55) -> 0 | AF55: =_xlfn.XLOOKUP($A55,'Акция 6'!$F:$F,'Акция 6'!$L:$L,0,0) -> 0 | AG55: =(_xlfn.XLOOKUP($A55,'Акция 6'!$F:$F,'Акция 6'!$O:$O,0,0))% -> 0 | AH55: =AF55/(100%-AG55) -> 0 | AI55: =_xlfn.XLOOKUP($A55,'Акция 7'!$F:$F,'Акция 7'!$L:$L,0,0) -> 0 | AJ55: =(_xlfn.XLOOKUP($A55,'Акция 7'!$F:$F,'Акция 7'!$O:$O,0,0))% -> 0 | AK55: =AI55/(100%-AJ55) -> 0 | AL55: =_xlfn.XLOOKUP($A55,'Акция 8'!$F:$F,'Акция 8'!$L:$L,0,0) -> 0 | AM55: =(_xlfn.XLOOKUP($A55,'Акция 8'!$F:$F,'Акция 8'!$S:$S,0,0))% -> 0 | AN55: =AL55/(100%-AM55) -> 0 | AO55: =_xlfn.XLOOKUP($A55,'Акция 9'!$F:$F,'Акция 9'!$L:$L,0,0) -> 0 | AP55: =(_xlfn.XLOOKUP($A55,'Акция 9'!$F:$F,'Акция 9'!$O:$O,0,0))% -> 0 | AQ55: =AO55/(100%-AP55) -> 0 | AR55: =_xlfn.XLOOKUP($A55,'Акция 10'!$F:$F,'Акция 10'!$L:$L,0,0) -> 0 | AS55: =(_xlfn.XLOOKUP($A55,'Акция 10'!$F:$F,'Акция 10'!$O:$O,0,0))% -> 0 | AT55: =AR55/(100%-AS55) -> 0 | AU55: =_xlfn.XLOOKUP($A55,'Акция 11'!$F:$F,'Акция 11'!$L:$L,0,0) -> 0 | AV55: =(_xlfn.XLOOKUP($A55,'Акция 11'!$F:$F,'Акция 11'!$O:$O,0,0))% -> 0 | AW55: =AU55/(100%-AV55) -> 0 | BA55: =MAX($Q55,$T55,W55,Z55,AC55,AF55,AL55,AO55,AR55,AU55,AX55,AI55) -> 0 | BB55: =IF(BA55=0,0,_xlfn.XLOOKUP($BA55,$Q55:$AZ55,$Q$1:$AZ$1,0,0)) -> 0 | BC55: =_xlfn.XLOOKUP($BB55,$Q$1:$AZ$1,$Q55:$AZ55,0,0) -> 0 | BD55: =IF(BA55=0,0,$BD$3) -> 0 | BE55: =BC55/(100%-BD55) -> 0 | BF55: =_xlfn.XLOOKUP(A55,[1]Юнит!$A:$A,[1]Юнит!$AU:$AU,0) -> 0 | BG55: =P55 -> 0 | BI55: =MROUND(IF($BH55="*",$BE55,K55),1) -> 0 | BJ55: =IF($BH55="*",$BD55,J55) -> 0.3 | BK55: =MROUND(BI55-BI55*BJ55,1) -> 0 | BL55: =IF(BH55="*",1,0) -> 0 | BM55: =_xlfn.XLOOKUP(A55,'Текущая цена на ВБ'!C:C,'Текущая цена на ВБ'!F:F) | BN55: =_xlfn.XLOOKUP(A55,'Текущая цена на ВБ'!C:C,'Текущая цена на ВБ'!H:H)
A56: =[1]Юнит!A55 -> 550445280 | B56: =[1]Юнит!C55 -> ACRF1KP101BL | C56: =[1]Юнит!D55 -> Капа синий/белый | D56: =[1]Юнит!E55 -> 2046391283545 | E56: 602 | F56: 0.3 | G56: 860 | H56: 0 | I56: =_xlfn.XLOOKUP(D56,[1]Юнит!$E:$E,[1]Юнит!$AN:$AN) -> 0 | J56: =$J$4 -> 0.3 | K56: =I56/(100%-J54) -> 0 | L56: =_xlfn.XLOOKUP(D56,[1]Юнит!$E:$E,[1]Юнит!$AR:$AR) -> #DIV/0! | M56: =MROUND(O56-O56*N56,1) -> 602 | N56: =_xlfn.XLOOKUP($A56,'Текущая цена на ВБ'!$C:$C,'Текущая цена на ВБ'!$K:$K,0,0)% -> 0.3 | O56: =_xlfn.XLOOKUP($A56,'Текущая цена на ВБ'!$C:$C,'Текущая цена на ВБ'!$I:$I,0,0) -> 860 | P56: =_xlfn.XLOOKUP($A56,[1]Юнит!$A:$A,[1]Юнит!$AJ:$AJ,0) -> 0 | Q56: =_xlfn.XLOOKUP($A56,'Акция 1'!$F:$F,'Акция 1'!$L:$L,0,0) -> 0 | R56: =(_xlfn.XLOOKUP($A56,'Акция 1'!$F:$F,'Акция 1'!$P:$P,0,0))% -> 0 | S56: =Q56/(100%-R56) -> 0 | T56: =_xlfn.XLOOKUP($A56,'Акция 2'!$F:$F,'Акция 2'!$L:$L,0,0) -> 0 | U56: =(_xlfn.XLOOKUP($A56,'Акция 2'!$F:$F,'Акция 2'!$O:$O,0,0))% -> 0 | V56: =T56/(100%-U56) -> 0 | W56: =_xlfn.XLOOKUP($A56,'Акция 3'!$F:$F,'Акция 3'!$L:$L,0,0) -> 0 | X56: =(_xlfn.XLOOKUP($A56,'Акция 3'!$F:$F,'Акция 3'!$P:$P,0,0))% -> 0 | Y56: =W56/(100%-X56) -> 0 | Z56: =_xlfn.XLOOKUP($A56,'Акция 4'!$F:$F,'Акция 4'!$L:$L,0,0) -> 0 | AA56: =(_xlfn.XLOOKUP($A56,'Акция 4'!$F:$F,'Акция 4'!$P:$P,0,0))% -> 0 | AB56: =Z56/(100%-AA56) -> 0 | AC56: =_xlfn.XLOOKUP($A56,'Акция 5'!$F:$F,'Акция 5'!$L:$L,0,0) -> 0 | AD56: =(_xlfn.XLOOKUP($A56,'Акция 5'!$F:$F,'Акция 5'!O:O,0,0))% -> 0 | AE56: =AC56/(100%-AD56) -> 0 | AF56: =_xlfn.XLOOKUP($A56,'Акция 6'!$F:$F,'Акция 6'!$L:$L,0,0) -> 0 | AG56: =(_xlfn.XLOOKUP($A56,'Акция 6'!$F:$F,'Акция 6'!$O:$O,0,0))% -> 0 | AH56: =AF56/(100%-AG56) -> 0 | AI56: =_xlfn.XLOOKUP($A56,'Акция 7'!$F:$F,'Акция 7'!$L:$L,0,0) -> 0 | AJ56: =(_xlfn.XLOOKUP($A56,'Акция 7'!$F:$F,'Акция 7'!$O:$O,0,0))% -> 0 | AK56: =AI56/(100%-AJ56) -> 0 | AL56: =_xlfn.XLOOKUP($A56,'Акция 8'!$F:$F,'Акция 8'!$L:$L,0,0) -> 0 | AM56: =(_xlfn.XLOOKUP($A56,'Акция 8'!$F:$F,'Акция 8'!$S:$S,0,0))% -> 0 | AN56: =AL56/(100%-AM56) -> 0 | AO56: =_xlfn.XLOOKUP($A56,'Акция 9'!$F:$F,'Акция 9'!$L:$L,0,0) -> 0 | AP56: =(_xlfn.XLOOKUP($A56,'Акция 9'!$F:$F,'Акция 9'!$O:$O,0,0))% -> 0 | AQ56: =AO56/(100%-AP56) -> 0 | AR56: =_xlfn.XLOOKUP($A56,'Акция 10'!$F:$F,'Акция 10'!$L:$L,0,0) -> 0 | AS56: =(_xlfn.XLOOKUP($A56,'Акция 10'!$F:$F,'Акция 10'!$O:$O,0,0))% -> 0 | AT56: =AR56/(100%-AS56) -> 0 | AU56: =_xlfn.XLOOKUP($A56,'Акция 11'!$F:$F,'Акция 11'!$L:$L,0,0) -> 0 | AV56: =(_xlfn.XLOOKUP($A56,'Акция 11'!$F:$F,'Акция 11'!$O:$O,0,0))% -> 0 | AW56: =AU56/(100%-AV56) -> 0 | BA56: =MAX($Q56,$T56,W56,Z56,AC56,AF56,AL56,AO56,AR56,AU56,AX56,AI56) -> 0 | BB56: =IF(BA56=0,0,_xlfn.XLOOKUP($BA56,$Q56:$AZ56,$Q$1:$AZ$1,0,0)) -> 0 | BC56: =_xlfn.XLOOKUP($BB56,$Q$1:$AZ$1,$Q56:$AZ56,0,0) -> 0 | BD56: =IF(BA56=0,0,$BD$3) -> 0 | BE56: =BC56/(100%-BD56) -> 0 | BF56: =_xlfn.XLOOKUP(A56,[1]Юнит!$A:$A,[1]Юнит!$AU:$AU,0) -> 0 | BG56: =P56 -> 0 | BI56: =MROUND(IF($BH56="*",$BE56,K56),1) -> 0 | BJ56: =IF($BH56="*",$BD56,J56) -> 0.3 | BK56: =MROUND(BI56-BI56*BJ56,1) -> 0 | BL56: =IF(BH56="*",1,0) -> 0 | BM56: =_xlfn.XLOOKUP(A56,'Текущая цена на ВБ'!C:C,'Текущая цена на ВБ'!F:F) | BN56: =_xlfn.XLOOKUP(A56,'Текущая цена на ВБ'!C:C,'Текущая цена на ВБ'!H:H)
A57: =[1]Юнит!A56 -> 550445281 | B57: =[1]Юнит!C56 -> ACRF1KP101GN | C57: =[1]Юнит!D56 -> Капа зеленый/белый | D57: =[1]Юнит!E56 -> 2046391283569 | E57: 602 | F57: 0.3 | G57: 860 | H57: 0 | I57: =_xlfn.XLOOKUP(D57,[1]Юнит!$E:$E,[1]Юнит!$AN:$AN) -> 0 | J57: =$J$4 -> 0.3 | K57: =I57/(100%-J55) -> 0 | L57: =_xlfn.XLOOKUP(D57,[1]Юнит!$E:$E,[1]Юнит!$AR:$AR) -> #DIV/0! | M57: =MROUND(O57-O57*N57,1) -> 602 | N57: =_xlfn.XLOOKUP($A57,'Текущая цена на ВБ'!$C:$C,'Текущая цена на ВБ'!$K:$K,0,0)% -> 0.3 | O57: =_xlfn.XLOOKUP($A57,'Текущая цена на ВБ'!$C:$C,'Текущая цена на ВБ'!$I:$I,0,0) -> 860 | P57: =_xlfn.XLOOKUP($A57,[1]Юнит!$A:$A,[1]Юнит!$AJ:$AJ,0) -> 0 | Q57: =_xlfn.XLOOKUP($A57,'Акция 1'!$F:$F,'Акция 1'!$L:$L,0,0) -> 0 | R57: =(_xlfn.XLOOKUP($A57,'Акция 1'!$F:$F,'Акция 1'!$P:$P,0,0))% -> 0 | S57: =Q57/(100%-R57) -> 0 | T57: =_xlfn.XLOOKUP($A57,'Акция 2'!$F:$F,'Акция 2'!$L:$L,0,0) -> 0 | U57: =(_xlfn.XLOOKUP($A57,'Акция 2'!$F:$F,'Акция 2'!$O:$O,0,0))% -> 0 | V57: =T57/(100%-U57) -> 0 | W57: =_xlfn.XLOOKUP($A57,'Акция 3'!$F:$F,'Акция 3'!$L:$L,0,0) -> 0 | X57: =(_xlfn.XLOOKUP($A57,'Акция 3'!$F:$F,'Акция 3'!$P:$P,0,0))% -> 0 | Y57: =W57/(100%-X57) -> 0 | Z57: =_xlfn.XLOOKUP($A57,'Акция 4'!$F:$F,'Акция 4'!$L:$L,0,0) -> 0 | AA57: =(_xlfn.XLOOKUP($A57,'Акция 4'!$F:$F,'Акция 4'!$P:$P,0,0))% -> 0 | AB57: =Z57/(100%-AA57) -> 0 | AC57: =_xlfn.XLOOKUP($A57,'Акция 5'!$F:$F,'Акция 5'!$L:$L,0,0) -> 0 | AD57: =(_xlfn.XLOOKUP($A57,'Акция 5'!$F:$F,'Акция 5'!O:O,0,0))% -> 0 | AE57: =AC57/(100%-AD57) -> 0 | AF57: =_xlfn.XLOOKUP($A57,'Акция 6'!$F:$F,'Акция 6'!$L:$L,0,0) -> 0 | AG57: =(_xlfn.XLOOKUP($A57,'Акция 6'!$F:$F,'Акция 6'!$O:$O,0,0))% -> 0 | AH57: =AF57/(100%-AG57) -> 0 | AI57: =_xlfn.XLOOKUP($A57,'Акция 7'!$F:$F,'Акция 7'!$L:$L,0,0) -> 0 | AJ57: =(_xlfn.XLOOKUP($A57,'Акция 7'!$F:$F,'Акция 7'!$O:$O,0,0))% -> 0 | AK57: =AI57/(100%-AJ57) -> 0 | AL57: =_xlfn.XLOOKUP($A57,'Акция 8'!$F:$F,'Акция 8'!$L:$L,0,0) -> 0 | AM57: =(_xlfn.XLOOKUP($A57,'Акция 8'!$F:$F,'Акция 8'!$S:$S,0,0))% -> 0 | AN57: =AL57/(100%-AM57) -> 0 | AO57: =_xlfn.XLOOKUP($A57,'Акция 9'!$F:$F,'Акция 9'!$L:$L,0,0) -> 0 | AP57: =(_xlfn.XLOOKUP($A57,'Акция 9'!$F:$F,'Акция 9'!$O:$O,0,0))% -> 0 | AQ57: =AO57/(100%-AP57) -> 0 | AR57: =_xlfn.XLOOKUP($A57,'Акция 10'!$F:$F,'Акция 10'!$L:$L,0,0) -> 0 | AS57: =(_xlfn.XLOOKUP($A57,'Акция 10'!$F:$F,'Акция 10'!$O:$O,0,0))% -> 0 | AT57: =AR57/(100%-AS57) -> 0 | AU57: =_xlfn.XLOOKUP($A57,'Акция 11'!$F:$F,'Акция 11'!$L:$L,0,0) -> 0 | AV57: =(_xlfn.XLOOKUP($A57,'Акция 11'!$F:$F,'Акция 11'!$O:$O,0,0))% -> 0 | AW57: =AU57/(100%-AV57) -> 0 | BA57: =MAX($Q57,$T57,W57,Z57,AC57,AF57,AL57,AO57,AR57,AU57,AX57,AI57) -> 0 | BB57: =IF(BA57=0,0,_xlfn.XLOOKUP($BA57,$Q57:$AZ57,$Q$1:$AZ$1,0,0)) -> 0 | BC57: =_xlfn.XLOOKUP($BB57,$Q$1:$AZ$1,$Q57:$AZ57,0,0) -> 0 | BD57: =IF(BA57=0,0,$BD$3) -> 0 | BE57: =BC57/(100%-BD57) -> 0 | BF57: =_xlfn.XLOOKUP(A57,[1]Юнит!$A:$A,[1]Юнит!$AU:$AU,0) -> 0 | BG57: =P57 -> 0 | BI57: =MROUND(IF($BH57="*",$BE57,K57),1) -> 0 | BJ57: =IF($BH57="*",$BD57,J57) -> 0.3 | BK57: =MROUND(BI57-BI57*BJ57,1) -> 0 | BL57: =IF(BH57="*",1,0) -> 0 | BM57: =_xlfn.XLOOKUP(A57,'Текущая цена на ВБ'!C:C,'Текущая цена на ВБ'!F:F) | BN57: =_xlfn.XLOOKUP(A57,'Текущая цена на ВБ'!C:C,'Текущая цена на ВБ'!H:H)
A58: =[1]Юнит!A57 -> 550445283 | B58: =[1]Юнит!C57 -> ACRF1KP102GN | C58: =[1]Юнит!D57 -> Капа зеленый/черный | D58: =[1]Юнит!E57 -> 2046391283613 | E58: 602 | F58: 0.3 | G58: 860 | H58: 0 | I58: =_xlfn.XLOOKUP(D58,[1]Юнит!$E:$E,[1]Юнит!$AN:$AN) -> 0 | J58: =$J$4 -> 0.3 | K58: =I58/(100%-J56) -> 0 | L58: =_xlfn.XLOOKUP(D58,[1]Юнит!$E:$E,[1]Юнит!$AR:$AR) -> #DIV/0! | M58: =MROUND(O58-O58*N58,1) -> 602 | N58: =_xlfn.XLOOKUP($A58,'Текущая цена на ВБ'!$C:$C,'Текущая цена на ВБ'!$K:$K,0,0)% -> 0.3 | O58: =_xlfn.XLOOKUP($A58,'Текущая цена на ВБ'!$C:$C,'Текущая цена на ВБ'!$I:$I,0,0) -> 860 | P58: =_xlfn.XLOOKUP($A58,[1]Юнит!$A:$A,[1]Юнит!$AJ:$AJ,0) -> 0 | Q58: =_xlfn.XLOOKUP($A58,'Акция 1'!$F:$F,'Акция 1'!$L:$L,0,0) -> 0 | R58: =(_xlfn.XLOOKUP($A58,'Акция 1'!$F:$F,'Акция 1'!$P:$P,0,0))% -> 0 | S58: =Q58/(100%-R58) -> 0 | T58: =_xlfn.XLOOKUP($A58,'Акция 2'!$F:$F,'Акция 2'!$L:$L,0,0) -> 0 | U58: =(_xlfn.XLOOKUP($A58,'Акция 2'!$F:$F,'Акция 2'!$O:$O,0,0))% -> 0 | V58: =T58/(100%-U58) -> 0 | W58: =_xlfn.XLOOKUP($A58,'Акция 3'!$F:$F,'Акция 3'!$L:$L,0,0) -> 0 | X58: =(_xlfn.XLOOKUP($A58,'Акция 3'!$F:$F,'Акция 3'!$P:$P,0,0))% -> 0 | Y58: =W58/(100%-X58) -> 0 | Z58: =_xlfn.XLOOKUP($A58,'Акция 4'!$F:$F,'Акция 4'!$L:$L,0,0) -> 0 | AA58: =(_xlfn.XLOOKUP($A58,'Акция 4'!$F:$F,'Акция 4'!$P:$P,0,0))% -> 0 | AB58: =Z58/(100%-AA58) -> 0 | AC58: =_xlfn.XLOOKUP($A58,'Акция 5'!$F:$F,'Акция 5'!$L:$L,0,0) -> 0 | AD58: =(_xlfn.XLOOKUP($A58,'Акция 5'!$F:$F,'Акция 5'!O:O,0,0))% -> 0 | AE58: =AC58/(100%-AD58) -> 0 | AF58: =_xlfn.XLOOKUP($A58,'Акция 6'!$F:$F,'Акция 6'!$L:$L,0,0) -> 0 | AG58: =(_xlfn.XLOOKUP($A58,'Акция 6'!$F:$F,'Акция 6'!$O:$O,0,0))% -> 0 | AH58: =AF58/(100%-AG58) -> 0 | AI58: =_xlfn.XLOOKUP($A58,'Акция 7'!$F:$F,'Акция 7'!$L:$L,0,0) -> 0 | AJ58: =(_xlfn.XLOOKUP($A58,'Акция 7'!$F:$F,'Акция 7'!$O:$O,0,0))% -> 0 | AK58: =AI58/(100%-AJ58) -> 0 | AL58: =_xlfn.XLOOKUP($A58,'Акция 8'!$F:$F,'Акция 8'!$L:$L,0,0) -> 0 | AM58: =(_xlfn.XLOOKUP($A58,'Акция 8'!$F:$F,'Акция 8'!$S:$S,0,0))% -> 0 | AN58: =AL58/(100%-AM58) -> 0 | AO58: =_xlfn.XLOOKUP($A58,'Акция 9'!$F:$F,'Акция 9'!$L:$L,0,0) -> 0 | AP58: =(_xlfn.XLOOKUP($A58,'Акция 9'!$F:$F,'Акция 9'!$O:$O,0,0))% -> 0 | AQ58: =AO58/(100%-AP58) -> 0 | AR58: =_xlfn.XLOOKUP($A58,'Акция 10'!$F:$F,'Акция 10'!$L:$L,0,0) -> 0 | AS58: =(_xlfn.XLOOKUP($A58,'Акция 10'!$F:$F,'Акция 10'!$O:$O,0,0))% -> 0 | AT58: =AR58/(100%-AS58) -> 0 | AU58: =_xlfn.XLOOKUP($A58,'Акция 11'!$F:$F,'Акция 11'!$L:$L,0,0) -> 0 | AV58: =(_xlfn.XLOOKUP($A58,'Акция 11'!$F:$F,'Акция 11'!$O:$O,0,0))% -> 0 | AW58: =AU58/(100%-AV58) -> 0 | BA58: =MAX($Q58,$T58,W58,Z58,AC58,AF58,AL58,AO58,AR58,AU58,AX58,AI58) -> 0 | BB58: =IF(BA58=0,0,_xlfn.XLOOKUP($BA58,$Q58:$AZ58,$Q$1:$AZ$1,0,0)) -> 0 | BC58: =_xlfn.XLOOKUP($BB58,$Q$1:$AZ$1,$Q58:$AZ58,0,0) -> 0 | BD58: =IF(BA58=0,0,$BD$3) -> 0 | BE58: =BC58/(100%-BD58) -> 0 | BF58: =_xlfn.XLOOKUP(A58,[1]Юнит!$A:$A,[1]Юнит!$AU:$AU,0) -> 0 | BG58: =P58 -> 0 | BI58: =MROUND(IF($BH58="*",$BE58,K58),1) -> 0 | BJ58: =IF($BH58="*",$BD58,J58) -> 0.3 | BK58: =MROUND(BI58-BI58*BJ58,1) -> 0 | BL58: =IF(BH58="*",1,0) -> 0 | BM58: =_xlfn.XLOOKUP(A58,'Текущая цена на ВБ'!C:C,'Текущая цена на ВБ'!F:F) | BN58: =_xlfn.XLOOKUP(A58,'Текущая цена на ВБ'!C:C,'Текущая цена на ВБ'!H:H)
A59: =[1]Юнит!A58 -> 186826338 | B59: =[1]Юнит!C58 -> ACRA7TB201BC | C59: =[1]Юнит!D58 -> Таблетница прям 7*2 черн | D59: =[1]Юнит!E58 -> 2038891723249 | E59: 868 | F59: 0.4 | G59: 1447 | H59: 0.21931833 | I59: =_xlfn.XLOOKUP(D59,[1]Юнит!$E:$E,[1]Юнит!$AN:$AN) -> 869 | J59: =$J$4 -> 0.3 | K59: =I59/(100%-J57) -> 1241.4286 | L59: =_xlfn.XLOOKUP(D59,[1]Юнит!$E:$E,[1]Юнит!$AR:$AR) -> 0.21974366 | M59: =MROUND(O59-O59*N59,1) -> 868 | N59: =_xlfn.XLOOKUP($A59,'Текущая цена на ВБ'!$C:$C,'Текущая цена на ВБ'!$K:$K,0,0)% -> 0.4 | O59: =_xlfn.XLOOKUP($A59,'Текущая цена на ВБ'!$C:$C,'Текущая цена на ВБ'!$I:$I,0,0) -> 1447 | P59: =_xlfn.XLOOKUP($A59,[1]Юнит!$A:$A,[1]Юнит!$AJ:$AJ,0) -> 0.21908919 | Q59: =_xlfn.XLOOKUP($A59,'Акция 1'!$F:$F,'Акция 1'!$L:$L,0,0) -> 0 | R59: =(_xlfn.XLOOKUP($A59,'Акция 1'!$F:$F,'Акция 1'!$P:$P,0,0))% -> 0 | S59: =Q59/(100%-R59) -> 0 | T59: =_xlfn.XLOOKUP($A59,'Акция 2'!$F:$F,'Акция 2'!$L:$L,0,0) -> 868 | U59: =(_xlfn.XLOOKUP($A59,'Акция 2'!$F:$F,'Акция 2'!$O:$O,0,0))% -> 0.3 | V59: =T59/(100%-U59) -> 1240 | W59: =_xlfn.XLOOKUP($A59,'Акция 3'!$F:$F,'Акция 3'!$L:$L,0,0) -> 638 | X59: =(_xlfn.XLOOKUP($A59,'Акция 3'!$F:$F,'Акция 3'!$P:$P,0,0))% -> 0.49 | Y59: =W59/(100%-X59) -> 1250.9804 | Z59: =_xlfn.XLOOKUP($A59,'Акция 4'!$F:$F,'Акция 4'!$L:$L,0,0) -> 0 | AA59: =(_xlfn.XLOOKUP($A59,'Акция 4'!$F:$F,'Акция 4'!$P:$P,0,0))% -> 0 | AB59: =Z59/(100%-AA59) -> 0 | AC59: =_xlfn.XLOOKUP($A59,'Акция 5'!$F:$F,'Акция 5'!$L:$L,0,0) -> 0 | AD59: =(_xlfn.XLOOKUP($A59,'Акция 5'!$F:$F,'Акция 5'!O:O,0,0))% -> 0 | AE59: =AC59/(100%-AD59) -> 0 | AF59: =_xlfn.XLOOKUP($A59,'Акция 6'!$F:$F,'Акция 6'!$L:$L,0,0) -> 0 | AG59: =(_xlfn.XLOOKUP($A59,'Акция 6'!$F:$F,'Акция 6'!$O:$O,0,0))% -> 0 | AH59: =AF59/(100%-AG59) -> 0 | AI59: =_xlfn.XLOOKUP($A59,'Акция 7'!$F:$F,'Акция 7'!$L:$L,0,0) -> 0 | AJ59: =(_xlfn.XLOOKUP($A59,'Акция 7'!$F:$F,'Акция 7'!$O:$O,0,0))% -> 0 | AK59: =AI59/(100%-AJ59) -> 0 | AL59: =_xlfn.XLOOKUP($A59,'Акция 8'!$F:$F,'Акция 8'!$L:$L,0,0) -> 0 | AM59: =(_xlfn.XLOOKUP($A59,'Акция 8'!$F:$F,'Акция 8'!$S:$S,0,0))% -> 0 | AN59: =AL59/(100%-AM59) -> 0 | AO59: =_xlfn.XLOOKUP($A59,'Акция 9'!$F:$F,'Акция 9'!$L:$L,0,0) -> 0 | AP59: =(_xlfn.XLOOKUP($A59,'Акция 9'!$F:$F,'Акция 9'!$O:$O,0,0))% -> 0 | AQ59: =AO59/(100%-AP59) -> 0 | AR59: =_xlfn.XLOOKUP($A59,'Акция 10'!$F:$F,'Акция 10'!$L:$L,0,0) -> 0 | AS59: =(_xlfn.XLOOKUP($A59,'Акция 10'!$F:$F,'Акция 10'!$O:$O,0,0))% -> 0 | AT59: =AR59/(100%-AS59) -> 0 | AU59: =_xlfn.XLOOKUP($A59,'Акция 11'!$F:$F,'Акция 11'!$L:$L,0,0) -> 0 | AV59: =(_xlfn.XLOOKUP($A59,'Акция 11'!$F:$F,'Акция 11'!$O:$O,0,0))% -> 0 | AW59: =AU59/(100%-AV59) -> 0 | BA59: =MAX($Q59,$T59,W59,Z59,AC59,AF59,AL59,AO59,AR59,AU59,AX59,AI59) -> 868 | BB59: =IF(BA59=0,0,_xlfn.XLOOKUP($BA59,$Q59:$AZ59,$Q$1:$AZ$1,0,0)) -> 2 | BC59: =_xlfn.XLOOKUP($BB59,$Q$1:$AZ$1,$Q59:$AZ59,0,0) -> 868 | BD59: =IF(BA59=0,0,$BD$3) -> 0.4 | BE59: =BC59/(100%-BD59) -> 1446.6667 | BF59: =_xlfn.XLOOKUP(A59,[1]Юнит!$A:$A,[1]Юнит!$AU:$AU,0) -> 0.21892539 | BG59: =P59 -> 0.21908919 | BH59: * | BI59: =MROUND(IF($BH59="*",$BE59,K59),1) -> 1447 | BJ59: =IF($BH59="*",$BD59,J59) -> 0.4 | BK59: =MROUND(BI59-BI59*BJ59,1) -> 868 | BL59: =IF(BH59="*",1,0) -> 1 | BM59: =_xlfn.XLOOKUP(A59,'Текущая цена на ВБ'!C:C,'Текущая цена на ВБ'!F:F) -> 457 | BN59: =_xlfn.XLOOKUP(A59,'Текущая цена на ВБ'!C:C,'Текущая цена на ВБ'!H:H) -> 273
