Workbook
Name discontinueDiscount: #REF!
Name discontinueDiscount: #REF!
Name discontinueDiscount: #REF!
Name discontinueDiscount: #REF!
Name discontinueDiscount: #REF!
Name discontinueDiscount: #REF!
Name formUrl: #REF!
Name formUrl: #REF!
Name formUrl: #REF!
Name formUrl: #REF!
Name formUrl: #REF!
Name formUrl: #REF!
Name g: #REF!
Name g: #REF!
Name g: #REF!
Name g: #REF!
Name g: #REF!
Name g: #REF!
Name groupByArticles: #REF!
Name groupByArticles: #REF!
Name groupByArticles: #REF!
Name groupByArticles: #REF!
Name groupByArticles: #REF!
Name groupByArticles: #REF!
Name h: #REF!
Name h: #REF!
Name h: #REF!
Name h: #REF!
Name h: #REF!
Name h: #REF!
Name instructionsUrl: #REF!
Name instructionsUrl: #REF!
Name instructionsUrl: #REF!
Name instructionsUrl: #REF!
Name instructionsUrl: #REF!
Name instructionsUrl: #REF!
Name loadingPeriod: #REF!
Name loadingPeriod: #REF!
Name loadingPeriod: #REF!
Name loadingPeriod: #REF!
Name loadingPeriod: #REF!
Name loadingPeriod: #REF!
Name loadsPerMonth: #REF!
Name loadsPerMonth: #REF!
Name loadsPerMonth: #REF!
Name loadsPerMonth: #REF!
Name loadsPerMonth: #REF!
Name loadsPerMonth: #REF!
Name logArticles: #REF!
Name logArticles: #REF!
Name logArticles: #REF!
Name logArticles: #REF!
Name logArticles: #REF!
Name logArticles: #REF!
Name logDeficiency: #REF!
Name logDeficiency: #REF!
Name logDeficiency: #REF!
Name logDeficiency: #REF!
Name logDeficiency: #REF!
Name logDeficiency: #REF!

Sheet 1
C1: Обязательно написать номер недели | D1: 1 | AI1: на 1 единицу проданного товара
A2: Арт. ВБ | B2: Артикул поставщика | C2: Название | D2: ШК | E2: Остаток на начало недели, шт | F2: Себестоимость на 1 ед | G2: Себестоимость остатков | H2: Оборачиваемость, дн | I2: % выкупа за 30 дн с уч возврата | J2: Скорость продаж | K2: Кол-во ПРОДАЖИ | L2: Кол-во ВОЗВРАТЫ | M2: Кол-во ПРОДАЖИ-ВОЗВРАТЫ | N2: Выручка ПРОДАЖИ по Цене в карточке | O2: Выручка ПРОДАЖИ по Цене ВБ реализовал | P2: Выручка ВОЗВРАТЫ | Q2: Выручка ПРОДАЖИ (цена в карточке)- ВОЗВРАТЫ | R2: Выручка ПРОДАЖИ (ВБ реализовал)- ВОЗВРАТЫ | S2: Доля выручки, % от общего объема | T2: Себестоимость продаж | U2: Комиссия, руб | V2: Комиссия, % | W2: Логистика | X2: Хранение | Y2: Реклама | Z2: Налог 7% | AA2: Прибыль | AB2: Доля прибыли, % от общего объема | AC2: Остаток на конец недели, шт | AD2: Конверсия в корзину, % | AE2: Конверсия в заказ, % | AF2: Маржинальность, % | AG2: Рентабельность, % | AI2: Выручка на 1 ед (средняя цена продажи со скидкой) | AJ2: Себестоимость на 1 ед | AK2: Комиссия на 1 ед | AL2: Логистика на 1 ед | AM2: Хранение на 1 ед. | AN2: Реклама на 1 ед | AO2: Налог на 1 ед | AP2: Прибыль на 1 ед
A3: 1 | B3: 2 | C3: 3 | D3: 4 | E3: 5 | F3: 6 | G3: 7 | H3: 8 | I3: 9 | J3: 10 | K3: 11 | L3: 12 | M3: 13 | N3: 14 | O3: 15 | P3: 16 | Q3: 17 | R3: 18 | S3: 19 | T3: 20 | U3: 21 | V3: 22 | W3: 23 | X3: 24 | Y3: 25 | Z3: 26 | AA3: 27 | AB3: 19 | AC3: 28 | AD3: 30 | AE3: 31 | AF3: 32 | AG3: 33 | AH3: 34 | AI3: 35 | AJ3: 36 | AK3: 37 | AL3: 38 | AM3: 39 | AN3: 40 | AO3: 41 | AP3: 42
A4: 169112569 | B4: ACRF1BN101PN | C4: Бандаж для лица розовый | D4: 2038161736993 | E4: 0 | F4: 111 | G4: 0 | H4: 513.33333 | I4: 100 | J4: 0.3 | K4: 0 | L4: 0 | M4: 0 | N4: 0 | O4: 0 | P4: 0 | Q4: 0 | R4: 0 | S4: 0 | T4: 0 | U4: -6.532459 | V4: 0 | W4: 0 | X4: 150.92 | Z4: 0 | AA4: -144.38754 | AB4: -0.014696206 | AC4: 154 | AD4: 7 | AE4: 33 | AF4: 0 | AG4: 0 | AI4: 0 | AJ4: 111 | AK4: 0 | AL4: 0 | AM4: 150.92 | AN4: 0 | AP4: 0
A5: 169153168 | B5: ACRF1BN101BC | C5: Бандаж для лица черный | D5: 2038162681926 | E5: 0 | F5: 90 | G5: 0 | H5: 999 | I5: 0 | J5: 0 | K5: 0 | L5: 0 | M5: 0 | N5: 0 | O5: 0 | P5: 0 | Q5: 0 | R5: 0 | S5: 0 | T5: 0 | U5: -2.9990164 | V5: 0 | W5: 0 | X5: 222.46 | Z5: 0 | AA5: -219.46098 | AB5: -0.022337411 | AC5: 227 | AD5: 5 | AE5: 0 | AF5: 0 | AG5: 0 | AI5: 0 | AJ5: 90 | AK5: 0 | AL5: 0 | AM5: 222.46 | AN5: 0 | AP5: 0
A6: 169395410 | B6: ACRF1BN201GR | C6: Бандаж для лица серый | D6: 2038172050200 | E6: 0 | F6: 206 | G6: 0 | H6: 258.75 | I6: 100 | J6: 0.8 | K6: 0 | L6: 0 | M6: 0 | N6: 0 | O6: 0 | P6: 0 | Q6: 0 | R6: 0 | S6: 0 | T6: 0 | U6: -10.700492 | V6: 0 | W6: 0 | X6: 202.86 | Z6: 0 | AA6: -192.15951 | AB6: -0.019558583 | AC6: 207 | AD6: 15 | AE6: 30 | AF6: 0 | AG6: 0 | AI6: 0 | AJ6: 206 | AK6: 0 | AL6: 0 | AM6: 202.86 | AN6: 0 | AP6: 0
A7: 172832355 | B7: AHMA7BW101BG | C7: Мешки 7 шт. | D7: 2038337652454 | E7: 0 | F7: 375 | G7: 0 | H7: 999 | I7: 0 | J7: 0 | K7: 0 | L7: 0 | M7: 0 | N7: 0 | O7: 0 | P7: 0 | Q7: 0 | R7: 0 | S7: 0 | T7: 0 | U7: 0 | V7: 0 | W7: 0 | X7: 496.3896 | Z7: 0 | AA7: -496.3896 | AB7: -0.050524054 | AC7: 134 | AD7: 12 | AE7: 0 | AF7: 0 | AG7: 0 | AI7: 0 | AJ7: 375 | AK7: 0 | AL7: 0 | AM7: 496.3896 | AN7: 0 | AP7: 0
A8: 176500218 | B8: AHMA1BW101BG | C8: Мешок для бюстгалтеров | D8: 2038597850744 | E8: 0 | F8: 71 | G8: 0 | H8: 676 | I8: 100 | J8: 0.5 | K8: 2 | L8: 0 | M8: 2 | N8: 987 | O8: 613 | P8: 0 | Q8: 987 | R8: 613 | S8: 0.020208233 | T8: 142 | U8: 297.00557 | V8: 0.3009175 | W8: 121.96 | X8: 333.2 | Z8: 42.91 | AA8: 49.924426 | AB8: 0.005081461 | AC8: 338 | AD8: 10 | AE8: 40 | AF8: 0.050581992 | AG8: 0.35158047 | AI8: 493.5 | AJ8: 71 | AK8: 148.50279 | AL8: 60.98 | AM8: 166.6 | AN8: 0 | AO8: 21.455 | AP8: 24.962213
A9: 177404837 | B9: AHMA3BW101BG | C9: Мешки 3 шт. | D9: 2038627692689 | E9: 0 | F9: 166 | G9: 0 | H9: 413.33333 | I9: 100 | J9: 0.3 | K9: 0 | L9: 0 | M9: 0 | N9: 0 | O9: 0 | P9: 0 | Q9: 0 | R9: 0 | S9: 0 | T9: 0 | U9: -10.445574 | V9: 0 | W9: 0 | X9: 303.8 | Z9: 0 | AA9: -293.35443 | AB9: -0.029858512 | AC9: 124 | AD9: 5 | AE9: 50 | AF9: 0 | AG9: 0 | AI9: 0 | AJ9: 166 | AK9: 0 | AL9: 0 | AM9: 303.8 | AN9: 0 | AP9: 0
A10: 177405495 | B10: AHMA3BW102BG | C10: Мешки/деликат 3 шт. | D10: 2038627713902 | E10: 0 | F10: 156 | G10: 0 | H10: 416 | I10: 100 | J10: 0.5 | K10: 1 | L10: 0 | M10: 1 | N10: 989.4 | O10: 657 | P10: 0 | Q10: 989.4 | R10: 657 | S10: 0.020257371 | T10: 156 | U10: 287.17951 | V10: 0.29025622 | W10: 110.48 | X10: 348.194 | Z10: 45.99 | AA10: 41.556492 | AB10: 0.004229747 | AC10: 208 | AD10: 18 | AE10: 29 | AF10: 0.04200171 | AG10: 0.26638777 | AI10: 989.4 | AJ10: 156 | AK10: 287.17951 | AL10: 110.48 | AM10: 348.194 | AN10: 0 | AO10: 45.99 | AP10: 41.556492
A11: 176721350 | B11: AHMA3BW201WH | C11: Мешки/шнурок мелк 3 шт. | D11: 2038606201642 | E11: 0 | F11: 145 | G11: 0 | H11: 259 | I11: 100 | J11: 1 | K11: 1 | L11: 0 | M11: 1 | N11: 812 | O11: 543 | P11: 0 | Q11: 812 | R11: 543 | S11: 0.016625213 | T11: 145 | U11: 228.00508 | V11: 0.28079444 | W11: 61.77 | X11: 254.8 | Z11: 38.01 | AA11: 84.414918 | AB11: 0.0085920089 | AC11: 259 | AD11: 7 | AE11: 50 | AF11: 0.10395926 | AG11: 0.58217185 | AI11: 812 | AJ11: 145 | AK11: 228.00508 | AL11: 61.77 | AM11: 254.8 | AN11: 0 | AO11: 38.01 | AP11: 84.414918
A12: 176723275 | B12: AHMA3BW202WH | C12: Мешки/шнурок крупн 3 шт. | D12: 2038606256161 | E12: 0 | F12: 145 | G12: 0 | H12: 41.666667 | I12: 100 | J12: 3 | K12: 4 | L12: 0 | M12: 4 | N12: 3157 | O12: 2074 | P12: 0 | Q12: 3157 | R12: 2074 | S12: 0.064637681 | T12: 580 | U12: 879.75656 | V12: 0.27866853 | W12: 210.65 | X12: 126.42 | Z12: 145.18 | AA12: 1214.9934 | AB12: 0.12366575 | AC12: 125 | AD12: 16 | AE12: 52 | AF12: 0.38485697 | AG12: 2.0948163 | AI12: 789.25 | AJ12: 145 | AK12: 219.93914 | AL12: 52.6625 | AM12: 31.605 | AN12: 0 | AO12: 36.295 | AP12: 303.74836
A13: 204615141 | B13: AHMA2BW201WH | C13: Мешки 2 шт. серый | D13: 2039404446068 | E13: 0 | F13: 92 | G13: 0 | H13: 656.66667 | I13: 100 | J13: 0.3 | K13: 1 | L13: 0 | M13: 1 | N13: 654 | O13: 410 | P13: 0 | Q13: 654 | R13: 410 | S13: 0.013390258 | T13: 92 | U13: 175.14869 | V13: 0.26781145 | W13: 50.68 | X13: 194.04 | Z13: 28.7 | AA13: 113.43131 | AB13: 0.011545386 | AC13: 197 | AD13: 10 | AE13: 50 | AF13: 0.17344237 | AG13: 1.232949 | AI13: 654 | AJ13: 92 | AK13: 175.14869 | AL13: 50.68 | AM13: 194.04 | AN13: 0 | AO13: 28.7 | AP13: 113.43131
A14: 236074677 | B14: AHMA2BW202WH | C14: Мешки 2 шт. розовый | D14: 2040278862540 | E14: 0 | F14: 149 | G14: 0 | H14: 999 | I14: 0 | J14: 0 | K14: 0 | L14: 0 | M14: 0 | N14: 0 | O14: 0 | P14: 0 | Q14: 0 | R14: 0 | S14: 0 | T14: 0 | U14: 0 | V14: 0 | W14: 0 | X14: 49 | Z14: 0 | AA14: -49 | AB14: -0.0049873701 | AC14: 50 | AD14: 0 | AE14: 0 | AF14: 0 | AG14: 0 | AI14: 0 | AJ14: 149 | AK14: 0 | AL14: 0 | AM14: 49 | AN14: 0 | AP14: 0
A15: 236929187 | B15: AHMA1BW112WH | C15: Мешок 60*80 крупн | D15: 2040335626849 | E15: 0 | F15: 93 | G15: 0 | H15: 104.61538 | I15: 80 | J15: 1.3 | K15: 4 | L15: 0 | M15: 4 | N15: 2683 | O15: 1708 | P15: 0 | Q15: 2683 | R15: 1708 | S15: 0.054932815 | T15: 372 | U15: 798.35 | V15: 0.2975587 | W15: 190.08 | X15: 137.2 | Z15: 119.56 | AA15: 1065.81 | AB15: 0.10848141 | AC15: 136 | AD15: 16 | AE15: 25 | AF15: 0.39724562 | AG15: 2.8650806 | AI15: 670.75 | AJ15: 93 | AK15: 199.5875 | AL15: 47.52 | AM15: 34.3 | AN15: 0 | AO15: 29.89 | AP15: 266.4525
A16: 236929188 | B16: AHMA1BW111WH | C16: Мешок 60*80 мелк | D16: 2040335648124 | E16: 0 | F16: 93 | G16: 0 | H16: 22.325581 | I16: 94 | J16: 4.3 | K16: 5 | L16: 0 | M16: 5 | N16: 2932.96 | O16: 1895.06 | P16: 0 | Q16: 2932.96 | R16: 1895.06 | S16: 0.060050596 | T16: 465 | U16: 802.28311 | V16: 0.27354042 | W16: 230.17 | X16: 98.98 | Z16: 132.6542 | AA16: 1203.8727 | AB16: 0.12253385 | AC16: 96 | AD16: 23 | AE16: 34 | AF16: 0.41046338 | AG16: 2.5889735 | AI16: 586.592 | AJ16: 93 | AK16: 160.45662 | AL16: 46.034 | AM16: 19.796 | AN16: 0 | AO16: 26.53084 | AP16: 240.77454
A17: 239235150 | B17: AHMA1BW301WH | C17: Мешок для обуви L - 30 см | D17: 2040478720961 | E17: 0 | F17: 115 | G17: 0 | H17: 999 | I17: 0 | J17: 0 | K17: 0 | L17: 0 | M17: 0 | N17: 0 | O17: 0 | P17: 0 | Q17: 0 | R17: 0 | S17: 0 | T17: 0 | U17: 0 | V17: 0 | W17: 0 | X17: 59.78 | Z17: 0 | AA17: -59.78 | AB17: -0.0060845915 | AC17: 61 | AD17: 25 | AE17: 0 | AF17: 0 | AG17: 0 | AI17: 0 | AJ17: 115 | AK17: 0 | AL17: 0 | AM17: 59.78 | AN17: 0 | AP17: 0
A18: 239233529 | B18: AHMA1BW302WH | C18: Мешок для обуви XL - 35 см | D18: 2040478696884 | E18: 0 | F18: 144 | G18: 0 | H18: 276.66667 | I18: 100 | J18: 0.3 | K18: 0 | L18: 0 | M18: 0 | N18: 0 | O18: 0 | P18: 0 | Q18: 0 | R18: 0 | S18: 0 | T18: 0 | U18: -10.624918 | V18: 0 | W18: 0 | X18: 157.47424 | Z18: 0 | AA18: -146.84932 | AB18: -0.014946774 | AC18: 83 | AD18: 20 | AE18: 50 | AF18: 0 | AG18: 0 | AI18: 0 | AJ18: 144 | AK18: 0 | AL18: 0 | AM18: 157.47424 | AN18: 0 | AP18: 0
A19: 173605843 | B19: ACRH1MS101RJ | C19: Массажер для пальцев | D19: 2038430289250 | E19: 0 | F19: 66 | G19: 0 | H19: 1846.6667 | I19: 100 | J19: 0.3 | K19: 0 | L19: 0 | M19: 0 | N19: 0 | O19: 0 | P19: 0 | Q19: 0 | R19: 0 | S19: 0 | T19: 0 | U19: 0 | V19: 0 | W19: 0 | X19: 542.92 | Z19: 0 | AA19: -542.92 | AB19: -0.055260061 | AC19: 554 | AD19: 60 | AE19: 33 | AF19: 0 | AG19: 0 | AI19: 0 | AJ19: 66 | AK19: 0 | AL19: 0 | AM19: 542.92 | AN19: 0 | AP19: 0
A20: 223420736 | B20: ACRB1MS101RJ | C20: Массажер для тела оранжевый | D20: 2039813223373 | E20: 0 | F20: 151 | G20: 0 | H20: 41.25 | I20: 100 | J20: 0.8 | K20: 0 | L20: 0 | M20: 0 | N20: 0 | O20: 0 | P20: 0 | Q20: 0 | R20: 0 | S20: 0 | T20: 0 | U20: -8.7685246 | V20: 0 | W20: 0 | X20: 32.34 | Z20: 0 | AA20: -23.571475 | AB20: -0.002399177 | AC20: 33 | AD20: 9 | AE20: 43 | AF20: 0 | AG20: 0 | AI20: 0 | AJ20: 151 | AK20: 0 | AL20: 0 | AM20: 32.34 | AN20: 0 | AP20: 0
A21: 275208801 | B21: ACRB1MS101PN | C21: Массажер для тела розовый | D21: 2041591042329 | E21: 0 | F21: 151 | G21: 0 | H21: 999 | I21: 0 | J21: 0 | K21: 1 | L21: 0 | M21: 1 | N21: 698 | O21: 525 | P21: 0 | Q21: 698 | R21: 525 | S21: 0.014291131 | T21: 151 | U21: 203.60639 | V21: 0.2916997 | W21: 71.28 | X21: 74.48 | Z21: 36.75 | AA21: 160.88361 | AB21: 0.016375226 | AC21: 75 | AD21: 0 | AE21: 0 | AF21: 0.23049227 | AG21: 1.0654543 | AI21: 698 | AJ21: 151 | AK21: 203.60639 | AL21: 71.28 | AM21: 74.48 | AN21: 0 | AO21: 36.75 | AP21: 160.88361
A22: 275208802 | B22: ACRB1MS101BL | C22: Массажер для тела голубой | D22: 2041591055954 | E22: 0 | F22: 151 | G22: 0 | H22: 93.333333 | I22: 100 | J22: 0.3 | K22: 1 | L22: 0 | M22: 1 | N22: 794 | O22: 569 | P22: 0 | Q22: 794 | R22: 569 | S22: 0.016256674 | T22: 151 | U22: 217.82656 | V22: 0.27434075 | W22: 55.44 | X22: 28.42 | Z22: 39.83 | AA22: 301.48344 | AB22: 0.030685908 | AC22: 28 | AD22: 6 | AE22: 25 | AF22: 0.37970207 | AG22: 1.9965791 | AI22: 794 | AJ22: 151 | AK22: 217.82656 | AL22: 55.44 | AM22: 28.42 | AN22: 0 | AO22: 39.83 | AP22: 301.48344
A23: 236072835 | B23: ACRB1MS106WH | C23: Мяч с шипами белый 6 см | D23: 2040278804496 | E23: 0 | F23: 59 | G23: 0 | H23: 252.66667 | I23: 83 | J23: 1.5 | K23: 1 | L23: 0 | M23: 1 | N23: 802 | O23: 582 | P23: 0 | Q23: 802 | R23: 582 | S23: 0.016420469 | T23: 59 | U23: 234.1477 | V23: 0.29195474 | W23: 119.49 | X23: 372.4 | Z23: 40.74 | AA23: -23.777705 | AB23: -0.0024201676 | AC23: 379 | AD23: 19 | AE23: 46 | AF23: -0.029648011 | AG23: -0.40301195 | AI23: 802 | AJ23: 59 | AK23: 234.1477 | AL23: 119.49 | AM23: 372.4 | AN23: 0 | AO23: 40.74 | AP23: -23.777705
A24: 236072836 | B24: ACRB1MS106PN | C24: Мяч с шипами розовый 6 см | D24: 2040278810534 | E24: 0 | F24: 64 | G24: 0 | H24: 168.33333 | I24: 86 | J24: 1.8 | K24: 3 | L24: 0 | M24: 3 | N24: 1816 | O24: 1258 | P24: 0 | Q24: 1816 | R24: 1258 | S24: 0.03718151 | T24: 192 | U24: 549.52934 | V24: 0.30260426 | W24: 153.59 | X24: 299.88 | Z24: 88.06 | AA24: 532.94066 | AB24: 0.054244332 | AC24: 303 | AD24: 30 | AE24: 50 | AF24: 0.29346952 | AG24: 2.7757326 | AI24: 605.33333 | AJ24: 64 | AK24: 183.17645 | AL24: 51.196667 | AM24: 99.96 | AN24: 0 | AO24: 29.353333 | AP24: 177.64689
A25: 236072834 | B25: ACRB1MS106BL | C25: Мяч с шипами голубой 6 см | D25: 2040278804649 | E25: 0 | F25: 59 | G25: 0 | H25: 783.33333 | I25: 100 | J25: 0.3 | K25: 0 | L25: 0 | M25: 0 | N25: 0 | O25: 0 | P25: 0 | Q25: 0 | R25: 0 | S25: 0 | T25: 0 | U25: -9.8537705 | V25: 0 | W25: 0 | X25: 230.3 | Z25: 0 | AA25: -220.44623 | AB25: -0.022437693 | AC25: 235 | AD25: 20 | AE25: 25 | AF25: 0 | AG25: 0 | AI25: 0 | AJ25: 59 | AK25: 0 | AL25: 0 | AM25: 230.3 | AN25: 0 | AP25: 0
A26: 223671295 | B26: ACRB1MS106RJ | C26: Мяч с шипами оранжевый 6 см | D26: 2039818580389 | E26: 0 | F26: 59 | G26: 0 | H26: 999 | I26: 0 | J26: 0 | K26: 0 | L26: 0 | M26: 0 | N26: 0 | O26: 0 | P26: 0 | Q26: 0 | R26: 0 | S26: 0 | T26: 0 | U26: 0 | V26: 0 | W26: 0 | X26: 443.94 | Z26: 0 | AA26: -443.94 | AB26: -0.045185573 | AC26: 453 | AD26: 0 | AE26: 0 | AF26: 0 | AG26: 0 | AI26: 0 | AJ26: 59 | AK26: 0 | AL26: 0 | AM26: 443.94 | AN26: 0 | AP26: 0
A27: 370591238 | B27: ACRB1MS106BС | C27: Мяч с шипами черный 6 см | D27: 2043369663040 | E27: 0 | F27: 49 | G27: 0 | H27: 196 | I27: 67 | J27: 1 | K27: 1 | L27: 0 | M27: 1 | N27: 479 | O27: 343 | P27: 0 | Q27: 479 | R27: 343 | S27: 0.0098072376 | T27: 49 | U27: 112.90115 | V27: 0.23570177 | W27: 45.93 | X27: 193.06 | Z27: 24.01 | AA27: 54.098852 | AB27: 0.0055063469 | AC27: 196 | AD27: 25 | AE27: 67 | AF27: 0.11294124 | AG27: 1.1040582 | AI27: 479 | AJ27: 49 | AK27: 112.90115 | AL27: 45.93 | AM27: 193.06 | AN27: 0 | AO27: 24.01 | AP27: 54.098852
A28: 419145391 | B28: ACRB1MS107WH | C28: Мяч с шипами белый 7 см | D28: 2044025326637 | E28: 0 | F28: 62 | G28: 0 | H28: 3.8461538 | I28: 60 | J28: 1.3 | K28: 1 | L28: 0 | M28: 1 | N28: 753 | O28: 520 | P28: 0 | Q28: 753 | R28: 520 | S28: 0.015417223 | T28: 62 | U28: 201.5841 | V28: 0.26770797 | W28: 63.16 | X28: 5.88 | Z28: 36.4 | AA28: 383.9759 | AB28: 0.039082243 | AC28: 5 | AD28: 13 | AE28: 50 | AF28: 0.50992816 | AG28: 6.1931597 | AI28: 753 | AJ28: 62 | AK28: 201.5841 | AL28: 63.16 | AM28: 5.88 | AN28: 0 | AO28: 36.4 | AP28: 383.9759
A29: 419145389 | B29: ACRB1MS107PN | C29: Мяч с шипами розовый 7 см | D29: 2044025316447 | E29: 0 | F29: 63 | G29: 0 | H29: 999 | I29: 0 | J29: 0 | K29: 0 | L29: 0 | M29: 0 | N29: 0 | O29: 0 | P29: 0 | Q29: 0 | R29: 0 | S29: 0 | T29: 0 | U29: 0 | V29: 0 | W29: 0 | X29: 60.76 | Z29: 0 | AA29: -60.76 | AB29: -0.0061843389 | AC29: 62 | AD29: 0 | AE29: 0 | AF29: 0 | AG29: 0 | AI29: 0 | AJ29: 63 | AK29: 0 | AL29: 0 | AM29: 60.76 | AN29: 0 | AP29: 0
A30: 419145748 | B30: ACRB1MS107BL | C30: Мяч с шипами голубой 7 см | D30: 2044025338661 | E30: 0 | F30: 63 | G30: 0 | H30: 999 | I30: 0 | J30: 0 | K30: 0 | L30: 0 | M30: 0 | N30: 0 | O30: 0 | P30: 0 | Q30: 0 | R30: 0 | S30: 0 | T30: 0 | U30: 0 | V30: 0 | W30: 0 | X30: 78.4 | Z30: 0 | AA30: -78.4 | AB30: -0.0079797922 | AC30: 80 | AD30: 0 | AE30: 0 | AF30: 0 | AG30: 0 | AI30: 0 | AJ30: 63 | AK30: 0 | AL30: 0 | AM30: 78.4 | AN30: 0 | AP30: 0
A31: 419141548 | B31: ACRB1MS107RJ | C31: Мяч с шипами оранжевый 7 см | D31: 2044025288003 | E31: 0 | F31: 63 | G31: 0 | H31: 999 | I31: 0 | J31: 0 | K31: 0 | L31: 0 | M31: 0 | N31: 0 | O31: 0 | P31: 0 | Q31: 0 | R31: 0 | S31: 0 | T31: 0 | U31: 0 | V31: 0 | W31: 0 | X31: 75.46 | Z31: 0 | AA31: -75.46 | AB31: -0.0076805499 | AC31: 77 | AD31: 29 | AE31: 0 | AF31: 0 | AG31: 0 | AI31: 0 | AJ31: 63 | AK31: 0 | AL31: 0 | AM31: 75.46 | AN31: 0 | AP31: 0
A32: 419145985 | B32: ACRB1MS107BС | C32: Мяч с шипами черный 7 см | D32: 2044025344532 | E32: 0 | F32: 63 | G32: 0 | H32: 999 | I32: 0 | J32: 0 | K32: 0 | L32: 0 | M32: 0 | N32: 0 | O32: 0 | P32: 0 | Q32: 0 | R32: 0 | S32: 0 | T32: 0 | U32: 0 | V32: 0 | W32: 0 | X32: 71.54 | Z32: 0 | AA32: -71.54 | AB32: -0.0072815603 | AC32: 73 | AD32: 0 | AE32: 0 | AF32: 0 | AG32: 0 | AI32: 0 | AJ32: 63 | AK32: 0 | AL32: 0 | AM32: 71.54 | AN32: 0 | AP32: 0
A33: 419145390 | B33: ACRB1MS109PN | C33: Мяч с шипами розовый 9 см | D33: 2044025321588 | E33: 0 | F33: 91 | G33: 0 | H33: 134 | I33: 50 | J33: 0.5 | K33: 1 | L33: 0 | M33: 1 | N33: 553 | O33: 391 | P33: 0 | Q33: 553 | R33: 391 | S33: 0.011322343 | T33: 91 | U33: 152.9818 | V33: 0.27663979 | W33: 57.91 | X33: 66.64 | Z33: 27.37 | AA33: 157.0982 | AB33: 0.015989936 | AC33: 67 | AD33: 13 | AE33: 50 | AF33: 0.28408354 | AG33: 1.7263538 | AI33: 553 | AJ33: 91 | AK33: 152.9818 | AL33: 57.91 | AM33: 66.64 | AN33: 0 | AO33: 27.37 | AP33: 157.0982
A34: 419145749 | B34: ACRB1MS109BL | C34: Мяч с шипами голубой 9 см | D34: 2044025342057 | E34: 0 | F34: 91 | G34: 0 | H34: 266.66667 | I34: 100 | J34: 0.3 | K34: 1 | L34: 0 | M34: 1 | N34: 628 | O34: 449 | P34: 0 | Q34: 628 | R34: 449 | S34: 0.012857923 | T34: 91 | U34: 203.22967 | V34: 0.32361413 | W34: 51.97 | X34: 79.38 | Z34: 31.43 | AA34: 170.99033 | AB34: 0.017403919 | AC34: 80 | AD34: 8 | AE34: 100 | AF34: 0.27227759 | AG34: 1.8790146 | AI34: 628 | AJ34: 91 | AK34: 203.22967 | AL34: 51.97 | AM34: 79.38 | AN34: 0 | AO34: 31.43 | AP34: 170.99033
A35: 419141549 | B35: ACRB1MS109RJ | C35: Мяч с шипами оранжевый 9 см | D35: 2044025291485 | E35: 0 | F35: 91 | G35: 0 | H35: 206.66667 | I35: 100 | J35: 0.3 | K35: 0 | L35: 0 | M35: 0 | N35: 0 | O35: 0 | P35: 0 | Q35: 0 | R35: 0 | S35: 0 | T35: 0 | U35: -17.477869 | V35: 0 | W35: 0 | X35: 60.76 | Z35: 0 | AA35: -43.282131 | AB35: -0.0044053879 | AC35: 62 | AD35: 13 | AE35: 100 | AF35: 0 | AG35: 0 | AI35: 0 | AJ35: 91 | AK35: 0 | AL35: 0 | AM35: 60.76 | AN35: 0 | AP35: 0
A36: 419145986 | B36: ACRB1MS109BС | C36: Мяч с шипами черный 9 см | D36: 2044025347953 | E36: 0 | F36: 91 | G36: 0 | H36: 999 | I36: 0 | J36: 0 | K36: 0 | L36: 0 | M36: 0 | N36: 0 | O36: 0 | P36: 0 | Q36: 0 | R36: 0 | S36: 0 | T36: 0 | U36: 0 | V36: 0 | W36: 0 | X36: 96.04 | Z36: 0 | AA36: -96.04 | AB36: -0.0097752454 | AC36: 98 | AD36: 14 | AE36: 0 | AF36: 0 | AG36: 0 | AI36: 0 | AJ36: 91 | AK36: 0 | AL36: 0 | AM36: 96.04 | AN36: 0 | AP36: 0
A37: 419146579 | B37: ACRB1MS109LI | C37: Мяч с шипами фиолетовый 9 см | D37: 2044025354937 | E37: 0 | F37: 91 | G37: 0 | H37: 373.33333 | I37: 0 | J37: 0.3 | K37: 0 | L37: 0 | M37: 0 | N37: 0 | O37: 0 | P37: 0 | Q37: 0 | R37: 0 | S37: 0 | T37: 0 | U37: -16.351639 | V37: 0 | W37: 0 | X37: 109.76 | Z37: 0 | AA37: -93.408361 | AB37: -0.0095073891 | AC37: 112 | AD37: 16 | AE37: 33 | AF37: 0 | AG37: 0 | AI37: 0 | AJ37: 91 | AK37: 0 | AL37: 0 | AM37: 109.76 | AN37: 0 | AP37: 0
A38: 340734340 | B38: ACRB1MS103PN | C38: Мяч гладкий розовый | D38: 2042985583893 | E38: 0 | F38: 87 | G38: 0 | H38: 103.33333 | I38: 100 | J38: 0.3 | K38: 0 | L38: 0 | M38: 0 | N38: 0 | O38: 0 | P38: 0 | Q38: 0 | R38: 0 | S38: 0 | T38: 0 | U38: -8.362459 | V38: 0 | W38: 0 | X38: 30.38 | Z38: 0 | AA38: -22.017541 | AB38: -0.0022410128 | AC38: 31 | AD38: 8 | AE38: 100 | AF38: 0 | AG38: 0 | AI38: 0 | AJ38: 87 | AK38: 0 | AL38: 0 | AM38: 30.38 | AN38: 0 | AP38: 0
A39: 340741532 | B39: ACRB1MS103BL | C39: Мяч гладкий голубой | D39: 2042986356632 | E39: 0 | F39: 87 | G39: 0 | H39: 999 | I39: 0 | J39: 0 | K39: 0 | L39: 0 | M39: 0 | N39: 0 | O39: 0 | P39: 0 | Q39: 0 | R39: 0 | S39: 0 | T39: 0 | U39: 0 | V39: 0 | W39: 0 | X39: 80.36 | Z39: 0 | AA39: -80.36 | AB39: -0.008179287 | AC39: 82 | AD39: 17 | AE39: 0 | AF39: 0 | AG39: 0 | AI39: 0 | AJ39: 87 | AK39: 0 | AL39: 0 | AM39: 80.36 | AN39: 0 | AP39: 0
A40: 340743352 | B40: ACRB1MS103LI | C40: Мяч гладкий сиреневый | D40: 2042986372359 | E40: 0 | F40: 87 | G40: 0 | H40: 999 | I40: 0 | J40: 0 | K40: 0 | L40: 0 | M40: 0 | N40: 0 | O40: 0 | P40: 0 | Q40: 0 | R40: 0 | S40: 0 | T40: 0 | U40: 0 | V40: 0 | W40: 0 | X40: 53.9 | Z40: 0 | AA40: -53.9 | AB40: -0.0054861071 | AC40: 55 | AD40: 17 | AE40: 0 | AF40: 0 | AG40: 0 | AI40: 0 | AJ40: 87 | AK40: 0 | AL40: 0 | AM40: 53.9 | AN40: 0 | AP40: 0
A41: 340743911 | B41: ACRB1MS103RJ | C41: Мяч гладкий оранжевый | D41: 2042986377583 | E41: 0 | F41: 88 | G41: 0 | H41: 114 | I41: 100 | J41: 0.5 | K41: 0 | L41: 0 | M41: 0 | N41: 0 | O41: 0 | P41: 0 | Q41: 0 | R41: 0 | S41: 0 | T41: 0 | U41: -11.030984 | V41: 0 | W41: 0 | X41: 55.86 | Z41: 0 | AA41: -44.829016 | AB41: -0.0045628346 | AC41: 57 | AD41: 43 | AE41: 67 | AF41: 0 | AG41: 0 | AI41: 0 | AJ41: 88 | AK41: 0 | AL41: 0 | AM41: 55.86 | AN41: 0 | AP41: 0
A42: 550530967 | B42: ACRB3FR100CL | C42: Набор эластичных лент 3 шт. в мешке | D42: 2046392440640 | E42: 0 | F42: 437 | G42: 0 | H42: 999 | I42: 0 | J42: 0 | K42: 0 | L42: 0 | M42: 0 | N42: 0 | O42: 0 | P42: 0 | Q42: 0 | R42: 0 | S42: 0 | T42: 0 | U42: 0 | V42: 0 | W42: 0 | X42: 64.0332 | Z42: 0 | AA42: -64.0332 | AB42: -0.0065174952 | AC42: 33 | AD42: 17 | AE42: 0 | AF42: 0 | AG42: 0 | AI42: 0 | AJ42: 437 | AK42: 0 | AL42: 0 | AM42: 64.0332 | AN42: 0 | AP42: 0
A43: 550539998 | B43: ACRB5FR200CL | C43: Набор эластичных лент 5 шт. в мешке | D43: 2046392546618 | E43: 0 | F43: 467 | G43: 0 | H43: 999 | I43: 0 | J43: 0 | K43: 0 | L43: 0 | M43: 0 | N43: 0 | O43: 0 | P43: 0 | Q43: 0 | R43: 0 | S43: 0 | T43: 0 | U43: 0 | V43: 0 | W43: 0 | X43: 34.3 | Z43: 0 | AA43: -34.3 | AB43: -0.0034911591 | AC43: 35 | AD43: 50 | AE43: 0 | AF43: 0 | AG43: 0 | AI43: 0 | AJ43: 467 | AK43: 0 | AL43: 0 | AM43: 34.3 | AN43: 0 | AP43: 0
A44: 550539999 | B44: ACRB4FR300CL | C44: Набор эластичных лент 4 шт. | D44: 2046392546632 | E44: 0 | F44: 309 | G44: 0 | H44: 999 | I44: 0 | J44: 0 | K44: 0 | L44: 0 | M44: 0 | N44: 0 | O44: 0 | P44: 0 | Q44: 0 | R44: 0 | S44: 0 | T44: 0 | U44: 0 | V44: 0 | W44: 0 | X44: 34.3 | Z44: 0 | AA44: -34.3 | AB44: -0.0034911591 | AC44: 35 | AD44: 0 | AE44: 0 | AF44: 0 | AG44: 0 | AI44: 0 | AJ44: 309 | AK44: 0 | AL44: 0 | AM44: 34.3 | AN44: 0 | AP44: 0
A45: 550540000 | B45: ACRB5FR400CL | C45: Набор эластичных лент 5 шт. | D45: 2046392546656 | E45: 0 | F45: 142 | G45: 0 | H45: 0 | I45: 0 | J45: 0 | K45: 0 | L45: 0 | M45: 0 | N45: 0 | O45: 0 | P45: 0 | Q45: 0 | R45: 0 | S45: 0 | T45: 0 | U45: 0 | V45: 0 | W45: 0 | X45: 0 | Z45: 0 | AA45: 0 | AB45: 0 | AC45: 0 | AD45: 0 | AE45: 0 | AF45: 0 | AG45: 0 | AI45: 0 | AJ45: 142 | AK45: 0 | AL45: 0 | AM45: 0 | AN45: 0 | AP45: 0
A46: 550445272 | B46: ACRF1KP101BC | C46: Капа черный/красный - черная коробка | D46: 2046391283330 | E46: 0 | F46: 80 | G46: 0 | H46: 0 | I46: 0 | J46: 0 | K46: 0 | L46: 0 | M46: 0 | N46: 0 | O46: 0 | P46: 0 | Q46: 0 | R46: 0 | S46: 0 | T46: 0 | U46: 0 | V46: 0 | W46: 0 | X46: 0 | Z46: 0 | AA46: 0 | AB46: 0 | AC46: 0 | AD46: 0 | AE46: 0 | AF46: 0 | AG46: 0 | AI46: 0 | AJ46: 80 | AK46: 0 | AL46: 0 | AM46: 0 | AN46: 0 | AP46: 0
... A53: 550445283 | B53: ACRF1KP102GN | C53: Капа зеленый/черный | D53: 2046391283613 | E53: 0 | F53: 80 | G53: 0 | H53: 0 | I53: 0 | J53: 0 | K53: 0 | L53: 0 | M53: 0 | N53: 0 | O53: 0 | P53: 0 | Q53: 0 | R53: 0 | S53: 0 | T53: 0 | U53: 0 | V53: 0 | W53: 0 | X53: 0 | Z53: 0 | AA53: 0 | AB53: 0 | AC53: 0 | AD53: 0 | AE53: 0 | AF53: 0 | AG53: 0 | AI53: 0 | AJ53: 80 | AK53: 0 | AL53: 0 | AM53: 0 | AN53: 0 | AP53: 0
A54: 186826338 | B54: ACRA7TB201BC | C54: Таблетница прям 7*2 черн | D54: 2038891723249 | E54: 0 | F54: 171 | G54: 0 | H54: 766.25 | I54: 67 | J54: 0.8 | K54: 3 | L54: 0 | M54: 3 | N54: 2743 | O54: 1997 | P54: 0 | Q54: 2743 | R54: 1997 | S54: 0.056161279 | T54: 513 | U54: 737.02344 | V54: 0.26869247 | W54: 202.74 | X54: 603.68 | Z54: 139.79 | AA54: 546.76656 | AB54: 0.055651575 | AC54: 613 | AD54: 10 | AE54: 23 | AF54: 0.19933159 | AG54: 1.0658217 | AI54: 914.33333 | AJ54: 171 | AK54: 245.67448 | AL54: 67.58 | AM54: 201.22667 | AN54: 0 | AO54: 46.596667 | AP54: 182.25552
A55: 419130077 | B55: ACRA7TB201CL | C55: Таблетница прям 7*2 черн/цветн | D55: 2044025155923 | E55: 0 | F55: 171 | G55: 0 | H55: 340 | I55: 100 | J55: 0.8 | K55: 3 | L55: 0 | M55: 3 | N55: 2266.3 | O55: 1865.67 | P55: 0 | Q55: 2266.3 | R55: 1865.67 | S55: 0.046401133 | T55: 513 | U55: 638.36033 | V55: 0.28167512 | W55: 147.29 | X55: 269.5 | Z55: 130.5969 | AA55: 567.55277 | AB55: 0.05776726 | AC55: 272 | AD55: 8 | AE55: 43 | AF55: 0.25043144 | AG55: 1.1063407 | AI55: 755.43333 | AJ55: 171 | AK55: 212.78678 | AL55: 49.096667 | AM55: 89.833333 | AN55: 0 | AO55: 43.5323 | AP55: 189.18426
A56: 448248943 | B56: ACRA7TB201WH | C56: Таблетница прям 7*2 бел/цветн | D56: 2044516485386 | E56: 0 | F56: 171 | G56: 0 | H56: 138.66667 | I56: 100 | J56: 1.5 | K56: 6 | L56: 0 | M56: 6 | N56: 4729 | O56: 3402 | P56: 0 | Q56: 4729 | R56: 3402 | S56: 0.096823438 | T56: 1026 | U56: 1282.0493 | V56: 0.27110369 | W56: 397.56 | X56: 209.72 | Z56: 238.14 | AA56: 1575.5307 | AB56: 0.16036234 | AC56: 208 | AD56: 9 | AE56: 50 | AF56: 0.3331636 | AG56: 1.5356049 | AI56: 788.16667 | AJ56: 171 | AK56: 213.67489 | AL56: 66.26 | AM56: 34.953333 | AN56: 0 | AO56: 39.69 | AP56: 262.58844
A57: 448254852 | B57: ACRA7TB201LI | C57: Таблетница прям 7*2 сирен/цветн | D57: 2044516498812 | E57: 0 | F57: 171 | G57: 0 | H57: 999 | I57: 0 | J57: 0 | K57: 1 | L57: 0 | M57: 1 | N57: 691 | O57: 481 | P57: 0 | Q57: 691 | R57: 481 | S57: 0.01414781 | T57: 171 | U57: 186.79574 | V57: 0.27032668 | W57: 61.77 | X57: 208.74 | Z57: 33.67 | AA57: 29.024262 | AB57: 0.0029541783 | AC57: 212 | AD57: 7 | AE57: 0 | AF57: 0.042003274 | AG57: 0.16973253 | AI57: 691 | AJ57: 171 | AK57: 186.79574 | AL57: 61.77 | AM57: 208.74 | AN57: 0 | AO57: 33.67 | AP57: 29.024262
A58: 186800214 | B58: ACRA7TB101BC | C58: Таблетница круглая 7*2 черн | D58: 2038890789598 | E58: 0 | F58: 250 | G58: 0 | H58: 999 | I58: 0 | J58: 0 | K58: 0 | L58: 0 | M58: 0 | N58: 0 | O58: 0 | P58: 0 | Q58: 0 | R58: 0 | S58: 0 | T58: 0 | U58: 0 | V58: 0 | W58: 0 | X58: 306.47736 | Z58: 0 | AA58: -306.47736 | AB58: -0.031194204 | AC58: 219 | AD58: 11 | AE58: 0 | AF58: 0 | AG58: 0 | AI58: 0 | AJ58: 250 | AK58: 0 | AL58: 0 | AM58: 306.47736 | AN58: 0 | AP58: 0
A59: 298193176 | B59: ACRA7TB101CL | C59: Таблетница круглая 7*2 черн/цвет | D59: 2042160422832 | E59: 0 | F59: 250 | G59: 0 | H59: 999 | I59: 0 | J59: 0 | K59: 0 | L59: 0 | M59: 0 | N59: 0 | O59: 0 | P59: 0 | Q59: 0 | R59: 0 | S59: 0 | T59: 0 | U59: 0 | V59: 0 | W59: 0 | X59: 243.50256 | Z59: 0 | AA59: -243.50256 | AB59: -0.024784436 | AC59: 174 | AD59: 0 | AE59: 0 | AF59: 0 | AG59: 0 | AI59: 0 | AJ59: 250 | AK59: 0 | AL59: 0 | AM59: 243.50256 | AN59: 0 | AP59: 0
A60: 278515093 | B60: ACRA7TB301GR | C60: Таблетница круглая 7*2 сер | D60: 2041680530447 | E60: 0 | F60: 142 | G60: 0 | H60: 83.6 | I60: 90 | J60: 2.5 | K60: 5 | L60: 0 | M60: 5 | N60: 4025.58 | O60: 3003.9 | P60: 0 | Q60: 4025.58 | R60: 3003.9 | S60: 0.082421335 | T60: 710 | U60: 1056.9336 | V60: 0.26255437 | W60: 548.28 | X60: 299.48016 | Z60: 210.273 | AA60: 1200.6132 | AB60: 0.12220209 | AC60: 209 | AD60: 18 | AE60: 29 | AF60: 0.29824603 | AG60: 1.6910046 | AI60: 805.116 | AJ60: 142 | AK60: 211.38672 | AL60: 109.656 | AM60: 59.896032 | AN60: 0 | AO60: 42.0546 | AP60: 240.12265
A61: 345168494 | B61: ACRA7TB301CL | C61: Таблетница круглая 7*2 сер /цвет | D61: 2043048226719 | E61: 0 | F61: 142 | G61: 0 | H61: 720 | I61: 100 | J61: 0.3 | K61: 1 | L61: 0 | M61: 1 | N61: 993 | O61: 634 | P61: 0 | Q61: 993 | R61: 634 | S61: 0.020331079 | T61: 142 | U61: 267.80738 | V61: 0.26969524 | W61: 266.16 | X61: 303.67848 | Z61: 44.38 | AA61: -31.025857 | AB61: -0.0031579068 | AC61: 216 | AD61: 7 | AE61: 25 | AF61: -0.031244569 | AG61: -0.21849195 | AI61: 993 | AJ61: 142 | AK61: 267.80738 | AL61: 266.16 | AM61: 303.67848 | AN61: 0 | AO61: 44.38 | AP61: -31.025857
A62: 273516556 | B62: ACRA7TB301WH | C62: Таблетница круглая 7*2 бел | D62: 2041532808502 | E62: 0 | F62: 142 | G62: 0 | H62: 356.66667 | I62: 0 | J62: 0.3 | K62: 0 | L62: 0 | M62: 0 | N62: 0 | O62: 0 | P62: 0 | Q62: 0 | R62: 0 | S62: 0 | T62: 0 | U62: 0 | V62: 0 | W62: 0 | X62: 149.74008 | Z62: 0 | AA62: -149.74008 | AB62: -0.015241004 | AC62: 107 | AD62: 9 | AE62: 25 | AF62: 0 | AG62: 0 | AI62: 0 | AJ62: 142 | AK62: 0 | AL62: 0 | AM62: 149.74008 | AN62: 0 | AP62: 0
A63: 321907864 | B63: ACRA7TB401BC | C63: Таблетница автомат 7*2 черн | D63: 2042676873814 | E63: 0 | F63: 335 | G63: 0 | H63: 0 | I63: 0 | J63: 0 | K63: 0 | L63: 0 | M63: 0 | N63: 0 | O63: 0 | P63: 0 | Q63: 0 | R63: 0 | S63: 0 | T63: 0 | U63: 0 | V63: 0 | W63: 0 | X63: 0 | Z63: 0 | AA63: 0 | AB63: 0 | AC63: 0 | AD63: 0 | AE63: 0 | AF63: 0 | AG63: 0 | AI63: 0 | AJ63: 335 | AK63: 0 | AL63: 0 | AM63: 0 | AN63: 0 | AP63: 0
A64: 271440668 | B64: ACRB1SK101BC | C64: Скакалка черная | D64: 2041473034138 | E64: 0 | F64: 282 | G64: 0 | H64: 500 | I64: 100 | J64: 0.3 | K64: 1 | L64: 0 | M64: 1 | N64: 880 | O64: 528 | P64: 0 | Q64: 880 | R64: 528 | S64: 0.018017472 | T64: 282 | U64: 233.95492 | V64: 0.26585786 | W64: 41.18 | X64: 147.98 | Z64: 36.96 | AA64: 137.92508 | AB64: 0.014038437 | AC64: 150 | AD64: 2 | AE64: 100 | AF64: 0.15673305 | AG64: 0.48909604 | AI64: 880 | AJ64: 282 | AK64: 233.95492 | AL64: 41.18 | AM64: 147.98 | AN64: 0 | AO64: 36.96 | AP64: 137.92508
A65: 271440669 | B65: ACRB1SK101RD | C65: Скакалка красная | D65: 2041473034145 | E65: 0 | F65: 282 | G65: 0 | H65: 999 | I65: 0 | J65: 0 | K65: 0 | L65: 0 | M65: 0 | N65: 0 | O65: 0 | P65: 0 | Q65: 0 | R65: 0 | S65: 0 | T65: 0 | U65: -2.8806557 | V65: 0 | W65: 0 | X65: 137.2 | Z65: 0 | AA65: -134.31934 | AB65: -0.013671434 | AC65: 140 | AD65: 0 | AE65: 0 | AF65: 0 | AG65: 0 | AI65: 0 | AJ65: 282 | AK65: 0 | AL65: 0 | AM65: 137.2 | AN65: 0 | AP65: 0
A66: 271440670 | B66: ACRB1SK101BL | C66: Скакалка синяя | D66: 2041473034169 | E66: 0 | F66: 282 | G66: 0 | H66: 148.75 | I66: 100 | J66: 0.8 | K66: 2 | L66: 1 | M66: 1 | N66: 1658.57 | O66: 1100 | P66: 815.77 | Q66: 842.8 | R66: 284.23 | S66: 0.017255824 | T66: 282 | U66: -443.54475 | V66: -0.52627522 | W66: 141.37 | X66: 118.58 | Z66: 19.8961 | AA66: 724.49865 | AB66: 0.073741692 | AC66: 119 | AD66: 14 | AE66: 100 | AF66: 1.0256546 | AG66: 3.0653252 | AI66: 842.8 | AJ66: 282 | AK66: -443.54475 | AL66: 70.685 | AM66: 59.29 | AN66: 0 | AO66: 9.94805 | AP66: 864.4217
A67: 271441230 | B67: ACRB1SK201BC | C67: Скакалка со счетчиком | D67: 2041473042966 | E67: 0 | F67: 268 | G67: 0 | H67: 0 | I67: 0 | J67: 0 | K67: 0 | L67: 0 | M67: 0 | N67: 0 | O67: 0 | P67: 0 | Q67: 0 | R67: 0 | S67: 0 | T67: 0 | U67: 0 | V67: 0 | W67: 0 | X67: 0 | Z67: 0 | AA67: 0 | AB67: 0 | AC67: 0 | AD67: 0 | AE67: 0 | AF67: 0 | AG67: 0 | AI67: 0 | AJ67: 268 | AK67: 0 | AL67: 0 | AM67: 0 | AN67: 0 | AP67: 0
A68: 251537223 | B68: AAND1BL101RD | C68: Мяч регби красный | D68: 2040903539366 | E68: 0 | F68: 121 | G68: 0 | H68: 131.33333 | I68: 100 | J68: 1.5 | K68: 4 | L68: 0 | M68: 4 | N68: 2044 | O68: 1599 | P68: 0 | Q68: 2044 | R68: 1599 | S68: 0.041849674 | T68: 484 | U68: 429.38361 | V68: 0.21007026 | W68: 237.6 | X68: 196.98 | Z68: 111.93 | AA68: 584.10639 | AB68: 0.059452138 | AC68: 197 | AD68: 10 | AE68: 38 | AF68: 0.28576634 | AG68: 1.2068314 | AI68: 511 | AJ68: 121 | AK68: 107.3459 | AL68: 59.4 | AM68: 49.245 | AN68: 0 | AO68: 27.9825 | AP68: 146.0266
A69: 251537413 | B69: AAND1BL101BL | C69: Мяч регби синий | D69: 2040903547941 | E69: 0 | F69: 121 | G69: 0 | H69: 218 | I69: 100 | J69: 1 | K69: 3 | L69: 0 | M69: 3 | N69: 1533 | O69: 1211 | P69: 0 | Q69: 1533 | R69: 1211 | S69: 0.031387255 | T69: 363 | U69: 330.08262 | V69: 0.21531808 | W69: 149.28 | X69: 216.58 | Z69: 84.77 | AA69: 389.28738 | AB69: 0.039622862 | AC69: 218 | AD69: 11 | AE69: 33 | AF69: 0.25393828 | AG69: 1.072417 | AI69: 511 | AJ69: 121 | AK69: 110.02754 | AL69: 49.76 | AM69: 72.193333 | AN69: 0 | AO69: 28.256667 | AP69: 129.76246
A70: 251516159 | B70: AAND1BL102RD | C70: Мяч шина красный | D70: 2040902555480 | E70: 0 | F70: 137 | G70: 0 | H70: 278 | I70: 100 | J70: 0.5 | K70: 2 | L70: 0 | M70: 2 | N70: 1553 | O70: 1203 | P70: 0 | Q70: 1553 | R70: 1203 | S70: 0.031796743 | T70: 274 | U70: 317.09492 | V70: 0.20418218 | W70: 130.68 | X70: 138.18 | Z70: 84.21 | AA70: 608.83508 | AB70: 0.0619691 | AC70: 139 | AD70: 9 | AE70: 20 | AF70: 0.39203804 | AG70: 2.2220258 | AI70: 776.5 | AJ70: 137 | AK70: 158.54746 | AL70: 65.34 | AM70: 69.09 | AN70: 0 | AO70: 42.105 | AP70: 304.41754
A71: 251407392 | B71: AAND1BL102BL | C71: Мяч шина синий | D71: 2040900511679 | E71: 0 | F71: 137 | G71: 0 | H71: 57.5 | I71: 100 | J71: 2 | K71: 4 | L71: 0 | M71: 4 | N71: 2948 | O71: 2226 | P71: 0 | Q71: 2948 | R71: 2226 | S71: 0.060358531 | T71: 548 | U71: 584.99131 | V71: 0.19843667 | W71: 230.17 | X71: 116.62 | Z71: 155.82 | AA71: 1312.3987 | AB71: 0.13357996 | AC71: 115 | AD71: 20 | AE71: 22 | AF71: 0.44518273 | AG71: 2.3948881 | AI71: 737 | AJ71: 137 | AK71: 146.24783 | AL71: 57.5425 | AM71: 29.155 | AN71: 0 | AO71: 38.955 | AP71: 328.09967
A72: 302564795 | B72: AAND1ST202BL | C72: Палочка для жевания | D72: 2042253544953 | E72: 0 | F72: 204 | G72: 0 | H72: 0 | I72: 0 | J72: 0 | K72: 0 | L72: 0 | M72: 0 | N72: 0 | O72: 0 | P72: 0 | Q72: 0 | R72: 0 | S72: 0 | T72: 0 | U72: 0 | V72: 0 | W72: 0 | X72: 0 | Z72: 0 | AA72: 0 | AB72: 0 | AC72: 0 | AD72: 6 | AE72: 0 | AF72: 0 | AG72: 0 | AI72: 0 | AJ72: 204 | AK72: 0 | AL72: 0 | AM72: 0 | AN72: 0 | AP72: 0
A73: 273588520 | B73: AAND1RP301BG | C73: Канат бол бежевый 55см/520гр | D73: 2041534216404 | E73: 0 | F73: 478 | G73: 0 | H73: 999 | I73: 0 | J73: 0 | K73: 0 | L73: 0 | M73: 0 | N73: 0 | O73: 0 | P73: 0 | Q73: 0 | R73: 0 | S73: 0 | T73: 0 | U73: 0 | V73: 0 | W73: 0 | X73: 48.11408 | Z73: 0 | AA73: -48.11408 | AB73: -0.0048971984 | AC73: 17 | AD73: 13 | AE73: 0 | AF73: 0 | AG73: 0 | AI73: 0 | AJ73: 478 | AK73: 0 | AL73: 0 | AM73: 48.11408 | AN73: 0 | AP73: 0
A74: 273589771 | B74: AAND1RP301YL | C74: Канат мал желтый 55см/330гр | D74: 2041534288661 | E74: 0 | F74: 326 | G74: 0 | H74: 999 | I74: 0 | J74: 0 | K74: 0 | L74: 0 | M74: 0 | N74: 0 | O74: 0 | P74: 0 | Q74: 0 | R74: 0 | S74: 0 | T74: 0 | U74: 0 | V74: 0 | W74: 0 | X74: 27.783 | Z74: 0 | AA74: -27.783 | AB74: -0.0028278388 | AC74: 15 | AD74: 0 | AE74: 0 | AF74: 0 | AG74: 0 | AI74: 0 | AJ74: 326 | AK74: 0 | AL74: 0 | AM74: 27.783 | AN74: 0 | AP74: 0
A75: 273556717 | B75: AKTA4ST101CL | C75: Набор пробок 4 шт. в коробке нежн | D75: 2041533648312 | E75: 0 | F75: 104 | G75: 0 | H75: 84.5 | I75: 100 | J75: 2 | K75: 1 | L75: 0 | M75: 1 | N75: 610 | O75: 411 | P75: 0 | Q75: 610 | R75: 411 | S75: 0.012489384 | T75: 104 | U75: 158.16721 | V75: 0.25929051 | W75: 50.19 | X75: 166.6 | Z75: 28.77 | AA75: 102.27279 | AB75: 0.010409638 | AC75: 169 | AD75: 11 | AE75: 53 | AF75: 0.16766031 | AG75: 0.98339218 | AI75: 610 | AJ75: 104 | AK75: 158.16721 | AL75: 50.19 | AM75: 166.6 | AN75: 0 | AO75: 28.77 | AP75: 102.27279
A76: 370594147 | B76: AKTA4ST103CL | C76: Набор пробок 4 шт. в коробке ярк | D76: 2043369755509 | E76: 0 | F76: 123 | G76: 0 | H76: 81 | I76: 100 | J76: 1 | K76: 2 | L76: 0 | M76: 2 | N76: 1220 | O76: 813 | P76: 0 | Q76: 1220 | R76: 813 | S76: 0.024978768 | T76: 246 | U76: 333.92475 | V76: 0.27370881 | W76: 91.37 | X76: 81.34 | Z76: 56.91 | AA76: 410.45525 | AB76: 0.041777392 | AC76: 81 | AD76: 14 | AE76: 14 | AF76: 0.33643873 | AG76: 1.6685173 | AI76: 610 | AJ76: 123 | AK76: 166.96238 | AL76: 45.685 | AM76: 40.67 | AN76: 0 | AO76: 28.455 | AP76: 205.22762
A77: 321959186 | B77: AKTA4ST102CL | C77: Набор пробок 4 шт. | D77: 2042678197468 | E77: 0 | F77: 121 | G77: 0 | H77: 44.615385 | I77: 100 | J77: 1.3 | K77: 3 | L77: 0 | M77: 3 | N77: 1830 | O77: 1186 | P77: 0 | Q77: 1830 | R77: 1186 | S77: 0.037468152 | T77: 363 | U77: 524.35639 | V77: 0.28653355 | W77: 149.28 | X77: 59.78 | Z77: 83.02 | AA77: 650.56361 | AB77: 0.066216357 | AC77: 58 | AD77: 13 | AE77: 25 | AF77: 0.35549924 | AG77: 1.7921862 | AI77: 610 | AJ77: 121 | AK77: 174.78546 | AL77: 49.76 | AM77: 19.926667 | AN77: 0 | AO77: 27.673333 | AP77: 216.85454
A78: 273546535 | B78: AKTA2KN101YL | C78: Шпатель желтый | D78: 2041533399818 | E78: 0 | F78: 171 | G78: 0 | H78: 999 | I78: 0 | J78: 0 | K78: 0 | L78: 0 | M78: 0 | N78: 0 | O78: 0 | P78: 0 | Q78: 0 | R78: 0 | S78: 0 | T78: 0 | U78: 0 | V78: 0 | W78: 0 | X78: 68.6 | Z78: 0 | AA78: -68.6 | AB78: -0.0069823181 | AC78: 70 | AD78: 9 | AE78: 0 | AF78: 0 | AG78: 0 | AI78: 0 | AJ78: 171 | AK78: 0 | AL78: 0 | AM78: 68.6 | AN78: 0 | AP78: 0
A79: 273551028 | B79: AKTA2KN101BL | C79: Шпатель голубой | D79: 2041533587000 | E79: 0 | F79: 242 | G79: 0 | H79: 0 | I79: 0 | J79: 0 | K79: 0 | L79: 0 | M79: 0 | N79: 0 | O79: 0 | P79: 0 | Q79: 0 | R79: 0 | S79: 0 | T79: 0 | U79: 0 | V79: 0 | W79: 0 | X79: 0 | Z79: 0 | AA79: 0 | AB79: 0 | AC79: 0 | AD79: 0 | AE79: 0 | AF79: 0 | AG79: 0 | AI79: 0 | AJ79: 242 | AK79: 0 | AL79: 0 | AM79: 0 | AN79: 0 | AP79: 0
A80: 273527791 | B80: AKTA2KN102YL | C80: Нож для пиццы желтый | D80: 2041533038113 | E80: 0 | F80: 127 | G80: 0 | H80: 999 | I80: 0 | J80: 0 | K80: 0 | L80: 0 | M80: 0 | N80: 0 | O80: 0 | P80: 0 | Q80: 0 | R80: 0 | S80: 0 | T80: 0 | U80: 0 | V80: 0 | W80: 0 | X80: 126.42 | Z80: 0 | AA80: -126.42 | AB80: -0.012867415 | AC80: 129 | AD80: 3 | AE80: 0 | AF80: 0 | AG80: 0 | AI80: 0 | AJ80: 127 | AK80: 0 | AL80: 0 | AM80: 126.42 | AN80: 0 | AP80: 0
A81: 327442631 | B81: AKTA2KN102GN | C81: Нож для пиццы зеленый | D81: 2042777181566 | E81: 0 | F81: 127 | G81: 0 | H81: 999 | I81: 0 | J81: 0 | K81: 1 | L81: 0 | M81: 1 | N81: 632.44 | O81: 392 | P81: 0 | Q81: 632.44 | R81: 392 | S81: 0.01294883 | T81: 127 | U81: 187.27525 | V81: 0.29611544 | W81: 66.82 | X81: 84.28 | Z81: 27.44 | AA81: 139.62475 | AB81: 0.014211435 | AC81: 85 | AD81: 8 | AE81: 0 | AF81: 0.22077154 | AG81: 1.0994075 | AI81: 632.44 | AJ81: 127 | AK81: 187.27525 | AL81: 66.82 | AM81: 84.28 | AN81: 0 | AO81: 27.44 | AP81: 139.62475
A82: 340948906 | B82: AKTA1KN101GR | C82: Консервный нож | D82: 2042988749289 | E82: 0 | F82: 254 | G82: 0 | H82: 50 | I82: 100 | J82: 0.3 | K82: 1 | L82: 0 | M82: 1 | N82: 562 | O82: 342 | P82: 0 | Q82: 562 | R82: 342 | S82: 0.011506613 | T82: 254 | U82: 172.53033 | V82: 0.30699347 | W82: 63.16 | X82: 15.68 | Z82: 23.94 | AA82: 32.689672 | AB82: 0.003327255 | AC82: 15 | AD82: 13 | AE82: 33 | AF82: 0.058166676 | AG82: 0.1286995 | AI82: 562 | AJ82: 254 | AK82: 172.53033 | AL82: 63.16 | AM82: 15.68 | AN82: 0 | AO82: 23.94 | AP82: 32.689672
A83: 340802685 | B83: AKTA1PR101GR | C83: Чеснокодавка | D83: 2042987041841 | E83: 0 | F83: 235 | G83: 0 | H83: 999 | I83: 0 | J83: 0 | K83: 0 | L83: 0 | M83: 0 | N83: 0 | O83: 0 | P83: 0 | Q83: 0 | R83: 0 | S83: 0 | T83: 0 | U83: 0 | V83: 0 | W83: 0 | X83: 22.54 | Z83: 0 | AA83: -22.54 | AB83: -0.0022941902 | AC83: 23 | AD83: 0 | AE83: 0 | AF83: 0 | AG83: 0 | AI83: 0 | AJ83: 235 | AK83: 0 | AL83: 0 | AM83: 22.54 | AN83: 0 | AP83: 0
A84: Итого | E84: 0 | G84: 0 | H84: 0 | K84: 71 | L84: 1 | M84: 70 | N84: 49657.25 | O84: 34931.63 | P84: 815.77 | Q84: 48841.48 | R84: 34115.86 | S84: 1 | T84: 9200 | U84: 12231.226 | V84: 0.25042701 | W84: 4569.46 | X84: 10627.867 | Y84: 0 | Z84: 2388.1102 | AA84: 9824.8173 | AB84: 1 | AC84: 9515 | AF84: 0.20115724 | AG84: 1.0679149
Z85: в т.ч убытки | AA85: -4722.8018
Z86: Проверка | AA86: 9824.5669
Z87: Платная приемка | AA87: 0
Z88: Прочие удержания | AA88: 0
Z89: Штрафы | AA89: 0

Sheet 2
C1: Обязательно написать номер недели | D1: 2 | AI1: на 1 единицу проданного товара
A2: Арт. ВБ | B2: Артикул поставщика | C2: Название | D2: ШК | E2: Остаток на начало недели, шт | F2: Себестоимость на 1 ед | G2: Себестоимость остатков | H2: Оборачиваемость, дн | I2: % выкупа за 30 дн с уч возврата | J2: Скорость продаж | K2: Кол-во ПРОДАЖИ | L2: Кол-во ВОЗВРАТЫ | M2: Кол-во ПРОДАЖИ-ВОЗВРАТЫ | N2: Выручка ПРОДАЖИ по Цене в карточке | O2: Выручка ПРОДАЖИ по Цене ВБ реализовал | P2: Выручка ВОЗВРАТЫ | Q2: Выручка ПРОДАЖИ (цена в карточке)- ВОЗВРАТЫ | R2: Выручка ПРОДАЖИ (ВБ реализовал)- ВОЗВРАТЫ | S2: Доля выручки, % от общего объема | T2: Себестоимость продаж | U2: Комиссия, руб | V2: Комиссия, % | W2: Логистика | X2: Хранение | Y2: Реклама | Z2: Налог 7% | AA2: Прибыль | AB2: Доля прибыли, % от общего объема | AC2: Остаток на конец недели, шт | AD2: Конверсия в корзину, % | AE2: Конверсия в заказ, % | AF2: Маржинальность, % | AG2: Рентабельность, % | AI2: Выручка на 1 ед (средняя цена продажи со скидкой) | AJ2: Себестоимость на 1 ед | AK2: Комиссия на 1 ед | AL2: Логистика на 1 ед | AM2: Хранение на 1 ед. | AN2: Реклама на 1 ед | AO2: Налог на 1 ед | AP2: Прибыль на 1 ед
A3: 1 | B3: 2 | C3: 3 | D3: 4 | E3: 5 | F3: 6 | G3: 7 | H3: 8 | I3: 9 | J3: 10 | K3: 11 | L3: 12 | M3: 13 | N3: 14 | O3: 15 | P3: 16 | Q3: 17 | R3: 18 | S3: 19 | T3: 20 | U3: 21 | V3: 22 | W3: 23 | X3: 24 | Y3: 25 | Z3: 26 | AA3: 27 | AB3: 19 | AC3: 28 | AD3: 30 | AE3: 31 | AF3: 32 | AG3: 33 | AH3: 34 | AI3: 35 | AJ3: 36 | AK3: 37 | AL3: 38 | AM3: 39 | AN3: 40 | AO3: 41 | AP3: 42
A4: 169112569 | B4: ACRF1BN101PN | C4: Бандаж для лица розовый | D4: 2038161736993 | E4: 154 | F4: 111 | G4: 17094 | H4: 385 | I4: 50 | J4: 0.4 | K4: 2 | L4: 0 | M4: 2 | N4: 1251 | O4: 858 | P4: 0 | Q4: 1251 | R4: 858 | S4: 0.0076645972 | T4: 222 | U4: 417.90164 | V4: 0.33405407 | W4: 97.8 | X4: 152.88 | Z4: 60.06 | AA4: 300.35836 | AB4: 0.0059530199 | AC4: 154 | AD4: 11 | AE4: 43 | AF4: 0.24009461 | AG4: 1.3529656 | AI4: 625.5 | AJ4: 111 | AK4: 208.95082 | AL4: 48.9 | AM4: 76.44 | AN4: 0 | AO4: 30.03 | AP4: 150.17918
A5: 169153168 | B5: ACRF1BN101BC | C5: Бандаж для лица черный | D5: 2038162681926 | E5: 227 | F5: 90 | G5: 20430 | H5: 2270 | I5: 0 | J5: 0.1 | K5: 2 | L5: 0 | M5: 2 | N5: 1282 | O5: 1005 | P5: 0 | Q5: 1282 | R5: 1005 | S5: 0.0078545273 | T5: 180 | U5: 407.34 | V5: 0.31773791 | W5: 91.37 | X5: 224.42 | Z5: 70.35 | AA5: 308.52 | AB5: 0.0061147814 | AC5: 227 | AD5: 4 | AE5: 33 | AF5: 0.24065523 | AG5: 1.714 | AI5: 641 | AJ5: 90 | AK5: 203.67 | AL5: 45.685 | AM5: 112.21 | AN5: 0 | AO5: 35.175 | AP5: 154.26
A6: 169395410 | B6: ACRF1BN201GR | C6: Бандаж для лица серый | D6: 2038172050200 | E6: 207 | F6: 206 | G6: 42642 | H6: 295.71429 | I6: 100 | J6: 0.7 | K6: 6 | L6: 0 | M6: 6 | N6: 5864.7 | O6: 4090 | P6: 0 | Q6: 5864.7 | R6: 4090 | S6: 0.035931705 | T6: 1236 | U6: 1886.8077 | V6: 0.3217228 | W6: 283.63 | X6: 208.74 | Z6: 286.3 | AA6: 1963.2223 | AB6: 0.038910525 | AC6: 207 | AD6: 13 | AE6: 23 | AF6: 0.33475238 | AG6: 1.5883676 | AI6: 977.45 | AJ6: 206 | AK6: 314.46795 | AL6: 47.271667 | AM6: 34.79 | AN6: 0 | AO6: 47.716667 | AP6: 327.20372
A7: 172832355 | B7: AHMA7BW101BG | C7: Мешки 7 шт. | D7: 2038337652454 | E7: 134 | F7: 375 | G7: 50250 | H7: 446.66667 | I7: 100 | J7: 0.3 | K7: 1 | L7: 0 | M7: 1 | N7: 1684.61 | O7: 1227.42 | P7: 0 | Q7: 1684.61 | R7: 1227.42 | S7: 0.010321229 | T7: 375 | U7: 509.17426 | V7: 0.30225053 | W7: 189.15 | X7: 500.094 | Z7: 85.9194 | AA7: 25.272338 | AB7: 0.00050089077 | AC7: 134 | AD7: 3 | AE7: 50 | AF7: 0.015001892 | AG7: 0.067392901 | AI7: 1684.61 | AJ7: 375 | AK7: 509.17426 | AL7: 189.15 | AM7: 500.094 | AN7: 0 | AO7: 85.9194 | AP7: 25.272338
A8: 176500218 | B8: AHMA1BW101BG | C8: Мешок для бюстгалтеров | D8: 2038597850744 | E8: 338 | F8: 71 | G8: 23998 | H8: 375.55556 | I8: 100 | J8: 0.9 | K8: 5 | L8: 0 | M8: 5 | N8: 2315 | O8: 1435 | P8: 0 | Q8: 2315 | R8: 1435 | S8: 0.014183487 | T8: 355 | U8: 653.11721 | V8: 0.28212407 | W8: 289.85 | X8: 336.14 | Z8: 100.45 | AA8: 580.44279 | AB8: 0.011504216 | AC8: 338 | AD8: 15 | AE8: 35 | AF8: 0.25073123 | AG8: 1.6350501 | AI8: 463 | AJ8: 71 | AK8: 130.62344 | AL8: 57.97 | AM8: 67.228 | AN8: 0 | AO8: 20.09 | AP8: 116.08856
A9: 177404837 | B9: AHMA3BW101BG | C9: Мешки 3 шт. | D9: 2038627692689 | E9: 124 | F9: 166 | G9: 20584 | H9: 999 | I9: 0 | J9: 0 | K9: 1 | L9: 0 | M9: 1 | N9: 1103 | O9: 735 | P9: 0 | Q9: 1103 | R9: 735 | S9: 0.0067578343 | T9: 166 | U9: 317.74033 | V9: 0.2880692 | W9: 149.24 | X9: 306.25 | Z9: 51.45 | AA9: 112.31967 | AB9: 0.0022261449 | AC9: 124 | AD9: 6 | AE9: 0 | AF9: 0.10183107 | AG9: 0.67662453 | AI9: 1103 | AJ9: 166 | AK9: 317.74033 | AL9: 149.24 | AM9: 306.25 | AN9: 0 | AO9: 51.45 | AP9: 112.31967
A10: 177405495 | B10: AHMA3BW102BG | C10: Мешки/деликат 3 шт. | D10: 2038627713902 | E10: 208 | F10: 156 | G10: 32448 | H10: 2080 | I10: 0 | J10: 0.1 | K10: 1 | L10: 0 | M10: 1 | N10: 1020 | O10: 640 | P10: 0 | Q10: 1020 | R10: 640 | S10: 0.0062493119 | T10: 156 | U10: 284.37623 | V10: 0.27880023 | W10: 88.38 | X10: 348.194 | Z10: 44.8 | AA10: 98.24977 | AB10: 0.0019472834 | AC10: 208 | AD10: 4 | AE10: 20 | AF10: 0.096323304 | AG10: 0.62980622 | AI10: 1020 | AJ10: 156 | AK10: 284.37623 | AL10: 88.38 | AM10: 348.194 | AN10: 0 | AO10: 44.8 | AP10: 98.24977
A11: 176721350 | B11: AHMA3BW201WH | C11: Мешки/шнурок мелк 3 шт. | D11: 2038606201642 | E11: 259 | F11: 145 | G11: 37555 | H11: 161.875 | I11: 83 | J11: 1.6 | K11: 7 | L11: 0 | M11: 7 | N11: 5236 | O11: 3339 | P11: 0 | Q11: 5236 | R11: 3339 | S11: 0.032079801 | T11: 1015 | U11: 1565.7859 | V11: 0.29904238 | W11: 617.92 | X11: 260.68 | Z11: 233.73 | AA11: 1542.8841 | AB11: 0.030579538 | AC11: 259 | AD11: 9 | AE11: 48 | AF11: 0.29466847 | AG11: 1.5200829 | AI11: 748 | AJ11: 145 | AK11: 223.6837 | AL11: 88.274286 | AM11: 37.24 | AN11: 0 | AO11: 33.39 | AP11: 220.41201
A12: 176723275 | B12: AHMA3BW202WH | C12: Мешки/шнурок крупн 3 шт. | D12: 2038606256161 | E12: 125 | F12: 145 | G12: 18125 | H12: 41.666667 | I12: 100 | J12: 3 | K12: 23 | L12: 0 | M12: 23 | N12: 18686.2 | O12: 12026 | P12: 0 | Q12: 18686.2 | R12: 12026 | S12: 0.11448617 | T12: 3335 | U12: 5418.4638 | V12: 0.28997141 | W12: 1368.45 | X12: 145.04 | Z12: 841.82 | AA12: 7577.4262 | AB12: 0.1501825 | AC12: 125 | AD12: 13 | AE12: 43 | AF12: 0.40550921 | AG12: 2.2720918 | AI12: 812.44348 | AJ12: 145 | AK12: 235.58538 | AL12: 59.497826 | AM12: 6.306087 | AN12: 0 | AO12: 36.60087 | AP12: 329.45331
A13: 204615141 | B13: AHMA2BW201WH | C13: Мешки 2 шт. серый | D13: 2039404446068 | E13: 197 | F13: 92 | G13: 18124 | H13: 492.5 | I13: 100 | J13: 0.4 | K13: 1 | L13: 0 | M13: 1 | N13: 571.33 | O13: 342 | P13: 0 | Q13: 571.33 | R13: 342 | S13: 0.0035004111 | T13: 92 | U13: 162.39393 | V13: 0.28423842 | W13: 33.26 | X13: 194.04 | Z13: 23.94 | AA13: 65.696066 | AB13: 0.0013020779 | AC13: 197 | AD13: 14 | AE13: 60 | AF13: 0.11498795 | AG13: 0.71408767 | AI13: 571.33 | AJ13: 92 | AK13: 162.39393 | AL13: 33.26 | AM13: 194.04 | AN13: 0 | AO13: 23.94 | AP13: 65.696066
A14: 236074677 | B14: AHMA2BW202WH | C14: Мешки 2 шт. розовый | D14: 2040278862540 | E14: 50 | F14: 149 | G14: 7450 | H14: 125 | I14: 100 | J14: 0.4 | K14: 3 | L14: 0 | M14: 3 | N14: 1587.35 | O14: 1037.75 | P14: 0 | Q14: 1587.35 | R14: 1037.75 | S14: 0.0097253385 | T14: 447 | U14: 460.45934 | V14: 0.29008054 | W14: 152.04 | X14: 51.94 | Z14: 72.6425 | AA14: 403.26816 | AB14: 0.0079926637 | AC14: 50 | AD14: 29 | AE14: 27 | AF14: 0.25405119 | AG14: 0.9021659 | AI14: 529.11667 | AJ14: 149 | AK14: 153.48645 | AL14: 50.68 | AM14: 17.313333 | AN14: 0 | AO14: 24.214167 | AP14: 134.42272
A15: 236929187 | B15: AHMA1BW112WH | C15: Мешок 60*80 крупн | D15: 2040335626849 | E15: 136 | F15: 93 | G15: 12648 | H15: 64.761905 | I15: 100 | J15: 2.1 | K15: 10 | L15: 0 | M15: 10 | N15: 6562.38 | O15: 4165 | P15: 0 | Q15: 6562.38 | R15: 4165 | S15: 0.040206235 | T15: 930 | U15: 1913.6046 | V15: 0.29160222 | W15: 644.98 | X15: 143.08 | Z15: 291.55 | AA15: 2639.1654 | AB15: 0.052307531 | AC15: 136 | AD15: 11 | AE15: 33 | AF15: 0.40216589 | AG15: 2.8378123 | AI15: 656.238 | AJ15: 93 | AK15: 191.36046 | AL15: 64.498 | AM15: 14.308 | AN15: 0 | AO15: 29.155 | AP15: 263.91654
A16: 236929188 | B16: AHMA1BW111WH | C16: Мешок 60*80 мелк | D16: 2040335648124 | E16: 96 | F16: 93 | G16: 8928 | H16: 16.842105 | I16: 86 | J16: 5.7 | K16: 30 | L16: 0 | M16: 30 | N16: 17702.68 | O16: 11328 | P16: 0 | Q16: 17702.68 | R16: 11328 | S16: 0.10846036 | T16: 2790 | U16: 5018.8396 | V16: 0.28350733 | W16: 1848.32 | X16: 123.48 | Z16: 792.96 | AA16: 7129.0804 | AB16: 0.14129641 | AC16: 96 | AD16: 15 | AE16: 42 | AF16: 0.40271193 | AG16: 2.555226 | AI16: 590.08933 | AJ16: 93 | AK16: 167.29465 | AL16: 61.610667 | AM16: 4.116 | AN16: 0 | AO16: 26.432 | AP16: 237.63601
A17: 239235150 | B17: AHMA1BW301WH | C17: Мешок для обуви L - 30 см | D17: 2040478720961 | E17: 61 | F17: 115 | G17: 7015 | H17: 610 | I17: 100 | J17: 0.1 | K17: 0 | L17: 0 | M17: 0 | N17: 0 | O17: 0 | P17: 0 | Q17: 0 | R17: 0 | S17: 0 | T17: 0 | U17: 0 | V17: 0 | W17: 0 | X17: 59.78 | Z17: 0 | AA17: -59.78 | AB17: -0.0011848231 | AC17: 61 | AD17: 29 | AE17: 50 | AF17: 0 | AG17: 0 | AI17: 0 | AJ17: 115 | AK17: 0 | AL17: 0 | AM17: 59.78 | AN17: 0 | AP17: 0
A18: 239233529 | B18: AHMA1BW302WH | C18: Мешок для обуви XL - 35 см | D18: 2040478696884 | E18: 83 | F18: 144 | G18: 11952 | H18: 999 | I18: 0 | J18: 0 | K18: 1 | L18: 0 | M18: 1 | N18: 842 | O18: 536 | P18: 0 | Q18: 842 | R18: 536 | S18: 0.0051587457 | T18: 144 | U18: 245.62443 | V18: 0.29171547 | W18: 127.65 | X18: 159.37152 | Z18: 37.52 | AA18: 127.83405 | AB18: 0.0025336357 | AC18: 83 | AD18: 0 | AE18: 0 | AF18: 0.15182192 | AG18: 0.88773648 | AI18: 842 | AJ18: 144 | AK18: 245.62443 | AL18: 127.65 | AM18: 159.37152 | AN18: 0 | AO18: 37.52 | AP18: 127.83405
A19: 173605843 | B19: ACRH1MS101RJ | C19: Массажер для пальцев | D19: 2038430289250 | E19: 554 | F19: 66 | G19: 36564 | H19: 1846.6667 | I19: 100 | J19: 0.3 | K19: 2 | L19: 0 | M19: 2 | N19: 911 | O19: 629 | P19: 0 | Q19: 911 | R19: 629 | S19: 0.0055814933 | T19: 132 | U19: 274.51279 | V19: 0.30133127 | W19: 108.1 | X19: 544.88 | Z19: 44.03 | AA19: -192.52279 | AB19: -0.0038157486 | AC19: 554 | AD19: 30 | AE19: 29 | AF19: -0.21133127 | AG19: -1.458506 | AI19: 455.5 | AJ19: 66 | AK19: 137.25639 | AL19: 54.05 | AM19: 272.44 | AN19: 0 | AO19: 22.015 | AP19: -96.261393
A20: 223420736 | B20: ACRB1MS101RJ | C20: Массажер для тела оранжевый | D20: 2039813223373 | E20: 33 | F20: 151 | G20: 4983 | H20: 55 | I20: 100 | J20: 0.6 | K20: 4 | L20: 0 | M20: 4 | N20: 2619 | O20: 1837 | P20: 0 | Q20: 2619 | R20: 1837 | S20: 0.016046027 | T20: 604 | U20: 833.29295 | V20: 0.31817218 | W20: 217 | X20: 36.26 | Z20: 128.59 | AA20: 799.85705 | AB20: 0.015852946 | AC20: 33 | AD20: 9 | AE20: 29 | AF20: 0.30540552 | AG20: 1.3242666 | AI20: 654.75 | AJ20: 151 | AK20: 208.32324 | AL20: 54.25 | AM20: 9.065 | AN20: 0 | AO20: 32.1475 | AP20: 199.96426
A21: 275208801 | B21: ACRB1MS101PN | C21: Массажер для тела розовый | D21: 2041591042329 | E21: 75 | F21: 151 | G21: 11325 | H21: 999 | I21: 0 | J21: 0 | K21: 0 | L21: 0 | M21: 0 | N21: 0 | O21: 0 | P21: 0 | Q21: 0 | R21: 0 | S21: 0 | T21: 0 | U21: 0 | V21: 0 | W21: 0 | X21: 73.5 | Z21: 0 | AA21: -73.5 | AB21: -0.0014567497 | AC21: 75 | AD21: 4 | AE21: 0 | AF21: 0 | AG21: 0 | AI21: 0 | AJ21: 151 | AK21: 0 | AL21: 0 | AM21: 73.5 | AN21: 0 | AP21: 0
A22: 275208802 | B22: ACRB1MS101BL | C22: Массажер для тела голубой | D22: 2041591055954 | E22: 28 | F22: 151 | G22: 4228 | H22: 280 | I22: 100 | J22: 0.1 | K22: 1 | L22: 0 | M22: 1 | N22: 714 | O22: 485 | P22: 0 | Q22: 714 | R22: 485 | S22: 0.0043745183 | T22: 151 | U22: 224.83885 | V22: 0.31490035 | W22: 50.68 | X22: 28.42 | Z22: 33.95 | AA22: 225.11115 | AB22: 0.0044616409 | AC22: 28 | AD22: 9 | AE22: 6 | AF22: 0.31528172 | AG22: 1.4908023 | AI22: 714 | AJ22: 151 | AK22: 224.83885 | AL22: 50.68 | AM22: 28.42 | AN22: 0 | AO22: 33.95 | AP22: 225.11115
A23: 236072835 | B23: ACRB1MS106WH | C23: Мяч с шипами белый 6 см | D23: 2040278804496 | E23: 379 | F23: 59 | G23: 22361 | H23: 189.5 | I23: 78 | J23: 2 | K23: 8 | L23: 0 | M23: 8 | N23: 6756 | O23: 4862 | P23: 0 | Q23: 6756 | R23: 4862 | S23: 0.041392501 | T23: 472 | U23: 2069.5126 | V23: 0.30632218 | W23: 669.68 | X23: 379.26 | Z23: 340.34 | AA23: 2825.2074 | AB23: 0.055994832 | AC23: 379 | AD23: 18 | AE23: 29 | AF23: 0.41817753 | AG23: 5.9856088 | AI23: 844.5 | AJ23: 59 | AK23: 258.68908 | AL23: 83.71 | AM23: 47.4075 | AN23: 0 | AO23: 42.5425 | AP23: 353.15092
A24: 236072836 | B24: ACRB1MS106PN | C24: Мяч с шипами розовый 6 см | D24: 2040278810534 | E24: 303 | F24: 64 | G24: 19392 | H24: 178.23529 | I24: 100 | J24: 1.7 | K24: 8 | L24: 0 | M24: 8 | N24: 4623.01 | O24: 3113 | P24: 0 | Q24: 4623.01 | R24: 3113 | S24: 0.028324148 | T24: 512 | U24: 1390.0566 | V24: 0.30068214 | W24: 530.87 | X24: 304.78 | Z24: 217.91 | AA24: 1667.3934 | AB24: 0.033047278 | AC24: 303 | AD24: 18 | AE24: 31 | AF24: 0.36067269 | AG24: 3.2566278 | AI24: 577.87625 | AJ24: 64 | AK24: 173.75707 | AL24: 66.35875 | AM24: 38.0975 | AN24: 0 | AO24: 27.23875 | AP24: 208.42418
A25: 236072834 | B25: ACRB1MS106BL | C25: Мяч с шипами голубой 6 см | D25: 2040278804649 | E25: 235 | F25: 59 | G25: 13865 | H25: 587.5 | I25: 0 | J25: 0.4 | K25: 1 | L25: 0 | M25: 1 | N25: 595 | O25: 420 | P25: 0 | Q25: 595 | R25: 420 | S25: 0.0036454319 | T25: 59 | U25: 167.30016 | V25: 0.28117675 | W25: 381.1 | X25: 231.28 | Z25: 29.4 | AA25: -273.08016 | AB25: -0.0054123736 | AC25: 235 | AD25: 7 | AE25: 38 | AF25: -0.45895826 | AG25: -4.6284774 | AI25: 595 | AJ25: 59 | AK25: 167.30016 | AL25: 381.1 | AM25: 231.28 | AN25: 0 | AO25: 29.4 | AP25: -273.08016
A26: 223671295 | B26: ACRB1MS106RJ | C26: Мяч с шипами оранжевый 6 см | D26: 2039818580389 | E26: 453 | F26: 59 | G26: 26727 | H26: 1132.5 | I26: 0 | J26: 0.4 | K26: 0 | L26: 0 | M26: 0 | N26: 0 | O26: 0 | P26: 0 | Q26: 0 | R26: 0 | S26: 0 | T26: 0 | U26: -22.443443 | V26: 0 | W26: 106.62 | X26: 443.94 | Z26: 0 | AA26: -528.11656 | AB26: -0.010467125 | AC26: 453 | AD26: 10 | AE26: 30 | AF26: 0 | AG26: 0 | AI26: 0 | AJ26: 59 | AK26: 0 | AL26: 106.62 | AM26: 443.94 | AN26: 0 | AP26: 0
A27: 370591238 | B27: ACRB1MS106BС | C27: Мяч с шипами черный 6 см | D27: 2043369663040 | E27: 196 | F27: 49 | G27: 9604 | H27: 122.5 | I27: 71 | J27: 1.6 | K27: 6 | L27: 0 | M27: 6 | N27: 3068 | O27: 2125 | P27: 0 | Q27: 3068 | R27: 2125 | S27: 0.01879695 | T27: 294 | U27: 911.64426 | V27: 0.29714611 | W27: 648.08 | X27: 197.96 | Z27: 148.75 | AA27: 867.56574 | AB27: 0.017194914 | AC27: 196 | AD27: 20 | AE27: 38 | AF27: 0.28277892 | AG27: 2.9509039 | AI27: 511.33333 | AJ27: 49 | AK27: 151.94071 | AL27: 108.01333 | AM27: 32.993333 | AN27: 0 | AO27: 24.791667 | AP27: 144.59429
A28: 419145391 | B28: ACRB1MS107WH | C28: Мяч с шипами белый 7 см | D28: 2044025326637 | E28: 5 | F28: 62 | G28: 310 | H28: 4.5454545 | I28: 80 | J28: 1.1 | K28: 5 | L28: 0 | M28: 5 | N28: 3524.06 | O28: 2504 | P28: 0 | Q28: 3524.06 | R28: 2504 | S28: 0.021591127 | T28: 310 | U28: 1086.0475 | V28: 0.30818077 | W28: 433.01 | X28: 9.8 | Z28: 175.28 | AA28: 1509.9225 | AB28: 0.029926247 | AC28: 5 | AD28: 17 | AE28: 24 | AF28: 0.42846105 | AG28: 4.8707176 | AI28: 704.812 | AJ28: 62 | AK28: 217.20951 | AL28: 86.602 | AM28: 1.96 | AN28: 0 | AO28: 35.056 | AP28: 301.98449
A29: 419145389 | B29: ACRB1MS107PN | C29: Мяч с шипами розовый 7 см | D29: 2044025316447 | E29: 62 | F29: 63 | G29: 3906 | H29: 999 | I29: 0 | J29: 0 | K29: 0 | L29: 0 | M29: 0 | N29: 0 | O29: 0 | P29: 0 | Q29: 0 | R29: 0 | S29: 0 | T29: 0 | U29: 0 | V29: 0 | W29: 0 | X29: 60.76 | Z29: 0 | AA29: -60.76 | AB29: -0.0012042465 | AC29: 62 | AD29: 5 | AE29: 0 | AF29: 0 | AG29: 0 | AI29: 0 | AJ29: 63 | AK29: 0 | AL29: 0 | AM29: 60.76 | AN29: 0 | AP29: 0
A30: 419145748 | B30: ACRB1MS107BL | C30: Мяч с шипами голубой 7 см | D30: 2044025338661 | E30: 80 | F30: 63 | G30: 5040 | H30: 999 | I30: 0 | J30: 0 | K30: 0 | L30: 0 | M30: 0 | N30: 0 | O30: 0 | P30: 0 | Q30: 0 | R30: 0 | S30: 0 | T30: 0 | U30: 0 | V30: 0 | W30: 0 | X30: 78.4 | Z30: 0 | AA30: -78.4 | AB30: -0.0015538664 | AC30: 80 | AD30: 0 | AE30: 0 | AF30: 0 | AG30: 0 | AI30: 0 | AJ30: 63 | AK30: 0 | AL30: 0 | AM30: 78.4 | AN30: 0 | AP30: 0
A31: 419141548 | B31: ACRB1MS107RJ | C31: Мяч с шипами оранжевый 7 см | D31: 2044025288003 | E31: 77 | F31: 63 | G31: 4851 | H31: 999 | I31: 0 | J31: 0 | K31: 0 | L31: 0 | M31: 0 | N31: 0 | O31: 0 | P31: 0 | Q31: 0 | R31: 0 | S31: 0 | T31: 0 | U31: 0 | V31: 0 | W31: 0 | X31: 75.46 | Z31: 0 | AA31: -75.46 | AB31: -0.0014955964 | AC31: 77 | AD31: 8 | AE31: 0 | AF31: 0 | AG31: 0 | AI31: 0 | AJ31: 63 | AK31: 0 | AL31: 0 | AM31: 75.46 | AN31: 0 | AP31: 0
A32: 419145985 | B32: ACRB1MS107BС | C32: Мяч с шипами черный 7 см | D32: 2044025344532 | E32: 73 | F32: 63 | G32: 4599 | H32: 730 | I32: 0 | J32: 0.1 | K32: 0 | L32: 0 | M32: 0 | N32: 0 | O32: 0 | P32: 0 | Q32: 0 | R32: 0 | S32: 0 | T32: 0 | U32: -7.5831148 | V32: 0 | W32: 0 | X32: 71.54 | Z32: 0 | AA32: -63.956885 | AB32: -0.0012676078 | AC32: 73 | AD32: 4 | AE32: 100 | AF32: 0 | AG32: 0 | AI32: 0 | AJ32: 63 | AK32: 0 | AL32: 0 | AM32: 71.54 | AN32: 0 | AP32: 0
A33: 419145390 | B33: ACRB1MS109PN | C33: Мяч с шипами розовый 9 см | D33: 2044025321588 | E33: 67 | F33: 91 | G33: 6097 | H33: 670 | I33: 0 | J33: 0.1 | K33: 0 | L33: 0 | M33: 0 | N33: 0 | O33: 0 | P33: 0 | Q33: 0 | R33: 0 | S33: 0 | T33: 0 | U33: -3.4232787 | V33: 0 | W33: 94.55 | X33: 65.66 | Z33: 0 | AA33: -156.78672 | AB33: -0.0031074696 | AC33: 67 | AD33: 9 | AE33: 25 | AF33: 0 | AG33: 0 | AI33: 0 | AJ33: 91 | AK33: 0 | AL33: 94.55 | AM33: 65.66 | AN33: 0 | AP33: 0
A34: 419145749 | B34: ACRB1MS109BL | C34: Мяч с шипами голубой 9 см | D34: 2044025342057 | E34: 80 | F34: 91 | G34: 7280 | H34: 999 | I34: 0 | J34: 0 | K34: 0 | L34: 0 | M34: 0 | N34: 0 | O34: 0 | P34: 0 | Q34: 0 | R34: 0 | S34: 0 | T34: 0 | U34: 0 | V34: 0 | W34: 0 | X34: 78.4 | Z34: 0 | AA34: -78.4 | AB34: -0.0015538664 | AC34: 80 | AD34: 0 | AE34: 0 | AF34: 0 | AG34: 0 | AI34: 0 | AJ34: 91 | AK34: 0 | AL34: 0 | AM34: 78.4 | AN34: 0 | AP34: 0
A35: 419141549 | B35: ACRB1MS109RJ | C35: Мяч с шипами оранжевый 9 см | D35: 2044025291485 | E35: 62 | F35: 91 | G35: 5642 | H35: 155 | I35: 67 | J35: 0.4 | K35: 3 | L35: 0 | M35: 3 | N35: 1490 | O35: 1050 | P35: 0 | Q35: 1490 | R35: 1050 | S35: 0.0091288968 | T35: 273 | U35: 459.79902 | V35: 0.30858994 | W35: 166.31 | X35: 63.7 | Z35: 73.5 | AA35: 453.69098 | AB35: 0.0089920302 | AC35: 62 | AD35: 31 | AE35: 30 | AF35: 0.30449059 | AG35: 1.6618717 | AI35: 496.66667 | AJ35: 91 | AK35: 153.26634 | AL35: 55.436667 | AM35: 21.233333 | AN35: 0 | AO35: 24.5 | AP35: 151.23033
A36: 419145986 | B36: ACRB1MS109BС | C36: Мяч с шипами черный 9 см | D36: 2044025347953 | E36: 98 | F36: 91 | G36: 8918 | H36: 999 | I36: 0 | J36: 0 | K36: 0 | L36: 0 | M36: 0 | N36: 0 | O36: 0 | P36: 0 | Q36: 0 | R36: 0 | S36: 0 | T36: 0 | U36: 0 | V36: 0 | W36: 0 | X36: 96.04 | Z36: 0 | AA36: -96.04 | AB36: -0.0019034863 | AC36: 98 | AD36: 7 | AE36: 0 | AF36: 0 | AG36: 0 | AI36: 0 | AJ36: 91 | AK36: 0 | AL36: 0 | AM36: 96.04 | AN36: 0 | AP36: 0
A37: 419146579 | B37: ACRB1MS109LI | C37: Мяч с шипами фиолетовый 9 см | D37: 2044025354937 | E37: 112 | F37: 91 | G37: 10192 | H37: 1120 | I37: 100 | J37: 0.1 | K37: 0 | L37: 0 | M37: 0 | N37: 0 | O37: 0 | P37: 0 | Q37: 0 | R37: 0 | S37: 0 | T37: 0 | U37: -4.2108197 | V37: 0 | W37: 0 | X37: 109.76 | Z37: 0 | AA37: -105.54918 | AB37: -0.0020919557 | AC37: 112 | AD37: 20 | AE37: 14 | AF37: 0 | AG37: 0 | AI37: 0 | AJ37: 91 | AK37: 0 | AL37: 0 | AM37: 109.76 | AN37: 0 | AP37: 0
A38: 340734340 | B38: ACRB1MS103PN | C38: Мяч гладкий розовый | D38: 2042985583893 | E38: 31 | F38: 87 | G38: 2697 | H38: 28.181818 | I38: 100 | J38: 1.1 | K38: 2 | L38: 0 | M38: 2 | N38: 768.67 | O38: 530 | P38: 0 | Q38: 768.67 | R38: 530 | S38: 0.0047094692 | T38: 174 | U38: 219.5923 | V38: 0.28567824 | W38: 167.7 | X38: 32.34 | Z38: 37.1 | AA38: 137.9377 | AB38: 0.0027338873 | AC38: 31 | AD38: 24 | AE38: 57 | AF38: 0.17944984 | AG38: 0.79274543 | AI38: 384.335 | AJ38: 87 | AK38: 109.79615 | AL38: 83.85 | AM38: 16.17 | AN38: 0 | AO38: 18.55 | AP38: 68.968852
A39: 340741532 | B39: ACRB1MS103BL | C39: Мяч гладкий голубой | D39: 2042986356632 | E39: 82 | F39: 87 | G39: 7134 | H39: 999 | I39: 0 | J39: 0 | K39: 0 | L39: 0 | M39: 0 | N39: 0 | O39: 0 | P39: 0 | Q39: 0 | R39: 0 | S39: 0 | T39: 0 | U39: 0 | V39: 0 | W39: 0 | X39: 80.36 | Z39: 0 | AA39: -80.36 | AB39: -0.0015927131 | AC39: 82 | AD39: 0 | AE39: 0 | AF39: 0 | AG39: 0 | AI39: 0 | AJ39: 87 | AK39: 0 | AL39: 0 | AM39: 80.36 | AN39: 0 | AP39: 0
A40: 340743352 | B40: ACRB1MS103LI | C40: Мяч гладкий сиреневый | D40: 2042986372359 | E40: 55 | F40: 87 | G40: 4785 | H40: 137.5 | I40: 100 | J40: 0.4 | K40: 0 | L40: 0 | M40: 0 | N40: 0 | O40: 0 | P40: 0 | Q40: 0 | R40: 0 | S40: 0 | T40: 0 | U40: -17.916721 | V40: 0 | W40: 0 | X40: 53.9 | Z40: 0 | AA40: -35.983279 | AB40: -0.00071317867 | AC40: 55 | AD40: 22 | AE40: 30 | AF40: 0 | AG40: 0 | AI40: 0 | AJ40: 87 | AK40: 0 | AL40: 0 | AM40: 53.9 | AN40: 0 | AP40: 0
A41: 340743911 | B41: ACRB1MS103RJ | C41: Мяч гладкий оранжевый | D41: 2042986377583 | E41: 57 | F41: 88 | G41: 5016 | H41: 999 | I41: 0 | J41: 0 | K41: 1 | L41: 0 | M41: 1 | N41: 369.57 | O41: 261 | P41: 0 | Q41: 369.57 | R41: 261 | S41: 0.0022642727 | T41: 88 | U41: 116.27344 | V41: 0.31461818 | W41: 63.16 | X41: 56.84 | Z41: 18.27 | AA41: 27.026557 | AB41: 0.00053565892 | AC41: 57 | AD41: 7 | AE41: 0 | AF41: 0.073129738 | AG41: 0.30711997 | AI41: 369.57 | AJ41: 88 | AK41: 116.27344 | AL41: 63.16 | AM41: 56.84 | AN41: 0 | AO41: 18.27 | AP41: 27.026557
A42: 550530967 | B42: ACRB3FR100CL | C42: Набор эластичных лент 3 шт. в мешке | D42: 2046392440640 | E42: 33 | F42: 437 | G42: 14421 | H42: 82.5 | I42: 0 | J42: 0.4 | K42: 0 | L42: 0 | M42: 0 | N42: 0 | O42: 0 | P42: 0 | Q42: 0 | R42: 0 | S42: 0 | T42: 0 | U42: -27.50918 | V42: 0 | W42: 149.66 | X42: 64.0332 | Z42: 0 | AA42: -186.18402 | AB42: -0.003690116 | AC42: 33 | AD42: 43 | AE42: 100 | AF42: 0 | AG42: 0 | AI42: 0 | AJ42: 437 | AK42: 0 | AL42: 149.66 | AM42: 64.0332 | AN42: 0 | AP42: 0
A43: 550539998 | B43: ACRB5FR200CL | C43: Набор эластичных лент 5 шт. в мешке | D43: 2046392546618 | E43: 35 | F43: 467 | G43: 16345 | H43: 999 | I43: 0 | J43: 0 | K43: 0 | L43: 0 | M43: 0 | N43: 0 | O43: 0 | P43: 0 | Q43: 0 | R43: 0 | S43: 0 | T43: 0 | U43: 0 | V43: 0 | W43: 0 | X43: 34.3 | Z43: 0 | AA43: -34.3 | AB43: -0.00067981655 | AC43: 35 | AD43: 0 | AE43: 0 | AF43: 0 | AG43: 0 | AI43: 0 | AJ43: 467 | AK43: 0 | AL43: 0 | AM43: 34.3 | AN43: 0 | AP43: 0
A44: 550539999 | B44: ACRB4FR300CL | C44: Набор эластичных лент 4 шт. | D44: 2046392546632 | E44: 35 | F44: 309 | G44: 10815 | H44: 999 | I44: 0 | J44: 0 | K44: 0 | L44: 0 | M44: 0 | N44: 0 | O44: 0 | P44: 0 | Q44: 0 | R44: 0 | S44: 0 | T44: 0 | U44: 0 | V44: 0 | W44: 0 | X44: 34.3 | Z44: 0 | AA44: -34.3 | AB44: -0.00067981655 | AC44: 35 | AD44: 0 | AE44: 0 | AF44: 0 | AG44: 0 | AI44: 0 | AJ44: 309 | AK44: 0 | AL44: 0 | AM44: 34.3 | AN44: 0 | AP44: 0
A45: 550540000 | B45: ACRB5FR400CL | C45: Набор эластичных лент 5 шт. | D45: 2046392546656 | E45: 0 | F45: 142 | G45: 0 | H45: 0 | I45: 0 | J45: 0 | K45: 0 | L45: 0 | M45: 0 | N45: 0 | O45: 0 | P45: 0 | Q45: 0 | R45: 0 | S45: 0 | T45: 0 | U45: 0 | V45: 0 | W45: 0 | X45: 0 | Z45: 0 | AA45: 0 | AB45: 0 | AC45: 0 | AD45: 0 | AE45: 0 | AF45: 0 | AG45: 0 | AI45: 0 | AJ45: 142 | AK45: 0 | AL45: 0 | AM45: 0 | AN45: 0 | AP45: 0
A46: 550445272 | B46: ACRF1KP101BC | C46: Капа черный/красный - черная коробка | D46: 2046391283330 | E46: 0 | F46: 80 | G46: 0 | H46: 0 | I46: 0 | J46: 0 | K46: 0 | L46: 0 | M46: 0 | N46: 0 | O46: 0 | P46: 0 | Q46: 0 | R46: 0 | S46: 0 | T46: 0 | U46: 0 | V46: 0 | W46: 0 | X46: 0 | Z46: 0 | AA46: 0 | AB46: 0 | AC46: 0 | AD46: 0 | AE46: 0 | AF46: 0 | AG46: 0 | AI46: 0 | AJ46: 80 | AK46: 0 | AL46: 0 | AM46: 0 | AN46: 0 | AP46: 0
A47: 550445274 | B47: ACRF1KP102BC | C47: Капа черный/белый-черная коробка | D47: 2046391283385 | E47: 0 | F47: 80 | G47: 0 | H47: 0 | I47: 0 | J47: 0 | K47: 0 | L47: 0 | M47: 0 | N47: 0 | O47: 0 | P47: 0 | Q47: 0 | R47: 0 | S47: 0 | T47: 0 | U47: 0 | V47: 0 | W47: 0 | X47: 0 | Z47: 0 | AA47: 0 | AB47: 0 | AC47: 0 | AD47: 0 | AE47: 0 | AF47: 0 | AG47: 0 | AI47: 0 | AJ47: 80 | AK47: 0 | AL47: 0 | AM47: 0 | AN47: 0 | AP47: 0
A48: 550445275 | B48: ACRF1KP103BC | C48: Капа белый/черный | D48: 2046391283415 | E48: 0 | F48: 80 | G48: 0 | H48: 0 | I48: 0 | J48: 0 | K48: 0 | L48: 0 | M48: 0 | N48: 0 | O48: 0 | P48: 0 | Q48: 0 | R48: 0 | S48: 0 | T48: 0 | U48: 0 | V48: 0 | W48: 0 | X48: 0 | Z48: 0 | AA48: 0 | AB48: 0 | AC48: 0 | AD48: 0 | AE48: 0 | AF48: 0 | AG48: 0 | AI48: 0 | AJ48: 80 | AK48: 0 | AL48: 0 | AM48: 0 | AN48: 0 | AP48: 0
A49: 550445277 | B49: ACRF1KP101RD | C49: Капа белый/красный | D49: 2046391283446 | E49: 0 | F49: 80 | G49: 0 | H49: 0 | I49: 0 | J49: 0 | K49: 0 | L49: 0 | M49: 0 | N49: 0 | O49: 0 | P49: 0 | Q49: 0 | R49: 0 | S49: 0 | T49: 0 | U49: 0 | V49: 0 | W49: 0 | X49: 0 | Z49: 0 | AA49: 0 | AB49: 0 | AC49: 0 | AD49: 0 | AE49: 0 | AF49: 0 | AG49: 0 | AI49: 0 | AJ49: 80 | AK49: 0 | AL49: 0 | AM49: 0 | AN49: 0 | AP49: 0
A50: 550445279 | B50: ACRF1KP102RD | C50: Капа красный/белый | D50: 2046391283507 | E50: 0 | F50: 80 | G50: 0 | H50: 0 | I50: 0 | J50: 0 | K50: 0 | L50: 0 | M50: 0 | N50: 0 | O50: 0 | P50: 0 | Q50: 0 | R50: 0 | S50: 0 | T50: 0 | U50: 0 | V50: 0 | W50: 0 | X50: 0 | Z50: 0 | AA50: 0 | AB50: 0 | AC50: 0 | AD50: 0 | AE50: 0 | AF50: 0 | AG50: 0 | AI50: 0 | AJ50: 80 | AK50: 0 | AL50: 0 | AM50: 0 | AN50: 0 | AP50: 0
A51: 550445280 | B51: ACRF1KP101BL | C51: Капа синий/белый | D51: 2046391283545 | E51: 0 | F51: 80 | G51: 0 | H51: 0 | I51: 0 | J51: 0 | K51: 0 | L51: 0 | M51: 0 | N51: 0 | O51: 0 | P51: 0 | Q51: 0 | R51: 0 | S51: 0 | T51: 0 | U51: 0 | V51: 0 | W51: 0 | X51: 0 | Z51: 0 | AA51: 0 | AB51: 0 | AC51: 0 | AD51: 0 | AE51: 0 | AF51: 0 | AG51: 0 | AI51: 0 | AJ51: 80 | AK51: 0 | AL51: 0 | AM51: 0 | AN51: 0 | AP51: 0
A52: 550445281 | B52: ACRF1KP101GN | C52: Капа зеленый/белый | D52: 2046391283569 | E52: 0 | F52: 80 | G52: 0 | H52: 0 | I52: 0 | J52: 0 | K52: 0 | L52: 0 | M52: 0 | N52: 0 | O52: 0 | P52: 0 | Q52: 0 | R52: 0 | S52: 0 | T52: 0 | U52: 0 | V52: 0 | W52: 0 | X52: 0 | Z52: 0 | AA52: 0 | AB52: 0 | AC52: 0 | AD52: 0 | AE52: 0 | AF52: 0 | AG52: 0 | AI52: 0 | AJ52: 80 | AK52: 0 | AL52: 0 | AM52: 0 | AN52: 0 | AP52: 0
A53: 550445283 | B53: ACRF1KP102GN | C53: Капа зеленый/черный | D53: 2046391283613 | E53: 0 | F53: 80 | G53: 0 | H53: 0 | I53: 0 | J53: 0 | K53: 0 | L53: 0 | M53: 0 | N53: 0 | O53: 0 | P53: 0 | Q53: 0 | R53: 0 | S53: 0 | T53: 0 | U53: 0 | V53: 0 | W53: 0 | X53: 0 | Z53: 0 | AA53: 0 | AB53: 0 | AC53: 0 | AD53: 0 | AE53: 0 | AF53: 0 | AG53: 0 | AI53: 0 | AJ53: 80 | AK53: 0 | AL53: 0 | AM53: 0 | AN53: 0 | AP53: 0
A54: 186826338 | B54: ACRA7TB201BC | C54: Таблетница прям 7*2 черн | D54: 2038891723249 | E54: 613 | F54: 171 | G54: 104823 | H54: 235.76923 | I54: 94 | J54: 2.6 | K54: 10 | L54: 0 | M54: 10 | N54: 7278.1 | O54: 4919 | P54: 0 | Q54: 7278.1 | R54: 4919 | S54: 0.044591291 | T54: 1710 | U54: 1986.7815 | V54: 0.27298079 | W54: 859.57 | X54: 610.54 | Z54: 344.33 | AA54: 1766.8785 | AB54: 0.035019045 | AC54: 613 | AD54: 20 | AE54: 21 | AF54: 0.24276645 | AG54: 1.0332623 | AI54: 727.81 | AJ54: 171 | AK54: 198.67815 | AL54: 85.957 | AM54: 61.054 | AN54: 0 | AO54: 34.433 | AP54: 176.68785
A55: 419130077 | B55: ACRA7TB201CL | C55: Таблетница прям 7*2 черн/цветн | D55: 2044025155923 | E55: 272 | F55: 171 | G55: 46512 | H55: 143.15789 | I55: 100 | J55: 1.9 | K55: 8 | L55: 0 | M55: 8 | N55: 5880.7 | O55: 4411.87 | P55: 0 | Q55: 5880.7 | R55: 4411.87 | S55: 0.036029734 | T55: 1368 | U55: 1571.2926 | V55: 0.26719483 | W55: 470.4 | X55: 274.4 | Z55: 308.8309 | AA55: 1887.7765 | AB55: 0.037415209 | AC55: 272 | AD55: 12 | AE55: 39 | AF55: 0.32101221 | AG55: 1.3799536 | AI55: 735.0875 | AJ55: 171 | AK55: 196.41158 | AL55: 58.8 | AM55: 34.3 | AN55: 0 | AO55: 38.603863 | AP55: 235.97206
A56: 448248943 | B56: ACRA7TB201WH | C56: Таблетница прям 7*2 бел/цветн | D56: 2044516485386 | E56: 208 | F56: 171 | G56: 35568 | H56: 231.11111 | I56: 100 | J56: 0.9 | K56: 6 | L56: 0 | M56: 6 | N56: 4514 | O56: 3127 | P56: 0 | Q56: 4514 | R56: 3127 | S56: 0.027656268 | T56: 1026 | U56: 1187.8093 | V56: 0.26313898 | W56: 367.46 | X56: 209.72 | Z56: 218.89 | AA56: 1504.1207 | AB56: 0.029811257 | AC56: 208 | AD56: 11 | AE56: 23 | AF56: 0.33321237 | AG56: 1.4660045 | AI56: 752.33333 | AJ56: 171 | AK56: 197.96822 | AL56: 61.243333 | AM56: 34.953333 | AN56: 0 | AO56: 36.481667 | AP56: 250.68678
A57: 448254852 | B57: ACRA7TB201LI | C57: Таблетница прям 7*2 сирен/цветн | D57: 2044516498812 | E57: 212 | F57: 171 | G57: 36252 | H57: 353.33333 | I57: 100 | J57: 0.6 | K57: 3 | L57: 0 | M57: 3 | N57: 2177 | O57: 1522 | P57: 0 | Q57: 2177 | R57: 1522 | S57: 0.013337992 | T57: 513 | U57: 596.27098 | V57: 0.27389572 | W57: 171.06 | X57: 210.7 | Z57: 106.54 | AA57: 579.42902 | AB57: 0.011484123 | AC57: 212 | AD57: 6 | AE57: 44 | AF57: 0.2661594 | AG57: 1.1294913 | AI57: 725.66667 | AJ57: 171 | AK57: 198.75699 | AL57: 57.02 | AM57: 70.233333 | AN57: 0 | AO57: 35.513333 | AP57: 193.14301
A58: 186800214 | B58: ACRA7TB101BC | C58: Таблетница круглая 7*2 черн | D58: 2038890789598 | E58: 219 | F58: 250 | G58: 54750 | H58: 2190 | I58: 0 | J58: 0.1 | K58: 0 | L58: 0 | M58: 0 | N58: 0 | O58: 0 | P58: 0 | Q58: 0 | R58: 0 | S58: 0 | T58: 0 | U58: 0 | V58: 0 | W58: 0 | X58: 306.47736 | Z58: 0 | AA58: -306.47736 | AB58: -0.0060742968 | AC58: 219 | AD58: 50 | AE58: 33 | AF58: 0 | AG58: 0 | AI58: 0 | AJ58: 250 | AK58: 0 | AL58: 0 | AM58: 306.47736 | AN58: 0 | AP58: 0
A59: 298193176 | B59: ACRA7TB101CL | C59: Таблетница круглая 7*2 черн/цвет | D59: 2042160422832 | E59: 174 | F59: 250 | G59: 43500 | H59: 1740 | I59: 100 | J59: 0.1 | K59: 0 | L59: 0 | M59: 0 | N59: 0 | O59: 0 | P59: 0 | Q59: 0 | R59: 0 | S59: 0 | T59: 0 | U59: -10.294426 | V59: 0 | W59: 0 | X59: 243.50256 | Z59: 0 | AA59: -233.20813 | AB59: -0.0046221209 | AC59: 174 | AD59: 17 | AE59: 50 | AF59: 0 | AG59: 0 | AI59: 0 | AJ59: 250 | AK59: 0 | AL59: 0 | AM59: 243.50256 | AN59: 0 | AP59: 0
A60: 278515093 | B60: ACRA7TB301GR | C60: Таблетница круглая 7*2 сер | D60: 2041680530447 | E60: 209 | F60: 142 | G60: 29678 | H60: 69.666667 | I60: 65 | J60: 3 | K60: 14 | L60: 1 | M60: 13 | N60: 10901.26 | O60: 7555 | P60: 758 | Q60: 10143.26 | R60: 6797 | S60: 0.062145486 | T60: 1846 | U60: 2186.3877 | V60: 0.21555079 | W60: 2076.02 | X60: 312.07512 | Z60: 475.79 | AA60: 3246.9872 | AB60: 0.064354391 | AC60: 209 | AD60: 17 | AE60: 23 | AF60: 0.34028019 | AG60: 1.8697456 | AI60: 780.25077 | AJ60: 142 | AK60: 168.18367 | AL60: 148.28714 | AM60: 22.29108 | AN60: 0 | AO60: 33.985 | AP60: 265.50388
A61: 345168494 | B61: ACRA7TB301CL | C61: Таблетница круглая 7*2 сер /цвет | D61: 2043048226719 | E61: 216 | F61: 142 | G61: 30672 | H61: 2160 | I61: 100 | J61: 0.1 | K61: 0 | L61: 0 | M61: 0 | N61: 0 | O61: 0 | P61: 0 | Q61: 0 | R61: 0 | S61: 0 | T61: 0 | U61: -7.1506557 | V61: 0 | W61: 0 | X61: 302.27904 | Z61: 0 | AA61: -295.12838 | AB61: -0.0058493632 | AC61: 216 | AD61: 9 | AE61: 6 | AF61: 0 | AG61: 0 | AI61: 0 | AJ61: 142 | AK61: 0 | AL61: 0 | AM61: 302.27904 | AN61: 0 | AP61: 0
A62: 273516556 | B62: ACRA7TB301WH | C62: Таблетница круглая 7*2 бел | D62: 2041532808502 | E62: 107 | F62: 142 | G62: 15194 | H62: 356.66667 | I62: 0 | J62: 0.3 | K62: 0 | L62: 0 | M62: 0 | N62: 0 | O62: 0 | P62: 0 | Q62: 0 | R62: 0 | S62: 0 | T62: 0 | U62: -14.995082 | V62: 0 | W62: 432.42 | X62: 149.74008 | Z62: 0 | AA62: -567.165 | AB62: -0.011241054 | AC62: 107 | AD62: 7 | AE62: 22 | AF62: 0 | AG62: 0 | AI62: 0 | AJ62: 142 | AK62: 0 | AL62: 432.42 | AM62: 149.74008 | AN62: 0 | AP62: 0
A63: 321907864 | B63: ACRA7TB401BC | C63: Таблетница автомат 7*2 черн | D63: 2042676873814 | E63: 0 | F63: 335 | G63: 0 | H63: 0 | I63: 0 | J63: 0 | K63: 0 | L63: 0 | M63: 0 | N63: 0 | O63: 0 | P63: 0 | Q63: 0 | R63: 0 | S63: 0 | T63: 0 | U63: 0 | V63: 0 | W63: 0 | X63: 0 | Z63: 0 | AA63: 0 | AB63: 0 | AC63: 0 | AD63: 0 | AE63: 0 | AF63: 0 | AG63: 0 | AI63: 0 | AJ63: 335 | AK63: 0 | AL63: 0 | AM63: 0 | AN63: 0 | AP63: 0
A64: 271440668 | B64: ACRB1SK101BC | C64: Скакалка черная | D64: 2041473034138 | E64: 150 | F64: 282 | G64: 42300 | H64: 214.28571 | I64: 80 | J64: 0.7 | K64: 1 | L64: 0 | M64: 1 | N64: 826 | O64: 503 | P64: 0 | Q64: 826 | R64: 503 | S64: 0.0050607173 | T64: 282 | U64: 228.07607 | V64: 0.27612114 | W64: 164.53 | X64: 147.98 | Z64: 35.21 | AA64: -31.796066 | AB64: -0.00063018926 | AC64: 150 | AD64: 6 | AE64: 71 | AF64: -0.038494026 | AG64: -0.11275201 | AI64: 826 | AJ64: 282 | AK64: 228.07607 | AL64: 164.53 | AM64: 147.98 | AN64: 0 | AO64: 35.21 | AP64: -31.796066
A65: 271440669 | B65: ACRB1SK101RD | C65: Скакалка красная | D65: 2041473034145 | E65: 140 | F65: 282 | G65: 39480 | H65: 1400 | I65: 0 | J65: 0.1 | K65: 1 | L65: 0 | M65: 1 | N65: 857 | O65: 503 | P65: 0 | Q65: 857 | R65: 503 | S65: 0.0052506473 | T65: 282 | U65: 243.05672 | V65: 0.28361344 | W65: 57.91 | X65: 138.18 | Z65: 35.21 | AA65: 100.64328 | AB65: 0.001994722 | AC65: 140 | AD65: 7 | AE65: 33 | AF65: 0.11743673 | AG65: 0.35689106 | AI65: 857 | AJ65: 282 | AK65: 243.05672 | AL65: 57.91 | AM65: 138.18 | AN65: 0 | AO65: 35.21 | AP65: 100.64328
A66: 271440670 | B66: ACRB1SK101BL | C66: Скакалка синяя | D66: 2041473034169 | E66: 119 | F66: 282 | G66: 33558 | H66: 132.22222 | I66: 67 | J66: 0.9 | K66: 4 | L66: 0 | M66: 4 | N66: 3364.29 | O66: 2332.91 | P66: 0 | Q66: 3364.29 | R66: 2332.91 | S66: 0.020612252 | T66: 1128 | U66: 889.65836 | V66: 0.26444164 | W66: 503.05 | X66: 120.54 | Z66: 163.3037 | AA66: 559.73794 | AB66: 0.011093852 | AC66: 119 | AD66: 9 | AE66: 67 | AF66: 0.16637625 | AG66: 0.49622158 | AI66: 841.0725 | AJ66: 282 | AK66: 222.41459 | AL66: 125.7625 | AM66: 30.135 | AN66: 0 | AO66: 40.825925 | AP66: 139.93448
A67: 271441230 | B67: ACRB1SK201BC | C67: Скакалка со счетчиком | D67: 2041473042966 | E67: 0 | F67: 268 | G67: 0 | H67: 0 | I67: 0 | J67: 0 | K67: 0 | L67: 0 | M67: 0 | N67: 0 | O67: 0 | P67: 0 | Q67: 0 | R67: 0 | S67: 0 | T67: 0 | U67: 0 | V67: 0 | W67: 0 | X67: 0 | Z67: 0 | AA67: 0 | AB67: 0 | AC67: 0 | AD67: 0 | AE67: 0 | AF67: 0 | AG67: 0 | AI67: 0 | AJ67: 268 | AK67: 0 | AL67: 0 | AM67: 0 | AN67: 0 | AP67: 0
A68: 251537223 | B68: AAND1BL101RD | C68: Мяч регби красный | D68: 2040903539366 | E68: 197 | F68: 121 | G68: 23837 | H68: 63.548387 | I68: 76 | J68: 3.1 | K68: 12 | L68: 0 | M68: 12 | N68: 5581.98 | O68: 4281.15 | P68: 0 | Q68: 5581.98 | R68: 4281.15 | S68: 0.034199543 | T68: 1452 | U68: 1141.8333 | V68: 0.20455704 | W68: 866.63 | X68: 204.82 | Z68: 299.6805 | AA68: 1617.0162 | AB68: 0.032048816 | AC68: 197 | AD68: 13 | AE68: 41 | AF68: 0.28968506 | AG68: 1.1136475 | AI68: 465.165 | AJ68: 121 | AK68: 95.152773 | AL68: 72.219167 | AM68: 17.068333 | AN68: 0 | AO68: 24.973375 | AP68: 134.75135
A69: 251537413 | B69: AAND1BL101BL | C69: Мяч регби синий | D69: 2040903547941 | E69: 218 | F69: 121 | G69: 26378 | H69: 167.69231 | I69: 100 | J69: 1.3 | K69: 5 | L69: 0 | M69: 5 | N69: 2335 | O69: 1735 | P69: 0 | Q69: 2335 | R69: 1735 | S69: 0.014306023 | T69: 605 | U69: 498.27574 | V69: 0.21339432 | W69: 308.62 | X69: 218.54 | Z69: 121.45 | AA69: 583.11426 | AB69: 0.011557164 | AC69: 218 | AD69: 9 | AE69: 41 | AF69: 0.24972774 | AG69: 0.96382523 | AI69: 467 | AJ69: 121 | AK69: 99.655148 | AL69: 61.724 | AM69: 43.708 | AN69: 0 | AO69: 24.29 | AP69: 116.62285
A70: 251516159 | B70: AAND1BL102RD | C70: Мяч шина красный | D70: 2040902555480 | E70: 139 | F70: 137 | G70: 19043 | H70: 51.481481 | I70: 75 | J70: 2.7 | K70: 6 | L70: 0 | M70: 6 | N70: 4814.4 | O70: 3845.72 | P70: 0 | Q70: 4814.4 | R70: 3845.72 | S70: 0.029496752 | T70: 822 | U70: 990.16025 | V70: 0.20566639 | W70: 506.87 | X70: 142.1 | Z70: 269.2004 | AA70: 2084.0694 | AB70: 0.04130568 | AC70: 139 | AD70: 13 | AE70: 38 | AF70: 0.43288247 | AG70: 2.5353642 | AI70: 802.4 | AJ70: 137 | AK70: 165.02671 | AL70: 84.478333 | AM70: 23.683333 | AN70: 0 | AO70: 44.866733 | AP70: 347.34489
A71: 251407392 | B71: AAND1BL102BL | C71: Мяч шина синий | D71: 2040900511679 | E71: 115 | F71: 137 | G71: 15755 | H71: 54.761905 | I71: 100 | J71: 2.1 | K71: 15 | L71: 0 | M71: 15 | N71: 10865.98 | O71: 8400.14 | P71: 0 | Q71: 10865.98 | R71: 8400.14 | S71: 0.066573429 | T71: 2055 | U71: 2384.6179 | V71: 0.21945723 | W71: 831.56 | X71: 127.4 | Z71: 588.0098 | AA71: 4879.3923 | AB71: 0.096708211 | AC71: 115 | AD71: 16 | AE71: 20 | AF71: 0.44905221 | AG71: 2.3744002 | AI71: 724.39867 | AJ71: 137 | AK71: 158.97452 | AL71: 55.437333 | AM71: 8.4933333 | AN71: 0 | AO71: 39.200653 | AP71: 325.29282
A72: 302564795 | B72: AAND1ST202BL | C72: Палочка для жевания | D72: 2042253544953 | E72: 0 | F72: 204 | G72: 0 | H72: 0 | I72: 0 | J72: 0.1 | K72: 1 | L72: 0 | M72: 1 | N72: 647 | O72: 465 | P72: 0 | Q72: 647 | R72: 465 | S72: 0.0039640243 | T72: 204 | U72: 123.78836 | V72: 0.19132668 | W72: 47.52 | X72: 0.98 | Z72: 32.55 | AA72: 238.16164 | AB72: 0.004720298 | AC72: 0 | AD72: 22 | AE72: 50 | AF72: 0.36810145 | AG72: 1.167459 | AI72: 647 | AJ72: 204 | AK72: 123.78836 | AL72: 47.52 | AM72: 0.98 | AN72: 0 | AO72: 32.55 | AP72: 238.16164
A73: 273588520 | B73: AAND1RP301BG | C73: Канат бол бежевый 55см/520гр | D73: 2041534216404 | E73: 17 | F73: 478 | G73: 8126 | H73: 999 | I73: 0 | J73: 0 | K73: 0 | L73: 0 | M73: 0 | N73: 0 | O73: 0 | P73: 0 | Q73: 0 | R73: 0 | S73: 0 | T73: 0 | U73: 0 | V73: 0 | W73: 0 | X73: 48.11408 | Z73: 0 | AA73: -48.11408 | AB73: -0.0009536078 | AC73: 17 | AD73: 21 | AE73: 0 | AF73: 0 | AG73: 0 | AI73: 0 | AJ73: 478 | AK73: 0 | AL73: 0 | AM73: 48.11408 | AN73: 0 | AP73: 0
A74: 273589771 | B74: AAND1RP301YL | C74: Канат мал желтый 55см/330гр | D74: 2041534288661 | E74: 15 | F74: 326 | G74: 4890 | H74: 150 | I74: 100 | J74: 0.1 | K74: 1 | L74: 0 | M74: 1 | N74: 728 | O74: 535 | P74: 0 | Q74: 728 | R74: 535 | S74: 0.0044602932 | T74: 326 | U74: 157.22623 | V74: 0.2159701 | W74: 92.59 | X74: 29.6352 | Z74: 37.45 | AA74: 85.09857 | AB74: 0.0016866302 | AC74: 15 | AD74: 24 | AE74: 25 | AF74: 0.11689364 | AG74: 0.26103856 | AI74: 728 | AJ74: 326 | AK74: 157.22623 | AL74: 92.59 | AM74: 29.6352 | AN74: 0 | AO74: 37.45 | AP74: 85.09857
A75: 273556717 | B75: AKTA4ST101CL | C75: Набор пробок 4 шт. в коробке нежн | D75: 2041533648312 | E75: 169 | F75: 104 | G75: 17576 | H75: 73.478261 | I75: 92 | J75: 2.3 | K75: 8 | L75: 0 | M75: 8 | N75: 4682.7 | O75: 3118.78 | P75: 0 | Q75: 4682.7 | R75: 3118.78 | S75: 0.028689856 | T75: 832 | U75: 1368.873 | V75: 0.29232557 | W75: 533.69 | X75: 173.46 | Z75: 218.3146 | AA75: 1556.3624 | AB75: 0.030846675 | AC75: 169 | AD75: 17 | AE75: 31 | AF75: 0.33236433 | AG75: 1.8706279 | AI75: 585.3375 | AJ75: 104 | AK75: 171.10912 | AL75: 66.71125 | AM75: 21.6825 | AN75: 0 | AO75: 27.289325 | AP75: 194.54531
A76: 370594147 | B76: AKTA4ST103CL | C76: Набор пробок 4 шт. в коробке ярк | D76: 2043369755509 | E76: 81 | F76: 123 | G76: 9963 | H76: 42.631579 | I76: 82 | J76: 1.9 | K76: 8 | L76: 0 | M76: 8 | N76: 4513 | O76: 2844 | P76: 0 | Q76: 4513 | R76: 2844 | S76: 0.027650142 | T76: 984 | U76: 1303.5223 | V76: 0.2888372 | W76: 526.16 | X76: 87.22 | Z76: 199.08 | AA76: 1413.0177 | AB76: 0.028005621 | AC76: 81 | AD76: 12 | AE76: 32 | AF76: 0.31309942 | AG76: 1.4359936 | AI76: 564.125 | AJ76: 123 | AK76: 162.94029 | AL76: 65.77 | AM76: 10.9025 | AN76: 0 | AO76: 24.885 | AP76: 176.62721
A77: 321959186 | B77: AKTA4ST102CL | C77: Набор пробок 4 шт. | D77: 2042678197468 | E77: 58 | F77: 121 | G77: 7018 | H77: 52.727273 | I77: 100 | J77: 1.1 | K77: 5 | L77: 0 | M77: 5 | N77: 2825 | O77: 1772 | P77: 0 | Q77: 2825 | R77: 1772 | S77: 0.017308143 | T77: 605 | U77: 818.47098 | V77: 0.28972424 | W77: 244.02 | X77: 61.74 | Z77: 124.04 | AA77: 971.72902 | AB77: 0.019259401 | AC77: 58 | AD77: 11 | AE77: 22 | AF77: 0.34397487 | AG77: 1.6061637 | AI77: 565 | AJ77: 121 | AK77: 163.6942 | AL77: 48.804 | AM77: 12.348 | AN77: 0 | AO77: 24.808 | AP77: 194.3458
A78: 273546535 | B78: AKTA2KN101YL | C78: Шпатель желтый | D78: 2041533399818 | E78: 70 | F78: 171 | G78: 11970 | H78: 233.33333 | I78: 0 | J78: 0.3 | K78: 0 | L78: 0 | M78: 0 | N78: 0 | O78: 0 | P78: 0 | Q78: 0 | R78: 0 | S78: 0 | T78: 0 | U78: 0 | V78: 0 | W78: 81.18 | X78: 68.6 | Z78: 0 | AA78: -149.78 | AB78: -0.0029685983 | AC78: 70 | AD78: 10 | AE78: 67 | AF78: 0 | AG78: 0 | AI78: 0 | AJ78: 171 | AK78: 0 | AL78: 81.18 | AM78: 68.6 | AN78: 0 | AP78: 0
A79: 273551028 | B79: AKTA2KN101BL | C79: Шпатель голубой | D79: 2041533587000 | E79: 0 | F79: 242 | G79: 0 | H79: 0 | I79: 0 | J79: 0 | K79: 0 | L79: 0 | M79: 0 | N79: 0 | O79: 0 | P79: 0 | Q79: 0 | R79: 0 | S79: 0 | T79: 0 | U79: 0 | V79: 0 | W79: 0 | X79: 0 | Z79: 0 | AA79: 0 | AB79: 0 | AC79: 0 | AD79: 0 | AE79: 0 | AF79: 0 | AG79: 0 | AI79: 0 | AJ79: 242 | AK79: 0 | AL79: 0 | AM79: 0 | AN79: 0 | AP79: 0
A80: 273527791 | B80: AKTA2KN102YL | C80: Нож для пиццы желтый | D80: 2041533038113 | E80: 129 | F80: 127 | G80: 16383 | H80: 1290 | I80: 0 | J80: 0.1 | K80: 0 | L80: 0 | M80: 0 | N80: 0 | O80: 0 | P80: 0 | Q80: 0 | R80: 0 | S80: 0 | T80: 0 | U80: 0 | V80: 0 | W80: 0 | X80: 126.42 | Z80: 0 | AA80: -126.42 | AB80: -0.0025056096 | AC80: 129 | AD80: 16 | AE80: 11 | AF80: 0 | AG80: 0 | AI80: 0 | AJ80: 127 | AK80: 0 | AL80: 0 | AM80: 126.42 | AN80: 0 | AP80: 0
A81: 327442631 | B81: AKTA2KN102GN | C81: Нож для пиццы зеленый | D81: 2042777181566 | E81: 85 | F81: 127 | G81: 10795 | H81: 283.33333 | I81: 100 | J81: 0.3 | K81: 1 | L81: 0 | M81: 1 | N81: 641 | O81: 416 | P81: 0 | Q81: 641 | R81: 416 | S81: 0.0039272636 | T81: 127 | U81: 171.32049 | V81: 0.26727066 | W81: 57.91 | X81: 84.28 | Z81: 29.12 | AA81: 171.36951 | AB81: 0.0033964964 | AC81: 85 | AD81: 14 | AE81: 29 | AF81: 0.26734713 | AG81: 1.3493662 | AI81: 641 | AJ81: 127 | AK81: 171.32049 | AL81: 57.91 | AM81: 84.28 | AN81: 0 | AO81: 29.12 | AP81: 171.36951
A82: 340948906 | B82: AKTA1KN101GR | C82: Консервный нож | D82: 2042988749289 | E82: 15 | F82: 254 | G82: 3810 | H82: 150 | I82: 0 | J82: 0.1 | K82: 1 | L82: 0 | M82: 1 | N82: 648 | O82: 434 | P82: 0 | Q82: 648 | R82: 434 | S82: 0.0039701511 | T82: 254 | U82: 187.98082 | V82: 0.29009386 | W82: 43.06 | X82: 15.68 | Z82: 30.38 | AA82: 116.89918 | AB82: 0.0023169095 | AC82: 15 | AD82: 28 | AE82: 20 | AF82: 0.18039997 | AG82: 0.46023299 | AI82: 648 | AJ82: 254 | AK82: 187.98082 | AL82: 43.06 | AM82: 15.68 | AN82: 0 | AO82: 30.38 | AP82: 116.89918
A83: 340802685 | B83: AKTA1PR101GR | C83: Чеснокодавка | D83: 2042987041841 | E83: 23 | F83: 235 | G83: 5405 | H83: 999 | I83: 0 | J83: 0 | K83: 0 | L83: 0 | M83: 0 | N83: 0 | O83: 0 | P83: 0 | Q83: 0 | R83: 0 | S83: 0 | T83: 0 | U83: 0 | V83: 0 | W83: 0 | X83: 22.54 | Z83: 0 | AA83: -22.54 | AB83: -0.00044673659 | AC83: 23 | AD83: 0 | AE83: 0 | AF83: 0 | AG83: 0 | AI83: 0 | AJ83: 235 | AK83: 0 | AL83: 0 | AM83: 22.54 | AN83: 0 | AP83: 0
A84: Итого | E84: 9515 | G84: 1272482 | H84: 276.36929 | K84: 242 | L84: 1 | M84: 241 | N84: 163975.97 | O84: 112442.74 | P84: 758 | Q84: 163217.97 | R84: 111684.74 | S84: 1 | T84: 30711 | U84: 44516.474 | V84: 0.27274248 | W84: 18912.99 | X84: 10804.786 | Y84: 0 | Z84: 7817.9318 | AA84: 50454.788 | AB84: 1 | AC84: 9515 | AF84: 0.3091252 | AG84: 1.6428898
Z85: в т.ч убытки | AA85: -3994.1086
Z86: Проверка | AA86: 50454.516
Z87: Платная приемка | AA87: 0
Z88: Прочие удержания | AA88: 0
Z89: Штрафы | AA89: 0

Sheet 3
C1: Обязательно написать номер недели | D1: 3 | AI1: на 1 единицу проданного товара
A2: Арт. ВБ | B2: Артикул поставщика | C2: Название | D2: ШК | E2: Остаток на начало недели, шт | F2: Себестоимость на 1 ед | G2: Себестоимость остатков | H2: Оборачиваемость, дн | I2: % выкупа за 30 дн с уч возврата | J2: Скорость продаж | K2: Кол-во ПРОДАЖИ | L2: Кол-во ВОЗВРАТЫ | M2: Кол-во ПРОДАЖИ-ВОЗВРАТЫ | N2: Выручка ПРОДАЖИ по Цене в карточке | O2: Выручка ПРОДАЖИ по Цене ВБ реализовал | P2: Выручка ВОЗВРАТЫ | Q2: Выручка ПРОДАЖИ (цена в карточке)- ВОЗВРАТЫ | R2: Выручка ПРОДАЖИ (ВБ реализовал)- ВОЗВРАТЫ | S2: Доля выручки, % от общего объема | T2: Себестоимость продаж | U2: Комиссия, руб | V2: Комиссия, % | W2: Логистика | X2: Хранение | Y2: Реклама | Z2: Налог 7% | AA2: Прибыль | AB2: Доля прибыли, % от общего объема | AC2: Остаток на конец недели, шт | AD2: Конверсия в корзину, % | AE2: Конверсия в заказ, % | AF2: Маржинальность, % | AG2: Рентабельность, % | AI2: Выручка на 1 ед (средняя цена продажи со скидкой) | AJ2: Себестоимость на 1 ед | AK2: Комиссия на 1 ед | AL2: Логистика на 1 ед | AM2: Хранение на 1 ед. | AN2: Реклама на 1 ед | AO2: Налог на 1 ед | AP2: Прибыль на 1 ед
A3: 1 | B3: 2 | C3: 3 | D3: 4 | E3: 5 | F3: 6 | G3: 7 | H3: 8 | I3: 9 | J3: 10 | K3: 11 | L3: 12 | M3: 13 | N3: 14 | O3: 15 | P3: 16 | Q3: 17 | R3: 18 | S3: 19 | T3: 20 | U3: 21 | V3: 22 | W3: 23 | X3: 24 | Y3: 25 | Z3: 26 | AA3: 27 | AB3: 19 | AC3: 28 | AD3: 30 | AE3: 31 | AF3: 32 | AG3: 33 | AH3: 34 | AI3: 35 | AJ3: 36 | AK3: 37 | AL3: 38 | AM3: 39 | AN3: 40 | AO3: 41 | AP3: 42
A4: 169112569 | B4: ACRF1BN101PN | C4: Бандаж для лица розовый | D4: 2038161736993 | E4: 154 | F4: 111 | G4: 17094 | H4: 1560 | I4: 0 | J4: 0.1 | K4: 1 | L4: 0 | M4: 1 | N4: 604 | O4: 435 | P4: 0 | Q4: 604 | R4: 435 | S4: 0.0027650774 | T4: 111 | U4: 181.98328 | V4: 0.30129682 | W4: 254.42 | X4: 153.86 | Z4: 30.45 | AA4: -127.71328 | AB4: -0.0017621929 | AC4: 156 | AD4: 10 | AE4: 14 | AF4: -0.21144583 | AG4: -1.1505701 | AI4: 604 | AJ4: 111 | AK4: 181.98328 | AL4: 254.42 | AM4: 153.86 | AN4: 0 | AO4: 30.45 | AP4: -127.71328
A5: 169153168 | B5: ACRF1BN101BC | C5: Бандаж для лица черный | D5: 2038162681926 | E5: 227 | F5: 90 | G5: 20430 | H5: 222.72727 | I5: 100 | J5: 1.1 | K5: 2 | L5: 0 | M5: 2 | N5: 1187.86 | O5: 1003.52 | P5: 0 | Q5: 1187.86 | R5: 1003.52 | S5: 0.0054379551 | T5: 180 | U5: 370.94754 | V5: 0.31228221 | W5: 197.99 | X5: 242.06 | Z5: 70.2464 | AA5: 126.61606 | AB5: 0.0017470535 | AC5: 245 | AD5: 17 | AE5: 35 | AF5: 0.10659174 | AG5: 0.70342255 | AI5: 593.93 | AJ5: 90 | AK5: 185.47377 | AL5: 98.995 | AM5: 121.03 | AN5: 0 | AO5: 35.1232 | AP5: 63.30803
A6: 169395410 | B6: ACRF1BN201GR | C6: Бандаж для лица серый | D6: 2038172050200 | E6: 207 | F6: 206 | G6: 42642 | H6: 341.42857 | I6: 100 | J6: 0.7 | K6: 6 | L6: 0 | M6: 6 | N6: 5651 | O6: 3807 | P6: 0 | Q6: 5651 | R6: 3807 | S6: 0.025869954 | T6: 1236 | U6: 1819.742 | V6: 0.32202123 | W6: 295.51 | X6: 240.1 | Z6: 266.49 | AA6: 1793.158 | AB6: 0.024742066 | AC6: 239 | AD6: 14 | AE6: 23 | AF6: 0.31731694 | AG6: 1.4507751 | AI6: 941.83333 | AJ6: 206 | AK6: 303.29033 | AL6: 49.251667 | AM6: 40.016667 | AN6: 0 | AO6: 44.415 | AP6: 298.85967
A7: 172832355 | B7: AHMA7BW101BG | C7: Мешки 7 шт. | D7: 2038337652454 | E7: 134 | F7: 375 | G7: 50250 | H7: 1640 | I7: 100 | J7: 0.1 | K7: 1 | L7: 0 | M7: 1 | N7: 1652 | O7: 996 | P7: 0 | Q7: 1652 | R7: 996 | S7: 0.0075627614 | T7: 375 | U7: 407.02393 | V7: 0.24638253 | W7: 373.66 | X7: 611.226 | Z7: 69.72 | AA7: -184.62993 | AB7: -0.0025475312 | AC7: 164 | AD7: 8 | AE7: 11 | AF7: -0.11176146 | AG7: -0.49234649 | AI7: 1652 | AJ7: 375 | AK7: 407.02393 | AL7: 373.66 | AM7: 611.226 | AN7: 0 | AO7: 69.72 | AP7: -184.62993
A8: 176500218 | B8: AHMA1BW101BG | C8: Мешок для бюстгалтеров | D8: 2038597850744 | E8: 338 | F8: 71 | G8: 23998 | H8: 658.33333 | I8: 100 | J8: 0.6 | K8: 8 | L8: 0 | M8: 8 | N8: 3642.74 | O8: 2261.7 | P8: 0 | Q8: 3642.74 | R8: 2261.7 | S8: 0.016676255 | T8: 568 | U8: 1042.2416 | V8: 0.28611475 | W8: 462.49 | X8: 394.94 | Z8: 158.319 | AA8: 1016.7494 | AB8: 0.014029148 | AC8: 395 | AD8: 10 | AE8: 40 | AF8: 0.27911664 | AG8: 1.7900517 | AI8: 455.3425 | AJ8: 71 | AK8: 130.2802 | AL8: 57.81125 | AM8: 49.3675 | AN8: 0 | AO8: 19.789875 | AP8: 127.09367
A9: 177404837 | B9: AHMA3BW101BG | C9: Мешки 3 шт. | D9: 2038627692689 | E9: 124 | F9: 166 | G9: 20584 | H9: 556.66667 | I9: 100 | J9: 0.3 | K9: 1 | L9: 0 | M9: 1 | N9: 993 | O9: 580 | P9: 0 | Q9: 993 | R9: 580 | S9: 0.0045458971 | T9: 166 | U9: 272.49443 | V9: 0.27441533 | W9: 106.12 | X9: 411.6 | Z9: 40.6 | AA9: -3.8144262 | AB9: -5.2631606e-05 | AC9: 167 | AD9: 4 | AE9: 67 | AF9: -0.0038413154 | AG9: -0.022978471 | AI9: 993 | AJ9: 166 | AK9: 272.49443 | AL9: 106.12 | AM9: 411.6 | AN9: 0 | AO9: 40.6 | AP9: -3.8144262
A10: 177405495 | B10: AHMA3BW102BG | C10: Мешки/деликат 3 шт. | D10: 2038627713902 | E10: 208 | F10: 156 | G10: 32448 | H10: 625 | I10: 100 | J10: 0.4 | K10: 2 | L10: 0 | M10: 2 | N10: 1777.88 | O10: 1002 | P10: 0 | Q10: 1777.88 | R10: 1002 | S10: 0.0081390329 | T10: 312 | U10: 508.18705 | V10: 0.28583878 | W10: 215.44 | X10: 419.832 | Z10: 70.14 | AA10: 252.28095 | AB10: 0.0034809827 | AC10: 250 | AD10: 6 | AE10: 43 | AF10: 0.14189988 | AG10: 0.80859279 | AI10: 888.94 | AJ10: 156 | AK10: 254.09352 | AL10: 107.72 | AM10: 209.916 | AN10: 0 | AO10: 35.07 | AP10: 126.14048
A11: 176721350 | B11: AHMA3BW201WH | C11: Мешки/шнурок мелк 3 шт. | D11: 2038606201642 | E11: 259 | F11: 145 | G11: 37555 | H11: 437.14286 | I11: 100 | J11: 0.7 | K11: 9 | L11: 0 | M11: 9 | N11: 6584.14 | O11: 4180.91 | P11: 0 | Q11: 6584.14 | R11: 4180.91 | S11: 0.030141816 | T11: 1305 | U11: 1840.5113 | V11: 0.27953709 | W11: 621.76 | X11: 308.7 | Z11: 292.6637 | AA11: 2215.505 | AB11: 0.030569627 | AC11: 306 | AD11: 7 | AE11: 38 | AF11: 0.33649117 | AG11: 1.697705 | AI11: 731.57111 | AJ11: 145 | AK11: 204.50126 | AL11: 69.084444 | AM11: 34.3 | AN11: 0 | AO11: 32.518189 | AP11: 246.16722
A12: 176723275 | B12: AHMA3BW202WH | C12: Мешки/шнурок крупн 3 шт. | D12: 2038606256161 | E12: 125 | F12: 145 | G12: 18125 | H12: 59.615385 | I12: 100 | J12: 2.6 | K12: 20 | L12: 0 | M12: 20 | N12: 16357.12 | O12: 10040 | P12: 0 | Q12: 16357.12 | R12: 10040 | S12: 0.074881959 | T12: 2900 | U12: 4486.7172 | V12: 0.27429751 | W12: 1081.74 | X12: 171.5 | Z12: 702.8 | AA12: 7014.3628 | AB12: 0.096784459 | AC12: 155 | AD12: 11 | AE12: 47 | AF12: 0.42882627 | AG12: 2.4187458 | AI12: 817.856 | AJ12: 145 | AK12: 224.33586 | AL12: 54.087 | AM12: 8.575 | AN12: 0 | AO12: 35.14 | AP12: 350.71814
A13: 204615141 | B13: AHMA2BW201WH | C13: Мешки 2 шт. серый | D13: 2039404446068 | E13: 197 | F13: 92 | G13: 18124 | H13: 853.33333 | I13: 0 | J13: 0.3 | K13: 1 | L13: 0 | M13: 1 | N13: 600 | O13: 358 | P13: 0 | Q13: 600 | R13: 358 | S13: 0.0027467656 | T13: 92 | U13: 143.20705 | V13: 0.23867842 | W13: 162.45 | X13: 251.86 | Z13: 25.06 | AA13: -74.577049 | AB13: -0.0010290171 | AC13: 256 | AD13: 13 | AE13: 33 | AF13: -0.12429508 | AG13: -0.8106201 | AI13: 600 | AJ13: 92 | AK13: 143.20705 | AL13: 162.45 | AM13: 251.86 | AN13: 0 | AO13: 25.06 | AP13: -74.577049
A14: 236074677 | B14: AHMA2BW202WH | C14: Мешки 2 шт. розовый | D14: 2040278862540 | E14: 50 | F14: 149 | G14: 7450 | H14: 163.33333 | I14: 100 | J14: 0.3 | K14: 1 | L14: 0 | M14: 1 | N14: 519 | O14: 295 | P14: 0 | Q14: 519 | R14: 295 | S14: 0.0023759523 | T14: 149 | U14: 114.97377 | V14: 0.22152942 | W14: 50.68 | X14: 49 | Z14: 20.65 | AA14: 134.69623 | AB14: 0.001858544 | AC14: 49 | AD14: 29 | AE14: 18 | AF14: 0.25953031 | AG14: 0.90400154 | AI14: 519 | AJ14: 149 | AK14: 114.97377 | AL14: 50.68 | AM14: 49 | AN14: 0 | AO14: 20.65 | AP14: 134.69623
A15: 236929187 | B15: AHMA1BW112WH | C15: Мешок 60*80 крупн | D15: 2040335626849 | E15: 136 | F15: 93 | G15: 12648 | H15: 73.043478 | I15: 92 | J15: 2.3 | K15: 16 | L15: 0 | M15: 16 | N15: 10247.48 | O15: 6280 | P15: 0 | Q15: 10247.48 | R15: 6280 | S15: 0.046912377 | T15: 1488 | U15: 2877.7649 | V15: 0.2808266 | W15: 881.56 | X15: 180.32 | Z15: 439.6 | AA15: 4380.2351 | AB15: 0.060438659 | AC15: 168 | AD15: 12 | AE15: 43 | AF15: 0.4274451 | AG15: 2.9437064 | AI15: 640.4675 | AJ15: 93 | AK15: 179.86031 | AL15: 55.0975 | AM15: 11.27 | AN15: 0 | AO15: 27.475 | AP15: 273.76469
... A20: 223420736 | B20: ACRB1MS101RJ | C20: Массажер для тела оранжевый | D20: 2039813223373 | E20: 33 | F20: 151 | G20: 4983 | H20: 48.571429 | I20: 100 | J20: 0.7 | K20: 7 | L20: 0 | M20: 7 | N20: 4325.43 | O20: 2890 | P20: 0 | Q20: 4325.43 | R20: 2890 | S20: 0.019801571 | T20: 1057 | U20: 1285.1595 | V20: 0.29711717 | W20: 362.73 | X20: 40.18 | Z20: 202.3 | AA20: 1378.0605 | AB20: 0.019014534 | AC20: 34 | AD20: 12 | AE20: 14 | AF20: 0.31859503 | AG20: 1.3037469 | AI20: 617.91857 | AJ20: 151 | AK20: 183.59422 | AL20: 51.818571 | AM20: 5.74 | AN20: 0 | AO20: 28.9 | AP20: 196.86578
A21: 275208801 | B21: ACRB1MS101PN | C21: Массажер для тела розовый | D21: 2041591042329 | E21: 75 | F21: 151 | G21: 11325 | H21: 250 | I21: 100 | J21: 0.3 | K21: 0 | L21: 0 | M21: 0 | N21: 0 | O21: 0 | P21: 0 | Q21: 0 | R21: 0 | S21: 0 | T21: 0 | U21: -5.2696721 | V21: 0 | W21: 0 | X21: 73.5 | Z21: 0 | AA21: -68.230328 | AB21: -0.0009414448 | AC21: 75 | AD21: 4 | AE21: 67 | AF21: 0 | AG21: 0 | AI21: 0 | AJ21: 151 | AK21: 0 | AL21: 0 | AM21: 73.5 | AN21: 0 | AP21: 0
A22: 275208802 | B22: ACRB1MS101BL | C22: Массажер для тела голубой | D22: 2041591055954 | E22: 28 | F22: 151 | G22: 4228 | H22: 90 | I22: 100 | J22: 0.3 | K22: 2 | L22: 0 | M22: 2 | N22: 1420 | O22: 964 | P22: 0 | Q22: 1420 | R22: 964 | S22: 0.0065006787 | T22: 302 | U22: 424.13262 | V22: 0.29868495 | W22: 126.72 | X22: 28.42 | Z22: 67.48 | AA22: 471.24738 | AB22: 0.0065022902 | AC22: 27 | AD22: 11 | AE22: 15 | AF22: 0.33186435 | AG22: 1.5604218 | AI22: 710 | AJ22: 151 | AK22: 212.06631 | AL22: 63.36 | AM22: 14.21 | AN22: 0 | AO22: 33.74 | AP22: 235.62369
A23: 236072835 | B23: ACRB1MS106WH | C23: Мяч с шипами белый 6 см | D23: 2040278804496 | E23: 379 | F23: 59 | G23: 22361 | H23: 236.5 | I23: 80 | J23: 2 | K23: 13 | L23: 0 | M23: 13 | N23: 9053.06 | O23: 6078 | P23: 0 | Q23: 9053.06 | R23: 6078 | S23: 0.04144439 | T23: 767 | U23: 2645.1401 | V23: 0.29218188 | W23: 821.73 | X23: 476.28 | Z23: 425.46 | AA23: 3917.4499 | AB23: 0.054053131 | AC23: 473 | AD23: 17 | AE23: 35 | AF23: 0.43272108 | AG23: 5.1074966 | AI23: 696.38923 | AJ23: 59 | AK23: 203.47231 | AL23: 63.21 | AM23: 36.636923 | AN23: 0 | AO23: 32.727692 | AP23: 301.3423
A24: 236072836 | B24: ACRB1MS106PN | C24: Мяч с шипами розовый 6 см | D24: 2040278810534 | E24: 303 | F24: 64 | G24: 19392 | H24: 127.3913 | I24: 82 | J24: 2.3 | K24: 13 | L24: 0 | M24: 13 | N24: 7205 | O24: 4931 | P24: 0 | Q24: 7205 | R24: 4931 | S24: 0.032984078 | T24: 832 | U24: 2066.1718 | V24: 0.28676916 | W24: 809.33 | X24: 299.88 | Z24: 345.17 | AA24: 2852.4482 | AB24: 0.039358194 | AC24: 293 | AD24: 22 | AE24: 33 | AF24: 0.39589843 | AG24: 3.4284233 | AI24: 554.23077 | AJ24: 64 | AK24: 158.93629 | AL24: 62.256154 | AM24: 23.067692 | AN24: 0 | AO24: 26.551538 | AP24: 219.41909
A25: 236072834 | B25: ACRB1MS106BL | C25: Мяч с шипами голубой 6 см | D25: 2040278804649 | E25: 235 | F25: 59 | G25: 13865 | H25: 281.11111 | I25: 100 | J25: 0.9 | K25: 3 | L25: 0 | M25: 3 | N25: 1645 | O25: 1159 | P25: 0 | Q25: 1645 | R25: 1159 | S25: 0.0075307158 | T25: 177 | U25: 466.94705 | V25: 0.28385839 | W25: 132.06 | X25: 250.88 | Z25: 81.13 | AA25: 536.98295 | AB25: 0.0074093122 | AC25: 253 | AD25: 13 | AE25: 55 | AF25: 0.3264334 | AG25: 3.033802 | AI25: 548.33333 | AJ25: 59 | AK25: 155.64902 | AL25: 44.02 | AM25: 83.626667 | AN25: 0 | AO25: 27.043333 | AP25: 178.99432
A26: 223671295 | B26: ACRB1MS106RJ | C26: Мяч с шипами оранжевый 6 см | D26: 2039818580389 | E26: 453 | F26: 59 | G26: 26727 | H26: 1660 | I26: 100 | J26: 0.3 | K26: 1 | L26: 0 | M26: 1 | N26: 525 | O26: 365 | P26: 0 | Q26: 525 | R26: 365 | S26: 0.0024034199 | T26: 59 | U26: 156.95049 | V26: 0.29895332 | W26: 142.66 | X26: 489.02 | Z26: 25.55 | AA26: -348.18049 | AB26: -0.0048042084 | AC26: 498 | AD26: 2 | AE26: 200 | AF26: -0.66320094 | AG26: -5.9013643 | AI26: 525 | AJ26: 59 | AK26: 156.95049 | AL26: 142.66 | AM26: 489.02 | AN26: 0 | AO26: 25.55 | AP26: -348.18049
A27: 370591238 | B27: ACRB1MS106BС | C27: Мяч с шипами черный 6 см | D27: 2043369663040 | E27: 196 | F27: 49 | G27: 9604 | H27: 104.5 | I27: 63 | J27: 2 | K27: 9 | L27: 0 | M27: 9 | N27: 4466 | O27: 3015 | P27: 0 | Q27: 4466 | R27: 3015 | S27: 0.020445092 | T27: 441 | U27: 1335.6044 | V27: 0.29906055 | W27: 909.08 | X27: 213.64 | Z27: 211.05 | AA27: 1355.6256 | AB27: 0.018704976 | AC27: 209 | AD27: 20 | AE27: 50 | AF27: 0.30354357 | AG27: 3.0739809 | AI27: 496.22222 | AJ27: 49 | AK27: 148.40049 | AL27: 101.00889 | AM27: 23.737778 | AN27: 0 | AO27: 23.45 | AP27: 150.62506
A28: 419145391 | B28: ACRB1MS107WH | C28: Мяч с шипами белый 7 см | D28: 2044025326637 | E28: 5 | F28: 62 | G28: 310 | H28: 2.6315789 | I28: 83 | J28: 1.9 | K28: 7 | L28: 0 | M28: 7 | N28: 4925 | O28: 3243 | P28: 0 | Q28: 4925 | R28: 3243 | S28: 0.022546368 | T28: 434 | U28: 1436.9616 | V28: 0.29176886 | W28: 656.7 | X28: 11.76 | Z28: 227.01 | AA28: 2158.5684 | AB28: 0.029784013 | AC28: 5 | AD28: 13 | AE28: 38 | AF28: 0.43828799 | AG28: 4.9736598 | AI28: 703.57143 | AJ28: 62 | AK28: 205.28023 | AL28: 93.814286 | AM28: 1.68 | AN28: 0 | AO28: 32.43 | AP28: 308.36691
A29: 419145389 | B29: ACRB1MS107PN | C29: Мяч с шипами розовый 7 см | D29: 2044025316447 | E29: 62 | F29: 63 | G29: 3906 | H29: 203.33333 | I29: 100 | J29: 0.3 | K29: 1 | L29: 0 | M29: 1 | N29: 615 | O29: 418 | P29: 0 | Q29: 615 | R29: 418 | S29: 0.0028154348 | T29: 63 | U29: 185.58393 | V29: 0.3017625 | W29: 64.59 | X29: 60.76 | Z29: 29.26 | AA29: 211.80607 | AB29: 0.0029225086 | AC29: 61 | AD29: 23 | AE29: 22 | AF29: 0.34440011 | AG29: 3.362001 | AI29: 615 | AJ29: 63 | AK29: 185.58393 | AL29: 64.59 | AM29: 60.76 | AN29: 0 | AO29: 29.26 | AP29: 211.80607
A30: 419145748 | B30: ACRB1MS107BL | C30: Мяч с шипами голубой 7 см | D30: 2044025338661 | E30: 80 | F30: 63 | G30: 5040 | H30: 790 | I30: 100 | J30: 0.1 | K30: 1 | L30: 0 | M30: 1 | N30: 525 | O30: 361 | P30: 0 | Q30: 525 | R30: 361 | S30: 0.0024034199 | T30: 63 | U30: 160.63869 | V30: 0.30597845 | W30: 55.98 | X30: 78.4 | Z30: 25.27 | AA30: 141.71131 | AB30: 0.0019553383 | AC30: 79 | AD30: 17 | AE30: 20 | AF30: 0.26992631 | AG30: 2.2493859 | AI30: 525 | AJ30: 63 | AK30: 160.63869 | AL30: 55.98 | AM30: 78.4 | AN30: 0 | AO30: 25.27 | AP30: 141.71131
A31: 419141548 | B31: ACRB1MS107RJ | C31: Мяч с шипами оранжевый 7 см | D31: 2044025288003 | E31: 77 | F31: 63 | G31: 4851 | H31: 250 | I31: 0 | J31: 0.3 | K31: 0 | L31: 0 | M31: 0 | N31: 0 | O31: 0 | P31: 0 | Q31: 0 | R31: 0 | S31: 0 | T31: 0 | U31: -8.4134426 | V31: 0 | W31: 0 | X31: 73.5 | Z31: 0 | AA31: -65.086557 | AB31: -0.00089806692 | AC31: 75 | AD31: 3 | AE31: 200 | AF31: 0 | AG31: 0 | AI31: 0 | AJ31: 63 | AK31: 0 | AL31: 0 | AM31: 73.5 | AN31: 0 | AP31: 0
A32: 419145985 | B32: ACRB1MS107BС | C32: Мяч с шипами черный 7 см | D32: 2044025344532 | E32: 73 | F32: 63 | G32: 4599 | H32: 999 | I32: 0 | J32: 0 | K32: 0 | L32: 0 | M32: 0 | N32: 0 | O32: 0 | P32: 0 | Q32: 0 | R32: 0 | S32: 0 | T32: 0 | U32: 0 | V32: 0 | W32: 95.93 | X32: 71.54 | Z32: 0 | AA32: -167.47 | AB32: -0.0023107578 | AC32: 73 | AD32: 3 | AE32: 0 | AF32: 0 | AG32: 0 | AI32: 0 | AJ32: 63 | AK32: 0 | AL32: 95.93 | AM32: 71.54 | AN32: 0 | AP32: 0
A33: 419145390 | B33: ACRB1MS109PN | C33: Мяч с шипами розовый 9 см | D33: 2044025321588 | E33: 67 | F33: 91 | G33: 6097 | H33: 200 | I33: 100 | J33: 0.4 | K33: 3 | L33: 0 | M33: 3 | N33: 1585 | O33: 1068 | P33: 0 | Q33: 1585 | R33: 1068 | S33: 0.0072560393 | T33: 273 | U33: 461.47525 | V33: 0.29115157 | W33: 277.19 | X33: 81.34 | Z33: 74.76 | AA33: 417.23475 | AB33: 0.0057570218 | AC33: 80 | AD33: 24 | AE33: 27 | AF33: 0.26323959 | AG33: 1.5283324 | AI33: 528.33333 | AJ33: 91 | AK33: 153.82508 | AL33: 92.396667 | AM33: 27.113333 | AN33: 0 | AO33: 24.92 | AP33: 139.07825
A34: 419145749 | B34: ACRB1MS109BL | C34: Мяч с шипами голубой 9 см | D34: 2044025342057 | E34: 80 | F34: 91 | G34: 7280 | H34: 900 | I34: 100 | J34: 0.1 | K34: 2 | L34: 0 | M34: 2 | N34: 1109 | O34: 768 | P34: 0 | Q34: 1109 | R34: 768 | S34: 0.0050769385 | T34: 182 | U34: 331.57115 | V34: 0.2989821 | W34: 87.61 | X34: 90.16 | Z34: 53.76 | AA34: 363.89885 | AB34: 0.0050210909 | AC34: 90 | AD34: 0 | AE34: 0 | AF34: 0.32813242 | AG34: 1.9994442 | AI34: 554.5 | AJ34: 91 | AK34: 165.78557 | AL34: 43.805 | AM34: 45.08 | AN34: 0 | AO34: 26.88 | AP34: 181.94943
A35: 419141549 | B35: ACRB1MS109RJ | C35: Мяч с шипами оранжевый 9 см | D35: 2044025291485 | E35: 62 | F35: 91 | G35: 5642 | H35: 999 | I35: 0 | J35: 0 | K35: 1 | L35: 0 | M35: 1 | N35: 482 | O35: 336 | P35: 0 | Q35: 482 | R35: 336 | S35: 0.0022065684 | T35: 91 | U35: 147.49148 | V35: 0.30599891 | W35: 167.31 | X35: 69.58 | Z35: 23.52 | AA35: -16.901475 | AB35: -0.00023320723 | AC35: 70 | AD35: 10 | AE35: 0 | AF35: -0.035065302 | AG35: -0.1857305 | AI35: 482 | AJ35: 91 | AK35: 147.49148 | AL35: 167.31 | AM35: 69.58 | AN35: 0 | AO35: 23.52 | AP35: -16.901475
A36: 419145986 | B36: ACRB1MS109BС | C36: Мяч с шипами черный 9 см | D36: 2044025347953 | E36: 98 | F36: 91 | G36: 8918 | H36: 999 | I36: 0 | J36: 0 | K36: 0 | L36: 0 | M36: 0 | N36: 0 | O36: 0 | P36: 0 | Q36: 0 | R36: 0 | S36: 0 | T36: 0 | U36: 0 | V36: 0 | W36: 0 | X36: 105.84 | Z36: 0 | AA36: -105.84 | AB36: -0.0014603846 | AC36: 108 | AD36: 5 | AE36: 0 | AF36: 0 | AG36: 0 | AI36: 0 | AJ36: 91 | AK36: 0 | AL36: 0 | AM36: 105.84 | AN36: 0 | AP36: 0
A37: 419146579 | B37: ACRB1MS109LI | C37: Мяч с шипами фиолетовый 9 см | D37: 2044025354937 | E37: 112 | F37: 91 | G37: 10192 | H37: 340 | I37: 33 | J37: 0.4 | K37: 3 | L37: 0 | M37: 3 | N37: 1486 | O37: 1046 | P37: 0 | Q37: 1486 | R37: 1046 | S37: 0.0068028229 | T37: 273 | U37: 458.73246 | V37: 0.30870287 | W37: 118.79 | X37: 136.22 | Z37: 73.22 | AA37: 426.03754 | AB37: 0.005878483 | AC37: 136 | AD37: 21 | AE37: 43 | AF37: 0.2867009 | AG37: 1.5605771 | AI37: 495.33333 | AJ37: 91 | AK37: 152.91082 | AL37: 39.596667 | AM37: 45.406667 | AN37: 0 | AO37: 24.406667 | AP37: 142.01251
A38: 340734340 | B38: ACRB1MS103PN | C38: Мяч гладкий розовый | D38: 2042985583893 | E38: 31 | F38: 87 | G38: 2697 | H38: 20 | I38: 88 | J38: 1.4 | K38: 8 | L38: 0 | M38: 8 | N38: 2956.9 | O38: 2008 | P38: 0 | Q38: 2956.9 | R38: 2008 | S38: 0.013536519 | T38: 696 | U38: 866.35328 | V38: 0.29299377 | W38: 556.71 | X38: 35.28 | Z38: 140.56 | AA38: 661.99672 | AB38: 0.0091342573 | AC38: 28 | AD38: 24 | AE38: 48 | AF38: 0.22388201 | AG38: 0.95114471 | AI38: 369.6125 | AJ38: 87 | AK38: 108.29416 | AL38: 69.58875 | AM38: 4.41 | AN38: 0 | AO38: 17.57 | AP38: 82.74959
A39: 340741532 | B39: ACRB1MS103BL | C39: Мяч гладкий голубой | D39: 2042986356632 | E39: 82 | F39: 87 | G39: 7134 | H39: 266.66667 | I39: 50 | J39: 0.3 | K39: 0 | L39: 0 | M39: 0 | N39: 0 | O39: 0 | P39: 0 | Q39: 0 | R39: 0 | S39: 0 | T39: 0 | U39: 0 | V39: 0 | W39: 0 | X39: 78.4 | Z39: 0 | AA39: -78.4 | AB39: -0.0010817663 | AC39: 80 | AD39: 12 | AE39: 67 | AF39: 0 | AG39: 0 | AI39: 0 | AJ39: 87 | AK39: 0 | AL39: 0 | AM39: 78.4 | AN39: 0 | AP39: 0
A40: 340743352 | B40: ACRB1MS103LI | C40: Мяч гладкий сиреневый | D40: 2042986372359 | E40: 55 | F40: 87 | G40: 4785 | H40: 127.5 | I40: 0 | J40: 0.4 | K40: 3 | L40: 0 | M40: 3 | N40: 1068 | O40: 738 | P40: 0 | Q40: 1068 | R40: 738 | S40: 0.0048892429 | T40: 261 | U40: 341.74967 | V40: 0.31999033 | W40: 120.57 | X40: 52.92 | Z40: 51.66 | AA40: 240.10033 | AB40: 0.0033129139 | AC40: 51 | AD40: 7 | AE40: 100 | AF40: 0.22481304 | AG40: 0.91992463 | AI40: 356 | AJ40: 87 | AK40: 113.91656 | AL40: 40.19 | AM40: 17.64 | AN40: 0 | AO40: 17.22 | AP40: 80.033443
A41: 340743911 | B41: ACRB1MS103RJ | C41: Мяч гладкий оранжевый | D41: 2042986377583 | E41: 57 | F41: 88 | G41: 5016 | H41: 560 | I41: 0 | J41: 0.1 | K41: 1 | L41: 0 | M41: 1 | N41: 381 | O41: 266 | P41: 0 | Q41: 381 | R41: 266 | S41: 0.0017441962 | T41: 88 | U41: 115.09607 | V41: 0.30208941 | W41: 43.06 | X41: 55.86 | Z41: 18.62 | AA41: 60.363934 | AB41: 0.00083290398 | AC41: 56 | AD41: 14 | AE41: 33 | AF41: 0.15843552 | AG41: 0.6859538 | AI41: 381 | AJ41: 88 | AK41: 115.09607 | AL41: 43.06 | AM41: 55.86 | AN41: 0 | AO41: 18.62 | AP41: 60.363934
A42: 550530967 | B42: ACRB3FR100CL | C42: Набор эластичных лент 3 шт. в мешке | D42: 2046392440640 | E42: 33 | F42: 437 | G42: 14421 | H42: 999 | I42: 0 | J42: 0 | K42: 0 | L42: 0 | M42: 0 | N42: 0 | O42: 0 | P42: 0 | Q42: 0 | R42: 0 | S42: 0 | T42: 0 | U42: -26.92377 | V42: 0 | W42: 149.66 | X42: 79.5564 | Z42: 0 | AA42: -202.29263 | AB42: -0.0027912418 | AC42: 41 | AD42: 0 | AE42: 0 | AF42: 0 | AG42: 0 | AI42: 0 | AJ42: 437 | AK42: 0 | AL42: 149.66 | AM42: 79.5564 | AN42: 0 | AP42: 0
A43: 550539998 | B43: ACRB5FR200CL | C43: Набор эластичных лент 5 шт. в мешке | D43: 2046392546618 | E43: 35 | F43: 467 | G43: 16345 | H43: 999 | I43: 0 | J43: 0 | K43: 0 | L43: 0 | M43: 0 | N43: 0 | O43: 0 | P43: 0 | Q43: 0 | R43: 0 | S43: 0 | T43: 0 | U43: 0 | V43: 0 | W43: 0 | X43: 43.12 | Z43: 0 | AA43: -43.12 | AB43: -0.00059497149 | AC43: 44 | AD43: 0 | AE43: 0 | AF43: 0 | AG43: 0 | AI43: 0 | AJ43: 467 | AK43: 0 | AL43: 0 | AM43: 43.12 | AN43: 0 | AP43: 0
A44: 550539999 | B44: ACRB4FR300CL | C44: Набор эластичных лент 4 шт. | D44: 2046392546632 | E44: 35 | F44: 309 | G44: 10815 | H44: 999 | I44: 0 | J44: 0 | K44: 0 | L44: 0 | M44: 0 | N44: 0 | O44: 0 | P44: 0 | Q44: 0 | R44: 0 | S44: 0 | T44: 0 | U44: 0 | V44: 0 | W44: 0 | X44: 46.06 | Z44: 0 | AA44: -46.06 | AB44: -0.00063553772 | AC44: 47 | AD44: 20 | AE44: 0 | AF44: 0 | AG44: 0 | AI44: 0 | AJ44: 309 | AK44: 0 | AL44: 0 | AM44: 46.06 | AN44: 0 | AP44: 0
A45: 550540000 | B45: ACRB5FR400CL | C45: Набор эластичных лент 5 шт. | D45: 2046392546656 | E45: 0 | F45: 142 | G45: 0 | H45: 0 | I45: 0 | J45: 0 | K45: 0 | L45: 0 | M45: 0 | N45: 0 | O45: 0 | P45: 0 | Q45: 0 | R45: 0 | S45: 0 | T45: 0 | U45: 0 | V45: 0 | W45: 0 | X45: 0 | Z45: 0 | AA45: 0 | AB45: 0 | AC45: 0 | AD45: 0 | AE45: 0 | AF45: 0 | AG45: 0 | AI45: 0 | AJ45: 142 | AK45: 0 | AL45: 0 | AM45: 0 | AN45: 0 | AP45: 0
A46: 550445272 | B46: ACRF1KP101BC | C46: Капа черный/красный - черная коробка | D46: 2046391283330 | E46: 0 | F46: 80 | G46: 0 | H46: 0 | I46: 0 | J46: 0 | K46: 0 | L46: 0 | M46: 0 | N46: 0 | O46: 0 | P46: 0 | Q46: 0 | R46: 0 | S46: 0 | T46: 0 | U46: 0 | V46: 0 | W46: 0 | X46: 0 | Z46: 0 | AA46: 0 | AB46: 0 | AC46: 0 | AD46: 0 | AE46: 0 | AF46: 0 | AG46: 0 | AI46: 0 | AJ46: 80 | AK46: 0 | AL46: 0 | AM46: 0 | AN46: 0 | AP46: 0
A47: 550445274 | B47: ACRF1KP102BC | C47: Капа черный/белый-черная коробка | D47: 2046391283385 | E47: 0 | F47: 80 | G47: 0 | H47: 0 | I47: 0 | J47: 0 | K47: 0 | L47: 0 | M47: 0 | N47: 0 | O47: 0 | P47: 0 | Q47: 0 | R47: 0 | S47: 0 | T47: 0 | U47: 0 | V47: 0 | W47: 0 | X47: 0 | Z47: 0 | AA47: 0 | AB47: 0 | AC47: 0 | AD47: 0 | AE47: 0 | AF47: 0 | AG47: 0 | AI47: 0 | AJ47: 80 | AK47: 0 | AL47: 0 | AM47: 0 | AN47: 0 | AP47: 0
A48: 550445275 | B48: ACRF1KP103BC | C48: Капа белый/черный | D48: 2046391283415 | E48: 0 | F48: 80 | G48: 0 | H48: 0 | I48: 0 | J48: 0 | K48: 0 | L48: 0 | M48: 0 | N48: 0 | O48: 0 | P48: 0 | Q48: 0 | R48: 0 | S48: 0 | T48: 0 | U48: 0 | V48: 0 | W48: 0 | X48: 0 | Z48: 0 | AA48: 0 | AB48: 0 | AC48: 0 | AD48: 0 | AE48: 0 | AF48: 0 | AG48: 0 | AI48: 0 | AJ48: 80 | AK48: 0 | AL48: 0 | AM48: 0 | AN48: 0 | AP48: 0
A49: 550445277 | B49: ACRF1KP101RD | C49: Капа белый/красный | D49: 2046391283446 | E49: 0 | F49: 80 | G49: 0 | H49: 0 | I49: 0 | J49: 0 | K49: 0 | L49: 0 | M49: 0 | N49: 0 | O49: 0 | P49: 0 | Q49: 0 | R49: 0 | S49: 0 | T49: 0 | U49: 0 | V49: 0 | W49: 0 | X49: 0 | Z49: 0 | AA49: 0 | AB49: 0 | AC49: 0 | AD49: 0 | AE49: 0 | AF49: 0 | AG49: 0 | AI49: 0 | AJ49: 80 | AK49: 0 | AL49: 0 | AM49: 0 | AN49: 0 | AP49: 0
A50: 550445279 | B50: ACRF1KP102RD | C50: Капа красный/белый | D50: 2046391283507 | E50: 0 | F50: 80 | G50: 0 | H50: 0 | I50: 0 | J50: 0 | K50: 0 | L50: 0 | M50: 0 | N50: 0 | O50: 0 | P50: 0 | Q50: 0 | R50: 0 | S50: 0 | T50: 0 | U50: 0 | V50: 0 | W50: 0 | X50: 0 | Z50: 0 | AA50: 0 | AB50: 0 | AC50: 0 | AD50: 0 | AE50: 0 | AF50: 0 | AG50: 0 | AI50: 0 | AJ50: 80 | AK50: 0 | AL50: 0 | AM50: 0 | AN50: 0 | AP50: 0
A51: 550445280 | B51: ACRF1KP101BL | C51: Капа синий/белый | D51: 2046391283545 | E51: 0 | F51: 80 | G51: 0 | H51: 0 | I51: 0 | J51: 0 | K51: 0 | L51: 0 | M51: 0 | N51: 0 | O51: 0 | P51: 0 | Q51: 0 | R51: 0 | S51: 0 | T51: 0 | U51: 0 | V51: 0 | W51: 0 | X51: 0 | Z51: 0 | AA51: 0 | AB51: 0 | AC51: 0 | AD51: 0 | AE51: 0 | AF51: 0 | AG51: 0 | AI51: 0 | AJ51: 80 | AK51: 0 | AL51: 0 | AM51: 0 | AN51: 0 | AP51: 0
A52: 550445281 | B52: ACRF1KP101GN | C52: Капа зеленый/белый | D52: 2046391283569 | E52: 0 | F52: 80 | G52: 0 | H52: 0 | I52: 0 | J52: 0 | K52: 0 | L52: 0 | M52: 0 | N52: 0 | O52: 0 | P52: 0 | Q52: 0 | R52: 0 | S52: 0 | T52: 0 | U52: 0 | V52: 0 | W52: 0 | X52: 0 | Z52: 0 | AA52: 0 | AB52: 0 | AC52: 0 | AD52: 0 | AE52: 0 | AF52: 0 | AG52: 0 | AI52: 0 | AJ52: 80 | AK52: 0 | AL52: 0 | AM52: 0 | AN52: 0 | AP52: 0
A53: 550445283 | B53: ACRF1KP102GN | C53: Капа зеленый/черный | D53: 2046391283613 | E53: 0 | F53: 80 | G53: 0 | H53: 0 | I53: 0 | J53: 0 | K53: 0 | L53: 0 | M53: 0 | N53: 0 | O53: 0 | P53: 0 | Q53: 0 | R53: 0 | S53: 0 | T53: 0 | U53: 0 | V53: 0 | W53: 0 | X53: 0 | Z53: 0 | AA53: 0 | AB53: 0 | AC53: 0 | AD53: 0 | AE53: 0 | AF53: 0 | AG53: 0 | AI53: 0 | AJ53: 80 | AK53: 0 | AL53: 0 | AM53: 0 | AN53: 0 | AP53: 0
A54: 186826338 | B54: ACRA7TB201BC | C54: Таблетница прям 7*2 черн | D54: 2038891723249 | E54: 613 | F54: 171 | G54: 104823 | H54: 183.07692 | I54: 73 | J54: 3.9 | K54: 15 | L54: 1 | M54: 14 | N54: 11068 | O54: 7576 | P54: 848 | Q54: 10220 | R54: 6728 | S54: 0.046786575 | T54: 2394 | U54: 1900.929 | V54: 0.18600088 | W54: 1385.66 | X54: 714.42 | Z54: 470.96 | AA54: 3354.031 | AB54: 0.046279054 | AC54: 714 | AD54: 15 | AE54: 33 | AF54: 0.34495437 | AG54: 1.4726122 | AI54: 730 | AJ54: 171 | AK54: 135.78064 | AL54: 92.377333 | AM54: 47.628 | AN54: 0 | AO54: 31.397333 | AP54: 251.81669
A55: 419130077 | B55: ACRA7TB201CL | C55: Таблетница прям 7*2 черн/цветн | D55: 2044025155923 | E55: 272 | F55: 171 | G55: 46512 | H55: 195 | I55: 100 | J55: 1.6 | K55: 12 | L55: 0 | M55: 12 | N55: 8562.94 | O55: 5972.32 | P55: 0 | Q55: 8562.94 | R55: 5972.32 | S55: 0.039200649 | T55: 2052 | U55: 2229.0359 | V55: 0.26031198 | W55: 755.52 | X55: 317.52 | Z55: 418.0624 | AA55: 2790.8017 | AB55: 0.038507594 | AC55: 312 | AD55: 12 | AE55: 28 | AF55: 0.3259163 | AG55: 1.3600398 | AI55: 713.57833 | AJ55: 171 | AK55: 185.75299 | AL55: 62.96 | AM55: 26.46 | AN55: 0 | AO55: 34.838533 | AP55: 232.56681
A56: 448248943 | B56: ACRA7TB201WH | C56: Таблетница прям 7*2 бел/цветн | D56: 2044516485386 | E56: 208 | F56: 171 | G56: 35568 | H56: 256.66667 | I56: 60 | J56: 0.9 | K56: 4 | L56: 0 | M56: 4 | N56: 2857 | O56: 1893 | P56: 0 | Q56: 2857 | R56: 1893 | S56: 0.013079182 | T56: 684 | U56: 681.2177 | V56: 0.23843812 | W56: 242.34 | X56: 230.3 | Z56: 132.51 | AA56: 886.6323 | AB56: 0.012233788 | AC56: 231 | AD56: 9 | AE56: 25 | AF56: 0.31033682 | AG56: 1.296246 | AI56: 714.25 | AJ56: 171 | AK56: 170.30443 | AL56: 60.585 | AM56: 57.575 | AN56: 0 | AO56: 33.1275 | AP56: 221.65807
A57: 448254852 | B57: ACRA7TB201LI | C57: Таблетница прям 7*2 сирен/цветн | D57: 2044516498812 | E57: 212 | F57: 171 | G57: 36252 | H57: 999 | I57: 0 | J57: 0 | K57: 1 | L57: 0 | M57: 1 | N57: 717 | O57: 509 | P57: 0 | Q57: 717 | R57: 509 | S57: 0.003282385 | T57: 171 | U57: 182.88295 | V57: 0.25506688 | W57: 61.77 | X57: 227.36 | Z57: 35.63 | AA57: 38.357049 | AB57: 0.0005292521 | AC57: 231 | AD57: 2 | AE57: 0 | AF57: 0.053496582 | AG57: 0.22431023 | AI57: 717 | AJ57: 171 | AK57: 182.88295 | AL57: 61.77 | AM57: 227.36 | AN57: 0 | AO57: 35.63 | AP57: 38.357049
A58: 186800214 | B58: ACRA7TB101BC | C58: Таблетница круглая 7*2 черн | D58: 2038890789598 | E58: 219 | F58: 250 | G58: 54750 | H58: 793.33333 | I58: 0 | J58: 0.3 | K58: 0 | L58: 0 | M58: 0 | N58: 0 | O58: 0 | P58: 0 | Q58: 0 | R58: 0 | S58: 0 | T58: 0 | U58: -28.771967 | V58: 0 | W58: 300.72 | X58: 333.06672 | Z58: 0 | AA58: -605.01475 | AB58: -0.0083480178 | AC58: 238 | AD58: 4 | AE58: 200 | AF58: 0 | AG58: 0 | AI58: 0 | AJ58: 250 | AK58: 0 | AL58: 300.72 | AM58: 333.06672 | AN58: 0 | AP58: 0
A59: 298193176 | B59: ACRA7TB101CL | C59: Таблетница круглая 7*2 черн/цвет | D59: 2042160422832 | E59: 174 | F59: 250 | G59: 43500 | H59: 1840 | I59: 100 | J59: 0.1 | K59: 2 | L59: 0 | M59: 2 | N59: 1974 | O59: 1412 | P59: 0 | Q59: 1974 | R59: 1412 | S59: 0.009036859 | T59: 500 | U59: 509.47803 | V59: 0.25809424 | W59: 164.68 | X59: 260.29584 | Z59: 98.84 | AA59: 440.70613 | AB59: 0.0060808808 | AC59: 184 | AD59: 7 | AE59: 50 | AF59: 0.22325538 | AG59: 0.88141225 | AI59: 987 | AJ59: 250 | AK59: 254.73902 | AL59: 82.34 | AM59: 130.14792 | AN59: 0 | AO59: 49.42 | AP59: 220.35306
A60: 278515093 | B60: ACRA7TB301GR | C60: Таблетница круглая 7*2 сер | D60: 2041680530447 | E60: 209 | F60: 142 | G60: 29678 | H60: 70.909091 | I60: 79 | J60: 3.3 | K60: 18 | L60: 0 | M60: 18 | N60: 13346 | O60: 9192 | P60: 0 | Q60: 13346 | R60: 9192 | S60: 0.061097224 | T60: 2556 | U60: 3323.6348 | V60: 0.24903602 | W60: 2521.85 | X60: 352.65888 | Z60: 643.44 | AA60: 3948.4164 | AB60: 0.054480407 | AC60: 234 | AD60: 16 | AE60: 28 | AF60: 0.29585017 | AG60: 1.5447638 | AI60: 741.44444 | AJ60: 142 | AK60: 184.64638 | AL60: 140.10278 | AM60: 19.59216 | AN60: 0 | AO60: 35.746667 | AP60: 219.35646
A61: 345168494 | B61: ACRA7TB301CL | C61: Таблетница круглая 7*2 сер /цвет | D61: 2043048226719 | E61: 216 | F61: 142 | G61: 30672 | H61: 813.33333 | I61: 0 | J61: 0.3 | K61: 1 | L61: 0 | M61: 1 | N61: 894 | O61: 598 | P61: 0 | Q61: 894 | R61: 598 | S61: 0.0040926808 | T61: 142 | U61: 234.94639 | V61: 0.26280357 | W61: 263.58 | X61: 342.8628 | Z61: 41.86 | AA61: -131.24919 | AB61: -0.0018109816 | AC61: 244 | AD61: 6 | AE61: 20 | AF61: -0.14681118 | AG61: -0.92429009 | AI61: 894 | AJ61: 142 | AK61: 234.94639 | AL61: 263.58 | AM61: 342.8628 | AN61: 0 | AO61: 41.86 | AP61: -131.24919
A62: 273516556 | B62: ACRA7TB301WH | C62: Таблетница круглая 7*2 бел | D62: 2041532808502 | E62: 107 | F62: 142 | G62: 15194 | H62: 193.33333 | I62: 75 | J62: 0.6 | K62: 1 | L62: 0 | M62: 1 | N62: 867.18 | O62: 586 | P62: 0 | Q62: 867.18 | R62: 586 | S62: 0.0039699004 | T62: 142 | U62: 197.51967 | V62: 0.2277724 | W62: 268.74 | X62: 163.73448 | Z62: 41.02 | AA62: 54.165848 | AB62: 0.00074738254 | AC62: 116 | AD62: 8 | AE62: 44 | AF62: 0.062462058 | AG62: 0.38144963 | AI62: 867.18 | AJ62: 142 | AK62: 197.51967 | AL62: 268.74 | AM62: 163.73448 | AN62: 0 | AO62: 41.02 | AP62: 54.165848
A63: 321907864 | B63: ACRA7TB401BC | C63: Таблетница автомат 7*2 черн | D63: 2042676873814 | E63: 0 | F63: 335 | G63: 0 | H63: 0 | I63: 0 | J63: 0 | K63: 0 | L63: 0 | M63: 0 | N63: 0 | O63: 0 | P63: 0 | Q63: 0 | R63: 0 | S63: 0 | T63: 0 | U63: 0 | V63: 0 | W63: 0 | X63: 0 | Z63: 0 | AA63: 0 | AB63: 0 | AC63: 0 | AD63: 0 | AE63: 0 | AF63: 0 | AG63: 0 | AI63: 0 | AJ63: 335 | AK63: 0 | AL63: 0 | AM63: 0 | AN63: 0 | AP63: 0
A64: 271440668 | B64: ACRB1SK101BC | C64: Скакалка черная | D64: 2041473034138 | E64: 150 | F64: 282 | G64: 42300 | H64: 285 | I64: 100 | J64: 0.6 | K64: 5 | L64: 0 | M64: 5 | N64: 4070 | O64: 2530 | P64: 0 | Q64: 4070 | R64: 2530 | S64: 0.018632227 | T64: 1410 | U64: 1086.8023 | V64: 0.26702759 | W64: 160.85 | X64: 172.48 | Z64: 177.1 | AA64: 1062.7677 | AB64: 0.014664111 | AC64: 171 | AD64: 9 | AE64: 57 | AF64: 0.26112229 | AG64: 0.75373596 | AI64: 814 | AJ64: 282 | AK64: 217.36046 | AL64: 32.17 | AM64: 34.496 | AN64: 0 | AO64: 35.42 | AP64: 212.55354
A65: 271440669 | B65: ACRB1SK101RD | C65: Скакалка красная | D65: 2041473034145 | E65: 140 | F65: 282 | G65: 39480 | H65: 1600 | I65: 0 | J65: 0.1 | K65: 0 | L65: 0 | M65: 0 | N65: 0 | O65: 0 | P65: 0 | Q65: 0 | R65: 0 | S65: 0 | T65: 0 | U65: -12.681639 | V65: 0 | W65: 168.2 | X65: 156.8 | Z65: 0 | AA65: -312.31836 | AB65: -0.0043093812 | AC65: 160 | AD65: 3 | AE65: 100 | AF65: 0 | AG65: 0 | AI65: 0 | AJ65: 282 | AK65: 0 | AL65: 168.2 | AM65: 156.8 | AN65: 0 | AP65: 0
A66: 271440670 | B66: ACRB1SK101BL | C66: Скакалка синяя | D66: 2041473034169 | E66: 119 | F66: 282 | G66: 33558 | H66: 456.66667 | I66: 50 | J66: 0.3 | K66: 5 | L66: 0 | M66: 5 | N66: 4099.98 | O66: 2727.47 | P66: 0 | Q66: 4099.98 | R66: 2727.47 | S66: 0.018769474 | T66: 1410 | U66: 1100.1618 | V66: 0.26833346 | W66: 318.96 | X66: 139.16 | Z66: 190.9229 | AA66: 940.7753 | AB66: 0.012980855 | AC66: 137 | AD66: 8 | AE66: 50 | AF66: 0.22945851 | AG66: 0.66721652 | AI66: 819.996 | AJ66: 282 | AK66: 220.03236 | AL66: 63.792 | AM66: 27.832 | AN66: 0 | AO66: 38.18458 | AP66: 188.15506
A67: 271441230 | B67: ACRB1SK201BC | C67: Скакалка со счетчиком | D67: 2041473042966 | E67: 0 | F67: 268 | G67: 0 | H67: 0 | I67: 0 | J67: 0 | K67: 0 | L67: 0 | M67: 0 | N67: 0 | O67: 0 | P67: 0 | Q67: 0 | R67: 0 | S67: 0 | T67: 0 | U67: 0 | V67: 0 | W67: 0 | X67: 0 | Z67: 0 | AA67: 0 | AB67: 0 | AC67: 0 | AD67: 0 | AE67: 0 | AF67: 0 | AG67: 0 | AI67: 0 | AJ67: 268 | AK67: 0 | AL67: 0 | AM67: 0 | AN67: 0 | AP67: 0
A68: 251537223 | B68: AAND1BL101RD | C68: Мяч регби красный | D68: 2040903539366 | E68: 197 | F68: 121 | G68: 23837 | H68: 48.205128 | I68: 96 | J68: 3.9 | K68: 22 | L68: 0 | M68: 22 | N68: 10053.58 | O68: 7451 | P68: 0 | Q68: 10053.58 | R68: 7451 | S68: 0.046024714 | T68: 2662 | U68: 1961.4495 | V68: 0.19509961 | W68: 1726.2 | X68: 205.8 | Z68: 521.57 | AA68: 2976.5605 | AB68: 0.041070701 | AC68: 188 | AD68: 10 | AE68: 50 | AF68: 0.29606971 | AG68: 1.118167 | AI68: 456.98091 | AJ68: 121 | AK68: 89.156796 | AL68: 78.463636 | AM68: 9.3545455 | AN68: 0 | AO68: 23.707727 | AP68: 135.2982
A69: 251537413 | B69: AAND1BL101BL | C69: Мяч регби синий | D69: 2040903547941 | E69: 218 | F69: 121 | G69: 26378 | H69: 216 | I69: 100 | J69: 1 | K69: 9 | L69: 0 | M69: 9 | N69: 4143.18 | O69: 3205.35 | P69: 0 | Q69: 4143.18 | R69: 3205.35 | S69: 0.018967241 | T69: 1089 | U69: 792.67738 | V69: 0.19132101 | W69: 462.19 | X69: 220.5 | Z69: 224.3745 | AA69: 1354.4381 | AB69: 0.018688591 | AC69: 216 | AD69: 8 | AE69: 37 | AF69: 0.32690786 | AG69: 1.2437448 | AI69: 460.35333 | AJ69: 121 | AK69: 88.075264 | AL69: 51.354444 | AM69: 24.5 | AN69: 0 | AO69: 24.9305 | AP69: 150.49312
A70: 251516159 | B70: AAND1BL102RD | C70: Мяч шина красный | D70: 2040902555480 | E70: 139 | F70: 137 | G70: 19043 | H70: 73 | I70: 100 | J70: 2 | K70: 18 | L70: 1 | M70: 17 | N70: 13917.54 | O70: 10685.2 | P70: 753.69 | Q70: 13163.85 | R70: 9931.51 | S70: 0.060263352 | T70: 2329 | U70: 2293.981 | V70: 0.17426368 | W70: 1210.24 | X70: 160.72 | Z70: 695.2057 | AA70: 6474.7033 | AB70: 0.089338216 | AC70: 146 | AD70: 14 | AE70: 26 | AF70: 0.5005747 | AG70: 2.8293217 | AI70: 774.34412 | AJ70: 137 | AK70: 134.94006 | AL70: 67.235556 | AM70: 8.9288889 | AN70: 0 | AO70: 38.622539 | AP70: 387.61708
A71: 251407392 | B71: AAND1BL102BL | C71: Мяч шина синий | D71: 2040900511679 | E71: 115 | F71: 137 | G71: 15755 | H71: 38.787879 | I71: 94 | J71: 3.3 | K71: 18 | L71: 0 | M71: 18 | N71: 12765.64 | O71: 9745.58 | P71: 0 | Q71: 12765.64 | R71: 9745.58 | S71: 0.058440369 | T71: 2466 | U71: 2532.2134 | V71: 0.19836165 | W71: 1090.92 | X71: 143.08 | Z71: 682.1906 | AA71: 5851.236 | AB71: 0.080735589 | AC71: 128 | AD71: 16 | AE71: 30 | AF71: 0.45835822 | AG71: 2.372764 | AI71: 709.20222 | AJ71: 137 | AK71: 140.67852 | AL71: 60.606667 | AM71: 7.9488889 | AN71: 0 | AO71: 37.899478 | AP71: 325.06867
A72: 302564795 | B72: AAND1ST202BL | C72: Палочка для жевания | D72: 2042253544953 | E72: 0 | F72: 204 | G72: 0 | H72: 0 | I72: 0 | J72: 0 | K72: 1 | L72: 0 | M72: 1 | N72: 614 | O72: 494 | P72: 0 | Q72: 614 | R72: 494 | S72: 0.0028108568 | T72: 204 | U72: 115.89623 | V72: 0.18875607 | W72: 47.52 | X72: 0.98 | Z72: 34.58 | AA72: 211.02377 | AB72: 0.0029117144 | AC72: 0 | AD72: 0 | AE72: 0 | AF72: 0.34368692 | AG72: 1.0344302 | AI72: 614 | AJ72: 204 | AK72: 115.89623 | AL72: 47.52 | AM72: 0.98 | AN72: 0 | AO72: 34.58 | AP72: 211.02377
A73: 273588520 | B73: AAND1RP301BG | C73: Канат бол бежевый 55см/520гр | D73: 2041534216404 | E73: 17 | F73: 478 | G73: 8126 | H73: 53.333333 | I73: 100 | J73: 0.3 | K73: 1 | L73: 0 | M73: 1 | N73: 968 | O73: 733 | P73: 0 | Q73: 968 | R73: 733 | S73: 0.0044314486 | T73: 478 | U73: 201.6518 | V73: 0.20831798 | W73: 107.55 | X73: 48.11408 | Z73: 51.31 | AA73: 81.374117 | AB73: 0.0011228033 | AC73: 16 | AD73: 21 | AE73: 33 | AF73: 0.08406417 | AG73: 0.17023874 | AI73: 968 | AJ73: 478 | AK73: 201.6518 | AL73: 107.55 | AM73: 48.11408 | AN73: 0 | AO73: 51.31 | AP73: 81.374117
A74: 273589771 | B74: AAND1RP301YL | C74: Канат мал желтый 55см/330гр | D74: 2041534288661 | E74: 15 | F74: 326 | G74: 4890 | H74: 999 | I74: 0 | J74: 0 | K74: 0 | L74: 0 | M74: 0 | N74: 0 | O74: 0 | P74: 0 | Q74: 0 | R74: 0 | S74: 0 | T74: 0 | U74: 0 | V74: 0 | W74: 0 | X74: 27.783 | Z74: 0 | AA74: -27.783 | AB74: -0.00038335095 | AC74: 15 | AD74: 0 | AE74: 0 | AF74: 0 | AG74: 0 | AI74: 0 | AJ74: 326 | AK74: 0 | AL74: 0 | AM74: 27.783 | AN74: 0 | AP74: 0
A75: 273556717 | B75: AKTA4ST101CL | C75: Набор пробок 4 шт. в коробке нежн | D75: 2041533648312 | E75: 169 | F75: 104 | G75: 17576 | H75: 98.75 | I75: 80 | J75: 1.6 | K75: 15 | L75: 0 | M75: 15 | N75: 8190.69 | O75: 5082 | P75: 0 | Q75: 8190.69 | R75: 5082 | S75: 0.03749651 | T75: 1560 | U75: 2325.5821 | V75: 0.28392994 | W75: 747.7 | X75: 169.54 | Z75: 355.74 | AA75: 3032.1279 | AB75: 0.041837422 | AC75: 158 | AD75: 12 | AE75: 42 | AF75: 0.37019199 | AG75: 1.9436717 | AI75: 546.046 | AJ75: 104 | AK75: 155.03881 | AL75: 49.846667 | AM75: 11.302667 | AN75: 0 | AO75: 23.716 | AP75: 202.14186
A76: 370594147 | B76: AKTA4ST103CL | C76: Набор пробок 4 шт. в коробке ярк | D76: 2043369755509 | E76: 81 | F76: 123 | G76: 9963 | H76: 71.818182 | I76: 80 | J76: 1.1 | K76: 7 | L76: 0 | M76: 7 | N76: 3844 | O76: 2350 | P76: 0 | Q76: 3844 | R76: 2350 | S76: 0.017597612 | T76: 861 | U76: 1013.8069 | V76: 0.26373748 | W76: 596.55 | X76: 84.28 | Z76: 164.5 | AA76: 1123.8631 | AB76: 0.015507108 | AC76: 79 | AD76: 15 | AE76: 29 | AF76: 0.29236814 | AG76: 1.3052998 | AI76: 549.14286 | AJ76: 123 | AK76: 144.82956 | AL76: 85.221429 | AM76: 12.04 | AN76: 0 | AO76: 23.5 | AP76: 160.55187
A77: 321959186 | B77: AKTA4ST102CL | C77: Набор пробок 4 шт. | D77: 2042678197468 | E77: 58 | F77: 121 | G77: 7018 | H77: 91.666667 | I77: 100 | J77: 0.6 | K77: 6 | L77: 0 | M77: 6 | N77: 3288.53 | O77: 1965 | P77: 0 | Q77: 3288.53 | R77: 1965 | S77: 0.015054702 | T77: 726 | U77: 902.44705 | V77: 0.27442263 | W77: 241.14 | X77: 59.78 | Z77: 137.55 | AA77: 1221.613 | AB77: 0.016855864 | AC77: 55 | AD77: 7 | AE77: 40 | AF77: 0.37147691 | AG77: 1.6826625 | AI77: 548.08833 | AJ77: 121 | AK77: 150.40784 | AL77: 40.19 | AM77: 9.9633333 | AN77: 0 | AO77: 22.925 | AP77: 203.60216
A78: 273546535 | B78: AKTA2KN101YL | C78: Шпатель желтый | D78: 2041533399818 | E78: 70 | F78: 171 | G78: 11970 | H78: 900 | I78: 100 | J78: 0.1 | K78: 0 | L78: 0 | M78: 0 | N78: 0 | O78: 0 | P78: 0 | Q78: 0 | R78: 0 | S78: 0 | T78: 0 | U78: -21.435574 | V78: 0 | W78: 101.97 | X78: 88.2 | Z78: 0 | AA78: -168.73443 | AB78: -0.0023282044 | AC78: 90 | AD78: 14 | AE78: 20 | AF78: 0 | AG78: 0 | AI78: 0 | AJ78: 171 | AK78: 0 | AL78: 101.97 | AM78: 88.2 | AN78: 0 | AP78: 0
A79: 273551028 | B79: AKTA2KN101BL | C79: Шпатель голубой | D79: 2041533587000 | E79: 0 | F79: 242 | G79: 0 | H79: 0 | I79: 0 | J79: 0 | K79: 0 | L79: 0 | M79: 0 | N79: 0 | O79: 0 | P79: 0 | Q79: 0 | R79: 0 | S79: 0 | T79: 0 | U79: 0 | V79: 0 | W79: 0 | X79: 0 | Z79: 0 | AA79: 0 | AB79: 0 | AC79: 0 | AD79: 0 | AE79: 0 | AF79: 0 | AG79: 0 | AI79: 0 | AJ79: 242 | AK79: 0 | AL79: 0 | AM79: 0 | AN79: 0 | AP79: 0
A80: 273527791 | B80: AKTA2KN102YL | C80: Нож для пиццы желтый | D80: 2041533038113 | E80: 129 | F80: 127 | G80: 16383 | H80: 1310 | I80: 100 | J80: 0.1 | K80: 1 | L80: 0 | M80: 1 | N80: 610.13 | O80: 366 | P80: 0 | Q80: 610.13 | R80: 366 | S80: 0.0027931402 | T80: 127 | U80: 180.6318 | V80: 0.29605462 | W80: 65.34 | X80: 129.36 | Z80: 25.62 | AA80: 82.178197 | AB80: 0.001133898 | AC80: 131 | AD80: 14 | AE80: 13 | AF80: 0.13468965 | AG80: 0.64707242 | AI80: 610.13 | AJ80: 127 | AK80: 180.6318 | AL80: 65.34 | AM80: 129.36 | AN80: 0 | AO80: 25.62 | AP80: 82.178197
A81: 327442631 | B81: AKTA2KN102GN | C81: Нож для пиццы зеленый | D81: 2042777181566 | E81: 85 | F81: 127 | G81: 10795 | H81: 999 | I81: 0 | J81: 0 | K81: 1 | L81: 0 | M81: 1 | N81: 629 | O81: 358 | P81: 0 | Q81: 629 | R81: 358 | S81: 0.002879526 | T81: 127 | U81: 189.73426 | V81: 0.3016443 | W81: 65.34 | X81: 95.06 | Z81: 25.06 | AA81: 126.80574 | AB81: 0.0017496706 | AC81: 96 | AD81: 11 | AE81: 0 | AF81: 0.20159895 | AG81: 0.99847038 | AI81: 629 | AJ81: 127 | AK81: 189.73426 | AL81: 65.34 | AM81: 95.06 | AN81: 0 | AO81: 25.06 | AP81: 126.80574
A82: 340948906 | B82: AKTA1KN101GR | C82: Консервный нож | D82: 2042988749289 | E82: 15 | F82: 254 | G82: 3810 | H82: 140 | I82: 0 | J82: 0.1 | K82: 1 | L82: 0 | M82: 1 | N82: 583 | O82: 361 | P82: 0 | Q82: 583 | R82: 361 | S82: 0.0026689406 | T82: 254 | U82: 168.9541 | V82: 0.2898012 | W82: 63.16 | X82: 14.7 | Z82: 25.27 | AA82: 56.915902 | AB82: 0.00078532789 | AC82: 14 | AD82: 15 | AE82: 25 | AF82: 0.097625903 | AG82: 0.22407835 | AI82: 583 | AJ82: 254 | AK82: 168.9541 | AL82: 63.16 | AM82: 14.7 | AN82: 0 | AO82: 25.27 | AP82: 56.915902
A83: 340802685 | B83: AKTA1PR101GR | C83: Чеснокодавка | D83: 2042987041841 | E83: 23 | F83: 235 | G83: 5405 | H83: 999 | I83: 0 | J83: 0 | K83: 0 | L83: 0 | M83: 0 | N83: 0 | O83: 0 | P83: 0 | Q83: 0 | R83: 0 | S83: 0 | T83: 0 | U83: 0 | V83: 0 | W83: 0 | X83: 22.54 | Z83: 0 | AA83: -22.54 | AB83: -0.00031100782 | AC83: 23 | AD83: 33 | AE83: 0 | AF83: 0 | AG83: 0 | AI83: 0 | AJ83: 235 | AK83: 0 | AL83: 0 | AM83: 22.54 | AN83: 0 | AP83: 0
A84: Итого | E84: 9515 | G84: 1272482 | H84: 195.89706 | K84: 342 | L84: 2 | M84: 340 | N84: 220040.42 | O84: 148000.04 | P84: 1601.69 | Q84: 218438.73 | R84: 146398.35 | S84: 1 | T84: 42313 | U84: 55811.67 | V84: 0.25550263 | W84: 25479.63 | X84: 12112.484 | Y84: 0 | Z84: 10247.885 | AA84: 72474.061 | AB84: 1 | AC84: 10523 | AF84: 0.3317821 | AG84: 1.7128084
Z85: в т.ч убытки | AA85: -2890.6598
Z86: Проверка | AA86: 72473.806
Z87: Платная приемка | AA87: 0
Z88: Прочие удержания | AA88: 0
Z89: Штрафы | AA89: 0

Sheet 4

Sheet 5

Sheet 6

Sheet 7

Sheet 8

Sheet 9

Sheet 10

Sheet 11

Sheet 12

Sheet 13

Sheet 14

Sheet 15

Sheet 17

Sheet 18

Sheet 19

Sheet 16

Sheet 20

Sheet 21

Sheet 22

Sheet 23

Sheet 24

Sheet 25

Sheet 26

Sheet 27

Sheet 28

Sheet 29

Sheet 30

Sheet 31

Sheet 32

Sheet 33

Sheet 34

Sheet 35

Sheet 36

Sheet 37

Sheet 38

Sheet 39

Sheet 40

Sheet 41

Sheet 42

Sheet 43

Sheet 44

Sheet 45

Sheet 46

Sheet 47

Sheet 48

Sheet 49

Sheet 50

Sheet 51

Sheet 52

Sheet 53

Sheet ОстатОборач
A1: Динамика Отстаки и Оборачиваемость
A3: Недели № п/п | D3: =ДинамПродаж!F5 -> 1 | E3: =ДинамПродаж!G5 -> 2 | F3: =ДинамПродаж!H5 -> 3 | G3: =ДинамПродаж!I5 -> 4 | H3: =ДинамПродаж!J5 -> 5 | I3: =ДинамПродаж!K5 -> 6 | J3: =ДинамПродаж!L5 -> 7 | K3: =ДинамПродаж!M5 -> 8 | ... BC3: =ДинамПродаж!BE5 -> 52 | BD3: 53
A4: Даты | D4: =ДинамПродаж!F4 -> 01.01-04.01 | E4: =ДинамПродаж!G4 -> 05.01-11.01 | F4: =ДинамПродаж!H4 -> 12.01-18.01 | G4: =ДинамПродаж!I4 -> 0 | H4: =ДинамПродаж!J4 -> 0 | I4: =ДинамПродаж!K4 -> 0 | J4: =ДинамПродаж!L4 -> 0 | K4: =ДинамПродаж!M4 -> 0 | ... BD4: =ДинамПродаж!BF4 -> 0
A5: SKU | B5: Артикул поставщика | C5: Наименование | M5: ОСТАТКИ | AH5: ОСТАТКИ
A6: ='Сводный за нед'!A3 -> 169112569 | B6: ='Сводный за нед'!B3 -> ACRF1BN101PN | C6: ='Сводный за нед'!C3 -> Бандаж для лица розовый | D6: {=_xlfn.XLOOKUP($A6,INDIRECT(D$3&"!$A:$A"),INDIRECT(D$3&"!$AC:$AC"),0,0)} -> 154 | E6: {=_xlfn.XLOOKUP($A6,INDIRECT(E$3&"!$A:$A"),INDIRECT(E$3&"!$AC:$AC"),0,0)} -> 154 | F6: {=_xlfn.XLOOKUP($A6,INDIRECT(F$3&"!$A:$A"),INDIRECT(F$3&"!$AC:$AC"),0,0)} -> 156 | G6: {=_xlfn.XLOOKUP($A6,INDIRECT(G$3&"!$A:$A"),INDIRECT(G$3&"!$AC:$AC"),0,0)} -> 0 | H6: {=_xlfn.XLOOKUP($A6,INDIRECT(H$3&"!$A:$A"),INDIRECT(H$3&"!$AC:$AC"),0,0)} -> 0 | I6: {=_xlfn.XLOOKUP($A6,INDIRECT(I$3&"!$A:$A"),INDIRECT(I$3&"!$AC:$AC"),0,0)} -> 0 | J6: {=_xlfn.XLOOKUP($A6,INDIRECT(J$3&"!$A:$A"),INDIRECT(J$3&"!$AC:$AC"),0,0)} -> 0 | K6: {=_xlfn.XLOOKUP($A6,INDIRECT(K$3&"!$A:$A"),INDIRECT(K$3&"!$AC:$AC"),0,0)} -> 0 | ... BD6: {=_xlfn.XLOOKUP($A6,INDIRECT(BD$3&"!$A:$A"),INDIRECT(BD$3&"!$AC:$AC"),0,0)} -> 0
A7: ='Сводный за нед'!A4 -> 169153168 | B7: ='Сводный за нед'!B4 -> ACRF1BN101BC | C7: ='Сводный за нед'!C4 -> Бандаж для лица черный | D7: {=_xlfn.XLOOKUP($A7,INDIRECT(D$3&"!$A:$A"),INDIRECT(D$3&"!$AC:$AC"),0,0)} -> 227 | E7: {=_xlfn.XLOOKUP($A7,INDIRECT(E$3&"!$A:$A"),INDIRECT(E$3&"!$AC:$AC"),0,0)} -> 227 | F7: {=_xlfn.XLOOKUP($A7,INDIRECT(F$3&"!$A:$A"),INDIRECT(F$3&"!$AC:$AC"),0,0)} -> 245 | G7: {=_xlfn.XLOOKUP($A7,INDIRECT(G$3&"!$A:$A"),INDIRECT(G$3&"!$AC:$AC"),0,0)} -> 0 | H7: {=_xlfn.XLOOKUP($A7,INDIRECT(H$3&"!$A:$A"),INDIRECT(H$3&"!$AC:$AC"),0,0)} -> 0 | I7: {=_xlfn.XLOOKUP($A7,INDIRECT(I$3&"!$A:$A"),INDIRECT(I$3&"!$AC:$AC"),0,0)} -> 0 | J7: {=_xlfn.XLOOKUP($A7,INDIRECT(J$3&"!$A:$A"),INDIRECT(J$3&"!$AC:$AC"),0,0)} -> 0 | K7: {=_xlfn.XLOOKUP($A7,INDIRECT(K$3&"!$A:$A"),INDIRECT(K$3&"!$AC:$AC"),0,0)} -> 0 | ... BD7: {=_xlfn.XLOOKUP($A7,INDIRECT(BD$3&"!$A:$A"),INDIRECT(BD$3&"!$AC:$AC"),0,0)} -> 0
A8: ='Сводный за нед'!A5 -> 169395410 | B8: ='Сводный за нед'!B5 -> ACRF1BN201GR | C8: ='Сводный за нед'!C5 -> Бандаж для лица серый | D8: {=_xlfn.XLOOKUP($A8,INDIRECT(D$3&"!$A:$A"),INDIRECT(D$3&"!$AC:$AC"),0,0)} -> 207 | E8: {=_xlfn.XLOOKUP($A8,INDIRECT(E$3&"!$A:$A"),INDIRECT(E$3&"!$AC:$AC"),0,0)} -> 207 | F8: {=_xlfn.XLOOKUP($A8,INDIRECT(F$3&"!$A:$A"),INDIRECT(F$3&"!$AC:$AC"),0,0)} -> 239 | G8: {=_xlfn.XLOOKUP($A8,INDIRECT(G$3&"!$A:$A"),INDIRECT(G$3&"!$AC:$AC"),0,0)} -> 0 | H8: {=_xlfn.XLOOKUP($A8,INDIRECT(H$3&"!$A:$A"),INDIRECT(H$3&"!$AC:$AC"),0,0)} -> 0 | I8: {=_xlfn.XLOOKUP($A8,INDIRECT(I$3&"!$A:$A"),INDIRECT(I$3&"!$AC:$AC"),0,0)} -> 0 | J8: {=_xlfn.XLOOKUP($A8,INDIRECT(J$3&"!$A:$A"),INDIRECT(J$3&"!$AC:$AC"),0,0)} -> 0 | K8: {=_xlfn.XLOOKUP($A8,INDIRECT(K$3&"!$A:$A"),INDIRECT(K$3&"!$AC:$AC"),0,0)} -> 0 | ... BD8: {=_xlfn.XLOOKUP($A8,INDIRECT(BD$3&"!$A:$A"),INDIRECT(BD$3&"!$AC:$AC"),0,0)} -> 0
A9: ='Сводный за нед'!A6 -> 172832355 | B9: ='Сводный за нед'!B6 -> AHMA7BW101BG | C9: ='Сводный за нед'!C6 -> Мешки 7 шт. | D9: {=_xlfn.XLOOKUP($A9,INDIRECT(D$3&"!$A:$A"),INDIRECT(D$3&"!$AC:$AC"),0,0)} -> 134 | E9: {=_xlfn.XLOOKUP($A9,INDIRECT(E$3&"!$A:$A"),INDIRECT(E$3&"!$AC:$AC"),0,0)} -> 134 | F9: {=_xlfn.XLOOKUP($A9,INDIRECT(F$3&"!$A:$A"),INDIRECT(F$3&"!$AC:$AC"),0,0)} -> 164 | G9: {=_xlfn.XLOOKUP($A9,INDIRECT(G$3&"!$A:$A"),INDIRECT(G$3&"!$AC:$AC"),0,0)} -> 0 | H9: {=_xlfn.XLOOKUP($A9,INDIRECT(H$3&"!$A:$A"),INDIRECT(H$3&"!$AC:$AC"),0,0)} -> 0 | I9: {=_xlfn.XLOOKUP($A9,INDIRECT(I$3&"!$A:$A"),INDIRECT(I$3&"!$AC:$AC"),0,0)} -> 0 | J9: {=_xlfn.XLOOKUP($A9,INDIRECT(J$3&"!$A:$A"),INDIRECT(J$3&"!$AC:$AC"),0,0)} -> 0 | K9: {=_xlfn.XLOOKUP($A9,INDIRECT(K$3&"!$A:$A"),INDIRECT(K$3&"!$AC:$AC"),0,0)} -> 0 | ... BD9: {=_xlfn.XLOOKUP($A9,INDIRECT(BD$3&"!$A:$A"),INDIRECT(BD$3&"!$AC:$AC"),0,0)} -> 0
A10: ='Сводный за нед'!A7 -> 176500218 | B10: ='Сводный за нед'!B7 -> AHMA1BW101BG | C10: ='Сводный за нед'!C7 -> Мешок для бюстгалтеров | D10: {=_xlfn.XLOOKUP($A10,INDIRECT(D$3&"!$A:$A"),INDIRECT(D$3&"!$AC:$AC"),0,0)} -> 338 | E10: {=_xlfn.XLOOKUP($A10,INDIRECT(E$3&"!$A:$A"),INDIRECT(E$3&"!$AC:$AC"),0,0)} -> 338 | F10: {=_xlfn.XLOOKUP($A10,INDIRECT(F$3&"!$A:$A"),INDIRECT(F$3&"!$AC:$AC"),0,0)} -> 395 | G10: {=_xlfn.XLOOKUP($A10,INDIRECT(G$3&"!$A:$A"),INDIRECT(G$3&"!$AC:$AC"),0,0)} -> 0 | H10: {=_xlfn.XLOOKUP($A10,INDIRECT(H$3&"!$A:$A"),INDIRECT(H$3&"!$AC:$AC"),0,0)} -> 0 | I10: {=_xlfn.XLOOKUP($A10,INDIRECT(I$3&"!$A:$A"),INDIRECT(I$3&"!$AC:$AC"),0,0)} -> 0 | J10: {=_xlfn.XLOOKUP($A10,INDIRECT(J$3&"!$A:$A"),INDIRECT(J$3&"!$AC:$AC"),0,0)} -> 0 | K10: {=_xlfn.XLOOKUP($A10,INDIRECT(K$3&"!$A:$A"),INDIRECT(K$3&"!$AC:$AC"),0,0)} -> 0 | ... BD10: {=_xlfn.XLOOKUP($A10,INDIRECT(BD$3&"!$A:$A"),INDIRECT(BD$3&"!$AC:$AC"),0,0)} -> 0
A11: ='Сводный за нед'!A8 -> 177404837 | B11: ='Сводный за нед'!B8 -> AHMA3BW101BG | C11: ='Сводный за нед'!C8 -> Мешки 3 шт. | D11: {=_xlfn.XLOOKUP($A11,INDIRECT(D$3&"!$A:$A"),INDIRECT(D$3&"!$AC:$AC"),0,0)} -> 124 | E11: {=_xlfn.XLOOKUP($A11,INDIRECT(E$3&"!$A:$A"),INDIRECT(E$3&"!$AC:$AC"),0,0)} -> 124 | F11: {=_xlfn.XLOOKUP($A11,INDIRECT(F$3&"!$A:$A"),INDIRECT(F$3&"!$AC:$AC"),0,0)} -> 167 | G11: {=_xlfn.XLOOKUP($A11,INDIRECT(G$3&"!$A:$A"),INDIRECT(G$3&"!$AC:$AC"),0,0)} -> 0 | H11: {=_xlfn.XLOOKUP($A11,INDIRECT(H$3&"!$A:$A"),INDIRECT(H$3&"!$AC:$AC"),0,0)} -> 0 | I11: {=_xlfn.XLOOKUP($A11,INDIRECT(I$3&"!$A:$A"),INDIRECT(I$3&"!$AC:$AC"),0,0)} -> 0 | J11: {=_xlfn.XLOOKUP($A11,INDIRECT(J$3&"!$A:$A"),INDIRECT(J$3&"!$AC:$AC"),0,0)} -> 0 | K11: {=_xlfn.XLOOKUP($A11,INDIRECT(K$3&"!$A:$A"),INDIRECT(K$3&"!$AC:$AC"),0,0)} -> 0 | ... BD11: {=_xlfn.XLOOKUP($A11,INDIRECT(BD$3&"!$A:$A"),INDIRECT(BD$3&"!$AC:$AC"),0,0)} -> 0
A12: ='Сводный за нед'!A9 -> 177405495 | B12: ='Сводный за нед'!B9 -> AHMA3BW102BG | C12: ='Сводный за нед'!C9 -> Мешки/деликат 3 шт. | D12: {=_xlfn.XLOOKUP($A12,INDIRECT(D$3&"!$A:$A"),INDIRECT(D$3&"!$AC:$AC"),0,0)} -> 208 | E12: {=_xlfn.XLOOKUP($A12,INDIRECT(E$3&"!$A:$A"),INDIRECT(E$3&"!$AC:$AC"),0,0)} -> 208 | F12: {=_xlfn.XLOOKUP($A12,INDIRECT(F$3&"!$A:$A"),INDIRECT(F$3&"!$AC:$AC"),0,0)} -> 250 | G12: {=_xlfn.XLOOKUP($A12,INDIRECT(G$3&"!$A:$A"),INDIRECT(G$3&"!$AC:$AC"),0,0)} -> 0 | H12: {=_xlfn.XLOOKUP($A12,INDIRECT(H$3&"!$A:$A"),INDIRECT(H$3&"!$AC:$AC"),0,0)} -> 0 | I12: {=_xlfn.XLOOKUP($A12,INDIRECT(I$3&"!$A:$A"),INDIRECT(I$3&"!$AC:$AC"),0,0)} -> 0 | J12: {=_xlfn.XLOOKUP($A12,INDIRECT(J$3&"!$A:$A"),INDIRECT(J$3&"!$AC:$AC"),0,0)} -> 0 | K12: {=_xlfn.XLOOKUP($A12,INDIRECT(K$3&"!$A:$A"),INDIRECT(K$3&"!$AC:$AC"),0,0)} -> 0 | ... BD12: {=_xlfn.XLOOKUP($A12,INDIRECT(BD$3&"!$A:$A"),INDIRECT(BD$3&"!$AC:$AC"),0,0)} -> 0
A13: ='Сводный за нед'!A10 -> 176721350 | B13: ='Сводный за нед'!B10 -> AHMA3BW201WH | C13: ='Сводный за нед'!C10 -> Мешки/шнурок мелк 3 шт. | D13: {=_xlfn.XLOOKUP($A13,INDIRECT(D$3&"!$A:$A"),INDIRECT(D$3&"!$AC:$AC"),0,0)} -> 259 | E13: {=_xlfn.XLOOKUP($A13,INDIRECT(E$3&"!$A:$A"),INDIRECT(E$3&"!$AC:$AC"),0,0)} -> 259 | F13: {=_xlfn.XLOOKUP($A13,INDIRECT(F$3&"!$A:$A"),INDIRECT(F$3&"!$AC:$AC"),0,0)} -> 306 | G13: {=_xlfn.XLOOKUP($A13,INDIRECT(G$3&"!$A:$A"),INDIRECT(G$3&"!$AC:$AC"),0,0)} -> 0 | H13: {=_xlfn.XLOOKUP($A13,INDIRECT(H$3&"!$A:$A"),INDIRECT(H$3&"!$AC:$AC"),0,0)} -> 0 | I13: {=_xlfn.XLOOKUP($A13,INDIRECT(I$3&"!$A:$A"),INDIRECT(I$3&"!$AC:$AC"),0,0)} -> 0 | J13: {=_xlfn.XLOOKUP($A13,INDIRECT(J$3&"!$A:$A"),INDIRECT(J$3&"!$AC:$AC"),0,0)} -> 0 | K13: {=_xlfn.XLOOKUP($A13,INDIRECT(K$3&"!$A:$A"),INDIRECT(K$3&"!$AC:$AC"),0,0)} -> 0 | ... BD13: {=_xlfn.XLOOKUP($A13,INDIRECT(BD$3&"!$A:$A"),INDIRECT(BD$3&"!$AC:$AC"),0,0)} -> 0
A14: ='Сводный за нед'!A11 -> 176723275 | B14: ='Сводный за нед'!B11 -> AHMA3BW202WH | C14: ='Сводный за нед'!C11 -> Мешки/шнурок крупн 3 шт. | D14: {=_xlfn.XLOOKUP($A14,INDIRECT(D$3&"!$A:$A"),INDIRECT(D$3&"!$AC:$AC"),0,0)} -> 125 | E14: {=_xlfn.XLOOKUP($A14,INDIRECT(E$3&"!$A:$A"),INDIRECT(E$3&"!$AC:$AC"),0,0)} -> 125 | F14: {=_xlfn.XLOOKUP($A14,INDIRECT(F$3&"!$A:$A"),INDIRECT(F$3&"!$AC:$AC"),0,0)} -> 155 | G14: {=_xlfn.XLOOKUP($A14,INDIRECT(G$3&"!$A:$A"),INDIRECT(G$3&"!$AC:$AC"),0,0)} -> 0 | H14: {=_xlfn.XLOOKUP($A14,INDIRECT(H$3&"!$A:$A"),INDIRECT(H$3&"!$AC:$AC"),0,0)} -> 0 | I14: {=_xlfn.XLOOKUP($A14,INDIRECT(I$3&"!$A:$A"),INDIRECT(I$3&"!$AC:$AC"),0,0)} -> 0 | J14: {=_xlfn.XLOOKUP($A14,INDIRECT(J$3&"!$A:$A"),INDIRECT(J$3&"!$AC:$AC"),0,0)} -> 0 | K14: {=_xlfn.XLOOKUP($A14,INDIRECT(K$3&"!$A:$A"),INDIRECT(K$3&"!$AC:$AC"),0,0)} -> 0 | ... BD14: {=_xlfn.XLOOKUP($A14,INDIRECT(BD$3&"!$A:$A"),INDIRECT(BD$3&"!$AC:$AC"),0,0)} -> 0
A15: ='Сводный за нед'!A12 -> 204615141 | B15: ='Сводный за нед'!B12 -> AHMA2BW201WH | C15: ='Сводный за нед'!C12 -> Мешки 2 шт. серый | D15: {=_xlfn.XLOOKUP($A15,INDIRECT(D$3&"!$A:$A"),INDIRECT(D$3&"!$AC:$AC"),0,0)} -> 197 | E15: {=_xlfn.XLOOKUP($A15,INDIRECT(E$3&"!$A:$A"),INDIRECT(E$3&"!$AC:$AC"),0,0)} -> 197 | F15: {=_xlfn.XLOOKUP($A15,INDIRECT(F$3&"!$A:$A"),INDIRECT(F$3&"!$AC:$AC"),0,0)} -> 256 | G15: {=_xlfn.XLOOKUP($A15,INDIRECT(G$3&"!$A:$A"),INDIRECT(G$3&"!$AC:$AC"),0,0)} -> 0 | H15: {=_xlfn.XLOOKUP($A15,INDIRECT(H$3&"!$A:$A"),INDIRECT(H$3&"!$AC:$AC"),0,0)} -> 0 | I15: {=_xlfn.XLOOKUP($A15,INDIRECT(I$3&"!$A:$A"),INDIRECT(I$3&"!$AC:$AC"),0,0)} -> 0 | J15: {=_xlfn.XLOOKUP($A15,INDIRECT(J$3&"!$A:$A"),INDIRECT(J$3&"!$AC:$AC"),0,0)} -> 0 | K15: {=_xlfn.XLOOKUP($A15,INDIRECT(K$3&"!$A:$A"),INDIRECT(K$3&"!$AC:$AC"),0,0)} -> 0 | ... BD15: {=_xlfn.XLOOKUP($A15,INDIRECT(BD$3&"!$A:$A"),INDIRECT(BD$3&"!$AC:$AC"),0,0)} -> 0
A16: ='Сводный за нед'!A13 -> 236074677 | B16: ='Сводный за нед'!B13 -> AHMA2BW202WH | C16: ='Сводный за нед'!C13 -> Мешки 2 шт. розовый | D16: {=_xlfn.XLOOKUP($A16,INDIRECT(D$3&"!$A:$A"),INDIRECT(D$3&"!$AC:$AC"),0,0)} -> 50 | E16: {=_xlfn.XLOOKUP($A16,INDIRECT(E$3&"!$A:$A"),INDIRECT(E$3&"!$AC:$AC"),0,0)} -> 50 | F16: {=_xlfn.XLOOKUP($A16,INDIRECT(F$3&"!$A:$A"),INDIRECT(F$3&"!$AC:$AC"),0,0)} -> 49 | G16: {=_xlfn.XLOOKUP($A16,INDIRECT(G$3&"!$A:$A"),INDIRECT(G$3&"!$AC:$AC"),0,0)} -> 0 | H16: {=_xlfn.XLOOKUP($A16,INDIRECT(H$3&"!$A:$A"),INDIRECT(H$3&"!$AC:$AC"),0,0)} -> 0 | I16: {=_xlfn.XLOOKUP($A16,INDIRECT(I$3&"!$A:$A"),INDIRECT(I$3&"!$AC:$AC"),0,0)} -> 0 | J16: {=_xlfn.XLOOKUP($A16,INDIRECT(J$3&"!$A:$A"),INDIRECT(J$3&"!$AC:$AC"),0,0)} -> 0 | K16: {=_xlfn.XLOOKUP($A16,INDIRECT(K$3&"!$A:$A"),INDIRECT(K$3&"!$AC:$AC"),0,0)} -> 0 | ... BD16: {=_xlfn.XLOOKUP($A16,INDIRECT(BD$3&"!$A:$A"),INDIRECT(BD$3&"!$AC:$AC"),0,0)} -> 0
A17: ='Сводный за нед'!A14 -> 236929187 | B17: ='Сводный за нед'!B14 -> AHMA1BW112WH | C17: ='Сводный за нед'!C14 -> Мешок 60*80 крупн | D17: {=_xlfn.XLOOKUP($A17,INDIRECT(D$3&"!$A:$A"),INDIRECT(D$3&"!$AC:$AC"),0,0)} -> 136 | E17: {=_xlfn.XLOOKUP($A17,INDIRECT(E$3&"!$A:$A"),INDIRECT(E$3&"!$AC:$AC"),0,0)} -> 136 | F17: {=_xlfn.XLOOKUP($A17,INDIRECT(F$3&"!$A:$A"),INDIRECT(F$3&"!$AC:$AC"),0,0)} -> 168 | G17: {=_xlfn.XLOOKUP($A17,INDIRECT(G$3&"!$A:$A"),INDIRECT(G$3&"!$AC:$AC"),0,0)} -> 0 | H17: {=_xlfn.XLOOKUP($A17,INDIRECT(H$3&"!$A:$A"),INDIRECT(H$3&"!$AC:$AC"),0,0)} -> 0 | I17: {=_xlfn.XLOOKUP($A17,INDIRECT(I$3&"!$A:$A"),INDIRECT(I$3&"!$AC:$AC"),0,0)} -> 0 | J17: {=_xlfn.XLOOKUP($A17,INDIRECT(J$3&"!$A:$A"),INDIRECT(J$3&"!$AC:$AC"),0,0)} -> 0 | K17: {=_xlfn.XLOOKUP($A17,INDIRECT(K$3&"!$A:$A"),INDIRECT(K$3&"!$AC:$AC"),0,0)} -> 0 | ... BD17: {=_xlfn.XLOOKUP($A17,INDIRECT(BD$3&"!$A:$A"),INDIRECT(BD$3&"!$AC:$AC"),0,0)} -> 0
... A85: ='Сводный за нед'!A82 -> 340802685 | B85: ='Сводный за нед'!B82 -> AKTA1PR101GR | C85: ='Сводный за нед'!C82 -> Чеснокодавка | D85: {=_xlfn.XLOOKUP($A85,INDIRECT(D$3&"!$A:$A"),INDIRECT(D$3&"!$AC:$AC"),0,0)} -> 23 | E85: {=_xlfn.XLOOKUP($A85,INDIRECT(E$3&"!$A:$A"),INDIRECT(E$3&"!$AC:$AC"),0,0)} -> 23 | F85: {=_xlfn.XLOOKUP($A85,INDIRECT(F$3&"!$A:$A"),INDIRECT(F$3&"!$AC:$AC"),0,0)} -> 23 | G85: {=_xlfn.XLOOKUP($A85,INDIRECT(G$3&"!$A:$A"),INDIRECT(G$3&"!$AC:$AC"),0,0)} -> 0 | H85: {=_xlfn.XLOOKUP($A85,INDIRECT(H$3&"!$A:$A"),INDIRECT(H$3&"!$AC:$AC"),0,0)} -> 0 | I85: {=_xlfn.XLOOKUP($A85,INDIRECT(I$3&"!$A:$A"),INDIRECT(I$3&"!$AC:$AC"),0,0)} -> 0 | J85: {=_xlfn.XLOOKUP($A85,INDIRECT(J$3&"!$A:$A"),INDIRECT(J$3&"!$AC:$AC"),0,0)} -> 0 | K85: {=_xlfn.XLOOKUP($A85,INDIRECT(K$3&"!$A:$A"),INDIRECT(K$3&"!$AC:$AC"),0,0)} -> 0 | ... BD85: {=_xlfn.XLOOKUP($A85,INDIRECT(BD$3&"!$A:$A"),INDIRECT(BD$3&"!$AC:$AC"),0,0)} -> 0
C86: ИТОГО | D86: =SUM(D7:D85) -> 9482 | E86: =SUM(E7:E85) -> 9482 | F86: =SUM(F7:F85) -> 10482 | G86: =SUM(G7:G85) -> 0 | H86: =SUM(H7:H85) -> 0 | I86: =SUM(I7:I85) -> 0 | J86: =SUM(J7:J85) -> 0 | K86: =SUM(K7:K85) -> 0 | ... BD86: =SUM(BD7:BD85) -> 0
C87: в т.ч. с оборачиваемостью >120 | D87: =SUMIFS(D6:D85,D93:D172,">120") -> 8478 | E87: =SUMIFS(E6:E85,E93:E172,">120") -> 8242 | F87: =SUMIFS(F6:F85,F93:F172,">120") -> 8887 | G87: =SUMIFS(G6:G85,G93:G172,">120") -> 0 | H87: =SUMIFS(H6:H85,H93:H172,">120") -> 0 | I87: =SUMIFS(I6:I85,I93:I172,">120") -> 0 | J87: =SUMIFS(J6:J85,J93:J172,">120") -> 0 | K87: =SUMIFS(K6:K85,K93:K172,">120") -> 0 | ... BD87: =SUMIFS(BD6:BD85,BD93:BD172,">120") -> 0
D88: =D87/D86 -> 0.89411517 | E88: =E87/E86 -> 0.8692259 | F88: =F87/F86 -> 0.84783438 | G88: =G87/G86 -> #DIV/0! | H88: =H87/H86 -> #DIV/0! | I88: =I87/I86 -> #DIV/0! | J88: =J87/J86 -> #DIV/0! | K88: =K87/K86 -> #DIV/0! | ... BD88: =BD87/BD86 -> #DIV/0!
A90: =D3=ДинамПродаж!F5 -> TRUE | D90: =D3 -> 1 | E90: =E3 -> 2 | F90: =F3 -> 3 | G90: =G3 -> 4 | H90: =H3 -> 5 | I90: =I3 -> 6 | J90: =J3 -> 7 | K90: =K3 -> 8 | ... BC90: =BC3 -> 52 | BD90: 53
A91: Даты | D91: =D4 -> 01.01-04.01 | E91: =E4 -> 05.01-11.01 | F91: =F4 -> 12.01-18.01 | G91: =G4 -> 0 | H91: =H4 -> 0 | I91: =I4 -> 0 | J91: =J4 -> 0 | K91: =K4 -> 0 | ... BD91: =BD4 -> 0
A92: SKU | B92: Артикул поставщика | C92: Наименование | D92: ОБОРАЧИВАЕМОСТЬ (0-60-120 дн) | M92: ОБОРАЧИВАЕМОСТЬ (0-60-120 дн) | W92: ОБОРАЧИВАЕМОСТЬ (0-60-120 дн) | AG92: ОБОРАЧИВАЕМОСТЬ (0-60-120 дн) | AQ92: ОБОРАЧИВАЕМОСТЬ (0-60-120 дн)
A93: =A6 -> 169112569 | B93: =B6 -> ACRF1BN101PN | C93: =C6 -> Бандаж для лица розовый | D93: {=_xlfn.XLOOKUP($A93,INDIRECT(D$3&"!$A:$A"),INDIRECT(D$3&"!$H:$H"),0,0)} -> 513.33333 | E93: {=_xlfn.XLOOKUP($A93,INDIRECT(E$3&"!$A:$A"),INDIRECT(E$3&"!$H:$H"),0,0)} -> 385 | F93: {=_xlfn.XLOOKUP($A93,INDIRECT(F$3&"!$A:$A"),INDIRECT(F$3&"!$H:$H"),0,0)} -> 1560 | G93: {=_xlfn.XLOOKUP($A93,INDIRECT(G$3&"!$A:$A"),INDIRECT(G$3&"!$H:$H"),0,0)} -> 0 | H93: {=_xlfn.XLOOKUP($A93,INDIRECT(H$3&"!$A:$A"),INDIRECT(H$3&"!$H:$H"),0,0)} -> 0 | I93: {=_xlfn.XLOOKUP($A93,INDIRECT(I$3&"!$A:$A"),INDIRECT(I$3&"!$H:$H"),0,0)} -> 0 | J93: {=_xlfn.XLOOKUP($A93,INDIRECT(J$3&"!$A:$A"),INDIRECT(J$3&"!$H:$H"),0,0)} -> 0 | K93: {=_xlfn.XLOOKUP($A93,INDIRECT(K$3&"!$A:$A"),INDIRECT(K$3&"!$H:$H"),0,0)} -> 0 | ... BD93: {=_xlfn.XLOOKUP($A93,INDIRECT(BD$3&"!$A:$A"),INDIRECT(BD$3&"!$H:$H"),0,0)} -> 0
A94: =A7 -> 169153168 | B94: =B7 -> ACRF1BN101BC | C94: =C7 -> Бандаж для лица черный | D94: {=_xlfn.XLOOKUP($A94,INDIRECT(D$3&"!$A:$A"),INDIRECT(D$3&"!$H:$H"),0,0)} -> 999 | E94: {=_xlfn.XLOOKUP($A94,INDIRECT(E$3&"!$A:$A"),INDIRECT(E$3&"!$H:$H"),0,0)} -> 2270 | F94: {=_xlfn.XLOOKUP($A94,INDIRECT(F$3&"!$A:$A"),INDIRECT(F$3&"!$H:$H"),0,0)} -> 222.72727 | G94: {=_xlfn.XLOOKUP($A94,INDIRECT(G$3&"!$A:$A"),INDIRECT(G$3&"!$H:$H"),0,0)} -> 0 | H94: {=_xlfn.XLOOKUP($A94,INDIRECT(H$3&"!$A:$A"),INDIRECT(H$3&"!$H:$H"),0,0)} -> 0 | I94: {=_xlfn.XLOOKUP($A94,INDIRECT(I$3&"!$A:$A"),INDIRECT(I$3&"!$H:$H"),0,0)} -> 0 | J94: {=_xlfn.XLOOKUP($A94,INDIRECT(J$3&"!$A:$A"),INDIRECT(J$3&"!$H:$H"),0,0)} -> 0 | K94: {=_xlfn.XLOOKUP($A94,INDIRECT(K$3&"!$A:$A"),INDIRECT(K$3&"!$H:$H"),0,0)} -> 0 | ... BD94: {=_xlfn.XLOOKUP($A94,INDIRECT(BD$3&"!$A:$A"),INDIRECT(BD$3&"!$H:$H"),0,0)} -> 0
A95: =A8 -> 169395410 | B95: =B8 -> ACRF1BN201GR | C95: =C8 -> Бандаж для лица серый | D95: {=_xlfn.XLOOKUP($A95,INDIRECT(D$3&"!$A:$A"),INDIRECT(D$3&"!$H:$H"),0,0)} -> 258.75 | E95: {=_xlfn.XLOOKUP($A95,INDIRECT(E$3&"!$A:$A"),INDIRECT(E$3&"!$H:$H"),0,0)} -> 295.71429 | F95: {=_xlfn.XLOOKUP($A95,INDIRECT(F$3&"!$A:$A"),INDIRECT(F$3&"!$H:$H"),0,0)} -> 341.42857 | G95: {=_xlfn.XLOOKUP($A95,INDIRECT(G$3&"!$A:$A"),INDIRECT(G$3&"!$H:$H"),0,0)} -> 0 | H95: {=_xlfn.XLOOKUP($A95,INDIRECT(H$3&"!$A:$A"),INDIRECT(H$3&"!$H:$H"),0,0)} -> 0 | I95: {=_xlfn.XLOOKUP($A95,INDIRECT(I$3&"!$A:$A"),INDIRECT(I$3&"!$H:$H"),0,0)} -> 0 | J95: {=_xlfn.XLOOKUP($A95,INDIRECT(J$3&"!$A:$A"),INDIRECT(J$3&"!$H:$H"),0,0)} -> 0 | K95: {=_xlfn.XLOOKUP($A95,INDIRECT(K$3&"!$A:$A"),INDIRECT(K$3&"!$H:$H"),0,0)} -> 0 | ... BD95: {=_xlfn.XLOOKUP($A95,INDIRECT(BD$3&"!$A:$A"),INDIRECT(BD$3&"!$H:$H"),0,0)} -> 0
A96: =A9 -> 172832355 | B96: =B9 -> AHMA7BW101BG | C96: =C9 -> Мешки 7 шт. | D96: {=_xlfn.XLOOKUP($A96,INDIRECT(D$3&"!$A:$A"),INDIRECT(D$3&"!$H:$H"),0,0)} -> 999 | E96: {=_xlfn.XLOOKUP($A96,INDIRECT(E$3&"!$A:$A"),INDIRECT(E$3&"!$H:$H"),0,0)} -> 446.66667 | F96: {=_xlfn.XLOOKUP($A96,INDIRECT(F$3&"!$A:$A"),INDIRECT(F$3&"!$H:$H"),0,0)} -> 1640 | G96: {=_xlfn.XLOOKUP($A96,INDIRECT(G$3&"!$A:$A"),INDIRECT(G$3&"!$H:$H"),0,0)} -> 0 | H96: {=_xlfn.XLOOKUP($A96,INDIRECT(H$3&"!$A:$A"),INDIRECT(H$3&"!$H:$H"),0,0)} -> 0 | I96: {=_xlfn.XLOOKUP($A96,INDIRECT(I$3&"!$A:$A"),INDIRECT(I$3&"!$H:$H"),0,0)} -> 0 | J96: {=_xlfn.XLOOKUP($A96,INDIRECT(J$3&"!$A:$A"),INDIRECT(J$3&"!$H:$H"),0,0)} -> 0 | K96: {=_xlfn.XLOOKUP($A96,INDIRECT(K$3&"!$A:$A"),INDIRECT(K$3&"!$H:$H"),0,0)} -> 0 | ... BD96: {=_xlfn.XLOOKUP($A96,INDIRECT(BD$3&"!$A:$A"),INDIRECT(BD$3&"!$H:$H"),0,0)} -> 0
A97: =A10 -> 176500218 | B97: =B10 -> AHMA1BW101BG | C97: =C10 -> Мешок для бюстгалтеров | D97: {=_xlfn.XLOOKUP($A97,INDIRECT(D$3&"!$A:$A"),INDIRECT(D$3&"!$H:$H"),0,0)} -> 676 | E97: {=_xlfn.XLOOKUP($A97,INDIRECT(E$3&"!$A:$A"),INDIRECT(E$3&"!$H:$H"),0,0)} -> 375.55556 | F97: {=_xlfn.XLOOKUP($A97,INDIRECT(F$3&"!$A:$A"),INDIRECT(F$3&"!$H:$H"),0,0)} -> 658.33333 | G97: {=_xlfn.XLOOKUP($A97,INDIRECT(G$3&"!$A:$A"),INDIRECT(G$3&"!$H:$H"),0,0)} -> 0 | H97: {=_xlfn.XLOOKUP($A97,INDIRECT(H$3&"!$A:$A"),INDIRECT(H$3&"!$H:$H"),0,0)} -> 0 | I97: {=_xlfn.XLOOKUP($A97,INDIRECT(I$3&"!$A:$A"),INDIRECT(I$3&"!$H:$H"),0,0)} -> 0 | J97: {=_xlfn.XLOOKUP($A97,INDIRECT(J$3&"!$A:$A"),INDIRECT(J$3&"!$H:$H"),0,0)} -> 0 | K97: {=_xlfn.XLOOKUP($A97,INDIRECT(K$3&"!$A:$A"),INDIRECT(K$3&"!$H:$H"),0,0)} -> 0 | ... BD97: {=_xlfn.XLOOKUP($A97,INDIRECT(BD$3&"!$A:$A"),INDIRECT(BD$3&"!$H:$H"),0,0)} -> 0
A98: =A11 -> 177404837 | B98: =B11 -> AHMA3BW101BG | C98: =C11 -> Мешки 3 шт. | D98: {=_xlfn.XLOOKUP($A98,INDIRECT(D$3&"!$A:$A"),INDIRECT(D$3&"!$H:$H"),0,0)} -> 413.33333 | E98: {=_xlfn.XLOOKUP($A98,INDIRECT(E$3&"!$A:$A"),INDIRECT(E$3&"!$H:$H"),0,0)} -> 999 | F98: {=_xlfn.XLOOKUP($A98,INDIRECT(F$3&"!$A:$A"),INDIRECT(F$3&"!$H:$H"),0,0)} -> 556.66667 | G98: {=_xlfn.XLOOKUP($A98,INDIRECT(G$3&"!$A:$A"),INDIRECT(G$3&"!$H:$H"),0,0)} -> 0 | H98: {=_xlfn.XLOOKUP($A98,INDIRECT(H$3&"!$A:$A"),INDIRECT(H$3&"!$H:$H"),0,0)} -> 0 | I98: {=_xlfn.XLOOKUP($A98,INDIRECT(I$3&"!$A:$A"),INDIRECT(I$3&"!$H:$H"),0,0)} -> 0 | J98: {=_xlfn.XLOOKUP($A98,INDIRECT(J$3&"!$A:$A"),INDIRECT(J$3&"!$H:$H"),0,0)} -> 0 | K98: {=_xlfn.XLOOKUP($A98,INDIRECT(K$3&"!$A:$A"),INDIRECT(K$3&"!$H:$H"),0,0)} -> 0 | ... BD98: {=_xlfn.XLOOKUP($A98,INDIRECT(BD$3&"!$A:$A"),INDIRECT(BD$3&"!$H:$H"),0,0)} -> 0
A99: =A12 -> 177405495 | B99: =B12 -> AHMA3BW102BG | C99: =C12 -> Мешки/деликат 3 шт. | D99: {=_xlfn.XLOOKUP($A99,INDIRECT(D$3&"!$A:$A"),INDIRECT(D$3&"!$H:$H"),0,0)} -> 416 | E99: {=_xlfn.XLOOKUP($A99,INDIRECT(E$3&"!$A:$A"),INDIRECT(E$3&"!$H:$H"),0,0)} -> 2080 | F99: {=_xlfn.XLOOKUP($A99,INDIRECT(F$3&"!$A:$A"),INDIRECT(F$3&"!$H:$H"),0,0)} -> 625 | G99: {=_xlfn.XLOOKUP($A99,INDIRECT(G$3&"!$A:$A"),INDIRECT(G$3&"!$H:$H"),0,0)} -> 0 | H99: {=_xlfn.XLOOKUP($A99,INDIRECT(H$3&"!$A:$A"),INDIRECT(H$3&"!$H:$H"),0,0)} -> 0 | I99: {=_xlfn.XLOOKUP($A99,INDIRECT(I$3&"!$A:$A"),INDIRECT(I$3&"!$H:$H"),0,0)} -> 0 | J99: {=_xlfn.XLOOKUP($A99,INDIRECT(J$3&"!$A:$A"),INDIRECT(J$3&"!$H:$H"),0,0)} -> 0 | K99: {=_xlfn.XLOOKUP($A99,INDIRECT(K$3&"!$A:$A"),INDIRECT(K$3&"!$H:$H"),0,0)} -> 0 | ... BD99: {=_xlfn.XLOOKUP($A99,INDIRECT(BD$3&"!$A:$A"),INDIRECT(BD$3&"!$H:$H"),0,0)} -> 0
A100: =A13 -> 176721350 | B100: =B13 -> AHMA3BW201WH | C100: =C13 -> Мешки/шнурок мелк 3 шт. | D100: {=_xlfn.XLOOKUP($A100,INDIRECT(D$3&"!$A:$A"),INDIRECT(D$3&"!$H:$H"),0,0)} -> 259 | E100: {=_xlfn.XLOOKUP($A100,INDIRECT(E$3&"!$A:$A"),INDIRECT(E$3&"!$H:$H"),0,0)} -> 161.875 | F100: {=_xlfn.XLOOKUP($A100,INDIRECT(F$3&"!$A:$A"),INDIRECT(F$3&"!$H:$H"),0,0)} -> 437.14286 | G100: {=_xlfn.XLOOKUP($A100,INDIRECT(G$3&"!$A:$A"),INDIRECT(G$3&"!$H:$H"),0,0)} -> 0 | H100: {=_xlfn.XLOOKUP($A100,INDIRECT(H$3&"!$A:$A"),INDIRECT(H$3&"!$H:$H"),0,0)} -> 0 | I100: {=_xlfn.XLOOKUP($A100,INDIRECT(I$3&"!$A:$A"),INDIRECT(I$3&"!$H:$H"),0,0)} -> 0 | J100: {=_xlfn.XLOOKUP($A100,INDIRECT(J$3&"!$A:$A"),INDIRECT(J$3&"!$H:$H"),0,0)} -> 0 | K100: {=_xlfn.XLOOKUP($A100,INDIRECT(K$3&"!$A:$A"),INDIRECT(K$3&"!$H:$H"),0,0)} -> 0 | ... BD100: {=_xlfn.XLOOKUP($A100,INDIRECT(BD$3&"!$A:$A"),INDIRECT(BD$3&"!$H:$H"),0,0)} -> 0
A101: =A14 -> 176723275 | B101: =B14 -> AHMA3BW202WH | C101: =C14 -> Мешки/шнурок крупн 3 шт. | D101: {=_xlfn.XLOOKUP($A101,INDIRECT(D$3&"!$A:$A"),INDIRECT(D$3&"!$H:$H"),0,0)} -> 41.666667 | E101: {=_xlfn.XLOOKUP($A101,INDIRECT(E$3&"!$A:$A"),INDIRECT(E$3&"!$H:$H"),0,0)} -> 41.666667 | F101: {=_xlfn.XLOOKUP($A101,INDIRECT(F$3&"!$A:$A"),INDIRECT(F$3&"!$H:$H"),0,0)} -> 59.615385 | G101: {=_xlfn.XLOOKUP($A101,INDIRECT(G$3&"!$A:$A"),INDIRECT(G$3&"!$H:$H"),0,0)} -> 0 | H101: {=_xlfn.XLOOKUP($A101,INDIRECT(H$3&"!$A:$A"),INDIRECT(H$3&"!$H:$H"),0,0)} -> 0 | I101: {=_xlfn.XLOOKUP($A101,INDIRECT(I$3&"!$A:$A"),INDIRECT(I$3&"!$H:$H"),0,0)} -> 0 | J101: {=_xlfn.XLOOKUP($A101,INDIRECT(J$3&"!$A:$A"),INDIRECT(J$3&"!$H:$H"),0,0)} -> 0 | K101: {=_xlfn.XLOOKUP($A101,INDIRECT(K$3&"!$A:$A"),INDIRECT(K$3&"!$H:$H"),0,0)} -> 0 | ... BD101: {=_xlfn.XLOOKUP($A101,INDIRECT(BD$3&"!$A:$A"),INDIRECT(BD$3&"!$H:$H"),0,0)} -> 0
A102: =A15 -> 204615141 | B102: =B15 -> AHMA2BW201WH | C102: =C15 -> Мешки 2 шт. серый | D102: {=_xlfn.XLOOKUP($A102,INDIRECT(D$3&"!$A:$A"),INDIRECT(D$3&"!$H:$H"),0,0)} -> 656.66667 | E102: {=_xlfn.XLOOKUP($A102,INDIRECT(E$3&"!$A:$A"),INDIRECT(E$3&"!$H:$H"),0,0)} -> 492.5 | F102: {=_xlfn.XLOOKUP($A102,INDIRECT(F$3&"!$A:$A"),INDIRECT(F$3&"!$H:$H"),0,0)} -> 853.33333 | G102: {=_xlfn.XLOOKUP($A102,INDIRECT(G$3&"!$A:$A"),INDIRECT(G$3&"!$H:$H"),0,0)} -> 0 | H102: {=_xlfn.XLOOKUP($A102,INDIRECT(H$3&"!$A:$A"),INDIRECT(H$3&"!$H:$H"),0,0)} -> 0 | I102: {=_xlfn.XLOOKUP($A102,INDIRECT(I$3&"!$A:$A"),INDIRECT(I$3&"!$H:$H"),0,0)} -> 0 | J102: {=_xlfn.XLOOKUP($A102,INDIRECT(J$3&"!$A:$A"),INDIRECT(J$3&"!$H:$H"),0,0)} -> 0 | K102: {=_xlfn.XLOOKUP($A102,INDIRECT(K$3&"!$A:$A"),INDIRECT(K$3&"!$H:$H"),0,0)} -> 0 | ... BD102: {=_xlfn.XLOOKUP($A102,INDIRECT(BD$3&"!$A:$A"),INDIRECT(BD$3&"!$H:$H"),0,0)} -> 0
A103: =A16 -> 236074677 | B103: =B16 -> AHMA2BW202WH | C103: =C16 -> Мешки 2 шт. розовый | D103: {=_xlfn.XLOOKUP($A103,INDIRECT(D$3&"!$A:$A"),INDIRECT(D$3&"!$H:$H"),0,0)} -> 999 | E103: {=_xlfn.XLOOKUP($A103,INDIRECT(E$3&"!$A:$A"),INDIRECT(E$3&"!$H:$H"),0,0)} -> 125 | F103: {=_xlfn.XLOOKUP($A103,INDIRECT(F$3&"!$A:$A"),INDIRECT(F$3&"!$H:$H"),0,0)} -> 163.33333 | G103: {=_xlfn.XLOOKUP($A103,INDIRECT(G$3&"!$A:$A"),INDIRECT(G$3&"!$H:$H"),0,0)} -> 0 | H103: {=_xlfn.XLOOKUP($A103,INDIRECT(H$3&"!$A:$A"),INDIRECT(H$3&"!$H:$H"),0,0)} -> 0 | I103: {=_xlfn.XLOOKUP($A103,INDIRECT(I$3&"!$A:$A"),INDIRECT(I$3&"!$H:$H"),0,0)} -> 0 | J103: {=_xlfn.XLOOKUP($A103,INDIRECT(J$3&"!$A:$A"),INDIRECT(J$3&"!$H:$H"),0,0)} -> 0 | K103: {=_xlfn.XLOOKUP($A103,INDIRECT(K$3&"!$A:$A"),INDIRECT(K$3&"!$H:$H"),0,0)} -> 0 | ... BD103: {=_xlfn.XLOOKUP($A103,INDIRECT(BD$3&"!$A:$A"),INDIRECT(BD$3&"!$H:$H"),0,0)} -> 0
A104: =A17 -> 236929187 | B104: =B17 -> AHMA1BW112WH | C104: =C17 -> Мешок 60*80 крупн | D104: {=_xlfn.XLOOKUP($A104,INDIRECT(D$3&"!$A:$A"),INDIRECT(D$3&"!$H:$H"),0,0)} -> 104.61538 | E104: {=_xlfn.XLOOKUP($A104,INDIRECT(E$3&"!$A:$A"),INDIRECT(E$3&"!$H:$H"),0,0)} -> 64.761905 | F104: {=_xlfn.XLOOKUP($A104,INDIRECT(F$3&"!$A:$A"),INDIRECT(F$3&"!$H:$H"),0,0)} -> 73.043478 | G104: {=_xlfn.XLOOKUP($A104,INDIRECT(G$3&"!$A:$A"),INDIRECT(G$3&"!$H:$H"),0,0)} -> 0 | H104: {=_xlfn.XLOOKUP($A104,INDIRECT(H$3&"!$A:$A"),INDIRECT(H$3&"!$H:$H"),0,0)} -> 0 | I104: {=_xlfn.XLOOKUP($A104,INDIRECT(I$3&"!$A:$A"),INDIRECT(I$3&"!$H:$H"),0,0)} -> 0 | J104: {=_xlfn.XLOOKUP($A104,INDIRECT(J$3&"!$A:$A"),INDIRECT(J$3&"!$H:$H"),0,0)} -> 0 | K104: {=_xlfn.XLOOKUP($A104,INDIRECT(K$3&"!$A:$A"),INDIRECT(K$3&"!$H:$H"),0,0)} -> 0 | ... BD104: {=_xlfn.XLOOKUP($A104,INDIRECT(BD$3&"!$A:$A"),INDIRECT(BD$3&"!$H:$H"),0,0)} -> 0
... A172: =A85 -> 340802685 | B172: =B85 -> AKTA1PR101GR | C172: =C85 -> Чеснокодавка | D172: {=_xlfn.XLOOKUP($A172,INDIRECT(D$3&"!$A:$A"),INDIRECT(D$3&"!$H:$H"),0,0)} -> 999 | E172: {=_xlfn.XLOOKUP($A172,INDIRECT(E$3&"!$A:$A"),INDIRECT(E$3&"!$H:$H"),0,0)} -> 999 | F172: {=_xlfn.XLOOKUP($A172,INDIRECT(F$3&"!$A:$A"),INDIRECT(F$3&"!$H:$H"),0,0)} -> 999 | G172: {=_xlfn.XLOOKUP($A172,INDIRECT(G$3&"!$A:$A"),INDIRECT(G$3&"!$H:$H"),0,0)} -> 0 | H172: {=_xlfn.XLOOKUP($A172,INDIRECT(H$3&"!$A:$A"),INDIRECT(H$3&"!$H:$H"),0,0)} -> 0 | I172: {=_xlfn.XLOOKUP($A172,INDIRECT(I$3&"!$A:$A"),INDIRECT(I$3&"!$H:$H"),0,0)} -> 0 | J172: {=_xlfn.XLOOKUP($A172,INDIRECT(J$3&"!$A:$A"),INDIRECT(J$3&"!$H:$H"),0,0)} -> 0 | K172: {=_xlfn.XLOOKUP($A172,INDIRECT(K$3&"!$A:$A"),INDIRECT(K$3&"!$H:$H"),0,0)} -> 0 | ... BD172: {=_xlfn.XLOOKUP($A172,INDIRECT(BD$3&"!$A:$A"),INDIRECT(BD$3&"!$H:$H"),0,0)} -> 0

Sheet ДинамФинан
A1: Период | D1: Дата поступления дс | E1: Итого к перечислению на счет, руб | F1: Выручка | I1: Продажи из отчета ВБ | J1: Себестоимость общая | K1: Логистика WB | L1: Комиссия WB | M1: Хранение WB | N1: Платная приемка | O1: Штрафы | P1: Реклама WB | Q1: Реклама внешняя | R1: Налог | S1: Выкупы | T1: Итог Прибыль | U1: Итог месяц | V1: % Cебестоимости в продаже | W1: % Маржинальности | X1: % Рентабельности
A2: Нед | B2: Месяц | C2: Даты | F2: Продажи | G2: Возвраты | H2: Общая
A3: 1 | B3: Январь 1 | C3: 01.01-04.01 | E3: =H3-SUM(K3:Q3) -> 21412.928 | F3: {=INDIRECT($A3&"!N84")} -> 49657.25 | G3: {=INDIRECT($A3&"!P84")} -> 815.77 | H3: {=INDIRECT($A3&"!Q84")} -> 48841.48 | I3: {=INDIRECT($A3&"!R84")} -> 34115.86 | J3: {=INDIRECT($A3&"!T84")} -> 9200 | K3: {=INDIRECT($A3&"!W84")} -> 4569.46 | L3: {=INDIRECT($A3&"!U84")} -> 12231.226 | M3: {=INDIRECT($A3&"!X84")} -> 10627.867 | N3: {=INDIRECT($A3&"!AA87")} -> 0 | O3: {=INDIRECT($A3&"!AA89")} -> 0 | P3: {=INDIRECT($A3&"!AA88")} -> 0 | R3: =I3*7% -> 2388.1102 | T3: =H3-SUM(J3:S3) -> 9824.8173 | U3: =SUM(T3:T7) -> 132753.67 | V3: =IFERROR(J3/H3," ") -> 0.18836448 | W3: =IFERROR(T3/H3," ") -> 0.20115724 | X3: =IFERROR(T3/J3," ") -> 1.0679149
A4: 2 | B4: Январь 2 | C4: 05.01-11.01 | E4: =H4-SUM(K4:Q4) -> 88983.72 | F4: {=INDIRECT($A4&"!N84")} -> 163975.97 | G4: {=INDIRECT($A4&"!P84")} -> 758 | H4: {=INDIRECT($A4&"!Q84")} -> 163217.97 | I4: {=INDIRECT($A4&"!R84")} -> 111684.74 | J4: {=INDIRECT($A4&"!T84")} -> 30711 | K4: {=INDIRECT($A4&"!W84")} -> 18912.99 | L4: {=INDIRECT($A4&"!U84")} -> 44516.474 | M4: {=INDIRECT($A4&"!X84")} -> 10804.786 | N4: {=INDIRECT($A4&"!AA87")} -> 0 | O4: {=INDIRECT($A4&"!AA89")} -> 0 | P4: {=INDIRECT($A4&"!AA88")} -> 0 | R4: =I4*7% -> 7817.9318 | T4: =H4-SUM(J4:S4) -> 50454.788 | V4: =IFERROR(J4/H4," ") -> 0.18815943 | W4: =IFERROR(T4/H4," ") -> 0.3091252 | X4: =IFERROR(T4/J4," ") -> 1.6428898
A5: 3 | B5: Январь 3 | C5: 12.01-18.01 | E5: =H5-SUM(K5:Q5) -> 125034.95 | F5: {=INDIRECT($A5&"!N84")} -> 220040.42 | G5: {=INDIRECT($A5&"!P84")} -> 1601.69 | H5: {=INDIRECT($A5&"!Q84")} -> 218438.73 | I5: {=INDIRECT($A5&"!R84")} -> 146398.35 | J5: {=INDIRECT($A5&"!T84")} -> 42313 | K5: {=INDIRECT($A5&"!W84")} -> 25479.63 | L5: {=INDIRECT($A5&"!U84")} -> 55811.67 | M5: {=INDIRECT($A5&"!X84")} -> 12112.484 | N5: {=INDIRECT($A5&"!AA87")} -> 0 | O5: {=INDIRECT($A5&"!AA89")} -> 0 | P5: {=INDIRECT($A5&"!AA88")} -> 0 | R5: =I5*7% -> 10247.885 | T5: =H5-SUM(J5:S5) -> 72474.061 | V5: =IFERROR(J5/H5," ") -> 0.19370649 | W5: =IFERROR(T5/H5," ") -> 0.3317821 | X5: =IFERROR(T5/J5," ") -> 1.7128084
A6: 4 | B6: Январь 4 | E6: =H6-SUM(K6:Q6) -> 0 | F6: {=INDIRECT($A6&"!N84")} -> 0 | G6: {=INDIRECT($A6&"!P84")} -> 0 | H6: {=INDIRECT($A6&"!Q84")} -> 0 | I6: {=INDIRECT($A6&"!R84")} -> 0 | J6: {=INDIRECT($A6&"!T84")} -> 0 | K6: {=INDIRECT($A6&"!W84")} -> 0 | L6: {=INDIRECT($A6&"!U84")} -> 0 | M6: {=INDIRECT($A6&"!X84")} -> 0 | N6: {=INDIRECT($A6&"!AA87")} -> 0 | O6: {=INDIRECT($A6&"!AA89")} -> 0 | P6: {=INDIRECT($A6&"!AA88")} -> 0 | R6: =I6*7% -> 0 | T6: =H6-SUM(J6:S6) -> 0 | V6: =IFERROR(J6/H6," ") | W6: =IFERROR(T6/H6," ") | X6: =IFERROR(T6/J6," ")
A7: 5 | B7: Январь 5 | E7: =H7-SUM(K7:Q7) -> 0 | F7: {=INDIRECT($A7&"!N84")} -> 0 | G7: {=INDIRECT($A7&"!P84")} -> 0 | H7: {=INDIRECT($A7&"!Q84")} -> 0 | I7: {=INDIRECT($A7&"!R84")} -> 0 | J7: {=INDIRECT($A7&"!T84")} -> 0 | K7: {=INDIRECT($A7&"!W84")} -> 0 | L7: {=INDIRECT($A7&"!U84")} -> 0 | M7: {=INDIRECT($A7&"!X84")} -> 0 | N7: {=INDIRECT($A7&"!AA87")} -> 0 | O7: {=INDIRECT($A7&"!AA89")} -> 0 | P7: {=INDIRECT($A7&"!AA88")} -> 0 | R7: =I7*7% -> 0 | T7: =H7-SUM(J7:S7) -> 0 | V7: =IFERROR(J7/H7," ") | W7: =IFERROR(T7/H7," ") | X7: =IFERROR(T7/J7," ")
A8: 6 | B8: Февраль 1 | E8: =H8-SUM(K8:Q8) -> 0 | F8: {=INDIRECT($A8&"!N84")} -> 0 | G8: {=INDIRECT($A8&"!P84")} -> 0 | H8: {=INDIRECT($A8&"!Q84")} -> 0 | I8: {=INDIRECT($A8&"!R84")} -> 0 | J8: {=INDIRECT($A8&"!T84")} -> 0 | K8: {=INDIRECT($A8&"!W84")} -> 0 | L8: {=INDIRECT($A8&"!U84")} -> 0 | M8: {=INDIRECT($A8&"!X84")} -> 0 | N8: {=INDIRECT($A8&"!AA87")} -> 0 | O8: {=INDIRECT($A8&"!AA89")} -> 0 | P8: {=INDIRECT($A8&"!AA88")} -> 0 | R8: =I8*7% -> 0 | T8: =H8-SUM(J8:S8) -> 0 | U8: =SUM(T8:T11) -> 0 | V8: =IFERROR(J8/H8," ") | W8: =IFERROR(T8/H8," ") | X8: =IFERROR(T8/J8," ")
A9: 7 | B9: Февраль 2 | E9: =H9-SUM(K9:Q9) -> 0 | F9: {=INDIRECT($A9&"!N84")} -> 0 | G9: {=INDIRECT($A9&"!P84")} -> 0 | H9: {=INDIRECT($A9&"!Q84")} -> 0 | I9: {=INDIRECT($A9&"!R84")} -> 0 | J9: {=INDIRECT($A9&"!T84")} -> 0 | K9: {=INDIRECT($A9&"!W84")} -> 0 | L9: {=INDIRECT($A9&"!U84")} -> 0 | M9: {=INDIRECT($A9&"!X84")} -> 0 | N9: {=INDIRECT($A9&"!AA87")} -> 0 | O9: {=INDIRECT($A9&"!AA89")} -> 0 | P9: {=INDIRECT($A9&"!AA88")} -> 0 | R9: =I9*7% -> 0 | T9: =H9-SUM(J9:S9) -> 0 | V9: =IFERROR(J9/H9," ") | W9: =IFERROR(T9/H9," ") | X9: =IFERROR(T9/J9," ")
A10: 8 | B10: Февраль 3 | E10: =H10-SUM(K10:Q10) -> 0 | F10: {=INDIRECT($A10&"!N84")} -> 0 | G10: {=INDIRECT($A10&"!P84")} -> 0 | H10: {=INDIRECT($A10&"!Q84")} -> 0 | I10: {=INDIRECT($A10&"!R84")} -> 0 | J10: {=INDIRECT($A10&"!T84")} -> 0 | K10: {=INDIRECT($A10&"!W84")} -> 0 | L10: {=INDIRECT($A10&"!U84")} -> 0 | M10: {=INDIRECT($A10&"!X84")} -> 0 | N10: {=INDIRECT($A10&"!AA87")} -> 0 | O10: {=INDIRECT($A10&"!AA89")} -> 0 | P10: {=INDIRECT($A10&"!AA88")} -> 0 | R10: =I10*7% -> 0 | T10: =H10-SUM(J10:S10) -> 0 | V10: =IFERROR(J10/H10," ") | W10: =IFERROR(T10/H10," ") | X10: =IFERROR(T10/J10," ")
A11: 9 | B11: Февраль 4 | E11: =H11-SUM(K11:Q11) -> 0 | F11: {=INDIRECT($A11&"!N84")} -> 0 | G11: {=INDIRECT($A11&"!P84")} -> 0 | H11: {=INDIRECT($A11&"!Q84")} -> 0 | I11: {=INDIRECT($A11&"!R84")} -> 0 | J11: {=INDIRECT($A11&"!T84")} -> 0 | K11: {=INDIRECT($A11&"!W84")} -> 0 | L11: {=INDIRECT($A11&"!U84")} -> 0 | M11: {=INDIRECT($A11&"!X84")} -> 0 | N11: {=INDIRECT($A11&"!AA87")} -> 0 | O11: {=INDIRECT($A11&"!AA89")} -> 0 | P11: {=INDIRECT($A11&"!AA88")} -> 0 | R11: =I11*7% -> 0 | T11: =H11-SUM(J11:S11) -> 0 | V11: =IFERROR(J11/H11," ") | W11: =IFERROR(T11/H11," ") | X11: =IFERROR(T11/J11," ")
A12: 10 | B12: Март 1 | E12: =H12-SUM(K12:Q12) -> 0 | F12: {=INDIRECT($A12&"!N84")} -> 0 | G12: {=INDIRECT($A12&"!P84")} -> 0 | H12: {=INDIRECT($A12&"!Q84")} -> 0 | I12: {=INDIRECT($A12&"!R84")} -> 0 | J12: {=INDIRECT($A12&"!T84")} -> 0 | K12: {=INDIRECT($A12&"!W84")} -> 0 | L12: {=INDIRECT($A12&"!U84")} -> 0 | M12: {=INDIRECT($A12&"!X84")} -> 0 | N12: {=INDIRECT($A12&"!AA87")} -> 0 | O12: {=INDIRECT($A12&"!AA89")} -> 0 | P12: {=INDIRECT($A12&"!AA88")} -> 0 | R12: =I12*7% -> 0 | T12: =H12-SUM(J12:S12) -> 0 | U12: =SUM(T12:T15) -> 0 | V12: =IFERROR(J12/H12," ") | W12: =IFERROR(T12/H12," ") | X12: =IFERROR(T12/J12," ")
A13: 11 | B13: Март 2 | E13: =H13-SUM(K13:Q13) -> 0 | F13: {=INDIRECT($A13&"!N84")} -> 0 | G13: {=INDIRECT($A13&"!P84")} -> 0 | H13: {=INDIRECT($A13&"!Q84")} -> 0 | I13: {=INDIRECT($A13&"!R84")} -> 0 | J13: {=INDIRECT($A13&"!T84")} -> 0 | K13: {=INDIRECT($A13&"!W84")} -> 0 | L13: {=INDIRECT($A13&"!U84")} -> 0 | M13: {=INDIRECT($A13&"!X84")} -> 0 | N13: {=INDIRECT($A13&"!AA87")} -> 0 | O13: {=INDIRECT($A13&"!AA89")} -> 0 | P13: {=INDIRECT($A13&"!AA88")} -> 0 | R13: =I13*7% -> 0 | T13: =H13-SUM(J13:S13) -> 0 | V13: =IFERROR(J13/H13," ") | W13: =IFERROR(T13/H13," ") | X13: =IFERROR(T13/J13," ")
A14: 12 | B14: Март 3 | E14: =H14-SUM(K14:Q14) -> 0 | F14: {=INDIRECT($A14&"!N84")} -> 0 | G14: {=INDIRECT($A14&"!P84")} -> 0 | H14: {=INDIRECT($A14&"!Q84")} -> 0 | I14: {=INDIRECT($A14&"!R84")} -> 0 | J14: {=INDIRECT($A14&"!T84")} -> 0 | K14: {=INDIRECT($A14&"!W84")} -> 0 | L14: {=INDIRECT($A14&"!U84")} -> 0 | M14: {=INDIRECT($A14&"!X84")} -> 0 | N14: {=INDIRECT($A14&"!AA87")} -> 0 | O14: {=INDIRECT($A14&"!AA89")} -> 0 | P14: {=INDIRECT($A14&"!AA88")} -> 0 | R14: =I14*7% -> 0 | T14: =H14-SUM(J14:S14) -> 0 | V14: =IFERROR(J14/H14," ") | W14: =IFERROR(T14/H14," ") | X14: =IFERROR(T14/J14," ")
A15: 13 | B15: Март 4 | E15: =H15-SUM(K15:Q15) -> 0 | F15: {=INDIRECT($A15&"!N84")} -> 0 | G15: {=INDIRECT($A15&"!P84")} -> 0 | H15: {=INDIRECT($A15&"!Q84")} -> 0 | I15: {=INDIRECT($A15&"!R84")} -> 0 | J15: {=INDIRECT($A15&"!T84")} -> 0 | K15: {=INDIRECT($A15&"!W84")} -> 0 | L15: {=INDIRECT($A15&"!U84")} -> 0 | M15: {=INDIRECT($A15&"!X84")} -> 0 | N15: {=INDIRECT($A15&"!AA87")} -> 0 | O15: {=INDIRECT($A15&"!AA89")} -> 0 | P15: {=INDIRECT($A15&"!AA88")} -> 0 | R15: =I15*7% -> 0 | T15: =H15-SUM(J15:S15) -> 0 | V15: =IFERROR(J15/H15," ") | W15: =IFERROR(T15/H15," ") | X15: =IFERROR(T15/J15," ")
A16: 14 | B16: Апрель 1 | E16: =H16-SUM(K16:Q16) -> 0 | F16: {=INDIRECT($A16&"!N84")} -> 0 | G16: {=INDIRECT($A16&"!P84")} -> 0 | H16: {=INDIRECT($A16&"!Q84")} -> 0 | I16: {=INDIRECT($A16&"!R84")} -> 0 | J16: {=INDIRECT($A16&"!T84")} -> 0 | K16: {=INDIRECT($A16&"!W84")} -> 0 | L16: {=INDIRECT($A16&"!U84")} -> 0 | M16: {=INDIRECT($A16&"!X84")} -> 0 | N16: {=INDIRECT($A16&"!AA87")} -> 0 | O16: {=INDIRECT($A16&"!AA89")} -> 0 | P16: {=INDIRECT($A16&"!AA88")} -> 0 | R16: =I16*7% -> 0 | T16: =H16-SUM(J16:S16) -> 0 | U16: =SUM(T16:T19) -> 0 | V16: =IFERROR(J16/H16," ") | W16: =IFERROR(T16/H16," ") | X16: =IFERROR(T16/J16," ")
A17: 15 | B17: Апрель 2 | E17: =H17-SUM(K17:Q17) -> 0 | F17: {=INDIRECT($A17&"!N84")} -> 0 | G17: {=INDIRECT($A17&"!P84")} -> 0 | H17: {=INDIRECT($A17&"!Q84")} -> 0 | I17: {=INDIRECT($A17&"!R84")} -> 0 | J17: {=INDIRECT($A17&"!T84")} -> 0 | K17: {=INDIRECT($A17&"!W84")} -> 0 | L17: {=INDIRECT($A17&"!U84")} -> 0 | M17: {=INDIRECT($A17&"!X84")} -> 0 | N17: {=INDIRECT($A17&"!AA87")} -> 0 | O17: {=INDIRECT($A17&"!AA89")} -> 0 | P17: {=INDIRECT($A17&"!AA88")} -> 0 | R17: =I17*7% -> 0 | T17: =H17-SUM(J17:S17) -> 0 | V17: =IFERROR(J17/H17," ") | W17: =IFERROR(T17/H17," ") | X17: =IFERROR(T17/J17," ")
A18: 16 | B18: Апрель 3 | E18: =H18-SUM(K18:Q18) -> 0 | F18: {=INDIRECT($A18&"!N84")} -> 0 | G18: {=INDIRECT($A18&"!P84")} -> 0 | H18: {=INDIRECT($A18&"!Q84")} -> 0 | I18: {=INDIRECT($A18&"!R84")} -> 0 | J18: {=INDIRECT($A18&"!T84")} -> 0 | K18: {=INDIRECT($A18&"!W84")} -> 0 | L18: {=INDIRECT($A18&"!U84")} -> 0 | M18: {=INDIRECT($A18&"!X84")} -> 0 | N18: {=INDIRECT($A18&"!AA87")} -> 0 | O18: {=INDIRECT($A18&"!AA89")} -> 0 | P18: {=INDIRECT($A18&"!AA88")} -> 0 | R18: =I18*7% -> 0 | T18: =H18-SUM(J18:S18) -> 0 | V18: =IFERROR(J18/H18," ") | W18: =IFERROR(T18/H18," ") | X18: =IFERROR(T18/J18," ")
A19: 17 | B19: Апрель 4 | E19: =H19-SUM(K19:Q19) -> 0 | F19: {=INDIRECT($A19&"!N84")} -> 0 | G19: {=INDIRECT($A19&"!P84")} -> 0 | H19: {=INDIRECT($A19&"!Q84")} -> 0 | I19: {=INDIRECT($A19&"!R84")} -> 0 | J19: {=INDIRECT($A19&"!T84")} -> 0 | K19: {=INDIRECT($A19&"!W84")} -> 0 | L19: {=INDIRECT($A19&"!U84")} -> 0 | M19: {=INDIRECT($A19&"!X84")} -> 0 | N19: {=INDIRECT($A19&"!AA87")} -> 0 | O19: {=INDIRECT($A19&"!AA89")} -> 0 | P19: {=INDIRECT($A19&"!AA88")} -> 0 | R19: =I19*7% -> 0 | T19: =H19-SUM(J19:S19) -> 0 | V19: =IFERROR(J19/H19," ") | W19: =IFERROR(T19/H19," ") | X19: =IFERROR(T19/J19," ")
A20: 18 | B20: Май 1 | E20: =H20-SUM(K20:Q20) -> 0 | F20: {=INDIRECT($A20&"!N84")} -> 0 | G20: {=INDIRECT($A20&"!P84")} -> 0 | H20: {=INDIRECT($A20&"!Q84")} -> 0 | I20: {=INDIRECT($A20&"!R84")} -> 0 | J20: {=INDIRECT($A20&"!T84")} -> 0 | K20: {=INDIRECT($A20&"!W84")} -> 0 | L20: {=INDIRECT($A20&"!U84")} -> 0 | M20: {=INDIRECT($A20&"!X84")} -> 0 | N20: {=INDIRECT($A20&"!AA87")} -> 0 | O20: {=INDIRECT($A20&"!AA89")} -> 0 | P20: {=INDIRECT($A20&"!AA88")} -> 0 | R20: =I20*7% -> 0 | T20: =H20-SUM(J20:S20) -> 0 | U20: =SUM(T20:T24) -> 0 | V20: =IFERROR(J20/H20," ") | W20: =IFERROR(T20/H20," ") | X20: =IFERROR(T20/J20," ")
A21: 19 | B21: Май 2 | E21: =H21-SUM(K21:Q21) -> 0 | F21: {=INDIRECT($A21&"!N84")} -> 0 | G21: {=INDIRECT($A21&"!P84")} -> 0 | H21: {=INDIRECT($A21&"!Q84")} -> 0 | I21: {=INDIRECT($A21&"!R84")} -> 0 | J21: {=INDIRECT($A21&"!T84")} -> 0 | K21: {=INDIRECT($A21&"!W84")} -> 0 | L21: {=INDIRECT($A21&"!U84")} -> 0 | M21: {=INDIRECT($A21&"!X84")} -> 0 | N21: {=INDIRECT($A21&"!AA87")} -> 0 | O21: {=INDIRECT($A21&"!AA89")} -> 0 | P21: {=INDIRECT($A21&"!AA88")} -> 0 | R21: =I21*7% -> 0 | T21: =H21-SUM(J21:S21) -> 0 | V21: =IFERROR(J21/H21," ") | W21: =IFERROR(T21/H21," ") | X21: =IFERROR(T21/J21," ")
A22: 20 | B22: Май 3 | E22: =H22-SUM(K22:Q22) -> 0 | F22: {=INDIRECT($A22&"!N84")} -> 0 | G22: {=INDIRECT($A22&"!P84")} -> 0 | H22: {=INDIRECT($A22&"!Q84")} -> 0 | I22: {=INDIRECT($A22&"!R84")} -> 0 | J22: {=INDIRECT($A22&"!T84")} -> 0 | K22: {=INDIRECT($A22&"!W84")} -> 0 | L22: {=INDIRECT($A22&"!U84")} -> 0 | M22: {=INDIRECT($A22&"!X84")} -> 0 | N22: {=INDIRECT($A22&"!AA87")} -> 0 | O22: {=INDIRECT($A22&"!AA89")} -> 0 | P22: {=INDIRECT($A22&"!AA88")} -> 0 | R22: =I22*7% -> 0 | T22: =H22-SUM(J22:S22) -> 0 | V22: =IFERROR(J22/H22," ") | W22: =IFERROR(T22/H22," ") | X22: =IFERROR(T22/J22," ")
A23: 21 | B23: Май 4 | E23: =H23-SUM(K23:Q23) -> 0 | F23: {=INDIRECT($A23&"!N84")} -> 0 | G23: {=INDIRECT($A23&"!P84")} -> 0 | H23: {=INDIRECT($A23&"!Q84")} -> 0 | I23: {=INDIRECT($A23&"!R84")} -> 0 | J23: {=INDIRECT($A23&"!T84")} -> 0 | K23: {=INDIRECT($A23&"!W84")} -> 0 | L23: {=INDIRECT($A23&"!U84")} -> 0 | M23: {=INDIRECT($A23&"!X84")} -> 0 | N23: {=INDIRECT($A23&"!AA87")} -> 0 | O23: {=INDIRECT($A23&"!AA89")} -> 0 | P23: {=INDIRECT($A23&"!AA88")} -> 0 | R23: =I23*7% -> 0 | T23: =H23-SUM(J23:S23) -> 0 | V23: =IFERROR(J23/H23," ") | W23: =IFERROR(T23/H23," ") | X23: =IFERROR(T23/J23," ")
A24: 22 | B24: Май 5 | E24: =H24-SUM(K24:Q24) -> 0 | F24: {=INDIRECT($A24&"!N84")} -> 0 | G24: {=INDIRECT($A24&"!P84")} -> 0 | H24: {=INDIRECT($A24&"!Q84")} -> 0 | I24: {=INDIRECT($A24&"!R84")} -> 0 | J24: {=INDIRECT($A24&"!T84")} -> 0 | K24: {=INDIRECT($A24&"!W84")} -> 0 | L24: {=INDIRECT($A24&"!U84")} -> 0 | M24: {=INDIRECT($A24&"!X84")} -> 0 | N24: {=INDIRECT($A24&"!AA87")} -> 0 | O24: {=INDIRECT($A24&"!AA89")} -> 0 | P24: {=INDIRECT($A24&"!AA88")} -> 0 | R24: =I24*7% -> 0 | T24: =H24-SUM(J24:S24) -> 0 | V24: =IFERROR(J24/H24," ") | W24: =IFERROR(T24/H24," ") | X24: =IFERROR(T24/J24," ")
A25: 23 | B25: Июнь 1 | E25: =H25-SUM(K25:Q25) -> 0 | F25: {=INDIRECT($A25&"!N84")} -> 0 | G25: {=INDIRECT($A25&"!P84")} -> 0 | H25: {=INDIRECT($A25&"!Q84")} -> 0 | I25: {=INDIRECT($A25&"!R84")} -> 0 | J25: {=INDIRECT($A25&"!T84")} -> 0 | K25: {=INDIRECT($A25&"!W84")} -> 0 | L25: {=INDIRECT($A25&"!U84")} -> 0 | M25: {=INDIRECT($A25&"!X84")} -> 0 | N25: {=INDIRECT($A25&"!AA87")} -> 0 | O25: {=INDIRECT($A25&"!AA89")} -> 0 | P25: {=INDIRECT($A25&"!AA88")} -> 0 | R25: =I25*7% -> 0 | T25: =H25-SUM(J25:S25) -> 0 | U25: =SUM(T25:T28) -> 0 | V25: =IFERROR(J25/H25," ") | W25: =IFERROR(T25/H25," ") | X25: =IFERROR(T25/J25," ")
A26: 24 | B26: Июнь 2 | E26: =H26-SUM(K26:Q26) -> 0 | F26: {=INDIRECT($A26&"!N84")} -> 0 | G26: {=INDIRECT($A26&"!P84")} -> 0 | H26: {=INDIRECT($A26&"!Q84")} -> 0 | I26: {=INDIRECT($A26&"!R84")} -> 0 | J26: {=INDIRECT($A26&"!T84")} -> 0 | K26: {=INDIRECT($A26&"!W84")} -> 0 | L26: {=INDIRECT($A26&"!U84")} -> 0 | M26: {=INDIRECT($A26&"!X84")} -> 0 | N26: {=INDIRECT($A26&"!AA87")} -> 0 | O26: {=INDIRECT($A26&"!AA89")} -> 0 | P26: {=INDIRECT($A26&"!AA88")} -> 0 | R26: =I26*7% -> 0 | T26: =H26-SUM(J26:S26) -> 0 | V26: =IFERROR(J26/H26," ") | W26: =IFERROR(T26/H26," ") | X26: =IFERROR(T26/J26," ")
A27: 25 | B27: Июнь 3 | E27: =H27-SUM(K27:Q27) -> 0 | F27: {=INDIRECT($A27&"!N84")} -> 0 | G27: {=INDIRECT($A27&"!P84")} -> 0 | H27: {=INDIRECT($A27&"!Q84")} -> 0 | I27: {=INDIRECT($A27&"!R84")} -> 0 | J27: {=INDIRECT($A27&"!T84")} -> 0 | K27: {=INDIRECT($A27&"!W84")} -> 0 | L27: {=INDIRECT($A27&"!U84")} -> 0 | M27: {=INDIRECT($A27&"!X84")} -> 0 | N27: {=INDIRECT($A27&"!AA87")} -> 0 | O27: {=INDIRECT($A27&"!AA89")} -> 0 | P27: {=INDIRECT($A27&"!AA88")} -> 0 | R27: =I27*7% -> 0 | T27: =H27-SUM(J27:S27) -> 0 | V27: =IFERROR(J27/H27," ") | W27: =IFERROR(T27/H27," ") | X27: =IFERROR(T27/J27," ")
A28: 26 | B28: Июнь 4 | E28: =H28-SUM(K28:Q28) -> 0 | F28: {=INDIRECT($A28&"!N84")} -> 0 | G28: {=INDIRECT($A28&"!P84")} -> 0 | H28: {=INDIRECT($A28&"!Q84")} -> 0 | I28: {=INDIRECT($A28&"!R84")} -> 0 | J28: {=INDIRECT($A28&"!T84")} -> 0 | K28: {=INDIRECT($A28&"!W84")} -> 0 | L28: {=INDIRECT($A28&"!U84")} -> 0 | M28: {=INDIRECT($A28&"!X84")} -> 0 | N28: {=INDIRECT($A28&"!AA87")} -> 0 | O28: {=INDIRECT($A28&"!AA89")} -> 0 | P28: {=INDIRECT($A28&"!AA88")} -> 0 | R28: =I28*7% -> 0 | T28: =H28-SUM(J28:S28) -> 0 | V28: =IFERROR(J28/H28," ") | W28: =IFERROR(T28/H28," ") | X28: =IFERROR(T28/J28," ")
A29: 27 | B29: Июль 1 | E29: =H29-SUM(K29:Q29) -> 0 | F29: {=INDIRECT($A29&"!N84")} -> 0 | G29: {=INDIRECT($A29&"!P84")} -> 0 | H29: {=INDIRECT($A29&"!Q84")} -> 0 | I29: {=INDIRECT($A29&"!R84")} -> 0 | J29: {=INDIRECT($A29&"!T84")} -> 0 | K29: {=INDIRECT($A29&"!W84")} -> 0 | L29: {=INDIRECT($A29&"!U84")} -> 0 | M29: {=INDIRECT($A29&"!X84")} -> 0 | N29: {=INDIRECT($A29&"!AA87")} -> 0 | O29: {=INDIRECT($A29&"!AA89")} -> 0 | P29: {=INDIRECT($A29&"!AA88")} -> 0 | R29: =I29*7% -> 0 | T29: =H29-SUM(J29:S29) -> 0 | U29: =SUM(T29:T32) -> 0 | V29: =IFERROR(J29/H29," ") | W29: =IFERROR(T29/H29," ") | X29: =IFERROR(T29/J29," ")
A30: 28 | B30: Июль 2 | E30: =H30-SUM(K30:Q30) -> 0 | F30: {=INDIRECT($A30&"!N84")} -> 0 | G30: {=INDIRECT($A30&"!P84")} -> 0 | H30: {=INDIRECT($A30&"!Q84")} -> 0 | I30: {=INDIRECT($A30&"!R84")} -> 0 | J30: {=INDIRECT($A30&"!T84")} -> 0 | K30: {=INDIRECT($A30&"!W84")} -> 0 | L30: {=INDIRECT($A30&"!U84")} -> 0 | M30: {=INDIRECT($A30&"!X84")} -> 0 | N30: {=INDIRECT($A30&"!AA87")} -> 0 | O30: {=INDIRECT($A30&"!AA89")} -> 0 | P30: {=INDIRECT($A30&"!AA88")} -> 0 | R30: =I30*7% -> 0 | T30: =H30-SUM(J30:S30) -> 0 | V30: =IFERROR(J30/H30," ") | W30: =IFERROR(T30/H30," ") | X30: =IFERROR(T30/J30," ")
A31: 29 | B31: Июль 3 | E31: =H31-SUM(K31:Q31) -> 0 | F31: {=INDIRECT($A31&"!N84")} -> 0 | G31: {=INDIRECT($A31&"!P84")} -> 0 | H31: {=INDIRECT($A31&"!Q84")} -> 0 | I31: {=INDIRECT($A31&"!R84")} -> 0 | J31: {=INDIRECT($A31&"!T84")} -> 0 | K31: {=INDIRECT($A31&"!W84")} -> 0 | L31: {=INDIRECT($A31&"!U84")} -> 0 | M31: {=INDIRECT($A31&"!X84")} -> 0 | N31: {=INDIRECT($A31&"!AA87")} -> 0 | O31: {=INDIRECT($A31&"!AA89")} -> 0 | P31: {=INDIRECT($A31&"!AA88")} -> 0 | R31: =I31*7% -> 0 | T31: =H31-SUM(J31:S31) -> 0 | V31: =IFERROR(J31/H31," ") | W31: =IFERROR(T31/H31," ") | X31: =IFERROR(T31/J31," ")
A32: 30 | B32: Июль 4 | E32: =H32-SUM(K32:Q32) -> 0 | F32: {=INDIRECT($A32&"!N84")} -> 0 | G32: {=INDIRECT($A32&"!P84")} -> 0 | H32: {=INDIRECT($A32&"!Q84")} -> 0 | I32: {=INDIRECT($A32&"!R84")} -> 0 | J32: {=INDIRECT($A32&"!T84")} -> 0 | K32: {=INDIRECT($A32&"!W84")} -> 0 | L32: {=INDIRECT($A32&"!U84")} -> 0 | M32: {=INDIRECT($A32&"!X84")} -> 0 | N32: {=INDIRECT($A32&"!AA87")} -> 0 | O32: {=INDIRECT($A32&"!AA89")} -> 0 | P32: {=INDIRECT($A32&"!AA88")} -> 0 | R32: =I32*7% -> 0 | T32: =H32-SUM(J32:S32) -> 0 | V32: =IFERROR(J32/H32," ") | W32: =IFERROR(T32/H32," ") | X32: =IFERROR(T32/J32," ")
A33: 31 | B33: Август 1 | E33: =H33-SUM(K33:Q33) -> 0 | F33: {=INDIRECT($A33&"!N84")} -> 0 | G33: {=INDIRECT($A33&"!P84")} -> 0 | H33: {=INDIRECT($A33&"!Q84")} -> 0 | I33: {=INDIRECT($A33&"!R84")} -> 0 | J33: {=INDIRECT($A33&"!T84")} -> 0 | K33: {=INDIRECT($A33&"!W84")} -> 0 | L33: {=INDIRECT($A33&"!U84")} -> 0 | M33: {=INDIRECT($A33&"!X84")} -> 0 | N33: {=INDIRECT($A33&"!AA87")} -> 0 | O33: {=INDIRECT($A33&"!AA89")} -> 0 | P33: {=INDIRECT($A33&"!AA88")} -> 0 | R33: =I33*7% -> 0 | T33: =H33-SUM(J33:S33) -> 0 | U33: =SUM(T33:T37) -> 0 | V33: =IFERROR(J33/H33," ") | W33: =IFERROR(T33/H33," ") | X33: =IFERROR(T33/J33," ")
A34: 32 | B34: Август 2 | E34: =H34-SUM(K34:Q34) -> 0 | F34: {=INDIRECT($A34&"!N84")} -> 0 | G34: {=INDIRECT($A34&"!P84")} -> 0 | H34: {=INDIRECT($A34&"!Q84")} -> 0 | I34: {=INDIRECT($A34&"!R84")} -> 0 | J34: {=INDIRECT($A34&"!T84")} -> 0 | K34: {=INDIRECT($A34&"!W84")} -> 0 | L34: {=INDIRECT($A34&"!U84")} -> 0 | M34: {=INDIRECT($A34&"!X84")} -> 0 | N34: {=INDIRECT($A34&"!AA87")} -> 0 | O34: {=INDIRECT($A34&"!AA89")} -> 0 | P34: {=INDIRECT($A34&"!AA88")} -> 0 | R34: =I34*7% -> 0 | T34: =H34-SUM(J34:S34) -> 0 | V34: =IFERROR(J34/H34," ") | W34: =IFERROR(T34/H34," ") | X34: =IFERROR(T34/J34," ")
A35: 33 | B35: Август 3 | E35: =H35-SUM(K35:Q35) -> 0 | F35: {=INDIRECT($A35&"!N84")} -> 0 | G35: {=INDIRECT($A35&"!P84")} -> 0 | H35: {=INDIRECT($A35&"!Q84")} -> 0 | I35: {=INDIRECT($A35&"!R84")} -> 0 | J35: {=INDIRECT($A35&"!T84")} -> 0 | K35: {=INDIRECT($A35&"!W84")} -> 0 | L35: {=INDIRECT($A35&"!U84")} -> 0 | M35: {=INDIRECT($A35&"!X84")} -> 0 | N35: {=INDIRECT($A35&"!AA87")} -> 0 | O35: {=INDIRECT($A35&"!AA89")} -> 0 | P35: {=INDIRECT($A35&"!AA88")} -> 0 | R35: =I35*7% -> 0 | T35: =H35-SUM(J35:S35) -> 0 | V35: =IFERROR(J35/H35," ") | W35: =IFERROR(T35/H35," ") | X35: =IFERROR(T35/J35," ")
A36: 34 | B36: Август 4 | E36: =H36-SUM(K36:Q36) -> 0 | F36: {=INDIRECT($A36&"!N84")} -> 0 | G36: {=INDIRECT($A36&"!P84")} -> 0 | H36: {=INDIRECT($A36&"!Q84")} -> 0 | I36: {=INDIRECT($A36&"!R84")} -> 0 | J36: {=INDIRECT($A36&"!T84")} -> 0 | K36: {=INDIRECT($A36&"!W84")} -> 0 | L36: {=INDIRECT($A36&"!U84")} -> 0 | M36: {=INDIRECT($A36&"!X84")} -> 0 | N36: {=INDIRECT($A36&"!AA87")} -> 0 | O36: {=INDIRECT($A36&"!AA89")} -> 0 | P36: {=INDIRECT($A36&"!AA88")} -> 0 | R36: =I36*7% -> 0 | T36: =H36-SUM(J36:S36) -> 0 | V36: =IFERROR(J36/H36," ") | W36: =IFERROR(T36/H36," ") | X36: =IFERROR(T36/J36," ")
A37: 35 | B37: Август 5 | E37: =H37-SUM(K37:Q37) -> 0 | F37: {=INDIRECT($A37&"!N84")} -> 0 | G37: {=INDIRECT($A37&"!P84")} -> 0 | H37: {=INDIRECT($A37&"!Q84")} -> 0 | I37: {=INDIRECT($A37&"!R84")} -> 0 | J37: {=INDIRECT($A37&"!T84")} -> 0 | K37: {=INDIRECT($A37&"!W84")} -> 0 | L37: {=INDIRECT($A37&"!U84")} -> 0 | M37: {=INDIRECT($A37&"!X84")} -> 0 | N37: {=INDIRECT($A37&"!AA87")} -> 0 | O37: {=INDIRECT($A37&"!AA89")} -> 0 | P37: {=INDIRECT($A37&"!AA88")} -> 0 | R37: =I37*7% -> 0 | T37: =H37-SUM(J37:S37) -> 0 | V37: =IFERROR(J37/H37," ") | W37: =IFERROR(T37/H37," ") | X37: =IFERROR(T37/J37," ")
A38: 36 | B38: Сентябрь 1 | E38: =H38-SUM(K38:Q38) -> 0 | F38: {=INDIRECT($A38&"!N84")} -> 0 | G38: {=INDIRECT($A38&"!P84")} -> 0 | H38: {=INDIRECT($A38&"!Q84")} -> 0 | I38: {=INDIRECT($A38&"!R84")} -> 0 | J38: {=INDIRECT($A38&"!T84")} -> 0 | K38: {=INDIRECT($A38&"!W84")} -> 0 | L38: {=INDIRECT($A38&"!U84")} -> 0 | M38: {=INDIRECT($A38&"!X84")} -> 0 | N38: {=INDIRECT($A38&"!AA87")} -> 0 | O38: {=INDIRECT($A38&"!AA89")} -> 0 | P38: {=INDIRECT($A38&"!AA88")} -> 0 | R38: =I38*7% -> 0 | T38: =H38-SUM(J38:S38) -> 0 | U38: =SUM(T38:T41) -> 0 | V38: =IFERROR(J38/H38," ") | W38: =IFERROR(T38/H38," ") | X38: =IFERROR(T38/J38," ")
A39: 37 | B39: Сентябрь 2 | E39: =H39-SUM(K39:Q39) -> 0 | F39: {=INDIRECT($A39&"!N84")} -> 0 | G39: {=INDIRECT($A39&"!P84")} -> 0 | H39: {=INDIRECT($A39&"!Q84")} -> 0 | I39: {=INDIRECT($A39&"!R84")} -> 0 | J39: {=INDIRECT($A39&"!T84")} -> 0 | K39: {=INDIRECT($A39&"!W84")} -> 0 | L39: {=INDIRECT($A39&"!U84")} -> 0 | M39: {=INDIRECT($A39&"!X84")} -> 0 | N39: {=INDIRECT($A39&"!AA87")} -> 0 | O39: {=INDIRECT($A39&"!AA89")} -> 0 | P39: {=INDIRECT($A39&"!AA88")} -> 0 | R39: =I39*7% -> 0 | T39: =H39-SUM(J39:S39) -> 0 | V39: =IFERROR(J39/H39," ") | W39: =IFERROR(T39/H39," ") | X39: =IFERROR(T39/J39," ")
A40: 38 | B40: Сентябрь 3 | E40: =H40-SUM(K40:Q40) -> 0 | F40: {=INDIRECT($A40&"!N84")} -> 0 | G40: {=INDIRECT($A40&"!P84")} -> 0 | H40: {=INDIRECT($A40&"!Q84")} -> 0 | I40: {=INDIRECT($A40&"!R84")} -> 0 | J40: {=INDIRECT($A40&"!T84")} -> 0 | K40: {=INDIRECT($A40&"!W84")} -> 0 | L40: {=INDIRECT($A40&"!U84")} -> 0 | M40: {=INDIRECT($A40&"!X84")} -> 0 | N40: {=INDIRECT($A40&"!AA87")} -> 0 | O40: {=INDIRECT($A40&"!AA89")} -> 0 | P40: {=INDIRECT($A40&"!AA88")} -> 0 | R40: =I40*7% -> 0 | T40: =H40-SUM(J40:S40) -> 0 | V40: =IFERROR(J40/H40," ") | W40: =IFERROR(T40/H40," ") | X40: =IFERROR(T40/J40," ")
A41: 39 | B41: Сентябрь 4 | E41: =H41-SUM(K41:Q41) -> 0 | F41: {=INDIRECT($A41&"!N84")} -> 0 | G41: {=INDIRECT($A41&"!P84")} -> 0 | H41: {=INDIRECT($A41&"!Q84")} -> 0 | I41: {=INDIRECT($A41&"!R84")} -> 0 | J41: {=INDIRECT($A41&"!T84")} -> 0 | K41: {=INDIRECT($A41&"!W84")} -> 0 | L41: {=INDIRECT($A41&"!U84")} -> 0 | M41: {=INDIRECT($A41&"!X84")} -> 0 | N41: {=INDIRECT($A41&"!AA87")} -> 0 | O41: {=INDIRECT($A41&"!AA89")} -> 0 | P41: {=INDIRECT($A41&"!AA88")} -> 0 | R41: =I41*7% -> 0 | T41: =H41-SUM(J41:S41) -> 0 | V41: =IFERROR(J41/H41," ") | W41: =IFERROR(T41/H41," ") | X41: =IFERROR(T41/J41," ")
A42: 40 | B42: Октябрь 1 | E42: =H42-SUM(K42:Q42) -> 0 | F42: {=INDIRECT($A42&"!N84")} -> 0 | G42: {=INDIRECT($A42&"!P84")} -> 0 | H42: {=INDIRECT($A42&"!Q84")} -> 0 | I42: {=INDIRECT($A42&"!R84")} -> 0 | J42: {=INDIRECT($A42&"!T84")} -> 0 | K42: {=INDIRECT($A42&"!W84")} -> 0 | L42: {=INDIRECT($A42&"!U84")} -> 0 | M42: {=INDIRECT($A42&"!X84")} -> 0 | N42: {=INDIRECT($A42&"!AA87")} -> 0 | O42: {=INDIRECT($A42&"!AA89")} -> 0 | P42: {=INDIRECT($A42&"!AA88")} -> 0 | R42: =I42*7% -> 0 | T42: =H42-SUM(J42:S42) -> 0 | U42: =SUM(T42:T46) -> 0 | V42: =IFERROR(J42/H42," ") | W42: =IFERROR(T42/H42," ") | X42: =IFERROR(T42/J42," ")
A43: 41 | B43: Октябрь 2 | E43: =H43-SUM(K43:Q43) -> 0 | F43: {=INDIRECT($A43&"!N84")} -> 0 | G43: {=INDIRECT($A43&"!P84")} -> 0 | H43: {=INDIRECT($A43&"!Q84")} -> 0 | I43: {=INDIRECT($A43&"!R84")} -> 0 | J43: {=INDIRECT($A43&"!T84")} -> 0 | K43: {=INDIRECT($A43&"!W84")} -> 0 | L43: {=INDIRECT($A43&"!U84")} -> 0 | M43: {=INDIRECT($A43&"!X84")} -> 0 | N43: {=INDIRECT($A43&"!AA87")} -> 0 | O43: {=INDIRECT($A43&"!AA89")} -> 0 | P43: {=INDIRECT($A43&"!AA88")} -> 0 | R43: =I43*7% -> 0 | T43: =H43-SUM(J43:S43) -> 0 | V43: =IFERROR(J43/H43," ") | W43: =IFERROR(T43/H43," ") | X43: =IFERROR(T43/J43," ")
A44: 42 | B44: Октябрь 3 | E44: =H44-SUM(K44:Q44) -> 0 | F44: {=INDIRECT($A44&"!N84")} -> 0 | G44: {=INDIRECT($A44&"!P84")} -> 0 | H44: {=INDIRECT($A44&"!Q84")} -> 0 | I44: {=INDIRECT($A44&"!R84")} -> 0 | J44: {=INDIRECT($A44&"!T84")} -> 0 | K44: {=INDIRECT($A44&"!W84")} -> 0 | L44: {=INDIRECT($A44&"!U84")} -> 0 | M44: {=INDIRECT($A44&"!X84")} -> 0 | N44: {=INDIRECT($A44&"!AA87")} -> 0 | O44: {=INDIRECT($A44&"!AA89")} -> 0 | P44: {=INDIRECT($A44&"!AA88")} -> 0 | R44: =I44*7% -> 0 | T44: =H44-SUM(J44:S44) -> 0 | V44: =IFERROR(J44/H44," ") | W44: =IFERROR(T44/H44," ") | X44: =IFERROR(T44/J44," ")
A45: 43 | B45: Октябрь 4 | E45: =H45-SUM(K45:Q45) -> 0 | F45: {=INDIRECT($A45&"!N84")} -> 0 | G45: {=INDIRECT($A45&"!P84")} -> 0 | H45: {=INDIRECT($A45&"!Q84")} -> 0 | I45: {=INDIRECT($A45&"!R84")} -> 0 | J45: {=INDIRECT($A45&"!T84")} -> 0 | K45: {=INDIRECT($A45&"!W84")} -> 0 | L45: {=INDIRECT($A45&"!U84")} -> 0 | M45: {=INDIRECT($A45&"!X84")} -> 0 | N45: {=INDIRECT($A45&"!AA87")} -> 0 | O45: {=INDIRECT($A45&"!AA89")} -> 0 | P45: {=INDIRECT($A45&"!AA88")} -> 0 | R45: =I45*7% -> 0 | T45: =H45-SUM(J45:S45) -> 0 | V45: =IFERROR(J45/H45," ") | W45: =IFERROR(T45/H45," ") | X45: =IFERROR(T45/J45," ")
A46: 44 | B46: Октябрь 5 | E46: =H46-SUM(K46:Q46) -> 0 | F46: {=INDIRECT($A46&"!N84")} -> 0 | G46: {=INDIRECT($A46&"!P84")} -> 0 | H46: {=INDIRECT($A46&"!Q84")} -> 0 | I46: {=INDIRECT($A46&"!R84")} -> 0 | J46: {=INDIRECT($A46&"!T84")} -> 0 | K46: {=INDIRECT($A46&"!W84")} -> 0 | L46: {=INDIRECT($A46&"!U84")} -> 0 | M46: {=INDIRECT($A46&"!X84")} -> 0 | N46: {=INDIRECT($A46&"!AA87")} -> 0 | O46: {=INDIRECT($A46&"!AA89")} -> 0 | P46: {=INDIRECT($A46&"!AA88")} -> 0 | R46: =I46*7% -> 0 | T46: =H46-SUM(J46:S46) -> 0 | V46: =IFERROR(J46/H46," ") | W46: =IFERROR(T46/H46," ") | X46: =IFERROR(T46/J46," ")
A47: 45 | B47: Ноябрь 1 | E47: =H47-SUM(K47:Q47) -> 0 | F47: {=INDIRECT($A47&"!N84")} -> 0 | G47: {=INDIRECT($A47&"!P84")} -> 0 | H47: {=INDIRECT($A47&"!Q84")} -> 0 | I47: {=INDIRECT($A47&"!R84")} -> 0 | J47: {=INDIRECT($A47&"!T84")} -> 0 | K47: {=INDIRECT($A47&"!W84")} -> 0 | L47: {=INDIRECT($A47&"!U84")} -> 0 | M47: {=INDIRECT($A47&"!X84")} -> 0 | N47: {=INDIRECT($A47&"!AA87")} -> 0 | O47: {=INDIRECT($A47&"!AA89")} -> 0 | P47: {=INDIRECT($A47&"!AA88")} -> 0 | R47: =I47*7% -> 0 | T47: =H47-SUM(J47:S47) -> 0 | U47: =SUM(T47:T50) -> 0 | V47: =IFERROR(J47/H47," ") | W47: =IFERROR(T47/H47," ") | X47: =IFERROR(T47/J47," ")
A48: 46 | B48: Ноябрь 2 | E48: =H48-SUM(K48:Q48) -> 0 | F48: {=INDIRECT($A48&"!N84")} -> 0 | G48: {=INDIRECT($A48&"!P84")} -> 0 | H48: {=INDIRECT($A48&"!Q84")} -> 0 | I48: {=INDIRECT($A48&"!R84")} -> 0 | J48: {=INDIRECT($A48&"!T84")} -> 0 | K48: {=INDIRECT($A48&"!W84")} -> 0 | L48: {=INDIRECT($A48&"!U84")} -> 0 | M48: {=INDIRECT($A48&"!X84")} -> 0 | N48: {=INDIRECT($A48&"!AA87")} -> 0 | O48: {=INDIRECT($A48&"!AA89")} -> 0 | P48: {=INDIRECT($A48&"!AA88")} -> 0 | R48: =I48*7% -> 0 | T48: =H48-SUM(J48:S48) -> 0 | V48: =IFERROR(J48/H48," ") | W48: =IFERROR(T48/H48," ") | X48: =IFERROR(T48/J48," ")
A49: 47 | B49: Ноябрь 3 | E49: =H49-SUM(K49:Q49) -> 0 | F49: {=INDIRECT($A49&"!N84")} -> 0 | G49: {=INDIRECT($A49&"!P84")} -> 0 | H49: {=INDIRECT($A49&"!Q84")} -> 0 | I49: {=INDIRECT($A49&"!R84")} -> 0 | J49: {=INDIRECT($A49&"!T84")} -> 0 | K49: {=INDIRECT($A49&"!W84")} -> 0 | L49: {=INDIRECT($A49&"!U84")} -> 0 | M49: {=INDIRECT($A49&"!X84")} -> 0 | N49: {=INDIRECT($A49&"!AA87")} -> 0 | O49: {=INDIRECT($A49&"!AA89")} -> 0 | P49: {=INDIRECT($A49&"!AA88")} -> 0 | R49: =I49*7% -> 0 | T49: =H49-SUM(J49:S49) -> 0 | V49: =IFERROR(J49/H49," ") | W49: =IFERROR(T49/H49," ") | X49: =IFERROR(T49/J49," ")
A50: 48 | B50: Ноябрь 4 | E50: =H50-SUM(K50:Q50) -> 0 | F50: {=INDIRECT($A50&"!N84")} -> 0 | G50: {=INDIRECT($A50&"!P84")} -> 0 | H50: {=INDIRECT($A50&"!Q84")} -> 0 | I50: {=INDIRECT($A50&"!R84")} -> 0 | J50: {=INDIRECT($A50&"!T84")} -> 0 | K50: {=INDIRECT($A50&"!W84")} -> 0 | L50: {=INDIRECT($A50&"!U84")} -> 0 | M50: {=INDIRECT($A50&"!X84")} -> 0 | N50: {=INDIRECT($A50&"!AA87")} -> 0 | O50: {=INDIRECT($A50&"!AA89")} -> 0 | P50: {=INDIRECT($A50&"!AA88")} -> 0 | R50: =I50*7% -> 0 | T50: =H50-SUM(J50:S50) -> 0 | V50: =IFERROR(J50/H50," ") | W50: =IFERROR(T50/H50," ") | X50: =IFERROR(T50/J50," ")
A51: 49 | B51: Декабрь 1 | E51: =H51-SUM(K51:Q51) -> 0 | F51: {=INDIRECT($A51&"!N84")} -> 0 | G51: {=INDIRECT($A51&"!P84")} -> 0 | H51: {=INDIRECT($A51&"!Q84")} -> 0 | I51: {=INDIRECT($A51&"!R84")} -> 0 | J51: {=INDIRECT($A51&"!T84")} -> 0 | K51: {=INDIRECT($A51&"!W84")} -> 0 | L51: {=INDIRECT($A51&"!U84")} -> 0 | M51: {=INDIRECT($A51&"!X84")} -> 0 | N51: {=INDIRECT($A51&"!AA87")} -> 0 | O51: {=INDIRECT($A51&"!AA89")} -> 0 | P51: {=INDIRECT($A51&"!AA88")} -> 0 | R51: =I51*7% -> 0 | T51: =H51-SUM(J51:S51) -> 0 | U51: =SUM(T51:T55) -> 0 | V51: =IFERROR(J51/H51," ") | W51: =IFERROR(T51/H51," ") | X51: =IFERROR(T51/J51," ")
A52: 50 | B52: Декабрь 2 | E52: =H52-SUM(K52:Q52) -> 0 | F52: {=INDIRECT($A52&"!N84")} -> 0 | G52: {=INDIRECT($A52&"!P84")} -> 0 | H52: {=INDIRECT($A52&"!Q84")} -> 0 | I52: {=INDIRECT($A52&"!R84")} -> 0 | J52: {=INDIRECT($A52&"!T84")} -> 0 | K52: {=INDIRECT($A52&"!W84")} -> 0 | L52: {=INDIRECT($A52&"!U84")} -> 0 | M52: {=INDIRECT($A52&"!X84")} -> 0 | N52: {=INDIRECT($A52&"!AA87")} -> 0 | O52: {=INDIRECT($A52&"!AA89")} -> 0 | P52: {=INDIRECT($A52&"!AA88")} -> 0 | R52: =I52*7% -> 0 | T52: =H52-SUM(J52:S52) -> 0 | V52: =IFERROR(J52/H52," ") | W52: =IFERROR(T52/H52," ") | X52: =IFERROR(T52/J52," ")
A53: 51 | B53: Декабрь 3 | E53: =H53-SUM(K53:Q53) -> 0 | F53: {=INDIRECT($A53&"!N84")} -> 0 | G53: {=INDIRECT($A53&"!P84")} -> 0 | H53: {=INDIRECT($A53&"!Q84")} -> 0 | I53: {=INDIRECT($A53&"!R84")} -> 0 | J53: {=INDIRECT($A53&"!T84")} -> 0 | K53: {=INDIRECT($A53&"!W84")} -> 0 | L53: {=INDIRECT($A53&"!U84")} -> 0 | M53: {=INDIRECT($A53&"!X84")} -> 0 | N53: {=INDIRECT($A53&"!AA87")} -> 0 | O53: {=INDIRECT($A53&"!AA89")} -> 0 | P53: {=INDIRECT($A53&"!AA88")} -> 0 | R53: =I53*7% -> 0 | T53: =H53-SUM(J53:S53) -> 0 | V53: =IFERROR(J53/H53," ") | W53: =IFERROR(T53/H53," ") | X53: =IFERROR(T53/J53," ")
A54: 52 | B54: Декабрь 4 | E54: =H54-SUM(K54:Q54) -> 0 | F54: {=INDIRECT($A54&"!N84")} -> 0 | G54: {=INDIRECT($A54&"!P84")} -> 0 | H54: {=INDIRECT($A54&"!Q84")} -> 0 | I54: {=INDIRECT($A54&"!R84")} -> 0 | J54: {=INDIRECT($A54&"!T84")} -> 0 | K54: {=INDIRECT($A54&"!W84")} -> 0 | L54: {=INDIRECT($A54&"!U84")} -> 0 | M54: {=INDIRECT($A54&"!X84")} -> 0 | N54: {=INDIRECT($A54&"!AA87")} -> 0 | O54: {=INDIRECT($A54&"!AA89")} -> 0 | P54: {=INDIRECT($A54&"!AA88")} -> 0 | R54: =I54*7% -> 0 | T54: =H54-SUM(J54:S54) -> 0 | V54: =IFERROR(J54/H54," ") | W54: =IFERROR(T54/H54," ") | X54: =IFERROR(T54/J54," ") | AB54: ё
A55: 53 | B55: Декабрь 5 | E55: =H55-SUM(K55:Q55) -> 0 | F55: {=INDIRECT($A55&"!N84")} -> 0 | G55: {=INDIRECT($A55&"!P84")} -> 0 | H55: {=INDIRECT($A55&"!Q84")} -> 0 | I55: {=INDIRECT($A55&"!R84")} -> 0 | J55: {=INDIRECT($A55&"!T84")} -> 0 | K55: {=INDIRECT($A55&"!W84")} -> 0 | L55: {=INDIRECT($A55&"!U84")} -> 0 | M55: {=INDIRECT($A55&"!X84")} -> 0 | N55: {=INDIRECT($A55&"!AA87")} -> 0 | O55: {=INDIRECT($A55&"!AA89")} -> 0 | P55: {=INDIRECT($A55&"!AA88")} -> 0 | R55: =I55*7% -> 0 | T55: =H55-SUM(J55:S55) -> 0 | V55: =IFERROR(J55/H55," ") | W55: =IFERROR(T55/H55," ") | X55: =IFERROR(T55/J55," ")
B56: Итого | E56: =SUM(E3:E55) -> 235431.59 | F56: =SUM(F3:F55) -> 433673.64 | G56: =SUM(G3:G55) -> 3175.46 | H56: =SUM(H3:H55) -> 430498.18 | I56: =SUM(I3:I55) -> 292198.95 | J56: =SUM(J3:J55) -> 82224 | K56: =SUM(K3:K55) -> 48962.08 | L56: =SUM(L3:L55) -> 112559.37 | ... U56: =SUM(U3:U55) -> 132753.67 | V56: =IFERROR(J56/H56," ") -> 0.19099732 | W56: =IFERROR(T56/H56," ") -> 0.30837219 | X56: =IFERROR(T56/J56," ") -> 1.6145367
T57: Рентабельность
A58: Текущий № недели | B58: 53 | C58: =B58+2 -> 55 | D58: % от выручки за все время | G58: =-G56/F56 -> -0.0073222343 | J58: =J56/$H$56 -> 0.19099732 | K58: =K56/$H$56 -> 0.11373354 | L58: =L56/$H$56 -> 0.26146305 | M58: =M56/$H$56 -> 0.077921671 | N58: =N56/$H$56 -> 0 | O58: =O56/$H$56 -> 0 | P58: =P56/$H$56 -> 0 | Q58: =Q56/$H$56 -> 0 | ... S58: =S56/$H$56 -> 0 | T58: =T56/J56 -> 1.6145367
B59: вводить текущ номер недели | D59: % от выручки за последнюю неделю | G59: {=INDIRECT("G"&$C$58)/INDIRECT("F"&$C$58)} -> #DIV/0! | J59: {=INDIRECT("J"&$C$58)/INDIRECT("H"&$C$58)} -> #DIV/0! | K59: {=INDIRECT("K"&$C$58)/INDIRECT("H"&$C$58)} -> #DIV/0! | L59: {=INDIRECT("L"&$C$58)/INDIRECT("H"&$C$58)} -> #DIV/0! | M59: {=INDIRECT("M"&$C$58)/INDIRECT("H"&$C$58)} -> #DIV/0! | N59: {=INDIRECT("N"&$C$58)/INDIRECT("H"&$C$58)} -> #DIV/0! | O59: {=INDIRECT("O"&$C$58)/INDIRECT("H"&$C$58)} -> #DIV/0! | P59: {=INDIRECT("P"&$C$58)/INDIRECT("H"&$C$58)} -> #DIV/0! | Q59: {=INDIRECT("Q"&$C$58)/INDIRECT("H"&$C$58)} -> #DIV/0! | R59: {=INDIRECT("R"&$C$58)/INDIRECT("H"&$C$58)} -> #DIV/0! | S59: {=INDIRECT("S"&$C$58)/INDIRECT("H"&$C$58)} -> #DIV/0!
D60: Изменение относительно прошлой недели | G60: {=-INDIRECT("G"&$C$58)/INDIRECT("F"&$C$58)+INDIRECT("G"&($C$58-1))/INDIRECT("F"&($C$58-1))} -> #DIV/0! | H60: {=INDIRECT("H"&$C$58)/INDIRECT("H"&($C$58-1))-1} -> #DIV/0! | J60: {=INDIRECT("I"&$C$58)/INDIRECT("I"&($C$58-1))-1} -> #DIV/0! | K60: {=INDIRECT("J"&$C$58)/INDIRECT("J"&($C$58-1))-1} -> #DIV/0! | L60: {=INDIRECT("K"&$C$58)/INDIRECT("K"&($C$58-1))-1} -> #DIV/0! | M60: {=INDIRECT("K"&$C$58)/INDIRECT("K"&($C$58-1))-1} -> #DIV/0! | N60: {=INDIRECT("M"&$C$58)/INDIRECT("M"&($C$58-1))-1} -> #DIV/0! | O60: {=INDIRECT("N"&$C$58)/INDIRECT("N"&($C$58-1))-1} -> #DIV/0! | P60: {=IFERROR(INDIRECT("O"&$C$58)/INDIRECT("O"&($C$58-1))-1,0)} -> 0 | Q60: {=IFERROR(INDIRECT("P"&$C$58)/INDIRECT("P"&($C$58-1))-1,0)} -> 0 | R60: {=INDIRECT("Q"&$C$58)/INDIRECT("Q"&($C$58-1))-1} -> #DIV/0! | S60: {=IFERROR(INDIRECT("R"&$C$58)/INDIRECT("R"&($C$58-1))-1,0)} -> 0 | T60: {=INDIRECT("S"&$C$58)/INDIRECT("S"&($C$58-1))-1} -> #DIV/0! | V60: {=INDIRECT("U"&$C$58)/INDIRECT("U"&($C$58-1))-1} -> #DIV/0! | W60: {=INDIRECT("V"&$C$58)/INDIRECT("V"&($C$58-1))-1} -> #VALUE! | X60: {=INDIRECT("W"&$C$58)/INDIRECT("W"&($C$58-1))-1} -> #VALUE!
V76: ё

Sheet ДинамПродаж
A1: Динамика по продажам (Выручка (продажи-возвраты) до вычета логистики, комиссии) | BH1: 0.8 | BI1: A
BH2: 0.15 | BI2: B
BG3: ТОП | BH3: =1-BH1-BH2 -> 0.05 | BI3: C
F4: 01.01-04.01 | G4: 05.01-11.01 | H4: 12.01-18.01 | BG4: Сумма за 4 нед | BL4: Показатели за последюю неделю
A5: Артикул ВБ | B5: Артикул поставщика | C5: Наименование | D5: ШК | F5: 1 | G5: 2 | H5: 3 | I5: 4 | J5: 5 | K5: 6 | L5: 7 | M5: 8 | N5: 9 | O5: 10 | P5: 11 | Q5: 12 | R5: 13 | S5: 14 | T5: 15 | U5: 16 | V5: 17 | W5: 18 | X5: 19 | Y5: 20 | Z5: 21 | AA5: 22 | AB5: 23 | AC5: 24 | AD5: 25 | AE5: 26 | AF5: 27 | AG5: 28 | AH5: 29 | AI5: 30 | AJ5: 31 | AK5: 32 | AL5: 33 | AM5: 34 | AN5: 35 | AO5: 36 | AP5: 37 | AQ5: 38 | AR5: 39 | AS5: 40 | AT5: 41 | AU5: 42 | AV5: 43 | AW5: 44 | AX5: 45 | AY5: 46 | AZ5: 47 | BA5: 48 | BB5: 49 | BC5: 50 | BD5: 51 | BE5: 52 | BF5: 53 | BH5: ABC | BI5: Выручка на 1 ед | BJ5: Себестоимость остатков | BK5: Оборачиваемость, дн | BL5: % выкупа | BM5: Скорость продаж | BN5: Прибыль на 1 ед | BO5: Маржинальность, % | BP5: Рентабельность, %
A6: ='Сводный за нед'!A3 -> 169112569 | B6: ='Сводный за нед'!B3 -> ACRF1BN101PN | C6: ='Сводный за нед'!C3 -> Бандаж для лица розовый | D6: ='Сводный за нед'!D3 -> 2038161736993 | F6: {=IFERROR(_xlfn.XLOOKUP($A6,INDIRECT(F$5&"!$A:$A"),INDIRECT(F$5&"!$Q:$Q"),,0),0)} -> 0 | G6: {=IFERROR(_xlfn.XLOOKUP($A6,INDIRECT(G$5&"!$A:$A"),INDIRECT(G$5&"!$Q:$Q"),,0),0)} -> 1251 | H6: {=IFERROR(_xlfn.XLOOKUP($A6,INDIRECT(H$5&"!$A:$A"),INDIRECT(H$5&"!$Q:$Q"),,0),0)} -> 604 | I6: {=IFERROR(_xlfn.XLOOKUP($A6,INDIRECT(I$5&"!$A:$A"),INDIRECT(I$5&"!$Q:$Q"),,0),0)} -> 0 | J6: {=IFERROR(_xlfn.XLOOKUP($A6,INDIRECT(J$5&"!$A:$A"),INDIRECT(J$5&"!$Q:$Q"),,0),0)} -> 0 | K6: {=IFERROR(_xlfn.XLOOKUP($A6,INDIRECT(K$5&"!$A:$A"),INDIRECT(K$5&"!$Q:$Q"),,0),0)} -> 0 | L6: {=IFERROR(_xlfn.XLOOKUP($A6,INDIRECT(L$5&"!$A:$A"),INDIRECT(L$5&"!$Q:$Q"),,0),0)} -> 0 | M6: {=IFERROR(_xlfn.XLOOKUP($A6,INDIRECT(M$5&"!$A:$A"),INDIRECT(M$5&"!$Q:$Q"),,0),0)} -> 0 | ... BF6: {=IFERROR(_xlfn.XLOOKUP($A6,INDIRECT(BF$5&"!$A:$A"),INDIRECT(BF$5&"!$Q:$Q"),,0),0)} -> 0 | BG6: =SUM(F6:BF6) -> 1855 | BH6: =BG6/$BG$86 -> 0.0057713027 | BI6: =_xlfn.XLOOKUP($A6,Текущая!$A:$A,Текущая!$AI:$AI,0,0) -> 604 | BJ6: =_xlfn.XLOOKUP($A6,Текущая!$A:$A,Текущая!$G:$G,0,0) -> 17094 | BK6: =_xlfn.XLOOKUP($A6,Текущая!$A:$A,Текущая!$H:$H,0) -> 1560 | BL6: =_xlfn.XLOOKUP($A6,Текущая!$A:$A,Текущая!$I:$I,0,0) -> 0 | BM6: =_xlfn.XLOOKUP($A6,Текущая!$A:$A,Текущая!$J:$J,0,0) -> 0.1 | BN6: =_xlfn.XLOOKUP($A6,Текущая!$A:$A,Текущая!$AP:$AP,0,0) -> -127.71328 | BO6: =_xlfn.XLOOKUP($A6,Текущая!$A:$A,Текущая!$AF:$AF,0,0) -> -0.21144583 | BP6: =_xlfn.XLOOKUP($A6,Текущая!$A:$A,Текущая!$AG:$AG,0,0) -> -1.1505701
A7: ='Сводный за нед'!A4 -> 169153168 | B7: ='Сводный за нед'!B4 -> ACRF1BN101BC | C7: ='Сводный за нед'!C4 -> Бандаж для лица черный | D7: ='Сводный за нед'!D4 -> 2038162681926 | F7: {=IFERROR(_xlfn.XLOOKUP($A7,INDIRECT(F$5&"!$A:$A"),INDIRECT(F$5&"!$Q:$Q"),,0),0)} -> 0 | G7: {=IFERROR(_xlfn.XLOOKUP($A7,INDIRECT(G$5&"!$A:$A"),INDIRECT(G$5&"!$Q:$Q"),,0),0)} -> 1282 | H7: {=IFERROR(_xlfn.XLOOKUP($A7,INDIRECT(H$5&"!$A:$A"),INDIRECT(H$5&"!$Q:$Q"),,0),0)} -> 1187.86 | I7: {=IFERROR(_xlfn.XLOOKUP($A7,INDIRECT(I$5&"!$A:$A"),INDIRECT(I$5&"!$Q:$Q"),,0),0)} -> 0 | J7: {=IFERROR(_xlfn.XLOOKUP($A7,INDIRECT(J$5&"!$A:$A"),INDIRECT(J$5&"!$Q:$Q"),,0),0)} -> 0 | K7: {=IFERROR(_xlfn.XLOOKUP($A7,INDIRECT(K$5&"!$A:$A"),INDIRECT(K$5&"!$Q:$Q"),,0),0)} -> 0 | L7: {=IFERROR(_xlfn.XLOOKUP($A7,INDIRECT(L$5&"!$A:$A"),INDIRECT(L$5&"!$Q:$Q"),,0),0)} -> 0 | M7: {=IFERROR(_xlfn.XLOOKUP($A7,INDIRECT(M$5&"!$A:$A"),INDIRECT(M$5&"!$Q:$Q"),,0),0)} -> 0 | ... BF7: {=IFERROR(_xlfn.XLOOKUP($A7,INDIRECT(BF$5&"!$A:$A"),INDIRECT(BF$5&"!$Q:$Q"),,0),0)} -> 0 | BG7: =SUM(F7:BF7) -> 2469.86 | BH7: =BG7/$BG$86 -> 0.007684264 | BI7: =_xlfn.XLOOKUP($A7,Текущая!$A:$A,Текущая!$AI:$AI,0,0) -> 593.93 | BJ7: =_xlfn.XLOOKUP($A7,Текущая!$A:$A,Текущая!$G:$G,0,0) -> 20430 | BK7: =_xlfn.XLOOKUP($A7,Текущая!$A:$A,Текущая!$H:$H,0) -> 222.72727 | BL7: =_xlfn.XLOOKUP($A7,Текущая!$A:$A,Текущая!$I:$I,0,0) -> 100 | BM7: =_xlfn.XLOOKUP($A7,Текущая!$A:$A,Текущая!$J:$J,0,0) -> 1.1 | BN7: =_xlfn.XLOOKUP($A7,Текущая!$A:$A,Текущая!$AP:$AP,0,0) -> 63.30803 | BO7: =_xlfn.XLOOKUP($A7,Текущая!$A:$A,Текущая!$AF:$AF,0,0) -> 0.10659174 | BP7: =_xlfn.XLOOKUP($A7,Текущая!$A:$A,Текущая!$AG:$AG,0,0) -> 0.70342255
A8: ='Сводный за нед'!A5 -> 169395410 | B8: ='Сводный за нед'!B5 -> ACRF1BN201GR | C8: ='Сводный за нед'!C5 -> Бандаж для лица серый | D8: ='Сводный за нед'!D5 -> 2038172050200 | F8: {=IFERROR(_xlfn.XLOOKUP($A8,INDIRECT(F$5&"!$A:$A"),INDIRECT(F$5&"!$Q:$Q"),,0),0)} -> 0 | G8: {=IFERROR(_xlfn.XLOOKUP($A8,INDIRECT(G$5&"!$A:$A"),INDIRECT(G$5&"!$Q:$Q"),,0),0)} -> 5864.7 | H8: {=IFERROR(_xlfn.XLOOKUP($A8,INDIRECT(H$5&"!$A:$A"),INDIRECT(H$5&"!$Q:$Q"),,0),0)} -> 5651 | I8: {=IFERROR(_xlfn.XLOOKUP($A8,INDIRECT(I$5&"!$A:$A"),INDIRECT(I$5&"!$Q:$Q"),,0),0)} -> 0 | J8: {=IFERROR(_xlfn.XLOOKUP($A8,INDIRECT(J$5&"!$A:$A"),INDIRECT(J$5&"!$Q:$Q"),,0),0)} -> 0 | K8: {=IFERROR(_xlfn.XLOOKUP($A8,INDIRECT(K$5&"!$A:$A"),INDIRECT(K$5&"!$Q:$Q"),,0),0)} -> 0 | L8: {=IFERROR(_xlfn.XLOOKUP($A8,INDIRECT(L$5&"!$A:$A"),INDIRECT(L$5&"!$Q:$Q"),,0),0)} -> 0 | M8: {=IFERROR(_xlfn.XLOOKUP($A8,INDIRECT(M$5&"!$A:$A"),INDIRECT(M$5&"!$Q:$Q"),,0),0)} -> 0 | ... BF8: {=IFERROR(_xlfn.XLOOKUP($A8,INDIRECT(BF$5&"!$A:$A"),INDIRECT(BF$5&"!$Q:$Q"),,0),0)} -> 0 | BG8: =SUM(F8:BF8) -> 11515.7 | BH8: =BG8/$BG$86 -> 0.035827812 | BI8: =_xlfn.XLOOKUP($A8,Текущая!$A:$A,Текущая!$AI:$AI,0,0) -> 941.83333 | BJ8: =_xlfn.XLOOKUP($A8,Текущая!$A:$A,Текущая!$G:$G,0,0) -> 42642 | BK8: =_xlfn.XLOOKUP($A8,Текущая!$A:$A,Текущая!$H:$H,0) -> 341.42857 | BL8: =_xlfn.XLOOKUP($A8,Текущая!$A:$A,Текущая!$I:$I,0,0) -> 100 | BM8: =_xlfn.XLOOKUP($A8,Текущая!$A:$A,Текущая!$J:$J,0,0) -> 0.7 | BN8: =_xlfn.XLOOKUP($A8,Текущая!$A:$A,Текущая!$AP:$AP,0,0) -> 298.85967 | BO8: =_xlfn.XLOOKUP($A8,Текущая!$A:$A,Текущая!$AF:$AF,0,0) -> 0.31731694 | BP8: =_xlfn.XLOOKUP($A8,Текущая!$A:$A,Текущая!$AG:$AG,0,0) -> 1.4507751
A9: ='Сводный за нед'!A6 -> 172832355 | B9: ='Сводный за нед'!B6 -> AHMA7BW101BG | C9: ='Сводный за нед'!C6 -> Мешки 7 шт. | D9: ='Сводный за нед'!D6 -> 2038337652454 | F9: {=IFERROR(_xlfn.XLOOKUP($A9,INDIRECT(F$5&"!$A:$A"),INDIRECT(F$5&"!$Q:$Q"),,0),0)} -> 0 | G9: {=IFERROR(_xlfn.XLOOKUP($A9,INDIRECT(G$5&"!$A:$A"),INDIRECT(G$5&"!$Q:$Q"),,0),0)} -> 1684.61 | H9: {=IFERROR(_xlfn.XLOOKUP($A9,INDIRECT(H$5&"!$A:$A"),INDIRECT(H$5&"!$Q:$Q"),,0),0)} -> 1652 | I9: {=IFERROR(_xlfn.XLOOKUP($A9,INDIRECT(I$5&"!$A:$A"),INDIRECT(I$5&"!$Q:$Q"),,0),0)} -> 0 | J9: {=IFERROR(_xlfn.XLOOKUP($A9,INDIRECT(J$5&"!$A:$A"),INDIRECT(J$5&"!$Q:$Q"),,0),0)} -> 0 | K9: {=IFERROR(_xlfn.XLOOKUP($A9,INDIRECT(K$5&"!$A:$A"),INDIRECT(K$5&"!$Q:$Q"),,0),0)} -> 0 | L9: {=IFERROR(_xlfn.XLOOKUP($A9,INDIRECT(L$5&"!$A:$A"),INDIRECT(L$5&"!$Q:$Q"),,0),0)} -> 0 | M9: {=IFERROR(_xlfn.XLOOKUP($A9,INDIRECT(M$5&"!$A:$A"),INDIRECT(M$5&"!$Q:$Q"),,0),0)} -> 0 | ... BF9: {=IFERROR(_xlfn.XLOOKUP($A9,INDIRECT(BF$5&"!$A:$A"),INDIRECT(BF$5&"!$Q:$Q"),,0),0)} -> 0 | BG9: =SUM(F9:BF9) -> 3336.61 | BH9: =BG9/$BG$86 -> 0.010380909 | BI9: =_xlfn.XLOOKUP($A9,Текущая!$A:$A,Текущая!$AI:$AI,0,0) -> 1652 | BJ9: =_xlfn.XLOOKUP($A9,Текущая!$A:$A,Текущая!$G:$G,0,0) -> 50250 | BK9: =_xlfn.XLOOKUP($A9,Текущая!$A:$A,Текущая!$H:$H,0) -> 1640 | BL9: =_xlfn.XLOOKUP($A9,Текущая!$A:$A,Текущая!$I:$I,0,0) -> 100 | BM9: =_xlfn.XLOOKUP($A9,Текущая!$A:$A,Текущая!$J:$J,0,0) -> 0.1 | BN9: =_xlfn.XLOOKUP($A9,Текущая!$A:$A,Текущая!$AP:$AP,0,0) -> -184.62993 | BO9: =_xlfn.XLOOKUP($A9,Текущая!$A:$A,Текущая!$AF:$AF,0,0) -> -0.11176146 | BP9: =_xlfn.XLOOKUP($A9,Текущая!$A:$A,Текущая!$AG:$AG,0,0) -> -0.49234649
A10: ='Сводный за нед'!A7 -> 176500218 | B10: ='Сводный за нед'!B7 -> AHMA1BW101BG | C10: ='Сводный за нед'!C7 -> Мешок для бюстгалтеров | D10: ='Сводный за нед'!D7 -> 2038597850744 | F10: {=IFERROR(_xlfn.XLOOKUP($A10,INDIRECT(F$5&"!$A:$A"),INDIRECT(F$5&"!$Q:$Q"),,0),0)} -> 987 | G10: {=IFERROR(_xlfn.XLOOKUP($A10,INDIRECT(G$5&"!$A:$A"),INDIRECT(G$5&"!$Q:$Q"),,0),0)} -> 2315 | H10: {=IFERROR(_xlfn.XLOOKUP($A10,INDIRECT(H$5&"!$A:$A"),INDIRECT(H$5&"!$Q:$Q"),,0),0)} -> 3642.74 | I10: {=IFERROR(_xlfn.XLOOKUP($A10,INDIRECT(I$5&"!$A:$A"),INDIRECT(I$5&"!$Q:$Q"),,0),0)} -> 0 | J10: {=IFERROR(_xlfn.XLOOKUP($A10,INDIRECT(J$5&"!$A:$A"),INDIRECT(J$5&"!$Q:$Q"),,0),0)} -> 0 | K10: {=IFERROR(_xlfn.XLOOKUP($A10,INDIRECT(K$5&"!$A:$A"),INDIRECT(K$5&"!$Q:$Q"),,0),0)} -> 0 | L10: {=IFERROR(_xlfn.XLOOKUP($A10,INDIRECT(L$5&"!$A:$A"),INDIRECT(L$5&"!$Q:$Q"),,0),0)} -> 0 | M10: {=IFERROR(_xlfn.XLOOKUP($A10,INDIRECT(M$5&"!$A:$A"),INDIRECT(M$5&"!$Q:$Q"),,0),0)} -> 0 | ... BF10: {=IFERROR(_xlfn.XLOOKUP($A10,INDIRECT(BF$5&"!$A:$A"),INDIRECT(BF$5&"!$Q:$Q"),,0),0)} -> 0 | BG10: =SUM(F10:BF10) -> 6944.74 | BH10: =BG10/$BG$86 -> 0.021606575 | BI10: =_xlfn.XLOOKUP($A10,Текущая!$A:$A,Текущая!$AI:$AI,0,0) -> 455.3425 | BJ10: =_xlfn.XLOOKUP($A10,Текущая!$A:$A,Текущая!$G:$G,0,0) -> 23998 | BK10: =_xlfn.XLOOKUP($A10,Текущая!$A:$A,Текущая!$H:$H,0) -> 658.33333 | BL10: =_xlfn.XLOOKUP($A10,Текущая!$A:$A,Текущая!$I:$I,0,0) -> 100 | BM10: =_xlfn.XLOOKUP($A10,Текущая!$A:$A,Текущая!$J:$J,0,0) -> 0.6 | BN10: =_xlfn.XLOOKUP($A10,Текущая!$A:$A,Текущая!$AP:$AP,0,0) -> 127.09367 | BO10: =_xlfn.XLOOKUP($A10,Текущая!$A:$A,Текущая!$AF:$AF,0,0) -> 0.27911664 | BP10: =_xlfn.XLOOKUP($A10,Текущая!$A:$A,Текущая!$AG:$AG,0,0) -> 1.7900517
A11: ='Сводный за нед'!A8 -> 177404837 | B11: ='Сводный за нед'!B8 -> AHMA3BW101BG | C11: ='Сводный за нед'!C8 -> Мешки 3 шт. | D11: ='Сводный за нед'!D8 -> 2038627692689 | F11: {=IFERROR(_xlfn.XLOOKUP($A11,INDIRECT(F$5&"!$A:$A"),INDIRECT(F$5&"!$Q:$Q"),,0),0)} -> 0 | G11: {=IFERROR(_xlfn.XLOOKUP($A11,INDIRECT(G$5&"!$A:$A"),INDIRECT(G$5&"!$Q:$Q"),,0),0)} -> 1103 | H11: {=IFERROR(_xlfn.XLOOKUP($A11,INDIRECT(H$5&"!$A:$A"),INDIRECT(H$5&"!$Q:$Q"),,0),0)} -> 993 | I11: {=IFERROR(_xlfn.XLOOKUP($A11,INDIRECT(I$5&"!$A:$A"),INDIRECT(I$5&"!$Q:$Q"),,0),0)} -> 0 | J11: {=IFERROR(_xlfn.XLOOKUP($A11,INDIRECT(J$5&"!$A:$A"),INDIRECT(J$5&"!$Q:$Q"),,0),0)} -> 0 | K11: {=IFERROR(_xlfn.XLOOKUP($A11,INDIRECT(K$5&"!$A:$A"),INDIRECT(K$5&"!$Q:$Q"),,0),0)} -> 0 | L11: {=IFERROR(_xlfn.XLOOKUP($A11,INDIRECT(L$5&"!$A:$A"),INDIRECT(L$5&"!$Q:$Q"),,0),0)} -> 0 | M11: {=IFERROR(_xlfn.XLOOKUP($A11,INDIRECT(M$5&"!$A:$A"),INDIRECT(M$5&"!$Q:$Q"),,0),0)} -> 0 | ... BF11: {=IFERROR(_xlfn.XLOOKUP($A11,INDIRECT(BF$5&"!$A:$A"),INDIRECT(BF$5&"!$Q:$Q"),,0),0)} -> 0 | BG11: =SUM(F11:BF11) -> 2096 | BH11: =BG11/$BG$86 -> 0.0065211054 | BI11: =_xlfn.XLOOKUP($A11,Текущая!$A:$A,Текущая!$AI:$AI,0,0) -> 993 | BJ11: =_xlfn.XLOOKUP($A11,Текущая!$A:$A,Текущая!$G:$G,0,0) -> 20584 | BK11: =_xlfn.XLOOKUP($A11,Текущая!$A:$A,Текущая!$H:$H,0) -> 556.66667 | BL11: =_xlfn.XLOOKUP($A11,Текущая!$A:$A,Текущая!$I:$I,0,0) -> 100 | BM11: =_xlfn.XLOOKUP($A11,Текущая!$A:$A,Текущая!$J:$J,0,0) -> 0.3 | BN11: =_xlfn.XLOOKUP($A11,Текущая!$A:$A,Текущая!$AP:$AP,0,0) -> -3.8144262 | BO11: =_xlfn.XLOOKUP($A11,Текущая!$A:$A,Текущая!$AF:$AF,0,0) -> -0.0038413154 | BP11: =_xlfn.XLOOKUP($A11,Текущая!$A:$A,Текущая!$AG:$AG,0,0) -> -0.022978471
