Workbook
Name _12_18__15_3__утолщенный_шелк_7_100шт: #REF!
Name _14_20__17_3___утолщенный_шелк_7_100шт: #REF!
Name _169112569_2038161736993_ACRF1BN101PN_Маска_бандаж_для_лица_розовая: #REF!
Name _169153168_2038162681926_ACRF1BN101BC_Маска_бандаж_для_лица_черная: #REF!
Name _169395410_2038172050200_ACRF1BN201GR_Маска_бандаж_для_лица_серая: #REF!
Name _170899505_2038224716238_AHMA6BW101BG_Набор_мешков_для_стирки_6_шт.: #REF!
Name _172832355_2038337652454_AHMA7BW101BG_Набор_мешков_для_стирки_7_шт.: #REF!
Name _173605843_2038430289250_ACRH1MS101RJ_Массажер_для_пальцев_суставов: #REF!
Name _176170511_2038586639107_ACRF1SK101WH_Скребок_Гуаша_белый_короб: #REF!
Name _176500218_2038597850744_AHMA1BW101BG_Мешок_для_стирки_бюстгалтеров: #REF!
Name _176709293_2038605982115_ACRF2RS201NF_Комплект_Гуаша_роллер_и_скребок_бол_нефрит_прем: #REF!
Name _176721350_2038606201642_AHMA3BW201WH_Комплект_мешков_сетка_мелкая_на_шнурке_3_шт.: #REF!
Name _176723275_2038606256161_AHMA3BW202WH_Комплект_мешков_сетка_крупная_на_шнурке_3_шт.: #REF!
Name _177404837_2038627692689_AHMA3BW101BG_Комплект_мешков_для_стирки_3_шт.: #REF!
Name _177405495_2038627713902_AHMA3BW102BG_Комплект_мешков_для_деликатной_стирки_3_шт.: #REF!
Name _18_27__23_4___утолщенный_шелк_7_100шт: #REF!
Name _186800214_2038890789598_ACRA7TB101BC_Таблетница_круглая_7_2: #REF!
Name _186826338_2038891723249_ACRA7TB201BC_Таблетница_прямоугольная_7_2_черная: #REF!
Name _188194883_2038931439581_AHMA3BW211WH_Комплект_мешков_сетка_мелкая_на_шнурке_3_шт._с_шаром: #REF!
Name _199452263_2039291528267_AHMA3BW212WH_Комплект_мешков_сетка_крупная_на_шнурке_3_шт._с_шаром: #REF!
Name _20_30__26_4___утолщенный_шелк_7_100шт: #REF!
Name _20_34__30_4___утолщенный_шелк_7_100шт: #REF!
Name _200946531_2039323172727_AHMA3BW221WH_Комплект_мешков_сетка_крупная_на_шнурке_3_шт._с_цилиндром: #REF!
Name _200953158_2039323305576_ACRA7TB301BC_Таблетница_прямоугольная_7_3: #REF!
Name _204260887_2039399347548_AHMA3BW222WH_Комплект_мешков_мелкая_сетка_на_шнурке_3_шт._с_цилиндром: #REF!
Name _204615141_2039404446068_AHMA2BW201WH_Комплект_мешков_2_шт._серый: #REF!
Name _205841460_2039422231875_ACRF1SK202NF_Скребок_Гуаша_нефрит: #REF!
Name _22_34__30_4___утолщенный_шелк_7_100шт: #REF!
Name _220252787_2039735724354_ACRL1MS101RJ_Массажер_для_ног: #REF!
Name _223420736_2039813223373_ACRB1MS101RJ_Массажер_для_тела: #REF!
Name _223671295_2039818580389_ACRB1MS102RJ_Массажер_мяч_оранжевый: #REF!
Name _236072834_2040278804649_ACRB1MS102BL_Массажер_мяч_голубой: #REF!
Name _236072835_2040278804496_ACRB1MS102WH_Массажер_мяч_белый: #REF!
Name _236072836_2040278810534_ACRB1MS102PN_Массажер_мяч_розовый: #REF!
Name _236074677_2040278862540_AHMA2BW202WH_Комплект_мешков_2_шт._розовый: #REF!
Name _236929187_2040335626849_AHMA1BW112WH_Мешок_большой_крупная_сетка_60_80: #REF!
Name _236929188_2040335648124_AHMA1BW111WH_Мешок_большой_мелкая_сетка_60_80: #REF!
Name _239233529_2040478696884_AHMA1BW302WH_Мешок_для_стирки_обуви_XL___35_см: #REF!
Name _239235150_2040478720961_AHMA1BW301WH_Мешок_для_стирки_обуви_L___30_см: #REF!
Name _24_34__30_4___утолщенный_шелк_7_100шт: #REF!
Name _248267432_2040797652776_AAND1ST201BL_Палочка_для_жевания: #REF!
Name _251407392_2040900511679_AAND1BL102BL_Мяч_шина_синий: #REF!
Name _251516159_2040902555480_AAND1BL102RD_Мяч_шина_красный: #REF!
Name _251537223_2040903539366_AAND1BL101RD_Мяч_регби_красный: #REF!
Name _251537413_2040903547941_AAND1BL101BL_Мяч_регби_синий: #REF!
Name _253681275_2040957863936_ACRA7TB401CL_Таблетница_прямоугольная_7_2_цветная: #REF!
Name A1016__мелкое_отверстие_30_40: #REF!
Name A1016__толстое_отверстие_30_40: #REF!
Name A1016__толстое_отверстие_40_50: #REF!
Name A1016__толстое_отверстие_60_80: #REF!
Name A1016__тонкое_отверстие_40_50: #REF!
Name A1016__тонкое_отверстие_50_60: #REF!
Name A1016__тонкое_отверстие_60_80: #REF!
Name A1016_толстое_отверстие_50_60: #REF!
Name Бандаж_лайкра_розовый: #REF!
Name Бандаж_лайкра_черный: #REF!
Name Бандаж_силикон_серый: #REF!
Name Бежевые_трусики_20_20: #REF!
Name Бежевый_Бюстгальтер_Раковина_18_16: #REF!
Name Белый__скребок_Гуаша_в_коробке: #REF!

Sheet Юнит
F1: Себестоимость до ВБ | G1: % себестоимости от цены продажи | H1: Себестоимость Карго | I1: Инд обработка | J1: Доставка | K1: Параметры для логистики | L1: Параметры с упаковкой для расчета логистики | S1: Цена продажи на ВБ | T1: Цена на ВБ | V1: Расходы ВБ | W1: % Расходов ВБ в выручке | X1: доставка, руб | Y1: возврат, руб | Z1: Логистика, руб | AB1: хранение, руб | AC1: Стоимость услуг ВБ за одну проданную единицу | AD1: % расходов на услуги (от цены продажи) | AE1: Комиссия ВБ | AG1: Кэшбэк | AH1: Скидка Клуба | AI1: Себестоимость товара на ВБ | AJ1: Маржинальность | AK1: ФИНАНСЫ | AN1: ЖЕЛАЕМАЯ ЦЕНА | AO1: ФИНАНСЫ | AR1: ЖЕЛАЕМАЯ МАРЖА | AS1: Участие в акиции | AT1: Цена акции | AU1: Маржа акции | AV1: ФИНАНСЫ | AY1: Остатки | AZ1: Оборачиваемость | BA1: Себестоимость Карго х на … | BC1: Цена продажи на OZON | BD1: Цена на OZON | BF1: Расходы OZON | BG1: % Расходов OZON в выроучке | BH1: Ссылка на справочник | BL1: Справочник FBO | BM1: По среднее время доставки | BQ1: Ссылка на справочник | BR1: Про обработку возврата | BS1: Пояснение к расчёту логистики с учётом выкупа | BV1: Себестоимость товара на ОЗОН | BW1: Маржинальность | BX1: ФИНАНСЫ | CA1: Желаемая цена | CB1: ФИНАНСЫ | CE1: Желаемая маржа | CF1: Участие в акиции | CG1: Цена акции | CH1: Маржа акции | CI1: ФИНАНСЫ | CL1: Остатки | CM1: Оборачиваемость | CN1: Себестоимость Карго х на … | CO1: Мин. Цены | CP1: Платное размещение, шт.
T2: Цена в карточке | U2: Скидка | BD2: Цена в карточке | BE2: Скидка | BH2: Комиссия OZON | BJ2: Эквайринг | BK2: хранение | BL2: Логистика доставки | BR2: Выкуп | BS2: ЛОГИСТИКА ИТОГО | BT2: % Логистики в выручке | BU2: Мои акции
A3: Код WB | B3: Код OZON | C3: Арт. Поставщика | D3: Номенклатура | E3: Штрихкод | J3: 8 | K3: Обьем, л | L3: Длина | M3: Ширина | N3: Высота | O3: Вес | P3: Упаковка | Q3: Сколько в короб ВБ | T3: руб. | U3: 0.3 | Z3: руб | AA3: % | AC3: руб. | AD3: % | AE3: % | AF3: руб | AH3: 0.03 | AK3: Прибыль | AL3: Чистая прибыль | AM3: Рентабельность вложенных инвестиций | AO3: Прибыль | AP3: Чистая прибыль | AQ3: Рентабельность вложенных инвестиций | AV3: Прибыль | AW3: Чистая прибыль | AX3: Рентабельность вложенных инвестиций | BD3: руб. | BE3: ='[1]Рассчет акции'!$J$4 -> Скидка | BH3: % | BI3: руб. | BJ3: 0.02 | BL3: 1 | BM3: часы | BN3: 35 | BO3: % | BP3: 25 | BQ3: итого | BR3: 0.85 | BS3: ИТОГО | BT3: % | BX3: Прибыль | BY3: Чистая прибыль | BZ3: Рентабельность вложенных инвестиций | CB3: Прибыль | CC3: Чистая прибыль | CD3: Рентабельность вложенных инвестиций | CI3: Прибыль | CJ3: Чистая прибыль | CK3: Рентабельность вложенных инвестиций
A4: 1 | B4: 2 | C4: 3 | D4: 4 | E4: 5 | F4: 6 | G4: 7 | H4: 8 | I4: 9 | J4: 10 | K4: 11 | L4: 12 | M4: 13 | N4: 14 | O4: 15 | P4: 16 | Q4: 17 | R4: 18 | S4: 19 | T4: 20 | U4: 21 | V4: 22 | W4: 23 | X4: 24 | Y4: 28 | AB4: 25 | AC4: 29 | AD4: 30 | AE4: 31 | AF4: 32 | AG4: 33 | AH4: 34 | AI4: 35 | AJ4: 36 | AK4: 37 | AL4: 38 | AM4: 39 | AN4: 40 | AO4: 41 | AP4: 42 | AQ4: 43 | AR4: 44 | AS4: 45 | AT4: 46 | AU4: 47 | AV4: 48 | AW4: 49 | AX4: 50 | AY4: 51 | AZ4: 52 | BA4: 53 | BB4: 54 | BC4: 55 | BD4: 56 | BE4: 57 | BF4: 58 | BG4: 59 | BH4: 60 | BI4: 61 | BJ4: 62 | BL4: 63 | BM4: 64 | BN4: 65 | BO4: 66 | BP4: 67 | BQ4: 68 | BR4: 69 | BS4: 70 | BT4: 71 | BU4: 72 | BV4: 73 | BW4: 74 | BX4: 75 | BY4: 76 | BZ4: 77 | CA4: 78 | CB4: 79 | CC4: 80 | CD4: 81 | CE4: 82 | CF4: 83 | CG4: 84 | CH4: 85 | CI4: 86 | CJ4: 87 | CK4: 88 | CL4: 89 | CM4: 90 | CN4: 91 | CO4: 92 | CP4: 93
A5: 169112569 | C5: ACRF1BN101PN | D5: Бандаж для лица розовый | E5: 2038161736993 | F5: =SUM(H5:J5) -> 126 | G5: =IFERROR(F5/S5*100%,0) -> 0.1689461 | H5: =IF(_xlfn.XLOOKUP($C5,'Юнит Карго'!$A:$A,'Юнит Карго'!$G:$G)=0,_xlfn.XLOOKUP(E5,'Себес 1С текущ'!G:G,'Себес 1С текущ'!H:H,0),_xlfn.XLOOKUP($C5,'Юнит Карго'!$A:$A,'Юнит Карго'!$P:$P,0,0)) -> 104 | I5: 14 | J5: =$J$3 -> 8 | K5: =(L5*M5*N5)/1000 -> 0.336 | L5: 14 | M5: 12 | N5: 2 | O5: =_xlfn.XLOOKUP($C5,'Юнит Карго'!$A:$A,'Юнит Карго'!$T:$T,0,0) -> 0.04 | P5: своя | S5: =T5-(T5*U5) -> 745.8 | T5: =_xlfn.XLOOKUP(E5,'[2]Рассчет акции'!$D:$D,'[2]Рассчет акции'!$G:$G,0) -> 1243 | U5: =_xlfn.XLOOKUP(E5,'[2]Рассчет акции'!$D:$D,'[2]Рассчет акции'!$F:$F,0) -> 0.4 | V5: =AC5+AF5+AH5+AG5 -> 402.41624 | W5: =IFERROR(V5/S5,0) -> 0.53957662 | X5: =IF(K5>1,('Тарифы ВБ'!$B$9+(K5-1)*'Тарифы ВБ'!$B$10)*'Тарифы ВБ'!$B$15*'Тарифы ВБ'!$B$12+S5*'Тарифы ВБ'!$B$13,'Тарифы ВБ'!$B$8*'Тарифы ВБ'!$B$15*'Тарифы ВБ'!$B$12+S5*'Тарифы ВБ'!$B$13) -> 73.65724 | Y5: =IF(K5>1,'Тарифы ВБ'!$B$9+(K5-1)*'Тарифы ВБ'!$B$10,'Тарифы ВБ'!$B$8) -> 32 | Z5: =SUM(X5:Y5) -> 105.65724 | AA5: =IFERROR(Z5/S5,0) -> 0.14166967 | AB5: =IF(K5>1,'Тарифы ВБ'!$B$14*'Тарифы ВБ'!$B$16*'Тарифы ВБ'!$B$15+(K5-1)*'Тарифы ВБ'!$B$14,'Тарифы ВБ'!$B$14*'Тарифы ВБ'!B$16*'Тарифы ВБ'!$B$15) -> 32 | AC5: =+X5+AB5+Y5 -> 137.65724 | AD5: =AC5/S5*100% -> 0.18457662 | AE5: 0.325 | AF5: =S5*AE5 -> 242.385 | AG5: =1.1*S5*$AG$3 -> 0 | AH5: =S5*$AH$3 -> 22.374 | AI5: =F5+V5 -> 528.41624 | AJ5: =IFERROR(AL5/S5,0) -> 0.22147729 | AK5: =S5-AI5 -> 217.38376 | AL5: =AK5-S5*7% -> 165.17776 | AM5: =AL5/H5 -> 1.5882477 | AN5: 829 | AO5: =$AN5-$AI5 -> 300.58376 | AP5: =$AO5-$AN5*7% -> 242.55376 | AQ5: =$AP5/$H5*100% -> 2.3322477 | AR5: =$AP5/$AN5 -> 0.29258596 | AS5: =IFERROR(_xlfn.XLOOKUP(A5,'[2]Рассчет акции'!$A:$A,'[2]Рассчет акции'!$BH:$BH),0) -> * | AT5: =IFERROR(_xlfn.XLOOKUP($A5,'[2]Рассчет акции'!$A:$A,'[2]Рассчет акции'!$BC:$BC),0) -> 746 | AU5: =IFERROR($AW5/$AT5,0) -> 0.22166724 | AV5: =$AT5-$AI5 -> 217.58376 | AW5: =$AV5-$AT5*7% -> 165.36376 | AX5: =$AW5/$H5*100% -> 1.5900362 | AY5: =IFERROR(_xlfn.XLOOKUP(E5,'[2]Рассчет акции'!$D:$D,'[2]Рассчет акции'!$BM:$BM),0) -> 128 | AZ5: =IFERROR(_xlfn.XLOOKUP(E5,'[2]Рассчет акции'!$D:$D,'[2]Рассчет акции'!$BN:$BN),0) -> 984 | BA5: =S5/H5 -> 7.1711538 | BC5: =_xlfn.XLOOKUP(B5,#REF!,#REF!,0) -> #REF! | BD5: =BC5/(100%-BE5) -> #REF! | BE5: =_xlfn.XLOOKUP($B5,'[1]Рассчет акции'!$A:$A,'[1]Рассчет акции'!$J:$J) -> 0 | BF5: =BS5+BI5+BJ5+BU5+BK5 -> #REF! | BG5: =IFERROR(BF5/BC5,0) -> 0 | BH5: 0.39 | BI5: =BC5*BH5 -> #REF! | BJ5: =BC5*$BJ$3 -> #REF! | BK5: =K5*$BK$3*30 -> 0 | BL5: =(IF(K5>$BL$3,('Тарифы ОЗОН'!$G$3+ROUNDUP(K5-$BL$3,0)*'Тарифы ОЗОН'!$G$4),'Тарифы ОЗОН'!$G$3)) -> 46.77 | BM5: =$BN$3 -> 35 | BN5: =_xlfn.XLOOKUP(BM5,'Тарифы ОЗОН'!$A:$A,'Тарифы ОЗОН'!$B:$B) -> 1.32 | BO5: =_xlfn.XLOOKUP(BM5,'Тарифы ОЗОН'!$A:$A,'Тарифы ОЗОН'!C:C) -> 0.016 | BP5: =$BP$3 -> 25 | BQ5: =BL5*BN5+BC5*BO5+BP5 -> #REF! | BR5: =$BR$3 -> 0.85 | BS5: =(100%/BR5)*BQ5+(100%/BR5-1)*BL5 -> #REF! | BT5: =IFERROR(BS5/BC5*100%,0) -> 0 | BU5: =BC5*$BU$3 -> #REF! | BV5: =BF5+F5 -> #REF! | BW5: =IFERROR(BY5/BC5,0) -> 0 | BX5: =IFERROR(BC5-BV5,0) -> 0 | BY5: =BX5-BC5*7% -> #REF! | BZ5: =IFERROR(BY5/H5*100%,0) -> 0 | CA5: 0 | CB5: =IF(BC5=0,0,CA5-BV5) -> #REF! | CC5: =IF(CB5=0,0,CB5-CA5*7%) -> #REF! | CD5: =CC5/H5*100% -> #REF! | CE5: =IFERROR(CC5/CA5,0) -> 0 | CF5: =_xlfn.XLOOKUP(B5,'[1]Рассчет акции'!$A:$A,'[1]Рассчет акции'!$R:$R,0) -> 0 | CG5: =_xlfn.XLOOKUP(B5,'[1]Рассчет акции'!$A:$A,'[1]Рассчет акции'!$M:$M,0) -> 0 | CH5: =IFERROR($CJ5/$CG5,0) -> 0 | CI5: =IF(CG5>0,CG5-BV5,0) -> 0 | CJ5: =IF(CI5>0,$CI5-$CG5*7%,0) -> 0 | CK5: =$CJ5/$H5*100% -> 0 | CL5: =_xlfn.XLOOKUP(B5,'[1]Рассчет акции'!$A:$A,'[1]Рассчет акции'!$W:$W,0) -> 0 | CM5: =_xlfn.XLOOKUP(B5,'[1]Рассчет акции'!$A:$A,'[1]Рассчет акции'!$X:$X,0) -> 0 | CN5: =BC5/H5 -> #REF! | CO5: =CA5-10%*CA5 -> 0 | CP5: =_xlfn.XLOOKUP(B5,'[1]Рассчет акции'!$A:$A,'[1]Рассчет акции'!$Z:$Z,0) -> 0
A6: 169153168 | B6: 2453533282 | C6: ACRF1BN101BC | D6: Бандаж для лица черный | E6: 2038162681926 | F6: =SUM(H6:J6) -> 105.26245 | G6: =IFERROR(F6/S6*100%,0) -> 0.14114032 | H6: =IF(_xlfn.XLOOKUP($C6,'Юнит Карго'!$A:$A,'Юнит Карго'!$G:$G)=0,_xlfn.XLOOKUP(E6,'Себес 1С текущ'!G:G,'Себес 1С текущ'!H:H),_xlfn.XLOOKUP($C6,'Юнит Карго'!$A:$A,'Юнит Карго'!$P:$P,0,0)) -> 83.262451 | I6: =_xlfn.XLOOKUP(E6,[3]ТЗ_ФФ!$D:$D,[3]ТЗ_ФФ!$BG:$BG,0) -> 14 | J6: =$J$3 -> 8 | K6: =(L6*M6*N6)/1000 -> 0.336 | L6: 14 | M6: 12 | N6: 2 | O6: =_xlfn.XLOOKUP($C6,'Юнит Карго'!$A:$A,'Юнит Карго'!$T:$T,0,0) -> 0.04 | P6: своя | S6: =T6-(T6*U6) -> 745.8 | T6: =_xlfn.XLOOKUP(E6,'[2]Рассчет акции'!$D:$D,'[2]Рассчет акции'!$G:$G,0) -> 1243 | U6: =_xlfn.XLOOKUP(E6,'[2]Рассчет акции'!$D:$D,'[2]Рассчет акции'!$F:$F,0) -> 0.4 | V6: =AC6+AF6+AH6+AG6 -> 402.41624 | W6: =IFERROR(V6/S6,0) -> 0.53957662 | X6: =IF(K6>1,('Тарифы ВБ'!$B$9+(K6-1)*'Тарифы ВБ'!$B$10)*'Тарифы ВБ'!$B$15*'Тарифы ВБ'!$B$12+S6*'Тарифы ВБ'!$B$13,'Тарифы ВБ'!$B$8*'Тарифы ВБ'!$B$15*'Тарифы ВБ'!$B$12+S6*'Тарифы ВБ'!$B$13) -> 73.65724 | Y6: =IF(K6>1,'Тарифы ВБ'!$B$9+(K6-1)*'Тарифы ВБ'!$B$10,'Тарифы ВБ'!$B$8) -> 32 | Z6: =SUM(X6:Y6) -> 105.65724 | AA6: =IFERROR(Z6/S6,0) -> 0.14166967 | AB6: =IF(K6>1,'Тарифы ВБ'!$B$14*'Тарифы ВБ'!$B$16*'Тарифы ВБ'!$B$15+(K6-1)*'Тарифы ВБ'!$B$14,'Тарифы ВБ'!$B$14*'Тарифы ВБ'!B$16*'Тарифы ВБ'!$B$15) -> 32 | AC6: =+X6+AB6+Y6 -> 137.65724 | AD6: =AC6/S6*100% -> 0.18457662 | AE6: 0.325 | AF6: =S6*AE6 -> 242.385 | AG6: =1.1*S6*$AG$3 -> 0 | AH6: =S6*$AH$3 -> 22.374 | AI6: =F6+V6 -> 507.67869 | AJ6: =IFERROR(AL6/S6,0) -> 0.24928306 | AK6: =S6-AI6 -> 238.12131 | AL6: =AK6-S6*7% -> 185.91531 | AM6: =AL6/H6 -> 2.232883 | AN6: 829 | AO6: =$AN6-$AI6 -> 321.32131 | AP6: =$AO6-$AN6*7% -> 263.29131 | AQ6: =$AP6/$H6*100% -> 3.1621854 | AR6: =$AP6/$AN6 -> 0.3176011 | AS6: =IFERROR(_xlfn.XLOOKUP(A6,'[2]Рассчет акции'!$A:$A,'[2]Рассчет акции'!$BH:$BH),0) -> * | AT6: =IFERROR(_xlfn.XLOOKUP($A6,'[2]Рассчет акции'!$A:$A,'[2]Рассчет акции'!$BC:$BC),0) -> 746 | AU6: =IFERROR($AW6/$AT6,0) -> 0.24946556 | AV6: =$AT6-$AI6 -> 238.32131 | AW6: =$AV6-$AT6*7% -> 186.10131 | AX6: =$AW6/$H6*100% -> 2.2351169 | AY6: =IFERROR(_xlfn.XLOOKUP(E6,'[2]Рассчет акции'!$D:$D,'[2]Рассчет акции'!$BM:$BM),0) -> 216 | AZ6: =IFERROR(_xlfn.XLOOKUP(E6,'[2]Рассчет акции'!$D:$D,'[2]Рассчет акции'!$BN:$BN),0) -> 999 | BA6: =S6/H6 -> 8.9572189 | BC6: =_xlfn.XLOOKUP(B6,#REF!,#REF!,0) -> #REF! | BD6: =BC6/(100%-BE6) -> #REF! | BE6: =_xlfn.XLOOKUP($B6,'[1]Рассчет акции'!$A:$A,'[1]Рассчет акции'!$J:$J) -> 0.34996841 | BF6: =BS6+BI6+BJ6+BU6+BK6 -> #REF! | BG6: =IFERROR(BF6/BC6,0) -> 0 | BH6: 0.39 | BI6: =BC6*BH6 -> #REF! | BJ6: =BC6*$BJ$3 -> #REF! | BK6: =K6*$BK$3*30 -> 0 | BL6: =(IF(K6>$BL$3,('Тарифы ОЗОН'!$G$3+ROUNDUP(K6-$BL$3,0)*'Тарифы ОЗОН'!$G$4),'Тарифы ОЗОН'!$G$3)) -> 46.77 | BM6: =$BN$3 -> 35 | BN6: =_xlfn.XLOOKUP(BM6,'Тарифы ОЗОН'!$A:$A,'Тарифы ОЗОН'!$B:$B) -> 1.32 | BO6: =_xlfn.XLOOKUP(BM6,'Тарифы ОЗОН'!$A:$A,'Тарифы ОЗОН'!C:C) -> 0.016 | BP6: =$BP$3 -> 25 | BQ6: =BL6*BN6+BC6*BO6+BP6 -> #REF! | BR6: =$BR$3 -> 0.85 | BS6: =(100%/BR6)*BQ6+(100%/BR6-1)*BL6 -> #REF! | BT6: =IFERROR(BS6/BC6*100%,0) -> 0 | BU6: =BC6*$BU$3 -> #REF! | BV6: =BF6+F6 -> #REF! | BW6: =IFERROR(BY6/BC6,0) -> 0 | BX6: =IFERROR(BC6-BV6,0) -> 0 | BY6: =BX6-BC6*7% -> #REF! | BZ6: =IFERROR(BY6/H6*100%,0) -> 0 | CA6: 799 | CB6: =IF(BC6=0,0,CA6-BV6) -> #REF! | CC6: =IF(CB6=0,0,CB6-CA6*7%) -> #REF! | CD6: =CC6/H6*100% -> #REF! | CE6: =IFERROR(CC6/CA6,0) -> 0 | CF6: =_xlfn.XLOOKUP(B6,'[1]Рассчет акции'!$A:$A,'[1]Рассчет акции'!$R:$R,0) -> 0 | CG6: =_xlfn.XLOOKUP(B6,'[1]Рассчет акции'!$A:$A,'[1]Рассчет акции'!$M:$M,0) -> 710 | CH6: =IFERROR($CJ6/$CG6,0) -> 0 | CI6: =IF(BC6>0,CG6-BV6,0) -> #REF! | CJ6: =IF(CI6>0,$CI6-$CG6*7%,0) -> #REF! | CK6: =$CJ6/$H6*100% -> #REF! | CL6: =_xlfn.XLOOKUP(B6,'[1]Рассчет акции'!$A:$A,'[1]Рассчет акции'!$W:$W,0) -> 0 | CM6: =_xlfn.XLOOKUP(B6,'[1]Рассчет акции'!$A:$A,'[1]Рассчет акции'!$X:$X,0) -> 0 | CN6: =BC6/H6 -> #REF! | CO6: =CA6-10%*CA6 -> 719.1 | CP6: =_xlfn.XLOOKUP(B6,'[1]Рассчет акции'!$A:$A,'[1]Рассчет акции'!$Z:$Z,0) -> 0
A7: 169395410 | B7: 2419349210 | C7: ACRF1BN201GR | D7: Бандаж для лица серый | E7: 2038172050200 | F7: =SUM(H7:J7) -> 222.95301 | G7: =IFERROR(F7/S7*100%,0) -> 0.21331134 | H7: =IF(_xlfn.XLOOKUP($C7,'Юнит Карго'!$A:$A,'Юнит Карго'!$G:$G)=0,_xlfn.XLOOKUP(E7,'Себес 1С текущ'!G:G,'Себес 1С текущ'!H:H),_xlfn.XLOOKUP($C7,'Юнит Карго'!$A:$A,'Юнит Карго'!$P:$P,0,0)) -> 200.95301 | I7: =_xlfn.XLOOKUP(E7,[3]ТЗ_ФФ!$D:$D,[3]ТЗ_ФФ!$BG:$BG,0) -> 14 | J7: =$J$3 -> 8 | K7: =(L7*M7*N7)/1000 -> 0.798 | L7: 19 | M7: 14 | N7: 3 | O7: =_xlfn.XLOOKUP($C7,'Юнит Карго'!$A:$A,'Юнит Карго'!$T:$T,0,0) -> 0.09 | P7: своя | S7: =T7-(T7*U7) -> 1045.2 | T7: =_xlfn.XLOOKUP(E7,'[2]Рассчет акции'!$D:$D,'[2]Рассчет акции'!$G:$G,0) -> 1742 | U7: =_xlfn.XLOOKUP(E7,'[2]Рассчет акции'!$D:$D,'[2]Рассчет акции'!$F:$F,0) -> 0.4 | V7: =AC7+AF7+AH7+AG7 -> 511.03856 | W7: =IFERROR(V7/S7,0) -> 0.48893854 | X7: =IF(K7>1,('Тарифы ВБ'!$B$9+(K7-1)*'Тарифы ВБ'!$B$10)*'Тарифы ВБ'!$B$15*'Тарифы ВБ'!$B$12+S7*'Тарифы ВБ'!$B$13,'Тарифы ВБ'!$B$8*'Тарифы ВБ'!$B$15*'Тарифы ВБ'!$B$12+S7*'Тарифы ВБ'!$B$13) -> 75.99256 | Y7: =IF(K7>1,'Тарифы ВБ'!$B$9+(K7-1)*'Тарифы ВБ'!$B$10,'Тарифы ВБ'!$B$8) -> 32 | Z7: =SUM(X7:Y7) -> 107.99256 | AA7: =IFERROR(Z7/S7,0) -> 0.10332239 | AB7: =IF(K7>1,'Тарифы ВБ'!$B$14*'Тарифы ВБ'!$B$16*'Тарифы ВБ'!$B$15+(K7-1)*'Тарифы ВБ'!$B$14,'Тарифы ВБ'!$B$14*'Тарифы ВБ'!B$16*'Тарифы ВБ'!$B$15) -> 32 | AC7: =+X7+AB7+Y7 -> 139.99256 | AD7: =AC7/S7*100% -> 0.13393854 | AE7: 0.325 | AF7: =S7*AE7 -> 339.69 | AG7: =1.1*S7*$AG$3 -> 0 | AH7: =S7*$AH$3 -> 31.356 | AI7: =F7+V7 -> 733.99157 | AJ7: =IFERROR(AL7/S7,0) -> 0.22775012 | AK7: =S7-AI7 -> 311.20843 | AL7: =AK7-S7*7% -> 238.04443 | AM7: =AL7/H7 -> 1.1845775 | AN7: 1159 | AO7: =$AN7-$AI7 -> 425.00843 | AP7: =$AO7-$AN7*7% -> 343.87843 | AQ7: =$AP7/$H7*100% -> 1.711238 | AR7: =$AP7/$AN7 -> 0.2967027 | AS7: =IFERROR(_xlfn.XLOOKUP(A7,'[2]Рассчет акции'!$A:$A,'[2]Рассчет акции'!$BH:$BH),0) -> * | AT7: =IFERROR(_xlfn.XLOOKUP($A7,'[2]Рассчет акции'!$A:$A,'[2]Рассчет акции'!$BC:$BC),0) -> 1045 | AU7: =IFERROR($AW7/$AT7,0) -> 0.22761572 | AV7: =$AT7-$AI7 -> 311.00843 | AW7: =$AV7-$AT7*7% -> 237.85843 | AX7: =$AW7/$H7*100% -> 1.1836519 | AY7: =IFERROR(_xlfn.XLOOKUP(E7,'[2]Рассчет акции'!$D:$D,'[2]Рассчет акции'!$BM:$BM),0) -> 202 | AZ7: =IFERROR(_xlfn.XLOOKUP(E7,'[2]Рассчет акции'!$D:$D,'[2]Рассчет акции'!$BN:$BN),0) -> 999 | BA7: =S7/H7 -> 5.2012158 | BC7: =_xlfn.XLOOKUP(B7,#REF!,#REF!,0) -> #REF! | BD7: =BC7/(100%-BE7) -> #REF! | BE7: =_xlfn.XLOOKUP($B7,'[1]Рассчет акции'!$A:$A,'[1]Рассчет акции'!$J:$J) -> 0.3498749 | BF7: =BS7+BI7+BJ7+BU7+BK7 -> #REF! | BG7: =IFERROR(BF7/BC7,0) -> 0 | BH7: 0.39 | BI7: =BC7*BH7 -> #REF! | BJ7: =BC7*$BJ$3 -> #REF! | BK7: =K7*$BK$3*30 -> 0 | BL7: =(IF(K7>$BL$3,('Тарифы ОЗОН'!$G$3+ROUNDUP(K7-$BL$3,0)*'Тарифы ОЗОН'!$G$4),'Тарифы ОЗОН'!$G$3)) -> 46.77 | BM7: =$BN$3 -> 35 | BN7: =_xlfn.XLOOKUP(BM7,'Тарифы ОЗОН'!$A:$A,'Тарифы ОЗОН'!$B:$B) -> 1.32 | BO7: =_xlfn.XLOOKUP(BM7,'Тарифы ОЗОН'!$A:$A,'Тарифы ОЗОН'!C:C) -> 0.016 | BP7: =$BP$3 -> 25 | BQ7: =BL7*BN7+BC7*BO7+BP7 -> #REF! | BR7: =$BR$3 -> 0.85 | BS7: =(100%/BR7)*BQ7+(100%/BR7-1)*BL7 -> #REF! | BT7: =IFERROR(BS7/BC7*100%,0) -> 0 | BU7: =BC7*$BU$3 -> #REF! | BV7: =BF7+F7 -> #REF! | BW7: =IFERROR(BY7/BC7,0) -> 0 | BX7: =IFERROR(BC7-BV7,0) -> 0 | BY7: =BX7-BC7*7% -> #REF! | BZ7: =IFERROR(BY7/H7*100%,0) -> 0 | CA7: 1299 | CB7: =IF(BC7=0,0,CA7-BV7) -> #REF! | CC7: =IF(CB7=0,0,CB7-CA7*7%) -> #REF! | CD7: =CC7/H7*100% -> #REF! | CE7: =IFERROR(CC7/CA7,0) -> 0 | CF7: =_xlfn.XLOOKUP(B7,'[1]Рассчет акции'!$A:$A,'[1]Рассчет акции'!$R:$R,0) -> 0 | CG7: =_xlfn.XLOOKUP(B7,'[1]Рассчет акции'!$A:$A,'[1]Рассчет акции'!$M:$M,0) -> 1115 | CH7: =IFERROR($CJ7/$CG7,0) -> 0 | CI7: =IF(BC7>0,CG7-BV7,0) -> #REF! | CJ7: =IF(CI7>0,$CI7-$CG7*7%,0) -> #REF! | CK7: =$CJ7/$H7*100% -> #REF! | CL7: =_xlfn.XLOOKUP(B7,'[1]Рассчет акции'!$A:$A,'[1]Рассчет акции'!$W:$W,0) -> 0 | CM7: =_xlfn.XLOOKUP(B7,'[1]Рассчет акции'!$A:$A,'[1]Рассчет акции'!$X:$X,0) -> 0 | CN7: =BC7/H7 -> #REF! | CO7: =CA7-10%*CA7 -> 1169.1 | CP7: =_xlfn.XLOOKUP(B7,'[1]Рассчет акции'!$A:$A,'[1]Рассчет акции'!$Z:$Z,0) -> 0
A8: 172832355 | B8: 2419349460 | C8: AHMA7BW101BG | D8: Мешки 7 шт. | E8: 2038337652454 | F8: =SUM(H8:J8) -> 390.77055 | G8: =IFERROR(F8/S8*100%,0) -> 0.18634742 | H8: =IF(_xlfn.XLOOKUP($C8,'Юнит Карго'!$A:$A,'Юнит Карго'!$G:$G)=0,_xlfn.XLOOKUP(E8,'Себес 1С текущ'!G:G,'Себес 1С текущ'!H:H),_xlfn.XLOOKUP($C8,'Юнит Карго'!$A:$A,'Юнит Карго'!$P:$P,0,0)) -> 368.77055 | I8: =_xlfn.XLOOKUP(E8,[3]ТЗ_ФФ!$D:$D,[3]ТЗ_ФФ!$BG:$BG,0) -> 14 | J8: =$J$3 -> 8 | K8: =(L8*M8*N8)/1000 -> 3.78 | L8: 30 | M8: 21 | N8: 6 | O8: =_xlfn.XLOOKUP($C8,'Юнит Карго'!$A:$A,'Юнит Карго'!$T:$T,0,0) -> 0.315 | P8: своя | Q8: 20 | S8: =T8-(T8*U8) -> 2097 | T8: =_xlfn.XLOOKUP(E8,'[2]Рассчет акции'!$D:$D,'[2]Рассчет акции'!$G:$G,0) -> 3495 | U8: =_xlfn.XLOOKUP(E8,'[2]Рассчет акции'!$D:$D,'[2]Рассчет акции'!$F:$F,0) -> 0.4 | V8: =AC8+AF8+AH8+AG8 -> 995.0544 | W8: =IFERROR(V8/S8,0) -> 0.4745133 | X8: =IF(K8>1,('Тарифы ВБ'!$B$9+(K8-1)*'Тарифы ВБ'!$B$10)*'Тарифы ВБ'!$B$15*'Тарифы ВБ'!$B$12+S8*'Тарифы ВБ'!$B$13,'Тарифы ВБ'!$B$8*'Тарифы ВБ'!$B$15*'Тарифы ВБ'!$B$12+S8*'Тарифы ВБ'!$B$13) -> 196.387 | Y8: =IF(K8>1,'Тарифы ВБ'!$B$9+(K8-1)*'Тарифы ВБ'!$B$10,'Тарифы ВБ'!$B$8) -> 84.92 | Z8: =SUM(X8:Y8) -> 281.307 | AA8: =IFERROR(Z8/S8,0) -> 0.13414735 | AB8: =IF(K8>1,'Тарифы ВБ'!$B$14*'Тарифы ВБ'!$B$16*'Тарифы ВБ'!$B$15+(K8-1)*'Тарифы ВБ'!$B$14,'Тарифы ВБ'!$B$14*'Тарифы ВБ'!B$16*'Тарифы ВБ'!$B$15) -> 32.2224 | AC8: =+X8+AB8+Y8 -> 313.5294 | AD8: =AC8/S8*100% -> 0.1495133 | AE8: 0.295 | AF8: =S8*AE8 -> 618.615 | AG8: =1.1*S8*$AG$3 -> 0 | AH8: =S8*$AH$3 -> 62.91 | AI8: =F8+V8 -> 1385.8249 | AJ8: =IFERROR(AL8/S8,0) -> 0.26913927 | AK8: =S8-AI8 -> 711.17505 | AL8: =AK8-S8*7% -> 564.38505 | AM8: =AL8/H8 -> 1.5304504 | AN8: 2119 | AO8: =$AN8-$AI8 -> 733.17505 | AP8: =$AO8-$AN8*7% -> 584.84505 | AQ8: =$AP8/$H8*100% -> 1.5859321 | AR8: =$AP8/$AN8 -> 0.2760005 | AS8: =IFERROR(_xlfn.XLOOKUP(A8,'[2]Рассчет акции'!$A:$A,'[2]Рассчет акции'!$BH:$BH),0) -> * | AT8: =IFERROR(_xlfn.XLOOKUP($A8,'[2]Рассчет акции'!$A:$A,'[2]Рассчет акции'!$BC:$BC),0) -> 2097 | AU8: =IFERROR($AW8/$AT8,0) -> 0.26913927 | AV8: =$AT8-$AI8 -> 711.17505 | AW8: =$AV8-$AT8*7% -> 564.38505 | AX8: =$AW8/$H8*100% -> 1.5304504 | AY8: =IFERROR(_xlfn.XLOOKUP(E8,'[2]Рассчет акции'!$D:$D,'[2]Рассчет акции'!$BM:$BM),0) -> 139 | AZ8: =IFERROR(_xlfn.XLOOKUP(E8,'[2]Рассчет акции'!$D:$D,'[2]Рассчет акции'!$BN:$BN),0) -> 269 | BA8: =S8/H8 -> 5.6864628 | BC8: =_xlfn.XLOOKUP(B8,#REF!,#REF!,0) -> #REF! | BD8: =BC8/(100%-BE8) -> #REF! | BE8: =_xlfn.XLOOKUP($B8,'[1]Рассчет акции'!$A:$A,'[1]Рассчет акции'!$J:$J) -> 0.34997678 | BF8: =BS8+BI8+BJ8+BU8+BK8 -> #REF! | BG8: =IFERROR(BF8/BC8,0) -> 0 | BH8: 0.4 | BI8: =BC8*BH8 -> #REF! | BJ8: =BC8*$BJ$3 -> #REF! | BK8: =K8*$BK$3*30 -> 0 | BL8: =(IF(K8>$BL$3,('Тарифы ОЗОН'!$G$3+ROUNDUP(K8-$BL$3,0)*'Тарифы ОЗОН'!$G$4+5),'Тарифы ОЗОН'!$G$3)) -> 82.28 | BM8: =$BN$3 -> 35 | BN8: =_xlfn.XLOOKUP(BM8,'Тарифы ОЗОН'!$A:$A,'Тарифы ОЗОН'!$B:$B) -> 1.32 | BO8: =_xlfn.XLOOKUP(BM8,'Тарифы ОЗОН'!$A:$A,'Тарифы ОЗОН'!C:C) -> 0.016 | BP8: =$BP$3 -> 25 | BQ8: =BL8*BN8+BC8*BO8+BP8 -> #REF! | BR8: =$BR$3 -> 0.85 | BS8: =(100%/BR8)*BQ8+(100%/BR8-1)*BL8 -> #REF! | BT8: =IFERROR(BS8/BC8*100%,0) -> 0 | BU8: =BC8*$BU$3 -> #REF! | BV8: =BF8+F8 -> #REF! | BW8: =IFERROR(BY8/BC8,0) -> 0 | BX8: =IFERROR(BC8-BV8,0) -> 0 | BY8: =BX8-BC8*7% -> #REF! | BZ8: =IFERROR(BY8/H8*100%,0) -> 0 | CA8: 1959 | CB8: =IF(BC8=0,0,CA8-BV8) -> #REF! | CC8: =IF(CB8=0,0,CB8-CA8*7%) -> #REF! | CD8: =CC8/H8*100% -> #REF! | CE8: =IFERROR(CC8/CA8,0) -> 0 | CF8: =_xlfn.XLOOKUP(B8,'[1]Рассчет акции'!$A:$A,'[1]Рассчет акции'!$R:$R,0) -> 0 | CG8: =_xlfn.XLOOKUP(B8,'[1]Рассчет акции'!$A:$A,'[1]Рассчет акции'!$M:$M,0) -> 1719 | CH8: =IFERROR($CJ8/$CG8,0) -> 0 | CI8: =IF(BC8>0,CG8-BV8,0) -> #REF! | CJ8: =IF(CI8>0,$CI8-$CG8*7%,0) -> #REF! | CK8: =$CJ8/$H8*100% -> #REF! | CL8: =_xlfn.XLOOKUP(B8,'[1]Рассчет акции'!$A:$A,'[1]Рассчет акции'!$W:$W,0) -> 5 | CM8: =_xlfn.XLOOKUP(B8,'[1]Рассчет акции'!$A:$A,'[1]Рассчет акции'!$X:$X,0) -> 999 | CN8: =BC8/H8 -> #REF! | CO8: =CA8-10%*CA8 -> 1763.1 | CP8: =_xlfn.XLOOKUP(B8,'[1]Рассчет акции'!$A:$A,'[1]Рассчет акции'!$Z:$Z,0) -> 0
A9: 176500218 | B9: 2138709303 | C9: AHMA1BW101BG | D9: Мешок для бюстгалтеров | E9: 2038597850744 | F9: =SUM(H9:J9) -> 85.788676 | G9: =IFERROR(F9/S9*100%,0) -> 0.15922174 | H9: =IF(_xlfn.XLOOKUP($C9,'Юнит Карго'!$A:$A,'Юнит Карго'!$G:$G)=0,_xlfn.XLOOKUP(E9,'Себес 1С текущ'!G:G,'Себес 1С текущ'!H:H),_xlfn.XLOOKUP($C9,'Юнит Карго'!$A:$A,'Юнит Карго'!$P:$P,0,0)) -> 63.788676 | I9: =_xlfn.XLOOKUP(E9,[3]ТЗ_ФФ!$D:$D,[3]ТЗ_ФФ!$BG:$BG,0) -> 14 | J9: =$J$3 -> 8 | K9: =(L9*M9*N9)/1000 -> 0.918 | L9: 18 | M9: 17 | N9: 3 | O9: =_xlfn.XLOOKUP($C9,'Юнит Карго'!$A:$A,'Юнит Карго'!$T:$T,0,0) -> 0.06 | P9: своя, ОРР 24*34 | Q9: 140 | S9: =T9-(T9*U9) -> 538.8 | T9: =_xlfn.XLOOKUP(E9,'[2]Рассчет акции'!$D:$D,'[2]Рассчет акции'!$G:$G,0) -> 898 | U9: =_xlfn.XLOOKUP(E9,'[2]Рассчет акции'!$D:$D,'[2]Рассчет акции'!$F:$F,0) -> 0.4 | V9: =AC9+AF9+AH9+AG9 -> 311.15264 | W9: =IFERROR(V9/S9,0) -> 0.57749191 | X9: =IF(K9>1,('Тарифы ВБ'!$B$9+(K9-1)*'Тарифы ВБ'!$B$10)*'Тарифы ВБ'!$B$15*'Тарифы ВБ'!$B$12+S9*'Тарифы ВБ'!$B$13,'Тарифы ВБ'!$B$8*'Тарифы ВБ'!$B$15*'Тарифы ВБ'!$B$12+S9*'Тарифы ВБ'!$B$13) -> 72.04264 | Y9: =IF(K9>1,'Тарифы ВБ'!$B$9+(K9-1)*'Тарифы ВБ'!$B$10,'Тарифы ВБ'!$B$8) -> 32 | Z9: =SUM(X9:Y9) -> 104.04264 | AA9: =IFERROR(Z9/S9,0) -> 0.19310067 | AB9: =IF(K9>1,'Тарифы ВБ'!$B$14*'Тарифы ВБ'!$B$16*'Тарифы ВБ'!$B$15+(K9-1)*'Тарифы ВБ'!$B$14,'Тарифы ВБ'!$B$14*'Тарифы ВБ'!B$16*'Тарифы ВБ'!$B$15) -> 32 | AC9: =+X9+AB9+Y9 -> 136.04264 | AD9: =AC9/S9*100% -> 0.25249191 | AE9: 0.295 | AF9: =S9*AE9 -> 158.946 | AG9: =1.1*S9*$AG$3 -> 0 | AH9: =S9*$AH$3 -> 16.164 | AI9: =F9+V9 -> 396.94132 | AJ9: =IFERROR(AL9/S9,0) -> 0.19328635 | AK9: =S9-AI9 -> 141.85868 | AL9: =AK9-S9*7% -> 104.14268 | AM9: =AL9/H9 -> 1.6326202 | AN9: 599 | AO9: =$AN9-$AI9 -> 202.05868 | AP9: =$AO9-$AN9*7% -> 160.12868 | AQ9: =$AP9/$H9*100% -> 2.5102995 | AR9: =$AP9/$AN9 -> 0.26732668 | AS9: =IFERROR(_xlfn.XLOOKUP(A9,'[2]Рассчет акции'!$A:$A,'[2]Рассчет акции'!$BH:$BH),0) -> * | AT9: =IFERROR(_xlfn.XLOOKUP($A9,'[2]Рассчет акции'!$A:$A,'[2]Рассчет акции'!$BC:$BC),0) -> 539 | AU9: =IFERROR($AW9/$AT9,0) -> 0.19355971 | AV9: =$AT9-$AI9 -> 142.05868 | AW9: =$AV9-$AT9*7% -> 104.32868 | AX9: =$AW9/$H9*100% -> 1.6355361 | AY9: =IFERROR(_xlfn.XLOOKUP(E9,'[2]Рассчет акции'!$D:$D,'[2]Рассчет акции'!$BM:$BM),0) -> 320 | AZ9: =IFERROR(_xlfn.XLOOKUP(E9,'[2]Рассчет акции'!$D:$D,'[2]Рассчет акции'!$BN:$BN),0) -> 726 | BA9: =S9/H9 -> 8.4466403 | BC9: =_xlfn.XLOOKUP(B9,#REF!,#REF!,0) -> #REF! | BD9: =BC9/(100%-BE9) -> #REF! | BE9: =_xlfn.XLOOKUP($B9,'[1]Рассчет акции'!$A:$A,'[1]Рассчет акции'!$J:$J) -> 0.35003253 | BF9: =BS9+BI9+BJ9+BU9+BK9 -> #REF! | BG9: =IFERROR(BF9/BC9,0) -> 0 | BH9: 0.4 | BI9: =BC9*BH9 -> #REF! | BJ9: =BC9*$BJ$3 -> #REF! | BK9: =K9*$BK$3*30 -> 0 | BL9: =(IF(K9>$BL$3,('Тарифы ОЗОН'!$G$3+ROUNDUP(K9-$BL$3,0)*'Тарифы ОЗОН'!$G$4),'Тарифы ОЗОН'!$G$3)) -> 46.77 | BM9: =$BN$3 -> 35 | BN9: =_xlfn.XLOOKUP(BM9,'Тарифы ОЗОН'!$A:$A,'Тарифы ОЗОН'!$B:$B) -> 1.32 | BO9: =_xlfn.XLOOKUP(BM9,'Тарифы ОЗОН'!$A:$A,'Тарифы ОЗОН'!C:C) -> 0.016 | BP9: =$BP$3 -> 25 | BQ9: =BL9*BN9+BC9*BO9+BP9 -> #REF! | BR9: =$BR$3 -> 0.85 | BS9: =(100%/BR9)*BQ9+(100%/BR9-1)*BL9 -> #REF! | BT9: =IFERROR(BS9/BC9*100%,0) -> 0 | BU9: =BC9*$BU$3 -> #REF! | BV9: =BF9+F9 -> #REF! | BW9: =IFERROR(BY9/BC9,0) -> 0 | BX9: =IFERROR(BC9-BV9,0) -> 0 | BY9: =BX9-BC9*7% -> #REF! | BZ9: =IFERROR(BY9/H9*100%,0) -> 0 | CA9: 769 | CB9: =IF(BC9=0,0,CA9-BV9) -> #REF! | CC9: =IF(CB9=0,0,CB9-CA9*7%) -> #REF! | CD9: =CC9/H9*100% -> #REF! | CE9: =IFERROR(CC9/CA9,0) -> 0 | CF9: =_xlfn.XLOOKUP(B9,'[1]Рассчет акции'!$A:$A,'[1]Рассчет акции'!$R:$R,0) -> 0 | CG9: =_xlfn.XLOOKUP(B9,'[1]Рассчет акции'!$A:$A,'[1]Рассчет акции'!$M:$M,0) -> 0 | CH9: =IFERROR($CJ9/$CG9,0) -> 0 | CI9: =IF(BC9>0,CG9-BV9,0) -> #REF! | CJ9: =IF(CI9>0,$CI9-$CG9*7%,0) -> #REF! | CK9: =$CJ9/$H9*100% -> #REF! | CL9: =_xlfn.XLOOKUP(B9,'[1]Рассчет акции'!$A:$A,'[1]Рассчет акции'!$W:$W,0) -> 0 | CM9: =_xlfn.XLOOKUP(B9,'[1]Рассчет акции'!$A:$A,'[1]Рассчет акции'!$X:$X,0) -> 0 | CN9: =BC9/H9 -> #REF! | CO9: =CA9-10%*CA9 -> 692.1 | CP9: =_xlfn.XLOOKUP(B9,'[1]Рассчет акции'!$A:$A,'[1]Рассчет акции'!$Z:$Z,0) -> 0
A10: 177404837 | B10: 2419349262 | C10: AHMA3BW101BG | D10: Мешки 3 шт. | E10: 2038627692689 | F10: =SUM(H10:J10) -> 211 | G10: =IFERROR(F10/S10*100%,0) -> 0.16931472 | H10: =IF(_xlfn.XLOOKUP($C10,'Юнит Карго'!$A:$A,'Юнит Карго'!$G:$G)=0,_xlfn.XLOOKUP(E10,'Себес 1С текущ'!G:G,'Себес 1С текущ'!H:H),_xlfn.XLOOKUP($C10,'Юнит Карго'!$A:$A,'Юнит Карго'!$P:$P,0,0)) -> 165 | I10: =_xlfn.XLOOKUP(E10,[3]ТЗ_ФФ!$D:$D,[3]ТЗ_ФФ!$BG:$BG,0) -> 38 | J10: =$J$3 -> 8 | K10: =(L10*M10*N10)/1000 -> 2.5 | L10: 25 | M10: 20 | N10: 5 | O10: =_xlfn.XLOOKUP($C10,'Юнит Карго'!$A:$A,'Юнит Карго'!$T:$T,0,0) -> 0.14 | P10: слайдер 25*30, ОРР 24*34 | Q10: 40 | S10: =T10-(T10*U10) -> 1246.2 | T10: =_xlfn.XLOOKUP(E10,'[2]Рассчет акции'!$D:$D,'[2]Рассчет акции'!$G:$G,0) -> 2077 | U10: =_xlfn.XLOOKUP(E10,'[2]Рассчет акции'!$D:$D,'[2]Рассчет акции'!$F:$F,0) -> 0.4 | V10: =AC10+AF10+AH10+AG10 -> 655.89536 | W10: =IFERROR(V10/S10,0) -> 0.52631629 | X10: =IF(K10>1,('Тарифы ВБ'!$B$9+(K10-1)*'Тарифы ВБ'!$B$10)*'Тарифы ВБ'!$B$15*'Тарифы ВБ'!$B$12+S10*'Тарифы ВБ'!$B$13,'Тарифы ВБ'!$B$8*'Тарифы ВБ'!$B$15*'Тарифы ВБ'!$B$12+S10*'Тарифы ВБ'!$B$13) -> 151.76036 | Y10: =IF(K10>1,'Тарифы ВБ'!$B$9+(K10-1)*'Тарифы ВБ'!$B$10,'Тарифы ВБ'!$B$8) -> 67 | Z10: =SUM(X10:Y10) -> 218.76036 | AA10: =IFERROR(Z10/S10,0) -> 0.17554194 | AB10: =IF(K10>1,'Тарифы ВБ'!$B$14*'Тарифы ВБ'!$B$16*'Тарифы ВБ'!$B$15+(K10-1)*'Тарифы ВБ'!$B$14,'Тарифы ВБ'!$B$14*'Тарифы ВБ'!B$16*'Тарифы ВБ'!$B$15) -> 32.12 | AC10: =+X10+AB10+Y10 -> 250.88036 | AD10: =AC10/S10*100% -> 0.20131629 | AE10: 0.295 | AF10: =S10*AE10 -> 367.629 | AG10: =1.1*S10*$AG$3 -> 0 | AH10: =S10*$AH$3 -> 37.386 | AI10: =F10+V10 -> 866.89536 | AJ10: =IFERROR(AL10/S10,0) -> 0.23436899 | AK10: =S10-AI10 -> 379.30464 | AL10: =AK10-S10*7% -> 292.07064 | AM10: =AL10/H10 -> 1.7701251 | AN10: 1259 | AO10: =$AN10-$AI10 -> 392.10464 | AP10: =$AO10-$AN10*7% -> 303.97464 | AQ10: =$AP10/$H10*100% -> 1.8422705 | AR10: =$AP10/$AN10 -> 0.24144133 | AS10: =IFERROR(_xlfn.XLOOKUP(A10,'[2]Рассчет акции'!$A:$A,'[2]Рассчет акции'!$BH:$BH),0) -> * | AT10: =IFERROR(_xlfn.XLOOKUP($A10,'[2]Рассчет акции'!$A:$A,'[2]Рассчет акции'!$BC:$BC),0) -> 1246 | AU10: =IFERROR($AW10/$AT10,0) -> 0.23425734 | AV10: =$AT10-$AI10 -> 379.10464 | AW10: =$AV10-$AT10*7% -> 291.88464 | AX10: =$AW10/$H10*100% -> 1.7689978 | AY10: =IFERROR(_xlfn.XLOOKUP(E10,'[2]Рассчет акции'!$D:$D,'[2]Рассчет акции'!$BM:$BM),0) -> 146 | AZ10: =IFERROR(_xlfn.XLOOKUP(E10,'[2]Рассчет акции'!$D:$D,'[2]Рассчет акции'!$BN:$BN),0) -> 502 | BA10: =S10/H10 -> 7.5527273 | BC10: =_xlfn.XLOOKUP(B10,#REF!,#REF!,0) -> #REF! | BD10: =BC10/(100%-BE10) -> #REF! | BE10: =_xlfn.XLOOKUP($B10,'[1]Рассчет акции'!$A:$A,'[1]Рассчет акции'!$J:$J) -> 0.35007225 | BF10: =BS10+BI10+BJ10+BU10+BK10 -> #REF! | BG10: =IFERROR(BF10/BC10,0) -> 0 | BH10: 0.4 | BI10: =BC10*BH10 -> #REF! | BJ10: =BC10*$BJ$3 -> #REF! | BK10: =K10*$BK$3*30 -> 0 | BL10: =(IF(K10>$BL$3,('Тарифы ОЗОН'!$G$3+ROUNDUP(K10-$BL$3,0)*'Тарифы ОЗОН'!$G$4),'Тарифы ОЗОН'!$G$3)) -> 67.11 | BM10: =$BN$3 -> 35 | BN10: =_xlfn.XLOOKUP(BM10,'Тарифы ОЗОН'!$A:$A,'Тарифы ОЗОН'!$B:$B) -> 1.32 | BO10: =_xlfn.XLOOKUP(BM10,'Тарифы ОЗОН'!$A:$A,'Тарифы ОЗОН'!C:C) -> 0.016 | BP10: =$BP$3 -> 25 | BQ10: =BL10*BN10+BC10*BO10+BP10 -> #REF! | BR10: =$BR$3 -> 0.85 | BS10: =(100%/BR10)*BQ10+(100%/BR10-1)*BL10 -> #REF! | BT10: =IFERROR(BS10/BC10*100%,0) -> 0 | BU10: =BC10*$BU$3 -> #REF! | BV10: =BF10+F10 -> #REF! | BW10: =IFERROR(BY10/BC10,0) -> 0 | BX10: =IFERROR(BC10-BV10,0) -> 0 | BY10: =BX10-BC10*7% -> #REF! | BZ10: =IFERROR(BY10/H10*100%,0) -> 0 | CA10: 1099 | CB10: =IF(BC10=0,0,CA10-BV10) -> #REF! | CC10: =IF(CB10=0,0,CB10-CA10*7%) -> #REF! | CD10: =CC10/H10*100% -> #REF! | CE10: =IFERROR(CC10/CA10,0) -> 0 | CF10: =_xlfn.XLOOKUP(B10,'[1]Рассчет акции'!$A:$A,'[1]Рассчет акции'!$R:$R,0) -> 0 | CG10: =_xlfn.XLOOKUP(B10,'[1]Рассчет акции'!$A:$A,'[1]Рассчет акции'!$M:$M,0) -> 1071 | CH10: =IFERROR($CJ10/$CG10,0) -> 0 | CI10: =IF(BC10>0,CG10-BV10,0) -> #REF! | CJ10: =IF(CI10>0,$CI10-$CG10*7%,0) -> #REF! | CK10: =$CJ10/$H10*100% -> #REF! | CL10: =_xlfn.XLOOKUP(B10,'[1]Рассчет акции'!$A:$A,'[1]Рассчет акции'!$W:$W,0) -> 5 | CM10: =_xlfn.XLOOKUP(B10,'[1]Рассчет акции'!$A:$A,'[1]Рассчет акции'!$X:$X,0) -> 999 | CN10: =BC10/H10 -> #REF! | CO10: =CA10-10%*CA10 -> 989.1 | CP10: =_xlfn.XLOOKUP(B10,'[1]Рассчет акции'!$A:$A,'[1]Рассчет акции'!$Z:$Z,0) -> 0
A11: 177405495 | B11: 2576041357 | C11: AHMA3BW102BG | D11: Мешки/деликат 3 шт. | E11: 2038627713902 | F11: =SUM(H11:J11) -> 195.35735 | G11: =IFERROR(F11/S11*100%,0) -> 0.17628348 | H11: =IF(_xlfn.XLOOKUP($C11,'Юнит Карго'!$A:$A,'Юнит Карго'!$G:$G)=0,_xlfn.XLOOKUP(E11,'Себес 1С текущ'!G:G,'Себес 1С текущ'!H:H),_xlfn.XLOOKUP($C11,'Юнит Карго'!$A:$A,'Юнит Карго'!$P:$P,0,0)) -> 149.35735 | I11: =_xlfn.XLOOKUP(E11,[3]ТЗ_ФФ!$D:$D,[3]ТЗ_ФФ!$BG:$BG,0) -> 38 | J11: =$J$3 -> 8 | K11: =(L11*M11*N11)/1000 -> 1.7 | L11: 25 | M11: 17 | N11: 4 | O11: =_xlfn.XLOOKUP($C11,'Юнит Карго'!$A:$A,'Юнит Карго'!$T:$T,0,0) -> 0.12 | P11: ОРР 24*34 слайдер 20*30 | Q11: 50 | S11: =T11-(T11*U11) -> 1108.2 | T11: =_xlfn.XLOOKUP(E11,'[2]Рассчет акции'!$D:$D,'[2]Рассчет акции'!$G:$G,0) -> 1847 | U11: =_xlfn.XLOOKUP(E11,'[2]Рассчет акции'!$D:$D,'[2]Рассчет акции'!$F:$F,0) -> 0.4 | V11: =AC11+AF11+AH11+AG11 -> 574.96096 | W11: =IFERROR(V11/S11,0) -> 0.51882418 | X11: =IF(K11>1,('Тарифы ВБ'!$B$9+(K11-1)*'Тарифы ВБ'!$B$10)*'Тарифы ВБ'!$B$15*'Тарифы ВБ'!$B$12+S11*'Тарифы ВБ'!$B$13,'Тарифы ВБ'!$B$8*'Тарифы ВБ'!$B$15*'Тарифы ВБ'!$B$12+S11*'Тарифы ВБ'!$B$13) -> 126.93996 | Y11: =IF(K11>1,'Тарифы ВБ'!$B$9+(K11-1)*'Тарифы ВБ'!$B$10,'Тарифы ВБ'!$B$8) -> 55.8 | Z11: =SUM(X11:Y11) -> 182.73996 | AA11: =IFERROR(Z11/S11,0) -> 0.164898 | AB11: =IF(K11>1,'Тарифы ВБ'!$B$14*'Тарифы ВБ'!$B$16*'Тарифы ВБ'!$B$15+(K11-1)*'Тарифы ВБ'!$B$14,'Тарифы ВБ'!$B$14*'Тарифы ВБ'!B$16*'Тарифы ВБ'!$B$15) -> 32.056 | AC11: =+X11+AB11+Y11 -> 214.79596 | AD11: =AC11/S11*100% -> 0.19382418 | AE11: 0.295 | AF11: =S11*AE11 -> 326.919 | AG11: =1.1*S11*$AG$3 -> 0 | AH11: =S11*$AH$3 -> 33.246 | AI11: =F11+V11 -> 770.31831 | AJ11: =IFERROR(AL11/S11,0) -> 0.23489234 | AK11: =S11-AI11 -> 337.88169 | AL11: =AK11-S11*7% -> 260.30769 | AM11: =AL11/H11 -> 1.7428515 | AN11: 1119 | AO11: =$AN11-$AI11 -> 348.68169 | AP11: =$AO11-$AN11*7% -> 270.35169 | AQ11: =$AP11/$H11*100% -> 1.8100996 | AR11: =$AP11/$AN11 -> 0.24160115 | AS11: =IFERROR(_xlfn.XLOOKUP(A11,'[2]Рассчет акции'!$A:$A,'[2]Рассчет акции'!$BH:$BH),0) -> * | AT11: =IFERROR(_xlfn.XLOOKUP($A11,'[2]Рассчет акции'!$A:$A,'[2]Рассчет акции'!$BC:$BC),0) -> 1108 | AU11: =IFERROR($AW11/$AT11,0) -> 0.23476687 | AV11: =$AT11-$AI11 -> 337.68169 | AW11: =$AV11-$AT11*7% -> 260.12169 | AX11: =$AW11/$H11*100% -> 1.7416062 | AY11: =IFERROR(_xlfn.XLOOKUP(E11,'[2]Рассчет акции'!$D:$D,'[2]Рассчет акции'!$BM:$BM),0) -> 264 | AZ11: =IFERROR(_xlfn.XLOOKUP(E11,'[2]Рассчет акции'!$D:$D,'[2]Рассчет акции'!$BN:$BN),0) -> 999 | BA11: =S11/H11 -> 7.4197887 | BC11: =_xlfn.XLOOKUP(B11,#REF!,#REF!,0) -> #REF! | BD11: =BC11/(100%-BE11) -> #REF! | BE11: =_xlfn.XLOOKUP($B11,'[1]Рассчет акции'!$A:$A,'[1]Рассчет акции'!$J:$J) -> 0.35 | BF11: =BS11+BI11+BJ11+BU11+BK11 -> #REF! | BG11: =IFERROR(BF11/BC11,0) -> 0 | BH11: 0.4 | BI11: =BC11*BH11 -> #REF! | BJ11: =BC11*$BJ$3 -> #REF! | BK11: =K11*$BK$3*30 -> 0 | BL11: =(IF(K11>$BL$3,('Тарифы ОЗОН'!$G$3+ROUNDUP(K11-$BL$3,0)*'Тарифы ОЗОН'!$G$4),'Тарифы ОЗОН'!$G$3)) -> 56.94 | BM11: =$BN$3 -> 35 | BN11: =_xlfn.XLOOKUP(BM11,'Тарифы ОЗОН'!$A:$A,'Тарифы ОЗОН'!$B:$B) -> 1.32 | BO11: =_xlfn.XLOOKUP(BM11,'Тарифы ОЗОН'!$A:$A,'Тарифы ОЗОН'!C:C) -> 0.016 | BP11: =$BP$3 -> 25 | BQ11: =BL11*BN11+BC11*BO11+BP11 -> #REF! | BR11: =$BR$3 -> 0.85 | BS11: =(100%/BR11)*BQ11+(100%/BR11-1)*BL11 -> #REF! | BT11: =IFERROR(BS11/BC11*100%,0) -> 0 | BU11: =BC11*$BU$3 -> #REF! | BV11: =BF11+F11 -> #REF! | BW11: =IFERROR(BY11/BC11,0) -> 0 | BX11: =IFERROR(BC11-BV11,0) -> 0 | BY11: =BX11-BC11*7% -> #REF! | BZ11: =IFERROR(BY11/H11*100%,0) -> 0 | CA11: 1009 | CB11: =IF(BC11=0,0,CA11-BV11) -> #REF! | CC11: =IF(CB11=0,0,CB11-CA11*7%) -> #REF! | CD11: =CC11/H11*100% -> #REF! | CE11: =IFERROR(CC11/CA11,0) -> 0 | CF11: =_xlfn.XLOOKUP(B11,'[1]Рассчет акции'!$A:$A,'[1]Рассчет акции'!$R:$R,0) -> 0 | CG11: =_xlfn.XLOOKUP(B11,'[1]Рассчет акции'!$A:$A,'[1]Рассчет акции'!$M:$M,0) -> 1092 | CH11: =IFERROR($CJ11/$CG11,0) -> 0 | CI11: =IF(BC11>0,CG11-BV11,0) -> #REF! | CJ11: =IF(CI11>0,$CI11-$CG11*7%,0) -> #REF! | CK11: =$CJ11/$H11*100% -> #REF! | CL11: =_xlfn.XLOOKUP(B11,'[1]Рассчет акции'!$A:$A,'[1]Рассчет акции'!$W:$W,0) -> 2 | CM11: =_xlfn.XLOOKUP(B11,'[1]Рассчет акции'!$A:$A,'[1]Рассчет акции'!$X:$X,0) -> 7 | CN11: =BC11/H11 -> #REF! | CO11: =CA11-10%*CA11 -> 908.1 | CP11: =_xlfn.XLOOKUP(B11,'[1]Рассчет акции'!$A:$A,'[1]Рассчет акции'!$Z:$Z,0) -> 0
A12: 176721350 | B12: 2419349585 | C12: AHMA3BW201WH | D12: Мешки/шнурок мелк 3 шт. | E12: 2038606201642 | F12: =SUM(H12:J12) -> 183.44246 | G12: =IFERROR(F12/S12*100%,0) -> 0.24226422 | H12: =IF(_xlfn.XLOOKUP($C12,'Юнит Карго'!$A:$A,'Юнит Карго'!$G:$G)=0,_xlfn.XLOOKUP(E12,'Себес 1С текущ'!G:G,'Себес 1С текущ'!H:H),_xlfn.XLOOKUP($C12,'Юнит Карго'!$A:$A,'Юнит Карго'!$P:$P,0,0)) -> 137.44246 | I12: =_xlfn.XLOOKUP(E12,[3]ТЗ_ФФ!$D:$D,[3]ТЗ_ФФ!$BG:$BG,0) -> 38 | J12: =$J$3 -> 8 | K12: =(L12*M12*N12)/1000 -> 0.945 | L12: 21 | M12: 15 | N12: 3 | O12: =_xlfn.XLOOKUP($C12,'Юнит Карго'!$A:$A,'Юнит Карго'!$T:$T,0,0) -> 0.13 | P12: ОРР 24*34 слайдер 20*30 | Q12: 100 | S12: =T12-(T12*U12) -> 757.2 | T12: =_xlfn.XLOOKUP(E12,'[2]Рассчет акции'!$D:$D,'[2]Рассчет акции'!$G:$G,0) -> 1262 | U12: =_xlfn.XLOOKUP(E12,'[2]Рассчет акции'!$D:$D,'[2]Рассчет акции'!$F:$F,0) -> 0.4 | V12: =AC12+AF12+AH12+AG12 -> 383.83616 | W12: =IFERROR(V12/S12,0) -> 0.50691516 | X12: =IF(K12>1,('Тарифы ВБ'!$B$9+(K12-1)*'Тарифы ВБ'!$B$10)*'Тарифы ВБ'!$B$15*'Тарифы ВБ'!$B$12+S12*'Тарифы ВБ'!$B$13,'Тарифы ВБ'!$B$8*'Тарифы ВБ'!$B$15*'Тарифы ВБ'!$B$12+S12*'Тарифы ВБ'!$B$13) -> 73.74616 | Y12: =IF(K12>1,'Тарифы ВБ'!$B$9+(K12-1)*'Тарифы ВБ'!$B$10,'Тарифы ВБ'!$B$8) -> 32 | Z12: =SUM(X12:Y12) -> 105.74616 | AA12: =IFERROR(Z12/S12,0) -> 0.1396542 | AB12: =IF(K12>1,'Тарифы ВБ'!$B$14*'Тарифы ВБ'!$B$16*'Тарифы ВБ'!$B$15+(K12-1)*'Тарифы ВБ'!$B$14,'Тарифы ВБ'!$B$14*'Тарифы ВБ'!B$16*'Тарифы ВБ'!$B$15) -> 32 | AC12: =+X12+AB12+Y12 -> 137.74616 | AD12: =AC12/S12*100% -> 0.18191516 | AE12: 0.295 | AF12: =S12*AE12 -> 223.374 | AG12: =1.1*S12*$AG$3 -> 0 | AH12: =S12*$AH$3 -> 22.716 | AI12: =F12+V12 -> 567.27862 | AJ12: =IFERROR(AL12/S12,0) -> 0.18082062 | AK12: =S12-AI12 -> 189.92138 | AL12: =AK12-S12*7% -> 136.91738 | AM12: =AL12/H12 -> 0.99617957 | AN12: 839 | AO12: =$AN12-$AI12 -> 271.72138 | AP12: =$AO12-$AN12*7% -> 212.99138 | AQ12: =$AP12/$H12*100% -> 1.5496766 | AR12: =$AP12/$AN12 -> 0.25386338 | AS12: =IFERROR(_xlfn.XLOOKUP(A12,'[2]Рассчет акции'!$A:$A,'[2]Рассчет акции'!$BH:$BH),0) -> * | AT12: =IFERROR(_xlfn.XLOOKUP($A12,'[2]Рассчет акции'!$A:$A,'[2]Рассчет акции'!$BC:$BC),0) -> 757 | AU12: =IFERROR($AW12/$AT12,0) -> 0.18062269 | AV12: =$AT12-$AI12 -> 189.72138 | AW12: =$AV12-$AT12*7% -> 136.73138 | AX12: =$AW12/$H12*100% -> 0.99482627 | AY12: =IFERROR(_xlfn.XLOOKUP(E12,'[2]Рассчет акции'!$D:$D,'[2]Рассчет акции'!$BM:$BM),0) -> 258 | AZ12: =IFERROR(_xlfn.XLOOKUP(E12,'[2]Рассчет акции'!$D:$D,'[2]Рассчет акции'!$BN:$BN),0) -> 334 | BA12: =S12/H12 -> 5.5092144 | BC12: =_xlfn.XLOOKUP(B12,#REF!,#REF!,0) -> #REF! | BD12: =BC12/(100%-BE12) -> #REF! | BE12: =_xlfn.XLOOKUP($B12,'[1]Рассчет акции'!$A:$A,'[1]Рассчет акции'!$J:$J) -> 0.35011136 | BF12: =BS12+BI12+BJ12+BU12+BK12 -> #REF! | BG12: =IFERROR(BF12/BC12,0) -> 0 | BH12: 0.4 | BI12: =BC12*BH12 -> #REF! | BJ12: =BC12*$BJ$3 -> #REF! | BK12: =K12*$BK$3*30 -> 0 | BL12: =(IF(K12>$BL$3,('Тарифы ОЗОН'!$G$3+ROUNDUP(K12-$BL$3,0)*'Тарифы ОЗОН'!$G$4),'Тарифы ОЗОН'!$G$3)) -> 46.77 | BM12: =$BN$3 -> 35 | BN12: =_xlfn.XLOOKUP(BM12,'Тарифы ОЗОН'!$A:$A,'Тарифы ОЗОН'!$B:$B) -> 1.32 | BO12: =_xlfn.XLOOKUP(BM12,'Тарифы ОЗОН'!$A:$A,'Тарифы ОЗОН'!C:C) -> 0.016 | BP12: =$BP$3 -> 25 | BQ12: =BL12*BN12+BC12*BO12+BP12 -> #REF! | BR12: =$BR$3 -> 0.85 | BS12: =(100%/BR12)*BQ12+(100%/BR12-1)*BL12 -> #REF! | BT12: =IFERROR(BS12/BC12*100%,0) -> 0 | BU12: =BC12*$BU$3 -> #REF! | BV12: =BF12+F12 -> #REF! | BW12: =IFERROR(BY12/BC12,0) -> 0 | BX12: =IFERROR(BC12-BV12,0) -> 0 | BY12: =BX12-BC12*7% -> #REF! | BZ12: =IFERROR(BY12/H12*100%,0) -> 0 | CA12: 1099 | CB12: =IF(BC12=0,0,CA12-BV12) -> #REF! | CC12: =IF(CB12=0,0,CB12-CA12*7%) -> #REF! | CD12: =CC12/H12*100% -> #REF! | CE12: =IFERROR(CC12/CA12,0) -> 0 | CF12: =_xlfn.XLOOKUP(B12,'[1]Рассчет акции'!$A:$A,'[1]Рассчет акции'!$R:$R,0) -> 0 | CG12: =_xlfn.XLOOKUP(B12,'[1]Рассчет акции'!$A:$A,'[1]Рассчет акции'!$M:$M,0) -> 1060 | CH12: =IFERROR($CJ12/$CG12,0) -> 0 | CI12: =IF(BC12>0,CG12-BV12,0) -> #REF! | CJ12: =IF(CI12>0,$CI12-$CG12*7%,0) -> #REF! | CK12: =$CJ12/$H12*100% -> #REF! | CL12: =_xlfn.XLOOKUP(B12,'[1]Рассчет акции'!$A:$A,'[1]Рассчет акции'!$W:$W,0) -> 3 | CM12: =_xlfn.XLOOKUP(B12,'[1]Рассчет акции'!$A:$A,'[1]Рассчет акции'!$X:$X,0) -> 999 | CN12: =BC12/H12 -> #REF! | CO12: =CA12-10%*CA12 -> 989.1 | CP12: =_xlfn.XLOOKUP(B12,'[1]Рассчет акции'!$A:$A,'[1]Рассчет акции'!$Z:$Z,0) -> 0
A13: 176723275 | B13: 2419349501 | C13: AHMA3BW202WH | D13: Мешки/шнурок крупн 3 шт. | E13: 2038606256161 | F13: =SUM(H13:J13) -> 183.44246 | G13: =IFERROR(F13/S13*100%,0) -> 0.21869631 | H13: =IF(_xlfn.XLOOKUP($C13,'Юнит Карго'!$A:$A,'Юнит Карго'!$G:$G)=0,_xlfn.XLOOKUP(E13,'Себес 1С текущ'!G:G,'Себес 1С текущ'!H:H),_xlfn.XLOOKUP($C13,'Юнит Карго'!$A:$A,'Юнит Карго'!$P:$P,0,0)) -> 137.44246 | I13: =_xlfn.XLOOKUP(E13,[3]ТЗ_ФФ!$D:$D,[3]ТЗ_ФФ!$BG:$BG,0) -> 38 | J13: =$J$3 -> 8 | K13: =(L13*M13*N13)/1000 -> 0.945 | L13: 21 | M13: 15 | N13: 3 | O13: =_xlfn.XLOOKUP($C13,'Юнит Карго'!$A:$A,'Юнит Карго'!$T:$T,0,0) -> 0.13 | P13: OPP 20*34 слайдер 18*25 | Q13: 100 | S13: =T13-(T13*U13) -> 838.8 | T13: =_xlfn.XLOOKUP(E13,'[2]Рассчет акции'!$D:$D,'[2]Рассчет акции'!$G:$G,0) -> 1398 | U13: =_xlfn.XLOOKUP(E13,'[2]Рассчет акции'!$D:$D,'[2]Рассчет акции'!$F:$F,0) -> 0.4 | V13: =AC13+AF13+AH13+AG13 -> 410.99264 | W13: =IFERROR(V13/S13,0) -> 0.48997692 | X13: =IF(K13>1,('Тарифы ВБ'!$B$9+(K13-1)*'Тарифы ВБ'!$B$10)*'Тарифы ВБ'!$B$15*'Тарифы ВБ'!$B$12+S13*'Тарифы ВБ'!$B$13,'Тарифы ВБ'!$B$8*'Тарифы ВБ'!$B$15*'Тарифы ВБ'!$B$12+S13*'Тарифы ВБ'!$B$13) -> 74.38264 | Y13: =IF(K13>1,'Тарифы ВБ'!$B$9+(K13-1)*'Тарифы ВБ'!$B$10,'Тарифы ВБ'!$B$8) -> 32 | Z13: =SUM(X13:Y13) -> 106.38264 | AA13: =IFERROR(Z13/S13,0) -> 0.12682718 | AB13: =IF(K13>1,'Тарифы ВБ'!$B$14*'Тарифы ВБ'!$B$16*'Тарифы ВБ'!$B$15+(K13-1)*'Тарифы ВБ'!$B$14,'Тарифы ВБ'!$B$14*'Тарифы ВБ'!B$16*'Тарифы ВБ'!$B$15) -> 32 | AC13: =+X13+AB13+Y13 -> 138.38264 | AD13: =AC13/S13*100% -> 0.16497692 | AE13: 0.295 | AF13: =S13*AE13 -> 247.446 | AG13: =1.1*S13*$AG$3 -> 0 | AH13: =S13*$AH$3 -> 25.164 | AI13: =F13+V13 -> 594.4351 | AJ13: =IFERROR(AL13/S13,0) -> 0.22132677 | AK13: =S13-AI13 -> 244.3649 | AL13: =AK13-S13*7% -> 185.6489 | AM13: =AL13/H13 -> 1.350739 | AN13: 839 | AO13: =$AN13-$AI13 -> 244.5649 | AP13: =$AO13-$AN13*7% -> 185.8349 | AQ13: =$AP13/$H13*100% -> 1.3520923 | AR13: =$AP13/$AN13 -> 0.2214957 | AS13: =IFERROR(_xlfn.XLOOKUP(A13,'[2]Рассчет акции'!$A:$A,'[2]Рассчет акции'!$BH:$BH),0) -> 0 | AT13: =IFERROR(_xlfn.XLOOKUP($A13,'[2]Рассчет акции'!$A:$A,'[2]Рассчет акции'!$BC:$BC),0) -> 839 | AU13: =IFERROR($AW13/$AT13,0) -> 0.2214957 | AV13: =$AT13-$AI13 -> 244.5649 | AW13: =$AV13-$AT13*7% -> 185.8349 | AX13: =$AW13/$H13*100% -> 1.3520923 | AY13: =IFERROR(_xlfn.XLOOKUP(E13,'[2]Рассчет акции'!$D:$D,'[2]Рассчет акции'!$BM:$BM),0) -> 92 | AZ13: =IFERROR(_xlfn.XLOOKUP(E13,'[2]Рассчет акции'!$D:$D,'[2]Рассчет акции'!$BN:$BN),0) -> 87 | BA13: =S13/H13 -> 6.1029173 | BC13: =_xlfn.XLOOKUP(B13,#REF!,#REF!,0) -> #REF! | BD13: =BC13/(100%-BE13) -> #REF! | BE13: =_xlfn.XLOOKUP($B13,'[1]Рассчет акции'!$A:$A,'[1]Рассчет акции'!$J:$J) -> 0.35011136 | BF13: =BS13+BI13+BJ13+BU13+BK13 -> #REF! | BG13: =IFERROR(BF13/BC13,0) -> 0 | BH13: 0.4 | BI13: =BC13*BH13 -> #REF! | BJ13: =BC13*$BJ$3 -> #REF! | BK13: =K13*$BK$3*30 -> 0 | BL13: =(IF(K13>$BL$3,('Тарифы ОЗОН'!$G$3+ROUNDUP(K13-$BL$3,0)*'Тарифы ОЗОН'!$G$4),'Тарифы ОЗОН'!$G$3)) -> 46.77 | BM13: =$BN$3 -> 35 | BN13: =_xlfn.XLOOKUP(BM13,'Тарифы ОЗОН'!$A:$A,'Тарифы ОЗОН'!$B:$B) -> 1.32 | BO13: =_xlfn.XLOOKUP(BM13,'Тарифы ОЗОН'!$A:$A,'Тарифы ОЗОН'!C:C) -> 0.016 | BP13: =$BP$3 -> 25 | BQ13: =BL13*BN13+BC13*BO13+BP13 -> #REF! | BR13: =$BR$3 -> 0.85 | BS13: =(100%/BR13)*BQ13+(100%/BR13-1)*BL13 -> #REF! | BT13: =IFERROR(BS13/BC13*100%,0) -> 0 | BU13: =BC13*$BU$3 -> #REF! | BV13: =BF13+F13 -> #REF! | BW13: =IFERROR(BY13/BC13,0) -> 0 | BX13: =IFERROR(BC13-BV13,0) -> 0 | BY13: =BX13-BC13*7% -> #REF! | BZ13: =IFERROR(BY13/H13*100%,0) -> 0 | CA13: 1099 | CB13: =IF(BC13=0,0,CA13-BV13) -> #REF! | CC13: =IF(CB13=0,0,CB13-CA13*7%) -> #REF! | CD13: =CC13/H13*100% -> #REF! | CE13: =IFERROR(CC13/CA13,0) -> 0 | CF13: =_xlfn.XLOOKUP(B13,'[1]Рассчет акции'!$A:$A,'[1]Рассчет акции'!$R:$R,0) -> 0 | CG13: =_xlfn.XLOOKUP(B13,'[1]Рассчет акции'!$A:$A,'[1]Рассчет акции'!$M:$M,0) -> 1060 | CH13: =IFERROR($CJ13/$CG13,0) -> 0 | CI13: =IF(BC13>0,CG13-BV13,0) -> #REF! | CJ13: =IF(CI13>0,$CI13-$CG13*7%,0) -> #REF! | CK13: =$CJ13/$H13*100% -> #REF! | CL13: =_xlfn.XLOOKUP(B13,'[1]Рассчет акции'!$A:$A,'[1]Рассчет акции'!$W:$W,0) -> 8 | CM13: =_xlfn.XLOOKUP(B13,'[1]Рассчет акции'!$A:$A,'[1]Рассчет акции'!$X:$X,0) -> 56 | CN13: =BC13/H13 -> #REF! | CO13: =CA13-10%*CA13 -> 989.1 | CP13: =_xlfn.XLOOKUP(B13,'[1]Рассчет акции'!$A:$A,'[1]Рассчет акции'!$Z:$Z,0) -> 0
A14: 204615141 | B14: 2419349453 | C14: AHMA2BW201WH | D14: Мешки 2 шт. серый | E14: 2039404446068 | F14: =SUM(H14:J14) -> 127.96368 | G14: =IFERROR(F14/S14*100%,0) -> 0.21391454 | H14: =IF(_xlfn.XLOOKUP($C14,'Юнит Карго'!$A:$A,'Юнит Карго'!$G:$G)=0,_xlfn.XLOOKUP(E14,'Себес 1С текущ'!G:G,'Себес 1С текущ'!H:H),_xlfn.XLOOKUP($C14,'Юнит Карго'!$A:$A,'Юнит Карго'!$P:$P,0,0)) -> 84.963676 | I14: =_xlfn.XLOOKUP(E14,[3]ТЗ_ФФ!$D:$D,[3]ТЗ_ФФ!$BG:$BG,0) -> 35 | J14: =$J$3 -> 8 | K14: =(L14*M14*N14)/1000 -> 0.96 | L14: 20 | M14: 16 | N14: 3 | O14: =_xlfn.XLOOKUP($C14,'Юнит Карго'!$A:$A,'Юнит Карго'!$T:$T,0,0) -> 0.06 | P14: ОРР 22*34 слайдер 18*25 | Q14: 90 | S14: =T14-(T14*U14) -> 598.2 | T14: =_xlfn.XLOOKUP(E14,'[2]Рассчет акции'!$D:$D,'[2]Рассчет акции'!$G:$G,0) -> 997 | U14: =_xlfn.XLOOKUP(E14,'[2]Рассчет акции'!$D:$D,'[2]Рассчет акции'!$F:$F,0) -> 0.4 | V14: =AC14+AF14+AH14+AG14 -> 330.92096 | W14: =IFERROR(V14/S14,0) -> 0.55319452 | X14: =IF(K14>1,('Тарифы ВБ'!$B$9+(K14-1)*'Тарифы ВБ'!$B$10)*'Тарифы ВБ'!$B$15*'Тарифы ВБ'!$B$12+S14*'Тарифы ВБ'!$B$13,'Тарифы ВБ'!$B$8*'Тарифы ВБ'!$B$15*'Тарифы ВБ'!$B$12+S14*'Тарифы ВБ'!$B$13) -> 72.50596 | Y14: =IF(K14>1,'Тарифы ВБ'!$B$9+(K14-1)*'Тарифы ВБ'!$B$10,'Тарифы ВБ'!$B$8) -> 32 | Z14: =SUM(X14:Y14) -> 104.50596 | AA14: =IFERROR(Z14/S14,0) -> 0.1747007 | AB14: =IF(K14>1,'Тарифы ВБ'!$B$14*'Тарифы ВБ'!$B$16*'Тарифы ВБ'!$B$15+(K14-1)*'Тарифы ВБ'!$B$14,'Тарифы ВБ'!$B$14*'Тарифы ВБ'!B$16*'Тарифы ВБ'!$B$15) -> 32 | AC14: =+X14+AB14+Y14 -> 136.50596 | AD14: =AC14/S14*100% -> 0.22819452 | AE14: 0.295 | AF14: =S14*AE14 -> 176.469 | AG14: =1.1*S14*$AG$3 -> 0 | AH14: =S14*$AH$3 -> 17.946 | AI14: =F14+V14 -> 458.88464 | AJ14: =IFERROR(AL14/S14,0) -> 0.16289095 | AK14: =S14-AI14 -> 139.31536 | AL14: =AK14-S14*7% -> 97.441364 | AM14: =AL14/H14 -> 1.1468591 | AN14: 659 | AO14: =$AN14-$AI14 -> 200.11536 | AP14: =$AO14-$AN14*7% -> 153.98536 | AQ14: =$AP14/$H14*100% -> 1.812367 | AR14: =$AP14/$AN14 -> 0.2336652 | AS14: =IFERROR(_xlfn.XLOOKUP(A14,'[2]Рассчет акции'!$A:$A,'[2]Рассчет акции'!$BH:$BH),0) -> * | AT14: =IFERROR(_xlfn.XLOOKUP($A14,'[2]Рассчет акции'!$A:$A,'[2]Рассчет акции'!$BC:$BC),0) -> 598 | AU14: =IFERROR($AW14/$AT14,0) -> 0.16263439 | AV14: =$AT14-$AI14 -> 139.11536 | AW14: =$AV14-$AT14*7% -> 97.255364 | AX14: =$AW14/$H14*100% -> 1.1446699 | AY14: =IFERROR(_xlfn.XLOOKUP(E14,'[2]Рассчет акции'!$D:$D,'[2]Рассчет акции'!$BM:$BM),0) -> 222 | AZ14: =IFERROR(_xlfn.XLOOKUP(E14,'[2]Рассчет акции'!$D:$D,'[2]Рассчет акции'!$BN:$BN),0) -> 602 | BA14: =S14/H14 -> 7.0406558 | BC14: =_xlfn.XLOOKUP(B14,#REF!,#REF!,0) -> #REF! | BD14: =BC14/(100%-BE14) -> #REF! | BE14: =_xlfn.XLOOKUP($B14,'[1]Рассчет акции'!$A:$A,'[1]Рассчет акции'!$J:$J) -> 0.3501355 | BF14: =BS14+BI14+BJ14+BU14+BK14 -> #REF! | BG14: =IFERROR(BF14/BC14,0) -> 0 | BH14: 0.4 | BI14: =BC14*BH14 -> #REF! | BJ14: =BC14*$BJ$3 -> #REF! | BK14: =K14*$BK$3*30 -> 0 | BL14: =(IF(K14>$BL$3,('Тарифы ОЗОН'!$G$3+ROUNDUP(K14-$BL$3,0)*'Тарифы ОЗОН'!$G$4),'Тарифы ОЗОН'!$G$3)) -> 46.77 | BM14: =$BN$3 -> 35 | BN14: =_xlfn.XLOOKUP(BM14,'Тарифы ОЗОН'!$A:$A,'Тарифы ОЗОН'!$B:$B) -> 1.32 | BO14: =_xlfn.XLOOKUP(BM14,'Тарифы ОЗОН'!$A:$A,'Тарифы ОЗОН'!C:C) -> 0.016 | BP14: =$BP$3 -> 25 | BQ14: =BL14*BN14+BC14*BO14+BP14 -> #REF! | BR14: =$BR$3 -> 0.85 | BS14: =(100%/BR14)*BQ14+(100%/BR14-1)*BL14 -> #REF! | BT14: =IFERROR(BS14/BC14*100%,0) -> 0 | BU14: =BC14*$BU$3 -> #REF! | BV14: =BF14+F14 -> #REF! | BW14: =IFERROR(BY14/BC14,0) -> 0 | BX14: =IFERROR(BC14-BV14,0) -> 0 | BY14: =BX14-BC14*7% -> #REF! | BZ14: =IFERROR(BY14/H14*100%,0) -> 0 | CA14: 869 | CB14: =IF(BC14=0,0,CA14-BV14) -> #REF! | CC14: =IF(CB14=0,0,CB14-CA14*7%) -> #REF! | CD14: =CC14/H14*100% -> #REF! | CE14: =IFERROR(CC14/CA14,0) -> 0 | CF14: =_xlfn.XLOOKUP(B14,'[1]Рассчет акции'!$A:$A,'[1]Рассчет акции'!$R:$R,0) -> 0 | CG14: =_xlfn.XLOOKUP(B14,'[1]Рассчет акции'!$A:$A,'[1]Рассчет акции'!$M:$M,0) -> 827 | CH14: =IFERROR($CJ14/$CG14,0) -> 0 | CI14: =IF(BC14>0,CG14-BV14,0) -> #REF! | CJ14: =IF(CI14>0,$CI14-$CG14*7%,0) -> #REF! | CK14: =$CJ14/$H14*100% -> #REF! | CL14: =_xlfn.XLOOKUP(B14,'[1]Рассчет акции'!$A:$A,'[1]Рассчет акции'!$W:$W,0) -> 1 | CM14: =_xlfn.XLOOKUP(B14,'[1]Рассчет акции'!$A:$A,'[1]Рассчет акции'!$X:$X,0) -> 7 | CN14: =BC14/H14 -> #REF! | CO14: =CA14-10%*CA14 -> 782.1 | CP14: =_xlfn.XLOOKUP(B14,'[1]Рассчет акции'!$A:$A,'[1]Рассчет акции'!$Z:$Z,0) -> 0
A15: 236074677 | C15: AHMA2BW202WH | D15: Мешки 2 шт. розовый | E15: 2040278862540 | F15: =SUM(H15:J15) -> 185 | G15: =IFERROR(F15/S15*100%,0) -> 0.24666667 | H15: =IF(_xlfn.XLOOKUP($C15,'Юнит Карго'!$A:$A,'Юнит Карго'!$G:$G)=0,_xlfn.XLOOKUP(E15,'Себес 1С текущ'!G:G,'Себес 1С текущ'!H:H),_xlfn.XLOOKUP($C15,'Юнит Карго'!$A:$A,'Юнит Карго'!$P:$P,0,0)) -> 142 | I15: 35 | J15: =$J$3 -> 8 | K15: =(L15*M15*N15)/1000 -> 0.96 | L15: 20 | M15: 16 | N15: 3 | O15: =_xlfn.XLOOKUP($C15,'Юнит Карго'!$A:$A,'Юнит Карго'!$T:$T,0,0) -> 0.095 | P15: 18*25 | Q15: 90 | S15: =T15-(T15*U15) -> 750 | T15: =_xlfn.XLOOKUP(E15,'[2]Рассчет акции'!$D:$D,'[2]Рассчет акции'!$G:$G,0) -> 1250 | U15: =_xlfn.XLOOKUP(E15,'[2]Рассчет акции'!$D:$D,'[2]Рассчет акции'!$F:$F,0) -> 0.4 | V15: =AC15+AF15+AH15+AG15 -> 381.44 | W15: =IFERROR(V15/S15,0) -> 0.50858667 | X15: =IF(K15>1,('Тарифы ВБ'!$B$9+(K15-1)*'Тарифы ВБ'!$B$10)*'Тарифы ВБ'!$B$15*'Тарифы ВБ'!$B$12+S15*'Тарифы ВБ'!$B$13,'Тарифы ВБ'!$B$8*'Тарифы ВБ'!$B$15*'Тарифы ВБ'!$B$12+S15*'Тарифы ВБ'!$B$13) -> 73.69 | Y15: =IF(K15>1,'Тарифы ВБ'!$B$9+(K15-1)*'Тарифы ВБ'!$B$10,'Тарифы ВБ'!$B$8) -> 32 | Z15: =SUM(X15:Y15) -> 105.69 | AA15: =IFERROR(Z15/S15,0) -> 0.14092 | AB15: =IF(K15>1,'Тарифы ВБ'!$B$14*'Тарифы ВБ'!$B$16*'Тарифы ВБ'!$B$15+(K15-1)*'Тарифы ВБ'!$B$14,'Тарифы ВБ'!$B$14*'Тарифы ВБ'!B$16*'Тарифы ВБ'!$B$15) -> 32 | AC15: =+X15+AB15+Y15 -> 137.69 | AD15: =AC15/S15*100% -> 0.18358667 | AE15: 0.295 | AF15: =S15*AE15 -> 221.25 | AG15: =1.1*S15*$AG$3 -> 0 | AH15: =S15*$AH$3 -> 22.5 | AI15: =F15+V15 -> 566.44 | AJ15: =IFERROR(AL15/S15,0) -> 0.17474667 | AK15: =S15-AI15 -> 183.56 | AL15: =AK15-S15*7% -> 131.06 | AM15: =AL15/H15 -> 0.92295775 | AN15: 759 | AO15: =$AN15-$AI15 -> 192.56 | AP15: =$AO15-$AN15*7% -> 139.43 | AQ15: =$AP15/$H15*100% -> 0.98190141 | AR15: =$AP15/$AN15 -> 0.18370224 | AS15: =IFERROR(_xlfn.XLOOKUP(A15,'[2]Рассчет акции'!$A:$A,'[2]Рассчет акции'!$BH:$BH),0) -> * | AT15: =IFERROR(_xlfn.XLOOKUP($A15,'[2]Рассчет акции'!$A:$A,'[2]Рассчет акции'!$BC:$BC),0) -> 750 | AU15: =IFERROR($AW15/$AT15,0) -> 0.17474667 | AV15: =$AT15-$AI15 -> 183.56 | AW15: =$AV15-$AT15*7% -> 131.06 | AX15: =$AW15/$H15*100% -> 0.92295775 | AY15: =IFERROR(_xlfn.XLOOKUP(E15,'[2]Рассчет акции'!$D:$D,'[2]Рассчет акции'!$BM:$BM),0) -> 18 | AZ15: =IFERROR(_xlfn.XLOOKUP(E15,'[2]Рассчет акции'!$D:$D,'[2]Рассчет акции'!$BN:$BN),0) -> 152 | BA15: =S15/H15 -> 5.2816901 | BC15: =_xlfn.XLOOKUP(B15,#REF!,#REF!,0) -> #REF! | BD15: =BC15/(100%-BE15) -> #REF! | BE15: =_xlfn.XLOOKUP($B15,'[1]Рассчет акции'!$A:$A,'[1]Рассчет акции'!$J:$J) -> 0 | BF15: =BS15+BI15+BJ15+BU15+BK15 -> #REF! | BG15: =IFERROR(BF15/BC15,0) -> 0 | BH15: 0.4 | BI15: =BC15*BH15 -> #REF! | BJ15: =BC15*$BJ$3 -> #REF! | BK15: =K15*$BK$3*30 -> 0 | BL15: =(IF(K15>$BL$3,('Тарифы ОЗОН'!$G$3+ROUNDUP(K15-$BL$3,0)*'Тарифы ОЗОН'!$G$4),'Тарифы ОЗОН'!$G$3)) -> 46.77 | BM15: =$BN$3 -> 35 | BN15: =_xlfn.XLOOKUP(BM15,'Тарифы ОЗОН'!$A:$A,'Тарифы ОЗОН'!$B:$B) -> 1.32 | BO15: =_xlfn.XLOOKUP(BM15,'Тарифы ОЗОН'!$A:$A,'Тарифы ОЗОН'!C:C) -> 0.016 | BP15: =$BP$3 -> 25 | BQ15: =BL15*BN15+BC15*BO15+BP15 -> #REF! | BR15: =$BR$3 -> 0.85 | BS15: =(100%/BR15)*BQ15+(100%/BR15-1)*BL15 -> #REF! | BT15: =IFERROR(BS15/BC15*100%,0) -> 0 | BU15: =BC15*$BU$3 -> #REF! | BV15: =BF15+F15 -> #REF! | BW15: =IFERROR(BY15/BC15,0) -> 0 | BX15: =IFERROR(BC15-BV15,0) -> 0 | BY15: =BX15-BC15*7% -> #REF! | BZ15: =IFERROR(BY15/H15*100%,0) -> 0 | CA15: 0 | CB15: =IF(BC15=0,0,CA15-BV15) -> #REF! | CC15: =IF(CB15=0,0,CB15-CA15*7%) -> #REF! | CD15: =CC15/H15*100% -> #REF! | CE15: =IFERROR(CC15/CA15,0) -> 0 | CF15: =_xlfn.XLOOKUP(B15,'[1]Рассчет акции'!$A:$A,'[1]Рассчет акции'!$R:$R,0) -> 0 | CG15: =_xlfn.XLOOKUP(B15,'[1]Рассчет акции'!$A:$A,'[1]Рассчет акции'!$M:$M,0) -> 0 | CH15: =IFERROR($CJ15/$CG15,0) -> 0 | CI15: =IF(BC15>0,CG15-BV15,0) -> #REF! | CJ15: =IF(CI15>0,$CI15-$CG15*7%,0) -> #REF! | CK15: =$CJ15/$H15*100% -> #REF! | CL15: =_xlfn.XLOOKUP(B15,'[1]Рассчет акции'!$A:$A,'[1]Рассчет акции'!$W:$W,0) -> 0 | CM15: =_xlfn.XLOOKUP(B15,'[1]Рассчет акции'!$A:$A,'[1]Рассчет акции'!$X:$X,0) -> 0 | CN15: =BC15/H15 -> #REF! | CO15: =CA15-10%*CA15 -> 0 | CP15: =_xlfn.XLOOKUP(B15,'[1]Рассчет акции'!$A:$A,'[1]Рассчет акции'!$Z:$Z,0) -> 0
A16: 236929187 | B16: 2419349360 | C16: AHMA1BW112WH | D16: Мешок 60*80 крупн | E16: 2040335626849 | F16: =SUM(H16:J16) -> 107.34113 | G16: =IFERROR(F16/S16*100%,0) -> 0.16045011 | H16: =IF(_xlfn.XLOOKUP($C16,'Юнит Карго'!$A:$A,'Юнит Карго'!$G:$G)=0,_xlfn.XLOOKUP(E16,'Себес 1С текущ'!G:G,'Себес 1С текущ'!H:H),_xlfn.XLOOKUP($C16,'Юнит Карго'!$A:$A,'Юнит Карго'!$P:$P,0,0)) -> 85.341127 | I16: =_xlfn.XLOOKUP(E16,[3]ТЗ_ФФ!$D:$D,[3]ТЗ_ФФ!$BG:$BG,0) -> 14 | J16: =$J$3 -> 8 | K16: =(L16*M16*N16)/1000 -> 0.616 | L16: 28 | M16: 22 | N16: 1 | O16: =_xlfn.XLOOKUP($C16,'Юнит Карго'!$A:$A,'Юнит Карго'!$T:$T,0,0) -> 0.1 | P16: своя | S16: =T16-(T16*U16) -> 669 | T16: =_xlfn.XLOOKUP(E16,'[2]Рассчет акции'!$D:$D,'[2]Рассчет акции'!$G:$G,0) -> 1115 | U16: =_xlfn.XLOOKUP(E16,'[2]Рассчет акции'!$D:$D,'[2]Рассчет акции'!$F:$F,0) -> 0.4 | V16: =AC16+AF16+AH16+AG16 -> 354.4832 | W16: =IFERROR(V16/S16,0) -> 0.52987025 | X16: =IF(K16>1,('Тарифы ВБ'!$B$9+(K16-1)*'Тарифы ВБ'!$B$10)*'Тарифы ВБ'!$B$15*'Тарифы ВБ'!$B$12+S16*'Тарифы ВБ'!$B$13,'Тарифы ВБ'!$B$8*'Тарифы ВБ'!$B$15*'Тарифы ВБ'!$B$12+S16*'Тарифы ВБ'!$B$13) -> 73.0582 | Y16: =IF(K16>1,'Тарифы ВБ'!$B$9+(K16-1)*'Тарифы ВБ'!$B$10,'Тарифы ВБ'!$B$8) -> 32 | Z16: =SUM(X16:Y16) -> 105.0582 | AA16: =IFERROR(Z16/S16,0) -> 0.15703767 | AB16: =IF(K16>1,'Тарифы ВБ'!$B$14*'Тарифы ВБ'!$B$16*'Тарифы ВБ'!$B$15+(K16-1)*'Тарифы ВБ'!$B$14,'Тарифы ВБ'!$B$14*'Тарифы ВБ'!B$16*'Тарифы ВБ'!$B$15) -> 32 | AC16: =+X16+AB16+Y16 -> 137.0582 | AD16: =AC16/S16*100% -> 0.20487025 | AE16: 0.295 | AF16: =S16*AE16 -> 197.355 | AG16: =1.1*S16*$AG$3 -> 0 | AH16: =S16*$AH$3 -> 20.07 | AI16: =F16+V16 -> 461.82433 | AJ16: =IFERROR(AL16/S16,0) -> 0.23967963 | AK16: =S16-AI16 -> 207.17567 | AL16: =AK16-S16*7% -> 160.34567 | AM16: =AL16/H16 -> 1.8788793 | AN16: 669 | AO16: =$AN16-$AI16 -> 207.17567 | AP16: =$AO16-$AN16*7% -> 160.34567 | AQ16: =$AP16/$H16*100% -> 1.8788793 | AR16: =$AP16/$AN16 -> 0.23967963 | AS16: =IFERROR(_xlfn.XLOOKUP(A16,'[2]Рассчет акции'!$A:$A,'[2]Рассчет акции'!$BH:$BH),0) -> 0 | AT16: =IFERROR(_xlfn.XLOOKUP($A16,'[2]Рассчет акции'!$A:$A,'[2]Рассчет акции'!$BC:$BC),0) -> 669 | AU16: =IFERROR($AW16/$AT16,0) -> 0.23967963 | AV16: =$AT16-$AI16 -> 207.17567 | AW16: =$AV16-$AT16*7% -> 160.34567 | AX16: =$AW16/$H16*100% -> 1.8788793 | AY16: =IFERROR(_xlfn.XLOOKUP(E16,'[2]Рассчет акции'!$D:$D,'[2]Рассчет акции'!$BM:$BM),0) -> 94 | AZ16: =IFERROR(_xlfn.XLOOKUP(E16,'[2]Рассчет акции'!$D:$D,'[2]Рассчет акции'!$BN:$BN),0) -> 72 | BA16: =S16/H16 -> 7.8391278 | BC16: =_xlfn.XLOOKUP(B16,#REF!,#REF!,0) -> #REF! | BD16: =BC16/(100%-BE16) -> #REF! | BE16: =_xlfn.XLOOKUP($B16,'[1]Рассчет акции'!$A:$A,'[1]Рассчет акции'!$J:$J) -> 0.3500887 | BF16: =BS16+BI16+BJ16+BU16+BK16 -> #REF! | BG16: =IFERROR(BF16/BC16,0) -> 0 | BH16: 0.4 | BI16: =BC16*BH16 -> #REF! | BJ16: =BC16*$BJ$3 -> #REF! | BK16: =K16*$BK$3*30 -> 0 | BL16: =(IF(K16>$BL$3,('Тарифы ОЗОН'!$G$3+ROUNDUP(K16-$BL$3,0)*'Тарифы ОЗОН'!$G$4),'Тарифы ОЗОН'!$G$3)) -> 46.77 | BM16: =$BN$3 -> 35 | BN16: =_xlfn.XLOOKUP(BM16,'Тарифы ОЗОН'!$A:$A,'Тарифы ОЗОН'!$B:$B) -> 1.32 | BO16: =_xlfn.XLOOKUP(BM16,'Тарифы ОЗОН'!$A:$A,'Тарифы ОЗОН'!C:C) -> 0.016 | BP16: =$BP$3 -> 25 | BQ16: =BL16*BN16+BC16*BO16+BP16 -> #REF! | BR16: =$BR$3 -> 0.85 | BS16: =(100%/BR16)*BQ16+(100%/BR16-1)*BL16 -> #REF! | BT16: =IFERROR(BS16/BC16*100%,0) -> 0 | BU16: =BC16*$BU$3 -> #REF! | BV16: =BF16+F16 -> #REF! | BW16: =IFERROR(BY16/BC16,0) -> 0 | BX16: =IFERROR(BC16-BV16,0) -> 0 | BY16: =BX16-BC16*7% -> #REF! | BZ16: =IFERROR(BY16/H16*100%,0) -> 0 | CA16: 859 | CB16: =IF(BC16=0,0,CA16-BV16) -> #REF! | CC16: =IF(CB16=0,0,CB16-CA16*7%) -> #REF! | CD16: =CC16/H16*100% -> #REF! | CE16: =IFERROR(CC16/CA16,0) -> 0 | CF16: =_xlfn.XLOOKUP(B16,'[1]Рассчет акции'!$A:$A,'[1]Рассчет акции'!$R:$R,0) -> 0 | CG16: =_xlfn.XLOOKUP(B16,'[1]Рассчет акции'!$A:$A,'[1]Рассчет акции'!$M:$M,0) -> 670 | CH16: =IFERROR($CJ16/$CG16,0) -> 0 | CI16: =IF(BC16>0,CG16-BV16,0) -> #REF! | CJ16: =IF(CI16>0,$CI16-$CG16*7%,0) -> #REF! | CK16: =$CJ16/$H16*100% -> #REF! | CL16: =_xlfn.XLOOKUP(B16,'[1]Рассчет акции'!$A:$A,'[1]Рассчет акции'!$W:$W,0) -> 1 | CM16: =_xlfn.XLOOKUP(B16,'[1]Рассчет акции'!$A:$A,'[1]Рассчет акции'!$X:$X,0) -> 7 | CN16: =BC16/H16 -> #REF! | CO16: =CA16-10%*CA16 -> 773.1 | CP16: =_xlfn.XLOOKUP(B16,'[1]Рассчет акции'!$A:$A,'[1]Рассчет акции'!$Z:$Z,0) -> 0
A17: 236929188 | B17: 2419349422 | C17: AHMA1BW111WH | D17: Мешок 60*80 мелк | E17: 2040335648124 | F17: =SUM(H17:J17) -> 107.34113 | G17: =IFERROR(F17/S17*100%,0) -> 0.16040216 | H17: =IF(_xlfn.XLOOKUP($C17,'Юнит Карго'!$A:$A,'Юнит Карго'!$G:$G)=0,_xlfn.XLOOKUP(E17,'Себес 1С текущ'!G:G,'Себес 1С текущ'!H:H),_xlfn.XLOOKUP($C17,'Юнит Карго'!$A:$A,'Юнит Карго'!$P:$P,0,0)) -> 85.341127 | I17: =_xlfn.XLOOKUP(E17,[3]ТЗ_ФФ!$D:$D,[3]ТЗ_ФФ!$BG:$BG,0) -> 14 | J17: =$J$3 -> 8 | K17: =(L17*M17*N17)/1000 -> 0.616 | L17: 28 | M17: 22 | N17: 1 | O17: =_xlfn.XLOOKUP($C17,'Юнит Карго'!$A:$A,'Юнит Карго'!$T:$T,0,0) -> 0.1 | P17: своя | S17: =T17-(T17*U17) -> 669.2 | T17: =_xlfn.XLOOKUP(E17,'[2]Рассчет акции'!$D:$D,'[2]Рассчет акции'!$G:$G,0) -> 956 | U17: =_xlfn.XLOOKUP(E17,'[2]Рассчет акции'!$D:$D,'[2]Рассчет акции'!$F:$F,0) -> 0.3 | V17: =AC17+AF17+AH17+AG17 -> 354.54976 | W17: =IFERROR(V17/S17,0) -> 0.52981136 | X17: =IF(K17>1,('Тарифы ВБ'!$B$9+(K17-1)*'Тарифы ВБ'!$B$10)*'Тарифы ВБ'!$B$15*'Тарифы ВБ'!$B$12+S17*'Тарифы ВБ'!$B$13,'Тарифы ВБ'!$B$8*'Тарифы ВБ'!$B$15*'Тарифы ВБ'!$B$12+S17*'Тарифы ВБ'!$B$13) -> 73.05976 | Y17: =IF(K17>1,'Тарифы ВБ'!$B$9+(K17-1)*'Тарифы ВБ'!$B$10,'Тарифы ВБ'!$B$8) -> 32 | Z17: =SUM(X17:Y17) -> 105.05976 | AA17: =IFERROR(Z17/S17,0) -> 0.15699307 | AB17: =IF(K17>1,'Тарифы ВБ'!$B$14*'Тарифы ВБ'!$B$16*'Тарифы ВБ'!$B$15+(K17-1)*'Тарифы ВБ'!$B$14,'Тарифы ВБ'!$B$14*'Тарифы ВБ'!B$16*'Тарифы ВБ'!$B$15) -> 32 | AC17: =+X17+AB17+Y17 -> 137.05976 | AD17: =AC17/S17*100% -> 0.20481136 | AE17: 0.295 | AF17: =S17*AE17 -> 197.414 | AG17: =1.1*S17*$AG$3 -> 0 | AH17: =S17*$AH$3 -> 20.076 | AI17: =F17+V17 -> 461.89089 | AJ17: =IFERROR(AL17/S17,0) -> 0.23978648 | AK17: =S17-AI17 -> 207.30911 | AL17: =AK17-S17*7% -> 160.46511 | AM17: =AL17/H17 -> 1.8802788 | AN17: 669 | AO17: =$AN17-$AI17 -> 207.10911 | AP17: =$AO17-$AN17*7% -> 160.27911 | AQ17: =$AP17/$H17*100% -> 1.8780993 | AR17: =$AP17/$AN17 -> 0.23958014 | AS17: =IFERROR(_xlfn.XLOOKUP(A17,'[2]Рассчет акции'!$A:$A,'[2]Рассчет акции'!$BH:$BH),0) -> * | AT17: =IFERROR(_xlfn.XLOOKUP($A17,'[2]Рассчет акции'!$A:$A,'[2]Рассчет акции'!$BC:$BC),0) -> 0 | AU17: =IFERROR($AW17/$AT17,0) -> 0 | AV17: =$AT17-$AI17 -> -461.89089 | AW17: =$AV17-$AT17*7% -> -461.89089 | AX17: =$AW17/$H17*100% -> -5.4122895 | AY17: =IFERROR(_xlfn.XLOOKUP(E17,'[2]Рассчет акции'!$D:$D,'[2]Рассчет акции'!$BM:$BM),0) -> 130 | AZ17: =IFERROR(_xlfn.XLOOKUP(E17,'[2]Рассчет акции'!$D:$D,'[2]Рассчет акции'!$BN:$BN),0) -> 999 | BA17: =S17/H17 -> 7.8414713 | BC17: =_xlfn.XLOOKUP(B17,#REF!,#REF!,0) -> #REF! | BD17: =BC17/(100%-BE17) -> #REF! | BE17: =_xlfn.XLOOKUP($B17,'[1]Рассчет акции'!$A:$A,'[1]Рассчет акции'!$J:$J) -> 0.3500887 | BF17: =BS17+BI17+BJ17+BU17+BK17 -> #REF! | BG17: =IFERROR(BF17/BC17,0) -> 0 | BH17: 0.4 | BI17: =BC17*BH17 -> #REF! | BJ17: =BC17*$BJ$3 -> #REF! | BK17: =K17*$BK$3*30 -> 0 | BL17: =(IF(K17>$BL$3,('Тарифы ОЗОН'!$G$3+ROUNDUP(K17-$BL$3,0)*'Тарифы ОЗОН'!$G$4),'Тарифы ОЗОН'!$G$3)) -> 46.77 | BM17: =$BN$3 -> 35 | BN17: =_xlfn.XLOOKUP(BM17,'Тарифы ОЗОН'!$A:$A,'Тарифы ОЗОН'!$B:$B) -> 1.32 | BO17: =_xlfn.XLOOKUP(BM17,'Тарифы ОЗОН'!$A:$A,'Тарифы ОЗОН'!C:C) -> 0.016 | BP17: =$BP$3 -> 25 | BQ17: =BL17*BN17+BC17*BO17+BP17 -> #REF! | BR17: =$BR$3 -> 0.85 | BS17: =(100%/BR17)*BQ17+(100%/BR17-1)*BL17 -> #REF! | BT17: =IFERROR(BS17/BC17*100%,0) -> 0 | BU17: =BC17*$BU$3 -> #REF! | BV17: =BF17+F17 -> #REF! | BW17: =IFERROR(BY17/BC17,0) -> 0 | BX17: =IFERROR(BC17-BV17,0) -> 0 | BY17: =BX17-BC17*7% -> #REF! | BZ17: =IFERROR(BY17/H17*100%,0) -> 0 | CA17: 859 | CB17: =IF(BC17=0,0,CA17-BV17) -> #REF! | CC17: =IF(CB17=0,0,CB17-CA17*7%) -> #REF! | CD17: =CC17/H17*100% -> #REF! | CE17: =IFERROR(CC17/CA17,0) -> 0 | CF17: =_xlfn.XLOOKUP(B17,'[1]Рассчет акции'!$A:$A,'[1]Рассчет акции'!$R:$R,0) -> 0 | CG17: =_xlfn.XLOOKUP(B17,'[1]Рассчет акции'!$A:$A,'[1]Рассчет акции'!$M:$M,0) -> 670 | CH17: =IFERROR($CJ17/$CG17,0) -> 0 | CI17: =IF(BC17>0,CG17-BV17,0) -> #REF! | CJ17: =IF(CI17>0,$CI17-$CG17*7%,0) -> #REF! | CK17: =$CJ17/$H17*100% -> #REF! | CL17: =_xlfn.XLOOKUP(B17,'[1]Рассчет акции'!$A:$A,'[1]Рассчет акции'!$W:$W,0) -> 0 | CM17: =_xlfn.XLOOKUP(B17,'[1]Рассчет акции'!$A:$A,'[1]Рассчет акции'!$X:$X,0) -> 0 | CN17: =BC17/H17 -> #REF! | CO17: =CA17-10%*CA17 -> 773.1 | CP17: =_xlfn.XLOOKUP(B17,'[1]Рассчет акции'!$A:$A,'[1]Рассчет акции'!$Z:$Z,0) -> 0
A18: 239235150 | C18: AHMA1BW301WH | D18: Мешок для обуви L - 30 см | E18: 2040478720961 | F18: 115 | G18: =IFERROR(F18/S18*100%,0) -> 0.23288781 | H18: =IF(_xlfn.XLOOKUP($C18,'Юнит Карго'!$A:$A,'Юнит Карго'!$G:$G)=0,_xlfn.XLOOKUP(E18,'Себес 1С текущ'!G:G,'Себес 1С текущ'!H:H),_xlfn.XLOOKUP($C18,'Юнит Карго'!$A:$A,'Юнит Карго'!$P:$P,0,0)) -> 139 | I18: 14 | J18: =$J$3 -> 8 | K18: =(L18*M18*N18)/1000 -> 0.969 | L18: 19 | M18: 17 | N18: 3 | O18: =_xlfn.XLOOKUP($C18,'Юнит Карго'!$A:$A,'Юнит Карго'!$T:$T,0,0) -> 0 | P18: 22*34 | Q18: 100 | S18: =T18-(T18*U18) -> 493.8 | T18: =_xlfn.XLOOKUP(E18,'[2]Рассчет акции'!$D:$D,'[2]Рассчет акции'!$G:$G,0) -> 823 | U18: =_xlfn.XLOOKUP(E18,'[2]Рассчет акции'!$D:$D,'[2]Рассчет акции'!$F:$F,0) -> 0.4 | V18: =AC18+AF18+AH18+AG18 -> 296.17664 | W18: =IFERROR(V18/S18,0) -> 0.59979068 | X18: =IF(K18>1,('Тарифы ВБ'!$B$9+(K18-1)*'Тарифы ВБ'!$B$10)*'Тарифы ВБ'!$B$15*'Тарифы ВБ'!$B$12+S18*'Тарифы ВБ'!$B$13,'Тарифы ВБ'!$B$8*'Тарифы ВБ'!$B$15*'Тарифы ВБ'!$B$12+S18*'Тарифы ВБ'!$B$13) -> 71.69164 | Y18: =IF(K18>1,'Тарифы ВБ'!$B$9+(K18-1)*'Тарифы ВБ'!$B$10,'Тарифы ВБ'!$B$8) -> 32 | Z18: =SUM(X18:Y18) -> 103.69164 | AA18: =IFERROR(Z18/S18,0) -> 0.20998712 | AB18: =IF(K18>1,'Тарифы ВБ'!$B$14*'Тарифы ВБ'!$B$16*'Тарифы ВБ'!$B$15+(K18-1)*'Тарифы ВБ'!$B$14,'Тарифы ВБ'!$B$14*'Тарифы ВБ'!B$16*'Тарифы ВБ'!$B$15) -> 32 | AC18: =+X18+AB18+Y18 -> 135.69164 | AD18: =AC18/S18*100% -> 0.27479068 | AE18: 0.295 | AF18: =S18*AE18 -> 145.671 | AG18: =1.1*S18*$AG$3 -> 0 | AH18: =S18*$AH$3 -> 14.814 | AI18: =F18+V18 -> 411.17664 | AJ18: =IFERROR(AL18/S18,0) -> 0.097321507 | AK18: =S18-AI18 -> 82.62336 | AL18: =AK18-S18*7% -> 48.05736 | AM18: =AL18/H18 -> 0.3457364 | AN18: 499 | AO18: =$AN18-$AI18 -> 87.82336 | AP18: =$AO18-$AN18*7% -> 52.89336 | AQ18: =$AP18/$H18*100% -> 0.38052777 | AR18: =$AP18/$AN18 -> 0.10599872 | AS18: =IFERROR(_xlfn.XLOOKUP(A18,'[2]Рассчет акции'!$A:$A,'[2]Рассчет акции'!$BH:$BH),0) -> 0 | AT18: =IFERROR(_xlfn.XLOOKUP($A18,'[2]Рассчет акции'!$A:$A,'[2]Рассчет акции'!$BC:$BC),0) -> 494 | AU18: =IFERROR($AW18/$AT18,0) -> 0.097658623 | AV18: =$AT18-$AI18 -> 82.82336 | AW18: =$AV18-$AT18*7% -> 48.24336 | AX18: =$AW18/$H18*100% -> 0.34707453 | AY18: =IFERROR(_xlfn.XLOOKUP(E18,'[2]Рассчет акции'!$D:$D,'[2]Рассчет акции'!$BM:$BM),0) -> 1 | AZ18: =IFERROR(_xlfn.XLOOKUP(E18,'[2]Рассчет акции'!$D:$D,'[2]Рассчет акции'!$BN:$BN),0) -> 18 | BA18: =S18/H18 -> 3.552518 | BC18: =_xlfn.XLOOKUP(B18,#REF!,#REF!,0) -> #REF! | BD18: =BC18/(100%-BE18) -> #REF! | BE18: =_xlfn.XLOOKUP($B18,'[1]Рассчет акции'!$A:$A,'[1]Рассчет акции'!$J:$J) -> 0 | BF18: =BS18+BI18+BJ18+BU18+BK18 -> #REF! | BG18: =IFERROR(BF18/BC18,0) -> 0 | BH18: 0.4 | BI18: =BC18*BH18 -> #REF! | BJ18: =BC18*$BJ$3 -> #REF! | BK18: =K18*$BK$3*30 -> 0 | BL18: =(IF(K18>$BL$3,('Тарифы ОЗОН'!$G$3+ROUNDUP(K18-$BL$3,0)*'Тарифы ОЗОН'!$G$4),'Тарифы ОЗОН'!$G$3)) -> 46.77 | BM18: =$BN$3 -> 35 | BN18: =_xlfn.XLOOKUP(BM18,'Тарифы ОЗОН'!$A:$A,'Тарифы ОЗОН'!$B:$B) -> 1.32 | BO18: =_xlfn.XLOOKUP(BM18,'Тарифы ОЗОН'!$A:$A,'Тарифы ОЗОН'!C:C) -> 0.016 | BP18: =$BP$3 -> 25 | BQ18: =BL18*BN18+BC18*BO18+BP18 -> #REF! | BR18: =$BR$3 -> 0.85 | BS18: =(100%/BR18)*BQ18+(100%/BR18-1)*BL18 -> #REF! | BT18: =IFERROR(BS18/BC18*100%,0) -> 0 | BU18: =BC18*$BU$3 -> #REF! | BV18: =BF18+F18 -> #REF! | BW18: =IFERROR(BY18/BC18,0) -> 0 | BX18: =IFERROR(BC18-BV18,0) -> 0 | BY18: =BX18-BC18*7% -> #REF! | BZ18: =IFERROR(BY18/H18*100%,0) -> 0 | CA18: 0 | CB18: =IF(BC18=0,0,CA18-BV18) -> #REF! | CC18: =IF(CB18=0,0,CB18-CA18*7%) -> #REF! | CD18: =CC18/H18*100% -> #REF! | CE18: =IFERROR(CC18/CA18,0) -> 0 | CF18: =_xlfn.XLOOKUP(B18,'[1]Рассчет акции'!$A:$A,'[1]Рассчет акции'!$R:$R,0) -> 0 | CG18: =_xlfn.XLOOKUP(B18,'[1]Рассчет акции'!$A:$A,'[1]Рассчет акции'!$M:$M,0) -> 0 | CH18: =IFERROR($CJ18/$CG18,0) -> 0 | CI18: =IF(BC18>0,CG18-BV18,0) -> #REF! | CJ18: =IF(CI18>0,$CI18-$CG18*7%,0) -> #REF! | CK18: =$CJ18/$H18*100% -> #REF! | CL18: =_xlfn.XLOOKUP(B18,'[1]Рассчет акции'!$A:$A,'[1]Рассчет акции'!$W:$W,0) -> 0 | CM18: =_xlfn.XLOOKUP(B18,'[1]Рассчет акции'!$A:$A,'[1]Рассчет акции'!$X:$X,0) -> 0 | CN18: =BC18/H18 -> #REF! | CO18: =CA18-10%*CA18 -> 0 | CP18: =_xlfn.XLOOKUP(B18,'[1]Рассчет акции'!$A:$A,'[1]Рассчет акции'!$Z:$Z,0) -> 0
A19: 239233529 | C19: AHMA1BW302WH | D19: Мешок для обуви XL - 35 см | E19: 2040478696884 | F19: 144 | G19: =IFERROR(F19/S19*100%,0) -> 0.20512821 | H19: =IF(_xlfn.XLOOKUP($C19,'Юнит Карго'!$A:$A,'Юнит Карго'!$G:$G)=0,_xlfn.XLOOKUP(E19,'Себес 1С текущ'!G:G,'Себес 1С текущ'!H:H),_xlfn.XLOOKUP($C19,'Юнит Карго'!$A:$A,'Юнит Карго'!$P:$P,0,0)) -> 110 | I19: 14 | J19: =$J$3 -> 8 | K19: =(L19*M19*N19)/1000 -> 1.936 | L19: 22 | M19: 22 | N19: 4 | O19: =_xlfn.XLOOKUP($C19,'Юнит Карго'!$A:$A,'Юнит Карго'!$T:$T,0,0) -> 0 | P19: 24*34 | Q19: 80 | S19: =T19-(T19*U19) -> 702 | T19: =_xlfn.XLOOKUP(E19,'[2]Рассчет акции'!$D:$D,'[2]Рассчет акции'!$G:$G,0) -> 1170 | U19: =_xlfn.XLOOKUP(E19,'[2]Рассчет акции'!$D:$D,'[2]Рассчет акции'!$F:$F,0) -> 0.4 | V19: =AC19+AF19+AH19+AG19 -> 450.10496 | W19: =IFERROR(V19/S19,0) -> 0.64117516 | X19: =IF(K19>1,('Тарифы ВБ'!$B$9+(K19-1)*'Тарифы ВБ'!$B$10)*'Тарифы ВБ'!$B$15*'Тарифы ВБ'!$B$12+S19*'Тарифы ВБ'!$B$13,'Тарифы ВБ'!$B$8*'Тарифы ВБ'!$B$15*'Тарифы ВБ'!$B$12+S19*'Тарифы ВБ'!$B$13) -> 130.77608 | Y19: =IF(K19>1,'Тарифы ВБ'!$B$9+(K19-1)*'Тарифы ВБ'!$B$10,'Тарифы ВБ'!$B$8) -> 59.104 | Z19: =SUM(X19:Y19) -> 189.88008 | AA19: =IFERROR(Z19/S19,0) -> 0.27048444 | AB19: =IF(K19>1,'Тарифы ВБ'!$B$14*'Тарифы ВБ'!$B$16*'Тарифы ВБ'!$B$15+(K19-1)*'Тарифы ВБ'!$B$14,'Тарифы ВБ'!$B$14*'Тарифы ВБ'!B$16*'Тарифы ВБ'!$B$15) -> 32.07488 | AC19: =+X19+AB19+Y19 -> 221.95496 | AD19: =AC19/S19*100% -> 0.31617516 | AE19: 0.295 | AF19: =S19*AE19 -> 207.09 | AG19: =1.1*S19*$AG$3 -> 0 | AH19: =S19*$AH$3 -> 21.06 | AI19: =F19+V19 -> 594.10496 | AJ19: =IFERROR(AL19/S19,0) -> 0.083696638 | AK19: =S19-AI19 -> 107.89504 | AL19: =AK19-S19*7% -> 58.75504 | AM19: =AL19/H19 -> 0.53413673 | AN19: 709 | AO19: =$AN19-$AI19 -> 114.89504 | AP19: =$AO19-$AN19*7% -> 65.26504 | AQ19: =$AP19/$H19*100% -> 0.59331855 | AR19: =$AP19/$AN19 -> 0.092052243 | AS19: =IFERROR(_xlfn.XLOOKUP(A19,'[2]Рассчет акции'!$A:$A,'[2]Рассчет акции'!$BH:$BH),0) -> * | AT19: =IFERROR(_xlfn.XLOOKUP($A19,'[2]Рассчет акции'!$A:$A,'[2]Рассчет акции'!$BC:$BC),0) -> 702 | AU19: =IFERROR($AW19/$AT19,0) -> 0.083696638 | AV19: =$AT19-$AI19 -> 107.89504 | AW19: =$AV19-$AT19*7% -> 58.75504 | AX19: =$AW19/$H19*100% -> 0.53413673 | AY19: =IFERROR(_xlfn.XLOOKUP(E19,'[2]Рассчет акции'!$D:$D,'[2]Рассчет акции'!$BM:$BM),0) -> 55 | AZ19: =IFERROR(_xlfn.XLOOKUP(E19,'[2]Рассчет акции'!$D:$D,'[2]Рассчет акции'!$BN:$BN),0) -> 290 | BA19: =S19/H19 -> 6.3818182 | BC19: =_xlfn.XLOOKUP(B19,#REF!,#REF!,0) -> #REF! | BD19: =BC19/(100%-BE19) -> #REF! | BE19: =_xlfn.XLOOKUP($B19,'[1]Рассчет акции'!$A:$A,'[1]Рассчет акции'!$J:$J) -> 0 | BF19: =BS19+BI19+BJ19+BU19+BK19 -> #REF! | BG19: =IFERROR(BF19/BC19,0) -> 0 | BH19: 0.4 | BI19: =BC19*BH19 -> #REF! | BJ19: =BC19*$BJ$3 -> #REF! | BK19: =K19*$BK$3*30 -> 0 | BL19: =(IF(K19>$BL$3,('Тарифы ОЗОН'!$G$3+ROUNDUP(K19-$BL$3,0)*'Тарифы ОЗОН'!$G$4),'Тарифы ОЗОН'!$G$3)) -> 56.94 | BM19: =$BN$3 -> 35 | BN19: =_xlfn.XLOOKUP(BM19,'Тарифы ОЗОН'!$A:$A,'Тарифы ОЗОН'!$B:$B) -> 1.32 | BO19: =_xlfn.XLOOKUP(BM19,'Тарифы ОЗОН'!$A:$A,'Тарифы ОЗОН'!C:C) -> 0.016 | BP19: =$BP$3 -> 25 | BQ19: =BL19*BN19+BC19*BO19+BP19 -> #REF! | BR19: =$BR$3 -> 0.85 | BS19: =(100%/BR19)*BQ19+(100%/BR19-1)*BL19 -> #REF! | BT19: =IFERROR(BS19/BC19*100%,0) -> 0 | BU19: =BC19*$BU$3 -> #REF! | BV19: =BF19+F19 -> #REF! | BW19: =IFERROR(BY19/BC19,0) -> 0 | BX19: =IFERROR(BC19-BV19,0) -> 0 | BY19: =BX19-BC19*7% -> #REF! | BZ19: =IFERROR(BY19/H19*100%,0) -> 0 | CA19: 0 | CB19: =IF(BC19=0,0,CA19-BV19) -> #REF! | CC19: =IF(CB19=0,0,CB19-CA19*7%) -> #REF! | CD19: =CC19/H19*100% -> #REF! | CE19: =IFERROR(CC19/CA19,0) -> 0 | CF19: =_xlfn.XLOOKUP(B19,'[1]Рассчет акции'!$A:$A,'[1]Рассчет акции'!$R:$R,0) -> 0 | CG19: =_xlfn.XLOOKUP(B19,'[1]Рассчет акции'!$A:$A,'[1]Рассчет акции'!$M:$M,0) -> 0 | CH19: =IFERROR($CJ19/$CG19,0) -> 0 | CI19: =IF(BC19>0,CG19-BV19,0) -> #REF! | CJ19: =IF(CI19>0,$CI19-$CG19*7%,0) -> #REF! | CK19: =$CJ19/$H19*100% -> #REF! | CL19: =_xlfn.XLOOKUP(B19,'[1]Рассчет акции'!$A:$A,'[1]Рассчет акции'!$W:$W,0) -> 0 | CM19: =_xlfn.XLOOKUP(B19,'[1]Рассчет акции'!$A:$A,'[1]Рассчет акции'!$X:$X,0) -> 0 | CN19: =BC19/H19 -> #REF! | CO19: =CA19-10%*CA19 -> 0 | CP19: =_xlfn.XLOOKUP(B19,'[1]Рассчет акции'!$A:$A,'[1]Рассчет акции'!$Z:$Z,0) -> 0
A20: 173605843 | B20: 1597441701 | C20: ACRH1MS101RJ | D20: Массажер для пальцев | E20: 2038430289250 | F20: =SUM(H20:J20) -> 81 | G20: =IFERROR(F20/S20*100%,0) -> 0.23601399 | H20: =IF(_xlfn.XLOOKUP($C20,'Юнит Карго'!$A:$A,'Юнит Карго'!$G:$G)=0,_xlfn.XLOOKUP(E20,'Себес 1С текущ'!G:G,'Себес 1С текущ'!H:H),_xlfn.XLOOKUP($C20,'Юнит Карго'!$A:$A,'Юнит Карго'!$P:$P,0,0)) -> 59 | I20: =_xlfn.XLOOKUP(E20,[3]ТЗ_ФФ!$D:$D,[3]ТЗ_ФФ!$BG:$BG,0) -> 14 | J20: =$J$3 -> 8 | K20: =(L20*M20*N20)/1000 -> 0.24 | L20: 15 | M20: 4 | N20: 4 | O20: =_xlfn.XLOOKUP($C20,'Юнит Карго'!$A:$A,'Юнит Карго'!$T:$T,0,0) -> 0.04 | P20: своя | Q20: 300 | S20: =T20-(T20*U20) -> 343.2 | T20: =_xlfn.XLOOKUP(E20,'[2]Рассчет акции'!$D:$D,'[2]Рассчет акции'!$G:$G,0) -> 572 | U20: =_xlfn.XLOOKUP(E20,'[2]Рассчет акции'!$D:$D,'[2]Рассчет акции'!$F:$F,0) -> 0.4 | V20: =AC20+AF20+AH20+AG20 -> 252.92096 | W20: =IFERROR(V20/S20,0) -> 0.73694918 | X20: =IF(K20>1,('Тарифы ВБ'!$B$9+(K20-1)*'Тарифы ВБ'!$B$10)*'Тарифы ВБ'!$B$15*'Тарифы ВБ'!$B$12+S20*'Тарифы ВБ'!$B$13,'Тарифы ВБ'!$B$8*'Тарифы ВБ'!$B$15*'Тарифы ВБ'!$B$12+S20*'Тарифы ВБ'!$B$13) -> 70.51696 | Y20: =IF(K20>1,'Тарифы ВБ'!$B$9+(K20-1)*'Тарифы ВБ'!$B$10,'Тарифы ВБ'!$B$8) -> 32 | Z20: =SUM(X20:Y20) -> 102.51696 | AA20: =IFERROR(Z20/S20,0) -> 0.29870909 | AB20: =IF(K20>1,'Тарифы ВБ'!$B$14*'Тарифы ВБ'!$B$16*'Тарифы ВБ'!$B$15+(K20-1)*'Тарифы ВБ'!$B$14,'Тарифы ВБ'!$B$14*'Тарифы ВБ'!B$16*'Тарифы ВБ'!$B$15) -> 32 | AC20: =+X20+AB20+Y20 -> 134.51696 | AD20: =AC20/S20*100% -> 0.39194918 | AE20: 0.315 | AF20: =S20*AE20 -> 108.108 | AG20: =1.1*S20*$AG$3 -> 0 | AH20: =S20*$AH$3 -> 10.296 | AI20: =F20+V20 -> 333.92096 | AJ20: =IFERROR(AL20/S20,0) -> -0.04296317 | AK20: =S20-AI20 -> 9.27904 | AL20: =AK20-S20*7% -> -14.74496 | AM20: =AL20/H20 -> -0.24991458 | AN20: 409 | AO20: =$AN20-$AI20 -> 75.07904 | AP20: =$AO20-$AN20*7% -> 46.44904 | AQ20: =$AP20/$H20*100% -> 0.78727186 | AR20: =$AP20/$AN20 -> 0.11356733 | AS20: =IFERROR(_xlfn.XLOOKUP(A20,'[2]Рассчет акции'!$A:$A,'[2]Рассчет акции'!$BH:$BH),0) -> * | AT20: =IFERROR(_xlfn.XLOOKUP($A20,'[2]Рассчет акции'!$A:$A,'[2]Рассчет акции'!$BC:$BC),0) -> 343 | AU20: =IFERROR($AW20/$AT20,0) -> -0.043530496 | AV20: =$AT20-$AI20 -> 9.07904 | AW20: =$AV20-$AT20*7% -> -14.93096 | AX20: =$AW20/$H20*100% -> -0.25306712 | AY20: =IFERROR(_xlfn.XLOOKUP(E20,'[2]Рассчет акции'!$D:$D,'[2]Рассчет акции'!$BM:$BM),0) -> 535 | AZ20: =IFERROR(_xlfn.XLOOKUP(E20,'[2]Рассчет акции'!$D:$D,'[2]Рассчет акции'!$BN:$BN),0) -> 999 | BA20: =S20/H20 -> 5.8169492 | BC20: =_xlfn.XLOOKUP(B20,#REF!,#REF!,0) -> #REF! | BD20: =BC20/(100%-BE20) -> #REF! | BE20: =_xlfn.XLOOKUP($B20,'[1]Рассчет акции'!$A:$A,'[1]Рассчет акции'!$J:$J) -> 0.3502008 | BF20: =BS20+BI20+BJ20+BU20+BK20 -> #REF! | BG20: =IFERROR(BF20/BC20,0) -> 0 | BH20: 0.37 | BI20: =BC20*BH20 -> #REF! | BJ20: =BC20*$BJ$3 -> #REF! | BK20: =K20*$BK$3*30 -> 0 | BL20: =(IF(K20>$BL$3,('Тарифы ОЗОН'!$G$3+ROUNDUP(K20-$BL$3,0)*'Тарифы ОЗОН'!$G$4),'Тарифы ОЗОН'!$G$3)) -> 46.77 | BM20: =$BN$3 -> 35 | BN20: =_xlfn.XLOOKUP(BM20,'Тарифы ОЗОН'!$A:$A,'Тарифы ОЗОН'!$B:$B) -> 1.32 | BO20: =_xlfn.XLOOKUP(BM20,'Тарифы ОЗОН'!$A:$A,'Тарифы ОЗОН'!C:C) -> 0.016 | BP20: =$BP$3 -> 25 | BQ20: =BL20*BN20+BC20*BO20+BP20 -> #REF! | BR20: =$BR$3 -> 0.85 | BS20: =(100%/BR20)*BQ20+(100%/BR20-1)*BL20 -> #REF! | BT20: =IFERROR(BS20/BC20*100%,0) -> 0 | BU20: =BC20*$BU$3 -> #REF! | BV20: =BF20+F20 -> #REF! | BW20: =IFERROR(BY20/BC20,0) -> 0 | BX20: =IFERROR(BC20-BV20,0) -> 0 | BY20: =BX20-BC20*7% -> #REF! | BZ20: =IFERROR(BY20/H20*100%,0) -> 0 | CA20: 455 | CB20: =IF(BC20=0,0,CA20-BV20) -> #REF! | CC20: =IF(CB20=0,0,CB20-CA20*7%) -> #REF! | CD20: =CC20/H20*100% -> #REF! | CE20: =IFERROR(CC20/CA20,0) -> 0 | CF20: =_xlfn.XLOOKUP(B20,'[1]Рассчет акции'!$A:$A,'[1]Рассчет акции'!$R:$R,0) -> 0 | CG20: =_xlfn.XLOOKUP(B20,'[1]Рассчет акции'!$A:$A,'[1]Рассчет акции'!$M:$M,0) -> 567 | CH20: =IFERROR($CJ20/$CG20,0) -> 0 | CI20: =IF(BC20>0,CG20-BV20,0) -> #REF! | CJ20: =IF(CI20>0,$CI20-$CG20*7%,0) -> #REF! | CK20: =$CJ20/$H20*100% -> #REF! | CL20: =_xlfn.XLOOKUP(B20,'[1]Рассчет акции'!$A:$A,'[1]Рассчет акции'!$W:$W,0) -> 42 | CM20: =_xlfn.XLOOKUP(B20,'[1]Рассчет акции'!$A:$A,'[1]Рассчет акции'!$X:$X,0) -> 999 | CN20: =BC20/H20 -> #REF! | CO20: =CA20-10%*CA20 -> 409.5 | CP20: =_xlfn.XLOOKUP(B20,'[1]Рассчет акции'!$A:$A,'[1]Рассчет акции'!$Z:$Z,0) -> 0
A21: 223420736 | B21: 2415742732 | C21: ACRB1MS101RJ | D21: Массажер для тела оранжевый | E21: 2039813223373 | F21: =SUM(H21:J21) -> 165.0798 | G21: =IFERROR(F21/S21*100%,0) -> 0.18317777 | H21: =IF(_xlfn.XLOOKUP($C21,'Юнит Карго'!$A:$A,'Юнит Карго'!$G:$G)=0,_xlfn.XLOOKUP(E21,'Себес 1С текущ'!G:G,'Себес 1С текущ'!H:H),_xlfn.XLOOKUP($C21,'Юнит Карго'!$A:$A,'Юнит Карго'!$P:$P,0,0)) -> 143.0798 | I21: =_xlfn.XLOOKUP(E21,[3]ТЗ_ФФ!$D:$D,[3]ТЗ_ФФ!$BG:$BG,0) -> 14 | J21: =$J$3 -> 8 | K21: =(L21*M21*N21)/1000 -> 0.99 | L21: 55 | M21: 6 | N21: 3 | O21: =_xlfn.XLOOKUP($C21,'Юнит Карго'!$A:$A,'Юнит Карго'!$T:$T,0,0) -> 0.16 | P21: своя | S21: =T21-(T21*U21) -> 901.2 | T21: =_xlfn.XLOOKUP(E21,'[2]Рассчет акции'!$D:$D,'[2]Рассчет акции'!$G:$G,0) -> 1502 | U21: =_xlfn.XLOOKUP(E21,'[2]Рассчет акции'!$D:$D,'[2]Рассчет акции'!$F:$F,0) -> 0.4 | V21: =AC21+AF21+AH21+AG21 -> 449.78336 | W21: =IFERROR(V21/S21,0) -> 0.49909383 | X21: =IF(K21>1,('Тарифы ВБ'!$B$9+(K21-1)*'Тарифы ВБ'!$B$10)*'Тарифы ВБ'!$B$15*'Тарифы ВБ'!$B$12+S21*'Тарифы ВБ'!$B$13,'Тарифы ВБ'!$B$8*'Тарифы ВБ'!$B$15*'Тарифы ВБ'!$B$12+S21*'Тарифы ВБ'!$B$13) -> 74.86936 | Y21: =IF(K21>1,'Тарифы ВБ'!$B$9+(K21-1)*'Тарифы ВБ'!$B$10,'Тарифы ВБ'!$B$8) -> 32 | Z21: =SUM(X21:Y21) -> 106.86936 | AA21: =IFERROR(Z21/S21,0) -> 0.11858562 | AB21: =IF(K21>1,'Тарифы ВБ'!$B$14*'Тарифы ВБ'!$B$16*'Тарифы ВБ'!$B$15+(K21-1)*'Тарифы ВБ'!$B$14,'Тарифы ВБ'!$B$14*'Тарифы ВБ'!B$16*'Тарифы ВБ'!$B$15) -> 32 | AC21: =+X21+AB21+Y21 -> 138.86936 | AD21: =AC21/S21*100% -> 0.15409383 | AE21: 0.315 | AF21: =S21*AE21 -> 283.878 | AG21: =1.1*S21*$AG$3 -> 0 | AH21: =S21*$AH$3 -> 27.036 | AI21: =F21+V21 -> 614.86316 | AJ21: =IFERROR(AL21/S21,0) -> 0.2477284 | AK21: =S21-AI21 -> 286.33684 | AL21: =AK21-S21*7% -> 223.25284 | AM21: =AL21/H21 -> 1.5603379 | AN21: 919 | AO21: =$AN21-$AI21 -> 304.13684 | AP21: =$AO21-$AN21*7% -> 239.80684 | AQ21: =$AP21/$H21*100% -> 1.6760356 | AR21: =$AP21/$AN21 -> 0.26094324 | AS21: =IFERROR(_xlfn.XLOOKUP(A21,'[2]Рассчет акции'!$A:$A,'[2]Рассчет акции'!$BH:$BH),0) -> * | AT21: =IFERROR(_xlfn.XLOOKUP($A21,'[2]Рассчет акции'!$A:$A,'[2]Рассчет акции'!$BC:$BC),0) -> 901 | AU21: =IFERROR($AW21/$AT21,0) -> 0.24757696 | AV21: =$AT21-$AI21 -> 286.13684 | AW21: =$AV21-$AT21*7% -> 223.06684 | AX21: =$AW21/$H21*100% -> 1.5590379 | AY21: =IFERROR(_xlfn.XLOOKUP(E21,'[2]Рассчет акции'!$D:$D,'[2]Рассчет акции'!$BM:$BM),0) -> 56 | AZ21: =IFERROR(_xlfn.XLOOKUP(E21,'[2]Рассчет акции'!$D:$D,'[2]Рассчет акции'!$BN:$BN),0) -> 368 | BA21: =S21/H21 -> 6.2985829 | BC21: =_xlfn.XLOOKUP(B21,#REF!,#REF!,0) -> #REF! | BD21: =BC21/(100%-BE21) -> #REF! | BE21: =_xlfn.XLOOKUP($B21,'[1]Рассчет акции'!$A:$A,'[1]Рассчет акции'!$J:$J) -> 0.3501355 | BF21: =BS21+BI21+BJ21+BU21+BK21 -> #REF! | BG21: =IFERROR(BF21/BC21,0) -> 0 | BH21: 0.37 | BI21: =BC21*BH21 -> #REF! | BJ21: =BC21*$BJ$3 -> #REF! | BK21: =K21*$BK$3*30 -> 0 | BL21: =(IF(K21>$BL$3,('Тарифы ОЗОН'!$G$3+ROUNDUP(K21-$BL$3,0)*'Тарифы ОЗОН'!$G$4),'Тарифы ОЗОН'!$G$3)) -> 46.77 | BM21: =$BN$3 -> 35 | BN21: =_xlfn.XLOOKUP(BM21,'Тарифы ОЗОН'!$A:$A,'Тарифы ОЗОН'!$B:$B) -> 1.32 | BO21: =_xlfn.XLOOKUP(BM21,'Тарифы ОЗОН'!$A:$A,'Тарифы ОЗОН'!C:C) -> 0.016 | BP21: =$BP$3 -> 25 | BQ21: =BL21*BN21+BC21*BO21+BP21 -> #REF! | BR21: =$BR$3 -> 0.85 | BS21: =(100%/BR21)*BQ21+(100%/BR21-1)*BL21 -> #REF! | BT21: =IFERROR(BS21/BC21*100%,0) -> 0 | BU21: =BC21*$BU$3 -> #REF! | BV21: =BF21+F21 -> #REF! | BW21: =IFERROR(BY21/BC21,0) -> 0 | BX21: =IFERROR(BC21-BV21,0) -> 0 | BY21: =BX21-BC21*7% -> #REF! | BZ21: =IFERROR(BY21/H21*100%,0) -> 0 | CA21: 839 | CB21: =IF(BC21=0,0,CA21-BV21) -> #REF! | CC21: =IF(CB21=0,0,CB21-CA21*7%) -> #REF! | CD21: =CC21/H21*100% -> #REF! | CE21: =IFERROR(CC21/CA21,0) -> 0 | CF21: =_xlfn.XLOOKUP(B21,'[1]Рассчет акции'!$A:$A,'[1]Рассчет акции'!$R:$R,0) -> 0 | CG21: =_xlfn.XLOOKUP(B21,'[1]Рассчет акции'!$A:$A,'[1]Рассчет акции'!$M:$M,0) -> 835 | CH21: =IFERROR($CJ21/$CG21,0) -> 0 | CI21: =IF(BC21>0,CG21-BV21,0) -> #REF! | CJ21: =IF(CI21>0,$CI21-$CG21*7%,0) -> #REF! | CK21: =$CJ21/$H21*100% -> #REF! | CL21: =_xlfn.XLOOKUP(B21,'[1]Рассчет акции'!$A:$A,'[1]Рассчет акции'!$W:$W,0) -> 18 | CM21: =_xlfn.XLOOKUP(B21,'[1]Рассчет акции'!$A:$A,'[1]Рассчет акции'!$X:$X,0) -> 126 | CN21: =BC21/H21 -> #REF! | CO21: =CA21-10%*CA21 -> 755.1 | CP21: =_xlfn.XLOOKUP(B21,'[1]Рассчет акции'!$A:$A,'[1]Рассчет акции'!$Z:$Z,0) -> 0
A22: 275208801 | B22: 2415742511 | C22: ACRB1MS101PN | D22: Массажер для тела розовый | E22: 2041591042329 | F22: =SUM(H22:J22) -> 165.0798 | G22: =IFERROR(F22/S22*100%,0) -> 0.22775911 | H22: =IF(_xlfn.XLOOKUP($C22,'Юнит Карго'!$A:$A,'Юнит Карго'!$G:$G)=0,_xlfn.XLOOKUP(E22,'Себес 1С текущ'!G:G,'Себес 1С текущ'!H:H),_xlfn.XLOOKUP($C22,'Юнит Карго'!$A:$A,'Юнит Карго'!$P:$P,0,0)) -> 143.0798 | I22: =_xlfn.XLOOKUP(E22,[3]ТЗ_ФФ!$D:$D,[3]ТЗ_ФФ!$BG:$BG,0) -> 14 | J22: =$J$3 -> 8 | K22: =(L22*M22*N22)/1000 -> 0.99 | L22: 55 | M22: 6 | N22: 3 | O22: =_xlfn.XLOOKUP($C22,'Юнит Карго'!$A:$A,'Юнит Карго'!$T:$T,0,0) -> 0.16 | P22: своя | S22: =T22-(T22*U22) -> 724.8 | T22: =_xlfn.XLOOKUP(E22,'[2]Рассчет акции'!$D:$D,'[2]Рассчет акции'!$G:$G,0) -> 1208 | U22: =_xlfn.XLOOKUP(E22,'[2]Рассчет акции'!$D:$D,'[2]Рассчет акции'!$F:$F,0) -> 0.4 | V22: =AC22+AF22+AH22+AG22 -> 387.54944 | W22: =IFERROR(V22/S22,0) -> 0.53469845 | X22: =IF(K22>1,('Тарифы ВБ'!$B$9+(K22-1)*'Тарифы ВБ'!$B$10)*'Тарифы ВБ'!$B$15*'Тарифы ВБ'!$B$12+S22*'Тарифы ВБ'!$B$13,'Тарифы ВБ'!$B$8*'Тарифы ВБ'!$B$15*'Тарифы ВБ'!$B$12+S22*'Тарифы ВБ'!$B$13) -> 73.49344 | Y22: =IF(K22>1,'Тарифы ВБ'!$B$9+(K22-1)*'Тарифы ВБ'!$B$10,'Тарифы ВБ'!$B$8) -> 32 | Z22: =SUM(X22:Y22) -> 105.49344 | AA22: =IFERROR(Z22/S22,0) -> 0.14554834 | AB22: =IF(K22>1,'Тарифы ВБ'!$B$14*'Тарифы ВБ'!$B$16*'Тарифы ВБ'!$B$15+(K22-1)*'Тарифы ВБ'!$B$14,'Тарифы ВБ'!$B$14*'Тарифы ВБ'!B$16*'Тарифы ВБ'!$B$15) -> 32 | AC22: =+X22+AB22+Y22 -> 137.49344 | AD22: =AC22/S22*100% -> 0.18969845 | AE22: 0.315 | AF22: =S22*AE22 -> 228.312 | AG22: =1.1*S22*$AG$3 -> 0 | AH22: =S22*$AH$3 -> 21.744 | AI22: =F22+V22 -> 552.62924 | AJ22: =IFERROR(AL22/S22,0) -> 0.16754244 | AK22: =S22-AI22 -> 172.17076 | AL22: =AK22-S22*7% -> 121.43476 | AM22: =AL22/H22 -> 0.84872047 | AN22: 919 | AO22: =$AN22-$AI22 -> 366.37076 | AP22: =$AO22-$AN22*7% -> 302.04076 | AQ22: =$AP22/$H22*100% -> 2.1109951 | AR22: =$AP22/$AN22 -> 0.32866241 | AS22: =IFERROR(_xlfn.XLOOKUP(A22,'[2]Рассчет акции'!$A:$A,'[2]Рассчет акции'!$BH:$BH),0) -> * | AT22: =IFERROR(_xlfn.XLOOKUP($A22,'[2]Рассчет акции'!$A:$A,'[2]Рассчет акции'!$BC:$BC),0) -> 725 | AU22: =IFERROR($AW22/$AT22,0) -> 0.16775277 | AV22: =$AT22-$AI22 -> 172.37076 | AW22: =$AV22-$AT22*7% -> 121.62076 | AX22: =$AW22/$H22*100% -> 0.85002044 | AY22: =IFERROR(_xlfn.XLOOKUP(E22,'[2]Рассчет акции'!$D:$D,'[2]Рассчет акции'!$BM:$BM),0) -> 58 | AZ22: =IFERROR(_xlfn.XLOOKUP(E22,'[2]Рассчет акции'!$D:$D,'[2]Рассчет акции'!$BN:$BN),0) -> 215 | BA22: =S22/H22 -> 5.0657045 | BC22: =_xlfn.XLOOKUP(B22,#REF!,#REF!,0) -> #REF! | BD22: =BC22/(100%-BE22) -> #REF! | BE22: =_xlfn.XLOOKUP($B22,'[1]Рассчет акции'!$A:$A,'[1]Рассчет акции'!$J:$J) -> 0.3501355 | BF22: =BS22+BI22+BJ22+BU22+BK22 -> #REF! | BG22: =IFERROR(BF22/BC22,0) -> 0 | BH22: 0.37 | BI22: =BC22*BH22 -> #REF! | BJ22: =BC22*$BJ$3 -> #REF! | BK22: =K22*$BK$3*30 -> 0 | BL22: =(IF(K22>$BL$3,('Тарифы ОЗОН'!$G$3+ROUNDUP(K22-$BL$3,0)*'Тарифы ОЗОН'!$G$4),'Тарифы ОЗОН'!$G$3)) -> 46.77 | BM22: =$BN$3 -> 35 | BN22: =_xlfn.XLOOKUP(BM22,'Тарифы ОЗОН'!$A:$A,'Тарифы ОЗОН'!$B:$B) -> 1.32 | BO22: =_xlfn.XLOOKUP(BM22,'Тарифы ОЗОН'!$A:$A,'Тарифы ОЗОН'!C:C) -> 0.016 | BP22: =$BP$3 -> 25 | BQ22: =BL22*BN22+BC22*BO22+BP22 -> #REF! | BR22: =$BR$3 -> 0.85 | BS22: =(100%/BR22)*BQ22+(100%/BR22-1)*BL22 -> #REF! | BT22: =IFERROR(BS22/BC22*100%,0) -> 0 | BU22: =BC22*$BU$3 -> #REF! | BV22: =BF22+F22 -> #REF! | BW22: =IFERROR(BY22/BC22,0) -> 0 | BX22: =IFERROR(BC22-BV22,0) -> 0 | BY22: =BX22-BC22*7% -> #REF! | BZ22: =IFERROR(BY22/H22*100%,0) -> 0 | CA22: 839 | CB22: =IF(BC22=0,0,CA22-BV22) -> #REF! | CC22: =IF(CB22=0,0,CB22-CA22*7%) -> #REF! | CD22: =CC22/H22*100% -> #REF! | CE22: =IFERROR(CC22/CA22,0) -> 0 | CF22: =_xlfn.XLOOKUP(B22,'[1]Рассчет акции'!$A:$A,'[1]Рассчет акции'!$R:$R,0) -> 0 | CG22: =_xlfn.XLOOKUP(B22,'[1]Рассчет акции'!$A:$A,'[1]Рассчет акции'!$M:$M,0) -> 887 | CH22: =IFERROR($CJ22/$CG22,0) -> 0 | CI22: =IF(BC22>0,CG22-BV22,0) -> #REF! | CJ22: =IF(CI22>0,$CI22-$CG22*7%,0) -> #REF! | CK22: =$CJ22/$H22*100% -> #REF! | CL22: =_xlfn.XLOOKUP(B22,'[1]Рассчет акции'!$A:$A,'[1]Рассчет акции'!$W:$W,0) -> 23 | CM22: =_xlfn.XLOOKUP(B22,'[1]Рассчет акции'!$A:$A,'[1]Рассчет акции'!$X:$X,0) -> 999 | CN22: =BC22/H22 -> #REF! | CO22: =CA22-10%*CA22 -> 755.1 | CP22: =_xlfn.XLOOKUP(B22,'[1]Рассчет акции'!$A:$A,'[1]Рассчет акции'!$Z:$Z,0) -> 0
A23: 275208802 | B23: 2415742636 | C23: ACRB1MS101BL | D23: Массажер для тела голубой | E23: 2041591055954 | F23: =SUM(H23:J23) -> 165.0798 | G23: =IFERROR(F23/S23*100%,0) -> 0.17961027 | H23: =IF(_xlfn.XLOOKUP($C23,'Юнит Карго'!$A:$A,'Юнит Карго'!$G:$G)=0,_xlfn.XLOOKUP(E23,'Себес 1С текущ'!G:G,'Себес 1С текущ'!H:H),_xlfn.XLOOKUP($C23,'Юнит Карго'!$A:$A,'Юнит Карго'!$P:$P,0,0)) -> 143.0798 | I23: =_xlfn.XLOOKUP(E23,[3]ТЗ_ФФ!$D:$D,[3]ТЗ_ФФ!$BG:$BG,0) -> 14 | J23: =$J$3 -> 8 | K23: =(L23*M23*N23)/1000 -> 0.99 | L23: 55 | M23: 6 | N23: 3 | O23: =_xlfn.XLOOKUP($C23,'Юнит Карго'!$A:$A,'Юнит Карго'!$T:$T,0,0) -> 0.16 | P23: своя | S23: =T23-(T23*U23) -> 919.1 | T23: =_xlfn.XLOOKUP(E23,'[2]Рассчет акции'!$D:$D,'[2]Рассчет акции'!$G:$G,0) -> 1313 | U23: =_xlfn.XLOOKUP(E23,'[2]Рассчет акции'!$D:$D,'[2]Рассчет акции'!$F:$F,0) -> 0.3 | V23: =AC23+AF23+AH23+AG23 -> 456.09848 | W23: =IFERROR(V23/S23,0) -> 0.49624467 | X23: =IF(K23>1,('Тарифы ВБ'!$B$9+(K23-1)*'Тарифы ВБ'!$B$10)*'Тарифы ВБ'!$B$15*'Тарифы ВБ'!$B$12+S23*'Тарифы ВБ'!$B$13,'Тарифы ВБ'!$B$8*'Тарифы ВБ'!$B$15*'Тарифы ВБ'!$B$12+S23*'Тарифы ВБ'!$B$13) -> 75.00898 | Y23: =IF(K23>1,'Тарифы ВБ'!$B$9+(K23-1)*'Тарифы ВБ'!$B$10,'Тарифы ВБ'!$B$8) -> 32 | Z23: =SUM(X23:Y23) -> 107.00898 | AA23: =IFERROR(Z23/S23,0) -> 0.11642801 | AB23: =IF(K23>1,'Тарифы ВБ'!$B$14*'Тарифы ВБ'!$B$16*'Тарифы ВБ'!$B$15+(K23-1)*'Тарифы ВБ'!$B$14,'Тарифы ВБ'!$B$14*'Тарифы ВБ'!B$16*'Тарифы ВБ'!$B$15) -> 32 | AC23: =+X23+AB23+Y23 -> 139.00898 | AD23: =AC23/S23*100% -> 0.15124467 | AE23: 0.315 | AF23: =S23*AE23 -> 289.5165 | AG23: =1.1*S23*$AG$3 -> 0 | AH23: =S23*$AH$3 -> 27.573 | AI23: =F23+V23 -> 621.17828 | AJ23: =IFERROR(AL23/S23,0) -> 0.25414505 | AK23: =S23-AI23 -> 297.92172 | AL23: =AK23-S23*7% -> 233.58472 | AM23: =AL23/H23 -> 1.6325485 | AN23: 919 | AO23: =$AN23-$AI23 -> 297.82172 | AP23: =$AO23-$AN23*7% -> 233.49172 | AQ23: =$AP23/$H23*100% -> 1.6318985 | AR23: =$AP23/$AN23 -> 0.25407151 | AS23: =IFERROR(_xlfn.XLOOKUP(A23,'[2]Рассчет акции'!$A:$A,'[2]Рассчет акции'!$BH:$BH),0) -> 0 | AT23: =IFERROR(_xlfn.XLOOKUP($A23,'[2]Рассчет акции'!$A:$A,'[2]Рассчет акции'!$BC:$BC),0) -> 0 | AU23: =IFERROR($AW23/$AT23,0) -> 0 | AV23: =$AT23-$AI23 -> -621.17828 | AW23: =$AV23-$AT23*7% -> -621.17828 | AX23: =$AW23/$H23*100% -> -4.3414813 | AY23: =IFERROR(_xlfn.XLOOKUP(E23,'[2]Рассчет акции'!$D:$D,'[2]Рассчет акции'!$BM:$BM),0) -> 60 | AZ23: =IFERROR(_xlfn.XLOOKUP(E23,'[2]Рассчет акции'!$D:$D,'[2]Рассчет акции'!$BN:$BN),0) -> 999 | BA23: =S23/H23 -> 6.4236879 | BC23: =_xlfn.XLOOKUP(B23,#REF!,#REF!,0) -> #REF! | BD23: =BC23/(100%-BE23) -> #REF! | BE23: =_xlfn.XLOOKUP($B23,'[1]Рассчет акции'!$A:$A,'[1]Рассчет акции'!$J:$J) -> 0.3501355 | BF23: =BS23+BI23+BJ23+BU23+BK23 -> #REF! | BG23: =IFERROR(BF23/BC23,0) -> 0 | BH23: 0.37 | BI23: =BC23*BH23 -> #REF! | BJ23: =BC23*$BJ$3 -> #REF! | BK23: =K23*$BK$3*30 -> 0 | BL23: =(IF(K23>$BL$3,('Тарифы ОЗОН'!$G$3+ROUNDUP(K23-$BL$3,0)*'Тарифы ОЗОН'!$G$4),'Тарифы ОЗОН'!$G$3)) -> 46.77 | BM23: =$BN$3 -> 35 | BN23: =_xlfn.XLOOKUP(BM23,'Тарифы ОЗОН'!$A:$A,'Тарифы ОЗОН'!$B:$B) -> 1.32 | BO23: =_xlfn.XLOOKUP(BM23,'Тарифы ОЗОН'!$A:$A,'Тарифы ОЗОН'!C:C) -> 0.016 | BP23: =$BP$3 -> 25 | BQ23: =BL23*BN23+BC23*BO23+BP23 -> #REF! | BR23: =$BR$3 -> 0.85 | BS23: =(100%/BR23)*BQ23+(100%/BR23-1)*BL23 -> #REF! | BT23: =IFERROR(BS23/BC23*100%,0) -> 0 | BU23: =BC23*$BU$3 -> #REF! | BV23: =BF23+F23 -> #REF! | BW23: =IFERROR(BY23/BC23,0) -> 0 | BX23: =IFERROR(BC23-BV23,0) -> 0 | BY23: =BX23-BC23*7% -> #REF! | BZ23: =IFERROR(BY23/H23*100%,0) -> 0 | CA23: 839 | CB23: =IF(BC23=0,0,CA23-BV23) -> #REF! | CC23: =IF(CB23=0,0,CB23-CA23*7%) -> #REF! | CD23: =CC23/H23*100% -> #REF! | CE23: =IFERROR(CC23/CA23,0) -> 0 | CF23: =_xlfn.XLOOKUP(B23,'[1]Рассчет акции'!$A:$A,'[1]Рассчет акции'!$R:$R,0) -> 0 | CG23: =_xlfn.XLOOKUP(B23,'[1]Рассчет акции'!$A:$A,'[1]Рассчет акции'!$M:$M,0) -> 887 | CH23: =IFERROR($CJ23/$CG23,0) -> 0 | CI23: =IF(BC23>0,CG23-BV23,0) -> #REF! | CJ23: =IF(CI23>0,$CI23-$CG23*7%,0) -> #REF! | CK23: =$CJ23/$H23*100% -> #REF! | CL23: =_xlfn.XLOOKUP(B23,'[1]Рассчет акции'!$A:$A,'[1]Рассчет акции'!$W:$W,0) -> 21 | CM23: =_xlfn.XLOOKUP(B23,'[1]Рассчет акции'!$A:$A,'[1]Рассчет акции'!$X:$X,0) -> 999 | CN23: =BC23/H23 -> #REF! | CO23: =CA23-10%*CA23 -> 755.1 | CP23: =_xlfn.XLOOKUP(B23,'[1]Рассчет акции'!$A:$A,'[1]Рассчет акции'!$Z:$Z,0) -> 0
A24: 236072835 | B24: 1980924906 | C24: ACRB1MS106WH | D24: Мяч с шипами белый 6 см | E24: 2040278804496 | F24: =SUM(H24:J24) -> 73.802451 | G24: =IFERROR(F24/S24*100%,0) -> 0.1236222 | H24: =IF(_xlfn.XLOOKUP($C24,'Юнит Карго'!$A:$A,'Юнит Карго'!$G:$G)=0,_xlfn.XLOOKUP(E24,'Себес 1С текущ'!G:G,'Себес 1С текущ'!H:H),_xlfn.XLOOKUP($C24,'Юнит Карго'!$A:$A,'Юнит Карго'!$P:$P,0,0)) -> 51.802451 | I24: =_xlfn.XLOOKUP(E24,[3]ТЗ_ФФ!$D:$D,[3]ТЗ_ФФ!$BG:$BG,0) -> 14 | J24: =$J$3 -> 8 | K24: =(L24*M24*N24)/1000 -> 0.343 | L24: 7 | M24: 7 | N24: 7 | O24: =_xlfn.XLOOKUP($C24,'Юнит Карго'!$A:$A,'Юнит Карго'!$T:$T,0,0) -> 0.04 | P24: своя | Q24: 300 | S24: =T24-(T24*U24) -> 597 | T24: =_xlfn.XLOOKUP(E24,'[2]Рассчет акции'!$D:$D,'[2]Рассчет акции'!$G:$G,0) -> 995 | U24: =_xlfn.XLOOKUP(E24,'[2]Рассчет акции'!$D:$D,'[2]Рассчет акции'!$F:$F,0) -> 0.4 | V24: =AC24+AF24+AH24+AG24 -> 342.4616 | W24: =IFERROR(V24/S24,0) -> 0.57363752 | X24: =IF(K24>1,('Тарифы ВБ'!$B$9+(K24-1)*'Тарифы ВБ'!$B$10)*'Тарифы ВБ'!$B$15*'Тарифы ВБ'!$B$12+S24*'Тарифы ВБ'!$B$13,'Тарифы ВБ'!$B$8*'Тарифы ВБ'!$B$15*'Тарифы ВБ'!$B$12+S24*'Тарифы ВБ'!$B$13) -> 72.4966 | Y24: =IF(K24>1,'Тарифы ВБ'!$B$9+(K24-1)*'Тарифы ВБ'!$B$10,'Тарифы ВБ'!$B$8) -> 32 | Z24: =SUM(X24:Y24) -> 104.4966 | AA24: =IFERROR(Z24/S24,0) -> 0.17503618 | AB24: =IF(K24>1,'Тарифы ВБ'!$B$14*'Тарифы ВБ'!$B$16*'Тарифы ВБ'!$B$15+(K24-1)*'Тарифы ВБ'!$B$14,'Тарифы ВБ'!$B$14*'Тарифы ВБ'!B$16*'Тарифы ВБ'!$B$15) -> 32 | AC24: =+X24+AB24+Y24 -> 136.4966 | AD24: =AC24/S24*100% -> 0.22863752 | AE24: 0.315 | AF24: =S24*AE24 -> 188.055 | AG24: =1.1*S24*$AG$3 -> 0 | AH24: =S24*$AH$3 -> 17.91 | AI24: =F24+V24 -> 416.26405 | AJ24: =IFERROR(AL24/S24,0) -> 0.23274028 | AK24: =S24-AI24 -> 180.73595 | AL24: =AK24-S24*7% -> 138.94595 | AM24: =AL24/H24 -> 2.6822273 | AN24: 599 | AO24: =$AN24-$AI24 -> 182.73595 | AP24: =$AO24-$AN24*7% -> 140.80595 | AQ24: =$AP24/$H24*100% -> 2.718133 | AR24: =$AP24/$AN24 -> 0.23506836 | AS24: =IFERROR(_xlfn.XLOOKUP(A24,'[2]Рассчет акции'!$A:$A,'[2]Рассчет акции'!$BH:$BH),0) -> * | AT24: =IFERROR(_xlfn.XLOOKUP($A24,'[2]Рассчет акции'!$A:$A,'[2]Рассчет акции'!$BC:$BC),0) -> 597 | AU24: =IFERROR($AW24/$AT24,0) -> 0.23274028 | AV24: =$AT24-$AI24 -> 180.73595 | AW24: =$AV24-$AT24*7% -> 138.94595 | AX24: =$AW24/$H24*100% -> 2.6822273 | AY24: =IFERROR(_xlfn.XLOOKUP(E24,'[2]Рассчет акции'!$D:$D,'[2]Рассчет акции'!$BM:$BM),0) -> 427 | AZ24: =IFERROR(_xlfn.XLOOKUP(E24,'[2]Рассчет акции'!$D:$D,'[2]Рассчет акции'!$BN:$BN),0) -> 256 | BA24: =S24/H24 -> 11.524551 | BC24: =_xlfn.XLOOKUP(B24,#REF!,#REF!,0) -> #REF! | BD24: =BC24/(100%-BE24) -> #REF! | BE24: =_xlfn.XLOOKUP($B24,'[1]Рассчет акции'!$A:$A,'[1]Рассчет акции'!$J:$J) -> 0.34980392 | BF24: =BS24+BI24+BJ24+BU24+BK24 -> #REF! | BG24: =IFERROR(BF24/BC24,0) -> 0 | BH24: 0.37 | BI24: =BC24*BH24 -> #REF! | BJ24: =BC24*$BJ$3 -> #REF! | BK24: =K24*$BK$3*30 -> 0 | BL24: =(IF(K24>$BL$3,('Тарифы ОЗОН'!$G$3+ROUNDUP(K24-$BL$3,0)*'Тарифы ОЗОН'!$G$4),'Тарифы ОЗОН'!$G$3)) -> 46.77 | BM24: =$BN$3 -> 35 | BN24: =_xlfn.XLOOKUP(BM24,'Тарифы ОЗОН'!$A:$A,'Тарифы ОЗОН'!$B:$B) -> 1.32 | BO24: =_xlfn.XLOOKUP(BM24,'Тарифы ОЗОН'!$A:$A,'Тарифы ОЗОН'!C:C) -> 0.016 | BP24: =$BP$3 -> 25 | BQ24: =BL24*BN24+BC24*BO24+BP24 -> #REF! | BR24: =$BR$3 -> 0.85 | BS24: =(100%/BR24)*BQ24+(100%/BR24-1)*BL24 -> #REF! | BT24: =IFERROR(BS24/BC24*100%,0) -> 0 | BU24: =BC24*$BU$3 -> #REF! | BV24: =BF24+F24 -> #REF! | BW24: =IFERROR(BY24/BC24,0) -> 0 | BX24: =IFERROR(BC24-BV24,0) -> 0 | BY24: =BX24-BC24*7% -> #REF! | BZ24: =IFERROR(BY24/H24*100%,0) -> 0 | CA24: 600 | CB24: =IF(BC24=0,0,CA24-BV24) -> #REF! | CC24: =IF(CB24=0,0,CB24-CA24*7%) -> #REF! | CD24: =CC24/H24*100% -> #REF! | CE24: =IFERROR(CC24/CA24,0) -> 0 | CF24: =_xlfn.XLOOKUP(B24,'[1]Рассчет акции'!$A:$A,'[1]Рассчет акции'!$R:$R,0) -> 0 | CG24: =_xlfn.XLOOKUP(B24,'[1]Рассчет акции'!$A:$A,'[1]Рассчет акции'!$M:$M,0) -> 598 | CH24: =IFERROR($CJ24/$CG24,0) -> 0 | CI24: =IF(BC24>0,CG24-BV24,0) -> #REF! | CJ24: =IF(CI24>0,$CI24-$CG24*7%,0) -> #REF! | CK24: =$CJ24/$H24*100% -> #REF! | CL24: =_xlfn.XLOOKUP(B24,'[1]Рассчет акции'!$A:$A,'[1]Рассчет акции'!$W:$W,0) -> 48 | CM24: =_xlfn.XLOOKUP(B24,'[1]Рассчет акции'!$A:$A,'[1]Рассчет акции'!$X:$X,0) -> 168 | CN24: =BC24/H24 -> #REF! | CO24: =CA24-10%*CA24 -> 540 | CP24: =_xlfn.XLOOKUP(B24,'[1]Рассчет акции'!$A:$A,'[1]Рассчет акции'!$Z:$Z,0) -> 0
A25: 236072836 | B25: 1980925084 | C25: ACRB1MS106PN | D25: Мяч с шипами розовый 6 см | E25: 2040278810534 | F25: =SUM(H25:J25) -> 73.802451 | G25: =IFERROR(F25/S25*100%,0) -> 0.12449806 | H25: =IF(_xlfn.XLOOKUP($C25,'Юнит Карго'!$A:$A,'Юнит Карго'!$G:$G)=0,_xlfn.XLOOKUP(E25,'Себес 1С текущ'!G:G,'Себес 1С текущ'!H:H),_xlfn.XLOOKUP($C25,'Юнит Карго'!$A:$A,'Юнит Карго'!$P:$P,0,0)) -> 51.802451 | I25: =_xlfn.XLOOKUP(E25,[3]ТЗ_ФФ!$D:$D,[3]ТЗ_ФФ!$BG:$BG,0) -> 14 | J25: =$J$3 -> 8 | K25: =(L25*M25*N25)/1000 -> 0.343 | L25: 7 | M25: 7 | N25: 7 | O25: =_xlfn.XLOOKUP($C25,'Юнит Карго'!$A:$A,'Юнит Карго'!$T:$T,0,0) -> 0.04 | P25: своя | Q25: 300 | S25: =T25-(T25*U25) -> 592.8 | T25: =_xlfn.XLOOKUP(E25,'[2]Рассчет акции'!$D:$D,'[2]Рассчет акции'!$G:$G,0) -> 988 | U25: =_xlfn.XLOOKUP(E25,'[2]Рассчет акции'!$D:$D,'[2]Рассчет акции'!$F:$F,0) -> 0.4 | V25: =AC25+AF25+AH25+AG25 -> 340.97984 | W25: =IFERROR(V25/S25,0) -> 0.57520216 | X25: =IF(K25>1,('Тарифы ВБ'!$B$9+(K25-1)*'Тарифы ВБ'!$B$10)*'Тарифы ВБ'!$B$15*'Тарифы ВБ'!$B$12+S25*'Тарифы ВБ'!$B$13,'Тарифы ВБ'!$B$8*'Тарифы ВБ'!$B$15*'Тарифы ВБ'!$B$12+S25*'Тарифы ВБ'!$B$13) -> 72.46384 | Y25: =IF(K25>1,'Тарифы ВБ'!$B$9+(K25-1)*'Тарифы ВБ'!$B$10,'Тарифы ВБ'!$B$8) -> 32 | Z25: =SUM(X25:Y25) -> 104.46384 | AA25: =IFERROR(Z25/S25,0) -> 0.17622105 | AB25: =IF(K25>1,'Тарифы ВБ'!$B$14*'Тарифы ВБ'!$B$16*'Тарифы ВБ'!$B$15+(K25-1)*'Тарифы ВБ'!$B$14,'Тарифы ВБ'!$B$14*'Тарифы ВБ'!B$16*'Тарифы ВБ'!$B$15) -> 32 | AC25: =+X25+AB25+Y25 -> 136.46384 | AD25: =AC25/S25*100% -> 0.23020216 | AE25: 0.315 | AF25: =S25*AE25 -> 186.732 | AG25: =1.1*S25*$AG$3 -> 0 | AH25: =S25*$AH$3 -> 17.784 | AI25: =F25+V25 -> 414.78229 | AJ25: =IFERROR(AL25/S25,0) -> 0.23029978 | AK25: =S25-AI25 -> 178.01771 | AL25: =AK25-S25*7% -> 136.52171 | AM25: =AL25/H25 -> 2.6354295 | AN25: 599 | AO25: =$AN25-$AI25 -> 184.21771 | AP25: =$AO25-$AN25*7% -> 142.28771 | AQ25: =$AP25/$H25*100% -> 2.746737 | AR25: =$AP25/$AN25 -> 0.23754209 | AS25: =IFERROR(_xlfn.XLOOKUP(A25,'[2]Рассчет акции'!$A:$A,'[2]Рассчет акции'!$BH:$BH),0) -> * | AT25: =IFERROR(_xlfn.XLOOKUP($A25,'[2]Рассчет акции'!$A:$A,'[2]Рассчет акции'!$BC:$BC),0) -> 593 | AU25: =IFERROR($AW25/$AT25,0) -> 0.23053577 | AV25: =$AT25-$AI25 -> 178.21771 | AW25: =$AV25-$AT25*7% -> 136.70771 | AX25: =$AW25/$H25*100% -> 2.6390201 | AY25: =IFERROR(_xlfn.XLOOKUP(E25,'[2]Рассчет акции'!$D:$D,'[2]Рассчет акции'!$BM:$BM),0) -> 300 | AZ25: =IFERROR(_xlfn.XLOOKUP(E25,'[2]Рассчет акции'!$D:$D,'[2]Рассчет акции'!$BN:$BN),0) -> 638 | BA25: =S25/H25 -> 11.443474 | BC25: =_xlfn.XLOOKUP(B25,#REF!,#REF!,0) -> #REF! | BD25: =BC25/(100%-BE25) -> #REF! | BE25: =_xlfn.XLOOKUP($B25,'[1]Рассчет акции'!$A:$A,'[1]Рассчет акции'!$J:$J) -> 0.34980392 | BF25: =BS25+BI25+BJ25+BU25+BK25 -> #REF! | BG25: =IFERROR(BF25/BC25,0) -> 0 | BH25: 0.37 | BI25: =BC25*BH25 -> #REF! | BJ25: =BC25*$BJ$3 -> #REF! | BK25: =K25*$BK$3*30 -> 0 | BL25: =(IF(K25>$BL$3,('Тарифы ОЗОН'!$G$3+ROUNDUP(K25-$BL$3,0)*'Тарифы ОЗОН'!$G$4),'Тарифы ОЗОН'!$G$3)) -> 46.77 | BM25: =$BN$3 -> 35 | BN25: =_xlfn.XLOOKUP(BM25,'Тарифы ОЗОН'!$A:$A,'Тарифы ОЗОН'!$B:$B) -> 1.32 | BO25: =_xlfn.XLOOKUP(BM25,'Тарифы ОЗОН'!$A:$A,'Тарифы ОЗОН'!C:C) -> 0.016 | BP25: =$BP$3 -> 25 | BQ25: =BL25*BN25+BC25*BO25+BP25 -> #REF! | BR25: =$BR$3 -> 0.85 | BS25: =(100%/BR25)*BQ25+(100%/BR25-1)*BL25 -> #REF! | BT25: =IFERROR(BS25/BC25*100%,0) -> 0 | BU25: =BC25*$BU$3 -> #REF! | BV25: =BF25+F25 -> #REF! | BW25: =IFERROR(BY25/BC25,0) -> 0 | BX25: =IFERROR(BC25-BV25,0) -> 0 | BY25: =BX25-BC25*7% -> #REF! | BZ25: =IFERROR(BY25/H25*100%,0) -> 0 | CA25: 629 | CB25: =IF(BC25=0,0,CA25-BV25) -> #REF! | CC25: =IF(CB25=0,0,CB25-CA25*7%) -> #REF! | CD25: =CC25/H25*100% -> #REF! | CE25: =IFERROR(CC25/CA25,0) -> 0 | CF25: =_xlfn.XLOOKUP(B25,'[1]Рассчет акции'!$A:$A,'[1]Рассчет акции'!$R:$R,0) -> 0 | CG25: =_xlfn.XLOOKUP(B25,'[1]Рассчет акции'!$A:$A,'[1]Рассчет акции'!$M:$M,0) -> 598 | CH25: =IFERROR($CJ25/$CG25,0) -> 0 | CI25: =IF(BC25>0,CG25-BV25,0) -> #REF! | CJ25: =IF(CI25>0,$CI25-$CG25*7%,0) -> #REF! | CK25: =$CJ25/$H25*100% -> #REF! | CL25: =_xlfn.XLOOKUP(B25,'[1]Рассчет акции'!$A:$A,'[1]Рассчет акции'!$W:$W,0) -> 104 | CM25: =_xlfn.XLOOKUP(B25,'[1]Рассчет акции'!$A:$A,'[1]Рассчет акции'!$X:$X,0) -> 242.66667 | CN25: =BC25/H25 -> #REF! | CO25: =CA25-10%*CA25 -> 566.1 | CP25: =_xlfn.XLOOKUP(B25,'[1]Рассчет акции'!$A:$A,'[1]Рассчет акции'!$Z:$Z,0) -> 0
A26: 236072834 | B26: 1980924909 | C26: ACRB1MS106BL | D26: Мяч с шипами голубой 6 см | E26: 2040278804649 | F26: =SUM(H26:J26) -> 73.802451 | G26: =IFERROR(F26/S26*100%,0) -> 0.13546705 | H26: =IF(_xlfn.XLOOKUP($C26,'Юнит Карго'!$A:$A,'Юнит Карго'!$G:$G)=0,_xlfn.XLOOKUP(E26,'Себес 1С текущ'!G:G,'Себес 1С текущ'!H:H),_xlfn.XLOOKUP($C26,'Юнит Карго'!$A:$A,'Юнит Карго'!$P:$P,0,0)) -> 51.802451 | I26: =_xlfn.XLOOKUP(E26,[3]ТЗ_ФФ!$D:$D,[3]ТЗ_ФФ!$BG:$BG,0) -> 14 | J26: =$J$3 -> 8 | K26: =(L26*M26*N26)/1000 -> 0.343 | L26: 7 | M26: 7 | N26: 7 | O26: =_xlfn.XLOOKUP($C26,'Юнит Карго'!$A:$A,'Юнит Карго'!$T:$T,0,0) -> 0.04 | P26: своя | Q26: 300 | S26: =T26-(T26*U26) -> 544.8 | T26: =_xlfn.XLOOKUP(E26,'[2]Рассчет акции'!$D:$D,'[2]Рассчет акции'!$G:$G,0) -> 908 | U26: =_xlfn.XLOOKUP(E26,'[2]Рассчет акции'!$D:$D,'[2]Рассчет акции'!$F:$F,0) -> 0.4 | V26: =AC26+AF26+AH26+AG26 -> 324.04544 | W26: =IFERROR(V26/S26,0) -> 0.59479706 | X26: =IF(K26>1,('Тарифы ВБ'!$B$9+(K26-1)*'Тарифы ВБ'!$B$10)*'Тарифы ВБ'!$B$15*'Тарифы ВБ'!$B$12+S26*'Тарифы ВБ'!$B$13,'Тарифы ВБ'!$B$8*'Тарифы ВБ'!$B$15*'Тарифы ВБ'!$B$12+S26*'Тарифы ВБ'!$B$13) -> 72.08944 | Y26: =IF(K26>1,'Тарифы ВБ'!$B$9+(K26-1)*'Тарифы ВБ'!$B$10,'Тарифы ВБ'!$B$8) -> 32 | Z26: =SUM(X26:Y26) -> 104.08944 | AA26: =IFERROR(Z26/S26,0) -> 0.19105991 | AB26: =IF(K26>1,'Тарифы ВБ'!$B$14*'Тарифы ВБ'!$B$16*'Тарифы ВБ'!$B$15+(K26-1)*'Тарифы ВБ'!$B$14,'Тарифы ВБ'!$B$14*'Тарифы ВБ'!B$16*'Тарифы ВБ'!$B$15) -> 32 | AC26: =+X26+AB26+Y26 -> 136.08944 | AD26: =AC26/S26*100% -> 0.24979706 | AE26: 0.315 | AF26: =S26*AE26 -> 171.612 | AG26: =1.1*S26*$AG$3 -> 0 | AH26: =S26*$AH$3 -> 16.344 | AI26: =F26+V26 -> 397.84789 | AJ26: =IFERROR(AL26/S26,0) -> 0.19973588 | AK26: =S26-AI26 -> 146.95211 | AL26: =AK26-S26*7% -> 108.81611 | AM26: =AL26/H26 -> 2.1005977 | AN26: 599 | AO26: =$AN26-$AI26 -> 201.15211 | AP26: =$AO26-$AN26*7% -> 159.22211 | AQ26: =$AP26/$H26*100% -> 3.0736405 | AR26: =$AP26/$AN26 -> 0.2658132 | AS26: =IFERROR(_xlfn.XLOOKUP(A26,'[2]Рассчет акции'!$A:$A,'[2]Рассчет акции'!$BH:$BH),0) -> * | AT26: =IFERROR(_xlfn.XLOOKUP($A26,'[2]Рассчет акции'!$A:$A,'[2]Рассчет акции'!$BC:$BC),0) -> 545 | AU26: =IFERROR($AW26/$AT26,0) -> 0.20000387 | AV26: =$AT26-$AI26 -> 147.15211 | AW26: =$AV26-$AT26*7% -> 109.00211 | AX26: =$AW26/$H26*100% -> 2.1041883 | AY26: =IFERROR(_xlfn.XLOOKUP(E26,'[2]Рассчет акции'!$D:$D,'[2]Рассчет акции'!$BM:$BM),0) -> 254 | AZ26: =IFERROR(_xlfn.XLOOKUP(E26,'[2]Рассчет акции'!$D:$D,'[2]Рассчет акции'!$BN:$BN),0) -> 443 | BA26: =S26/H26 -> 10.516877 | BC26: =_xlfn.XLOOKUP(B26,#REF!,#REF!,0) -> #REF! | BD26: =BC26/(100%-BE26) -> #REF! | BE26: =_xlfn.XLOOKUP($B26,'[1]Рассчет акции'!$A:$A,'[1]Рассчет акции'!$J:$J) -> 0.34980392 | BF26: =BS26+BI26+BJ26+BU26+BK26 -> #REF! | BG26: =IFERROR(BF26/BC26,0) -> 0 | BH26: 0.37 | BI26: =BC26*BH26 -> #REF! | BJ26: =BC26*$BJ$3 -> #REF! | BK26: =K26*$BK$3*30 -> 0 | BL26: =(IF(K26>$BL$3,('Тарифы ОЗОН'!$G$3+ROUNDUP(K26-$BL$3,0)*'Тарифы ОЗОН'!$G$4),'Тарифы ОЗОН'!$G$3)) -> 46.77 | BM26: =$BN$3 -> 35 | BN26: =_xlfn.XLOOKUP(BM26,'Тарифы ОЗОН'!$A:$A,'Тарифы ОЗОН'!$B:$B) -> 1.32 | BO26: =_xlfn.XLOOKUP(BM26,'Тарифы ОЗОН'!$A:$A,'Тарифы ОЗОН'!C:C) -> 0.016 | BP26: =$BP$3 -> 25 | BQ26: =BL26*BN26+BC26*BO26+BP26 -> #REF! | BR26: =$BR$3 -> 0.85 | BS26: =(100%/BR26)*BQ26+(100%/BR26-1)*BL26 -> #REF! | BT26: =IFERROR(BS26/BC26*100%,0) -> 0 | BU26: =BC26*$BU$3 -> #REF! | BV26: =BF26+F26 -> #REF! | BW26: =IFERROR(BY26/BC26,0) -> 0 | BX26: =IFERROR(BC26-BV26,0) -> 0 | BY26: =BX26-BC26*7% -> #REF! | BZ26: =IFERROR(BY26/H26*100%,0) -> 0 | CA26: 629 | CB26: =IF(BC26=0,0,CA26-BV26) -> #REF! | CC26: =IF(CB26=0,0,CB26-CA26*7%) -> #REF! | CD26: =CC26/H26*100% -> #REF! | CE26: =IFERROR(CC26/CA26,0) -> 0 | CF26: =_xlfn.XLOOKUP(B26,'[1]Рассчет акции'!$A:$A,'[1]Рассчет акции'!$R:$R,0) -> 0 | CG26: =_xlfn.XLOOKUP(B26,'[1]Рассчет акции'!$A:$A,'[1]Рассчет акции'!$M:$M,0) -> 598 | CH26: =IFERROR($CJ26/$CG26,0) -> 0 | CI26: =IF(BC26>0,CG26-BV26,0) -> #REF! | CJ26: =IF(CI26>0,$CI26-$CG26*7%,0) -> #REF! | CK26: =$CJ26/$H26*100% -> #REF! | CL26: =_xlfn.XLOOKUP(B26,'[1]Рассчет акции'!$A:$A,'[1]Рассчет акции'!$W:$W,0) -> 50 | CM26: =_xlfn.XLOOKUP(B26,'[1]Рассчет акции'!$A:$A,'[1]Рассчет акции'!$X:$X,0) -> 175 | CN26: =BC26/H26 -> #REF! | CO26: =CA26-10%*CA26 -> 566.1 | CP26: =_xlfn.XLOOKUP(B26,'[1]Рассчет акции'!$A:$A,'[1]Рассчет акции'!$Z:$Z,0) -> 0
A27: 223671295 | B27: 1980924947 | C27: ACRB1MS106RJ | D27: Мяч с шипами оранжевый 6 см | E27: 2039818580389 | F27: =SUM(H27:J27) -> 73.802451 | G27: =IFERROR(F27/S27*100%,0) -> 0.17131488 | H27: =IF(_xlfn.XLOOKUP($C27,'Юнит Карго'!$A:$A,'Юнит Карго'!$G:$G)=0,_xlfn.XLOOKUP(E27,'Себес 1С текущ'!G:G,'Себес 1С текущ'!H:H),_xlfn.XLOOKUP($C27,'Юнит Карго'!$A:$A,'Юнит Карго'!$P:$P,0,0)) -> 51.802451 | I27: =_xlfn.XLOOKUP(E27,[3]ТЗ_ФФ!$D:$D,[3]ТЗ_ФФ!$BG:$BG,0) -> 14 | J27: =$J$3 -> 8 | K27: =(L27*M27*N27)/1000 -> 0.343 | L27: 7 | M27: 7 | N27: 7 | O27: =_xlfn.XLOOKUP($C27,'Юнит Карго'!$A:$A,'Юнит Карго'!$T:$T,0,0) -> 0.04 | P27: своя | Q27: 300 | S27: =T27-(T27*U27) -> 430.8 | T27: =_xlfn.XLOOKUP(E27,'[2]Рассчет акции'!$D:$D,'[2]Рассчет акции'!$G:$G,0) -> 718 | U27: =_xlfn.XLOOKUP(E27,'[2]Рассчет акции'!$D:$D,'[2]Рассчет акции'!$F:$F,0) -> 0.4 | V27: =AC27+AF27+AH27+AG27 -> 283.82624 | W27: =IFERROR(V27/S27,0) -> 0.65883528 | X27: =IF(K27>1,('Тарифы ВБ'!$B$9+(K27-1)*'Тарифы ВБ'!$B$10)*'Тарифы ВБ'!$B$15*'Тарифы ВБ'!$B$12+S27*'Тарифы ВБ'!$B$13,'Тарифы ВБ'!$B$8*'Тарифы ВБ'!$B$15*'Тарифы ВБ'!$B$12+S27*'Тарифы ВБ'!$B$13) -> 71.20024 | Y27: =IF(K27>1,'Тарифы ВБ'!$B$9+(K27-1)*'Тарифы ВБ'!$B$10,'Тарифы ВБ'!$B$8) -> 32 | Z27: =SUM(X27:Y27) -> 103.20024 | AA27: =IFERROR(Z27/S27,0) -> 0.23955487 | AB27: =IF(K27>1,'Тарифы ВБ'!$B$14*'Тарифы ВБ'!$B$16*'Тарифы ВБ'!$B$15+(K27-1)*'Тарифы ВБ'!$B$14,'Тарифы ВБ'!$B$14*'Тарифы ВБ'!B$16*'Тарифы ВБ'!$B$15) -> 32 | AC27: =+X27+AB27+Y27 -> 135.20024 | AD27: =AC27/S27*100% -> 0.31383528 | AE27: 0.315 | AF27: =S27*AE27 -> 135.702 | AG27: =1.1*S27*$AG$3 -> 0 | AH27: =S27*$AH$3 -> 12.924 | AI27: =F27+V27 -> 357.62869 | AJ27: =IFERROR(AL27/S27,0) -> 0.099849836 | AK27: =S27-AI27 -> 73.171309 | AL27: =AK27-S27*7% -> 43.015309 | AM27: =AL27/H27 -> 0.83037209 | AN27: 599 | AO27: =$AN27-$AI27 -> 241.37131 | AP27: =$AO27-$AN27*7% -> 199.44131 | AQ27: =$AP27/$H27*100% -> 3.8500362 | AR27: =$AP27/$AN27 -> 0.33295711 | AS27: =IFERROR(_xlfn.XLOOKUP(A27,'[2]Рассчет акции'!$A:$A,'[2]Рассчет акции'!$BH:$BH),0) -> * | AT27: =IFERROR(_xlfn.XLOOKUP($A27,'[2]Рассчет акции'!$A:$A,'[2]Рассчет акции'!$BC:$BC),0) -> 431 | AU27: =IFERROR($AW27/$AT27,0) -> 0.10023506 | AV27: =$AT27-$AI27 -> 73.371309 | AW27: =$AV27-$AT27*7% -> 43.201309 | AX27: =$AW27/$H27*100% -> 0.83396265 | AY27: =IFERROR(_xlfn.XLOOKUP(E27,'[2]Рассчет акции'!$D:$D,'[2]Рассчет акции'!$BM:$BM),0) -> 447 | AZ27: =IFERROR(_xlfn.XLOOKUP(E27,'[2]Рассчет акции'!$D:$D,'[2]Рассчет акции'!$BN:$BN),0) -> 823 | BA27: =S27/H27 -> 8.3162089 | BC27: =_xlfn.XLOOKUP(B27,#REF!,#REF!,0) -> #REF! | BD27: =BC27/(100%-BE27) -> #REF! | BE27: =_xlfn.XLOOKUP($B27,'[1]Рассчет акции'!$A:$A,'[1]Рассчет акции'!$J:$J) -> 0.34980392 | BF27: =BS27+BI27+BJ27+BU27+BK27 -> #REF! | BG27: =IFERROR(BF27/BC27,0) -> 0 | BH27: 0.37 | BI27: =BC27*BH27 -> #REF! | BJ27: =BC27*$BJ$3 -> #REF! | BK27: =K27*$BK$3*30 -> 0 | BL27: =(IF(K27>$BL$3,('Тарифы ОЗОН'!$G$3+ROUNDUP(K27-$BL$3,0)*'Тарифы ОЗОН'!$G$4),'Тарифы ОЗОН'!$G$3)) -> 46.77 | BM27: =$BN$3 -> 35 | BN27: =_xlfn.XLOOKUP(BM27,'Тарифы ОЗОН'!$A:$A,'Тарифы ОЗОН'!$B:$B) -> 1.32 | BO27: =_xlfn.XLOOKUP(BM27,'Тарифы ОЗОН'!$A:$A,'Тарифы ОЗОН'!C:C) -> 0.016 | BP27: =$BP$3 -> 25 | BQ27: =BL27*BN27+BC27*BO27+BP27 -> #REF! | BR27: =$BR$3 -> 0.85 | BS27: =(100%/BR27)*BQ27+(100%/BR27-1)*BL27 -> #REF! | BT27: =IFERROR(BS27/BC27*100%,0) -> 0 | BU27: =BC27*$BU$3 -> #REF! | BV27: =BF27+F27 -> #REF! | BW27: =IFERROR(BY27/BC27,0) -> 0 | BX27: =IFERROR(BC27-BV27,0) -> 0 | BY27: =BX27-BC27*7% -> #REF! | BZ27: =IFERROR(BY27/H27*100%,0) -> 0 | CA27: 629 | CB27: =IF(BC27=0,0,CA27-BV27) -> #REF! | CC27: =IF(CB27=0,0,CB27-CA27*7%) -> #REF! | CD27: =CC27/H27*100% -> #REF! | CE27: =IFERROR(CC27/CA27,0) -> 0 | CF27: =_xlfn.XLOOKUP(B27,'[1]Рассчет акции'!$A:$A,'[1]Рассчет акции'!$R:$R,0) -> 0 | CG27: =_xlfn.XLOOKUP(B27,'[1]Рассчет акции'!$A:$A,'[1]Рассчет акции'!$M:$M,0) -> 598 | CH27: =IFERROR($CJ27/$CG27,0) -> 0 | CI27: =IF(BC27>0,CG27-BV27,0) -> #REF! | CJ27: =IF(CI27>0,$CI27-$CG27*7%,0) -> #REF! | CK27: =$CJ27/$H27*100% -> #REF! | CL27: =_xlfn.XLOOKUP(B27,'[1]Рассчет акции'!$A:$A,'[1]Рассчет акции'!$W:$W,0) -> 63 | CM27: =_xlfn.XLOOKUP(B27,'[1]Рассчет акции'!$A:$A,'[1]Рассчет акции'!$X:$X,0) -> 999 | CN27: =BC27/H27 -> #REF! | CO27: =CA27-10%*CA27 -> 566.1 | CP27: =_xlfn.XLOOKUP(B27,'[1]Рассчет акции'!$A:$A,'[1]Рассчет акции'!$Z:$Z,0) -> 0
A28: 370591238 | B28: 1980924996 | C28: ACRB1MS106BС | D28: Мяч с шипами черный 6 см | E28: 2043369663040 | F28: =SUM(H28:J28) -> 61.702451 | G28: =IFERROR(F28/S28*100%,0) -> 0.10297472 | H28: =IF(_xlfn.XLOOKUP($C28,'Юнит Карго'!$A:$A,'Юнит Карго'!$G:$G)=0,_xlfn.XLOOKUP(E28,'Себес 1С текущ'!G:G,'Себес 1С текущ'!H:H),_xlfn.XLOOKUP($C28,'Юнит Карго'!$A:$A,'Юнит Карго'!$P:$P,0,0)) -> 39.702451 | I28: =_xlfn.XLOOKUP(E28,[3]ТЗ_ФФ!$D:$D,[3]ТЗ_ФФ!$BG:$BG,0) -> 14 | J28: =$J$3 -> 8 | K28: =(L28*M28*N28)/1000 -> 0.343 | L28: 7 | M28: 7 | N28: 7 | O28: =_xlfn.XLOOKUP($C28,'Юнит Карго'!$A:$A,'Юнит Карго'!$T:$T,0,0) -> 0.04 | P28: своя | Q28: 300 | S28: =T28-(T28*U28) -> 599.2 | T28: =_xlfn.XLOOKUP(E28,'[2]Рассчет акции'!$D:$D,'[2]Рассчет акции'!$G:$G,0) -> 856 | U28: =_xlfn.XLOOKUP(E28,'[2]Рассчет акции'!$D:$D,'[2]Рассчет акции'!$F:$F,0) -> 0.3 | V28: =AC28+AF28+AH28+AG28 -> 343.23776 | W28: =IFERROR(V28/S28,0) -> 0.5728267 | X28: =IF(K28>1,('Тарифы ВБ'!$B$9+(K28-1)*'Тарифы ВБ'!$B$10)*'Тарифы ВБ'!$B$15*'Тарифы ВБ'!$B$12+S28*'Тарифы ВБ'!$B$13,'Тарифы ВБ'!$B$8*'Тарифы ВБ'!$B$15*'Тарифы ВБ'!$B$12+S28*'Тарифы ВБ'!$B$13) -> 72.51376 | Y28: =IF(K28>1,'Тарифы ВБ'!$B$9+(K28-1)*'Тарифы ВБ'!$B$10,'Тарифы ВБ'!$B$8) -> 32 | Z28: =SUM(X28:Y28) -> 104.51376 | AA28: =IFERROR(Z28/S28,0) -> 0.17442216 | AB28: =IF(K28>1,'Тарифы ВБ'!$B$14*'Тарифы ВБ'!$B$16*'Тарифы ВБ'!$B$15+(K28-1)*'Тарифы ВБ'!$B$14,'Тарифы ВБ'!$B$14*'Тарифы ВБ'!B$16*'Тарифы ВБ'!$B$15) -> 32 | AC28: =+X28+AB28+Y28 -> 136.51376 | AD28: =AC28/S28*100% -> 0.2278267 | AE28: 0.315 | AF28: =S28*AE28 -> 188.748 | AG28: =1.1*S28*$AG$3 -> 0 | AH28: =S28*$AH$3 -> 17.976 | AI28: =F28+V28 -> 404.94021 | AJ28: =IFERROR(AL28/S28,0) -> 0.25419858 | AK28: =S28-AI28 -> 194.25979 | AL28: =AK28-S28*7% -> 152.31579 | AM28: =AL28/H28 -> 3.8364329 | AN28: 599 | AO28: =$AN28-$AI28 -> 194.05979 | AP28: =$AO28-$AN28*7% -> 152.12979 | AQ28: =$AP28/$H28*100% -> 3.8317481 | AR28: =$AP28/$AN28 -> 0.25397294 | AS28: =IFERROR(_xlfn.XLOOKUP(A28,'[2]Рассчет акции'!$A:$A,'[2]Рассчет акции'!$BH:$BH),0) -> 0 | AT28: =IFERROR(_xlfn.XLOOKUP($A28,'[2]Рассчет акции'!$A:$A,'[2]Рассчет акции'!$BC:$BC),0) -> 0 | AU28: =IFERROR($AW28/$AT28,0) -> 0 | AV28: =$AT28-$AI28 -> -404.94021 | AW28: =$AV28-$AT28*7% -> -404.94021 | AX28: =$AW28/$H28*100% -> -10.199376 | AY28: =IFERROR(_xlfn.XLOOKUP(E28,'[2]Рассчет акции'!$D:$D,'[2]Рассчет акции'!$BM:$BM),0) -> 252 | AZ28: =IFERROR(_xlfn.XLOOKUP(E28,'[2]Рассчет акции'!$D:$D,'[2]Рассчет акции'!$BN:$BN),0) -> 999 | BA28: =S28/H28 -> 15.092267 | BC28: =_xlfn.XLOOKUP(B28,#REF!,#REF!,0) -> #REF! | BD28: =BC28/(100%-BE28) -> #REF! | BE28: =_xlfn.XLOOKUP($B28,'[1]Рассчет акции'!$A:$A,'[1]Рассчет акции'!$J:$J) -> 0.34980392 | BF28: =BS28+BI28+BJ28+BU28+BK28 -> #REF! | BG28: =IFERROR(BF28/BC28,0) -> 0 | BH28: 0.37 | BI28: =BC28*BH28 -> #REF! | BJ28: =BC28*$BJ$3 -> #REF! | BK28: =K28*$BK$3*30 -> 0 | BL28: =(IF(K28>$BL$3,('Тарифы ОЗОН'!$G$3+ROUNDUP(K28-$BL$3,0)*'Тарифы ОЗОН'!$G$4),'Тарифы ОЗОН'!$G$3)) -> 46.77 | BM28: =$BN$3 -> 35 | BN28: =_xlfn.XLOOKUP(BM28,'Тарифы ОЗОН'!$A:$A,'Тарифы ОЗОН'!$B:$B) -> 1.32 | BO28: =_xlfn.XLOOKUP(BM28,'Тарифы ОЗОН'!$A:$A,'Тарифы ОЗОН'!C:C) -> 0.016 | BP28: =$BP$3 -> 25 | BQ28: =BL28*BN28+BC28*BO28+BP28 -> #REF! | BR28: =$BR$3 -> 0.85 | BS28: =(100%/BR28)*BQ28+(100%/BR28-1)*BL28 -> #REF! | BT28: =IFERROR(BS28/BC28*100%,0) -> 0 | BU28: =BC28*$BU$3 -> #REF! | BV28: =BF28+F28 -> #REF! | BW28: =IFERROR(BY28/BC28,0) -> 0 | BX28: =IFERROR(BC28-BV28,0) -> 0 | BY28: =BX28-BC28*7% -> #REF! | BZ28: =IFERROR(BY28/H28*100%,0) -> 0 | CA28: 629 | CB28: =IF(BC28=0,0,CA28-BV28) -> #REF! | CC28: =IF(CB28=0,0,CB28-CA28*7%) -> #REF! | CD28: =CC28/H28*100% -> #REF! | CE28: =IFERROR(CC28/CA28,0) -> 0 | CF28: =_xlfn.XLOOKUP(B28,'[1]Рассчет акции'!$A:$A,'[1]Рассчет акции'!$R:$R,0) -> 0 | CG28: =_xlfn.XLOOKUP(B28,'[1]Рассчет акции'!$A:$A,'[1]Рассчет акции'!$M:$M,0) -> 598 | CH28: =IFERROR($CJ28/$CG28,0) -> 0 | CI28: =IF(BC28>0,CG28-BV28,0) -> #REF! | CJ28: =IF(CI28>0,$CI28-$CG28*7%,0) -> #REF! | CK28: =$CJ28/$H28*100% -> #REF! | CL28: =_xlfn.XLOOKUP(B28,'[1]Рассчет акции'!$A:$A,'[1]Рассчет акции'!$W:$W,0) -> 78 | CM28: =_xlfn.XLOOKUP(B28,'[1]Рассчет акции'!$A:$A,'[1]Рассчет акции'!$X:$X,0) -> 999 | CN28: =BC28/H28 -> #REF! | CO28: =CA28-10%*CA28 -> 566.1 | CP28: =_xlfn.XLOOKUP(B28,'[1]Рассчет акции'!$A:$A,'[1]Рассчет акции'!$Z:$Z,0) -> 0
A29: 419145391 | B29: 2415742768 | C29: ACRB1MS107WH | D29: Мяч с шипами белый 7 см | E29: 2044025326637 | F29: =SUM(H29:J29) -> 72.478676 | G29: =IFERROR(F29/S29*100%,0) -> 0.11712779 | H29: =IF(_xlfn.XLOOKUP($C29,'Юнит Карго'!$A:$A,'Юнит Карго'!$G:$G)=0,_xlfn.XLOOKUP(E29,'Себес 1С текущ'!G:G,'Себес 1С текущ'!H:H),_xlfn.XLOOKUP($C29,'Юнит Карго'!$A:$A,'Юнит Карго'!$P:$P,0,0)) -> 50.478676 | I29: =_xlfn.XLOOKUP(E29,[3]ТЗ_ФФ!$D:$D,[3]ТЗ_ФФ!$BG:$BG,0) -> 14 | J29: =$J$3 -> 8 | K29: =(L29*M29*N29)/1000 -> 0.512 | L29: 8 | M29: 8 | N29: 8 | O29: =_xlfn.XLOOKUP($C29,'Юнит Карго'!$A:$A,'Юнит Карго'!$T:$T,0,0) -> 0.06 | P29: своя | S29: =T29-(T29*U29) -> 618.8 | T29: =_xlfn.XLOOKUP(E29,'[2]Рассчет акции'!$D:$D,'[2]Рассчет акции'!$G:$G,0) -> 884 | U29: =_xlfn.XLOOKUP(E29,'[2]Рассчет акции'!$D:$D,'[2]Рассчет акции'!$F:$F,0) -> 0.3 | V29: =AC29+AF29+AH29+AG29 -> 350.15264 | W29: =IFERROR(V29/S29,0) -> 0.56585753 | X29: =IF(K29>1,('Тарифы ВБ'!$B$9+(K29-1)*'Тарифы ВБ'!$B$10)*'Тарифы ВБ'!$B$15*'Тарифы ВБ'!$B$12+S29*'Тарифы ВБ'!$B$13,'Тарифы ВБ'!$B$8*'Тарифы ВБ'!$B$15*'Тарифы ВБ'!$B$12+S29*'Тарифы ВБ'!$B$13) -> 72.66664 | Y29: =IF(K29>1,'Тарифы ВБ'!$B$9+(K29-1)*'Тарифы ВБ'!$B$10,'Тарифы ВБ'!$B$8) -> 32 | Z29: =SUM(X29:Y29) -> 104.66664 | AA29: =IFERROR(Z29/S29,0) -> 0.16914454 | AB29: =IF(K29>1,'Тарифы ВБ'!$B$14*'Тарифы ВБ'!$B$16*'Тарифы ВБ'!$B$15+(K29-1)*'Тарифы ВБ'!$B$14,'Тарифы ВБ'!$B$14*'Тарифы ВБ'!B$16*'Тарифы ВБ'!$B$15) -> 32 | AC29: =+X29+AB29+Y29 -> 136.66664 | AD29: =AC29/S29*100% -> 0.22085753 | AE29: 0.315 | AF29: =S29*AE29 -> 194.922 | AG29: =1.1*S29*$AG$3 -> 0 | AH29: =S29*$AH$3 -> 18.564 | AI29: =F29+V29 -> 422.63132 | AJ29: =IFERROR(AL29/S29,0) -> 0.24701468 | AK29: =S29-AI29 -> 196.16868 | AL29: =AK29-S29*7% -> 152.85268 | AM29: =AL29/H29 -> 3.0280644 | AN29: 619 | AO29: =$AN29-$AI29 -> 196.36868 | AP29: =$AO29-$AN29*7% -> 153.03868 | AQ29: =$AP29/$H29*100% -> 3.0317492 | AR29: =$AP29/$AN29 -> 0.24723535 | AS29: =IFERROR(_xlfn.XLOOKUP(A29,'[2]Рассчет акции'!$A:$A,'[2]Рассчет акции'!$BH:$BH),0) -> 0 | AT29: =IFERROR(_xlfn.XLOOKUP($A29,'[2]Рассчет акции'!$A:$A,'[2]Рассчет акции'!$BC:$BC),0) -> 0 | AU29: =IFERROR($AW29/$AT29,0) -> 0 | AV29: =$AT29-$AI29 -> -422.63132 | AW29: =$AV29-$AT29*7% -> -422.63132 | AX29: =$AW29/$H29*100% -> -8.3724723 | AY29: =IFERROR(_xlfn.XLOOKUP(E29,'[2]Рассчет акции'!$D:$D,'[2]Рассчет акции'!$BM:$BM),0) -> 298 | AZ29: =IFERROR(_xlfn.XLOOKUP(E29,'[2]Рассчет акции'!$D:$D,'[2]Рассчет акции'!$BN:$BN),0) -> 999 | BA29: =S29/H29 -> 12.258642 | BC29: =_xlfn.XLOOKUP(B29,#REF!,#REF!,0) -> #REF! | BD29: =BC29/(100%-BE29) -> #REF! | BE29: =_xlfn.XLOOKUP($B29,'[1]Рассчет акции'!$A:$A,'[1]Рассчет акции'!$J:$J) -> 0.34980392 | BF29: =BS29+BI29+BJ29+BU29+BK29 -> #REF! | BG29: =IFERROR(BF29/BC29,0) -> 0 | BH29: 0.37 | BI29: =BC29*BH29 -> #REF! | BJ29: =BC29*$BJ$3 -> #REF! | BK29: =K29*$BK$3*30 -> 0 | BL29: =(IF(K29>$BL$3,('Тарифы ОЗОН'!$G$3+ROUNDUP(K29-$BL$3,0)*'Тарифы ОЗОН'!$G$4),'Тарифы ОЗОН'!$G$3)) -> 46.77 | BM29: =$BN$3 -> 35 | BN29: =_xlfn.XLOOKUP(BM29,'Тарифы ОЗОН'!$A:$A,'Тарифы ОЗОН'!$B:$B) -> 1.32 | BO29: =_xlfn.XLOOKUP(BM29,'Тарифы ОЗОН'!$A:$A,'Тарифы ОЗОН'!C:C) -> 0.016 | BP29: =$BP$3 -> 25 | BQ29: =BL29*BN29+BC29*BO29+BP29 -> #REF! | BR29: =$BR$3 -> 0.85 | BS29: =(100%/BR29)*BQ29+(100%/BR29-1)*BL29 -> #REF! | BT29: =IFERROR(BS29/BC29*100%,0) -> 0 | BU29: =BC29*$BU$3 -> #REF! | BV29: =BF29+F29 -> #REF! | BW29: =IFERROR(BY29/BC29,0) -> 0 | BX29: =IFERROR(BC29-BV29,0) -> 0 | BY29: =BX29-BC29*7% -> #REF! | BZ29: =IFERROR(BY29/H29*100%,0) -> 0 | CA29: 629 | CB29: =IF(BC29=0,0,CA29-BV29) -> #REF! | CC29: =IF(CB29=0,0,CB29-CA29*7%) -> #REF! | CD29: =CC29/H29*100% -> #REF! | CE29: =IFERROR(CC29/CA29,0) -> 0 | CF29: =_xlfn.XLOOKUP(B29,'[1]Рассчет акции'!$A:$A,'[1]Рассчет акции'!$R:$R,0) -> 0 | CG29: =_xlfn.XLOOKUP(B29,'[1]Рассчет акции'!$A:$A,'[1]Рассчет акции'!$M:$M,0) -> 626 | CH29: =IFERROR($CJ29/$CG29,0) -> 0 | CI29: =IF(BC29>0,CG29-BV29,0) -> #REF! | CJ29: =IF(CI29>0,$CI29-$CG29*7%,0) -> #REF! | CK29: =$CJ29/$H29*100% -> #REF! | CL29: =_xlfn.XLOOKUP(B29,'[1]Рассчет акции'!$A:$A,'[1]Рассчет акции'!$W:$W,0) -> 12 | CM29: =_xlfn.XLOOKUP(B29,'[1]Рассчет акции'!$A:$A,'[1]Рассчет акции'!$X:$X,0) -> 999 | CN29: =BC29/H29 -> #REF! | CO29: =CA29-10%*CA29 -> 566.1 | CP29: =_xlfn.XLOOKUP(B29,'[1]Рассчет акции'!$A:$A,'[1]Рассчет акции'!$Z:$Z,0) -> 0
A30: 419145389 | B30: 2415742912 | C30: ACRB1MS107PN | D30: Мяч с шипами розовый 7 см | E30: 2044025316447 | F30: =SUM(H30:J30) -> 72.478676 | G30: =IFERROR(F30/S30*100%,0) -> 0.11842921 | H30: =IF(_xlfn.XLOOKUP($C30,'Юнит Карго'!$A:$A,'Юнит Карго'!$G:$G)=0,_xlfn.XLOOKUP(E30,'Себес 1С текущ'!G:G,'Себес 1С текущ'!H:H),_xlfn.XLOOKUP($C30,'Юнит Карго'!$A:$A,'Юнит Карго'!$P:$P,0,0)) -> 50.478676 | I30: =_xlfn.XLOOKUP(E30,[3]ТЗ_ФФ!$D:$D,[3]ТЗ_ФФ!$BG:$BG,0) -> 14 | J30: =$J$3 -> 8 | K30: =(L30*M30*N30)/1000 -> 0.512 | L30: 8 | M30: 8 | N30: 8 | O30: =_xlfn.XLOOKUP($C30,'Юнит Карго'!$A:$A,'Юнит Карго'!$T:$T,0,0) -> 0.06 | P30: своя | S30: =T30-(T30*U30) -> 612 | T30: =_xlfn.XLOOKUP(E30,'[2]Рассчет акции'!$D:$D,'[2]Рассчет акции'!$G:$G,0) -> 1020 | U30: =_xlfn.XLOOKUP(E30,'[2]Рассчет акции'!$D:$D,'[2]Рассчет акции'!$F:$F,0) -> 0.4 | V30: =AC30+AF30+AH30+AG30 -> 347.7536 | W30: =IFERROR(V30/S30,0) -> 0.56822484 | X30: =IF(K30>1,('Тарифы ВБ'!$B$9+(K30-1)*'Тарифы ВБ'!$B$10)*'Тарифы ВБ'!$B$15*'Тарифы ВБ'!$B$12+S30*'Тарифы ВБ'!$B$13,'Тарифы ВБ'!$B$8*'Тарифы ВБ'!$B$15*'Тарифы ВБ'!$B$12+S30*'Тарифы ВБ'!$B$13) -> 72.6136 | Y30: =IF(K30>1,'Тарифы ВБ'!$B$9+(K30-1)*'Тарифы ВБ'!$B$10,'Тарифы ВБ'!$B$8) -> 32 | Z30: =SUM(X30:Y30) -> 104.6136 | AA30: =IFERROR(Z30/S30,0) -> 0.17093725 | AB30: =IF(K30>1,'Тарифы ВБ'!$B$14*'Тарифы ВБ'!$B$16*'Тарифы ВБ'!$B$15+(K30-1)*'Тарифы ВБ'!$B$14,'Тарифы ВБ'!$B$14*'Тарифы ВБ'!B$16*'Тарифы ВБ'!$B$15) -> 32 | AC30: =+X30+AB30+Y30 -> 136.6136 | AD30: =AC30/S30*100% -> 0.22322484 | AE30: 0.315 | AF30: =S30*AE30 -> 192.78 | AG30: =1.1*S30*$AG$3 -> 0 | AH30: =S30*$AH$3 -> 18.36 | AI30: =F30+V30 -> 420.23228 | AJ30: =IFERROR(AL30/S30,0) -> 0.24334595 | AK30: =S30-AI30 -> 191.76772 | AL30: =AK30-S30*7% -> 148.92772 | AM30: =AL30/H30 -> 2.9503096 | AN30: 619 | AO30: =$AN30-$AI30 -> 198.76772 | AP30: =$AO30-$AN30*7% -> 155.43772 | AQ30: =$AP30/$H30*100% -> 3.079275 | AR30: =$AP30/$AN30 -> 0.25111102 | AS30: =IFERROR(_xlfn.XLOOKUP(A30,'[2]Рассчет акции'!$A:$A,'[2]Рассчет акции'!$BH:$BH),0) -> * | AT30: =IFERROR(_xlfn.XLOOKUP($A30,'[2]Рассчет акции'!$A:$A,'[2]Рассчет акции'!$BC:$BC),0) -> 612 | AU30: =IFERROR($AW30/$AT30,0) -> 0.24334595 | AV30: =$AT30-$AI30 -> 191.76772 | AW30: =$AV30-$AT30*7% -> 148.92772 | AX30: =$AW30/$H30*100% -> 2.9503096 | AY30: =IFERROR(_xlfn.XLOOKUP(E30,'[2]Рассчет акции'!$D:$D,'[2]Рассчет акции'!$BM:$BM),0) -> 118 | AZ30: =IFERROR(_xlfn.XLOOKUP(E30,'[2]Рассчет акции'!$D:$D,'[2]Рассчет акции'!$BN:$BN),0) -> 717 | BA30: =S30/H30 -> 12.123931 | BC30: =_xlfn.XLOOKUP(B30,#REF!,#REF!,0) -> #REF! | BD30: =BC30/(100%-BE30) -> #REF! | BE30: =_xlfn.XLOOKUP($B30,'[1]Рассчет акции'!$A:$A,'[1]Рассчет акции'!$J:$J) -> 0.34980392 | BF30: =BS30+BI30+BJ30+BU30+BK30 -> #REF! | BG30: =IFERROR(BF30/BC30,0) -> 0 | BH30: 0.37 | BI30: =BC30*BH30 -> #REF! | BJ30: =BC30*$BJ$3 -> #REF! | BK30: =K30*$BK$3*30 -> 0 | BL30: =(IF(K30>$BL$3,('Тарифы ОЗОН'!$G$3+ROUNDUP(K30-$BL$3,0)*'Тарифы ОЗОН'!$G$4),'Тарифы ОЗОН'!$G$3)) -> 46.77 | BM30: =$BN$3 -> 35 | BN30: =_xlfn.XLOOKUP(BM30,'Тарифы ОЗОН'!$A:$A,'Тарифы ОЗОН'!$B:$B) -> 1.32 | BO30: =_xlfn.XLOOKUP(BM30,'Тарифы ОЗОН'!$A:$A,'Тарифы ОЗОН'!C:C) -> 0.016 | BP30: =$BP$3 -> 25 | BQ30: =BL30*BN30+BC30*BO30+BP30 -> #REF! | BR30: =$BR$3 -> 0.85 | BS30: =(100%/BR30)*BQ30+(100%/BR30-1)*BL30 -> #REF! | BT30: =IFERROR(BS30/BC30*100%,0) -> 0 | BU30: =BC30*$BU$3 -> #REF! | BV30: =BF30+F30 -> #REF! | BW30: =IFERROR(BY30/BC30,0) -> 0 | BX30: =IFERROR(BC30-BV30,0) -> 0 | BY30: =BX30-BC30*7% -> #REF! | BZ30: =IFERROR(BY30/H30*100%,0) -> 0 | CA30: 629 | CB30: =IF(BC30=0,0,CA30-BV30) -> #REF! | CC30: =IF(CB30=0,0,CB30-CA30*7%) -> #REF! | CD30: =CC30/H30*100% -> #REF! | CE30: =IFERROR(CC30/CA30,0) -> 0 | CF30: =_xlfn.XLOOKUP(B30,'[1]Рассчет акции'!$A:$A,'[1]Рассчет акции'!$R:$R,0) -> 0 | CG30: =_xlfn.XLOOKUP(B30,'[1]Рассчет акции'!$A:$A,'[1]Рассчет акции'!$M:$M,0) -> 626 | CH30: =IFERROR($CJ30/$CG30,0) -> 0 | CI30: =IF(BC30>0,CG30-BV30,0) -> #REF! | CJ30: =IF(CI30>0,$CI30-$CG30*7%,0) -> #REF! | CK30: =$CJ30/$H30*100% -> #REF! | CL30: =_xlfn.XLOOKUP(B30,'[1]Рассчет акции'!$A:$A,'[1]Рассчет акции'!$W:$W,0) -> 6 | CM30: =_xlfn.XLOOKUP(B30,'[1]Рассчет акции'!$A:$A,'[1]Рассчет акции'!$X:$X,0) -> 999 | CN30: =BC30/H30 -> #REF! | CO30: =CA30-10%*CA30 -> 566.1 | CP30: =_xlfn.XLOOKUP(B30,'[1]Рассчет акции'!$A:$A,'[1]Рассчет акции'!$Z:$Z,0) -> 0
A31: 419145748 | B31: 2415742611 | C31: ACRB1MS107BL | D31: Мяч с шипами голубой 7 см | E31: 2044025338661 | F31: =SUM(H31:J31) -> 72.478676 | G31: =IFERROR(F31/S31*100%,0) -> 0.13101713 | H31: =IF(_xlfn.XLOOKUP($C31,'Юнит Карго'!$A:$A,'Юнит Карго'!$G:$G)=0,_xlfn.XLOOKUP(E31,'Себес 1С текущ'!G:G,'Себес 1С текущ'!H:H),_xlfn.XLOOKUP($C31,'Юнит Карго'!$A:$A,'Юнит Карго'!$P:$P,0,0)) -> 50.478676 | I31: =_xlfn.XLOOKUP(E31,[3]ТЗ_ФФ!$D:$D,[3]ТЗ_ФФ!$BG:$BG,0) -> 14 | J31: =$J$3 -> 8 | K31: =(L31*M31*N31)/1000 -> 0.512 | L31: 8 | M31: 8 | N31: 8 | O31: =_xlfn.XLOOKUP($C31,'Юнит Карго'!$A:$A,'Юнит Карго'!$T:$T,0,0) -> 0.06 | P31: своя | S31: =T31-(T31*U31) -> 553.2 | T31: =_xlfn.XLOOKUP(E31,'[2]Рассчет акции'!$D:$D,'[2]Рассчет акции'!$G:$G,0) -> 922 | U31: =_xlfn.XLOOKUP(E31,'[2]Рассчет акции'!$D:$D,'[2]Рассчет акции'!$F:$F,0) -> 0.4 | V31: =AC31+AF31+AH31+AG31 -> 327.00896 | W31: =IFERROR(V31/S31,0) -> 0.59112249 | X31: =IF(K31>1,('Тарифы ВБ'!$B$9+(K31-1)*'Тарифы ВБ'!$B$10)*'Тарифы ВБ'!$B$15*'Тарифы ВБ'!$B$12+S31*'Тарифы ВБ'!$B$13,'Тарифы ВБ'!$B$8*'Тарифы ВБ'!$B$15*'Тарифы ВБ'!$B$12+S31*'Тарифы ВБ'!$B$13) -> 72.15496 | Y31: =IF(K31>1,'Тарифы ВБ'!$B$9+(K31-1)*'Тарифы ВБ'!$B$10,'Тарифы ВБ'!$B$8) -> 32 | Z31: =SUM(X31:Y31) -> 104.15496 | AA31: =IFERROR(Z31/S31,0) -> 0.18827722 | AB31: =IF(K31>1,'Тарифы ВБ'!$B$14*'Тарифы ВБ'!$B$16*'Тарифы ВБ'!$B$15+(K31-1)*'Тарифы ВБ'!$B$14,'Тарифы ВБ'!$B$14*'Тарифы ВБ'!B$16*'Тарифы ВБ'!$B$15) -> 32 | AC31: =+X31+AB31+Y31 -> 136.15496 | AD31: =AC31/S31*100% -> 0.24612249 | AE31: 0.315 | AF31: =S31*AE31 -> 174.258 | AG31: =1.1*S31*$AG$3 -> 0 | AH31: =S31*$AH$3 -> 16.596 | AI31: =F31+V31 -> 399.48764 | AJ31: =IFERROR(AL31/S31,0) -> 0.20786038 | AK31: =S31-AI31 -> 153.71236 | AL31: =AK31-S31*7% -> 114.98836 | AM31: =AL31/H31 -> 2.2779592 | AN31: 619 | AO31: =$AN31-$AI31 -> 219.51236 | AP31: =$AO31-$AN31*7% -> 176.18236 | AQ31: =$AP31/$H31*100% -> 3.4902335 | AR31: =$AP31/$AN31 -> 0.28462417 | AS31: =IFERROR(_xlfn.XLOOKUP(A31,'[2]Рассчет акции'!$A:$A,'[2]Рассчет акции'!$BH:$BH),0) -> * | AT31: =IFERROR(_xlfn.XLOOKUP($A31,'[2]Рассчет акции'!$A:$A,'[2]Рассчет акции'!$BC:$BC),0) -> 553 | AU31: =IFERROR($AW31/$AT31,0) -> 0.20759921 | AV31: =$AT31-$AI31 -> 153.51236 | AW31: =$AV31-$AT31*7% -> 114.80236 | AX31: =$AW31/$H31*100% -> 2.2742745 | AY31: =IFERROR(_xlfn.XLOOKUP(E31,'[2]Рассчет акции'!$D:$D,'[2]Рассчет акции'!$BM:$BM),0) -> 109 | AZ31: =IFERROR(_xlfn.XLOOKUP(E31,'[2]Рассчет акции'!$D:$D,'[2]Рассчет акции'!$BN:$BN),0) -> 999 | BA31: =S31/H31 -> 10.959083 | BC31: =_xlfn.XLOOKUP(B31,#REF!,#REF!,0) -> #REF! | BD31: =BC31/(100%-BE31) -> #REF! | BE31: =_xlfn.XLOOKUP($B31,'[1]Рассчет акции'!$A:$A,'[1]Рассчет акции'!$J:$J) -> 0.34980392 | BF31: =BS31+BI31+BJ31+BU31+BK31 -> #REF! | BG31: =IFERROR(BF31/BC31,0) -> 0 | BH31: 0.37 | BI31: =BC31*BH31 -> #REF! | BJ31: =BC31*$BJ$3 -> #REF! | BK31: =K31*$BK$3*30 -> 0 | BL31: =(IF(K31>$BL$3,('Тарифы ОЗОН'!$G$3+ROUNDUP(K31-$BL$3,0)*'Тарифы ОЗОН'!$G$4),'Тарифы ОЗОН'!$G$3)) -> 46.77 | BM31: =$BN$3 -> 35 | BN31: =_xlfn.XLOOKUP(BM31,'Тарифы ОЗОН'!$A:$A,'Тарифы ОЗОН'!$B:$B) -> 1.32 | BO31: =_xlfn.XLOOKUP(BM31,'Тарифы ОЗОН'!$A:$A,'Тарифы ОЗОН'!C:C) -> 0.016 | BP31: =$BP$3 -> 25 | BQ31: =BL31*BN31+BC31*BO31+BP31 -> #REF! | BR31: =$BR$3 -> 0.85 | BS31: =(100%/BR31)*BQ31+(100%/BR31-1)*BL31 -> #REF! | BT31: =IFERROR(BS31/BC31*100%,0) -> 0 | BU31: =BC31*$BU$3 -> #REF! | BV31: =BF31+F31 -> #REF! | BW31: =IFERROR(BY31/BC31,0) -> 0 | BX31: =IFERROR(BC31-BV31,0) -> 0 | BY31: =BX31-BC31*7% -> #REF! | BZ31: =IFERROR(BY31/H31*100%,0) -> 0 | CA31: 629 | CB31: =IF(BC31=0,0,CA31-BV31) -> #REF! | CC31: =IF(CB31=0,0,CB31-CA31*7%) -> #REF! | CD31: =CC31/H31*100% -> #REF! | CE31: =IFERROR(CC31/CA31,0) -> 0 | CF31: =_xlfn.XLOOKUP(B31,'[1]Рассчет акции'!$A:$A,'[1]Рассчет акции'!$R:$R,0) -> 0 | CG31: =_xlfn.XLOOKUP(B31,'[1]Рассчет акции'!$A:$A,'[1]Рассчет акции'!$M:$M,0) -> 626 | CH31: =IFERROR($CJ31/$CG31,0) -> 0 | CI31: =IF(BC31>0,CG31-BV31,0) -> #REF! | CJ31: =IF(CI31>0,$CI31-$CG31*7%,0) -> #REF! | CK31: =$CJ31/$H31*100% -> #REF! | CL31: =_xlfn.XLOOKUP(B31,'[1]Рассчет акции'!$A:$A,'[1]Рассчет акции'!$W:$W,0) -> 8 | CM31: =_xlfn.XLOOKUP(B31,'[1]Рассчет акции'!$A:$A,'[1]Рассчет акции'!$X:$X,0) -> 999 | CN31: =BC31/H31 -> #REF! | CO31: =CA31-10%*CA31 -> 566.1 | CP31: =_xlfn.XLOOKUP(B31,'[1]Рассчет акции'!$A:$A,'[1]Рассчет акции'!$Z:$Z,0) -> 0
A32: 419141548 | B32: 2415742942 | C32: ACRB1MS107RJ | D32: Мяч с шипами оранжевый 7 см | E32: 2044025288003 | F32: =SUM(H32:J32) -> 72.478676 | G32: =IFERROR(F32/S32*100%,0) -> 0.12226497 | H32: =IF(_xlfn.XLOOKUP($C32,'Юнит Карго'!$A:$A,'Юнит Карго'!$G:$G)=0,_xlfn.XLOOKUP(E32,'Себес 1С текущ'!G:G,'Себес 1С текущ'!H:H),_xlfn.XLOOKUP($C32,'Юнит Карго'!$A:$A,'Юнит Карго'!$P:$P,0,0)) -> 50.478676 | I32: =_xlfn.XLOOKUP(E32,[3]ТЗ_ФФ!$D:$D,[3]ТЗ_ФФ!$BG:$BG,0) -> 14 | J32: =$J$3 -> 8 | K32: =(L32*M32*N32)/1000 -> 0.512 | L32: 8 | M32: 8 | N32: 8 | O32: =_xlfn.XLOOKUP($C32,'Юнит Карго'!$A:$A,'Юнит Карго'!$T:$T,0,0) -> 0.06 | P32: своя | S32: =T32-(T32*U32) -> 592.8 | T32: =_xlfn.XLOOKUP(E32,'[2]Рассчет акции'!$D:$D,'[2]Рассчет акции'!$G:$G,0) -> 988 | U32: =_xlfn.XLOOKUP(E32,'[2]Рассчет акции'!$D:$D,'[2]Рассчет акции'!$F:$F,0) -> 0.4 | V32: =AC32+AF32+AH32+AG32 -> 340.97984 | W32: =IFERROR(V32/S32,0) -> 0.57520216 | X32: =IF(K32>1,('Тарифы ВБ'!$B$9+(K32-1)*'Тарифы ВБ'!$B$10)*'Тарифы ВБ'!$B$15*'Тарифы ВБ'!$B$12+S32*'Тарифы ВБ'!$B$13,'Тарифы ВБ'!$B$8*'Тарифы ВБ'!$B$15*'Тарифы ВБ'!$B$12+S32*'Тарифы ВБ'!$B$13) -> 72.46384 | Y32: =IF(K32>1,'Тарифы ВБ'!$B$9+(K32-1)*'Тарифы ВБ'!$B$10,'Тарифы ВБ'!$B$8) -> 32 | Z32: =SUM(X32:Y32) -> 104.46384 | AA32: =IFERROR(Z32/S32,0) -> 0.17622105 | AB32: =IF(K32>1,'Тарифы ВБ'!$B$14*'Тарифы ВБ'!$B$16*'Тарифы ВБ'!$B$15+(K32-1)*'Тарифы ВБ'!$B$14,'Тарифы ВБ'!$B$14*'Тарифы ВБ'!B$16*'Тарифы ВБ'!$B$15) -> 32 | AC32: =+X32+AB32+Y32 -> 136.46384 | AD32: =AC32/S32*100% -> 0.23020216 | AE32: 0.315 | AF32: =S32*AE32 -> 186.732 | AG32: =1.1*S32*$AG$3 -> 0 | AH32: =S32*$AH$3 -> 17.784 | AI32: =F32+V32 -> 413.45852 | AJ32: =IFERROR(AL32/S32,0) -> 0.23253287 | AK32: =S32-AI32 -> 179.34148 | AL32: =AK32-S32*7% -> 137.84548 | AM32: =AL32/H32 -> 2.7307666 | AN32: 619 | AO32: =$AN32-$AI32 -> 205.54148 | AP32: =$AO32-$AN32*7% -> 162.21148 | AQ32: =$AP32/$H32*100% -> 3.2134655 | AR32: =$AP32/$AN32 -> 0.26205409 | AS32: =IFERROR(_xlfn.XLOOKUP(A32,'[2]Рассчет акции'!$A:$A,'[2]Рассчет акции'!$BH:$BH),0) -> * | AT32: =IFERROR(_xlfn.XLOOKUP($A32,'[2]Рассчет акции'!$A:$A,'[2]Рассчет акции'!$BC:$BC),0) -> 593 | AU32: =IFERROR($AW32/$AT32,0) -> 0.2327681 | AV32: =$AT32-$AI32 -> 179.54148 | AW32: =$AV32-$AT32*7% -> 138.03148 | AX32: =$AW32/$H32*100% -> 2.7344514 | AY32: =IFERROR(_xlfn.XLOOKUP(E32,'[2]Рассчет акции'!$D:$D,'[2]Рассчет акции'!$BM:$BM),0) -> 76 | AZ32: =IFERROR(_xlfn.XLOOKUP(E32,'[2]Рассчет акции'!$D:$D,'[2]Рассчет акции'!$BN:$BN),0) -> 258 | BA32: =S32/H32 -> 11.743573 | BC32: =_xlfn.XLOOKUP(B32,#REF!,#REF!,0) -> #REF! | BD32: =BC32/(100%-BE32) -> #REF! | BE32: =_xlfn.XLOOKUP($B32,'[1]Рассчет акции'!$A:$A,'[1]Рассчет акции'!$J:$J) -> 0.34980392 | BF32: =BS32+BI32+BJ32+BU32+BK32 -> #REF! | BG32: =IFERROR(BF32/BC32,0) -> 0 | BH32: 0.37 | BI32: =BC32*BH32 -> #REF! | BJ32: =BC32*$BJ$3 -> #REF! | BK32: =K32*$BK$3*30 -> 0 | BL32: =(IF(K32>$BL$3,('Тарифы ОЗОН'!$G$3+ROUNDUP(K32-$BL$3,0)*'Тарифы ОЗОН'!$G$4),'Тарифы ОЗОН'!$G$3)) -> 46.77 | BM32: =$BN$3 -> 35 | BN32: =_xlfn.XLOOKUP(BM32,'Тарифы ОЗОН'!$A:$A,'Тарифы ОЗОН'!$B:$B) -> 1.32 | BO32: =_xlfn.XLOOKUP(BM32,'Тарифы ОЗОН'!$A:$A,'Тарифы ОЗОН'!C:C) -> 0.016 | BP32: =$BP$3 -> 25 | BQ32: =BL32*BN32+BC32*BO32+BP32 -> #REF! | BR32: =$BR$3 -> 0.85 | BS32: =(100%/BR32)*BQ32+(100%/BR32-1)*BL32 -> #REF! | BT32: =IFERROR(BS32/BC32*100%,0) -> 0 | BU32: =BC32*$BU$3 -> #REF! | BV32: =BF32+F32 -> #REF! | BW32: =IFERROR(BY32/BC32,0) -> 0 | BX32: =IFERROR(BC32-BV32,0) -> 0 | BY32: =BX32-BC32*7% -> #REF! | BZ32: =IFERROR(BY32/H32*100%,0) -> 0 | CA32: 629 | CB32: =IF(BC32=0,0,CA32-BV32) -> #REF! | CC32: =IF(CB32=0,0,CB32-CA32*7%) -> #REF! | CD32: =CC32/H32*100% -> #REF! | CE32: =IFERROR(CC32/CA32,0) -> 0 | CF32: =_xlfn.XLOOKUP(B32,'[1]Рассчет акции'!$A:$A,'[1]Рассчет акции'!$R:$R,0) -> 0 | CG32: =_xlfn.XLOOKUP(B32,'[1]Рассчет акции'!$A:$A,'[1]Рассчет акции'!$M:$M,0) -> 626 | CH32: =IFERROR($CJ32/$CG32,0) -> 0 | CI32: =IF(BC32>0,CG32-BV32,0) -> #REF! | CJ32: =IF(CI32>0,$CI32-$CG32*7%,0) -> #REF! | CK32: =$CJ32/$H32*100% -> #REF! | CL32: =_xlfn.XLOOKUP(B32,'[1]Рассчет акции'!$A:$A,'[1]Рассчет акции'!$W:$W,0) -> 5 | CM32: =_xlfn.XLOOKUP(B32,'[1]Рассчет акции'!$A:$A,'[1]Рассчет акции'!$X:$X,0) -> 999 | CN32: =BC32/H32 -> #REF! | CO32: =CA32-10%*CA32 -> 566.1 | CP32: =_xlfn.XLOOKUP(B32,'[1]Рассчет акции'!$A:$A,'[1]Рассчет акции'!$Z:$Z,0) -> 0
A33: 419145985 | B33: 2415742795 | C33: ACRB1MS107BС | D33: Мяч с шипами черный 7 см | E33: 2044025344532 | F33: =SUM(H33:J33) -> 72.478676 | G33: =IFERROR(F33/S33*100%,0) -> 0.13130195 | H33: =IF(_xlfn.XLOOKUP($C33,'Юнит Карго'!$A:$A,'Юнит Карго'!$G:$G)=0,_xlfn.XLOOKUP(E33,'Себес 1С текущ'!G:G,'Себес 1С текущ'!H:H),_xlfn.XLOOKUP($C33,'Юнит Карго'!$A:$A,'Юнит Карго'!$P:$P,0,0)) -> 50.478676 | I33: =_xlfn.XLOOKUP(E33,[3]ТЗ_ФФ!$D:$D,[3]ТЗ_ФФ!$BG:$BG,0) -> 14 | J33: =$J$3 -> 8 | K33: =(L33*M33*N33)/1000 -> 0.512 | L33: 8 | M33: 8 | N33: 8 | O33: =_xlfn.XLOOKUP($C33,'Юнит Карго'!$A:$A,'Юнит Карго'!$T:$T,0,0) -> 0.06 | P33: своя | S33: =T33-(T33*U33) -> 552 | T33: =_xlfn.XLOOKUP(E33,'[2]Рассчет акции'!$D:$D,'[2]Рассчет акции'!$G:$G,0) -> 920 | U33: =_xlfn.XLOOKUP(E33,'[2]Рассчет акции'!$D:$D,'[2]Рассчет акции'!$F:$F,0) -> 0.4 | V33: =AC33+AF33+AH33+AG33 -> 326.5856 | W33: =IFERROR(V33/S33,0) -> 0.59164058 | X33: =IF(K33>1,('Тарифы ВБ'!$B$9+(K33-1)*'Тарифы ВБ'!$B$10)*'Тарифы ВБ'!$B$15*'Тарифы ВБ'!$B$12+S33*'Тарифы ВБ'!$B$13,'Тарифы ВБ'!$B$8*'Тарифы ВБ'!$B$15*'Тарифы ВБ'!$B$12+S33*'Тарифы ВБ'!$B$13) -> 72.1456 | Y33: =IF(K33>1,'Тарифы ВБ'!$B$9+(K33-1)*'Тарифы ВБ'!$B$10,'Тарифы ВБ'!$B$8) -> 32 | Z33: =SUM(X33:Y33) -> 104.1456 | AA33: =IFERROR(Z33/S33,0) -> 0.18866957 | AB33: =IF(K33>1,'Тарифы ВБ'!$B$14*'Тарифы ВБ'!$B$16*'Тарифы ВБ'!$B$15+(K33-1)*'Тарифы ВБ'!$B$14,'Тарифы ВБ'!$B$14*'Тарифы ВБ'!B$16*'Тарифы ВБ'!$B$15) -> 32 | AC33: =+X33+AB33+Y33 -> 136.1456 | AD33: =AC33/S33*100% -> 0.24664058 | AE33: 0.315 | AF33: =S33*AE33 -> 173.88 | AG33: =1.1*S33*$AG$3 -> 0 | AH33: =S33*$AH$3 -> 16.56 | AI33: =F33+V33 -> 399.06428 | AJ33: =IFERROR(AL33/S33,0) -> 0.20705747 | AK33: =S33-AI33 -> 152.93572 | AL33: =AK33-S33*7% -> 114.29572 | AM33: =AL33/H33 -> 2.2642378 | AN33: 619 | AO33: =$AN33-$AI33 -> 219.93572 | AP33: =$AO33-$AN33*7% -> 176.60572 | AQ33: =$AP33/$H33*100% -> 3.4986204 | AR33: =$AP33/$AN33 -> 0.28530812 | AS33: =IFERROR(_xlfn.XLOOKUP(A33,'[2]Рассчет акции'!$A:$A,'[2]Рассчет акции'!$BH:$BH),0) -> * | AT33: =IFERROR(_xlfn.XLOOKUP($A33,'[2]Рассчет акции'!$A:$A,'[2]Рассчет акции'!$BC:$BC),0) -> 552 | AU33: =IFERROR($AW33/$AT33,0) -> 0.20705747 | AV33: =$AT33-$AI33 -> 152.93572 | AW33: =$AV33-$AT33*7% -> 114.29572 | AX33: =$AW33/$H33*100% -> 2.2642378 | AY33: =IFERROR(_xlfn.XLOOKUP(E33,'[2]Рассчет акции'!$D:$D,'[2]Рассчет акции'!$BM:$BM),0) -> 90 | AZ33: =IFERROR(_xlfn.XLOOKUP(E33,'[2]Рассчет акции'!$D:$D,'[2]Рассчет акции'!$BN:$BN),0) -> 999 | BA33: =S33/H33 -> 10.935311 | BC33: =_xlfn.XLOOKUP(B33,#REF!,#REF!,0) -> #REF! | BD33: =BC33/(100%-BE33) -> #REF! | BE33: =_xlfn.XLOOKUP($B33,'[1]Рассчет акции'!$A:$A,'[1]Рассчет акции'!$J:$J) -> 0.34980392 | BF33: =BS33+BI33+BJ33+BU33+BK33 -> #REF! | BG33: =IFERROR(BF33/BC33,0) -> 0 | BH33: 0.37 | BI33: =BC33*BH33 -> #REF! | BJ33: =BC33*$BJ$3 -> #REF! | BK33: =K33*$BK$3*30 -> 0 | BL33: =(IF(K33>$BL$3,('Тарифы ОЗОН'!$G$3+ROUNDUP(K33-$BL$3,0)*'Тарифы ОЗОН'!$G$4),'Тарифы ОЗОН'!$G$3)) -> 46.77 | BM33: =$BN$3 -> 35 | BN33: =_xlfn.XLOOKUP(BM33,'Тарифы ОЗОН'!$A:$A,'Тарифы ОЗОН'!$B:$B) -> 1.32 | BO33: =_xlfn.XLOOKUP(BM33,'Тарифы ОЗОН'!$A:$A,'Тарифы ОЗОН'!C:C) -> 0.016 | BP33: =$BP$3 -> 25 | BQ33: =BL33*BN33+BC33*BO33+BP33 -> #REF! | BR33: =$BR$3 -> 0.85 | BS33: =(100%/BR33)*BQ33+(100%/BR33-1)*BL33 -> #REF! | BT33: =IFERROR(BS33/BC33*100%,0) -> 0 | BU33: =BC33*$BU$3 -> #REF! | BV33: =BF33+F33 -> #REF! | BW33: =IFERROR(BY33/BC33,0) -> 0 | BX33: =IFERROR(BC33-BV33,0) -> 0 | BY33: =BX33-BC33*7% -> #REF! | BZ33: =IFERROR(BY33/H33*100%,0) -> 0 | CA33: 629 | CB33: =IF(BC33=0,0,CA33-BV33) -> #REF! | CC33: =IF(CB33=0,0,CB33-CA33*7%) -> #REF! | CD33: =CC33/H33*100% -> #REF! | CE33: =IFERROR(CC33/CA33,0) -> 0 | CF33: =_xlfn.XLOOKUP(B33,'[1]Рассчет акции'!$A:$A,'[1]Рассчет акции'!$R:$R,0) -> 0 | CG33: =_xlfn.XLOOKUP(B33,'[1]Рассчет акции'!$A:$A,'[1]Рассчет акции'!$M:$M,0) -> 626 | CH33: =IFERROR($CJ33/$CG33,0) -> 0 | CI33: =IF(BC33>0,CG33-BV33,0) -> #REF! | CJ33: =IF(CI33>0,$CI33-$CG33*7%,0) -> #REF! | CK33: =$CJ33/$H33*100% -> #REF! | CL33: =_xlfn.XLOOKUP(B33,'[1]Рассчет акции'!$A:$A,'[1]Рассчет акции'!$W:$W,0) -> 8 | CM33: =_xlfn.XLOOKUP(B33,'[1]Рассчет акции'!$A:$A,'[1]Рассчет акции'!$X:$X,0) -> 999 | CN33: =BC33/H33 -> #REF! | CO33: =CA33-10%*CA33 -> 566.1 | CP33: =_xlfn.XLOOKUP(B33,'[1]Рассчет акции'!$A:$A,'[1]Рассчет акции'!$Z:$Z,0) -> 0
A34: 419145390 | B34: 2415742470 | C34: ACRB1MS109PN | D34: Мяч с шипами розовый 9 см | E34: 2044025321588 | F34: =SUM(H34:J34) -> 101.29113 | G34: =IFERROR(F34/S34*100%,0) -> 0.14284463 | H34: =IF(_xlfn.XLOOKUP($C34,'Юнит Карго'!$A:$A,'Юнит Карго'!$G:$G)=0,_xlfn.XLOOKUP(E34,'Себес 1С текущ'!G:G,'Себес 1С текущ'!H:H),_xlfn.XLOOKUP($C34,'Юнит Карго'!$A:$A,'Юнит Карго'!$P:$P,0,0)) -> 79.291127 | I34: =_xlfn.XLOOKUP(E34,[3]ТЗ_ФФ!$D:$D,[3]ТЗ_ФФ!$BG:$BG,0) -> 14 | J34: =$J$3 -> 8 | K34: =(L34*M34*N34)/1000 -> 0.729 | L34: 9 | M34: 9 | N34: 9 | O34: =_xlfn.XLOOKUP($C34,'Юнит Карго'!$A:$A,'Юнит Карго'!$T:$T,0,0) -> 0.1 | P34: своя | S34: =T34-(T34*U34) -> 709.1 | T34: =_xlfn.XLOOKUP(E34,'[2]Рассчет акции'!$D:$D,'[2]Рассчет акции'!$G:$G,0) -> 1013 | U34: =_xlfn.XLOOKUP(E34,'[2]Рассчет акции'!$D:$D,'[2]Рассчет акции'!$F:$F,0) -> 0.3 | V34: =AC34+AF34+AH34+AG34 -> 382.01048 | W34: =IFERROR(V34/S34,0) -> 0.53872582 | X34: =IF(K34>1,('Тарифы ВБ'!$B$9+(K34-1)*'Тарифы ВБ'!$B$10)*'Тарифы ВБ'!$B$15*'Тарифы ВБ'!$B$12+S34*'Тарифы ВБ'!$B$13,'Тарифы ВБ'!$B$8*'Тарифы ВБ'!$B$15*'Тарифы ВБ'!$B$12+S34*'Тарифы ВБ'!$B$13) -> 73.37098 | Y34: =IF(K34>1,'Тарифы ВБ'!$B$9+(K34-1)*'Тарифы ВБ'!$B$10,'Тарифы ВБ'!$B$8) -> 32 | Z34: =SUM(X34:Y34) -> 105.37098 | AA34: =IFERROR(Z34/S34,0) -> 0.14859819 | AB34: =IF(K34>1,'Тарифы ВБ'!$B$14*'Тарифы ВБ'!$B$16*'Тарифы ВБ'!$B$15+(K34-1)*'Тарифы ВБ'!$B$14,'Тарифы ВБ'!$B$14*'Тарифы ВБ'!B$16*'Тарифы ВБ'!$B$15) -> 32 | AC34: =+X34+AB34+Y34 -> 137.37098 | AD34: =AC34/S34*100% -> 0.19372582 | AE34: 0.315 | AF34: =S34*AE34 -> 223.3665 | AG34: =1.1*S34*$AG$3 -> 0 | AH34: =S34*$AH$3 -> 21.273 | AI34: =F34+V34 -> 483.30161 | AJ34: =IFERROR(AL34/S34,0) -> 0.24842955 | AK34: =S34-AI34 -> 225.79839 | AL34: =AK34-S34*7% -> 176.16139 | AM34: =AL34/H34 -> 2.2217037 | AN34: 709 | AO34: =$AN34-$AI34 -> 225.69839 | AP34: =$AO34-$AN34*7% -> 176.06839 | AQ34: =$AP34/$H34*100% -> 2.2205309 | AR34: =$AP34/$AN34 -> 0.24833342 | AS34: =IFERROR(_xlfn.XLOOKUP(A34,'[2]Рассчет акции'!$A:$A,'[2]Рассчет акции'!$BH:$BH),0) -> 0 | AT34: =IFERROR(_xlfn.XLOOKUP($A34,'[2]Рассчет акции'!$A:$A,'[2]Рассчет акции'!$BC:$BC),0) -> 0 | AU34: =IFERROR($AW34/$AT34,0) -> 0 | AV34: =$AT34-$AI34 -> -483.30161 | AW34: =$AV34-$AT34*7% -> -483.30161 | AX34: =$AW34/$H34*100% -> -6.0952798 | AY34: =IFERROR(_xlfn.XLOOKUP(E34,'[2]Рассчет акции'!$D:$D,'[2]Рассчет акции'!$BM:$BM),0) -> 152 | AZ34: =IFERROR(_xlfn.XLOOKUP(E34,'[2]Рассчет акции'!$D:$D,'[2]Рассчет акции'!$BN:$BN),0) -> 999 | BA34: =S34/H34 -> 8.9429931 | BC34: =_xlfn.XLOOKUP(B34,#REF!,#REF!,0) -> #REF! | BD34: =BC34/(100%-BE34) -> #REF! | BE34: =_xlfn.XLOOKUP($B34,'[1]Рассчет акции'!$A:$A,'[1]Рассчет акции'!$J:$J) -> 0.34983051 | BF34: =BS34+BI34+BJ34+BU34+BK34 -> #REF! | BG34: =IFERROR(BF34/BC34,0) -> 0 | BH34: 0.37 | BI34: =BC34*BH34 -> #REF! | BJ34: =BC34*$BJ$3 -> #REF! | BK34: =K34*$BK$3*30 -> 0 | BL34: =(IF(K34>$BL$3,('Тарифы ОЗОН'!$G$3+ROUNDUP(K34-$BL$3,0)*'Тарифы ОЗОН'!$G$4),'Тарифы ОЗОН'!$G$3)) -> 46.77 | BM34: =$BN$3 -> 35 | BN34: =_xlfn.XLOOKUP(BM34,'Тарифы ОЗОН'!$A:$A,'Тарифы ОЗОН'!$B:$B) -> 1.32 | BO34: =_xlfn.XLOOKUP(BM34,'Тарифы ОЗОН'!$A:$A,'Тарифы ОЗОН'!C:C) -> 0.016 | BP34: =$BP$3 -> 25 | BQ34: =BL34*BN34+BC34*BO34+BP34 -> #REF! | BR34: =$BR$3 -> 0.85 | BS34: =(100%/BR34)*BQ34+(100%/BR34-1)*BL34 -> #REF! | BT34: =IFERROR(BS34/BC34*100%,0) -> 0 | BU34: =BC34*$BU$3 -> #REF! | BV34: =BF34+F34 -> #REF! | BW34: =IFERROR(BY34/BC34,0) -> 0 | BX34: =IFERROR(BC34-BV34,0) -> 0 | BY34: =BX34-BC34*7% -> #REF! | BZ34: =IFERROR(BY34/H34*100%,0) -> 0 | CA34: 759 | CB34: =IF(BC34=0,0,CA34-BV34) -> #REF! | CC34: =IF(CB34=0,0,CB34-CA34*7%) -> #REF! | CD34: =CC34/H34*100% -> #REF! | CE34: =IFERROR(CC34/CA34,0) -> 0 | CF34: =_xlfn.XLOOKUP(B34,'[1]Рассчет акции'!$A:$A,'[1]Рассчет акции'!$R:$R,0) -> 0 | CG34: =_xlfn.XLOOKUP(B34,'[1]Рассчет акции'!$A:$A,'[1]Рассчет акции'!$M:$M,0) -> 701 | CH34: =IFERROR($CJ34/$CG34,0) -> 0 | CI34: =IF(BC34>0,CG34-BV34,0) -> #REF! | CJ34: =IF(CI34>0,$CI34-$CG34*7%,0) -> #REF! | CK34: =$CJ34/$H34*100% -> #REF! | CL34: =_xlfn.XLOOKUP(B34,'[1]Рассчет акции'!$A:$A,'[1]Рассчет акции'!$W:$W,0) -> 17 | CM34: =_xlfn.XLOOKUP(B34,'[1]Рассчет акции'!$A:$A,'[1]Рассчет акции'!$X:$X,0) -> 999 | CN34: =BC34/H34 -> #REF! | CO34: =CA34-10%*CA34 -> 683.1 | CP34: =_xlfn.XLOOKUP(B34,'[1]Рассчет акции'!$A:$A,'[1]Рассчет акции'!$Z:$Z,0) -> 0
A35: 419145749 | B35: 2415742615 | C35: ACRB1MS109BL | D35: Мяч с шипами голубой 9 см | E35: 2044025342057 | F35: =SUM(H35:J35) -> 101.29113 | G35: =IFERROR(F35/S35*100%,0) -> 0.2016948 | H35: =IF(_xlfn.XLOOKUP($C35,'Юнит Карго'!$A:$A,'Юнит Карго'!$G:$G)=0,_xlfn.XLOOKUP(E35,'Себес 1С текущ'!G:G,'Себес 1С текущ'!H:H),_xlfn.XLOOKUP($C35,'Юнит Карго'!$A:$A,'Юнит Карго'!$P:$P,0,0)) -> 79.291127 | I35: =_xlfn.XLOOKUP(E35,[3]ТЗ_ФФ!$D:$D,[3]ТЗ_ФФ!$BG:$BG,0) -> 14 | J35: =$J$3 -> 8 | K35: =(L35*M35*N35)/1000 -> 0.729 | L35: 9 | M35: 9 | N35: 9 | O35: =_xlfn.XLOOKUP($C35,'Юнит Карго'!$A:$A,'Юнит Карго'!$T:$T,0,0) -> 0.1 | P35: своя | S35: =T35-(T35*U35) -> 502.2 | T35: =_xlfn.XLOOKUP(E35,'[2]Рассчет акции'!$D:$D,'[2]Рассчет акции'!$G:$G,0) -> 837 | U35: =_xlfn.XLOOKUP(E35,'[2]Рассчет акции'!$D:$D,'[2]Рассчет акции'!$F:$F,0) -> 0.4 | V35: =AC35+AF35+AH35+AG35 -> 309.01616 | W35: =IFERROR(V35/S35,0) -> 0.61532489 | X35: =IF(K35>1,('Тарифы ВБ'!$B$9+(K35-1)*'Тарифы ВБ'!$B$10)*'Тарифы ВБ'!$B$15*'Тарифы ВБ'!$B$12+S35*'Тарифы ВБ'!$B$13,'Тарифы ВБ'!$B$8*'Тарифы ВБ'!$B$15*'Тарифы ВБ'!$B$12+S35*'Тарифы ВБ'!$B$13) -> 71.75716 | Y35: =IF(K35>1,'Тарифы ВБ'!$B$9+(K35-1)*'Тарифы ВБ'!$B$10,'Тарифы ВБ'!$B$8) -> 32 | Z35: =SUM(X35:Y35) -> 103.75716 | AA35: =IFERROR(Z35/S35,0) -> 0.20660526 | AB35: =IF(K35>1,'Тарифы ВБ'!$B$14*'Тарифы ВБ'!$B$16*'Тарифы ВБ'!$B$15+(K35-1)*'Тарифы ВБ'!$B$14,'Тарифы ВБ'!$B$14*'Тарифы ВБ'!B$16*'Тарифы ВБ'!$B$15) -> 32 | AC35: =+X35+AB35+Y35 -> 135.75716 | AD35: =AC35/S35*100% -> 0.27032489 | AE35: 0.315 | AF35: =S35*AE35 -> 158.193 | AG35: =1.1*S35*$AG$3 -> 0 | AH35: =S35*$AH$3 -> 15.066 | AI35: =F35+V35 -> 410.30729 | AJ35: =IFERROR(AL35/S35,0) -> 0.11298031 | AK35: =S35-AI35 -> 91.892713 | AL35: =AK35-S35*7% -> 56.738713 | AM35: =AL35/H35 -> 0.71557456 | AN35: 709 | AO35: =$AN35-$AI35 -> 298.69271 | AP35: =$AO35-$AN35*7% -> 249.06271 | AQ35: =$AP35/$H35*100% -> 3.1411171 | AR35: =$AP35/$AN35 -> 0.35128732 | AS35: =IFERROR(_xlfn.XLOOKUP(A35,'[2]Рассчет акции'!$A:$A,'[2]Рассчет акции'!$BH:$BH),0) -> * | AT35: =IFERROR(_xlfn.XLOOKUP($A35,'[2]Рассчет акции'!$A:$A,'[2]Рассчет акции'!$BC:$BC),0) -> 502 | AU35: =IFERROR($AW35/$AT35,0) -> 0.11265481 | AV35: =$AT35-$AI35 -> 91.692713 | AW35: =$AV35-$AT35*7% -> 56.552713 | AX35: =$AW35/$H35*100% -> 0.71322877 | AY35: =IFERROR(_xlfn.XLOOKUP(E35,'[2]Рассчет акции'!$D:$D,'[2]Рассчет акции'!$BM:$BM),0) -> 106 | AZ35: =IFERROR(_xlfn.XLOOKUP(E35,'[2]Рассчет акции'!$D:$D,'[2]Рассчет акции'!$BN:$BN),0) -> 816 | BA35: =S35/H35 -> 6.3336217 | BC35: =_xlfn.XLOOKUP(B35,#REF!,#REF!,0) -> #REF! | BD35: =BC35/(100%-BE35) -> #REF! | BE35: =_xlfn.XLOOKUP($B35,'[1]Рассчет акции'!$A:$A,'[1]Рассчет акции'!$J:$J) -> 0.34983051 | BF35: =BS35+BI35+BJ35+BU35+BK35 -> #REF! | BG35: =IFERROR(BF35/BC35,0) -> 0 | BH35: 0.37 | BI35: =BC35*BH35 -> #REF! | BJ35: =BC35*$BJ$3 -> #REF! | BK35: =K35*$BK$3*30 -> 0 | BL35: =(IF(K35>$BL$3,('Тарифы ОЗОН'!$G$3+ROUNDUP(K35-$BL$3,0)*'Тарифы ОЗОН'!$G$4),'Тарифы ОЗОН'!$G$3)) -> 46.77 | BM35: =$BN$3 -> 35 | BN35: =_xlfn.XLOOKUP(BM35,'Тарифы ОЗОН'!$A:$A,'Тарифы ОЗОН'!$B:$B) -> 1.32 | BO35: =_xlfn.XLOOKUP(BM35,'Тарифы ОЗОН'!$A:$A,'Тарифы ОЗОН'!C:C) -> 0.016 | BP35: =$BP$3 -> 25 | BQ35: =BL35*BN35+BC35*BO35+BP35 -> #REF! | BR35: =$BR$3 -> 0.85 | BS35: =(100%/BR35)*BQ35+(100%/BR35-1)*BL35 -> #REF! | BT35: =IFERROR(BS35/BC35*100%,0) -> 0 | BU35: =BC35*$BU$3 -> #REF! | BV35: =BF35+F35 -> #REF! | BW35: =IFERROR(BY35/BC35,0) -> 0 | BX35: =IFERROR(BC35-BV35,0) -> 0 | BY35: =BX35-BC35*7% -> #REF! | BZ35: =IFERROR(BY35/H35*100%,0) -> 0 | CA35: 759 | CB35: =IF(BC35=0,0,CA35-BV35) -> #REF! | CC35: =IF(CB35=0,0,CB35-CA35*7%) -> #REF! | CD35: =CC35/H35*100% -> #REF! | CE35: =IFERROR(CC35/CA35,0) -> 0 | CF35: =_xlfn.XLOOKUP(B35,'[1]Рассчет акции'!$A:$A,'[1]Рассчет акции'!$R:$R,0) -> 0 | CG35: =_xlfn.XLOOKUP(B35,'[1]Рассчет акции'!$A:$A,'[1]Рассчет акции'!$M:$M,0) -> 701 | CH35: =IFERROR($CJ35/$CG35,0) -> 0 | CI35: =IF(BC35>0,CG35-BV35,0) -> #REF! | CJ35: =IF(CI35>0,$CI35-$CG35*7%,0) -> #REF! | CK35: =$CJ35/$H35*100% -> #REF! | CL35: =_xlfn.XLOOKUP(B35,'[1]Рассчет акции'!$A:$A,'[1]Рассчет акции'!$W:$W,0) -> 20 | CM35: =_xlfn.XLOOKUP(B35,'[1]Рассчет акции'!$A:$A,'[1]Рассчет акции'!$X:$X,0) -> 140 | CN35: =BC35/H35 -> #REF! | CO35: =CA35-10%*CA35 -> 683.1 | CP35: =_xlfn.XLOOKUP(B35,'[1]Рассчет акции'!$A:$A,'[1]Рассчет акции'!$Z:$Z,0) -> 0
A36: 419141549 | B36: 2415742943 | C36: ACRB1MS109RJ | D36: Мяч с шипами оранжевый 9 см | E36: 2044025291485 | F36: =SUM(H36:J36) -> 101.29113 | G36: =IFERROR(F36/S36*100%,0) -> 0.14284463 | H36: =IF(_xlfn.XLOOKUP($C36,'Юнит Карго'!$A:$A,'Юнит Карго'!$G:$G)=0,_xlfn.XLOOKUP(E36,'Себес 1С текущ'!G:G,'Себес 1С текущ'!H:H),_xlfn.XLOOKUP($C36,'Юнит Карго'!$A:$A,'Юнит Карго'!$P:$P,0,0)) -> 79.291127 | I36: =_xlfn.XLOOKUP(E36,[3]ТЗ_ФФ!$D:$D,[3]ТЗ_ФФ!$BG:$BG,0) -> 14 | J36: =$J$3 -> 8 | K36: =(L36*M36*N36)/1000 -> 0.729 | L36: 9 | M36: 9 | N36: 9 | O36: =_xlfn.XLOOKUP($C36,'Юнит Карго'!$A:$A,'Юнит Карго'!$T:$T,0,0) -> 0.1 | P36: своя | S36: =T36-(T36*U36) -> 709.1 | T36: =_xlfn.XLOOKUP(E36,'[2]Рассчет акции'!$D:$D,'[2]Рассчет акции'!$G:$G,0) -> 1013 | U36: =_xlfn.XLOOKUP(E36,'[2]Рассчет акции'!$D:$D,'[2]Рассчет акции'!$F:$F,0) -> 0.3 | V36: =AC36+AF36+AH36+AG36 -> 382.01048 | W36: =IFERROR(V36/S36,0) -> 0.53872582 | X36: =IF(K36>1,('Тарифы ВБ'!$B$9+(K36-1)*'Тарифы ВБ'!$B$10)*'Тарифы ВБ'!$B$15*'Тарифы ВБ'!$B$12+S36*'Тарифы ВБ'!$B$13,'Тарифы ВБ'!$B$8*'Тарифы ВБ'!$B$15*'Тарифы ВБ'!$B$12+S36*'Тарифы ВБ'!$B$13) -> 73.37098 | Y36: =IF(K36>1,'Тарифы ВБ'!$B$9+(K36-1)*'Тарифы ВБ'!$B$10,'Тарифы ВБ'!$B$8) -> 32 | Z36: =SUM(X36:Y36) -> 105.37098 | AA36: =IFERROR(Z36/S36,0) -> 0.14859819 | AB36: =IF(K36>1,'Тарифы ВБ'!$B$14*'Тарифы ВБ'!$B$16*'Тарифы ВБ'!$B$15+(K36-1)*'Тарифы ВБ'!$B$14,'Тарифы ВБ'!$B$14*'Тарифы ВБ'!B$16*'Тарифы ВБ'!$B$15) -> 32 | AC36: =+X36+AB36+Y36 -> 137.37098 | AD36: =AC36/S36*100% -> 0.19372582 | AE36: 0.315 | AF36: =S36*AE36 -> 223.3665 | AG36: =1.1*S36*$AG$3 -> 0 | AH36: =S36*$AH$3 -> 21.273 | AI36: =F36+V36 -> 483.30161 | AJ36: =IFERROR(AL36/S36,0) -> 0.24842955 | AK36: =S36-AI36 -> 225.79839 | AL36: =AK36-S36*7% -> 176.16139 | AM36: =AL36/H36 -> 2.2217037 | AN36: 709 | AO36: =$AN36-$AI36 -> 225.69839 | AP36: =$AO36-$AN36*7% -> 176.06839 | AQ36: =$AP36/$H36*100% -> 2.2205309 | AR36: =$AP36/$AN36 -> 0.24833342 | AS36: =IFERROR(_xlfn.XLOOKUP(A36,'[2]Рассчет акции'!$A:$A,'[2]Рассчет акции'!$BH:$BH),0) -> 0 | AT36: =IFERROR(_xlfn.XLOOKUP($A36,'[2]Рассчет акции'!$A:$A,'[2]Рассчет акции'!$BC:$BC),0) -> 0 | AU36: =IFERROR($AW36/$AT36,0) -> 0 | AV36: =$AT36-$AI36 -> -483.30161 | AW36: =$AV36-$AT36*7% -> -483.30161 | AX36: =$AW36/$H36*100% -> -6.0952798 | AY36: =IFERROR(_xlfn.XLOOKUP(E36,'[2]Рассчет акции'!$D:$D,'[2]Рассчет акции'!$BM:$BM),0) -> 98 | AZ36: =IFERROR(_xlfn.XLOOKUP(E36,'[2]Рассчет акции'!$D:$D,'[2]Рассчет акции'!$BN:$BN),0) -> 339 | BA36: =S36/H36 -> 8.9429931 | BC36: =_xlfn.XLOOKUP(B36,#REF!,#REF!,0) -> #REF! | BD36: =BC36/(100%-BE36) -> #REF! | BE36: =_xlfn.XLOOKUP($B36,'[1]Рассчет акции'!$A:$A,'[1]Рассчет акции'!$J:$J) -> 0.34983051 | BF36: =BS36+BI36+BJ36+BU36+BK36 -> #REF! | BG36: =IFERROR(BF36/BC36,0) -> 0 | BH36: 0.37 | BI36: =BC36*BH36 -> #REF! | BJ36: =BC36*$BJ$3 -> #REF! | BK36: =K36*$BK$3*30 -> 0 | BL36: =(IF(K36>$BL$3,('Тарифы ОЗОН'!$G$3+ROUNDUP(K36-$BL$3,0)*'Тарифы ОЗОН'!$G$4),'Тарифы ОЗОН'!$G$3)) -> 46.77 | BM36: =$BN$3 -> 35 | BN36: =_xlfn.XLOOKUP(BM36,'Тарифы ОЗОН'!$A:$A,'Тарифы ОЗОН'!$B:$B) -> 1.32 | BO36: =_xlfn.XLOOKUP(BM36,'Тарифы ОЗОН'!$A:$A,'Тарифы ОЗОН'!C:C) -> 0.016 | BP36: =$BP$3 -> 25 | BQ36: =BL36*BN36+BC36*BO36+BP36 -> #REF! | BR36: =$BR$3 -> 0.85 | BS36: =(100%/BR36)*BQ36+(100%/BR36-1)*BL36 -> #REF! | BT36: =IFERROR(BS36/BC36*100%,0) -> 0 | BU36: =BC36*$BU$3 -> #REF! | BV36: =BF36+F36 -> #REF! | BW36: =IFERROR(BY36/BC36,0) -> 0 | BX36: =IFERROR(BC36-BV36,0) -> 0 | BY36: =BX36-BC36*7% -> #REF! | BZ36: =IFERROR(BY36/H36*100%,0) -> 0 | CA36: 759 | CB36: =IF(BC36=0,0,CA36-BV36) -> #REF! | CC36: =IF(CB36=0,0,CB36-CA36*7%) -> #REF! | CD36: =CC36/H36*100% -> #REF! | CE36: =IFERROR(CC36/CA36,0) -> 0 | CF36: =_xlfn.XLOOKUP(B36,'[1]Рассчет акции'!$A:$A,'[1]Рассчет акции'!$R:$R,0) -> 0 | CG36: =_xlfn.XLOOKUP(B36,'[1]Рассчет акции'!$A:$A,'[1]Рассчет акции'!$M:$M,0) -> 701 | CH36: =IFERROR($CJ36/$CG36,0) -> 0 | CI36: =IF(BC36>0,CG36-BV36,0) -> #REF! | CJ36: =IF(CI36>0,$CI36-$CG36*7%,0) -> #REF! | CK36: =$CJ36/$H36*100% -> #REF! | CL36: =_xlfn.XLOOKUP(B36,'[1]Рассчет акции'!$A:$A,'[1]Рассчет акции'!$W:$W,0) -> 24 | CM36: =_xlfn.XLOOKUP(B36,'[1]Рассчет акции'!$A:$A,'[1]Рассчет акции'!$X:$X,0) -> 999 | CN36: =BC36/H36 -> #REF! | CO36: =CA36-10%*CA36 -> 683.1 | CP36: =_xlfn.XLOOKUP(B36,'[1]Рассчет акции'!$A:$A,'[1]Рассчет акции'!$Z:$Z,0) -> 0
A37: 419145986 | B37: 2415742693 | C37: ACRB1MS109BС | D37: Мяч с шипами черный 9 см | E37: 2044025347953 | F37: =SUM(H37:J37) -> 101.29113 | G37: =IFERROR(F37/S37*100%,0) -> 0.14873881 | H37: =IF(_xlfn.XLOOKUP($C37,'Юнит Карго'!$A:$A,'Юнит Карго'!$G:$G)=0,_xlfn.XLOOKUP(E37,'Себес 1С текущ'!G:G,'Себес 1С текущ'!H:H),_xlfn.XLOOKUP($C37,'Юнит Карго'!$A:$A,'Юнит Карго'!$P:$P,0,0)) -> 79.291127 | I37: =_xlfn.XLOOKUP(E37,[3]ТЗ_ФФ!$D:$D,[3]ТЗ_ФФ!$BG:$BG,0) -> 14 | J37: =$J$3 -> 8 | K37: =(L37*M37*N37)/1000 -> 0.729 | L37: 9 | M37: 9 | N37: 9 | O37: =_xlfn.XLOOKUP($C37,'Юнит Карго'!$A:$A,'Юнит Карго'!$T:$T,0,0) -> 0.1 | P37: своя | S37: =T37-(T37*U37) -> 681 | T37: =_xlfn.XLOOKUP(E37,'[2]Рассчет акции'!$D:$D,'[2]Рассчет акции'!$G:$G,0) -> 1135 | U37: =_xlfn.XLOOKUP(E37,'[2]Рассчет акции'!$D:$D,'[2]Рассчет акции'!$F:$F,0) -> 0.4 | V37: =AC37+AF37+AH37+AG37 -> 372.0968 | W37: =IFERROR(V37/S37,0) -> 0.54639765 | X37: =IF(K37>1,('Тарифы ВБ'!$B$9+(K37-1)*'Тарифы ВБ'!$B$10)*'Тарифы ВБ'!$B$15*'Тарифы ВБ'!$B$12+S37*'Тарифы ВБ'!$B$13,'Тарифы ВБ'!$B$8*'Тарифы ВБ'!$B$15*'Тарифы ВБ'!$B$12+S37*'Тарифы ВБ'!$B$13) -> 73.1518 | Y37: =IF(K37>1,'Тарифы ВБ'!$B$9+(K37-1)*'Тарифы ВБ'!$B$10,'Тарифы ВБ'!$B$8) -> 32 | Z37: =SUM(X37:Y37) -> 105.1518 | AA37: =IFERROR(Z37/S37,0) -> 0.15440793 | AB37: =IF(K37>1,'Тарифы ВБ'!$B$14*'Тарифы ВБ'!$B$16*'Тарифы ВБ'!$B$15+(K37-1)*'Тарифы ВБ'!$B$14,'Тарифы ВБ'!$B$14*'Тарифы ВБ'!B$16*'Тарифы ВБ'!$B$15) -> 32 | AC37: =+X37+AB37+Y37 -> 137.1518 | AD37: =AC37/S37*100% -> 0.20139765 | AE37: 0.315 | AF37: =S37*AE37 -> 214.515 | AG37: =1.1*S37*$AG$3 -> 0 | AH37: =S37*$AH$3 -> 20.43 | AI37: =F37+V37 -> 473.38793 | AJ37: =IFERROR(AL37/S37,0) -> 0.23486354 | AK37: =S37-AI37 -> 207.61207 | AL37: =AK37-S37*7% -> 159.94207 | AM37: =AL37/H37 -> 2.0171497 | AN37: 709 | AO37: =$AN37-$AI37 -> 235.61207 | AP37: =$AO37-$AN37*7% -> 185.98207 | AQ37: =$AP37/$H37*100% -> 2.3455597 | AR37: =$AP37/$AN37 -> 0.26231604 | AS37: =IFERROR(_xlfn.XLOOKUP(A37,'[2]Рассчет акции'!$A:$A,'[2]Рассчет акции'!$BH:$BH),0) -> * | AT37: =IFERROR(_xlfn.XLOOKUP($A37,'[2]Рассчет акции'!$A:$A,'[2]Рассчет акции'!$BC:$BC),0) -> 681 | AU37: =IFERROR($AW37/$AT37,0) -> 0.23486354 | AV37: =$AT37-$AI37 -> 207.61207 | AW37: =$AV37-$AT37*7% -> 159.94207 | AX37: =$AW37/$H37*100% -> 2.0171497 | AY37: =IFERROR(_xlfn.XLOOKUP(E37,'[2]Рассчет акции'!$D:$D,'[2]Рассчет акции'!$BM:$BM),0) -> 119 | AZ37: =IFERROR(_xlfn.XLOOKUP(E37,'[2]Рассчет акции'!$D:$D,'[2]Рассчет акции'!$BN:$BN),0) -> 999 | BA37: =S37/H37 -> 8.5886029 | BC37: =_xlfn.XLOOKUP(B37,#REF!,#REF!,0) -> #REF! | BD37: =BC37/(100%-BE37) -> #REF! | BE37: =_xlfn.XLOOKUP($B37,'[1]Рассчет акции'!$A:$A,'[1]Рассчет акции'!$J:$J) -> 0.34983051 | BF37: =BS37+BI37+BJ37+BU37+BK37 -> #REF! | BG37: =IFERROR(BF37/BC37,0) -> 0 | BH37: 0.37 | BI37: =BC37*BH37 -> #REF! | BJ37: =BC37*$BJ$3 -> #REF! | BK37: =K37*$BK$3*30 -> 0 | BL37: =(IF(K37>$BL$3,('Тарифы ОЗОН'!$G$3+ROUNDUP(K37-$BL$3,0)*'Тарифы ОЗОН'!$G$4),'Тарифы ОЗОН'!$G$3)) -> 46.77 | BM37: =$BN$3 -> 35 | BN37: =_xlfn.XLOOKUP(BM37,'Тарифы ОЗОН'!$A:$A,'Тарифы ОЗОН'!$B:$B) -> 1.32 | BO37: =_xlfn.XLOOKUP(BM37,'Тарифы ОЗОН'!$A:$A,'Тарифы ОЗОН'!C:C) -> 0.016 | BP37: =$BP$3 -> 25 | BQ37: =BL37*BN37+BC37*BO37+BP37 -> #REF! | BR37: =$BR$3 -> 0.85 | BS37: =(100%/BR37)*BQ37+(100%/BR37-1)*BL37 -> #REF! | BT37: =IFERROR(BS37/BC37*100%,0) -> 0 | BU37: =BC37*$BU$3 -> #REF! | BV37: =BF37+F37 -> #REF! | BW37: =IFERROR(BY37/BC37,0) -> 0 | BX37: =IFERROR(BC37-BV37,0) -> 0 | BY37: =BX37-BC37*7% -> #REF! | BZ37: =IFERROR(BY37/H37*100%,0) -> 0 | CA37: 759 | CB37: =IF(BC37=0,0,CA37-BV37) -> #REF! | CC37: =IF(CB37=0,0,CB37-CA37*7%) -> #REF! | CD37: =CC37/H37*100% -> #REF! | CE37: =IFERROR(CC37/CA37,0) -> 0 | CF37: =_xlfn.XLOOKUP(B37,'[1]Рассчет акции'!$A:$A,'[1]Рассчет акции'!$R:$R,0) -> 0 | CG37: =_xlfn.XLOOKUP(B37,'[1]Рассчет акции'!$A:$A,'[1]Рассчет акции'!$M:$M,0) -> 701 | CH37: =IFERROR($CJ37/$CG37,0) -> 0 | CI37: =IF(BC37>0,CG37-BV37,0) -> #REF! | CJ37: =IF(CI37>0,$CI37-$CG37*7%,0) -> #REF! | CK37: =$CJ37/$H37*100% -> #REF! | CL37: =_xlfn.XLOOKUP(B37,'[1]Рассчет акции'!$A:$A,'[1]Рассчет акции'!$W:$W,0) -> 17 | CM37: =_xlfn.XLOOKUP(B37,'[1]Рассчет акции'!$A:$A,'[1]Рассчет акции'!$X:$X,0) -> 999 | CN37: =BC37/H37 -> #REF! | CO37: =CA37-10%*CA37 -> 683.1 | CP37: =_xlfn.XLOOKUP(B37,'[1]Рассчет акции'!$A:$A,'[1]Рассчет акции'!$Z:$Z,0) -> 0
A38: 419146579 | B38: 2415742565 | C38: ACRB1MS109LI | D38: Мяч с шипами фиолетовый 9 см | E38: 2044025354937 | F38: =SUM(H38:J38) -> 101.29113 | G38: =IFERROR(F38/S38*100%,0) -> 0.14428935 | H38: =IF(_xlfn.XLOOKUP($C38,'Юнит Карго'!$A:$A,'Юнит Карго'!$G:$G)=0,_xlfn.XLOOKUP(E38,'Себес 1С текущ'!G:G,'Себес 1С текущ'!H:H),_xlfn.XLOOKUP($C38,'Юнит Карго'!$A:$A,'Юнит Карго'!$P:$P,0,0)) -> 79.291127 | I38: =_xlfn.XLOOKUP(E38,[3]ТЗ_ФФ!$D:$D,[3]ТЗ_ФФ!$BG:$BG,0) -> 14 | J38: =$J$3 -> 8 | K38: =(L38*M38*N38)/1000 -> 0.729 | L38: 9 | M38: 9 | N38: 9 | O38: =_xlfn.XLOOKUP($C38,'Юнит Карго'!$A:$A,'Юнит Карго'!$T:$T,0,0) -> 0.1 | P38: своя | S38: =T38-(T38*U38) -> 702 | T38: =_xlfn.XLOOKUP(E38,'[2]Рассчет акции'!$D:$D,'[2]Рассчет акции'!$G:$G,0) -> 1170 | U38: =_xlfn.XLOOKUP(E38,'[2]Рассчет акции'!$D:$D,'[2]Рассчет акции'!$F:$F,0) -> 0.4 | V38: =AC38+AF38+AH38+AG38 -> 379.5056 | W38: =IFERROR(V38/S38,0) -> 0.54060627 | X38: =IF(K38>1,('Тарифы ВБ'!$B$9+(K38-1)*'Тарифы ВБ'!$B$10)*'Тарифы ВБ'!$B$15*'Тарифы ВБ'!$B$12+S38*'Тарифы ВБ'!$B$13,'Тарифы ВБ'!$B$8*'Тарифы ВБ'!$B$15*'Тарифы ВБ'!$B$12+S38*'Тарифы ВБ'!$B$13) -> 73.3156 | Y38: =IF(K38>1,'Тарифы ВБ'!$B$9+(K38-1)*'Тарифы ВБ'!$B$10,'Тарифы ВБ'!$B$8) -> 32 | Z38: =SUM(X38:Y38) -> 105.3156 | AA38: =IFERROR(Z38/S38,0) -> 0.15002222 | AB38: =IF(K38>1,'Тарифы ВБ'!$B$14*'Тарифы ВБ'!$B$16*'Тарифы ВБ'!$B$15+(K38-1)*'Тарифы ВБ'!$B$14,'Тарифы ВБ'!$B$14*'Тарифы ВБ'!B$16*'Тарифы ВБ'!$B$15) -> 32 | AC38: =+X38+AB38+Y38 -> 137.3156 | AD38: =AC38/S38*100% -> 0.19560627 | AE38: 0.315 | AF38: =S38*AE38 -> 221.13 | AG38: =1.1*S38*$AG$3 -> 0 | AH38: =S38*$AH$3 -> 21.06 | AI38: =F38+V38 -> 480.79673 | AJ38: =IFERROR(AL38/S38,0) -> 0.24510438 | AK38: =S38-AI38 -> 221.20327 | AL38: =AK38-S38*7% -> 172.06327 | AM38: =AL38/H38 -> 2.1700193 | AN38: 709 | AO38: =$AN38-$AI38 -> 228.20327 | AP38: =$AO38-$AN38*7% -> 178.57327 | AQ38: =$AP38/$H38*100% -> 2.2521218 | AR38: =$AP38/$AN38 -> 0.25186639 | AS38: =IFERROR(_xlfn.XLOOKUP(A38,'[2]Рассчет акции'!$A:$A,'[2]Рассчет акции'!$BH:$BH),0) -> * | AT38: =IFERROR(_xlfn.XLOOKUP($A38,'[2]Рассчет акции'!$A:$A,'[2]Рассчет акции'!$BC:$BC),0) -> 702 | AU38: =IFERROR($AW38/$AT38,0) -> 0.24510438 | AV38: =$AT38-$AI38 -> 221.20327 | AW38: =$AV38-$AT38*7% -> 172.06327 | AX38: =$AW38/$H38*100% -> 2.1700193 | AY38: =IFERROR(_xlfn.XLOOKUP(E38,'[2]Рассчет акции'!$D:$D,'[2]Рассчет акции'!$BM:$BM),0) -> 120 | AZ38: =IFERROR(_xlfn.XLOOKUP(E38,'[2]Рассчет акции'!$D:$D,'[2]Рассчет акции'!$BN:$BN),0) -> 999 | BA38: =S38/H38 -> 8.8534497 | BC38: =_xlfn.XLOOKUP(B38,#REF!,#REF!,0) -> #REF! | BD38: =BC38/(100%-BE38) -> #REF! | BE38: =_xlfn.XLOOKUP($B38,'[1]Рассчет акции'!$A:$A,'[1]Рассчет акции'!$J:$J) -> 0.34983051 | BF38: =BS38+BI38+BJ38+BU38+BK38 -> #REF! | BG38: =IFERROR(BF38/BC38,0) -> 0 | BH38: 0.37 | BI38: =BC38*BH38 -> #REF! | BJ38: =BC38*$BJ$3 -> #REF! | BK38: =K38*$BK$3*30 -> 0 | BL38: =(IF(K38>$BL$3,('Тарифы ОЗОН'!$G$3+ROUNDUP(K38-$BL$3,0)*'Тарифы ОЗОН'!$G$4),'Тарифы ОЗОН'!$G$3)) -> 46.77 | BM38: =$BN$3 -> 35 | BN38: =_xlfn.XLOOKUP(BM38,'Тарифы ОЗОН'!$A:$A,'Тарифы ОЗОН'!$B:$B) -> 1.32 | BO38: =_xlfn.XLOOKUP(BM38,'Тарифы ОЗОН'!$A:$A,'Тарифы ОЗОН'!C:C) -> 0.016 | BP38: =$BP$3 -> 25 | BQ38: =BL38*BN38+BC38*BO38+BP38 -> #REF! | BR38: =$BR$3 -> 0.85 | BS38: =(100%/BR38)*BQ38+(100%/BR38-1)*BL38 -> #REF! | BT38: =IFERROR(BS38/BC38*100%,0) -> 0 | BU38: =BC38*$BU$3 -> #REF! | BV38: =BF38+F38 -> #REF! | BW38: =IFERROR(BY38/BC38,0) -> 0 | BX38: =IFERROR(BC38-BV38,0) -> 0 | BY38: =BX38-BC38*7% -> #REF! | BZ38: =IFERROR(BY38/H38*100%,0) -> 0 | CA38: 759 | CB38: =IF(BC38=0,0,CA38-BV38) -> #REF! | CC38: =IF(CB38=0,0,CB38-CA38*7%) -> #REF! | CD38: =CC38/H38*100% -> #REF! | CE38: =IFERROR(CC38/CA38,0) -> 0 | CF38: =_xlfn.XLOOKUP(B38,'[1]Рассчет акции'!$A:$A,'[1]Рассчет акции'!$R:$R,0) -> 0 | CG38: =_xlfn.XLOOKUP(B38,'[1]Рассчет акции'!$A:$A,'[1]Рассчет акции'!$M:$M,0) -> 701 | CH38: =IFERROR($CJ38/$CG38,0) -> 0 | CI38: =IF(BC38>0,CG38-BV38,0) -> #REF! | CJ38: =IF(CI38>0,$CI38-$CG38*7%,0) -> #REF! | CK38: =$CJ38/$H38*100% -> #REF! | CL38: =_xlfn.XLOOKUP(B38,'[1]Рассчет акции'!$A:$A,'[1]Рассчет акции'!$W:$W,0) -> 4 | CM38: =_xlfn.XLOOKUP(B38,'[1]Рассчет акции'!$A:$A,'[1]Рассчет акции'!$X:$X,0) -> 999 | CN38: =BC38/H38 -> #REF! | CO38: =CA38-10%*CA38 -> 683.1 | CP38: =_xlfn.XLOOKUP(B38,'[1]Рассчет акции'!$A:$A,'[1]Рассчет акции'!$Z:$Z,0) -> 0
A39: 340734340 | B39: 2415742594 | C39: ACRB1MS103PN | D39: Мяч гладкий розовый | E39: 2042985583893 | F39: =SUM(H39:J39) -> 96 | G39: =IFERROR(F39/S39*100%,0) -> 0.1871345 | H39: =IF(_xlfn.XLOOKUP($C39,'Юнит Карго'!$A:$A,'Юнит Карго'!$G:$G)=0,_xlfn.XLOOKUP(E39,'Себес 1С текущ'!G:G,'Себес 1С текущ'!H:H),_xlfn.XLOOKUP($C39,'Юнит Карго'!$A:$A,'Юнит Карго'!$P:$P,0,0)) -> 80 | I39: =_xlfn.XLOOKUP(E39,[3]ТЗ_ФФ!$D:$D,[3]ТЗ_ФФ!$BG:$BG,0) -> 8 | J39: =$J$3 -> 8 | K39: =(L39*M39*N39)/1000 -> 0.384 | L39: 8 | M39: 8 | N39: 6 | O39: =_xlfn.XLOOKUP($C39,'Юнит Карго'!$A:$A,'Юнит Карго'!$T:$T,0,0) -> 0 | P39: своя | S39: =T39-(T39*U39) -> 513 | T39: =_xlfn.XLOOKUP(E39,'[2]Рассчет акции'!$D:$D,'[2]Рассчет акции'!$G:$G,0) -> 855 | U39: =_xlfn.XLOOKUP(E39,'[2]Рассчет акции'!$D:$D,'[2]Рассчет акции'!$F:$F,0) -> 0.4 | V39: =AC39+AF39+AH39+AG39 -> 312.8264 | W39: =IFERROR(V39/S39,0) -> 0.60979805 | X39: =IF(K39>1,('Тарифы ВБ'!$B$9+(K39-1)*'Тарифы ВБ'!$B$10)*'Тарифы ВБ'!$B$15*'Тарифы ВБ'!$B$12+S39*'Тарифы ВБ'!$B$13,'Тарифы ВБ'!$B$8*'Тарифы ВБ'!$B$15*'Тарифы ВБ'!$B$12+S39*'Тарифы ВБ'!$B$13) -> 71.8414 | Y39: =IF(K39>1,'Тарифы ВБ'!$B$9+(K39-1)*'Тарифы ВБ'!$B$10,'Тарифы ВБ'!$B$8) -> 32 | Z39: =SUM(X39:Y39) -> 103.8414 | AA39: =IFERROR(Z39/S39,0) -> 0.20241988 | AB39: =IF(K39>1,'Тарифы ВБ'!$B$14*'Тарифы ВБ'!$B$16*'Тарифы ВБ'!$B$15+(K39-1)*'Тарифы ВБ'!$B$14,'Тарифы ВБ'!$B$14*'Тарифы ВБ'!B$16*'Тарифы ВБ'!$B$15) -> 32 | AC39: =+X39+AB39+Y39 -> 135.8414 | AD39: =AC39/S39*100% -> 0.26479805 | AE39: 0.315 | AF39: =S39*AE39 -> 161.595 | AG39: =1.1*S39*$AG$3 -> 0 | AH39: =S39*$AH$3 -> 15.39 | AI39: =F39+V39 -> 408.8264 | AJ39: =IFERROR(AL39/S39,0) -> 0.13306745 | AK39: =S39-AI39 -> 104.1736 | AL39: =AK39-S39*7% -> 68.2636 | AM39: =AL39/H39 -> 0.853295 | AN39: 519 | AO39: =$AN39-$AI39 -> 110.1736 | AP39: =$AO39-$AN39*7% -> 73.8436 | AQ39: =$AP39/$H39*100% -> 0.923045 | AR39: =$AP39/$AN39 -> 0.14228054 | AS39: =IFERROR(_xlfn.XLOOKUP(A39,'[2]Рассчет акции'!$A:$A,'[2]Рассчет акции'!$BH:$BH),0) -> * | AT39: =IFERROR(_xlfn.XLOOKUP($A39,'[2]Рассчет акции'!$A:$A,'[2]Рассчет акции'!$BC:$BC),0) -> 513 | AU39: =IFERROR($AW39/$AT39,0) -> 0.13306745 | AV39: =$AT39-$AI39 -> 104.1736 | AW39: =$AV39-$AT39*7% -> 68.2636 | AX39: =$AW39/$H39*100% -> 0.853295 | AY39: =IFERROR(_xlfn.XLOOKUP(E39,'[2]Рассчет акции'!$D:$D,'[2]Рассчет акции'!$BM:$BM),0) -> 4 | AZ39: =IFERROR(_xlfn.XLOOKUP(E39,'[2]Рассчет акции'!$D:$D,'[2]Рассчет акции'!$BN:$BN),0) -> 999 | BA39: =S39/H39 -> 6.4125 | BC39: =_xlfn.XLOOKUP(B39,#REF!,#REF!,0) -> #REF! | BD39: =BC39/(100%-BE39) -> #REF! | BE39: =_xlfn.XLOOKUP($B39,'[1]Рассчет акции'!$A:$A,'[1]Рассчет акции'!$J:$J) -> 0.35022693 | BF39: =BS39+BI39+BJ39+BU39+BK39 -> #REF! | BG39: =IFERROR(BF39/BC39,0) -> 0 | BH39: 0.37 | BI39: =BC39*BH39 -> #REF! | BJ39: =BC39*$BJ$3 -> #REF! | BK39: =K39*$BK$3*30 -> 0 | BL39: =(IF(K39>$BL$3,('Тарифы ОЗОН'!$G$3+ROUNDUP(K39-$BL$3,0)*'Тарифы ОЗОН'!$G$4),'Тарифы ОЗОН'!$G$3)) -> 46.77 | BM39: =$BN$3 -> 35 | BN39: =_xlfn.XLOOKUP(BM39,'Тарифы ОЗОН'!$A:$A,'Тарифы ОЗОН'!$B:$B) -> 1.32 | BO39: =_xlfn.XLOOKUP(BM39,'Тарифы ОЗОН'!$A:$A,'Тарифы ОЗОН'!C:C) -> 0.016 | BP39: =$BP$3 -> 25 | BQ39: =BL39*BN39+BC39*BO39+BP39 -> #REF! | BR39: =$BR$3 -> 0.85 | BS39: =(100%/BR39)*BQ39+(100%/BR39-1)*BL39 -> #REF! | BT39: =IFERROR(BS39/BC39*100%,0) -> 0 | BU39: =BC39*$BU$3 -> #REF! | BV39: =BF39+F39 -> #REF! | CB39: =IF(BC39=0,0,CA39-BV39) -> #REF! | CC39: =IF(CB39=0,0,CB39-CA39*7%) -> #REF! | CD39: =CC39/H39*100% -> #REF! | CE39: =IFERROR(CC39/CA39,0) -> 0 | CF39: =_xlfn.XLOOKUP(B39,'[1]Рассчет акции'!$A:$A,'[1]Рассчет акции'!$R:$R,0) -> 0 | CG39: =_xlfn.XLOOKUP(B39,'[1]Рассчет акции'!$A:$A,'[1]Рассчет акции'!$M:$M,0) -> 0 | CH39: =IFERROR($CJ39/$CG39,0) -> 0 | CI39: =IF(BC39>0,CG39-BV39,0) -> #REF! | CJ39: =IF(CI39>0,$CI39-$CG39*7%,0) -> #REF! | CK39: =$CJ39/$H39*100% -> #REF! | CL39: =_xlfn.XLOOKUP(B39,'[1]Рассчет акции'!$A:$A,'[1]Рассчет акции'!$W:$W,0) -> 0 | CM39: =_xlfn.XLOOKUP(B39,'[1]Рассчет акции'!$A:$A,'[1]Рассчет акции'!$X:$X,0) -> 0 | CN39: =BC39/H39 -> #REF! | CO39: =CA39-10%*CA39 -> 0 | CP39: =_xlfn.XLOOKUP(B39,'[1]Рассчет акции'!$A:$A,'[1]Рассчет акции'!$Z:$Z,0) -> 0
A40: 340741532 | B40: 2415743200 | C40: ACRB1MS103BL | D40: Мяч гладкий голубой | E40: 2042986356632 | F40: =SUM(H40:J40) -> 96 | G40: =IFERROR(F40/S40*100%,0) -> 0.1871345 | H40: =IF(_xlfn.XLOOKUP($C40,'Юнит Карго'!$A:$A,'Юнит Карго'!$G:$G)=0,_xlfn.XLOOKUP(E40,'Себес 1С текущ'!G:G,'Себес 1С текущ'!H:H),_xlfn.XLOOKUP($C40,'Юнит Карго'!$A:$A,'Юнит Карго'!$P:$P,0,0)) -> 80 | I40: =_xlfn.XLOOKUP(E40,[3]ТЗ_ФФ!$D:$D,[3]ТЗ_ФФ!$BG:$BG,0) -> 8 | J40: =$J$3 -> 8 | K40: =(L40*M40*N40)/1000 -> 0.384 | L40: 8 | M40: 8 | N40: 6 | O40: =_xlfn.XLOOKUP($C40,'Юнит Карго'!$A:$A,'Юнит Карго'!$T:$T,0,0) -> 0 | P40: своя | S40: =T40-(T40*U40) -> 513 | T40: =_xlfn.XLOOKUP(E40,'[2]Рассчет акции'!$D:$D,'[2]Рассчет акции'!$G:$G,0) -> 855 | U40: =_xlfn.XLOOKUP(E40,'[2]Рассчет акции'!$D:$D,'[2]Рассчет акции'!$F:$F,0) -> 0.4 | V40: =AC40+AF40+AH40+AG40 -> 312.8264 | W40: =IFERROR(V40/S40,0) -> 0.60979805 | X40: =IF(K40>1,('Тарифы ВБ'!$B$9+(K40-1)*'Тарифы ВБ'!$B$10)*'Тарифы ВБ'!$B$15*'Тарифы ВБ'!$B$12+S40*'Тарифы ВБ'!$B$13,'Тарифы ВБ'!$B$8*'Тарифы ВБ'!$B$15*'Тарифы ВБ'!$B$12+S40*'Тарифы ВБ'!$B$13) -> 71.8414 | Y40: =IF(K40>1,'Тарифы ВБ'!$B$9+(K40-1)*'Тарифы ВБ'!$B$10,'Тарифы ВБ'!$B$8) -> 32 | Z40: =SUM(X40:Y40) -> 103.8414 | AA40: =IFERROR(Z40/S40,0) -> 0.20241988 | AB40: =IF(K40>1,'Тарифы ВБ'!$B$14*'Тарифы ВБ'!$B$16*'Тарифы ВБ'!$B$15+(K40-1)*'Тарифы ВБ'!$B$14,'Тарифы ВБ'!$B$14*'Тарифы ВБ'!B$16*'Тарифы ВБ'!$B$15) -> 32 | AC40: =+X40+AB40+Y40 -> 135.8414 | AD40: =AC40/S40*100% -> 0.26479805 | AE40: 0.315 | AF40: =S40*AE40 -> 161.595 | AG40: =1.1*S40*$AG$3 -> 0 | AH40: =S40*$AH$3 -> 15.39 | AI40: =F40+V40 -> 408.8264 | AJ40: =IFERROR(AL40/S40,0) -> 0.13306745 | AK40: =S40-AI40 -> 104.1736 | AL40: =AK40-S40*7% -> 68.2636 | AM40: =AL40/H40 -> 0.853295 | AN40: 519 | AO40: =$AN40-$AI40 -> 110.1736 | AP40: =$AO40-$AN40*7% -> 73.8436 | AQ40: =$AP40/$H40*100% -> 0.923045 | AR40: =$AP40/$AN40 -> 0.14228054 | AS40: =IFERROR(_xlfn.XLOOKUP(A40,'[2]Рассчет акции'!$A:$A,'[2]Рассчет акции'!$BH:$BH),0) -> * | AT40: =IFERROR(_xlfn.XLOOKUP($A40,'[2]Рассчет акции'!$A:$A,'[2]Рассчет акции'!$BC:$BC),0) -> 513 | AU40: =IFERROR($AW40/$AT40,0) -> 0.13306745 | AV40: =$AT40-$AI40 -> 104.1736 | AW40: =$AV40-$AT40*7% -> 68.2636 | AX40: =$AW40/$H40*100% -> 0.853295 | AY40: =IFERROR(_xlfn.XLOOKUP(E40,'[2]Рассчет акции'!$D:$D,'[2]Рассчет акции'!$BM:$BM),0) -> 60 | AZ40: =IFERROR(_xlfn.XLOOKUP(E40,'[2]Рассчет акции'!$D:$D,'[2]Рассчет акции'!$BN:$BN),0) -> 999 | BA40: =S40/H40 -> 6.4125 | BC40: =_xlfn.XLOOKUP(B40,#REF!,#REF!,0) -> #REF! | BD40: =BC40/(100%-BE40) -> #REF! | BE40: =_xlfn.XLOOKUP($B40,'[1]Рассчет акции'!$A:$A,'[1]Рассчет акции'!$J:$J) -> 0.35022693 | BF40: =BS40+BI40+BJ40+BU40+BK40 -> #REF! | BG40: =IFERROR(BF40/BC40,0) -> 0 | BH40: 0.37 | BI40: =BC40*BH40 -> #REF! | BJ40: =BC40*$BJ$3 -> #REF! | BK40: =K40*$BK$3*30 -> 0 | BL40: =(IF(K40>$BL$3,('Тарифы ОЗОН'!$G$3+ROUNDUP(K40-$BL$3,0)*'Тарифы ОЗОН'!$G$4),'Тарифы ОЗОН'!$G$3)) -> 46.77 | BM40: =$BN$3 -> 35 | BN40: =_xlfn.XLOOKUP(BM40,'Тарифы ОЗОН'!$A:$A,'Тарифы ОЗОН'!$B:$B) -> 1.32 | BO40: =_xlfn.XLOOKUP(BM40,'Тарифы ОЗОН'!$A:$A,'Тарифы ОЗОН'!C:C) -> 0.016 | BP40: =$BP$3 -> 25 | BQ40: =BL40*BN40+BC40*BO40+BP40 -> #REF! | BR40: =$BR$3 -> 0.85 | BS40: =(100%/BR40)*BQ40+(100%/BR40-1)*BL40 -> #REF! | BT40: =IFERROR(BS40/BC40*100%,0) -> 0 | BU40: =BC40*$BU$3 -> #REF! | BV40: =BF40+F40 -> #REF! | CB40: =IF(BC40=0,0,CA40-BV40) -> #REF! | CC40: =IF(CB40=0,0,CB40-CA40*7%) -> #REF! | CD40: =CC40/H40*100% -> #REF! | CE40: =IFERROR(CC40/CA40,0) -> 0 | CF40: =_xlfn.XLOOKUP(B40,'[1]Рассчет акции'!$A:$A,'[1]Рассчет акции'!$R:$R,0) -> 0 | CG40: =_xlfn.XLOOKUP(B40,'[1]Рассчет акции'!$A:$A,'[1]Рассчет акции'!$M:$M,0) -> 0 | CH40: =IFERROR($CJ40/$CG40,0) -> 0 | CI40: =IF(BC40>0,CG40-BV40,0) -> #REF! | CJ40: =IF(CI40>0,$CI40-$CG40*7%,0) -> #REF! | CK40: =$CJ40/$H40*100% -> #REF! | CL40: =_xlfn.XLOOKUP(B40,'[1]Рассчет акции'!$A:$A,'[1]Рассчет акции'!$W:$W,0) -> 0 | CM40: =_xlfn.XLOOKUP(B40,'[1]Рассчет акции'!$A:$A,'[1]Рассчет акции'!$X:$X,0) -> 0 | CN40: =BC40/H40 -> #REF! | CO40: =CA40-10%*CA40 -> 0 | CP40: =_xlfn.XLOOKUP(B40,'[1]Рассчет акции'!$A:$A,'[1]Рассчет акции'!$Z:$Z,0) -> 0
A41: 340743352 | B41: 2415742578 | C41: ACRB1MS103LI | D41: Мяч гладкий сиреневый | E41: 2042986372359 | F41: =SUM(H41:J41) -> 96 | G41: =IFERROR(F41/S41*100%,0) -> 0.1871345 | H41: =IF(_xlfn.XLOOKUP($C41,'Юнит Карго'!$A:$A,'Юнит Карго'!$G:$G)=0,_xlfn.XLOOKUP(E41,'Себес 1С текущ'!G:G,'Себес 1С текущ'!H:H),_xlfn.XLOOKUP($C41,'Юнит Карго'!$A:$A,'Юнит Карго'!$P:$P,0,0)) -> 80 | I41: =_xlfn.XLOOKUP(E41,[3]ТЗ_ФФ!$D:$D,[3]ТЗ_ФФ!$BG:$BG,0) -> 8 | J41: =$J$3 -> 8 | K41: =(L41*M41*N41)/1000 -> 0.384 | L41: 8 | M41: 8 | N41: 6 | O41: =_xlfn.XLOOKUP($C41,'Юнит Карго'!$A:$A,'Юнит Карго'!$T:$T,0,0) -> 0 | P41: своя | S41: =T41-(T41*U41) -> 513 | T41: =_xlfn.XLOOKUP(E41,'[2]Рассчет акции'!$D:$D,'[2]Рассчет акции'!$G:$G,0) -> 855 | U41: =_xlfn.XLOOKUP(E41,'[2]Рассчет акции'!$D:$D,'[2]Рассчет акции'!$F:$F,0) -> 0.4 | V41: =AC41+AF41+AH41+AG41 -> 312.8264 | W41: =IFERROR(V41/S41,0) -> 0.60979805 | X41: =IF(K41>1,('Тарифы ВБ'!$B$9+(K41-1)*'Тарифы ВБ'!$B$10)*'Тарифы ВБ'!$B$15*'Тарифы ВБ'!$B$12+S41*'Тарифы ВБ'!$B$13,'Тарифы ВБ'!$B$8*'Тарифы ВБ'!$B$15*'Тарифы ВБ'!$B$12+S41*'Тарифы ВБ'!$B$13) -> 71.8414 | Y41: =IF(K41>1,'Тарифы ВБ'!$B$9+(K41-1)*'Тарифы ВБ'!$B$10,'Тарифы ВБ'!$B$8) -> 32 | Z41: =SUM(X41:Y41) -> 103.8414 | AA41: =IFERROR(Z41/S41,0) -> 0.20241988 | AB41: =IF(K41>1,'Тарифы ВБ'!$B$14*'Тарифы ВБ'!$B$16*'Тарифы ВБ'!$B$15+(K41-1)*'Тарифы ВБ'!$B$14,'Тарифы ВБ'!$B$14*'Тарифы ВБ'!B$16*'Тарифы ВБ'!$B$15) -> 32 | AC41: =+X41+AB41+Y41 -> 135.8414 | AD41: =AC41/S41*100% -> 0.26479805 | AE41: 0.315 | AF41: =S41*AE41 -> 161.595 | AG41: =1.1*S41*$AG$3 -> 0 | AH41: =S41*$AH$3 -> 15.39 | AI41: =F41+V41 -> 408.8264 | AJ41: =IFERROR(AL41/S41,0) -> 0.13306745 | AK41: =S41-AI41 -> 104.1736 | AL41: =AK41-S41*7% -> 68.2636 | AM41: =AL41/H41 -> 0.853295 | AN41: 519 | AO41: =$AN41-$AI41 -> 110.1736 | AP41: =$AO41-$AN41*7% -> 73.8436 | AQ41: =$AP41/$H41*100% -> 0.923045 | AR41: =$AP41/$AN41 -> 0.14228054 | AS41: =IFERROR(_xlfn.XLOOKUP(A41,'[2]Рассчет акции'!$A:$A,'[2]Рассчет акции'!$BH:$BH),0) -> * | AT41: =IFERROR(_xlfn.XLOOKUP($A41,'[2]Рассчет акции'!$A:$A,'[2]Рассчет акции'!$BC:$BC),0) -> 513 | AU41: =IFERROR($AW41/$AT41,0) -> 0.13306745 | AV41: =$AT41-$AI41 -> 104.1736 | AW41: =$AV41-$AT41*7% -> 68.2636 | AX41: =$AW41/$H41*100% -> 0.853295 | AY41: =IFERROR(_xlfn.XLOOKUP(E41,'[2]Рассчет акции'!$D:$D,'[2]Рассчет акции'!$BM:$BM),0) -> 27 | AZ41: =IFERROR(_xlfn.XLOOKUP(E41,'[2]Рассчет акции'!$D:$D,'[2]Рассчет акции'!$BN:$BN),0) -> 216 | BA41: =S41/H41 -> 6.4125 | BC41: =_xlfn.XLOOKUP(B41,#REF!,#REF!,0) -> #REF! | BD41: =BC41/(100%-BE41) -> #REF! | BE41: =_xlfn.XLOOKUP($B41,'[1]Рассчет акции'!$A:$A,'[1]Рассчет акции'!$J:$J) -> 0.35022693 | BF41: =BS41+BI41+BJ41+BU41+BK41 -> #REF! | BG41: =IFERROR(BF41/BC41,0) -> 0 | BH41: 0.37 | BI41: =BC41*BH41 -> #REF! | BJ41: =BC41*$BJ$3 -> #REF! | BK41: =K41*$BK$3*30 -> 0 | BL41: =(IF(K41>$BL$3,('Тарифы ОЗОН'!$G$3+ROUNDUP(K41-$BL$3,0)*'Тарифы ОЗОН'!$G$4),'Тарифы ОЗОН'!$G$3)) -> 46.77 | BM41: =$BN$3 -> 35 | BN41: =_xlfn.XLOOKUP(BM41,'Тарифы ОЗОН'!$A:$A,'Тарифы ОЗОН'!$B:$B) -> 1.32 | BO41: =_xlfn.XLOOKUP(BM41,'Тарифы ОЗОН'!$A:$A,'Тарифы ОЗОН'!C:C) -> 0.016 | BP41: =$BP$3 -> 25 | BQ41: =BL41*BN41+BC41*BO41+BP41 -> #REF! | BR41: =$BR$3 -> 0.85 | BS41: =(100%/BR41)*BQ41+(100%/BR41-1)*BL41 -> #REF! | BT41: =IFERROR(BS41/BC41*100%,0) -> 0 | BU41: =BC41*$BU$3 -> #REF! | BV41: =BF41+F41 -> #REF! | CB41: =IF(BC41=0,0,CA41-BV41) -> #REF! | CC41: =IF(CB41=0,0,CB41-CA41*7%) -> #REF! | CD41: =CC41/H41*100% -> #REF! | CE41: =IFERROR(CC41/CA41,0) -> 0 | CF41: =_xlfn.XLOOKUP(B41,'[1]Рассчет акции'!$A:$A,'[1]Рассчет акции'!$R:$R,0) -> 0 | CG41: =_xlfn.XLOOKUP(B41,'[1]Рассчет акции'!$A:$A,'[1]Рассчет акции'!$M:$M,0) -> 0 | CH41: =IFERROR($CJ41/$CG41,0) -> 0 | CI41: =IF(BC41>0,CG41-BV41,0) -> #REF! | CJ41: =IF(CI41>0,$CI41-$CG41*7%,0) -> #REF! | CK41: =$CJ41/$H41*100% -> #REF! | CL41: =_xlfn.XLOOKUP(B41,'[1]Рассчет акции'!$A:$A,'[1]Рассчет акции'!$W:$W,0) -> 0 | CM41: =_xlfn.XLOOKUP(B41,'[1]Рассчет акции'!$A:$A,'[1]Рассчет акции'!$X:$X,0) -> 0 | CN41: =BC41/H41 -> #REF! | CO41: =CA41-10%*CA41 -> 0 | CP41: =_xlfn.XLOOKUP(B41,'[1]Рассчет акции'!$A:$A,'[1]Рассчет акции'!$Z:$Z,0) -> 0
A42: 340743911 | B42: 2415742537 | C42: ACRB1MS103RJ | D42: Мяч гладкий оранжевый | E42: 2042986377583 | F42: =SUM(H42:J42) -> 97 | G42: =IFERROR(F42/S42*100%,0) -> 0.19086974 | H42: =IF(_xlfn.XLOOKUP($C42,'Юнит Карго'!$A:$A,'Юнит Карго'!$G:$G)=0,_xlfn.XLOOKUP(E42,'Себес 1С текущ'!G:G,'Себес 1С текущ'!H:H),_xlfn.XLOOKUP($C42,'Юнит Карго'!$A:$A,'Юнит Карго'!$P:$P,0,0)) -> 81 | I42: =_xlfn.XLOOKUP(E42,[3]ТЗ_ФФ!$D:$D,[3]ТЗ_ФФ!$BG:$BG,0) -> 8 | J42: =$J$3 -> 8 | K42: =(L42*M42*N42)/1000 -> 0.384 | L42: 8 | M42: 8 | N42: 6 | O42: =_xlfn.XLOOKUP($C42,'Юнит Карго'!$A:$A,'Юнит Карго'!$T:$T,0,0) -> 0 | P42: своя | S42: =T42-(T42*U42) -> 508.2 | T42: =_xlfn.XLOOKUP(E42,'[2]Рассчет акции'!$D:$D,'[2]Рассчет акции'!$G:$G,0) -> 847 | U42: =_xlfn.XLOOKUP(E42,'[2]Рассчет акции'!$D:$D,'[2]Рассчет акции'!$F:$F,0) -> 0.4 | V42: =AC42+AF42+AH42+AG42 -> 311.13296 | W42: =IFERROR(V42/S42,0) -> 0.61222542 | X42: =IF(K42>1,('Тарифы ВБ'!$B$9+(K42-1)*'Тарифы ВБ'!$B$10)*'Тарифы ВБ'!$B$15*'Тарифы ВБ'!$B$12+S42*'Тарифы ВБ'!$B$13,'Тарифы ВБ'!$B$8*'Тарифы ВБ'!$B$15*'Тарифы ВБ'!$B$12+S42*'Тарифы ВБ'!$B$13) -> 71.80396 | Y42: =IF(K42>1,'Тарифы ВБ'!$B$9+(K42-1)*'Тарифы ВБ'!$B$10,'Тарифы ВБ'!$B$8) -> 32 | Z42: =SUM(X42:Y42) -> 103.80396 | AA42: =IFERROR(Z42/S42,0) -> 0.20425809 | AB42: =IF(K42>1,'Тарифы ВБ'!$B$14*'Тарифы ВБ'!$B$16*'Тарифы ВБ'!$B$15+(K42-1)*'Тарифы ВБ'!$B$14,'Тарифы ВБ'!$B$14*'Тарифы ВБ'!B$16*'Тарифы ВБ'!$B$15) -> 32 | AC42: =+X42+AB42+Y42 -> 135.80396 | AD42: =AC42/S42*100% -> 0.26722542 | AE42: 0.315 | AF42: =S42*AE42 -> 160.083 | AG42: =1.1*S42*$AG$3 -> 0 | AH42: =S42*$AH$3 -> 15.246 | AI42: =F42+V42 -> 408.13296 | AJ42: =IFERROR(AL42/S42,0) -> 0.12690484 | AK42: =S42-AI42 -> 100.06704 | AL42: =AK42-S42*7% -> 64.49304 | AM42: =AL42/H42 -> 0.79621037 | AN42: 519 | AO42: =$AN42-$AI42 -> 110.86704 | AP42: =$AO42-$AN42*7% -> 74.53704 | AQ42: =$AP42/$H42*100% -> 0.92021037 | AR42: =$AP42/$AN42 -> 0.14361665 | AS42: =IFERROR(_xlfn.XLOOKUP(A42,'[2]Рассчет акции'!$A:$A,'[2]Рассчет акции'!$BH:$BH),0) -> * | AT42: =IFERROR(_xlfn.XLOOKUP($A42,'[2]Рассчет акции'!$A:$A,'[2]Рассчет акции'!$BC:$BC),0) -> 508 | AU42: =IFERROR($AW42/$AT42,0) -> 0.12658866 | AV42: =$AT42-$AI42 -> 99.86704 | AW42: =$AV42-$AT42*7% -> 64.30704 | AX42: =$AW42/$H42*100% -> 0.79391407 | AY42: =IFERROR(_xlfn.XLOOKUP(E42,'[2]Рассчет акции'!$D:$D,'[2]Рассчет акции'!$BM:$BM),0) -> 13 | AZ42: =IFERROR(_xlfn.XLOOKUP(E42,'[2]Рассчет акции'!$D:$D,'[2]Рассчет акции'!$BN:$BN),0) -> 416 | BA42: =S42/H42 -> 6.2740741 | BC42: =_xlfn.XLOOKUP(B42,#REF!,#REF!,0) -> #REF! | BD42: =BC42/(100%-BE42) -> #REF! | BE42: =_xlfn.XLOOKUP($B42,'[1]Рассчет акции'!$A:$A,'[1]Рассчет акции'!$J:$J) -> 0.35022693 | BF42: =BS42+BI42+BJ42+BU42+BK42 -> #REF! | BG42: =IFERROR(BF42/BC42,0) -> 0 | BH42: 0.37 | BI42: =BC42*BH42 -> #REF! | BJ42: =BC42*$BJ$3 -> #REF! | BK42: =K42*$BK$3*30 -> 0 | BL42: =(IF(K42>$BL$3,('Тарифы ОЗОН'!$G$3+ROUNDUP(K42-$BL$3,0)*'Тарифы ОЗОН'!$G$4),'Тарифы ОЗОН'!$G$3)) -> 46.77 | BM42: =$BN$3 -> 35 | BN42: =_xlfn.XLOOKUP(BM42,'Тарифы ОЗОН'!$A:$A,'Тарифы ОЗОН'!$B:$B) -> 1.32 | BO42: =_xlfn.XLOOKUP(BM42,'Тарифы ОЗОН'!$A:$A,'Тарифы ОЗОН'!C:C) -> 0.016 | BP42: =$BP$3 -> 25 | BQ42: =BL42*BN42+BC42*BO42+BP42 -> #REF! | BR42: =$BR$3 -> 0.85 | BS42: =(100%/BR42)*BQ42+(100%/BR42-1)*BL42 -> #REF! | BT42: =IFERROR(BS42/BC42*100%,0) -> 0 | BU42: =BC42*$BU$3 -> #REF! | BV42: =BF42+F42 -> #REF! | CB42: =IF(BC42=0,0,CA42-BV42) -> #REF! | CC42: =IF(CB42=0,0,CB42-CA42*7%) -> #REF! | CD42: =CC42/H42*100% -> #REF! | CE42: =IFERROR(CC42/CA42,0) -> 0 | CF42: =_xlfn.XLOOKUP(B42,'[1]Рассчет акции'!$A:$A,'[1]Рассчет акции'!$R:$R,0) -> 0 | CG42: =_xlfn.XLOOKUP(B42,'[1]Рассчет акции'!$A:$A,'[1]Рассчет акции'!$M:$M,0) -> 0 | CH42: =IFERROR($CJ42/$CG42,0) -> 0 | CI42: =IF(BC42>0,CG42-BV42,0) -> #REF! | CJ42: =IF(CI42>0,$CI42-$CG42*7%,0) -> #REF! | CK42: =$CJ42/$H42*100% -> #REF! | CL42: =_xlfn.XLOOKUP(B42,'[1]Рассчет акции'!$A:$A,'[1]Рассчет акции'!$W:$W,0) -> 0 | CM42: =_xlfn.XLOOKUP(B42,'[1]Рассчет акции'!$A:$A,'[1]Рассчет акции'!$X:$X,0) -> 0 | CN42: =BC42/H42 -> #REF! | CO42: =CA42-10%*CA42 -> 0 | CP42: =_xlfn.XLOOKUP(B42,'[1]Рассчет акции'!$A:$A,'[1]Рассчет акции'!$Z:$Z,0) -> 0
A43: 820643010 | C43: ACRB3FR101CL | D43: Набор эластичных лент 3 шт. в мешке | E43: 2048933027488 | F43: =SUM(H43:J43) -> 443.69017 | G43: =IFERROR(F43/S43*100%,0) -> 0.29914386 | H43: =IF(_xlfn.XLOOKUP($C43,'Юнит Карго'!$A:$A,'Юнит Карго'!$G:$G)=0,_xlfn.XLOOKUP(E43,'Себес 1С текущ'!G:G,'Себес 1С текущ'!H:H),_xlfn.XLOOKUP($C43,'Юнит Карго'!$A:$A,'Юнит Карго'!$P:$P,0,0)) -> 408.69017 | I43: =_xlfn.XLOOKUP(E43,[3]ТЗ_ФФ!$D:$D,[3]ТЗ_ФФ!$BG:$BG,0) -> 27 | J43: =$J$3 -> 8 | K43: =(L43*M43*N43)/1000 -> 1.98 | L43: 30 | M43: 11 | N43: 6 | O43: =_xlfn.XLOOKUP($C43,'Юнит Карго'!$A:$A,'Юнит Карго'!$T:$T,0,0) -> 0.37 | S43: =T43-(T43*U43) -> 1483.2 | T43: =_xlfn.XLOOKUP(E43,'[2]Рассчет акции'!$D:$D,'[2]Рассчет акции'!$G:$G,0) -> 2472 | U43: =_xlfn.XLOOKUP(E43,'[2]Рассчет акции'!$D:$D,'[2]Рассчет акции'!$F:$F,0) -> 0.4 | V43: =AC43+AF43+AH43+AG43 -> 682.34976 | W43: =IFERROR(V43/S43,0) -> 0.46005243 | X43: =IF(K43>1,('Тарифы ВБ'!$B$9+(K43-1)*'Тарифы ВБ'!$B$10)*'Тарифы ВБ'!$B$15*'Тарифы ВБ'!$B$12+S43*'Тарифы ВБ'!$B$13,'Тарифы ВБ'!$B$8*'Тарифы ВБ'!$B$15*'Тарифы ВБ'!$B$12+S43*'Тарифы ВБ'!$B$13) -> 138.17536 | Y43: =IF(K43>1,'Тарифы ВБ'!$B$9+(K43-1)*'Тарифы ВБ'!$B$10,'Тарифы ВБ'!$B$8) -> 59.72 | Z43: =SUM(X43:Y43) -> 197.89536 | AA43: =IFERROR(Z43/S43,0) -> 0.1334246 | AB43: =IF(K43>1,'Тарифы ВБ'!$B$14*'Тарифы ВБ'!$B$16*'Тарифы ВБ'!$B$15+(K43-1)*'Тарифы ВБ'!$B$14,'Тарифы ВБ'!$B$14*'Тарифы ВБ'!B$16*'Тарифы ВБ'!$B$15) -> 32.0784 | AC43: =+X43+AB43+Y43 -> 229.97376 | AD43: =AC43/S43*100% -> 0.15505243 | AE43: 0.275 | AF43: =S43*AE43 -> 407.88 | AG43: =1.1*S43*$AG$3 -> 0 | AH43: =S43*$AH$3 -> 44.496 | AI43: =F43+V43 -> 1126.0399 | AJ43: =IFERROR(AL43/S43,0) -> 0.17080372 | AK43: =S43-AI43 -> 357.16007 | AL43: =AK43-S43*7% -> 253.33607 | AM43: =AL43/H43 -> 0.61987317 | AN43: 1499 | AO43: =$AN43-$AI43 -> 372.96007 | AP43: =$AO43-$AN43*7% -> 268.03007 | AQ43: =$AP43/$H43*100% -> 0.65582706 | AR43: =$AP43/$AN43 -> 0.17880592 | AS43: =IFERROR(_xlfn.XLOOKUP(A43,'[2]Рассчет акции'!$A:$A,'[2]Рассчет акции'!$BH:$BH),0) -> * | AT43: =IFERROR(_xlfn.XLOOKUP($A43,'[2]Рассчет акции'!$A:$A,'[2]Рассчет акции'!$BC:$BC),0) -> 1483 | AU43: =IFERROR($AW43/$AT43,0) -> 0.17070133 | AV43: =$AT43-$AI43 -> 356.96007 | AW43: =$AV43-$AT43*7% -> 253.15007 | AX43: =$AW43/$H43*100% -> 0.61941806 | AY43: =IFERROR(_xlfn.XLOOKUP(E43,'[2]Рассчет акции'!$D:$D,'[2]Рассчет акции'!$BM:$BM),0) -> 89 | AZ43: =IFERROR(_xlfn.XLOOKUP(E43,'[2]Рассчет акции'!$D:$D,'[2]Рассчет акции'!$BN:$BN),0) -> 520 | BA43: =S43/H43 -> 3.6291551 | BC43: =_xlfn.XLOOKUP(B43,#REF!,#REF!,0) -> #REF! | BD43: =BC43/(100%-BE43) -> #REF! | BE43: 0.35 | BF43: =BS43+BI43+BJ43+BU43+BK43 -> #REF! | BG43: =IFERROR(BF43/BC43,0) -> 0 | BH43: 0.37 | BI43: =BC43*BH43 -> #REF! | BJ43: =BC43*$BJ$3 -> #REF! | BK43: =K43*$BK$3*30 -> 0 | BL43: =(IF(K43>$BL$3,('Тарифы ОЗОН'!$G$3+ROUNDUP(K43-$BL$3,0)*'Тарифы ОЗОН'!$G$4),'Тарифы ОЗОН'!$G$3)) -> 56.94 | BM43: =$BN$3 -> 35 | BN43: =_xlfn.XLOOKUP(BM43,'Тарифы ОЗОН'!$A:$A,'Тарифы ОЗОН'!$B:$B) -> 1.32 | BO43: =_xlfn.XLOOKUP(BM43,'Тарифы ОЗОН'!$A:$A,'Тарифы ОЗОН'!C:C) -> 0.016 | BP43: =$BP$3 -> 25 | BQ43: =BL43*BN43+BC43*BO43+BP43 -> #REF! | BR43: =$BR$3 -> 0.85 | BS43: =(100%/BR43)*BQ43+(100%/BR43-1)*BL43 -> #REF! | BT43: =IFERROR(BS43/BC43*100%,0) -> 0 | BU43: =BC43*$BU$3 -> #REF! | BV43: =BF43+F43 -> #REF! | CB43: =IF(BC43=0,0,CA43-BV43) -> #REF! | CC43: =IF(CB43=0,0,CB43-CA43*7%) -> #REF! | CD43: =CC43/H43*100% -> #REF! | CE43: =IFERROR(CC43/CA43,0) -> 0 | CF43: =_xlfn.XLOOKUP(B43,'[1]Рассчет акции'!$A:$A,'[1]Рассчет акции'!$R:$R,0) -> 0 | CG43: =_xlfn.XLOOKUP(B43,'[1]Рассчет акции'!$A:$A,'[1]Рассчет акции'!$M:$M,0) -> 0 | CH43: =IFERROR($CJ43/$CG43,0) -> 0 | CI43: =IF(BC43>0,CG43-BV43,0) -> #REF! | CJ43: =IF(CI43>0,$CI43-$CG43*7%,0) -> #REF! | CK43: =$CJ43/$H43*100% -> #REF! | CL43: =_xlfn.XLOOKUP(B43,'[1]Рассчет акции'!$A:$A,'[1]Рассчет акции'!$W:$W,0) -> 0 | CM43: =_xlfn.XLOOKUP(B43,'[1]Рассчет акции'!$A:$A,'[1]Рассчет акции'!$X:$X,0) -> 0 | CN43: =BC43/H43 -> #REF! | CO43: =CA43-10%*CA43 -> 0 | CP43: =_xlfn.XLOOKUP(B43,'[1]Рассчет акции'!$A:$A,'[1]Рассчет акции'!$Z:$Z,0) -> 0
A44: 550539998 | C44: ACRB5FR200CL | D44: Набор эластичных лент 5 шт. в мешке | E44: 2046392546618 | F44: =SUM(H44:J44) -> 486.1747 | G44: =IFERROR(F44/S44*100%,0) -> 0.2993318 | H44: =IF(_xlfn.XLOOKUP($C44,'Юнит Карго'!$A:$A,'Юнит Карго'!$G:$G)=0,_xlfn.XLOOKUP(E44,'Себес 1С текущ'!G:G,'Себес 1С текущ'!H:H),_xlfn.XLOOKUP($C44,'Юнит Карго'!$A:$A,'Юнит Карго'!$P:$P,0,0)) -> 451.1747 | I44: =_xlfn.XLOOKUP(E44,[3]ТЗ_ФФ!$D:$D,[3]ТЗ_ФФ!$BG:$BG,0) -> 27 | J44: =$J$3 -> 8 | K44: =(L44*M44*N44)/1000 -> 0.95 | L44: 19 | M44: 10 | N44: 5 | O44: =_xlfn.XLOOKUP($C44,'Юнит Карго'!$A:$A,'Юнит Карго'!$T:$T,0,0) -> 0.24 | S44: =T44-(T44*U44) -> 1624.2 | T44: =_xlfn.XLOOKUP(E44,'[2]Рассчет акции'!$D:$D,'[2]Рассчет акции'!$G:$G,0) -> 2707 | U44: =_xlfn.XLOOKUP(E44,'[2]Рассчет акции'!$D:$D,'[2]Рассчет акции'!$F:$F,0) -> 0.4 | V44: =AC44+AF44+AH44+AG44 -> 639.88976 | W44: =IFERROR(V44/S44,0) -> 0.39397227 | X44: =IF(K44>1,('Тарифы ВБ'!$B$9+(K44-1)*'Тарифы ВБ'!$B$10)*'Тарифы ВБ'!$B$15*'Тарифы ВБ'!$B$12+S44*'Тарифы ВБ'!$B$13,'Тарифы ВБ'!$B$8*'Тарифы ВБ'!$B$15*'Тарифы ВБ'!$B$12+S44*'Тарифы ВБ'!$B$13) -> 80.50876 | Y44: =IF(K44>1,'Тарифы ВБ'!$B$9+(K44-1)*'Тарифы ВБ'!$B$10,'Тарифы ВБ'!$B$8) -> 32 | Z44: =SUM(X44:Y44) -> 112.50876 | AA44: =IFERROR(Z44/S44,0) -> 0.069270262 | AB44: =IF(K44>1,'Тарифы ВБ'!$B$14*'Тарифы ВБ'!$B$16*'Тарифы ВБ'!$B$15+(K44-1)*'Тарифы ВБ'!$B$14,'Тарифы ВБ'!$B$14*'Тарифы ВБ'!B$16*'Тарифы ВБ'!$B$15) -> 32 | AC44: =+X44+AB44+Y44 -> 144.50876 | AD44: =AC44/S44*100% -> 0.088972269 | AE44: 0.275 | AF44: =S44*AE44 -> 446.655 | AG44: =1.1*S44*$AG$3 -> 0 | AH44: =S44*$AH$3 -> 48.726 | AI44: =F44+V44 -> 1126.0645 | AJ44: =IFERROR(AL44/S44,0) -> 0.23669593 | AK44: =S44-AI44 -> 498.13554 | AL44: =AK44-S44*7% -> 384.44154 | AM44: =AL44/H44 -> 0.85209018 | AN44: 1379 | AO44: =$AN44-$AI44 -> 252.93554 | AP44: =$AO44-$AN44*7% -> 156.40554 | AQ44: =$AP44/$H44*100% -> 0.34666291 | AR44: =$AP44/$AN44 -> 0.11341953 | AS44: =IFERROR(_xlfn.XLOOKUP(A44,'[2]Рассчет акции'!$A:$A,'[2]Рассчет акции'!$BH:$BH),0) -> * | AT44: =IFERROR(_xlfn.XLOOKUP($A44,'[2]Рассчет акции'!$A:$A,'[2]Рассчет акции'!$BC:$BC),0) -> 1624 | AU44: =IFERROR($AW44/$AT44,0) -> 0.23661055 | AV44: =$AT44-$AI44 -> 497.93554 | AW44: =$AV44-$AT44*7% -> 384.25554 | AX44: =$AW44/$H44*100% -> 0.85167792 | AY44: =IFERROR(_xlfn.XLOOKUP(E44,'[2]Рассчет акции'!$D:$D,'[2]Рассчет акции'!$BM:$BM),0) -> 59 | AZ44: =IFERROR(_xlfn.XLOOKUP(E44,'[2]Рассчет акции'!$D:$D,'[2]Рассчет акции'!$BN:$BN),0) -> 999 | BA44: =S44/H44 -> 3.5999359 | BC44: =_xlfn.XLOOKUP(B44,#REF!,#REF!,0) -> #REF! | BD44: =BC44/(100%-BE44) -> #REF! | BE44: 0.35 | BF44: =BS44+BI44+BJ44+BU44+BK44 -> #REF! | BG44: =IFERROR(BF44/BC44,0) -> 0 | BH44: 0.37 | BI44: =BC44*BH44 -> #REF! | BJ44: =BC44*$BJ$3 -> #REF! | BK44: =K44*$BK$3*30 -> 0 | BL44: =(IF(K44>$BL$3,('Тарифы ОЗОН'!$G$3+ROUNDUP(K44-$BL$3,0)*'Тарифы ОЗОН'!$G$4),'Тарифы ОЗОН'!$G$3)) -> 46.77 | BM44: =$BN$3 -> 35 | BN44: =_xlfn.XLOOKUP(BM44,'Тарифы ОЗОН'!$A:$A,'Тарифы ОЗОН'!$B:$B) -> 1.32 | BO44: =_xlfn.XLOOKUP(BM44,'Тарифы ОЗОН'!$A:$A,'Тарифы ОЗОН'!C:C) -> 0.016 | BP44: =$BP$3 -> 25 | BQ44: =BL44*BN44+BC44*BO44+BP44 -> #REF! | BR44: =$BR$3 -> 0.85 | BS44: =(100%/BR44)*BQ44+(100%/BR44-1)*BL44 -> #REF! | BT44: =IFERROR(BS44/BC44*100%,0) -> 0 | BU44: =BC44*$BU$3 -> #REF! | BV44: =BF44+F44 -> #REF! | BW44: =IFERROR(BY44/BC44,0) -> 0 | BX44: =IFERROR(BC44-BV44,0) -> 0 | BY44: =BX44-BC44*7% -> #REF! | BZ44: =IFERROR(BY44/H44*100%,0) -> 0 | CA44: 0 | CB44: =IF(BC44=0,0,CA44-BV44) -> #REF! | CC44: =IF(CB44=0,0,CB44-CA44*7%) -> #REF! | CD44: =CC44/H44*100% -> #REF! | CE44: =IFERROR(CC44/CA44,0) -> 0 | CF44: =_xlfn.XLOOKUP(B44,'[1]Рассчет акции'!$A:$A,'[1]Рассчет акции'!$R:$R,0) -> 0 | CG44: =_xlfn.XLOOKUP(B44,'[1]Рассчет акции'!$A:$A,'[1]Рассчет акции'!$M:$M,0) -> 0 | CH44: =IFERROR($CJ44/$CG44,0) -> 0 | CI44: =IF(BC44>0,CG44-BV44,0) -> #REF! | CJ44: =IF(CI44>0,$CI44-$CG44*7%,0) -> #REF! | CK44: =$CJ44/$H44*100% -> #REF! | CL44: =_xlfn.XLOOKUP(B44,'[1]Рассчет акции'!$A:$A,'[1]Рассчет акции'!$W:$W,0) -> 0 | CM44: =_xlfn.XLOOKUP(B44,'[1]Рассчет акции'!$A:$A,'[1]Рассчет акции'!$X:$X,0) -> 0 | CN44: =BC44/H44 -> #REF! | CO44: =CA44-10%*CA44 -> 0 | CP44: =_xlfn.XLOOKUP(B44,'[1]Рассчет акции'!$A:$A,'[1]Рассчет акции'!$Z:$Z,0) -> 0
A45: 550539999 | C45: ACRB4FR300CL | D45: Набор эластичных лент 4 шт. | E45: 2046392546632 | F45: =SUM(H45:J45) -> 363 | G45: =IFERROR(F45/S45*100%,0) -> 0.36336336 | H45: =IF(_xlfn.XLOOKUP($C45,'Юнит Карго'!$A:$A,'Юнит Карго'!$G:$G)=0,_xlfn.XLOOKUP(E45,'Себес 1С текущ'!G:G,'Себес 1С текущ'!H:H),_xlfn.XLOOKUP($C45,'Юнит Карго'!$A:$A,'Юнит Карго'!$P:$P,0,0)) -> 309 | I45: =_xlfn.XLOOKUP(E45,[3]ТЗ_ФФ!$D:$D,[3]ТЗ_ФФ!$BG:$BG,0) -> 46 | J45: =$J$3 -> 8 | K45: =(L45*M45*N45)/1000 -> 0.85 | L45: 17 | M45: 10 | N45: 5 | O45: =_xlfn.XLOOKUP($C45,'Юнит Карго'!$A:$A,'Юнит Карго'!$T:$T,0,0) -> 0.25 | S45: =T45-(T45*U45) -> 999 | T45: =_xlfn.XLOOKUP(E45,'[2]Рассчет акции'!$D:$D,'[2]Рассчет акции'!$G:$G,0) -> 1665 | U45: =_xlfn.XLOOKUP(E45,'[2]Рассчет акции'!$D:$D,'[2]Рассчет акции'!$F:$F,0) -> 0.4 | V45: =AC45+AF45+AH45+AG45 -> 444.3272 | W45: =IFERROR(V45/S45,0) -> 0.44477197 | X45: =IF(K45>1,('Тарифы ВБ'!$B$9+(K45-1)*'Тарифы ВБ'!$B$10)*'Тарифы ВБ'!$B$15*'Тарифы ВБ'!$B$12+S45*'Тарифы ВБ'!$B$13,'Тарифы ВБ'!$B$8*'Тарифы ВБ'!$B$15*'Тарифы ВБ'!$B$12+S45*'Тарифы ВБ'!$B$13) -> 75.6322 | Y45: =IF(K45>1,'Тарифы ВБ'!$B$9+(K45-1)*'Тарифы ВБ'!$B$10,'Тарифы ВБ'!$B$8) -> 32 | Z45: =SUM(X45:Y45) -> 107.6322 | AA45: =IFERROR(Z45/S45,0) -> 0.10773994 | AB45: =IF(K45>1,'Тарифы ВБ'!$B$14*'Тарифы ВБ'!$B$16*'Тарифы ВБ'!$B$15+(K45-1)*'Тарифы ВБ'!$B$14,'Тарифы ВБ'!$B$14*'Тарифы ВБ'!B$16*'Тарифы ВБ'!$B$15) -> 32 | AC45: =+X45+AB45+Y45 -> 139.6322 | AD45: =AC45/S45*100% -> 0.13977197 | AE45: 0.275 | AF45: =S45*AE45 -> 274.725 | AG45: =1.1*S45*$AG$3 -> 0 | AH45: =S45*$AH$3 -> 29.97 | AI45: =F45+V45 -> 807.3272 | AJ45: =IFERROR(AL45/S45,0) -> 0.12186466 | AK45: =S45-AI45 -> 191.6728 | AL45: =AK45-S45*7% -> 121.7428 | AM45: =AL45/H45 -> 0.39398964 | AN45: 1019 | AO45: =$AN45-$AI45 -> 211.6728 | AP45: =$AO45-$AN45*7% -> 140.3428 | AQ45: =$AP45/$H45*100% -> 0.45418382 | AR45: =$AP45/$AN45 -> 0.13772601 | AS45: =IFERROR(_xlfn.XLOOKUP(A45,'[2]Рассчет акции'!$A:$A,'[2]Рассчет акции'!$BH:$BH),0) -> * | AT45: =IFERROR(_xlfn.XLOOKUP($A45,'[2]Рассчет акции'!$A:$A,'[2]Рассчет акции'!$BC:$BC),0) -> 999 | AU45: =IFERROR($AW45/$AT45,0) -> 0.12186466 | AV45: =$AT45-$AI45 -> 191.6728 | AW45: =$AV45-$AT45*7% -> 121.7428 | AX45: =$AW45/$H45*100% -> 0.39398964 | AY45: =IFERROR(_xlfn.XLOOKUP(E45,'[2]Рассчет акции'!$D:$D,'[2]Рассчет акции'!$BM:$BM),0) -> 40 | AZ45: =IFERROR(_xlfn.XLOOKUP(E45,'[2]Рассчет акции'!$D:$D,'[2]Рассчет акции'!$BN:$BN),0) -> 999 | BA45: =S45/H45 -> 3.2330097 | BC45: =_xlfn.XLOOKUP(B45,#REF!,#REF!,0) -> #REF! | BD45: =BC45/(100%-BE45) -> #REF! | BE45: 0.35 | BF45: =BS45+BI45+BJ45+BU45+BK45 -> #REF! | BG45: =IFERROR(BF45/BC45,0) -> 0 | BH45: 0.37 | BI45: =BC45*BH45 -> #REF! | BJ45: =BC45*$BJ$3 -> #REF! | BK45: =K45*$BK$3*30 -> 0 | BL45: =(IF(K45>$BL$3,('Тарифы ОЗОН'!$G$3+ROUNDUP(K45-$BL$3,0)*'Тарифы ОЗОН'!$G$4),'Тарифы ОЗОН'!$G$3)) -> 46.77 | BM45: =$BN$3 -> 35 | BN45: =_xlfn.XLOOKUP(BM45,'Тарифы ОЗОН'!$A:$A,'Тарифы ОЗОН'!$B:$B) -> 1.32 | BO45: =_xlfn.XLOOKUP(BM45,'Тарифы ОЗОН'!$A:$A,'Тарифы ОЗОН'!C:C) -> 0.016 | BP45: =$BP$3 -> 25 | BQ45: =BL45*BN45+BC45*BO45+BP45 -> #REF! | BR45: =$BR$3 -> 0.85 | BS45: =(100%/BR45)*BQ45+(100%/BR45-1)*BL45 -> #REF! | BT45: =IFERROR(BS45/BC45*100%,0) -> 0 | BU45: =BC45*$BU$3 -> #REF! | BV45: =BF45+F45 -> #REF! | BW45: =IFERROR(BY45/BC45,0) -> 0 | BX45: =IFERROR(BC45-BV45,0) -> 0 | BY45: =BX45-BC45*7% -> #REF! | BZ45: =IFERROR(BY45/H45*100%,0) -> 0 | CA45: 0 | CB45: =IF(BC45=0,0,CA45-BV45) -> #REF! | CC45: =IF(CB45=0,0,CB45-CA45*7%) -> #REF! | CD45: =CC45/H45*100% -> #REF! | CE45: =IFERROR(CC45/CA45,0) -> 0 | CF45: =_xlfn.XLOOKUP(B45,'[1]Рассчет акции'!$A:$A,'[1]Рассчет акции'!$R:$R,0) -> 0 | CG45: =_xlfn.XLOOKUP(B45,'[1]Рассчет акции'!$A:$A,'[1]Рассчет акции'!$M:$M,0) -> 0 | CH45: =IFERROR($CJ45/$CG45,0) -> 0 | CI45: =IF(BC45>0,CG45-BV45,0) -> #REF! | CJ45: =IF(CI45>0,$CI45-$CG45*7%,0) -> #REF! | CK45: =$CJ45/$H45*100% -> #REF! | CL45: =_xlfn.XLOOKUP(B45,'[1]Рассчет акции'!$A:$A,'[1]Рассчет акции'!$W:$W,0) -> 0 | CM45: =_xlfn.XLOOKUP(B45,'[1]Рассчет акции'!$A:$A,'[1]Рассчет акции'!$X:$X,0) -> 0 | CN45: =BC45/H45 -> #REF! | CO45: =CA45-10%*CA45 -> 0 | CP45: =_xlfn.XLOOKUP(B45,'[1]Рассчет акции'!$A:$A,'[1]Рассчет акции'!$Z:$Z,0) -> 0
A46: 550540000 | C46: ACRB5FR400CL | D46: Набор эластичных лент 5 шт. | E46: 2046392546656 | F46: =SUM(H46:J46) -> 45 | G46: =IFERROR(F46/S46*100%,0) -> 0.060080107 | I46: =_xlfn.XLOOKUP(E46,[3]ТЗ_ФФ!$D:$D,[3]ТЗ_ФФ!$BG:$BG,0) -> 37 | J46: =$J$3 -> 8 | K46: =(L46*M46*N46)/1000 -> 0.64 | L46: 20 | M46: 8 | N46: 4 | O46: =_xlfn.XLOOKUP($C46,'Юнит Карго'!$A:$A,'Юнит Карго'!$T:$T,0,0) -> 0.014 | S46: =T46-(T46*U46) -> 749 | T46: =_xlfn.XLOOKUP(E46,'[2]Рассчет акции'!$D:$D,'[2]Рассчет акции'!$G:$G,0) -> 1070 | U46: =_xlfn.XLOOKUP(E46,'[2]Рассчет акции'!$D:$D,'[2]Рассчет акции'!$F:$F,0) -> 0.3 | V46: =AC46+AF46+AH46+AG46 -> 366.1272 | W46: =IFERROR(V46/S46,0) -> 0.48882136 | X46: =IF(K46>1,('Тарифы ВБ'!$B$9+(K46-1)*'Тарифы ВБ'!$B$10)*'Тарифы ВБ'!$B$15*'Тарифы ВБ'!$B$12+S46*'Тарифы ВБ'!$B$13,'Тарифы ВБ'!$B$8*'Тарифы ВБ'!$B$15*'Тарифы ВБ'!$B$12+S46*'Тарифы ВБ'!$B$13) -> 73.6822 | Y46: =IF(K46>1,'Тарифы ВБ'!$B$9+(K46-1)*'Тарифы ВБ'!$B$10,'Тарифы ВБ'!$B$8) -> 32 | Z46: =SUM(X46:Y46) -> 105.6822 | AA46: =IFERROR(Z46/S46,0) -> 0.14109773 | AB46: =IF(K46>1,'Тарифы ВБ'!$B$14*'Тарифы ВБ'!$B$16*'Тарифы ВБ'!$B$15+(K46-1)*'Тарифы ВБ'!$B$14,'Тарифы ВБ'!$B$14*'Тарифы ВБ'!B$16*'Тарифы ВБ'!$B$15) -> 32 | AC46: =+X46+AB46+Y46 -> 137.6822 | AD46: =AC46/S46*100% -> 0.18382136 | AE46: 0.275 | AF46: =S46*AE46 -> 205.975 | AG46: =1.1*S46*$AG$3 -> 0 | AH46: =S46*$AH$3 -> 22.47 | AI46: =F46+V46 -> 411.1272 | AJ46: =IFERROR(AL46/S46,0) -> 0.38109853 | AK46: =S46-AI46 -> 337.8728 | AL46: =AK46-S46*7% -> 285.4428 | AM46: =AL46/H46 -> #DIV/0! | AN46: 0 | AO46: =$AN46-$AI46 -> -411.1272 | AP46: =$AO46-$AN46*7% -> -411.1272 | AQ46: =$AP46/$H46*100% -> #DIV/0! | AR46: =$AP46/$AN46 -> #DIV/0! | AS46: =IFERROR(_xlfn.XLOOKUP(A46,'[2]Рассчет акции'!$A:$A,'[2]Рассчет акции'!$BH:$BH),0) -> 0 | AT46: =IFERROR(_xlfn.XLOOKUP($A46,'[2]Рассчет акции'!$A:$A,'[2]Рассчет акции'!$BC:$BC),0) -> 0 | AU46: =IFERROR($AW46/$AT46,0) -> 0 | AV46: =$AT46-$AI46 -> -411.1272 | AW46: =$AV46-$AT46*7% -> -411.1272 | AX46: =$AW46/$H46*100% -> #DIV/0! | AY46: =IFERROR(_xlfn.XLOOKUP(E46,'[2]Рассчет акции'!$D:$D,'[2]Рассчет акции'!$BM:$BM),0) | AZ46: =IFERROR(_xlfn.XLOOKUP(E46,'[2]Рассчет акции'!$D:$D,'[2]Рассчет акции'!$BN:$BN),0) | BA46: =S46/H46 -> #DIV/0! | BC46: =_xlfn.XLOOKUP(B46,#REF!,#REF!,0) -> #REF! | BD46: =BC46/(100%-BE46) -> #REF! | BE46: 0.35 | BF46: =BS46+BI46+BJ46+BU46+BK46 -> #REF! | BG46: =IFERROR(BF46/BC46,0) -> 0 | BH46: 0.37 | BI46: =BC46*BH46 -> #REF! | BJ46: =BC46*$BJ$3 -> #REF! | BK46: =K46*$BK$3*30 -> 0 | BL46: =(IF(K46>$BL$3,('Тарифы ОЗОН'!$G$3+ROUNDUP(K46-$BL$3,0)*'Тарифы ОЗОН'!$G$4),'Тарифы ОЗОН'!$G$3)) -> 46.77 | BM46: =$BN$3 -> 35 | BN46: =_xlfn.XLOOKUP(BM46,'Тарифы ОЗОН'!$A:$A,'Тарифы ОЗОН'!$B:$B) -> 1.32 | BO46: =_xlfn.XLOOKUP(BM46,'Тарифы ОЗОН'!$A:$A,'Тарифы ОЗОН'!C:C) -> 0.016 | BP46: =$BP$3 -> 25 | BQ46: =BL46*BN46+BC46*BO46+BP46 -> #REF! | BR46: =$BR$3 -> 0.85 | BS46: =(100%/BR46)*BQ46+(100%/BR46-1)*BL46 -> #REF! | BT46: =IFERROR(BS46/BC46*100%,0) -> 0 | BU46: =BC46*$BU$3 -> #REF! | BV46: =BF46+F46 -> #REF! | BW46: =IFERROR(BY46/BC46,0) -> 0 | BX46: =IFERROR(BC46-BV46,0) -> 0 | BY46: =BX46-BC46*7% -> #REF! | BZ46: =IFERROR(BY46/H46*100%,0) -> 0 | CA46: 0 | CB46: =IF(BC46=0,0,CA46-BV46) -> #REF! | CC46: =IF(CB46=0,0,CB46-CA46*7%) -> #REF! | CD46: =CC46/H46*100% -> #REF! | CE46: =IFERROR(CC46/CA46,0) -> 0 | CF46: =_xlfn.XLOOKUP(B46,'[1]Рассчет акции'!$A:$A,'[1]Рассчет акции'!$R:$R,0) -> 0 | CG46: =_xlfn.XLOOKUP(B46,'[1]Рассчет акции'!$A:$A,'[1]Рассчет акции'!$M:$M,0) -> 0 | CH46: =IFERROR($CJ46/$CG46,0) -> 0 | CI46: =IF(BC46>0,CG46-BV46,0) -> #REF! | CJ46: =IF(CI46>0,$CI46-$CG46*7%,0) -> #REF! | CK46: =$CJ46/$H46*100% -> #REF! | CL46: =_xlfn.XLOOKUP(B46,'[1]Рассчет акции'!$A:$A,'[1]Рассчет акции'!$W:$W,0) -> 0 | CM46: =_xlfn.XLOOKUP(B46,'[1]Рассчет акции'!$A:$A,'[1]Рассчет акции'!$X:$X,0) -> 0 | CN46: =BC46/H46 -> #REF! | CO46: =CA46-10%*CA46 -> 0 | CP46: =_xlfn.XLOOKUP(B46,'[1]Рассчет акции'!$A:$A,'[1]Рассчет акции'!$Z:$Z,0) -> 0
A47: 271440668 | B47: 2415742680 | C47: ACRB1SK101BC | D47: Скакалка черная | E47: 2041473034138 | F47: =SUM(H47:J47) -> 318 | G47: =IFERROR(F47/S47*100%,0) -> 0.26368159 | H47: =IF(_xlfn.XLOOKUP($C47,'Юнит Карго'!$A:$A,'Юнит Карго'!$G:$G)=0,_xlfn.XLOOKUP(E47,'Себес 1С текущ'!G:G,'Себес 1С текущ'!H:H),_xlfn.XLOOKUP($C47,'Юнит Карго'!$A:$A,'Юнит Карго'!$P:$P,0,0)) -> 281 | I47: =_xlfn.XLOOKUP(E47,[3]ТЗ_ФФ!$D:$D,[3]ТЗ_ФФ!$BG:$BG,0) -> 29 | J47: =$J$3 -> 8 | K47: =(L47*M47*N47)/1000 -> 0.4 | L47: 20 | M47: 10 | N47: 2 | O47: =_xlfn.XLOOKUP($C47,'Юнит Карго'!$A:$A,'Юнит Карго'!$T:$T,0,0) -> 0.17 | P47: своя | S47: =T47-(T47*U47) -> 1206 | T47: =_xlfn.XLOOKUP(E47,'[2]Рассчет акции'!$D:$D,'[2]Рассчет акции'!$G:$G,0) -> 2010 | U47: =_xlfn.XLOOKUP(E47,'[2]Рассчет акции'!$D:$D,'[2]Рассчет акции'!$F:$F,0) -> 0.4 | V47: =AC47+AF47+AH47+AG47 -> 509.0768 | W47: =IFERROR(V47/S47,0) -> 0.42212007 | X47: =IF(K47>1,('Тарифы ВБ'!$B$9+(K47-1)*'Тарифы ВБ'!$B$10)*'Тарифы ВБ'!$B$15*'Тарифы ВБ'!$B$12+S47*'Тарифы ВБ'!$B$13,'Тарифы ВБ'!$B$8*'Тарифы ВБ'!$B$15*'Тарифы ВБ'!$B$12+S47*'Тарифы ВБ'!$B$13) -> 77.2468 | Y47: =IF(K47>1,'Тарифы ВБ'!$B$9+(K47-1)*'Тарифы ВБ'!$B$10,'Тарифы ВБ'!$B$8) -> 32 | Z47: =SUM(X47:Y47) -> 109.2468 | AA47: =IFERROR(Z47/S47,0) -> 0.09058607 | AB47: =IF(K47>1,'Тарифы ВБ'!$B$14*'Тарифы ВБ'!$B$16*'Тарифы ВБ'!$B$15+(K47-1)*'Тарифы ВБ'!$B$14,'Тарифы ВБ'!$B$14*'Тарифы ВБ'!B$16*'Тарифы ВБ'!$B$15) -> 32 | AC47: =+X47+AB47+Y47 -> 141.2468 | AD47: =AC47/S47*100% -> 0.11712007 | AE47: 0.275 | AF47: =S47*AE47 -> 331.65 | AG47: =1.1*S47*$AG$3 -> 0 | AH47: =S47*$AH$3 -> 36.18 | AI47: =F47+V47 -> 827.0768 | AJ47: =IFERROR(AL47/S47,0) -> 0.24419834 | AK47: =S47-AI47 -> 378.9232 | AL47: =AK47-S47*7% -> 294.5032 | AM47: =AL47/H47 -> 1.0480541 | AN47: 1219 | AO47: =$AN47-$AI47 -> 391.9232 | AP47: =$AO47-$AN47*7% -> 306.5932 | AQ47: =$AP47/$H47*100% -> 1.091079 | AR47: =$AP47/$AN47 -> 0.25151206 | AS47: =IFERROR(_xlfn.XLOOKUP(A47,'[2]Рассчет акции'!$A:$A,'[2]Рассчет акции'!$BH:$BH),0) -> * | AT47: =IFERROR(_xlfn.XLOOKUP($A47,'[2]Рассчет акции'!$A:$A,'[2]Рассчет акции'!$BC:$BC),0) -> 1206 | AU47: =IFERROR($AW47/$AT47,0) -> 0.24419834 | AV47: =$AT47-$AI47 -> 378.9232 | AW47: =$AV47-$AT47*7% -> 294.5032 | AX47: =$AW47/$H47*100% -> 1.0480541 | AY47: =IFERROR(_xlfn.XLOOKUP(E47,'[2]Рассчет акции'!$D:$D,'[2]Рассчет акции'!$BM:$BM),0) -> 130 | AZ47: =IFERROR(_xlfn.XLOOKUP(E47,'[2]Рассчет акции'!$D:$D,'[2]Рассчет акции'!$BN:$BN),0) -> 983 | BA47: =S47/H47 -> 4.2918149 | BC47: =_xlfn.XLOOKUP(B47,#REF!,#REF!,0) -> #REF! | BD47: =BC47/(100%-BE47) -> #REF! | BE47: =_xlfn.XLOOKUP($B47,'[1]Рассчет акции'!$A:$A,'[1]Рассчет акции'!$J:$J) -> 0.35007225 | BF47: =BS47+BI47+BJ47+BU47+BK47 -> #REF! | BG47: =IFERROR(BF47/BC47,0) -> 0 | BH47: 0.37 | BI47: =BC47*BH47 -> #REF! | BJ47: =BC47*$BJ$3 -> #REF! | BK47: =K47*$BK$3*30 -> 0 | BL47: =(IF(K47>$BL$3,('Тарифы ОЗОН'!$G$3+ROUNDUP(K47-$BL$3,0)*'Тарифы ОЗОН'!$G$4),'Тарифы ОЗОН'!$G$3)) -> 46.77 | BM47: =$BN$3 -> 35 | BN47: =_xlfn.XLOOKUP(BM47,'Тарифы ОЗОН'!$A:$A,'Тарифы ОЗОН'!$B:$B) -> 1.32 | BO47: =_xlfn.XLOOKUP(BM47,'Тарифы ОЗОН'!$A:$A,'Тарифы ОЗОН'!C:C) -> 0.016 | BP47: =$BP$3 -> 25 | BQ47: =BL47*BN47+BC47*BO47+BP47 -> #REF! | BR47: =$BR$3 -> 0.85 | BS47: =(100%/BR47)*BQ47+(100%/BR47-1)*BL47 -> #REF! | BT47: =IFERROR(BS47/BC47*100%,0) -> 0 | BU47: =BC47*$BU$3 -> #REF! | BV47: =BF47+F47 -> #REF! | BW47: =IFERROR(BY47/BC47,0) -> 0 | BX47: =IFERROR(BC47-BV47,0) -> 0 | BY47: =BX47-BC47*7% -> #REF! | BZ47: =IFERROR(BY47/H47*100%,0) -> 0 | CA47: 1395 | CB47: =IF(BC47=0,0,CA47-BV47) -> #REF! | CC47: =IF(CB47=0,0,CB47-CA47*7%) -> #REF! | CD47: =CC47/H47*100% -> #REF! | CE47: =IFERROR(CC47/CA47,0) -> 0 | CF47: =_xlfn.XLOOKUP(B47,'[1]Рассчет акции'!$A:$A,'[1]Рассчет акции'!$R:$R,0) -> 0 | CG47: =_xlfn.XLOOKUP(B47,'[1]Рассчет акции'!$A:$A,'[1]Рассчет акции'!$M:$M,0) -> 1295 | CH47: =IFERROR($CJ47/$CG47,0) -> 0 | CI47: =IF(BC47>0,CG47-BV47,0) -> #REF! | CJ47: =IF(CI47>0,$CI47-$CG47*7%,0) -> #REF! | CK47: =$CJ47/$H47*100% -> #REF! | CL47: =_xlfn.XLOOKUP(B47,'[1]Рассчет акции'!$A:$A,'[1]Рассчет акции'!$W:$W,0) -> 2 | CM47: =_xlfn.XLOOKUP(B47,'[1]Рассчет акции'!$A:$A,'[1]Рассчет акции'!$X:$X,0) -> 14 | CN47: =BC47/H47 -> #REF! | CO47: =CA47-10%*CA47 -> 1255.5 | CP47: =_xlfn.XLOOKUP(B47,'[1]Рассчет акции'!$A:$A,'[1]Рассчет акции'!$Z:$Z,0) -> 0
A48: 271440669 | B48: 2415742649 | C48: ACRB1SK101RD | D48: Скакалка красная | E48: 2041473034145 | F48: =SUM(H48:J48) -> 318 | G48: =IFERROR(F48/S48*100%,0) -> 0.29233315 | H48: =IF(_xlfn.XLOOKUP($C48,'Юнит Карго'!$A:$A,'Юнит Карго'!$G:$G)=0,_xlfn.XLOOKUP(E48,'Себес 1С текущ'!G:G,'Себес 1С текущ'!H:H),_xlfn.XLOOKUP($C48,'Юнит Карго'!$A:$A,'Юнит Карго'!$P:$P,0,0)) -> 281 | I48: =_xlfn.XLOOKUP(E48,[3]ТЗ_ФФ!$D:$D,[3]ТЗ_ФФ!$BG:$BG,0) -> 29 | J48: =$J$3 -> 8 | K48: =(L48*M48*N48)/1000 -> 0.4 | L48: 20 | M48: 10 | N48: 2 | O48: =_xlfn.XLOOKUP($C48,'Юнит Карго'!$A:$A,'Юнит Карго'!$T:$T,0,0) -> 0.17 | P48: своя | S48: =T48-(T48*U48) -> 1087.8 | T48: =_xlfn.XLOOKUP(E48,'[2]Рассчет акции'!$D:$D,'[2]Рассчет акции'!$G:$G,0) -> 1813 | U48: =_xlfn.XLOOKUP(E48,'[2]Рассчет акции'!$D:$D,'[2]Рассчет акции'!$F:$F,0) -> 0.4 | V48: =AC48+AF48+AH48+AG48 -> 472.10384 | W48: =IFERROR(V48/S48,0) -> 0.43399875 | X48: =IF(K48>1,('Тарифы ВБ'!$B$9+(K48-1)*'Тарифы ВБ'!$B$10)*'Тарифы ВБ'!$B$15*'Тарифы ВБ'!$B$12+S48*'Тарифы ВБ'!$B$13,'Тарифы ВБ'!$B$8*'Тарифы ВБ'!$B$15*'Тарифы ВБ'!$B$12+S48*'Тарифы ВБ'!$B$13) -> 76.32484 | Y48: =IF(K48>1,'Тарифы ВБ'!$B$9+(K48-1)*'Тарифы ВБ'!$B$10,'Тарифы ВБ'!$B$8) -> 32 | Z48: =SUM(X48:Y48) -> 108.32484 | AA48: =IFERROR(Z48/S48,0) -> 0.099581577 | AB48: =IF(K48>1,'Тарифы ВБ'!$B$14*'Тарифы ВБ'!$B$16*'Тарифы ВБ'!$B$15+(K48-1)*'Тарифы ВБ'!$B$14,'Тарифы ВБ'!$B$14*'Тарифы ВБ'!B$16*'Тарифы ВБ'!$B$15) -> 32 | AC48: =+X48+AB48+Y48 -> 140.32484 | AD48: =AC48/S48*100% -> 0.12899875 | AE48: 0.275 | AF48: =S48*AE48 -> 299.145 | AG48: =1.1*S48*$AG$3 -> 0 | AH48: =S48*$AH$3 -> 32.634 | AI48: =F48+V48 -> 790.10384 | AJ48: =IFERROR(AL48/S48,0) -> 0.2036681 | AK48: =S48-AI48 -> 297.69616 | AL48: =AK48-S48*7% -> 221.55016 | AM48: =AL48/H48 -> 0.78843473 | AN48: 1219 | AO48: =$AN48-$AI48 -> 428.89616 | AP48: =$AO48-$AN48*7% -> 343.56616 | AQ48: =$AP48/$H48*100% -> 1.2226554 | AR48: =$AP48/$AN48 -> 0.28184263 | AS48: =IFERROR(_xlfn.XLOOKUP(A48,'[2]Рассчет акции'!$A:$A,'[2]Рассчет акции'!$BH:$BH),0) -> * | AT48: =IFERROR(_xlfn.XLOOKUP($A48,'[2]Рассчет акции'!$A:$A,'[2]Рассчет акции'!$BC:$BC),0) -> 1088 | AU48: =IFERROR($AW48/$AT48,0) -> 0.20380162 | AV48: =$AT48-$AI48 -> 297.89616 | AW48: =$AV48-$AT48*7% -> 221.73616 | AX48: =$AW48/$H48*100% -> 0.78909665 | AY48: =IFERROR(_xlfn.XLOOKUP(E48,'[2]Рассчет акции'!$D:$D,'[2]Рассчет акции'!$BM:$BM),0) -> 128 | AZ48: =IFERROR(_xlfn.XLOOKUP(E48,'[2]Рассчет акции'!$D:$D,'[2]Рассчет акции'!$BN:$BN),0) -> 440 | BA48: =S48/H48 -> 3.8711744 | BC48: =_xlfn.XLOOKUP(B48,#REF!,#REF!,0) -> #REF! | BD48: =BC48/(100%-BE48) -> #REF! | BE48: =_xlfn.XLOOKUP($B48,'[1]Рассчет акции'!$A:$A,'[1]Рассчет акции'!$J:$J) -> 0.35007225 | BF48: =BS48+BI48+BJ48+BU48+BK48 -> #REF! | BG48: =IFERROR(BF48/BC48,0) -> 0 | BH48: 0.37 | BI48: =BC48*BH48 -> #REF! | BJ48: =BC48*$BJ$3 -> #REF! | BK48: =K48*$BK$3*30 -> 0 | BL48: =(IF(K48>$BL$3,('Тарифы ОЗОН'!$G$3+ROUNDUP(K48-$BL$3,0)*'Тарифы ОЗОН'!$G$4),'Тарифы ОЗОН'!$G$3)) -> 46.77 | BM48: =$BN$3 -> 35 | BN48: =_xlfn.XLOOKUP(BM48,'Тарифы ОЗОН'!$A:$A,'Тарифы ОЗОН'!$B:$B) -> 1.32 | BO48: =_xlfn.XLOOKUP(BM48,'Тарифы ОЗОН'!$A:$A,'Тарифы ОЗОН'!C:C) -> 0.016 | BP48: =$BP$3 -> 25 | BQ48: =BL48*BN48+BC48*BO48+BP48 -> #REF! | BR48: =$BR$3 -> 0.85 | BS48: =(100%/BR48)*BQ48+(100%/BR48-1)*BL48 -> #REF! | BT48: =IFERROR(BS48/BC48*100%,0) -> 0 | BU48: =BC48*$BU$3 -> #REF! | BV48: =BF48+F48 -> #REF! | BW48: =IFERROR(BY48/BC48,0) -> 0 | BX48: =IFERROR(BC48-BV48,0) -> 0 | BY48: =BX48-BC48*7% -> #REF! | BZ48: =IFERROR(BY48/H48*100%,0) -> 0 | CA48: 1395 | CB48: =IF(BC48=0,0,CA48-BV48) -> #REF! | CC48: =IF(CB48=0,0,CB48-CA48*7%) -> #REF! | CD48: =CC48/H48*100% -> #REF! | CE48: =IFERROR(CC48/CA48,0) -> 0 | CF48: =_xlfn.XLOOKUP(B48,'[1]Рассчет акции'!$A:$A,'[1]Рассчет акции'!$R:$R,0) -> 0 | CG48: =_xlfn.XLOOKUP(B48,'[1]Рассчет акции'!$A:$A,'[1]Рассчет акции'!$M:$M,0) -> 1295 | CH48: =IFERROR($CJ48/$CG48,0) -> 0 | CI48: =IF(BC48>0,CG48-BV48,0) -> #REF! | CJ48: =IF(CI48>0,$CI48-$CG48*7%,0) -> #REF! | CK48: =$CJ48/$H48*100% -> #REF! | CL48: =_xlfn.XLOOKUP(B48,'[1]Рассчет акции'!$A:$A,'[1]Рассчет акции'!$W:$W,0) -> 2 | CM48: =_xlfn.XLOOKUP(B48,'[1]Рассчет акции'!$A:$A,'[1]Рассчет акции'!$X:$X,0) -> 999 | CN48: =BC48/H48 -> #REF! | CO48: =CA48-10%*CA48 -> 1255.5 | CP48: =_xlfn.XLOOKUP(B48,'[1]Рассчет акции'!$A:$A,'[1]Рассчет акции'!$Z:$Z,0) -> 0
A49: 271440670 | B49: 2415743140 | C49: ACRB1SK101BL | D49: Скакалка синяя | E49: 2041473034169 | F49: =SUM(H49:J49) -> 318 | G49: =IFERROR(F49/S49*100%,0) -> 0.29233315 | H49: =IF(_xlfn.XLOOKUP($C49,'Юнит Карго'!$A:$A,'Юнит Карго'!$G:$G)=0,_xlfn.XLOOKUP(E49,'Себес 1С текущ'!G:G,'Себес 1С текущ'!H:H),_xlfn.XLOOKUP($C49,'Юнит Карго'!$A:$A,'Юнит Карго'!$P:$P,0,0)) -> 281 | I49: =_xlfn.XLOOKUP(E49,[3]ТЗ_ФФ!$D:$D,[3]ТЗ_ФФ!$BG:$BG,0) -> 29 | J49: =$J$3 -> 8 | K49: =(L49*M49*N49)/1000 -> 0.4 | L49: 20 | M49: 10 | N49: 2 | O49: =_xlfn.XLOOKUP($C49,'Юнит Карго'!$A:$A,'Юнит Карго'!$T:$T,0,0) -> 0.17 | P49: своя | S49: =T49-(T49*U49) -> 1087.8 | T49: =_xlfn.XLOOKUP(E49,'[2]Рассчет акции'!$D:$D,'[2]Рассчет акции'!$G:$G,0) -> 1813 | U49: =_xlfn.XLOOKUP(E49,'[2]Рассчет акции'!$D:$D,'[2]Рассчет акции'!$F:$F,0) -> 0.4 | V49: =AC49+AF49+AH49+AG49 -> 472.10384 | W49: =IFERROR(V49/S49,0) -> 0.43399875 | X49: =IF(K49>1,('Тарифы ВБ'!$B$9+(K49-1)*'Тарифы ВБ'!$B$10)*'Тарифы ВБ'!$B$15*'Тарифы ВБ'!$B$12+S49*'Тарифы ВБ'!$B$13,'Тарифы ВБ'!$B$8*'Тарифы ВБ'!$B$15*'Тарифы ВБ'!$B$12+S49*'Тарифы ВБ'!$B$13) -> 76.32484 | Y49: =IF(K49>1,'Тарифы ВБ'!$B$9+(K49-1)*'Тарифы ВБ'!$B$10,'Тарифы ВБ'!$B$8) -> 32 | Z49: =SUM(X49:Y49) -> 108.32484 | AA49: =IFERROR(Z49/S49,0) -> 0.099581577 | AB49: =IF(K49>1,'Тарифы ВБ'!$B$14*'Тарифы ВБ'!$B$16*'Тарифы ВБ'!$B$15+(K49-1)*'Тарифы ВБ'!$B$14,'Тарифы ВБ'!$B$14*'Тарифы ВБ'!B$16*'Тарифы ВБ'!$B$15) -> 32 | AC49: =+X49+AB49+Y49 -> 140.32484 | AD49: =AC49/S49*100% -> 0.12899875 | AE49: 0.275 | AF49: =S49*AE49 -> 299.145 | AG49: =1.1*S49*$AG$3 -> 0 | AH49: =S49*$AH$3 -> 32.634 | AI49: =F49+V49 -> 790.10384 | AJ49: =IFERROR(AL49/S49,0) -> 0.2036681 | AK49: =S49-AI49 -> 297.69616 | AL49: =AK49-S49*7% -> 221.55016 | AM49: =AL49/H49 -> 0.78843473 | AN49: 1219 | AO49: =$AN49-$AI49 -> 428.89616 | AP49: =$AO49-$AN49*7% -> 343.56616 | AQ49: =$AP49/$H49*100% -> 1.2226554 | AR49: =$AP49/$AN49 -> 0.28184263 | AS49: =IFERROR(_xlfn.XLOOKUP(A49,'[2]Рассчет акции'!$A:$A,'[2]Рассчет акции'!$BH:$BH),0) -> * | AT49: =IFERROR(_xlfn.XLOOKUP($A49,'[2]Рассчет акции'!$A:$A,'[2]Рассчет акции'!$BC:$BC),0) -> 1088 | AU49: =IFERROR($AW49/$AT49,0) -> 0.20380162 | AV49: =$AT49-$AI49 -> 297.89616 | AW49: =$AV49-$AT49*7% -> 221.73616 | AX49: =$AW49/$H49*100% -> 0.78909665 | AY49: =IFERROR(_xlfn.XLOOKUP(E49,'[2]Рассчет акции'!$D:$D,'[2]Рассчет акции'!$BM:$BM),0) -> 100 | AZ49: =IFERROR(_xlfn.XLOOKUP(E49,'[2]Рассчет акции'!$D:$D,'[2]Рассчет акции'!$BN:$BN),0) -> 999 | BA49: =S49/H49 -> 3.8711744 | BC49: =_xlfn.XLOOKUP(B49,#REF!,#REF!,0) -> #REF! | BD49: =BC49/(100%-BE49) -> #REF! | BE49: =_xlfn.XLOOKUP($B49,'[1]Рассчет акции'!$A:$A,'[1]Рассчет акции'!$J:$J) -> 0.35007225 | BF49: =BS49+BI49+BJ49+BU49+BK49 -> #REF! | BG49: =IFERROR(BF49/BC49,0) -> 0 | BH49: 0.37 | BI49: =BC49*BH49 -> #REF! | BJ49: =BC49*$BJ$3 -> #REF! | BK49: =K49*$BK$3*30 -> 0 | BL49: =(IF(K49>$BL$3,('Тарифы ОЗОН'!$G$3+ROUNDUP(K49-$BL$3,0)*'Тарифы ОЗОН'!$G$4),'Тарифы ОЗОН'!$G$3)) -> 46.77 | BM49: =$BN$3 -> 35 | BN49: =_xlfn.XLOOKUP(BM49,'Тарифы ОЗОН'!$A:$A,'Тарифы ОЗОН'!$B:$B) -> 1.32 | BO49: =_xlfn.XLOOKUP(BM49,'Тарифы ОЗОН'!$A:$A,'Тарифы ОЗОН'!C:C) -> 0.016 | BP49: =$BP$3 -> 25 | BQ49: =BL49*BN49+BC49*BO49+BP49 -> #REF! | BR49: =$BR$3 -> 0.85 | BS49: =(100%/BR49)*BQ49+(100%/BR49-1)*BL49 -> #REF! | BT49: =IFERROR(BS49/BC49*100%,0) -> 0 | BU49: =BC49*$BU$3 -> #REF! | BV49: =BF49+F49 -> #REF! | BW49: =IFERROR(BY49/BC49,0) -> 0 | BX49: =IFERROR(BC49-BV49,0) -> 0 | BY49: =BX49-BC49*7% -> #REF! | BZ49: =IFERROR(BY49/H49*100%,0) -> 0 | CA49: 1395 | CB49: =IF(BC49=0,0,CA49-BV49) -> #REF! | CC49: =IF(CB49=0,0,CB49-CA49*7%) -> #REF! | CD49: =CC49/H49*100% -> #REF! | CE49: =IFERROR(CC49/CA49,0) -> 0 | CF49: =_xlfn.XLOOKUP(B49,'[1]Рассчет акции'!$A:$A,'[1]Рассчет акции'!$R:$R,0) -> 0 | CG49: =_xlfn.XLOOKUP(B49,'[1]Рассчет акции'!$A:$A,'[1]Рассчет акции'!$M:$M,0) -> 1295 | CH49: =IFERROR($CJ49/$CG49,0) -> 0 | CI49: =IF(BC49>0,CG49-BV49,0) -> #REF! | CJ49: =IF(CI49>0,$CI49-$CG49*7%,0) -> #REF! | CK49: =$CJ49/$H49*100% -> #REF! | CL49: =_xlfn.XLOOKUP(B49,'[1]Рассчет акции'!$A:$A,'[1]Рассчет акции'!$W:$W,0) -> 3 | CM49: =_xlfn.XLOOKUP(B49,'[1]Рассчет акции'!$A:$A,'[1]Рассчет акции'!$X:$X,0) -> 999 | CN49: =BC49/H49 -> #REF! | CO49: =CA49-10%*CA49 -> 1255.5 | CP49: =_xlfn.XLOOKUP(B49,'[1]Рассчет акции'!$A:$A,'[1]Рассчет акции'!$Z:$Z,0) -> 0
